Workbook

Sheet Instructions
A1: THE LANDRY FAMILY EQUITY INVESTMENT OPERATING SYSTEM — STOCK SCORING & PORTFOLIO RISK WORKBOOK
A3: Companion workbook to Landry System v1.0. Aligned to: Version 1.0 (49 Hard Rules, Parts 1–12).
A4: If the Word document's rule numbers ever change in a future revision, check this line and the rule
A5: references throughout this workbook before relying on them.
A7: HOW TO USE THIS WORKBOOK
A8: 1. Market Data tab — enter or refresh price, volume, market cap, P/E, 52-week range, and dividend
A9: yield for each tracked ticker. Blue cells only. See that tab's note on optional live-data refresh.
A10: 2. Scoring tab — during a scoring session, enter each Tier 1/2/3 indicator's score (1–5) and Confidence
A11: tag (H/M/L) per Part 2's rubrics. The Composite Score, decision classification, and hard-rule flags
A12: (Rules 1–4) calculate automatically.
A13: 3. Dashboard tab — read-only summary of every tracked stock, sortable by Composite Score.
A14: 4. Price History / Returns (Calc) / Correlation Matrix tabs — enter monthly closing prices for up to 12
... A35: See the Schema Reference tab (last tab) for the exact column layout of every tab -- built for handoff to Claude Code or any future programmatic access.

Sheet Action Items
A1: ACTION ITEMS — everything requiring your decision, pulled live from every other tab. Everything else in this workbook is reference; this is what to open.
A2: Refresh by opening the workbook (F9 recalculates); all cells below are live formulas, nothing here is typed.
A4: 1. WATCH LIST — Rules 31-34 (see Watch List Tracker tab for detail)
A5: Deadlines passed (sell required within 30 days): | E5: =COUNTIF('Watch List Tracker'!K3:K22,"*SELL WITHIN 30 DAYS*") -> 0
A6: Deadlines approaching (within 14 days): | E6: =COUNTIF('Watch List Tracker'!K3:K22,"DEADLINE APPROACHING") -> 0
A7: Recovered — ready to remove/reclassify: | E7: =COUNTIF('Watch List Tracker'!K3:K22,"*RECOVERED*") -> 0
A9: 2. ACTIVE SELL TRIGGERS — Rules 21-30 (see Holding Monitor tab for detail)
A10: Holdings with action required within 30 days: | E10: =COUNTIF('Holding Monitor'!AB4:AB23,"*ACTION REQUIRED*") -> 0
A11: Holdings under Hold Through (monitor only, no action): | E11: =COUNTIF('Holding Monitor'!AB4:AB23,"*Hold Through*") -> 0
A13: 3. CORRELATION CAP — Rule 36 (see Correlation Matrix tab for detail)
A14: Rule 36 status: | E14: ='Correlation Matrix'!B17
A15: Positions exceeding cap: | E15: ='Correlation Matrix'!B16
A17: 4. PORTFOLIO DRAWDOWN STATUS — Rule 37 (see Portfolio Drawdown Log tab for detail)
A18: Most recent recorded status: | E18: =IFERROR(INDEX('Portfolio Drawdown Log'!E3:E42,COUNT('Portfolio Drawdown Log'!D3:D42)),"No entries yet")
A19: Most recent drawdown %: | E19: =IFERROR(INDEX('Portfolio Drawdown Log'!D3:D42,COUNT('Portfolio Drawdown Log'!D3:D42)),"")
A20: Required cash floor at this level: | E20: =IFERROR(INDEX('Portfolio Drawdown Log'!F3:F42,COUNT('Portfolio Drawdown Log'!D3:D42)),"")
A22: 5. CANDIDATE SCORING FLAGS — Rules 1-4 (see Scoring tab for detail)
A23: Candidates failing the Tier 1 floor, 3.0 (Rule 1): | E23: =COUNTIF(Scoring!AH3:AH27,"FAIL") -> 3
A24: Candidates auto-classified Avoid (Rule 3): | E24: =COUNTIF(Scoring!AJ3:AJ27,"AVOID") -> 3
A25: Candidates flagged for mandatory Tier 1 review (Rule 2): | E25: =COUNTIF(Scoring!AI3:AI27,"REVIEW") -> 2
A26: Candidates capped at Buy despite Strong Buy score (Rule 4): | E26: =COUNTIF(Scoring!AK3:AK27,"CAP AT BUY") -> 0
A27: 6. ENTRY AUTHORIZATION — Rules 5-13 (see Entry Checklist tab for detail)
A28: Candidates NOT authorized to enter (failing one or more Entry Rules): | E28: =COUNTIF('Entry Checklist'!Q3:Q27,"NO*") -> 0
A29: Candidates authorized, staged at reduced size (50%, per Rules 8-9): | E29: =COUNTIF('Entry Checklist'!H3:H27,"*50%*") -> 0

Sheet Current Positions
A1: Combined current positions, both accounts, as of 08/05/2026 (JT ULTRA, Fidelity) and 08/04/2026 (Self-Directed, Chase — cash sweep custodied at Schwab, swept to VMFXX for yield). Source: uploaded brokerage exports, aggregated by ticker. Update this tab at each quarterly/annual review; use it with Part 5 sizing modifiers and the Holding Monitor tab to prescribe classifications and follow-up actions. | O1: TAX-LOSS CARRYFORWARD (update annually)
A2: Account | B2: Ticker | C2: Description | D2: Asset Class | E2: Quantity | F2: Price ($) | G2: Market Value ($) | H2: Cost Basis ($) | I2: Unrealized G/L ($) | J2: Unrealized G/L (%) | K2: % of Account | L2: % of Combined Portfolio | M2: Classification / Notes (fill at review) | O2: Short-Term Loss Carryforward:
A3: JT ULTRA (Fidelity) | B3: ADBE | C3: Adobe Inc. | D3: Equity | E3: 45 | F3: 259.32 | G3: =E3*F3 -> 11669.4 | H3: 13836.24 | I3: =G3-H3 -> -2166.84 | J3: =IF(H3=0,"",G3/H3-1) -> -0.15660613 | K3: =G3/SUM(G3:G14) -> 0.028908948 | L3: =G3/SUM(G3:G14,G17:G35) -> 0.016652986 | O3: Long-Term Loss Carryforward:
A4: JT ULTRA (Fidelity) | B4: ANET | C4: Arista Networks | D4: Equity | E4: 70 | F4: 197.31 | G4: =E4*F4 -> 13811.7 | H4: 10182.2 | I4: =G4-H4 -> 3629.5 | J4: =IF(H4=0,"",G4/H4-1) -> 0.35645538 | K4: =G4/SUM(G3:G14) -> 0.03421613 | L4: =G4/SUM(G3:G14,G17:G35) -> 0.019710186
A5: JT ULTRA (Fidelity) | B5: ASML | C5: ASML Holding | D5: Equity | E5: 7 | F5: 1678.22 | G5: =E5*F5 -> 11747.54 | H5: 9989.88 | I5: =G5-H5 -> 1757.66 | J5: =IF(H5=0,"",G5/H5-1) -> 0.17594406 | K5: =G5/SUM(G3:G14) -> 0.029102526 | L5: =G5/SUM(G3:G14,G17:G35) -> 0.016764497
A6: JT ULTRA (Fidelity) | B6: CRWD | C6: CrowdStrike Holdings | D6: Equity | E6: 40 | F6: 209.86 | G6: =E6*F6 -> 8394.4 | H6: 4991.35 | I6: =G6-H6 -> 3403.05 | J6: =IF(H6=0,"",G6/H6-1) -> 0.6817895 | K6: =G6/SUM(G3:G14) -> 0.020795694 | L6: =G6/SUM(G3:G14,G17:G35) -> 0.01197935
A7: JT ULTRA (Fidelity) | B7: KLAC | C7: KLA Corporation | D7: Equity | E7: 100 | F7: 192.8 | G7: =E7*F7 -> 19280 | H7: 15412.54 | I7: =G7-H7 -> 3867.46 | J7: =IF(H7=0,"",G7/H7-1) -> 0.25092944 | K7: =G7/SUM(G3:G14) -> 0.047762911 | L7: =G7/SUM(G3:G14,G17:G35) -> 0.027513803
A8: JT ULTRA (Fidelity) | B8: MU | C8: Micron Technology | D8: Equity | E8: 7 | F8: 893.19 | G8: =E8*F8 -> 6252.33 | H8: 5836.11 | I8: =G8-H8 -> 416.22 | J8: =IF(H8=0,"",G8/H8-1) -> 0.071318053 | K8: =G8/SUM(G3:G14) -> 0.015489081 | L8: =G8/SUM(G3:G14,G17:G35) -> 0.008922478
A9: JT ULTRA (Fidelity) | B9: NVDA | C9: NVIDIA Corporation | D9: Equity | E9: 155 | F9: 219.22 | G9: =E9*F9 -> 33979.1 | H9: 26639.79 | I9: =G9-H9 -> 7339.31 | J9: =IF(H9=0,"",G9/H9-1) -> 0.2755018 | K9: =G9/SUM(G3:G14) -> 0.084177423 | L9: =G9/SUM(G3:G14,G17:G35) -> 0.048490366
A10: JT ULTRA (Fidelity) | B10: PLTR | C10: Palantir Technologies | D10: Equity | E10: 70 | F10: 158.43 | G10: =E10*F10 -> 11090.1 | H10: 11612.3 | I10: =G10-H10 -> -522.2 | J10: =IF(H10=0,"",G10/H10-1) -> -0.044969558 | K10: =G10/SUM(G3:G14) -> 0.027473831 | L10: =G10/SUM(G3:G14,G17:G35) -> 0.015826288
A11: JT ULTRA (Fidelity) | B11: TSM | C11: Taiwan Semiconductor | D11: Equity | E11: 25 | F11: 414 | G11: =E11*F11 -> 10350 | H11: 6069.64 | I11: =G11-H11 -> 4280.36 | J11: =IF(H11=0,"",G11/H11-1) -> 0.70520822 | K11: =G11/SUM(G3:G14) -> 0.025640359 | L11: =G11/SUM(G3:G14,G17:G35) -> 0.014770117
A12: JT ULTRA (Fidelity) | B12: VRT | C12: Vertiv Holdings | D12: Equity | E12: 30 | F12: 277.94 | G12: =E12*F12 -> 8338.2 | H12: 7876.8 | I12: =G12-H12 -> 461.4 | J12: =IF(H12=0,"",G12/H12-1) -> 0.058577087 | K12: =G12/SUM(G3:G14) -> 0.020656468 | L12: =G12/SUM(G3:G14,G17:G35) -> 0.011899149
A13: JT ULTRA (Fidelity) | B13: FZDXX | C13: Fidelity Money Market Premium | D13: Cash | E13: 249948.16 | F13: 1 | G13: =E13*F13 -> 249948.16 | H13: 249948.16 | I13: =G13-H13 -> 0 | J13: =IF(H13=0,"",G13/H13-1) -> 0 | K13: =G13/SUM(G3:G14) -> 0.61920393 | L13: =G13/SUM(G3:G14,G17:G35) -> 0.35669214
A14: JT ULTRA (Fidelity) | B14: FZFXX | C14: Fidelity Core Money Market | D14: Cash | E14: 18799.56 | F14: 1 | G14: =E14*F14 -> 18799.56 | H14: 18799.56 | I14: =G14-H14 -> 0 | J14: =IF(H14=0,"",G14/H14-1) -> 0 | K14: =G14/SUM(G3:G14) -> 0.046572703 | L14: =G14/SUM(G3:G14,G17:G35) -> 0.026828184
C15: JT ULTRA (Fidelity) SUBTOTAL | G15: =SUM(G3:G14) -> 403660.49 | H15: =SUM(H3:H14) -> 381194.57 | I15: =SUM(I3:I14) -> 22465.92
A17: Self-Directed (Chase) | B17: VMFXX | C17: Vanguard Federal Money Market | D17: Cash | E17: 75832.09 | F17: 1 | G17: =E17*F17 -> 75832.09 | H17: 75832.09 | I17: =G17-H17 -> 0 | J17: =IF(H17=0,"",G17/H17-1) -> 0 | K17: =G17/SUM(G17:G35) -> 0.25525926 | L17: =G17/SUM(G3:G14,G17:G35) -> 0.10821728
A18: Self-Directed (Chase) | B18: JEPQ | C18: JPMorgan Nasdaq Equity Premium Income ETF | D18: Alternative Assets | E18: 840.4376 | F18: 59.56 | G18: =E18*F18 -> 50056.463 | H18: 42412.88 | I18: =G18-H18 -> 7643.5835 | J18: =IF(H18=0,"",G18/H18-1) -> 0.18021845 | K18: =G18/SUM(G17:G35) -> 0.16849563 | L18: =G18/SUM(G3:G14,G17:G35) -> 0.071433801
A19: Self-Directed (Chase) | B19: AVUV | C19: Avantis US Small Cap Value ETF | D19: Equity | E19: 206.4216 | F19: 128.74 | G19: =E19*F19 -> 26574.717 | H19: 20598.51 | I19: =G19-H19 -> 5976.2068 | J19: =IF(H19=0,"",G19/H19-1) -> 0.29012811 | K19: =G19/SUM(G17:G35) -> 0.089453458 | L19: =G19/SUM(G3:G14,G17:G35) -> 0.037923834
A20: Self-Directed (Chase) | B20: CALF | C20: Pacer US Small Cap Cash Cows ETF | D20: Equity | E20: 409.5467 | F20: 56.12 | G20: =E20*F20 -> 22983.761 | H20: 19073.09 | I20: =G20-H20 -> 3910.6708 | J20: =IF(H20=0,"",G20/H20-1) -> 0.20503604 | K20: =G20/SUM(G17:G35) -> 0.0773659 | L20: =G20/SUM(G3:G14,G17:G35) -> 0.032799309
A21: Self-Directed (Chase) | B21: HELO | C21: JPMorgan Hedged Equity Laddered Overlay ETF | D21: Alternative Assets | E21: 300 | F21: 69.59 | G21: =E21*F21 -> 20877 | H21: 16782 | I21: =G21-H21 -> 4095 | J21: =IF(H21=0,"",G21/H21-1) -> 0.24401144 | K21: =G21/SUM(G17:G35) -> 0.070274308 | L21: =G21/SUM(G3:G14,G17:G35) -> 0.029792825
A22: Self-Directed (Chase) | B22: AVGO | C22: Broadcom Inc. | D22: Equity | E22: 35.0759 | F22: 418.16 | G22: =E22*F22 -> 14667.338 | H22: 12653.43 | I22: =G22-H22 -> 2013.9083 | J22: =IF(H22=0,"",G22/H22-1) -> 0.15915909 | K22: =G22/SUM(G17:G35) -> 0.049371895 | L22: =G22/SUM(G3:G14,G17:G35) -> 0.020931237
A23: Self-Directed (Chase) | B23: NVDA | C23: NVIDIA Corporation | D23: Equity | E23: 59.0219 | F23: 211.87 | G23: =E23*F23 -> 12504.97 | H23: 11377.73 | I23: =G23-H23 -> 1127.24 | J23: =IF(H23=0,"",G23/H23-1) -> 0.09907424 | K23: =G23/SUM(G17:G35) -> 0.042093122 | L23: =G23/SUM(G3:G14,G17:G35) -> 0.017845398
A24: Self-Directed (Chase) | B24: VRTX | C24: Vertex Pharmaceuticals | D24: Equity | E24: 25 | F24: 478.7 | G24: =E24*F24 -> 11967.5 | H24: 11348.3 | I24: =G24-H24 -> 619.2 | J24: =IF(H24=0,"",G24/H24-1) -> 0.054563239 | K24: =G24/SUM(G17:G35) -> 0.040283939 | L24: =G24/SUM(G3:G14,G17:G35) -> 0.017078394 | M24: HOLD -- re-scored 75.6 BUY 8/7/26; original Avoid was based on bad FCF source data, corrected
A25: Self-Directed (Chase) | B25: SPMO | C25: Invesco S&P 500 Momentum ETF | D25: Equity | E25: 76.9374 | F25: 151.16 | G25: =E25*F25 -> 11629.857 | H25: 9318.79 | I25: =G25-H25 -> 2311.0674 | J25: =IF(H25=0,"",G25/H25-1) -> 0.2480008 | K25: =G25/SUM(G17:G35) -> 0.039147396 | L25: =G25/SUM(G3:G14,G17:G35) -> 0.016596556
A26: Self-Directed (Chase) | B26: VFLO | C26: Vanguard US Multifactor ETF | D26: Equity | E26: 200 | F26: 50.5 | G26: =E26*F26 -> 10100 | H26: 9257 | I26: =G26-H26 -> 843 | J26: =IF(H26=0,"",G26/H26-1) -> 0.09106622 | K26: =G26/SUM(G17:G35) -> 0.033997725 | L26: =G26/SUM(G3:G14,G17:G35) -> 0.014413351
A27: Self-Directed (Chase) | B27: ANET | C27: Arista Networks | D27: Equity | E27: 50 | F27: 190.51 | G27: =E27*F27 -> 9525.5 | H27: 7394.5 | I27: =G27-H27 -> 2131 | J27: =IF(H27=0,"",G27/H27-1) -> 0.28818717 | K27: =G27/SUM(G17:G35) -> 0.032063894 | L27: =G27/SUM(G3:G14,G17:G35) -> 0.013593503
A28: Self-Directed (Chase) | B28: CRWD | C28: CrowdStrike Holdings | D28: Equity | E28: 45 | F28: 211.22 | G28: =E28*F28 -> 9504.9 | H28: 7099.31 | I28: =G28-H28 -> 2405.59 | J28: =IF(H28=0,"",G28/H28-1) -> 0.33884842 | K28: =G28/SUM(G17:G35) -> 0.031994553 | L28: =G28/SUM(G3:G14,G17:G35) -> 0.013564105
A29: Self-Directed (Chase) | B29: PLD | C29: Prologis Inc. | D29: Equity | E29: 61.4484 | F29: 139.06 | G29: =E29*F29 -> 8545.0145 | H29: 7630.55 | I29: =G29-H29 -> 914.4645 | J29: =IF(H29=0,"",G29/H29-1) -> 0.11984254 | K29: =G29/SUM(G17:G35) -> 0.028763471 | L29: =G29/SUM(G3:G14,G17:G35) -> 0.012194287
A30: Self-Directed (Chase) | B30: SFM | C30: Sprouts Farmers Market | D30: Equity | E30: 0 | F30: 86.07 | G30: =E30*F30 -> 0 | H30: 0 | I30: =G30-H30 -> 0 | J30: =IF(H30=0,"",G30/H30-1) | K30: =G30/SUM(G17:G35) -> 0 | L30: =G30/SUM(G3:G14,G17:G35) -> 0 | M30: SOLD 08/07/26 -- confirmed: -65 sh, $5,601.58 proceeds. Rule 3 Avoid. Proceeds added to VMFXX (row 17).
A31: Self-Directed (Chase) | B31: TSLA | C31: Tesla Inc. | D31: Equity | E31: 0 | F31: 327.35 | G31: =E31*F31 -> 0 | H31: 0 | I31: =G31-H31 -> 0 | J31: =IF(H31=0,"",G31/H31-1) | K31: =G31/SUM(G17:G35) -> 0 | L31: =G31/SUM(G3:G14,G17:G35) -> 0 | M31: SOLD 08/07/26 -- confirmed: -15 sh, $4,783.25 proceeds. Rule 3 Avoid. Proceeds added to VMFXX (row 17).
A32: Self-Directed (Chase) | B32: VGT | C32: Vanguard Information Technology ETF | D32: Equity | E32: 40.1779 | F32: 120.16 | G32: =E32*F32 -> 4827.7765 | H32: 3643.46 | I32: =G32-H32 -> 1184.3165 | J32: =IF(H32=0,"",G32/H32-1) -> 0.32505269 | K32: =G32/SUM(G17:G35) -> 0.016250834 | L32: =G32/SUM(G3:G14,G17:G35) -> 0.0068895483
A33: Self-Directed (Chase) | B33: QACDS | C33: Schwab Cash Features (Sweep) | D33: Cash | E33: 4228.61 | F33: 1 | G33: =E33*F33 -> 4228.61 | H33: 4228.61 | I33: =G33-H33 -> 0 | J33: =IF(H33=0,"",G33/H33-1) -> 0 | K33: =G33/SUM(G17:G35) -> 0.014233972 | L33: =G33/SUM(G3:G14,G17:G35) -> 0.0060344991
A34: Self-Directed (Chase) | B34: ONON | C34: On Holding AG | D34: Equity | E34: 0 | F34: 37.61 | G34: =E34*F34 -> 0 | H34: 0 | I34: =G34-H34 -> 0 | J34: =IF(H34=0,"",G34/H34-1) | K34: =G34/SUM(G17:G35) -> 0 | L34: =G34/SUM(G3:G14,G17:G35) -> 0 | M34: SOLD 08/07/26 -- confirmed: -100 sh, $3,764.92 proceeds. Rule 3 Avoid. Proceeds added to VMFXX (row 17).
A35: Self-Directed (Chase) | B35: PLTR | C35: Palantir Technologies | D35: Equity | E35: 20 | F35: 162.66 | G35: =E35*F35 -> 3253.2 | H35: 3178 | I35: =G35-H35 -> 75.2 | J35: =IF(H35=0,"",G35/H35-1) -> 0.023662681 | K35: =G35/SUM(G17:G35) -> 0.010950634 | L35: =G35/SUM(G3:G14,G17:G35) -> 0.0046425261
C36: Self-Directed (Chase) SUBTOTAL | G36: =SUM(G17:G35) -> 297078.7 | H36: =SUM(H17:H35) -> 261828.25 | I36: =SUM(I17:I35) -> 35250.448
C38: COMBINED PORTFOLIO TOTAL | G38: =SUM(G3:G14)+SUM(G17:G35) -> 700739.19 | H38: =SUM(H3:H14)+SUM(H17:H35) -> 643022.82 | I38: =SUM(I3:I14)+SUM(I17:I35) -> 57716.368
A40: NOTE: JT ULTRA's ASML/PLTR/MU quantities reflect trims already executed from the earlier rebalance session; SWAN is not currently held in this export (flagging in case that wasn't intentional). Several Self-Directed (Chase) tickers (JEPQ, AVUV, CALF, HELO, SPMO, VFLO, VGT, VRTX, PLD, SFM, ONON, TSLA) have not yet been run through the Scoring tab — that's the natural next step before classifying them.

Sheet Monitor & Recheck Triggers
A1: Recheck triggers for every name that's been scored, not just Watch List holdings. Update Current Price, Insider Activity, and Analyst Shift by hand for now (or during Claude Code automation later); Recheck Status calculates automatically from all signals together.
A2: Ticker | B2: Category | C2: Last Score Date | D2: Last Composite | E2: Last Tier 1 Wtd Avg | F2: Last Decision | G2: Price at Last Score | H2: Current Price | I2: % Price Change | J2: Next/Last Earnings Date | K2: Insider Activity? (Y/N) | L2: Insider Note | M2: Analyst Shift? (Y/N) | N2: Days Since Last Score | O2: Recheck Status | P2: Notes
A3: ADBE | B3: Owned | C3: 46240 | D3: 85.8 | E3: 4.57 | F3: STRONG BUY | G3: 259.32 | I3: =IF(OR(G3="",H3=""),"",H3/G3-1) | N3: =IF(C3="","",TODAY()-C3) -> 0 | O3: =IF(A3="","",IF(N3>180,"DUE — STALE (>180 days)",IF(J3<>"",IF(ABS(J3-TODAY())<=7,"DUE — EARNINGS WINDOW",IF(I3<>"",IF(ABS(I3)>=0.2,"DUE — PRICE MOVE ±20%",IF(K3="Y","DUE — INSIDER ACTIVITY",IF(I3<>"",IF(ABS(I3)>=0.15,"WATCH — PRICE MOVE ±15%",IF(M3="Y","WATCH — ANALYST SHIFT","Monitor Only")),IF(M3="Y","WATCH — ANALYST SHIFT","Monitor Only")))),IF(K3="Y","DUE — INSIDER ACTIVITY",IF(I3<>"",IF(ABS(I3)>=0.15,"WATCH — PRICE MOVE ±15%",IF(M3="Y","WATCH — ANALYST SHIFT","Monitor Only")),IF(M3="Y","WATCH — ANALYST SHIFT","Monitor Only"))))),IF(I3<>"",IF(ABS(I3)>=0.2,"DUE — PRICE MOVE ±20%",IF(K3="Y","DUE — INSIDER ACTIVITY",IF(I3<>"",IF(ABS(I3)>=0.15,"WATCH — PRICE MOVE ±15%",IF(M3="Y","WATCH — ANALYST SHIFT","Monitor Only")),IF(M3="Y","WATCH — ANALYST SHIFT","Monitor Only")))),IF(K3="Y","DUE — INSIDER ACTIVITY",IF(I3<>"",IF(ABS(I3)>=0.15,"WATCH — PRICE MOVE ±15%",IF(M3="Y","WATCH — ANALYST SHIFT","Monitor Only")),IF(M3="Y","WATCH — ANALYST SHIFT","Monitor Only"))))))) -> Monitor Only
A4: ANET | B4: Owned | C4: 46240 | D4: 85 | E4: 4.57 | F4: STRONG BUY | G4: 190.51 | I4: =IF(OR(G4="",H4=""),"",H4/G4-1) | N4: =IF(C4="","",TODAY()-C4) -> 0 | O4: =IF(A4="","",IF(N4>180,"DUE — STALE (>180 days)",IF(J4<>"",IF(ABS(J4-TODAY())<=7,"DUE — EARNINGS WINDOW",IF(I4<>"",IF(ABS(I4)>=0.2,"DUE — PRICE MOVE ±20%",IF(K4="Y","DUE — INSIDER ACTIVITY",IF(I4<>"",IF(ABS(I4)>=0.15,"WATCH — PRICE MOVE ±15%",IF(M4="Y","WATCH — ANALYST SHIFT","Monitor Only")),IF(M4="Y","WATCH — ANALYST SHIFT","Monitor Only")))),IF(K4="Y","DUE — INSIDER ACTIVITY",IF(I4<>"",IF(ABS(I4)>=0.15,"WATCH — PRICE MOVE ±15%",IF(M4="Y","WATCH — ANALYST SHIFT","Monitor Only")),IF(M4="Y","WATCH — ANALYST SHIFT","Monitor Only"))))),IF(I4<>"",IF(ABS(I4)>=0.2,"DUE — PRICE MOVE ±20%",IF(K4="Y","DUE — INSIDER ACTIVITY",IF(I4<>"",IF(ABS(I4)>=0.15,"WATCH — PRICE MOVE ±15%",IF(M4="Y","WATCH — ANALYST SHIFT","Monitor Only")),IF(M4="Y","WATCH — ANALYST SHIFT","Monitor Only")))),IF(K4="Y","DUE — INSIDER ACTIVITY",IF(I4<>"",IF(ABS(I4)>=0.15,"WATCH — PRICE MOVE ±15%",IF(M4="Y","WATCH — ANALYST SHIFT","Monitor Only")),IF(M4="Y","WATCH — ANALYST SHIFT","Monitor Only"))))))) -> Monitor Only
A5: ASML | B5: Owned | C5: 46240 | D5: 73.2 | E5: 3.57 | F5: BUY | G5: 1678.22 | I5: =IF(OR(G5="",H5=""),"",H5/G5-1) | N5: =IF(C5="","",TODAY()-C5) -> 0 | O5: =IF(A5="","",IF(N5>180,"DUE — STALE (>180 days)",IF(J5<>"",IF(ABS(J5-TODAY())<=7,"DUE — EARNINGS WINDOW",IF(I5<>"",IF(ABS(I5)>=0.2,"DUE — PRICE MOVE ±20%",IF(K5="Y","DUE — INSIDER ACTIVITY",IF(I5<>"",IF(ABS(I5)>=0.15,"WATCH — PRICE MOVE ±15%",IF(M5="Y","WATCH — ANALYST SHIFT","Monitor Only")),IF(M5="Y","WATCH — ANALYST SHIFT","Monitor Only")))),IF(K5="Y","DUE — INSIDER ACTIVITY",IF(I5<>"",IF(ABS(I5)>=0.15,"WATCH — PRICE MOVE ±15%",IF(M5="Y","WATCH — ANALYST SHIFT","Monitor Only")),IF(M5="Y","WATCH — ANALYST SHIFT","Monitor Only"))))),IF(I5<>"",IF(ABS(I5)>=0.2,"DUE — PRICE MOVE ±20%",IF(K5="Y","DUE — INSIDER ACTIVITY",IF(I5<>"",IF(ABS(I5)>=0.15,"WATCH — PRICE MOVE ±15%",IF(M5="Y","WATCH — ANALYST SHIFT","Monitor Only")),IF(M5="Y","WATCH — ANALYST SHIFT","Monitor Only")))),IF(K5="Y","DUE — INSIDER ACTIVITY",IF(I5<>"",IF(ABS(I5)>=0.15,"WATCH — PRICE MOVE ±15%",IF(M5="Y","WATCH — ANALYST SHIFT","Monitor Only")),IF(M5="Y","WATCH — ANALYST SHIFT","Monitor Only"))))))) -> Monitor Only
A6: CRWD | B6: Owned | C6: 46240 | D6: 70.4 | E6: 4 | F6: BUY | G6: 211.22 | I6: =IF(OR(G6="",H6=""),"",H6/G6-1) | N6: =IF(C6="","",TODAY()-C6) -> 0 | O6: =IF(A6="","",IF(N6>180,"DUE — STALE (>180 days)",IF(J6<>"",IF(ABS(J6-TODAY())<=7,"DUE — EARNINGS WINDOW",IF(I6<>"",IF(ABS(I6)>=0.2,"DUE — PRICE MOVE ±20%",IF(K6="Y","DUE — INSIDER ACTIVITY",IF(I6<>"",IF(ABS(I6)>=0.15,"WATCH — PRICE MOVE ±15%",IF(M6="Y","WATCH — ANALYST SHIFT","Monitor Only")),IF(M6="Y","WATCH — ANALYST SHIFT","Monitor Only")))),IF(K6="Y","DUE — INSIDER ACTIVITY",IF(I6<>"",IF(ABS(I6)>=0.15,"WATCH — PRICE MOVE ±15%",IF(M6="Y","WATCH — ANALYST SHIFT","Monitor Only")),IF(M6="Y","WATCH — ANALYST SHIFT","Monitor Only"))))),IF(I6<>"",IF(ABS(I6)>=0.2,"DUE — PRICE MOVE ±20%",IF(K6="Y","DUE — INSIDER ACTIVITY",IF(I6<>"",IF(ABS(I6)>=0.15,"WATCH — PRICE MOVE ±15%",IF(M6="Y","WATCH — ANALYST SHIFT","Monitor Only")),IF(M6="Y","WATCH — ANALYST SHIFT","Monitor Only")))),IF(K6="Y","DUE — INSIDER ACTIVITY",IF(I6<>"",IF(ABS(I6)>=0.15,"WATCH — PRICE MOVE ±15%",IF(M6="Y","WATCH — ANALYST SHIFT","Monitor Only")),IF(M6="Y","WATCH — ANALYST SHIFT","Monitor Only"))))))) -> Monitor Only
A7: KLAC | B7: Owned | C7: 46240 | D7: 68.6 | E7: 3.43 | F7: BUY | G7: 192.8 | I7: =IF(OR(G7="",H7=""),"",H7/G7-1) | N7: =IF(C7="","",TODAY()-C7) -> 0 | O7: =IF(A7="","",IF(N7>180,"DUE — STALE (>180 days)",IF(J7<>"",IF(ABS(J7-TODAY())<=7,"DUE — EARNINGS WINDOW",IF(I7<>"",IF(ABS(I7)>=0.2,"DUE — PRICE MOVE ±20%",IF(K7="Y","DUE — INSIDER ACTIVITY",IF(I7<>"",IF(ABS(I7)>=0.15,"WATCH — PRICE MOVE ±15%",IF(M7="Y","WATCH — ANALYST SHIFT","Monitor Only")),IF(M7="Y","WATCH — ANALYST SHIFT","Monitor Only")))),IF(K7="Y","DUE — INSIDER ACTIVITY",IF(I7<>"",IF(ABS(I7)>=0.15,"WATCH — PRICE MOVE ±15%",IF(M7="Y","WATCH — ANALYST SHIFT","Monitor Only")),IF(M7="Y","WATCH — ANALYST SHIFT","Monitor Only"))))),IF(I7<>"",IF(ABS(I7)>=0.2,"DUE — PRICE MOVE ±20%",IF(K7="Y","DUE — INSIDER ACTIVITY",IF(I7<>"",IF(ABS(I7)>=0.15,"WATCH — PRICE MOVE ±15%",IF(M7="Y","WATCH — ANALYST SHIFT","Monitor Only")),IF(M7="Y","WATCH — ANALYST SHIFT","Monitor Only")))),IF(K7="Y","DUE — INSIDER ACTIVITY",IF(I7<>"",IF(ABS(I7)>=0.15,"WATCH — PRICE MOVE ±15%",IF(M7="Y","WATCH — ANALYST SHIFT","Monitor Only")),IF(M7="Y","WATCH — ANALYST SHIFT","Monitor Only"))))))) -> Monitor Only
A8: MU | B8: Owned | C8: 46240 | D8: 71.8 | E8: 3.64 | F8: BUY | G8: 893.19 | I8: =IF(OR(G8="",H8=""),"",H8/G8-1) | N8: =IF(C8="","",TODAY()-C8) -> 0 | O8: =IF(A8="","",IF(N8>180,"DUE — STALE (>180 days)",IF(J8<>"",IF(ABS(J8-TODAY())<=7,"DUE — EARNINGS WINDOW",IF(I8<>"",IF(ABS(I8)>=0.2,"DUE — PRICE MOVE ±20%",IF(K8="Y","DUE — INSIDER ACTIVITY",IF(I8<>"",IF(ABS(I8)>=0.15,"WATCH — PRICE MOVE ±15%",IF(M8="Y","WATCH — ANALYST SHIFT","Monitor Only")),IF(M8="Y","WATCH — ANALYST SHIFT","Monitor Only")))),IF(K8="Y","DUE — INSIDER ACTIVITY",IF(I8<>"",IF(ABS(I8)>=0.15,"WATCH — PRICE MOVE ±15%",IF(M8="Y","WATCH — ANALYST SHIFT","Monitor Only")),IF(M8="Y","WATCH — ANALYST SHIFT","Monitor Only"))))),IF(I8<>"",IF(ABS(I8)>=0.2,"DUE — PRICE MOVE ±20%",IF(K8="Y","DUE — INSIDER ACTIVITY",IF(I8<>"",IF(ABS(I8)>=0.15,"WATCH — PRICE MOVE ±15%",IF(M8="Y","WATCH — ANALYST SHIFT","Monitor Only")),IF(M8="Y","WATCH — ANALYST SHIFT","Monitor Only")))),IF(K8="Y","DUE — INSIDER ACTIVITY",IF(I8<>"",IF(ABS(I8)>=0.15,"WATCH — PRICE MOVE ±15%",IF(M8="Y","WATCH — ANALYST SHIFT","Monitor Only")),IF(M8="Y","WATCH — ANALYST SHIFT","Monitor Only"))))))) -> Monitor Only
A9: NVDA | B9: Owned | C9: 46240 | D9: 93.2 | E9: 4.57 | F9: STRONG BUY | G9: 211.87 | I9: =IF(OR(G9="",H9=""),"",H9/G9-1) | N9: =IF(C9="","",TODAY()-C9) -> 0 | O9: =IF(A9="","",IF(N9>180,"DUE — STALE (>180 days)",IF(J9<>"",IF(ABS(J9-TODAY())<=7,"DUE — EARNINGS WINDOW",IF(I9<>"",IF(ABS(I9)>=0.2,"DUE — PRICE MOVE ±20%",IF(K9="Y","DUE — INSIDER ACTIVITY",IF(I9<>"",IF(ABS(I9)>=0.15,"WATCH — PRICE MOVE ±15%",IF(M9="Y","WATCH — ANALYST SHIFT","Monitor Only")),IF(M9="Y","WATCH — ANALYST SHIFT","Monitor Only")))),IF(K9="Y","DUE — INSIDER ACTIVITY",IF(I9<>"",IF(ABS(I9)>=0.15,"WATCH — PRICE MOVE ±15%",IF(M9="Y","WATCH — ANALYST SHIFT","Monitor Only")),IF(M9="Y","WATCH — ANALYST SHIFT","Monitor Only"))))),IF(I9<>"",IF(ABS(I9)>=0.2,"DUE — PRICE MOVE ±20%",IF(K9="Y","DUE — INSIDER ACTIVITY",IF(I9<>"",IF(ABS(I9)>=0.15,"WATCH — PRICE MOVE ±15%",IF(M9="Y","WATCH — ANALYST SHIFT","Monitor Only")),IF(M9="Y","WATCH — ANALYST SHIFT","Monitor Only")))),IF(K9="Y","DUE — INSIDER ACTIVITY",IF(I9<>"",IF(ABS(I9)>=0.15,"WATCH — PRICE MOVE ±15%",IF(M9="Y","WATCH — ANALYST SHIFT","Monitor Only")),IF(M9="Y","WATCH — ANALYST SHIFT","Monitor Only"))))))) -> Monitor Only
A10: PLTR | B10: Owned | C10: 46240 | D10: 75.2 | E10: 4 | F10: BUY | G10: 162.66 | I10: =IF(OR(G10="",H10=""),"",H10/G10-1) | N10: =IF(C10="","",TODAY()-C10) -> 0 | O10: =IF(A10="","",IF(N10>180,"DUE — STALE (>180 days)",IF(J10<>"",IF(ABS(J10-TODAY())<=7,"DUE — EARNINGS WINDOW",IF(I10<>"",IF(ABS(I10)>=0.2,"DUE — PRICE MOVE ±20%",IF(K10="Y","DUE — INSIDER ACTIVITY",IF(I10<>"",IF(ABS(I10)>=0.15,"WATCH — PRICE MOVE ±15%",IF(M10="Y","WATCH — ANALYST SHIFT","Monitor Only")),IF(M10="Y","WATCH — ANALYST SHIFT","Monitor Only")))),IF(K10="Y","DUE — INSIDER ACTIVITY",IF(I10<>"",IF(ABS(I10)>=0.15,"WATCH — PRICE MOVE ±15%",IF(M10="Y","WATCH — ANALYST SHIFT","Monitor Only")),IF(M10="Y","WATCH — ANALYST SHIFT","Monitor Only"))))),IF(I10<>"",IF(ABS(I10)>=0.2,"DUE — PRICE MOVE ±20%",IF(K10="Y","DUE — INSIDER ACTIVITY",IF(I10<>"",IF(ABS(I10)>=0.15,"WATCH — PRICE MOVE ±15%",IF(M10="Y","WATCH — ANALYST SHIFT","Monitor Only")),IF(M10="Y","WATCH — ANALYST SHIFT","Monitor Only")))),IF(K10="Y","DUE — INSIDER ACTIVITY",IF(I10<>"",IF(ABS(I10)>=0.15,"WATCH — PRICE MOVE ±15%",IF(M10="Y","WATCH — ANALYST SHIFT","Monitor Only")),IF(M10="Y","WATCH — ANALYST SHIFT","Monitor Only"))))))) -> Monitor Only
A11: TSM | B11: Owned | C11: 46240 | D11: 81 | E11: 4 | F11: STRONG BUY | G11: 414 | I11: =IF(OR(G11="",H11=""),"",H11/G11-1) | N11: =IF(C11="","",TODAY()-C11) -> 0 | O11: =IF(A11="","",IF(N11>180,"DUE — STALE (>180 days)",IF(J11<>"",IF(ABS(J11-TODAY())<=7,"DUE — EARNINGS WINDOW",IF(I11<>"",IF(ABS(I11)>=0.2,"DUE — PRICE MOVE ±20%",IF(K11="Y","DUE — INSIDER ACTIVITY",IF(I11<>"",IF(ABS(I11)>=0.15,"WATCH — PRICE MOVE ±15%",IF(M11="Y","WATCH — ANALYST SHIFT","Monitor Only")),IF(M11="Y","WATCH — ANALYST SHIFT","Monitor Only")))),IF(K11="Y","DUE — INSIDER ACTIVITY",IF(I11<>"",IF(ABS(I11)>=0.15,"WATCH — PRICE MOVE ±15%",IF(M11="Y","WATCH — ANALYST SHIFT","Monitor Only")),IF(M11="Y","WATCH — ANALYST SHIFT","Monitor Only"))))),IF(I11<>"",IF(ABS(I11)>=0.2,"DUE — PRICE MOVE ±20%",IF(K11="Y","DUE — INSIDER ACTIVITY",IF(I11<>"",IF(ABS(I11)>=0.15,"WATCH — PRICE MOVE ±15%",IF(M11="Y","WATCH — ANALYST SHIFT","Monitor Only")),IF(M11="Y","WATCH — ANALYST SHIFT","Monitor Only")))),IF(K11="Y","DUE — INSIDER ACTIVITY",IF(I11<>"",IF(ABS(I11)>=0.15,"WATCH — PRICE MOVE ±15%",IF(M11="Y","WATCH — ANALYST SHIFT","Monitor Only")),IF(M11="Y","WATCH — ANALYST SHIFT","Monitor Only"))))))) -> Monitor Only
A12: VRT | B12: Owned | C12: 46240 | D12: 82.8 | E12: 4.36 | F12: STRONG BUY | G12: 277.94 | I12: =IF(OR(G12="",H12=""),"",H12/G12-1) | N12: =IF(C12="","",TODAY()-C12) -> 0 | O12: =IF(A12="","",IF(N12>180,"DUE — STALE (>180 days)",IF(J12<>"",IF(ABS(J12-TODAY())<=7,"DUE — EARNINGS WINDOW",IF(I12<>"",IF(ABS(I12)>=0.2,"DUE — PRICE MOVE ±20%",IF(K12="Y","DUE — INSIDER ACTIVITY",IF(I12<>"",IF(ABS(I12)>=0.15,"WATCH — PRICE MOVE ±15%",IF(M12="Y","WATCH — ANALYST SHIFT","Monitor Only")),IF(M12="Y","WATCH — ANALYST SHIFT","Monitor Only")))),IF(K12="Y","DUE — INSIDER ACTIVITY",IF(I12<>"",IF(ABS(I12)>=0.15,"WATCH — PRICE MOVE ±15%",IF(M12="Y","WATCH — ANALYST SHIFT","Monitor Only")),IF(M12="Y","WATCH — ANALYST SHIFT","Monitor Only"))))),IF(I12<>"",IF(ABS(I12)>=0.2,"DUE — PRICE MOVE ±20%",IF(K12="Y","DUE — INSIDER ACTIVITY",IF(I12<>"",IF(ABS(I12)>=0.15,"WATCH — PRICE MOVE ±15%",IF(M12="Y","WATCH — ANALYST SHIFT","Monitor Only")),IF(M12="Y","WATCH — ANALYST SHIFT","Monitor Only")))),IF(K12="Y","DUE — INSIDER ACTIVITY",IF(I12<>"",IF(ABS(I12)>=0.15,"WATCH — PRICE MOVE ±15%",IF(M12="Y","WATCH — ANALYST SHIFT","Monitor Only")),IF(M12="Y","WATCH — ANALYST SHIFT","Monitor Only"))))))) -> Monitor Only
A13: AVGO | B13: Owned | C13: 46240 | D13: 80.8 | E13: 4.07 | F13: STRONG BUY | G13: 418.16 | I13: =IF(OR(G13="",H13=""),"",H13/G13-1) | N13: =IF(C13="","",TODAY()-C13) -> 0 | O13: =IF(A13="","",IF(N13>180,"DUE — STALE (>180 days)",IF(J13<>"",IF(ABS(J13-TODAY())<=7,"DUE — EARNINGS WINDOW",IF(I13<>"",IF(ABS(I13)>=0.2,"DUE — PRICE MOVE ±20%",IF(K13="Y","DUE — INSIDER ACTIVITY",IF(I13<>"",IF(ABS(I13)>=0.15,"WATCH — PRICE MOVE ±15%",IF(M13="Y","WATCH — ANALYST SHIFT","Monitor Only")),IF(M13="Y","WATCH — ANALYST SHIFT","Monitor Only")))),IF(K13="Y","DUE — INSIDER ACTIVITY",IF(I13<>"",IF(ABS(I13)>=0.15,"WATCH — PRICE MOVE ±15%",IF(M13="Y","WATCH — ANALYST SHIFT","Monitor Only")),IF(M13="Y","WATCH — ANALYST SHIFT","Monitor Only"))))),IF(I13<>"",IF(ABS(I13)>=0.2,"DUE — PRICE MOVE ±20%",IF(K13="Y","DUE — INSIDER ACTIVITY",IF(I13<>"",IF(ABS(I13)>=0.15,"WATCH — PRICE MOVE ±15%",IF(M13="Y","WATCH — ANALYST SHIFT","Monitor Only")),IF(M13="Y","WATCH — ANALYST SHIFT","Monitor Only")))),IF(K13="Y","DUE — INSIDER ACTIVITY",IF(I13<>"",IF(ABS(I13)>=0.15,"WATCH — PRICE MOVE ±15%",IF(M13="Y","WATCH — ANALYST SHIFT","Monitor Only")),IF(M13="Y","WATCH — ANALYST SHIFT","Monitor Only"))))))) -> Monitor Only
A14: PLD | B14: Owned | C14: 46240 | D14: 82 | E14: 4.36 | F14: STRONG BUY | G14: 139.06 | I14: =IF(OR(G14="",H14=""),"",H14/G14-1) | N14: =IF(C14="","",TODAY()-C14) -> 0 | O14: =IF(A14="","",IF(N14>180,"DUE — STALE (>180 days)",IF(J14<>"",IF(ABS(J14-TODAY())<=7,"DUE — EARNINGS WINDOW",IF(I14<>"",IF(ABS(I14)>=0.2,"DUE — PRICE MOVE ±20%",IF(K14="Y","DUE — INSIDER ACTIVITY",IF(I14<>"",IF(ABS(I14)>=0.15,"WATCH — PRICE MOVE ±15%",IF(M14="Y","WATCH — ANALYST SHIFT","Monitor Only")),IF(M14="Y","WATCH — ANALYST SHIFT","Monitor Only")))),IF(K14="Y","DUE — INSIDER ACTIVITY",IF(I14<>"",IF(ABS(I14)>=0.15,"WATCH — PRICE MOVE ±15%",IF(M14="Y","WATCH — ANALYST SHIFT","Monitor Only")),IF(M14="Y","WATCH — ANALYST SHIFT","Monitor Only"))))),IF(I14<>"",IF(ABS(I14)>=0.2,"DUE — PRICE MOVE ±20%",IF(K14="Y","DUE — INSIDER ACTIVITY",IF(I14<>"",IF(ABS(I14)>=0.15,"WATCH — PRICE MOVE ±15%",IF(M14="Y","WATCH — ANALYST SHIFT","Monitor Only")),IF(M14="Y","WATCH — ANALYST SHIFT","Monitor Only")))),IF(K14="Y","DUE — INSIDER ACTIVITY",IF(I14<>"",IF(ABS(I14)>=0.15,"WATCH — PRICE MOVE ±15%",IF(M14="Y","WATCH — ANALYST SHIFT","Monitor Only")),IF(M14="Y","WATCH — ANALYST SHIFT","Monitor Only"))))))) -> Monitor Only
A15: VRTX | B15: Owned | C15: 46241 | D15: 75.6 | E15: 3.79 | F15: BUY | G15: 478.7 | I15: =IF(OR(G15="",H15=""),"",H15/G15-1) | N15: =IF(C15="","",TODAY()-C15) -> -1 | O15: =IF(A15="","",IF(N15>180,"DUE — STALE (>180 days)",IF(J15<>"",IF(ABS(J15-TODAY())<=7,"DUE — EARNINGS WINDOW",IF(I15<>"",IF(ABS(I15)>=0.2,"DUE — PRICE MOVE ±20%",IF(K15="Y","DUE — INSIDER ACTIVITY",IF(I15<>"",IF(ABS(I15)>=0.15,"WATCH — PRICE MOVE ±15%",IF(M15="Y","WATCH — ANALYST SHIFT","Monitor Only")),IF(M15="Y","WATCH — ANALYST SHIFT","Monitor Only")))),IF(K15="Y","DUE — INSIDER ACTIVITY",IF(I15<>"",IF(ABS(I15)>=0.15,"WATCH — PRICE MOVE ±15%",IF(M15="Y","WATCH — ANALYST SHIFT","Monitor Only")),IF(M15="Y","WATCH — ANALYST SHIFT","Monitor Only"))))),IF(I15<>"",IF(ABS(I15)>=0.2,"DUE — PRICE MOVE ±20%",IF(K15="Y","DUE — INSIDER ACTIVITY",IF(I15<>"",IF(ABS(I15)>=0.15,"WATCH — PRICE MOVE ±15%",IF(M15="Y","WATCH — ANALYST SHIFT","Monitor Only")),IF(M15="Y","WATCH — ANALYST SHIFT","Monitor Only")))),IF(K15="Y","DUE — INSIDER ACTIVITY",IF(I15<>"",IF(ABS(I15)>=0.15,"WATCH — PRICE MOVE ±15%",IF(M15="Y","WATCH — ANALYST SHIFT","Monitor Only")),IF(M15="Y","WATCH — ANALYST SHIFT","Monitor Only"))))))) -> Monitor Only | P15: Re-scored 8/7/26: original Avoid was bad source data, corrected. See Journal.
A16: SFM | B16: Closed | C16: 46240 | E16: 1.86 | F16: AVOID | G16: 86.07 | I16: =IF(OR(G16="",H16=""),"",H16/G16-1) | N16: =IF(C16="","",TODAY()-C16) -> 0 | O16: =IF(A16="","",IF(N16>180,"DUE — STALE (>180 days)",IF(J16<>"",IF(ABS(J16-TODAY())<=7,"DUE — EARNINGS WINDOW",IF(I16<>"",IF(ABS(I16)>=0.2,"DUE — PRICE MOVE ±20%",IF(K16="Y","DUE — INSIDER ACTIVITY",IF(I16<>"",IF(ABS(I16)>=0.15,"WATCH — PRICE MOVE ±15%",IF(M16="Y","WATCH — ANALYST SHIFT","Monitor Only")),IF(M16="Y","WATCH — ANALYST SHIFT","Monitor Only")))),IF(K16="Y","DUE — INSIDER ACTIVITY",IF(I16<>"",IF(ABS(I16)>=0.15,"WATCH — PRICE MOVE ±15%",IF(M16="Y","WATCH — ANALYST SHIFT","Monitor Only")),IF(M16="Y","WATCH — ANALYST SHIFT","Monitor Only"))))),IF(I16<>"",IF(ABS(I16)>=0.2,"DUE — PRICE MOVE ±20%",IF(K16="Y","DUE — INSIDER ACTIVITY",IF(I16<>"",IF(ABS(I16)>=0.15,"WATCH — PRICE MOVE ±15%",IF(M16="Y","WATCH — ANALYST SHIFT","Monitor Only")),IF(M16="Y","WATCH — ANALYST SHIFT","Monitor Only")))),IF(K16="Y","DUE — INSIDER ACTIVITY",IF(I16<>"",IF(ABS(I16)>=0.15,"WATCH — PRICE MOVE ±15%",IF(M16="Y","WATCH — ANALYST SHIFT","Monitor Only")),IF(M16="Y","WATCH — ANALYST SHIFT","Monitor Only"))))))) -> Monitor Only | P16: Sold 08/07/26, confirmed. No longer an active recheck target.
A17: TSLA | B17: Closed | C17: 46240 | E17: 1.93 | F17: AVOID | G17: 327.35 | I17: =IF(OR(G17="",H17=""),"",H17/G17-1) | N17: =IF(C17="","",TODAY()-C17) -> 0 | O17: =IF(A17="","",IF(N17>180,"DUE — STALE (>180 days)",IF(J17<>"",IF(ABS(J17-TODAY())<=7,"DUE — EARNINGS WINDOW",IF(I17<>"",IF(ABS(I17)>=0.2,"DUE — PRICE MOVE ±20%",IF(K17="Y","DUE — INSIDER ACTIVITY",IF(I17<>"",IF(ABS(I17)>=0.15,"WATCH — PRICE MOVE ±15%",IF(M17="Y","WATCH — ANALYST SHIFT","Monitor Only")),IF(M17="Y","WATCH — ANALYST SHIFT","Monitor Only")))),IF(K17="Y","DUE — INSIDER ACTIVITY",IF(I17<>"",IF(ABS(I17)>=0.15,"WATCH — PRICE MOVE ±15%",IF(M17="Y","WATCH — ANALYST SHIFT","Monitor Only")),IF(M17="Y","WATCH — ANALYST SHIFT","Monitor Only"))))),IF(I17<>"",IF(ABS(I17)>=0.2,"DUE — PRICE MOVE ±20%",IF(K17="Y","DUE — INSIDER ACTIVITY",IF(I17<>"",IF(ABS(I17)>=0.15,"WATCH — PRICE MOVE ±15%",IF(M17="Y","WATCH — ANALYST SHIFT","Monitor Only")),IF(M17="Y","WATCH — ANALYST SHIFT","Monitor Only")))),IF(K17="Y","DUE — INSIDER ACTIVITY",IF(I17<>"",IF(ABS(I17)>=0.15,"WATCH — PRICE MOVE ±15%",IF(M17="Y","WATCH — ANALYST SHIFT","Monitor Only")),IF(M17="Y","WATCH — ANALYST SHIFT","Monitor Only"))))))) -> Monitor Only | P17: Sold 08/07/26, confirmed. No longer an active recheck target.
A18: ONON | B18: Closed | C18: 46240 | E18: 2.64 | F18: AVOID | G18: 37.61 | I18: =IF(OR(G18="",H18=""),"",H18/G18-1) | N18: =IF(C18="","",TODAY()-C18) -> 0 | O18: =IF(A18="","",IF(N18>180,"DUE — STALE (>180 days)",IF(J18<>"",IF(ABS(J18-TODAY())<=7,"DUE — EARNINGS WINDOW",IF(I18<>"",IF(ABS(I18)>=0.2,"DUE — PRICE MOVE ±20%",IF(K18="Y","DUE — INSIDER ACTIVITY",IF(I18<>"",IF(ABS(I18)>=0.15,"WATCH — PRICE MOVE ±15%",IF(M18="Y","WATCH — ANALYST SHIFT","Monitor Only")),IF(M18="Y","WATCH — ANALYST SHIFT","Monitor Only")))),IF(K18="Y","DUE — INSIDER ACTIVITY",IF(I18<>"",IF(ABS(I18)>=0.15,"WATCH — PRICE MOVE ±15%",IF(M18="Y","WATCH — ANALYST SHIFT","Monitor Only")),IF(M18="Y","WATCH — ANALYST SHIFT","Monitor Only"))))),IF(I18<>"",IF(ABS(I18)>=0.2,"DUE — PRICE MOVE ±20%",IF(K18="Y","DUE — INSIDER ACTIVITY",IF(I18<>"",IF(ABS(I18)>=0.15,"WATCH — PRICE MOVE ±15%",IF(M18="Y","WATCH — ANALYST SHIFT","Monitor Only")),IF(M18="Y","WATCH — ANALYST SHIFT","Monitor Only")))),IF(K18="Y","DUE — INSIDER ACTIVITY",IF(I18<>"",IF(ABS(I18)>=0.15,"WATCH — PRICE MOVE ±15%",IF(M18="Y","WATCH — ANALYST SHIFT","Monitor Only")),IF(M18="Y","WATCH — ANALYST SHIFT","Monitor Only"))))))) -> Monitor Only | P18: Sold 08/07/26, confirmed. No longer an active recheck target.
I19: =IF(OR(G19="",H19=""),"",H19/G19-1) | N19: =IF(C19="","",TODAY()-C19) | O19: =IF(A19="","",IF(N19>180,"DUE — STALE (>180 days)",IF(J19<>"",IF(ABS(J19-TODAY())<=7,"DUE — EARNINGS WINDOW",IF(I19<>"",IF(ABS(I19)>=0.2,"DUE — PRICE MOVE ±20%",IF(K19="Y","DUE — INSIDER ACTIVITY",IF(I19<>"",IF(ABS(I19)>=0.15,"WATCH — PRICE MOVE ±15%",IF(M19="Y","WATCH — ANALYST SHIFT","Monitor Only")),IF(M19="Y","WATCH — ANALYST SHIFT","Monitor Only")))),IF(K19="Y","DUE — INSIDER ACTIVITY",IF(I19<>"",IF(ABS(I19)>=0.15,"WATCH — PRICE MOVE ±15%",IF(M19="Y","WATCH — ANALYST SHIFT","Monitor Only")),IF(M19="Y","WATCH — ANALYST SHIFT","Monitor Only"))))),IF(I19<>"",IF(ABS(I19)>=0.2,"DUE — PRICE MOVE ±20%",IF(K19="Y","DUE — INSIDER ACTIVITY",IF(I19<>"",IF(ABS(I19)>=0.15,"WATCH — PRICE MOVE ±15%",IF(M19="Y","WATCH — ANALYST SHIFT","Monitor Only")),IF(M19="Y","WATCH — ANALYST SHIFT","Monitor Only")))),IF(K19="Y","DUE — INSIDER ACTIVITY",IF(I19<>"",IF(ABS(I19)>=0.15,"WATCH — PRICE MOVE ±15%",IF(M19="Y","WATCH — ANALYST SHIFT","Monitor Only")),IF(M19="Y","WATCH — ANALYST SHIFT","Monitor Only")))))))
I20: =IF(OR(G20="",H20=""),"",H20/G20-1) | N20: =IF(C20="","",TODAY()-C20) | O20: =IF(A20="","",IF(N20>180,"DUE — STALE (>180 days)",IF(J20<>"",IF(ABS(J20-TODAY())<=7,"DUE — EARNINGS WINDOW",IF(I20<>"",IF(ABS(I20)>=0.2,"DUE — PRICE MOVE ±20%",IF(K20="Y","DUE — INSIDER ACTIVITY",IF(I20<>"",IF(ABS(I20)>=0.15,"WATCH — PRICE MOVE ±15%",IF(M20="Y","WATCH — ANALYST SHIFT","Monitor Only")),IF(M20="Y","WATCH — ANALYST SHIFT","Monitor Only")))),IF(K20="Y","DUE — INSIDER ACTIVITY",IF(I20<>"",IF(ABS(I20)>=0.15,"WATCH — PRICE MOVE ±15%",IF(M20="Y","WATCH — ANALYST SHIFT","Monitor Only")),IF(M20="Y","WATCH — ANALYST SHIFT","Monitor Only"))))),IF(I20<>"",IF(ABS(I20)>=0.2,"DUE — PRICE MOVE ±20%",IF(K20="Y","DUE — INSIDER ACTIVITY",IF(I20<>"",IF(ABS(I20)>=0.15,"WATCH — PRICE MOVE ±15%",IF(M20="Y","WATCH — ANALYST SHIFT","Monitor Only")),IF(M20="Y","WATCH — ANALYST SHIFT","Monitor Only")))),IF(K20="Y","DUE — INSIDER ACTIVITY",IF(I20<>"",IF(ABS(I20)>=0.15,"WATCH — PRICE MOVE ±15%",IF(M20="Y","WATCH — ANALYST SHIFT","Monitor Only")),IF(M20="Y","WATCH — ANALYST SHIFT","Monitor Only")))))))
I21: =IF(OR(G21="",H21=""),"",H21/G21-1) | N21: =IF(C21="","",TODAY()-C21) | O21: =IF(A21="","",IF(N21>180,"DUE — STALE (>180 days)",IF(J21<>"",IF(ABS(J21-TODAY())<=7,"DUE — EARNINGS WINDOW",IF(I21<>"",IF(ABS(I21)>=0.2,"DUE — PRICE MOVE ±20%",IF(K21="Y","DUE — INSIDER ACTIVITY",IF(I21<>"",IF(ABS(I21)>=0.15,"WATCH — PRICE MOVE ±15%",IF(M21="Y","WATCH — ANALYST SHIFT","Monitor Only")),IF(M21="Y","WATCH — ANALYST SHIFT","Monitor Only")))),IF(K21="Y","DUE — INSIDER ACTIVITY",IF(I21<>"",IF(ABS(I21)>=0.15,"WATCH — PRICE MOVE ±15%",IF(M21="Y","WATCH — ANALYST SHIFT","Monitor Only")),IF(M21="Y","WATCH — ANALYST SHIFT","Monitor Only"))))),IF(I21<>"",IF(ABS(I21)>=0.2,"DUE — PRICE MOVE ±20%",IF(K21="Y","DUE — INSIDER ACTIVITY",IF(I21<>"",IF(ABS(I21)>=0.15,"WATCH — PRICE MOVE ±15%",IF(M21="Y","WATCH — ANALYST SHIFT","Monitor Only")),IF(M21="Y","WATCH — ANALYST SHIFT","Monitor Only")))),IF(K21="Y","DUE — INSIDER ACTIVITY",IF(I21<>"",IF(ABS(I21)>=0.15,"WATCH — PRICE MOVE ±15%",IF(M21="Y","WATCH — ANALYST SHIFT","Monitor Only")),IF(M21="Y","WATCH — ANALYST SHIFT","Monitor Only")))))))
I22: =IF(OR(G22="",H22=""),"",H22/G22-1) | N22: =IF(C22="","",TODAY()-C22) | O22: =IF(A22="","",IF(N22>180,"DUE — STALE (>180 days)",IF(J22<>"",IF(ABS(J22-TODAY())<=7,"DUE — EARNINGS WINDOW",IF(I22<>"",IF(ABS(I22)>=0.2,"DUE — PRICE MOVE ±20%",IF(K22="Y","DUE — INSIDER ACTIVITY",IF(I22<>"",IF(ABS(I22)>=0.15,"WATCH — PRICE MOVE ±15%",IF(M22="Y","WATCH — ANALYST SHIFT","Monitor Only")),IF(M22="Y","WATCH — ANALYST SHIFT","Monitor Only")))),IF(K22="Y","DUE — INSIDER ACTIVITY",IF(I22<>"",IF(ABS(I22)>=0.15,"WATCH — PRICE MOVE ±15%",IF(M22="Y","WATCH — ANALYST SHIFT","Monitor Only")),IF(M22="Y","WATCH — ANALYST SHIFT","Monitor Only"))))),IF(I22<>"",IF(ABS(I22)>=0.2,"DUE — PRICE MOVE ±20%",IF(K22="Y","DUE — INSIDER ACTIVITY",IF(I22<>"",IF(ABS(I22)>=0.15,"WATCH — PRICE MOVE ±15%",IF(M22="Y","WATCH — ANALYST SHIFT","Monitor Only")),IF(M22="Y","WATCH — ANALYST SHIFT","Monitor Only")))),IF(K22="Y","DUE — INSIDER ACTIVITY",IF(I22<>"",IF(ABS(I22)>=0.15,"WATCH — PRICE MOVE ±15%",IF(M22="Y","WATCH — ANALYST SHIFT","Monitor Only")),IF(M22="Y","WATCH — ANALYST SHIFT","Monitor Only")))))))
I23: =IF(OR(G23="",H23=""),"",H23/G23-1) | N23: =IF(C23="","",TODAY()-C23) | O23: =IF(A23="","",IF(N23>180,"DUE — STALE (>180 days)",IF(J23<>"",IF(ABS(J23-TODAY())<=7,"DUE — EARNINGS WINDOW",IF(I23<>"",IF(ABS(I23)>=0.2,"DUE — PRICE MOVE ±20%",IF(K23="Y","DUE — INSIDER ACTIVITY",IF(I23<>"",IF(ABS(I23)>=0.15,"WATCH — PRICE MOVE ±15%",IF(M23="Y","WATCH — ANALYST SHIFT","Monitor Only")),IF(M23="Y","WATCH — ANALYST SHIFT","Monitor Only")))),IF(K23="Y","DUE — INSIDER ACTIVITY",IF(I23<>"",IF(ABS(I23)>=0.15,"WATCH — PRICE MOVE ±15%",IF(M23="Y","WATCH — ANALYST SHIFT","Monitor Only")),IF(M23="Y","WATCH — ANALYST SHIFT","Monitor Only"))))),IF(I23<>"",IF(ABS(I23)>=0.2,"DUE — PRICE MOVE ±20%",IF(K23="Y","DUE — INSIDER ACTIVITY",IF(I23<>"",IF(ABS(I23)>=0.15,"WATCH — PRICE MOVE ±15%",IF(M23="Y","WATCH — ANALYST SHIFT","Monitor Only")),IF(M23="Y","WATCH — ANALYST SHIFT","Monitor Only")))),IF(K23="Y","DUE — INSIDER ACTIVITY",IF(I23<>"",IF(ABS(I23)>=0.15,"WATCH — PRICE MOVE ±15%",IF(M23="Y","WATCH — ANALYST SHIFT","Monitor Only")),IF(M23="Y","WATCH — ANALYST SHIFT","Monitor Only")))))))
I24: =IF(OR(G24="",H24=""),"",H24/G24-1) | N24: =IF(C24="","",TODAY()-C24) | O24: =IF(A24="","",IF(N24>180,"DUE — STALE (>180 days)",IF(J24<>"",IF(ABS(J24-TODAY())<=7,"DUE — EARNINGS WINDOW",IF(I24<>"",IF(ABS(I24)>=0.2,"DUE — PRICE MOVE ±20%",IF(K24="Y","DUE — INSIDER ACTIVITY",IF(I24<>"",IF(ABS(I24)>=0.15,"WATCH — PRICE MOVE ±15%",IF(M24="Y","WATCH — ANALYST SHIFT","Monitor Only")),IF(M24="Y","WATCH — ANALYST SHIFT","Monitor Only")))),IF(K24="Y","DUE — INSIDER ACTIVITY",IF(I24<>"",IF(ABS(I24)>=0.15,"WATCH — PRICE MOVE ±15%",IF(M24="Y","WATCH — ANALYST SHIFT","Monitor Only")),IF(M24="Y","WATCH — ANALYST SHIFT","Monitor Only"))))),IF(I24<>"",IF(ABS(I24)>=0.2,"DUE — PRICE MOVE ±20%",IF(K24="Y","DUE — INSIDER ACTIVITY",IF(I24<>"",IF(ABS(I24)>=0.15,"WATCH — PRICE MOVE ±15%",IF(M24="Y","WATCH — ANALYST SHIFT","Monitor Only")),IF(M24="Y","WATCH — ANALYST SHIFT","Monitor Only")))),IF(K24="Y","DUE — INSIDER ACTIVITY",IF(I24<>"",IF(ABS(I24)>=0.15,"WATCH — PRICE MOVE ±15%",IF(M24="Y","WATCH — ANALYST SHIFT","Monitor Only")),IF(M24="Y","WATCH — ANALYST SHIFT","Monitor Only")))))))
I25: =IF(OR(G25="",H25=""),"",H25/G25-1) | N25: =IF(C25="","",TODAY()-C25) | O25: =IF(A25="","",IF(N25>180,"DUE — STALE (>180 days)",IF(J25<>"",IF(ABS(J25-TODAY())<=7,"DUE — EARNINGS WINDOW",IF(I25<>"",IF(ABS(I25)>=0.2,"DUE — PRICE MOVE ±20%",IF(K25="Y","DUE — INSIDER ACTIVITY",IF(I25<>"",IF(ABS(I25)>=0.15,"WATCH — PRICE MOVE ±15%",IF(M25="Y","WATCH — ANALYST SHIFT","Monitor Only")),IF(M25="Y","WATCH — ANALYST SHIFT","Monitor Only")))),IF(K25="Y","DUE — INSIDER ACTIVITY",IF(I25<>"",IF(ABS(I25)>=0.15,"WATCH — PRICE MOVE ±15%",IF(M25="Y","WATCH — ANALYST SHIFT","Monitor Only")),IF(M25="Y","WATCH — ANALYST SHIFT","Monitor Only"))))),IF(I25<>"",IF(ABS(I25)>=0.2,"DUE — PRICE MOVE ±20%",IF(K25="Y","DUE — INSIDER ACTIVITY",IF(I25<>"",IF(ABS(I25)>=0.15,"WATCH — PRICE MOVE ±15%",IF(M25="Y","WATCH — ANALYST SHIFT","Monitor Only")),IF(M25="Y","WATCH — ANALYST SHIFT","Monitor Only")))),IF(K25="Y","DUE — INSIDER ACTIVITY",IF(I25<>"",IF(ABS(I25)>=0.15,"WATCH — PRICE MOVE ±15%",IF(M25="Y","WATCH — ANALYST SHIFT","Monitor Only")),IF(M25="Y","WATCH — ANALYST SHIFT","Monitor Only")))))))
I26: =IF(OR(G26="",H26=""),"",H26/G26-1) | N26: =IF(C26="","",TODAY()-C26) | O26: =IF(A26="","",IF(N26>180,"DUE — STALE (>180 days)",IF(J26<>"",IF(ABS(J26-TODAY())<=7,"DUE — EARNINGS WINDOW",IF(I26<>"",IF(ABS(I26)>=0.2,"DUE — PRICE MOVE ±20%",IF(K26="Y","DUE — INSIDER ACTIVITY",IF(I26<>"",IF(ABS(I26)>=0.15,"WATCH — PRICE MOVE ±15%",IF(M26="Y","WATCH — ANALYST SHIFT","Monitor Only")),IF(M26="Y","WATCH — ANALYST SHIFT","Monitor Only")))),IF(K26="Y","DUE — INSIDER ACTIVITY",IF(I26<>"",IF(ABS(I26)>=0.15,"WATCH — PRICE MOVE ±15%",IF(M26="Y","WATCH — ANALYST SHIFT","Monitor Only")),IF(M26="Y","WATCH — ANALYST SHIFT","Monitor Only"))))),IF(I26<>"",IF(ABS(I26)>=0.2,"DUE — PRICE MOVE ±20%",IF(K26="Y","DUE — INSIDER ACTIVITY",IF(I26<>"",IF(ABS(I26)>=0.15,"WATCH — PRICE MOVE ±15%",IF(M26="Y","WATCH — ANALYST SHIFT","Monitor Only")),IF(M26="Y","WATCH — ANALYST SHIFT","Monitor Only")))),IF(K26="Y","DUE — INSIDER ACTIVITY",IF(I26<>"",IF(ABS(I26)>=0.15,"WATCH — PRICE MOVE ±15%",IF(M26="Y","WATCH — ANALYST SHIFT","Monitor Only")),IF(M26="Y","WATCH — ANALYST SHIFT","Monitor Only")))))))
I27: =IF(OR(G27="",H27=""),"",H27/G27-1) | N27: =IF(C27="","",TODAY()-C27) | O27: =IF(A27="","",IF(N27>180,"DUE — STALE (>180 days)",IF(J27<>"",IF(ABS(J27-TODAY())<=7,"DUE — EARNINGS WINDOW",IF(I27<>"",IF(ABS(I27)>=0.2,"DUE — PRICE MOVE ±20%",IF(K27="Y","DUE — INSIDER ACTIVITY",IF(I27<>"",IF(ABS(I27)>=0.15,"WATCH — PRICE MOVE ±15%",IF(M27="Y","WATCH — ANALYST SHIFT","Monitor Only")),IF(M27="Y","WATCH — ANALYST SHIFT","Monitor Only")))),IF(K27="Y","DUE — INSIDER ACTIVITY",IF(I27<>"",IF(ABS(I27)>=0.15,"WATCH — PRICE MOVE ±15%",IF(M27="Y","WATCH — ANALYST SHIFT","Monitor Only")),IF(M27="Y","WATCH — ANALYST SHIFT","Monitor Only"))))),IF(I27<>"",IF(ABS(I27)>=0.2,"DUE — PRICE MOVE ±20%",IF(K27="Y","DUE — INSIDER ACTIVITY",IF(I27<>"",IF(ABS(I27)>=0.15,"WATCH — PRICE MOVE ±15%",IF(M27="Y","WATCH — ANALYST SHIFT","Monitor Only")),IF(M27="Y","WATCH — ANALYST SHIFT","Monitor Only")))),IF(K27="Y","DUE — INSIDER ACTIVITY",IF(I27<>"",IF(ABS(I27)>=0.15,"WATCH — PRICE MOVE ±15%",IF(M27="Y","WATCH — ANALYST SHIFT","Monitor Only")),IF(M27="Y","WATCH — ANALYST SHIFT","Monitor Only")))))))
I28: =IF(OR(G28="",H28=""),"",H28/G28-1) | N28: =IF(C28="","",TODAY()-C28) | O28: =IF(A28="","",IF(N28>180,"DUE — STALE (>180 days)",IF(J28<>"",IF(ABS(J28-TODAY())<=7,"DUE — EARNINGS WINDOW",IF(I28<>"",IF(ABS(I28)>=0.2,"DUE — PRICE MOVE ±20%",IF(K28="Y","DUE — INSIDER ACTIVITY",IF(I28<>"",IF(ABS(I28)>=0.15,"WATCH — PRICE MOVE ±15%",IF(M28="Y","WATCH — ANALYST SHIFT","Monitor Only")),IF(M28="Y","WATCH — ANALYST SHIFT","Monitor Only")))),IF(K28="Y","DUE — INSIDER ACTIVITY",IF(I28<>"",IF(ABS(I28)>=0.15,"WATCH — PRICE MOVE ±15%",IF(M28="Y","WATCH — ANALYST SHIFT","Monitor Only")),IF(M28="Y","WATCH — ANALYST SHIFT","Monitor Only"))))),IF(I28<>"",IF(ABS(I28)>=0.2,"DUE — PRICE MOVE ±20%",IF(K28="Y","DUE — INSIDER ACTIVITY",IF(I28<>"",IF(ABS(I28)>=0.15,"WATCH — PRICE MOVE ±15%",IF(M28="Y","WATCH — ANALYST SHIFT","Monitor Only")),IF(M28="Y","WATCH — ANALYST SHIFT","Monitor Only")))),IF(K28="Y","DUE — INSIDER ACTIVITY",IF(I28<>"",IF(ABS(I28)>=0.15,"WATCH — PRICE MOVE ±15%",IF(M28="Y","WATCH — ANALYST SHIFT","Monitor Only")),IF(M28="Y","WATCH — ANALYST SHIFT","Monitor Only")))))))
I29: =IF(OR(G29="",H29=""),"",H29/G29-1) | N29: =IF(C29="","",TODAY()-C29) | O29: =IF(A29="","",IF(N29>180,"DUE — STALE (>180 days)",IF(J29<>"",IF(ABS(J29-TODAY())<=7,"DUE — EARNINGS WINDOW",IF(I29<>"",IF(ABS(I29)>=0.2,"DUE — PRICE MOVE ±20%",IF(K29="Y","DUE — INSIDER ACTIVITY",IF(I29<>"",IF(ABS(I29)>=0.15,"WATCH — PRICE MOVE ±15%",IF(M29="Y","WATCH — ANALYST SHIFT","Monitor Only")),IF(M29="Y","WATCH — ANALYST SHIFT","Monitor Only")))),IF(K29="Y","DUE — INSIDER ACTIVITY",IF(I29<>"",IF(ABS(I29)>=0.15,"WATCH — PRICE MOVE ±15%",IF(M29="Y","WATCH — ANALYST SHIFT","Monitor Only")),IF(M29="Y","WATCH — ANALYST SHIFT","Monitor Only"))))),IF(I29<>"",IF(ABS(I29)>=0.2,"DUE — PRICE MOVE ±20%",IF(K29="Y","DUE — INSIDER ACTIVITY",IF(I29<>"",IF(ABS(I29)>=0.15,"WATCH — PRICE MOVE ±15%",IF(M29="Y","WATCH — ANALYST SHIFT","Monitor Only")),IF(M29="Y","WATCH — ANALYST SHIFT","Monitor Only")))),IF(K29="Y","DUE — INSIDER ACTIVITY",IF(I29<>"",IF(ABS(I29)>=0.15,"WATCH — PRICE MOVE ±15%",IF(M29="Y","WATCH — ANALYST SHIFT","Monitor Only")),IF(M29="Y","WATCH — ANALYST SHIFT","Monitor Only")))))))
I30: =IF(OR(G30="",H30=""),"",H30/G30-1) | N30: =IF(C30="","",TODAY()-C30) | O30: =IF(A30="","",IF(N30>180,"DUE — STALE (>180 days)",IF(J30<>"",IF(ABS(J30-TODAY())<=7,"DUE — EARNINGS WINDOW",IF(I30<>"",IF(ABS(I30)>=0.2,"DUE — PRICE MOVE ±20%",IF(K30="Y","DUE — INSIDER ACTIVITY",IF(I30<>"",IF(ABS(I30)>=0.15,"WATCH — PRICE MOVE ±15%",IF(M30="Y","WATCH — ANALYST SHIFT","Monitor Only")),IF(M30="Y","WATCH — ANALYST SHIFT","Monitor Only")))),IF(K30="Y","DUE — INSIDER ACTIVITY",IF(I30<>"",IF(ABS(I30)>=0.15,"WATCH — PRICE MOVE ±15%",IF(M30="Y","WATCH — ANALYST SHIFT","Monitor Only")),IF(M30="Y","WATCH — ANALYST SHIFT","Monitor Only"))))),IF(I30<>"",IF(ABS(I30)>=0.2,"DUE — PRICE MOVE ±20%",IF(K30="Y","DUE — INSIDER ACTIVITY",IF(I30<>"",IF(ABS(I30)>=0.15,"WATCH — PRICE MOVE ±15%",IF(M30="Y","WATCH — ANALYST SHIFT","Monitor Only")),IF(M30="Y","WATCH — ANALYST SHIFT","Monitor Only")))),IF(K30="Y","DUE — INSIDER ACTIVITY",IF(I30<>"",IF(ABS(I30)>=0.15,"WATCH — PRICE MOVE ±15%",IF(M30="Y","WATCH — ANALYST SHIFT","Monitor Only")),IF(M30="Y","WATCH — ANALYST SHIFT","Monitor Only")))))))
... I42: =IF(OR(G42="",H42=""),"",H42/G42-1) | N42: =IF(C42="","",TODAY()-C42) | O42: =IF(A42="","",IF(N42>180,"DUE — STALE (>180 days)",IF(J42<>"",IF(ABS(J42-TODAY())<=7,"DUE — EARNINGS WINDOW",IF(I42<>"",IF(ABS(I42)>=0.2,"DUE — PRICE MOVE ±20%",IF(K42="Y","DUE — INSIDER ACTIVITY",IF(I42<>"",IF(ABS(I42)>=0.15,"WATCH — PRICE MOVE ±15%",IF(M42="Y","WATCH — ANALYST SHIFT","Monitor Only")),IF(M42="Y","WATCH — ANALYST SHIFT","Monitor Only")))),IF(K42="Y","DUE — INSIDER ACTIVITY",IF(I42<>"",IF(ABS(I42)>=0.15,"WATCH — PRICE MOVE ±15%",IF(M42="Y","WATCH — ANALYST SHIFT","Monitor Only")),IF(M42="Y","WATCH — ANALYST SHIFT","Monitor Only"))))),IF(I42<>"",IF(ABS(I42)>=0.2,"DUE — PRICE MOVE ±20%",IF(K42="Y","DUE — INSIDER ACTIVITY",IF(I42<>"",IF(ABS(I42)>=0.15,"WATCH — PRICE MOVE ±15%",IF(M42="Y","WATCH — ANALYST SHIFT","Monitor Only")),IF(M42="Y","WATCH — ANALYST SHIFT","Monitor Only")))),IF(K42="Y","DUE — INSIDER ACTIVITY",IF(I42<>"",IF(ABS(I42)>=0.15,"WATCH — PRICE MOVE ±15%",IF(M42="Y","WATCH — ANALYST SHIFT","Monitor Only")),IF(M42="Y","WATCH — ANALYST SHIFT","Monitor Only")))))))

Sheet Price History
A1: Weekly closing price ($), week-ending Friday (Rule 36: weekly total returns, 24-month target, 12-month minimum, 36-month max). Enter ticker in row 2 header, prices below. Blue = input.
A2: Week Ending | B2: ADBE | C2: ANET | D2: ASML | E2: AVGO | F2: CRWD | G2: KLAC | H2: MU | I2: NVDA | J2: PLD | K2: PLTR | L2: TSM | M2: VRT | N2: VRTX | O2: Ticker 14 | P2: Ticker 15 | Q2: Ticker 16
A3: 45149 | B3: 508.45 | C3: 43.74 | D3: 661.78 | E3: 82.98 | F3: 37.06 | G3: 47.9 | H3: 64.37 | I3: 40.85 | J3: 123.51 | K3: 15.41 | L3: 91.99 | M3: 33.51 | N3: 349.86
A4: 45156 | B4: 508.13 | C4: 45.14 | D4: 655.33 | E4: 82.58 | F4: 36.7 | G4: 47.8 | H4: 63.59 | I4: 43.3 | J4: 121.47 | K4: 14.4 | L4: 91.1 | M4: 33.97 | N4: 344.82
A5: 45163 | B5: 525.06 | C5: 45.23 | D5: 651.01 | E5: 85.18 | F5: 37.4 | G5: 48.17 | H5: 63.72 | I5: 46.02 | J5: 122.66 | K5: 14.53 | L5: 93.1 | M5: 37.5 | N5: 350.06
A6: 45170 | B6: 563.21 | C6: 49.34 | D6: 662.52 | E6: 87.25 | F6: 40.31 | G6: 50.7 | H6: 70.39 | I6: 48.51 | J6: 124.59 | K6: 15.18 | L6: 93.19 | M6: 39.87 | N6: 351.1
A7: 45177 | B7: 560.36 | C7: 49.12 | D7: 627.86 | E7: 85.76 | F7: 42.02 | G7: 49.77 | H7: 70.18 | I7: 45.57 | J7: 122.48 | K7: 15.13 | L7: 89.64 | M7: 39.2 | N7: 343.05
A8: 45184 | B8: 528.89 | C8: 46.18 | D8: 596.66 | E8: 85.17 | F8: 41.36 | G8: 45.42 | H8: 69.88 | I8: 43.9 | J8: 123.18 | K8: 15.33 | L8: 89.25 | M8: 38.17 | N8: 348.9
A9: 45191 | B9: 512.9 | C9: 45.09 | D9: 587.1 | E9: 82.91 | F9: 40.64 | G9: 45.18 | H9: 68.88 | I9: 41.61 | J9: 114.07 | K9: 14.13 | L9: 85.64 | M9: 36.45 | N9: 349.53
A10: 45198 | B10: 509.9 | C10: 45.98 | D10: 588.66 | E10: 83.06 | F10: 41.85 | G10: 45.87 | H10: 68.03 | I10: 43.5 | J10: 112.21 | K10: 16 | L10: 86.9 | M10: 37.2 | N10: 347.74
A11: 45205 | B11: 526.68 | C11: 48.51 | D11: 597.36 | E11: 84.53 | F11: 44.17 | G11: 46.81 | H11: 69.96 | I11: 45.76 | J11: 108.91 | K11: 16.61 | L11: 89.29 | M11: 39.77 | N11: 360.62
A12: 45212 | B12: 548.76 | C12: 47.46 | D12: 599.75 | E12: 88.32 | F12: 46.43 | G12: 48.68 | H12: 69.21 | I12: 45.46 | J12: 109.65 | K12: 17.36 | L12: 90.46 | M12: 39.1 | N12: 371
A13: 45219 | B13: 540.96 | C13: 46.53 | D13: 580.1 | E13: 85.36 | F13: 44.69 | G13: 46.24 | H13: 67.22 | I13: 41.39 | J13: 102.43 | K13: 16.11 | L13: 91.31 | M13: 36.74 | N13: 361.86
A14: 45226 | B14: 508.12 | C14: 44.05 | D14: 590 | E14: 83.84 | F14: 43.21 | G14: 45.79 | H14: 65.65 | I14: 40.5 | J14: 97.32 | K14: 15.07 | L14: 85.99 | M14: 36.42 | N14: 355.28
... A158: 46234 | B158: 250.41 | C158: 180.35 | D158: 1629 | E158: 389.28 | F158: 190.86 | G158: 182.82 | H158: 823.03 | I158: 200.75 | J158: 144.61 | K158: 123.06 | L158: 404.25 | M158: 241.57 | N158: 477.1

Sheet Dashboard
A1: Ticker | B1: Company | C1: Date Scored | D1: Tier 1 Wtd Avg | E1: Composite Score | F1: Decision | G1: Rule 1 | H1: Rule 2 | I1: Rule 3 | J1: Rule 4
A2: =IF(Scoring!A3="","",Scoring!A3) -> MU | B2: =IF(Scoring!B3="","",Scoring!B3) -> Micron Technology | C2: =IF(Scoring!C3="","",Scoring!C3) -> 46240 | D2: =IF(Scoring!N3="","",Scoring!N3) -> 3.6428571 | E2: =IF(Scoring!AF3="","",Scoring!AF3) -> 71.8 | F2: =IF(Scoring!AG3="","",Scoring!AG3) -> BUY | G2: =IF(Scoring!AH3="","",Scoring!AH3) -> OK | H2: =IF(Scoring!AI3="","",Scoring!AI3) -> OK | I2: =IF(Scoring!AJ3="","",Scoring!AJ3) -> OK | J2: =IF(Scoring!AK3="","",Scoring!AK3) -> OK
A3: =IF(Scoring!A4="","",Scoring!A4) -> AVGO | B3: =IF(Scoring!B4="","",Scoring!B4) -> Broadcom Inc. | C3: =IF(Scoring!C4="","",Scoring!C4) -> 46240 | D3: =IF(Scoring!N4="","",Scoring!N4) -> 4.0714286 | E3: =IF(Scoring!AF4="","",Scoring!AF4) -> 80.8 | F3: =IF(Scoring!AG4="","",Scoring!AG4) -> STRONG BUY | G3: =IF(Scoring!AH4="","",Scoring!AH4) -> OK | H3: =IF(Scoring!AI4="","",Scoring!AI4) -> OK | I3: =IF(Scoring!AJ4="","",Scoring!AJ4) -> OK | J3: =IF(Scoring!AK4="","",Scoring!AK4) -> OK
A4: =IF(Scoring!A5="","",Scoring!A5) -> PLTR | B4: =IF(Scoring!B5="","",Scoring!B5) -> Palantir Technologies | C4: =IF(Scoring!C5="","",Scoring!C5) -> 46240 | D4: =IF(Scoring!N5="","",Scoring!N5) -> 4 | E4: =IF(Scoring!AF5="","",Scoring!AF5) -> 75.2 | F4: =IF(Scoring!AG5="","",Scoring!AG5) -> BUY | G4: =IF(Scoring!AH5="","",Scoring!AH5) -> OK | H4: =IF(Scoring!AI5="","",Scoring!AI5) -> OK | I4: =IF(Scoring!AJ5="","",Scoring!AJ5) -> OK | J4: =IF(Scoring!AK5="","",Scoring!AK5) -> OK
A5: =IF(Scoring!A6="","",Scoring!A6) -> NVDA | B5: =IF(Scoring!B6="","",Scoring!B6) -> NVIDIA Corporation | C5: =IF(Scoring!C6="","",Scoring!C6) -> 46240 | D5: =IF(Scoring!N6="","",Scoring!N6) -> 4.5714286 | E5: =IF(Scoring!AF6="","",Scoring!AF6) -> 93.2 | F5: =IF(Scoring!AG6="","",Scoring!AG6) -> STRONG BUY | G5: =IF(Scoring!AH6="","",Scoring!AH6) -> OK | H5: =IF(Scoring!AI6="","",Scoring!AI6) -> OK | I5: =IF(Scoring!AJ6="","",Scoring!AJ6) -> OK | J5: =IF(Scoring!AK6="","",Scoring!AK6) -> OK
A6: =IF(Scoring!A7="","",Scoring!A7) -> VRTX | B6: =IF(Scoring!B7="","",Scoring!B7) -> Vertex Pharmaceuticals | C6: =IF(Scoring!C7="","",Scoring!C7) -> 46241 | D6: =IF(Scoring!N7="","",Scoring!N7) -> 3.7857143 | E6: =IF(Scoring!AF7="","",Scoring!AF7) -> 75.6 | F6: =IF(Scoring!AG7="","",Scoring!AG7) -> BUY | G6: =IF(Scoring!AH7="","",Scoring!AH7) -> OK | H6: =IF(Scoring!AI7="","",Scoring!AI7) -> OK | I6: =IF(Scoring!AJ7="","",Scoring!AJ7) -> OK | J6: =IF(Scoring!AK7="","",Scoring!AK7) -> OK
A7: =IF(Scoring!A8="","",Scoring!A8) -> PLD | B7: =IF(Scoring!B8="","",Scoring!B8) -> Prologis Inc. (REIT-adapted) | C7: =IF(Scoring!C8="","",Scoring!C8) -> 46240 | D7: =IF(Scoring!N8="","",Scoring!N8) -> 4.3571429 | E7: =IF(Scoring!AF8="","",Scoring!AF8) -> 82 | F7: =IF(Scoring!AG8="","",Scoring!AG8) -> STRONG BUY | G7: =IF(Scoring!AH8="","",Scoring!AH8) -> OK | H7: =IF(Scoring!AI8="","",Scoring!AI8) -> OK | I7: =IF(Scoring!AJ8="","",Scoring!AJ8) -> OK | J7: =IF(Scoring!AK8="","",Scoring!AK8) -> OK
A8: =IF(Scoring!A9="","",Scoring!A9) -> SFM | B8: =IF(Scoring!B9="","",Scoring!B9) -> Sprouts Farmers Market | C8: =IF(Scoring!C9="","",Scoring!C9) -> 46240 | D8: =IF(Scoring!N9="","",Scoring!N9) -> 1.8571429 | E8: =IF(Scoring!AF9="","",Scoring!AF9) | F8: =IF(Scoring!AG9="","",Scoring!AG9) | G8: =IF(Scoring!AH9="","",Scoring!AH9) -> FAIL | H8: =IF(Scoring!AI9="","",Scoring!AI9) -> REVIEW | I8: =IF(Scoring!AJ9="","",Scoring!AJ9) -> AVOID | J8: =IF(Scoring!AK9="","",Scoring!AK9) -> OK
A9: =IF(Scoring!A10="","",Scoring!A10) -> ONON | B9: =IF(Scoring!B10="","",Scoring!B10) -> On Holding AG | C9: =IF(Scoring!C10="","",Scoring!C10) -> 46240 | D9: =IF(Scoring!N10="","",Scoring!N10) -> 2.6428571 | E9: =IF(Scoring!AF10="","",Scoring!AF10) | F9: =IF(Scoring!AG10="","",Scoring!AG10) | G9: =IF(Scoring!AH10="","",Scoring!AH10) -> FAIL | H9: =IF(Scoring!AI10="","",Scoring!AI10) -> OK | I9: =IF(Scoring!AJ10="","",Scoring!AJ10) -> AVOID | J9: =IF(Scoring!AK10="","",Scoring!AK10) -> OK
A10: =IF(Scoring!A11="","",Scoring!A11) -> TSLA | B10: =IF(Scoring!B11="","",Scoring!B11) -> Tesla Inc. | C10: =IF(Scoring!C11="","",Scoring!C11) -> 46240 | D10: =IF(Scoring!N11="","",Scoring!N11) -> 1.9285714 | E10: =IF(Scoring!AF11="","",Scoring!AF11) | F10: =IF(Scoring!AG11="","",Scoring!AG11) | G10: =IF(Scoring!AH11="","",Scoring!AH11) -> FAIL | H10: =IF(Scoring!AI11="","",Scoring!AI11) -> REVIEW | I10: =IF(Scoring!AJ11="","",Scoring!AJ11) -> AVOID | J10: =IF(Scoring!AK11="","",Scoring!AK11) -> OK
A11: =IF(Scoring!A12="","",Scoring!A12) -> ADBE | B11: =IF(Scoring!B12="","",Scoring!B12) -> Adobe Inc. | C11: =IF(Scoring!C12="","",Scoring!C12) -> 46240 | D11: =IF(Scoring!N12="","",Scoring!N12) -> 4.5714286 | E11: =IF(Scoring!AF12="","",Scoring!AF12) -> 85.8 | F11: =IF(Scoring!AG12="","",Scoring!AG12) -> STRONG BUY | G11: =IF(Scoring!AH12="","",Scoring!AH12) -> OK | H11: =IF(Scoring!AI12="","",Scoring!AI12) -> OK | I11: =IF(Scoring!AJ12="","",Scoring!AJ12) -> OK | J11: =IF(Scoring!AK12="","",Scoring!AK12) -> OK
A12: =IF(Scoring!A13="","",Scoring!A13) -> ANET | B12: =IF(Scoring!B13="","",Scoring!B13) -> Arista Networks | C12: =IF(Scoring!C13="","",Scoring!C13) -> 46240 | D12: =IF(Scoring!N13="","",Scoring!N13) -> 4.5714286 | E12: =IF(Scoring!AF13="","",Scoring!AF13) -> 85 | F12: =IF(Scoring!AG13="","",Scoring!AG13) -> STRONG BUY | G12: =IF(Scoring!AH13="","",Scoring!AH13) -> OK | H12: =IF(Scoring!AI13="","",Scoring!AI13) -> OK | I12: =IF(Scoring!AJ13="","",Scoring!AJ13) -> OK | J12: =IF(Scoring!AK13="","",Scoring!AK13) -> OK
A13: =IF(Scoring!A14="","",Scoring!A14) -> ASML | B13: =IF(Scoring!B14="","",Scoring!B14) -> ASML Holding | C13: =IF(Scoring!C14="","",Scoring!C14) -> 46240 | D13: =IF(Scoring!N14="","",Scoring!N14) -> 3.5714286 | E13: =IF(Scoring!AF14="","",Scoring!AF14) -> 73.2 | F13: =IF(Scoring!AG14="","",Scoring!AG14) -> BUY | G13: =IF(Scoring!AH14="","",Scoring!AH14) -> OK | H13: =IF(Scoring!AI14="","",Scoring!AI14) -> OK | I13: =IF(Scoring!AJ14="","",Scoring!AJ14) -> OK | J13: =IF(Scoring!AK14="","",Scoring!AK14) -> OK
... A26: =IF(Scoring!A27="","",Scoring!A27) | B26: =IF(Scoring!B27="","",Scoring!B27) | C26: =IF(Scoring!C27="","",Scoring!C27) | D26: =IF(Scoring!N27="","",Scoring!N27) | E26: =IF(Scoring!AF27="","",Scoring!AF27) | F26: =IF(Scoring!AG27="","",Scoring!AG27) | G26: =IF(Scoring!AH27="","",Scoring!AH27) | H26: =IF(Scoring!AI27="","",Scoring!AI27) | I26: =IF(Scoring!AJ27="","",Scoring!AJ27) | J26: =IF(Scoring!AK27="","",Scoring!AK27)
A28: This tab mirrors the Scoring tab automatically — do not type here. You can sort this tab directly (Data > Sort by Composite Score); Excel moves whole rows, so each row's links stay correct.

Sheet Scoring
D1: TIER 1 — 70% of Decision | P1: TIER 2 — 25% of Decision | Y1: TIER 3 — 5% of Decision | AH1: RULE FLAGS (1–4)
A2: Ticker | B2: Company | C2: Date Scored | D2: FCF Yield & Trend (20%) Score | E2: Conf (H/M/L) | F2: Rev Growth Consist. (15%) Score | G2: Conf (H/M/L) | H2: Moat Quality (15%) Score | I2: Conf (H/M/L) | J2: Rev Visibility (10%) Score | K2: Conf (H/M/L) | L2: FCF Margin Trend (10%) Score | M2: Conf (H/M/L) | N2: Tier 1 Wtd Avg (÷0.70) | O2: Tier 1 Contrib. | P2: Mgmt Quality & Cap Alloc (8%) Score | Q2: Conf (H/M/L) | R2: ROIC vs WACC (6%) Score | S2: Conf (H/M/L) | T2: Rel Strength vs SPY (3%) Score | U2: Conf (H/M/L) | V2: Valuation Multiples (8%) Score | W2: Conf (H/M/L) | X2: Tier 2 Contrib. | Y2: Technical Trend (2%) Score | Z2: Conf (H/M/L) | AA2: Analyst Consensus (2%) Score | AB2: Conf (H/M/L) | AC2: Volume & Accum. (1%) Score | AD2: Conf (H/M/L) | AE2: Tier 3 Contrib. | AF2: Composite Score | AG2: Decision | AH2: Rule 1 Tier1<3.0 | AI2: Rule 2 Any=1 | AJ2: Rule 3 2+≤2=Avoid | AK2: Rule 4 2+Low=Cap Buy
A3: MU | B3: Micron Technology | C3: 46240 | D3: 3 | E3: M | F3: 3 | G3: M | H3: 4 | I3: H | J3: 5 | K3: H | L3: 4 | M3: M | N3: =IF(COUNT(D3,F3,H3,J3,L3)=0,"",(D3*0.2+F3*0.15+H3*0.15+J3*0.1+L3*0.1)/0.7) -> 3.6428571 | O3: =IF(COUNT(D3,F3,H3,J3,L3)=0,"",D3*0.2+F3*0.15+H3*0.15+J3*0.1+L3*0.1) -> 2.55 | P3: 4 | Q3: M | R3: 5 | S3: M | T3: 5 | U3: H | V3: 1 | W3: H | X3: =IF(COUNT(P3,R3,T3,V3)=0,"",P3*0.08+R3*0.06+T3*0.03+V3*0.08) -> 0.85 | Y3: 5 | Z3: H | AA3: 3 | AB3: M | AC3: 3 | AD3: L | AE3: =IF(COUNT(Y3,AA3,AC3)=0,"",Y3*0.02+AA3*0.02+AC3*0.01) -> 0.19 | AF3: =IF(OR(O3="",X3="",AE3=""),"",(O3+X3+AE3)*20) -> 71.8 | AG3: =IF(AF3="","",IF(AF3>=80,"STRONG BUY",IF(AF3>=65,"BUY",IF(AF3>=50,"WATCH LIST",IF(AF3>=35,"AVOID","PASS"))))) -> BUY | AH3: =IF(N3="","",IF(N3<3,"FAIL","OK")) -> OK | AI3: =IF(COUNT(D3:L3)=0,"",IF(COUNTIF(D3:L3,1)>0,"REVIEW","OK")) -> OK | AJ3: =IF(COUNT(D3:L3)=0,"",IF(COUNTIF(D3:L3,"<=2")>=2,"AVOID","OK")) -> OK | AK3: =IF(COUNTA(E3:M3)=0,"",IF(COUNTIF(E3:M3,"L")>=2,"CAP AT BUY","OK")) -> OK
A4: AVGO | B4: Broadcom Inc. | C4: 46240 | D4: 3 | E4: M | F4: 4 | G4: H | H4: 5 | I4: H | J4: 4 | K4: M | L4: 5 | M4: H | N4: =IF(COUNT(D4,F4,H4,J4,L4)=0,"",(D4*0.2+F4*0.15+H4*0.15+J4*0.1+L4*0.1)/0.7) -> 4.0714286 | O4: =IF(COUNT(D4,F4,H4,J4,L4)=0,"",D4*0.2+F4*0.15+H4*0.15+J4*0.1+L4*0.1) -> 2.85 | P4: 4 | Q4: H | R4: 4 | S4: L | T4: 4 | U4: M | V4: 4 | W4: M | X4: =IF(COUNT(P4,R4,T4,V4)=0,"",P4*0.08+R4*0.06+T4*0.03+V4*0.08) -> 1 | Y4: 3 | Z4: M | AA4: 5 | AB4: H | AC4: 3 | AD4: M | AE4: =IF(COUNT(Y4,AA4,AC4)=0,"",Y4*0.02+AA4*0.02+AC4*0.01) -> 0.19 | AF4: =IF(OR(O4="",X4="",AE4=""),"",(O4+X4+AE4)*20) -> 80.8 | AG4: =IF(AF4="","",IF(AF4>=80,"STRONG BUY",IF(AF4>=65,"BUY",IF(AF4>=50,"WATCH LIST",IF(AF4>=35,"AVOID","PASS"))))) -> STRONG BUY | AH4: =IF(N4="","",IF(N4<3,"FAIL","OK")) -> OK | AI4: =IF(COUNT(D4:L4)=0,"",IF(COUNTIF(D4:L4,1)>0,"REVIEW","OK")) -> OK | AJ4: =IF(COUNT(D4:L4)=0,"",IF(COUNTIF(D4:L4,"<=2")>=2,"AVOID","OK")) -> OK | AK4: =IF(COUNTA(E4:M4)=0,"",IF(COUNTIF(E4:M4,"L")>=2,"CAP AT BUY","OK")) -> OK
A5: PLTR | B5: Palantir Technologies | C5: 46240 | D5: 2 | E5: H | F5: 5 | G5: H | H5: 5 | I5: M | J5: 4 | K5: M | L5: 5 | M5: H | N5: =IF(COUNT(D5,F5,H5,J5,L5)=0,"",(D5*0.2+F5*0.15+H5*0.15+J5*0.1+L5*0.1)/0.7) -> 4 | O5: =IF(COUNT(D5,F5,H5,J5,L5)=0,"",D5*0.2+F5*0.15+H5*0.15+J5*0.1+L5*0.1) -> 2.8 | P5: 3 | Q5: M | R5: 5 | S5: H | T5: 3 | U5: M | V5: 2 | W5: M | X5: =IF(COUNT(P5,R5,T5,V5)=0,"",P5*0.08+R5*0.06+T5*0.03+V5*0.08) -> 0.79 | Y5: 3 | Z5: L | AA5: 4 | AB5: M | AC5: 3 | AD5: L | AE5: =IF(COUNT(Y5,AA5,AC5)=0,"",Y5*0.02+AA5*0.02+AC5*0.01) -> 0.17 | AF5: =IF(OR(O5="",X5="",AE5=""),"",(O5+X5+AE5)*20) -> 75.2 | AG5: =IF(AF5="","",IF(AF5>=80,"STRONG BUY",IF(AF5>=65,"BUY",IF(AF5>=50,"WATCH LIST",IF(AF5>=35,"AVOID","PASS"))))) -> BUY | AH5: =IF(N5="","",IF(N5<3,"FAIL","OK")) -> OK | AI5: =IF(COUNT(D5:L5)=0,"",IF(COUNTIF(D5:L5,1)>0,"REVIEW","OK")) -> OK | AJ5: =IF(COUNT(D5:L5)=0,"",IF(COUNTIF(D5:L5,"<=2")>=2,"AVOID","OK")) -> OK | AK5: =IF(COUNTA(E5:M5)=0,"",IF(COUNTIF(E5:M5,"L")>=2,"CAP AT BUY","OK")) -> OK
A6: NVDA | B6: NVIDIA Corporation | C6: 46240 | D6: 4 | E6: H | F6: 5 | G6: H | H6: 5 | I6: H | J6: 4 | K6: H | L6: 5 | M6: H | N6: =IF(COUNT(D6,F6,H6,J6,L6)=0,"",(D6*0.2+F6*0.15+H6*0.15+J6*0.1+L6*0.1)/0.7) -> 4.5714286 | O6: =IF(COUNT(D6,F6,H6,J6,L6)=0,"",D6*0.2+F6*0.15+H6*0.15+J6*0.1+L6*0.1) -> 3.2 | P6: 5 | Q6: H | R6: 5 | S6: H | T6: 5 | U6: H | V6: 5 | W6: M | X6: =IF(COUNT(P6,R6,T6,V6)=0,"",P6*0.08+R6*0.06+T6*0.03+V6*0.08) -> 1.25 | Y6: 4 | Z6: M | AA6: 5 | AB6: M | AC6: 3 | AD6: L | AE6: =IF(COUNT(Y6,AA6,AC6)=0,"",Y6*0.02+AA6*0.02+AC6*0.01) -> 0.21 | AF6: =IF(OR(O6="",X6="",AE6=""),"",(O6+X6+AE6)*20) -> 93.2 | AG6: =IF(AF6="","",IF(AF6>=80,"STRONG BUY",IF(AF6>=65,"BUY",IF(AF6>=50,"WATCH LIST",IF(AF6>=35,"AVOID","PASS"))))) -> STRONG BUY | AH6: =IF(N6="","",IF(N6<3,"FAIL","OK")) -> OK | AI6: =IF(COUNT(D6:L6)=0,"",IF(COUNTIF(D6:L6,1)>0,"REVIEW","OK")) -> OK | AJ6: =IF(COUNT(D6:L6)=0,"",IF(COUNTIF(D6:L6,"<=2")>=2,"AVOID","OK")) -> OK | AK6: =IF(COUNTA(E6:M6)=0,"",IF(COUNTIF(E6:M6,"L")>=2,"CAP AT BUY","OK")) -> OK
A7: VRTX | B7: Vertex Pharmaceuticals | C7: 46241 | D7: 4 | E7: H | F7: 3 | G7: M | H7: 4 | I7: M | J7: 4 | K7: M | L7: 4 | M7: H | N7: =IF(COUNT(D7,F7,H7,J7,L7)=0,"",(D7*0.2+F7*0.15+H7*0.15+J7*0.1+L7*0.1)/0.7) -> 3.7857143 | O7: =IF(COUNT(D7,F7,H7,J7,L7)=0,"",D7*0.2+F7*0.15+H7*0.15+J7*0.1+L7*0.1) -> 2.65 | P7: 3 | Q7: M | R7: 4 | S7: M | T7: 4 | U7: M | V7: 4 | W7: M | X7: =IF(COUNT(P7,R7,T7,V7)=0,"",P7*0.08+R7*0.06+T7*0.03+V7*0.08) -> 0.92 | Y7: 4 | Z7: M | AA7: 5 | AB7: H | AC7: 3 | AD7: L | AE7: =IF(COUNT(Y7,AA7,AC7)=0,"",Y7*0.02+AA7*0.02+AC7*0.01) -> 0.21 | AF7: =IF(OR(O7="",X7="",AE7=""),"",(O7+X7+AE7)*20) -> 75.6 | AG7: =IF(AF7="","",IF(AF7>=80,"STRONG BUY",IF(AF7>=65,"BUY",IF(AF7>=50,"WATCH LIST",IF(AF7>=35,"AVOID","PASS"))))) -> BUY | AH7: =IF(N7="","",IF(N7<3,"FAIL","OK")) -> OK | AI7: =IF(COUNT(D7:L7)=0,"",IF(COUNTIF(D7:L7,1)>0,"REVIEW","OK")) -> OK | AJ7: =IF(COUNT(D7:L7)=0,"",IF(COUNTIF(D7:L7,"<=2")>=2,"AVOID","OK")) -> OK | AK7: =IF(COUNTA(E7:M7)=0,"",IF(COUNTIF(E7:M7,"L")>=2,"CAP AT BUY","OK")) -> OK
A8: PLD | B8: Prologis Inc. (REIT-adapted) | C8: 46240 | D8: 4 | E8: M | F8: 4 | G8: M | H8: 5 | I8: H | J8: 4 | K8: M | L8: 5 | M8: H | N8: =IF(COUNT(D8,F8,H8,J8,L8)=0,"",(D8*0.2+F8*0.15+H8*0.15+J8*0.1+L8*0.1)/0.7) -> 4.3571429 | O8: =IF(COUNT(D8,F8,H8,J8,L8)=0,"",D8*0.2+F8*0.15+H8*0.15+J8*0.1+L8*0.1) -> 3.05 | P8: 5 | Q8: H | R8: 3 | S8: L | T8: 4 | U8: L | V8: 2 | W8: H | X8: =IF(COUNT(P8,R8,T8,V8)=0,"",P8*0.08+R8*0.06+T8*0.03+V8*0.08) -> 0.86 | Y8: 4 | Z8: L | AA8: 4 | AB8: M | AC8: 3 | AD8: L | AE8: =IF(COUNT(Y8,AA8,AC8)=0,"",Y8*0.02+AA8*0.02+AC8*0.01) -> 0.19 | AF8: =IF(OR(O8="",X8="",AE8=""),"",(O8+X8+AE8)*20) -> 82 | AG8: =IF(AF8="","",IF(AF8>=80,"STRONG BUY",IF(AF8>=65,"BUY",IF(AF8>=50,"WATCH LIST",IF(AF8>=35,"AVOID","PASS"))))) -> STRONG BUY | AH8: =IF(N8="","",IF(N8<3,"FAIL","OK")) -> OK | AI8: =IF(COUNT(D8:L8)=0,"",IF(COUNTIF(D8:L8,1)>0,"REVIEW","OK")) -> OK | AJ8: =IF(COUNT(D8:L8)=0,"",IF(COUNTIF(D8:L8,"<=2")>=2,"AVOID","OK")) -> OK | AK8: =IF(COUNTA(E8:M8)=0,"",IF(COUNTIF(E8:M8,"L")>=2,"CAP AT BUY","OK")) -> OK
A9: SFM | B9: Sprouts Farmers Market | C9: 46240 | D9: 2 | E9: M | F9: 2 | G9: M | H9: 2 | I9: M | J9: 2 | K9: M | L9: 1 | M9: H | N9: =IF(COUNT(D9,F9,H9,J9,L9)=0,"",(D9*0.2+F9*0.15+H9*0.15+J9*0.1+L9*0.1)/0.7) -> 1.8571429 | O9: =IF(COUNT(D9,F9,H9,J9,L9)=0,"",D9*0.2+F9*0.15+H9*0.15+J9*0.1+L9*0.1) -> 1.3 | X9: =IF(COUNT(P9,R9,T9,V9)=0,"",P9*0.08+R9*0.06+T9*0.03+V9*0.08) | AE9: =IF(COUNT(Y9,AA9,AC9)=0,"",Y9*0.02+AA9*0.02+AC9*0.01) | AF9: =IF(OR(O9="",X9="",AE9=""),"",(O9+X9+AE9)*20) | AG9: =IF(AF9="","",IF(AF9>=80,"STRONG BUY",IF(AF9>=65,"BUY",IF(AF9>=50,"WATCH LIST",IF(AF9>=35,"AVOID","PASS"))))) | AH9: =IF(N9="","",IF(N9<3,"FAIL","OK")) -> FAIL | AI9: =IF(COUNT(D9:L9)=0,"",IF(COUNTIF(D9:L9,1)>0,"REVIEW","OK")) -> REVIEW | AJ9: =IF(COUNT(D9:L9)=0,"",IF(COUNTIF(D9:L9,"<=2")>=2,"AVOID","OK")) -> AVOID | AK9: =IF(COUNTA(E9:M9)=0,"",IF(COUNTIF(E9:M9,"L")>=2,"CAP AT BUY","OK")) -> OK
A10: ONON | B10: On Holding AG | C10: 46240 | D10: 2 | E10: M | F10: 4 | G10: H | H10: 3 | I10: M | J10: 2 | K10: M | L10: 2 | M10: H | N10: =IF(COUNT(D10,F10,H10,J10,L10)=0,"",(D10*0.2+F10*0.15+H10*0.15+J10*0.1+L10*0.1)/0.7) -> 2.6428571 | O10: =IF(COUNT(D10,F10,H10,J10,L10)=0,"",D10*0.2+F10*0.15+H10*0.15+J10*0.1+L10*0.1) -> 1.85 | X10: =IF(COUNT(P10,R10,T10,V10)=0,"",P10*0.08+R10*0.06+T10*0.03+V10*0.08) | AE10: =IF(COUNT(Y10,AA10,AC10)=0,"",Y10*0.02+AA10*0.02+AC10*0.01) | AF10: =IF(OR(O10="",X10="",AE10=""),"",(O10+X10+AE10)*20) | AG10: =IF(AF10="","",IF(AF10>=80,"STRONG BUY",IF(AF10>=65,"BUY",IF(AF10>=50,"WATCH LIST",IF(AF10>=35,"AVOID","PASS"))))) | AH10: =IF(N10="","",IF(N10<3,"FAIL","OK")) -> FAIL | AI10: =IF(COUNT(D10:L10)=0,"",IF(COUNTIF(D10:L10,1)>0,"REVIEW","OK")) -> OK | AJ10: =IF(COUNT(D10:L10)=0,"",IF(COUNTIF(D10:L10,"<=2")>=2,"AVOID","OK")) -> AVOID | AK10: =IF(COUNTA(E10:M10)=0,"",IF(COUNTIF(E10:M10,"L")>=2,"CAP AT BUY","OK")) -> OK
A11: TSLA | B11: Tesla Inc. | C11: 46240 | D11: 1 | E11: H | F11: 2 | G11: M | H11: 3 | I11: M | J11: 3 | K11: M | L11: 1 | M11: H | N11: =IF(COUNT(D11,F11,H11,J11,L11)=0,"",(D11*0.2+F11*0.15+H11*0.15+J11*0.1+L11*0.1)/0.7) -> 1.9285714 | O11: =IF(COUNT(D11,F11,H11,J11,L11)=0,"",D11*0.2+F11*0.15+H11*0.15+J11*0.1+L11*0.1) -> 1.35 | X11: =IF(COUNT(P11,R11,T11,V11)=0,"",P11*0.08+R11*0.06+T11*0.03+V11*0.08) | AE11: =IF(COUNT(Y11,AA11,AC11)=0,"",Y11*0.02+AA11*0.02+AC11*0.01) | AF11: =IF(OR(O11="",X11="",AE11=""),"",(O11+X11+AE11)*20) | AG11: =IF(AF11="","",IF(AF11>=80,"STRONG BUY",IF(AF11>=65,"BUY",IF(AF11>=50,"WATCH LIST",IF(AF11>=35,"AVOID","PASS"))))) | AH11: =IF(N11="","",IF(N11<3,"FAIL","OK")) -> FAIL | AI11: =IF(COUNT(D11:L11)=0,"",IF(COUNTIF(D11:L11,1)>0,"REVIEW","OK")) -> REVIEW | AJ11: =IF(COUNT(D11:L11)=0,"",IF(COUNTIF(D11:L11,"<=2")>=2,"AVOID","OK")) -> AVOID | AK11: =IF(COUNTA(E11:M11)=0,"",IF(COUNTIF(E11:M11,"L")>=2,"CAP AT BUY","OK")) -> OK
A12: ADBE | B12: Adobe Inc. | C12: 46240 | D12: 5 | E12: H | F12: 4 | G12: H | H12: 4 | I12: M | J12: 5 | K12: H | L12: 5 | M12: H | N12: =IF(COUNT(D12,F12,H12,J12,L12)=0,"",(D12*0.2+F12*0.15+H12*0.15+J12*0.1+L12*0.1)/0.7) -> 4.5714286 | O12: =IF(COUNT(D12,F12,H12,J12,L12)=0,"",D12*0.2+F12*0.15+H12*0.15+J12*0.1+L12*0.1) -> 3.2 | P12: 3 | Q12: M | R12: 5 | S12: H | T12: 1 | U12: H | V12: 5 | W12: H | X12: =IF(COUNT(P12,R12,T12,V12)=0,"",P12*0.08+R12*0.06+T12*0.03+V12*0.08) -> 0.97 | Y12: 2 | Z12: M | AA12: 3 | AB12: M | AC12: 2 | AD12: L | AE12: =IF(COUNT(Y12,AA12,AC12)=0,"",Y12*0.02+AA12*0.02+AC12*0.01) -> 0.12 | AF12: =IF(OR(O12="",X12="",AE12=""),"",(O12+X12+AE12)*20) -> 85.8 | AG12: =IF(AF12="","",IF(AF12>=80,"STRONG BUY",IF(AF12>=65,"BUY",IF(AF12>=50,"WATCH LIST",IF(AF12>=35,"AVOID","PASS"))))) -> STRONG BUY | AH12: =IF(N12="","",IF(N12<3,"FAIL","OK")) -> OK | AI12: =IF(COUNT(D12:L12)=0,"",IF(COUNTIF(D12:L12,1)>0,"REVIEW","OK")) -> OK | AJ12: =IF(COUNT(D12:L12)=0,"",IF(COUNTIF(D12:L12,"<=2")>=2,"AVOID","OK")) -> OK | AK12: =IF(COUNTA(E12:M12)=0,"",IF(COUNTIF(E12:M12,"L")>=2,"CAP AT BUY","OK")) -> OK
A13: ANET | B13: Arista Networks | C13: 46240 | D13: 4 | E13: M | F13: 5 | G13: H | H13: 5 | I13: H | J13: 4 | K13: M | L13: 5 | M13: H | N13: =IF(COUNT(D13,F13,H13,J13,L13)=0,"",(D13*0.2+F13*0.15+H13*0.15+J13*0.1+L13*0.1)/0.7) -> 4.5714286 | O13: =IF(COUNT(D13,F13,H13,J13,L13)=0,"",D13*0.2+F13*0.15+H13*0.15+J13*0.1+L13*0.1) -> 3.2 | P13: 4 | Q13: H | R13: 5 | S13: H | T13: 5 | U13: M | V13: 1 | W13: H | X13: =IF(COUNT(P13,R13,T13,V13)=0,"",P13*0.08+R13*0.06+T13*0.03+V13*0.08) -> 0.85 | Y13: 4 | Z13: M | AA13: 5 | AB13: H | AC13: 2 | AD13: M | AE13: =IF(COUNT(Y13,AA13,AC13)=0,"",Y13*0.02+AA13*0.02+AC13*0.01) -> 0.2 | AF13: =IF(OR(O13="",X13="",AE13=""),"",(O13+X13+AE13)*20) -> 85 | AG13: =IF(AF13="","",IF(AF13>=80,"STRONG BUY",IF(AF13>=65,"BUY",IF(AF13>=50,"WATCH LIST",IF(AF13>=35,"AVOID","PASS"))))) -> STRONG BUY | AH13: =IF(N13="","",IF(N13<3,"FAIL","OK")) -> OK | AI13: =IF(COUNT(D13:L13)=0,"",IF(COUNTIF(D13:L13,1)>0,"REVIEW","OK")) -> OK | AJ13: =IF(COUNT(D13:L13)=0,"",IF(COUNTIF(D13:L13,"<=2")>=2,"AVOID","OK")) -> OK | AK13: =IF(COUNTA(E13:M13)=0,"",IF(COUNTIF(E13:M13,"L")>=2,"CAP AT BUY","OK")) -> OK
A14: ASML | B14: ASML Holding | C14: 46240 | D14: 3 | E14: M | F14: 3 | G14: M | H14: 5 | I14: H | J14: 4 | K14: M | L14: 3 | M14: M | N14: =IF(COUNT(D14,F14,H14,J14,L14)=0,"",(D14*0.2+F14*0.15+H14*0.15+J14*0.1+L14*0.1)/0.7) -> 3.5714286 | O14: =IF(COUNT(D14,F14,H14,J14,L14)=0,"",D14*0.2+F14*0.15+H14*0.15+J14*0.1+L14*0.1) -> 2.5 | P14: 4 | Q14: M | R14: 5 | S14: H | T14: 5 | U14: H | V14: 2 | W14: M | X14: =IF(COUNT(P14,R14,T14,V14)=0,"",P14*0.08+R14*0.06+T14*0.03+V14*0.08) -> 0.93 | Y14: 5 | Z14: M | AA14: 5 | AB14: H | AC14: 3 | AD14: L | AE14: =IF(COUNT(Y14,AA14,AC14)=0,"",Y14*0.02+AA14*0.02+AC14*0.01) -> 0.23 | AF14: =IF(OR(O14="",X14="",AE14=""),"",(O14+X14+AE14)*20) -> 73.2 | AG14: =IF(AF14="","",IF(AF14>=80,"STRONG BUY",IF(AF14>=65,"BUY",IF(AF14>=50,"WATCH LIST",IF(AF14>=35,"AVOID","PASS"))))) -> BUY | AH14: =IF(N14="","",IF(N14<3,"FAIL","OK")) -> OK | AI14: =IF(COUNT(D14:L14)=0,"",IF(COUNTIF(D14:L14,1)>0,"REVIEW","OK")) -> OK | AJ14: =IF(COUNT(D14:L14)=0,"",IF(COUNTIF(D14:L14,"<=2")>=2,"AVOID","OK")) -> OK | AK14: =IF(COUNTA(E14:M14)=0,"",IF(COUNTIF(E14:M14,"L")>=2,"CAP AT BUY","OK")) -> OK
A15: CRWD | B15: CrowdStrike Holdings | C15: 46240 | D15: 3 | E15: M | F15: 4 | G15: M | H15: 4 | I15: M | J15: 5 | K15: H | L15: 5 | M15: H | N15: =IF(COUNT(D15,F15,H15,J15,L15)=0,"",(D15*0.2+F15*0.15+H15*0.15+J15*0.1+L15*0.1)/0.7) -> 4 | O15: =IF(COUNT(D15,F15,H15,J15,L15)=0,"",D15*0.2+F15*0.15+H15*0.15+J15*0.1+L15*0.1) -> 2.8 | P15: 3 | Q15: M | R15: 2 | S15: M | T15: 4 | U15: H | V15: 1 | W15: H | X15: =IF(COUNT(P15,R15,T15,V15)=0,"",P15*0.08+R15*0.06+T15*0.03+V15*0.08) -> 0.56 | Y15: 4 | Z15: M | AA15: 3 | AB15: M | AC15: 2 | AD15: M | AE15: =IF(COUNT(Y15,AA15,AC15)=0,"",Y15*0.02+AA15*0.02+AC15*0.01) -> 0.16 | AF15: =IF(OR(O15="",X15="",AE15=""),"",(O15+X15+AE15)*20) -> 70.4 | AG15: =IF(AF15="","",IF(AF15>=80,"STRONG BUY",IF(AF15>=65,"BUY",IF(AF15>=50,"WATCH LIST",IF(AF15>=35,"AVOID","PASS"))))) -> BUY | AH15: =IF(N15="","",IF(N15<3,"FAIL","OK")) -> OK | AI15: =IF(COUNT(D15:L15)=0,"",IF(COUNTIF(D15:L15,1)>0,"REVIEW","OK")) -> OK | AJ15: =IF(COUNT(D15:L15)=0,"",IF(COUNTIF(D15:L15,"<=2")>=2,"AVOID","OK")) -> OK | AK15: =IF(COUNTA(E15:M15)=0,"",IF(COUNTIF(E15:M15,"L")>=2,"CAP AT BUY","OK")) -> OK
A16: KLAC | B16: KLA Corporation | C16: 46240 | D16: 2 | E16: M | F16: 3 | G16: M | H16: 5 | I16: H | J16: 3 | K16: M | L16: 5 | M16: H | N16: =IF(COUNT(D16,F16,H16,J16,L16)=0,"",(D16*0.2+F16*0.15+H16*0.15+J16*0.1+L16*0.1)/0.7) -> 3.4285714 | O16: =IF(COUNT(D16,F16,H16,J16,L16)=0,"",D16*0.2+F16*0.15+H16*0.15+J16*0.1+L16*0.1) -> 2.4 | P16: 4 | Q16: H | R16: 5 | S16: H | T16: 3 | U16: M | V16: 2 | W16: M | X16: =IF(COUNT(P16,R16,T16,V16)=0,"",P16*0.08+R16*0.06+T16*0.03+V16*0.08) -> 0.87 | Y16: 2 | Z16: M | AA16: 5 | AB16: H | AC16: 2 | AD16: L | AE16: =IF(COUNT(Y16,AA16,AC16)=0,"",Y16*0.02+AA16*0.02+AC16*0.01) -> 0.16 | AF16: =IF(OR(O16="",X16="",AE16=""),"",(O16+X16+AE16)*20) -> 68.6 | AG16: =IF(AF16="","",IF(AF16>=80,"STRONG BUY",IF(AF16>=65,"BUY",IF(AF16>=50,"WATCH LIST",IF(AF16>=35,"AVOID","PASS"))))) -> BUY | AH16: =IF(N16="","",IF(N16<3,"FAIL","OK")) -> OK | AI16: =IF(COUNT(D16:L16)=0,"",IF(COUNTIF(D16:L16,1)>0,"REVIEW","OK")) -> OK | AJ16: =IF(COUNT(D16:L16)=0,"",IF(COUNTIF(D16:L16,"<=2")>=2,"AVOID","OK")) -> OK | AK16: =IF(COUNTA(E16:M16)=0,"",IF(COUNTIF(E16:M16,"L")>=2,"CAP AT BUY","OK")) -> OK
A17: TSM | B17: Taiwan Semiconductor Mfg. | C17: 46240 | D17: 3 | E17: M | F17: 5 | G17: H | H17: 5 | I17: H | J17: 4 | K17: M | L17: 3 | M17: M | N17: =IF(COUNT(D17,F17,H17,J17,L17)=0,"",(D17*0.2+F17*0.15+H17*0.15+J17*0.1+L17*0.1)/0.7) -> 4 | O17: =IF(COUNT(D17,F17,H17,J17,L17)=0,"",D17*0.2+F17*0.15+H17*0.15+J17*0.1+L17*0.1) -> 2.8 | P17: 4 | Q17: H | R17: 5 | S17: H | T17: 4 | U17: M | V17: 4 | W17: M | X17: =IF(COUNT(P17,R17,T17,V17)=0,"",P17*0.08+R17*0.06+T17*0.03+V17*0.08) -> 1.06 | Y17: 3 | Z17: M | AA17: 5 | AB17: H | AC17: 3 | AD17: L | AE17: =IF(COUNT(Y17,AA17,AC17)=0,"",Y17*0.02+AA17*0.02+AC17*0.01) -> 0.19 | AF17: =IF(OR(O17="",X17="",AE17=""),"",(O17+X17+AE17)*20) -> 81 | AG17: =IF(AF17="","",IF(AF17>=80,"STRONG BUY",IF(AF17>=65,"BUY",IF(AF17>=50,"WATCH LIST",IF(AF17>=35,"AVOID","PASS"))))) -> STRONG BUY | AH17: =IF(N17="","",IF(N17<3,"FAIL","OK")) -> OK | AI17: =IF(COUNT(D17:L17)=0,"",IF(COUNTIF(D17:L17,1)>0,"REVIEW","OK")) -> OK | AJ17: =IF(COUNT(D17:L17)=0,"",IF(COUNTIF(D17:L17,"<=2")>=2,"AVOID","OK")) -> OK | AK17: =IF(COUNTA(E17:M17)=0,"",IF(COUNTIF(E17:M17,"L")>=2,"CAP AT BUY","OK")) -> OK
A18: VRT | B18: Vertiv Holdings | C18: 46240 | D18: 4 | E18: H | F18: 5 | G18: H | H18: 4 | I18: M | J18: 4 | K18: M | L18: 5 | M18: H | N18: =IF(COUNT(D18,F18,H18,J18,L18)=0,"",(D18*0.2+F18*0.15+H18*0.15+J18*0.1+L18*0.1)/0.7) -> 4.3571429 | O18: =IF(COUNT(D18,F18,H18,J18,L18)=0,"",D18*0.2+F18*0.15+H18*0.15+J18*0.1+L18*0.1) -> 3.05 | P18: 4 | Q18: M | R18: 5 | S18: H | T18: 4 | U18: M | V18: 2 | W18: M | X18: =IF(COUNT(P18,R18,T18,V18)=0,"",P18*0.08+R18*0.06+T18*0.03+V18*0.08) -> 0.9 | Y18: 4 | Z18: M | AA18: 4 | AB18: M | AC18: 3 | AD18: L | AE18: =IF(COUNT(Y18,AA18,AC18)=0,"",Y18*0.02+AA18*0.02+AC18*0.01) -> 0.19 | AF18: =IF(OR(O18="",X18="",AE18=""),"",(O18+X18+AE18)*20) -> 82.8 | AG18: =IF(AF18="","",IF(AF18>=80,"STRONG BUY",IF(AF18>=65,"BUY",IF(AF18>=50,"WATCH LIST",IF(AF18>=35,"AVOID","PASS"))))) -> STRONG BUY | AH18: =IF(N18="","",IF(N18<3,"FAIL","OK")) -> OK | AI18: =IF(COUNT(D18:L18)=0,"",IF(COUNTIF(D18:L18,1)>0,"REVIEW","OK")) -> OK | AJ18: =IF(COUNT(D18:L18)=0,"",IF(COUNTIF(D18:L18,"<=2")>=2,"AVOID","OK")) -> OK | AK18: =IF(COUNTA(E18:M18)=0,"",IF(COUNTIF(E18:M18,"L")>=2,"CAP AT BUY","OK")) -> OK
N19: =IF(COUNT(D19,F19,H19,J19,L19)=0,"",(D19*0.2+F19*0.15+H19*0.15+J19*0.1+L19*0.1)/0.7) | O19: =IF(COUNT(D19,F19,H19,J19,L19)=0,"",D19*0.2+F19*0.15+H19*0.15+J19*0.1+L19*0.1) | X19: =IF(COUNT(P19,R19,T19,V19)=0,"",P19*0.08+R19*0.06+T19*0.03+V19*0.08) | AE19: =IF(COUNT(Y19,AA19,AC19)=0,"",Y19*0.02+AA19*0.02+AC19*0.01) | AF19: =IF(OR(O19="",X19="",AE19=""),"",(O19+X19+AE19)*20) | AG19: =IF(AF19="","",IF(AF19>=80,"STRONG BUY",IF(AF19>=65,"BUY",IF(AF19>=50,"WATCH LIST",IF(AF19>=35,"AVOID","PASS"))))) | AH19: =IF(N19="","",IF(N19<3,"FAIL","OK")) | AI19: =IF(COUNT(D19:L19)=0,"",IF(COUNTIF(D19:L19,1)>0,"REVIEW","OK")) | AJ19: =IF(COUNT(D19:L19)=0,"",IF(COUNTIF(D19:L19,"<=2")>=2,"AVOID","OK")) | AK19: =IF(COUNTA(E19:M19)=0,"",IF(COUNTIF(E19:M19,"L")>=2,"CAP AT BUY","OK"))
N20: =IF(COUNT(D20,F20,H20,J20,L20)=0,"",(D20*0.2+F20*0.15+H20*0.15+J20*0.1+L20*0.1)/0.7) | O20: =IF(COUNT(D20,F20,H20,J20,L20)=0,"",D20*0.2+F20*0.15+H20*0.15+J20*0.1+L20*0.1) | X20: =IF(COUNT(P20,R20,T20,V20)=0,"",P20*0.08+R20*0.06+T20*0.03+V20*0.08) | AE20: =IF(COUNT(Y20,AA20,AC20)=0,"",Y20*0.02+AA20*0.02+AC20*0.01) | AF20: =IF(OR(O20="",X20="",AE20=""),"",(O20+X20+AE20)*20) | AG20: =IF(AF20="","",IF(AF20>=80,"STRONG BUY",IF(AF20>=65,"BUY",IF(AF20>=50,"WATCH LIST",IF(AF20>=35,"AVOID","PASS"))))) | AH20: =IF(N20="","",IF(N20<3,"FAIL","OK")) | AI20: =IF(COUNT(D20:L20)=0,"",IF(COUNTIF(D20:L20,1)>0,"REVIEW","OK")) | AJ20: =IF(COUNT(D20:L20)=0,"",IF(COUNTIF(D20:L20,"<=2")>=2,"AVOID","OK")) | AK20: =IF(COUNTA(E20:M20)=0,"",IF(COUNTIF(E20:M20,"L")>=2,"CAP AT BUY","OK"))
N21: =IF(COUNT(D21,F21,H21,J21,L21)=0,"",(D21*0.2+F21*0.15+H21*0.15+J21*0.1+L21*0.1)/0.7) | O21: =IF(COUNT(D21,F21,H21,J21,L21)=0,"",D21*0.2+F21*0.15+H21*0.15+J21*0.1+L21*0.1) | X21: =IF(COUNT(P21,R21,T21,V21)=0,"",P21*0.08+R21*0.06+T21*0.03+V21*0.08) | AE21: =IF(COUNT(Y21,AA21,AC21)=0,"",Y21*0.02+AA21*0.02+AC21*0.01) | AF21: =IF(OR(O21="",X21="",AE21=""),"",(O21+X21+AE21)*20) | AG21: =IF(AF21="","",IF(AF21>=80,"STRONG BUY",IF(AF21>=65,"BUY",IF(AF21>=50,"WATCH LIST",IF(AF21>=35,"AVOID","PASS"))))) | AH21: =IF(N21="","",IF(N21<3,"FAIL","OK")) | AI21: =IF(COUNT(D21:L21)=0,"",IF(COUNTIF(D21:L21,1)>0,"REVIEW","OK")) | AJ21: =IF(COUNT(D21:L21)=0,"",IF(COUNTIF(D21:L21,"<=2")>=2,"AVOID","OK")) | AK21: =IF(COUNTA(E21:M21)=0,"",IF(COUNTIF(E21:M21,"L")>=2,"CAP AT BUY","OK"))
N22: =IF(COUNT(D22,F22,H22,J22,L22)=0,"",(D22*0.2+F22*0.15+H22*0.15+J22*0.1+L22*0.1)/0.7) | O22: =IF(COUNT(D22,F22,H22,J22,L22)=0,"",D22*0.2+F22*0.15+H22*0.15+J22*0.1+L22*0.1) | X22: =IF(COUNT(P22,R22,T22,V22)=0,"",P22*0.08+R22*0.06+T22*0.03+V22*0.08) | AE22: =IF(COUNT(Y22,AA22,AC22)=0,"",Y22*0.02+AA22*0.02+AC22*0.01) | AF22: =IF(OR(O22="",X22="",AE22=""),"",(O22+X22+AE22)*20) | AG22: =IF(AF22="","",IF(AF22>=80,"STRONG BUY",IF(AF22>=65,"BUY",IF(AF22>=50,"WATCH LIST",IF(AF22>=35,"AVOID","PASS"))))) | AH22: =IF(N22="","",IF(N22<3,"FAIL","OK")) | AI22: =IF(COUNT(D22:L22)=0,"",IF(COUNTIF(D22:L22,1)>0,"REVIEW","OK")) | AJ22: =IF(COUNT(D22:L22)=0,"",IF(COUNTIF(D22:L22,"<=2")>=2,"AVOID","OK")) | AK22: =IF(COUNTA(E22:M22)=0,"",IF(COUNTIF(E22:M22,"L")>=2,"CAP AT BUY","OK"))
N23: =IF(COUNT(D23,F23,H23,J23,L23)=0,"",(D23*0.2+F23*0.15+H23*0.15+J23*0.1+L23*0.1)/0.7) | O23: =IF(COUNT(D23,F23,H23,J23,L23)=0,"",D23*0.2+F23*0.15+H23*0.15+J23*0.1+L23*0.1) | X23: =IF(COUNT(P23,R23,T23,V23)=0,"",P23*0.08+R23*0.06+T23*0.03+V23*0.08) | AE23: =IF(COUNT(Y23,AA23,AC23)=0,"",Y23*0.02+AA23*0.02+AC23*0.01) | AF23: =IF(OR(O23="",X23="",AE23=""),"",(O23+X23+AE23)*20) | AG23: =IF(AF23="","",IF(AF23>=80,"STRONG BUY",IF(AF23>=65,"BUY",IF(AF23>=50,"WATCH LIST",IF(AF23>=35,"AVOID","PASS"))))) | AH23: =IF(N23="","",IF(N23<3,"FAIL","OK")) | AI23: =IF(COUNT(D23:L23)=0,"",IF(COUNTIF(D23:L23,1)>0,"REVIEW","OK")) | AJ23: =IF(COUNT(D23:L23)=0,"",IF(COUNTIF(D23:L23,"<=2")>=2,"AVOID","OK")) | AK23: =IF(COUNTA(E23:M23)=0,"",IF(COUNTIF(E23:M23,"L")>=2,"CAP AT BUY","OK"))
N24: =IF(COUNT(D24,F24,H24,J24,L24)=0,"",(D24*0.2+F24*0.15+H24*0.15+J24*0.1+L24*0.1)/0.7) | O24: =IF(COUNT(D24,F24,H24,J24,L24)=0,"",D24*0.2+F24*0.15+H24*0.15+J24*0.1+L24*0.1) | X24: =IF(COUNT(P24,R24,T24,V24)=0,"",P24*0.08+R24*0.06+T24*0.03+V24*0.08) | AE24: =IF(COUNT(Y24,AA24,AC24)=0,"",Y24*0.02+AA24*0.02+AC24*0.01) | AF24: =IF(OR(O24="",X24="",AE24=""),"",(O24+X24+AE24)*20) | AG24: =IF(AF24="","",IF(AF24>=80,"STRONG BUY",IF(AF24>=65,"BUY",IF(AF24>=50,"WATCH LIST",IF(AF24>=35,"AVOID","PASS"))))) | AH24: =IF(N24="","",IF(N24<3,"FAIL","OK")) | AI24: =IF(COUNT(D24:L24)=0,"",IF(COUNTIF(D24:L24,1)>0,"REVIEW","OK")) | AJ24: =IF(COUNT(D24:L24)=0,"",IF(COUNTIF(D24:L24,"<=2")>=2,"AVOID","OK")) | AK24: =IF(COUNTA(E24:M24)=0,"",IF(COUNTIF(E24:M24,"L")>=2,"CAP AT BUY","OK"))
N25: =IF(COUNT(D25,F25,H25,J25,L25)=0,"",(D25*0.2+F25*0.15+H25*0.15+J25*0.1+L25*0.1)/0.7) | O25: =IF(COUNT(D25,F25,H25,J25,L25)=0,"",D25*0.2+F25*0.15+H25*0.15+J25*0.1+L25*0.1) | X25: =IF(COUNT(P25,R25,T25,V25)=0,"",P25*0.08+R25*0.06+T25*0.03+V25*0.08) | AE25: =IF(COUNT(Y25,AA25,AC25)=0,"",Y25*0.02+AA25*0.02+AC25*0.01) | AF25: =IF(OR(O25="",X25="",AE25=""),"",(O25+X25+AE25)*20) | AG25: =IF(AF25="","",IF(AF25>=80,"STRONG BUY",IF(AF25>=65,"BUY",IF(AF25>=50,"WATCH LIST",IF(AF25>=35,"AVOID","PASS"))))) | AH25: =IF(N25="","",IF(N25<3,"FAIL","OK")) | AI25: =IF(COUNT(D25:L25)=0,"",IF(COUNTIF(D25:L25,1)>0,"REVIEW","OK")) | AJ25: =IF(COUNT(D25:L25)=0,"",IF(COUNTIF(D25:L25,"<=2")>=2,"AVOID","OK")) | AK25: =IF(COUNTA(E25:M25)=0,"",IF(COUNTIF(E25:M25,"L")>=2,"CAP AT BUY","OK"))
N26: =IF(COUNT(D26,F26,H26,J26,L26)=0,"",(D26*0.2+F26*0.15+H26*0.15+J26*0.1+L26*0.1)/0.7) | O26: =IF(COUNT(D26,F26,H26,J26,L26)=0,"",D26*0.2+F26*0.15+H26*0.15+J26*0.1+L26*0.1) | X26: =IF(COUNT(P26,R26,T26,V26)=0,"",P26*0.08+R26*0.06+T26*0.03+V26*0.08) | AE26: =IF(COUNT(Y26,AA26,AC26)=0,"",Y26*0.02+AA26*0.02+AC26*0.01) | AF26: =IF(OR(O26="",X26="",AE26=""),"",(O26+X26+AE26)*20) | AG26: =IF(AF26="","",IF(AF26>=80,"STRONG BUY",IF(AF26>=65,"BUY",IF(AF26>=50,"WATCH LIST",IF(AF26>=35,"AVOID","PASS"))))) | AH26: =IF(N26="","",IF(N26<3,"FAIL","OK")) | AI26: =IF(COUNT(D26:L26)=0,"",IF(COUNTIF(D26:L26,1)>0,"REVIEW","OK")) | AJ26: =IF(COUNT(D26:L26)=0,"",IF(COUNTIF(D26:L26,"<=2")>=2,"AVOID","OK")) | AK26: =IF(COUNTA(E26:M26)=0,"",IF(COUNTIF(E26:M26,"L")>=2,"CAP AT BUY","OK"))
N27: =IF(COUNT(D27,F27,H27,J27,L27)=0,"",(D27*0.2+F27*0.15+H27*0.15+J27*0.1+L27*0.1)/0.7) | O27: =IF(COUNT(D27,F27,H27,J27,L27)=0,"",D27*0.2+F27*0.15+H27*0.15+J27*0.1+L27*0.1) | X27: =IF(COUNT(P27,R27,T27,V27)=0,"",P27*0.08+R27*0.06+T27*0.03+V27*0.08) | AE27: =IF(COUNT(Y27,AA27,AC27)=0,"",Y27*0.02+AA27*0.02+AC27*0.01) | AF27: =IF(OR(O27="",X27="",AE27=""),"",(O27+X27+AE27)*20) | AG27: =IF(AF27="","",IF(AF27>=80,"STRONG BUY",IF(AF27>=65,"BUY",IF(AF27>=50,"WATCH LIST",IF(AF27>=35,"AVOID","PASS"))))) | AH27: =IF(N27="","",IF(N27<3,"FAIL","OK")) | AI27: =IF(COUNT(D27:L27)=0,"",IF(COUNTIF(D27:L27,1)>0,"REVIEW","OK")) | AJ27: =IF(COUNT(D27:L27)=0,"",IF(COUNTIF(D27:L27,"<=2")>=2,"AVOID","OK")) | AK27: =IF(COUNTA(E27:M27)=0,"",IF(COUNTIF(E27:M27,"L")>=2,"CAP AT BUY","OK"))

Sheet Entry Checklist
A1: Part 4 Entry Rules (5-10, 13). Rules 5-7 pull from the Scoring tab; Rules 11-12 pull from the Implied-Return Calculator; Rules 8-9-10-13 are entered here. Keep this tab's row order matching Scoring/Dashboard/Implied-Return Calculator for the same stock (row 3 = same stock across all four).
A2: Ticker | B2: Company | C2: Rule 5 Composite ≥65? | D2: Rule 6 Tier1 ≥3.0? | E2: Rule 7 No Tier1 =1? | F2: Rule 8 Above/reclaimed 200-wk MA? (Y/N) | G2: Rule 9 Monthly MACD positive/turning? (Y/N) | H2: Staging Result (Rules 8-9) | I2: Rule 10 Binary event risk present? (Y/N) | J2: Risk included in thesis? (Y/N) | K2: Rule 10 Result | L2: Rule 11 Bear Case ≥0%? | M2: Rule 12 Scenario tags OK? | N2: P/FCF (current) | O2: Consensus FCF growth, 2-yr annualized | P2: Rule 13 Valuation Ceiling | Q2: ENTRY AUTHORIZED? | R2: Recommended Action
A3: =IF(Scoring!A3="","",Scoring!A3) -> MU | B3: =IF(Scoring!B3="","",Scoring!B3) -> Micron Technology | C3: =IF(Scoring!AG3="","",IF(OR(Scoring!AG3="STRONG BUY",Scoring!AG3="BUY"),"PASS","FAIL")) -> PASS | D3: =IF(Scoring!AH3="","",IF(Scoring!AH3="OK","PASS","FAIL")) -> PASS | E3: =IF(Scoring!AI3="","",IF(Scoring!AI3="OK","PASS","FAIL — mandatory review required")) -> PASS | H3: =IF(OR(F3="",G3=""),"",IF(AND(F3="Y",G3="Y"),"Standard initial size","50% of normal initial size + 90-day technical review")) | K3: =IF(I3="","",IF(I3="N","PASS",IF(J3="Y","PASS — risk documented in thesis","FAIL — undocumented binary risk"))) | L3: =IF('Implied-Return Calculator'!T4="","",'Implied-Return Calculator'!T4) | M3: =IF('Implied-Return Calculator'!U4="","",'Implied-Return Calculator'!U4) | P3: =IF(OR(N3="",O3=""),"",IF(N3<=50,"PASS — within ceiling",IF(AND(O3>0.3,L3="PASS"),"PASS — growth+bear case exception met","FAIL — exceeds 50x, exception not met"))) | Q3: =IF(OR(C3="",D3="",E3="",K3="",L3="",M3="",P3=""),"",IF(AND(C3="PASS",D3="PASS",LEFT(E3,4)="PASS",LEFT(K3,4)="PASS",L3="PASS",M3="OK",LEFT(P3,4)="PASS"),"YES","NO — see failing rule(s)")) | R3: =IF(Q3="","",IF(Q3="YES","Initiate: "&H3,"DO NOT ENTER — resolve failing Entry Rule(s) above first"))
A4: =IF(Scoring!A4="","",Scoring!A4) -> AVGO | B4: =IF(Scoring!B4="","",Scoring!B4) -> Broadcom Inc. | C4: =IF(Scoring!AG4="","",IF(OR(Scoring!AG4="STRONG BUY",Scoring!AG4="BUY"),"PASS","FAIL")) -> PASS | D4: =IF(Scoring!AH4="","",IF(Scoring!AH4="OK","PASS","FAIL")) -> PASS | E4: =IF(Scoring!AI4="","",IF(Scoring!AI4="OK","PASS","FAIL — mandatory review required")) -> PASS | H4: =IF(OR(F4="",G4=""),"",IF(AND(F4="Y",G4="Y"),"Standard initial size","50% of normal initial size + 90-day technical review")) | K4: =IF(I4="","",IF(I4="N","PASS",IF(J4="Y","PASS — risk documented in thesis","FAIL — undocumented binary risk"))) | L4: =IF('Implied-Return Calculator'!T5="","",'Implied-Return Calculator'!T5) | M4: =IF('Implied-Return Calculator'!U5="","",'Implied-Return Calculator'!U5) | P4: =IF(OR(N4="",O4=""),"",IF(N4<=50,"PASS — within ceiling",IF(AND(O4>0.3,L4="PASS"),"PASS — growth+bear case exception met","FAIL — exceeds 50x, exception not met"))) | Q4: =IF(OR(C4="",D4="",E4="",K4="",L4="",M4="",P4=""),"",IF(AND(C4="PASS",D4="PASS",LEFT(E4,4)="PASS",LEFT(K4,4)="PASS",L4="PASS",M4="OK",LEFT(P4,4)="PASS"),"YES","NO — see failing rule(s)")) | R4: =IF(Q4="","",IF(Q4="YES","Initiate: "&H4,"DO NOT ENTER — resolve failing Entry Rule(s) above first"))
A5: =IF(Scoring!A5="","",Scoring!A5) -> PLTR | B5: =IF(Scoring!B5="","",Scoring!B5) -> Palantir Technologies | C5: =IF(Scoring!AG5="","",IF(OR(Scoring!AG5="STRONG BUY",Scoring!AG5="BUY"),"PASS","FAIL")) -> PASS | D5: =IF(Scoring!AH5="","",IF(Scoring!AH5="OK","PASS","FAIL")) -> PASS | E5: =IF(Scoring!AI5="","",IF(Scoring!AI5="OK","PASS","FAIL — mandatory review required")) -> PASS | H5: =IF(OR(F5="",G5=""),"",IF(AND(F5="Y",G5="Y"),"Standard initial size","50% of normal initial size + 90-day technical review")) | K5: =IF(I5="","",IF(I5="N","PASS",IF(J5="Y","PASS — risk documented in thesis","FAIL — undocumented binary risk"))) | L5: =IF('Implied-Return Calculator'!T6="","",'Implied-Return Calculator'!T6) | M5: =IF('Implied-Return Calculator'!U6="","",'Implied-Return Calculator'!U6) | P5: =IF(OR(N5="",O5=""),"",IF(N5<=50,"PASS — within ceiling",IF(AND(O5>0.3,L5="PASS"),"PASS — growth+bear case exception met","FAIL — exceeds 50x, exception not met"))) | Q5: =IF(OR(C5="",D5="",E5="",K5="",L5="",M5="",P5=""),"",IF(AND(C5="PASS",D5="PASS",LEFT(E5,4)="PASS",LEFT(K5,4)="PASS",L5="PASS",M5="OK",LEFT(P5,4)="PASS"),"YES","NO — see failing rule(s)")) | R5: =IF(Q5="","",IF(Q5="YES","Initiate: "&H5,"DO NOT ENTER — resolve failing Entry Rule(s) above first"))
A6: =IF(Scoring!A6="","",Scoring!A6) -> NVDA | B6: =IF(Scoring!B6="","",Scoring!B6) -> NVIDIA Corporation | C6: =IF(Scoring!AG6="","",IF(OR(Scoring!AG6="STRONG BUY",Scoring!AG6="BUY"),"PASS","FAIL")) -> PASS | D6: =IF(Scoring!AH6="","",IF(Scoring!AH6="OK","PASS","FAIL")) -> PASS | E6: =IF(Scoring!AI6="","",IF(Scoring!AI6="OK","PASS","FAIL — mandatory review required")) -> PASS | H6: =IF(OR(F6="",G6=""),"",IF(AND(F6="Y",G6="Y"),"Standard initial size","50% of normal initial size + 90-day technical review")) | K6: =IF(I6="","",IF(I6="N","PASS",IF(J6="Y","PASS — risk documented in thesis","FAIL — undocumented binary risk"))) | L6: =IF('Implied-Return Calculator'!T7="","",'Implied-Return Calculator'!T7) | M6: =IF('Implied-Return Calculator'!U7="","",'Implied-Return Calculator'!U7) | P6: =IF(OR(N6="",O6=""),"",IF(N6<=50,"PASS — within ceiling",IF(AND(O6>0.3,L6="PASS"),"PASS — growth+bear case exception met","FAIL — exceeds 50x, exception not met"))) | Q6: =IF(OR(C6="",D6="",E6="",K6="",L6="",M6="",P6=""),"",IF(AND(C6="PASS",D6="PASS",LEFT(E6,4)="PASS",LEFT(K6,4)="PASS",L6="PASS",M6="OK",LEFT(P6,4)="PASS"),"YES","NO — see failing rule(s)")) | R6: =IF(Q6="","",IF(Q6="YES","Initiate: "&H6,"DO NOT ENTER — resolve failing Entry Rule(s) above first"))
A7: =IF(Scoring!A7="","",Scoring!A7) -> VRTX | B7: =IF(Scoring!B7="","",Scoring!B7) -> Vertex Pharmaceuticals | C7: =IF(Scoring!AG7="","",IF(OR(Scoring!AG7="STRONG BUY",Scoring!AG7="BUY"),"PASS","FAIL")) -> PASS | D7: =IF(Scoring!AH7="","",IF(Scoring!AH7="OK","PASS","FAIL")) -> PASS | E7: =IF(Scoring!AI7="","",IF(Scoring!AI7="OK","PASS","FAIL — mandatory review required")) -> PASS | H7: =IF(OR(F7="",G7=""),"",IF(AND(F7="Y",G7="Y"),"Standard initial size","50% of normal initial size + 90-day technical review")) | K7: =IF(I7="","",IF(I7="N","PASS",IF(J7="Y","PASS — risk documented in thesis","FAIL — undocumented binary risk"))) | L7: =IF('Implied-Return Calculator'!T8="","",'Implied-Return Calculator'!T8) | M7: =IF('Implied-Return Calculator'!U8="","",'Implied-Return Calculator'!U8) | P7: =IF(OR(N7="",O7=""),"",IF(N7<=50,"PASS — within ceiling",IF(AND(O7>0.3,L7="PASS"),"PASS — growth+bear case exception met","FAIL — exceeds 50x, exception not met"))) | Q7: =IF(OR(C7="",D7="",E7="",K7="",L7="",M7="",P7=""),"",IF(AND(C7="PASS",D7="PASS",LEFT(E7,4)="PASS",LEFT(K7,4)="PASS",L7="PASS",M7="OK",LEFT(P7,4)="PASS"),"YES","NO — see failing rule(s)")) | R7: =IF(Q7="","",IF(Q7="YES","Initiate: "&H7,"DO NOT ENTER — resolve failing Entry Rule(s) above first"))
A8: =IF(Scoring!A8="","",Scoring!A8) -> PLD | B8: =IF(Scoring!B8="","",Scoring!B8) -> Prologis Inc. (REIT-adapted) | C8: =IF(Scoring!AG8="","",IF(OR(Scoring!AG8="STRONG BUY",Scoring!AG8="BUY"),"PASS","FAIL")) -> PASS | D8: =IF(Scoring!AH8="","",IF(Scoring!AH8="OK","PASS","FAIL")) -> PASS | E8: =IF(Scoring!AI8="","",IF(Scoring!AI8="OK","PASS","FAIL — mandatory review required")) -> PASS | H8: =IF(OR(F8="",G8=""),"",IF(AND(F8="Y",G8="Y"),"Standard initial size","50% of normal initial size + 90-day technical review")) | K8: =IF(I8="","",IF(I8="N","PASS",IF(J8="Y","PASS — risk documented in thesis","FAIL — undocumented binary risk"))) | L8: =IF('Implied-Return Calculator'!T9="","",'Implied-Return Calculator'!T9) | M8: =IF('Implied-Return Calculator'!U9="","",'Implied-Return Calculator'!U9) | P8: =IF(OR(N8="",O8=""),"",IF(N8<=50,"PASS — within ceiling",IF(AND(O8>0.3,L8="PASS"),"PASS — growth+bear case exception met","FAIL — exceeds 50x, exception not met"))) | Q8: =IF(OR(C8="",D8="",E8="",K8="",L8="",M8="",P8=""),"",IF(AND(C8="PASS",D8="PASS",LEFT(E8,4)="PASS",LEFT(K8,4)="PASS",L8="PASS",M8="OK",LEFT(P8,4)="PASS"),"YES","NO — see failing rule(s)")) | R8: =IF(Q8="","",IF(Q8="YES","Initiate: "&H8,"DO NOT ENTER — resolve failing Entry Rule(s) above first"))
A9: =IF(Scoring!A9="","",Scoring!A9) -> SFM | B9: =IF(Scoring!B9="","",Scoring!B9) -> Sprouts Farmers Market | C9: =IF(Scoring!AG9="","",IF(OR(Scoring!AG9="STRONG BUY",Scoring!AG9="BUY"),"PASS","FAIL")) | D9: =IF(Scoring!AH9="","",IF(Scoring!AH9="OK","PASS","FAIL")) -> FAIL | E9: =IF(Scoring!AI9="","",IF(Scoring!AI9="OK","PASS","FAIL — mandatory review required")) -> FAIL — mandatory review required | H9: =IF(OR(F9="",G9=""),"",IF(AND(F9="Y",G9="Y"),"Standard initial size","50% of normal initial size + 90-day technical review")) | K9: =IF(I9="","",IF(I9="N","PASS",IF(J9="Y","PASS — risk documented in thesis","FAIL — undocumented binary risk"))) | L9: =IF('Implied-Return Calculator'!T10="","",'Implied-Return Calculator'!T10) | M9: =IF('Implied-Return Calculator'!U10="","",'Implied-Return Calculator'!U10) | P9: =IF(OR(N9="",O9=""),"",IF(N9<=50,"PASS — within ceiling",IF(AND(O9>0.3,L9="PASS"),"PASS — growth+bear case exception met","FAIL — exceeds 50x, exception not met"))) | Q9: =IF(OR(C9="",D9="",E9="",K9="",L9="",M9="",P9=""),"",IF(AND(C9="PASS",D9="PASS",LEFT(E9,4)="PASS",LEFT(K9,4)="PASS",L9="PASS",M9="OK",LEFT(P9,4)="PASS"),"YES","NO — see failing rule(s)")) | R9: =IF(Q9="","",IF(Q9="YES","Initiate: "&H9,"DO NOT ENTER — resolve failing Entry Rule(s) above first"))
A10: =IF(Scoring!A10="","",Scoring!A10) -> ONON | B10: =IF(Scoring!B10="","",Scoring!B10) -> On Holding AG | C10: =IF(Scoring!AG10="","",IF(OR(Scoring!AG10="STRONG BUY",Scoring!AG10="BUY"),"PASS","FAIL")) | D10: =IF(Scoring!AH10="","",IF(Scoring!AH10="OK","PASS","FAIL")) -> FAIL | E10: =IF(Scoring!AI10="","",IF(Scoring!AI10="OK","PASS","FAIL — mandatory review required")) -> PASS | H10: =IF(OR(F10="",G10=""),"",IF(AND(F10="Y",G10="Y"),"Standard initial size","50% of normal initial size + 90-day technical review")) | K10: =IF(I10="","",IF(I10="N","PASS",IF(J10="Y","PASS — risk documented in thesis","FAIL — undocumented binary risk"))) | L10: =IF('Implied-Return Calculator'!T11="","",'Implied-Return Calculator'!T11) | M10: =IF('Implied-Return Calculator'!U11="","",'Implied-Return Calculator'!U11) | P10: =IF(OR(N10="",O10=""),"",IF(N10<=50,"PASS — within ceiling",IF(AND(O10>0.3,L10="PASS"),"PASS — growth+bear case exception met","FAIL — exceeds 50x, exception not met"))) | Q10: =IF(OR(C10="",D10="",E10="",K10="",L10="",M10="",P10=""),"",IF(AND(C10="PASS",D10="PASS",LEFT(E10,4)="PASS",LEFT(K10,4)="PASS",L10="PASS",M10="OK",LEFT(P10,4)="PASS"),"YES","NO — see failing rule(s)")) | R10: =IF(Q10="","",IF(Q10="YES","Initiate: "&H10,"DO NOT ENTER — resolve failing Entry Rule(s) above first"))
A11: =IF(Scoring!A11="","",Scoring!A11) -> TSLA | B11: =IF(Scoring!B11="","",Scoring!B11) -> Tesla Inc. | C11: =IF(Scoring!AG11="","",IF(OR(Scoring!AG11="STRONG BUY",Scoring!AG11="BUY"),"PASS","FAIL")) | D11: =IF(Scoring!AH11="","",IF(Scoring!AH11="OK","PASS","FAIL")) -> FAIL | E11: =IF(Scoring!AI11="","",IF(Scoring!AI11="OK","PASS","FAIL — mandatory review required")) -> FAIL — mandatory review required | H11: =IF(OR(F11="",G11=""),"",IF(AND(F11="Y",G11="Y"),"Standard initial size","50% of normal initial size + 90-day technical review")) | K11: =IF(I11="","",IF(I11="N","PASS",IF(J11="Y","PASS — risk documented in thesis","FAIL — undocumented binary risk"))) | L11: =IF('Implied-Return Calculator'!T12="","",'Implied-Return Calculator'!T12) | M11: =IF('Implied-Return Calculator'!U12="","",'Implied-Return Calculator'!U12) | P11: =IF(OR(N11="",O11=""),"",IF(N11<=50,"PASS — within ceiling",IF(AND(O11>0.3,L11="PASS"),"PASS — growth+bear case exception met","FAIL — exceeds 50x, exception not met"))) | Q11: =IF(OR(C11="",D11="",E11="",K11="",L11="",M11="",P11=""),"",IF(AND(C11="PASS",D11="PASS",LEFT(E11,4)="PASS",LEFT(K11,4)="PASS",L11="PASS",M11="OK",LEFT(P11,4)="PASS"),"YES","NO — see failing rule(s)")) | R11: =IF(Q11="","",IF(Q11="YES","Initiate: "&H11,"DO NOT ENTER — resolve failing Entry Rule(s) above first"))
A12: =IF(Scoring!A12="","",Scoring!A12) -> ADBE | B12: =IF(Scoring!B12="","",Scoring!B12) -> Adobe Inc. | C12: =IF(Scoring!AG12="","",IF(OR(Scoring!AG12="STRONG BUY",Scoring!AG12="BUY"),"PASS","FAIL")) -> PASS | D12: =IF(Scoring!AH12="","",IF(Scoring!AH12="OK","PASS","FAIL")) -> PASS | E12: =IF(Scoring!AI12="","",IF(Scoring!AI12="OK","PASS","FAIL — mandatory review required")) -> PASS | H12: =IF(OR(F12="",G12=""),"",IF(AND(F12="Y",G12="Y"),"Standard initial size","50% of normal initial size + 90-day technical review")) | K12: =IF(I12="","",IF(I12="N","PASS",IF(J12="Y","PASS — risk documented in thesis","FAIL — undocumented binary risk"))) | L12: =IF('Implied-Return Calculator'!T13="","",'Implied-Return Calculator'!T13) | M12: =IF('Implied-Return Calculator'!U13="","",'Implied-Return Calculator'!U13) | P12: =IF(OR(N12="",O12=""),"",IF(N12<=50,"PASS — within ceiling",IF(AND(O12>0.3,L12="PASS"),"PASS — growth+bear case exception met","FAIL — exceeds 50x, exception not met"))) | Q12: =IF(OR(C12="",D12="",E12="",K12="",L12="",M12="",P12=""),"",IF(AND(C12="PASS",D12="PASS",LEFT(E12,4)="PASS",LEFT(K12,4)="PASS",L12="PASS",M12="OK",LEFT(P12,4)="PASS"),"YES","NO — see failing rule(s)")) | R12: =IF(Q12="","",IF(Q12="YES","Initiate: "&H12,"DO NOT ENTER — resolve failing Entry Rule(s) above first"))
A13: =IF(Scoring!A13="","",Scoring!A13) -> ANET | B13: =IF(Scoring!B13="","",Scoring!B13) -> Arista Networks | C13: =IF(Scoring!AG13="","",IF(OR(Scoring!AG13="STRONG BUY",Scoring!AG13="BUY"),"PASS","FAIL")) -> PASS | D13: =IF(Scoring!AH13="","",IF(Scoring!AH13="OK","PASS","FAIL")) -> PASS | E13: =IF(Scoring!AI13="","",IF(Scoring!AI13="OK","PASS","FAIL — mandatory review required")) -> PASS | H13: =IF(OR(F13="",G13=""),"",IF(AND(F13="Y",G13="Y"),"Standard initial size","50% of normal initial size + 90-day technical review")) | K13: =IF(I13="","",IF(I13="N","PASS",IF(J13="Y","PASS — risk documented in thesis","FAIL — undocumented binary risk"))) | L13: =IF('Implied-Return Calculator'!T14="","",'Implied-Return Calculator'!T14) | M13: =IF('Implied-Return Calculator'!U14="","",'Implied-Return Calculator'!U14) | P13: =IF(OR(N13="",O13=""),"",IF(N13<=50,"PASS — within ceiling",IF(AND(O13>0.3,L13="PASS"),"PASS — growth+bear case exception met","FAIL — exceeds 50x, exception not met"))) | Q13: =IF(OR(C13="",D13="",E13="",K13="",L13="",M13="",P13=""),"",IF(AND(C13="PASS",D13="PASS",LEFT(E13,4)="PASS",LEFT(K13,4)="PASS",L13="PASS",M13="OK",LEFT(P13,4)="PASS"),"YES","NO — see failing rule(s)")) | R13: =IF(Q13="","",IF(Q13="YES","Initiate: "&H13,"DO NOT ENTER — resolve failing Entry Rule(s) above first"))
A14: =IF(Scoring!A14="","",Scoring!A14) -> ASML | B14: =IF(Scoring!B14="","",Scoring!B14) -> ASML Holding | C14: =IF(Scoring!AG14="","",IF(OR(Scoring!AG14="STRONG BUY",Scoring!AG14="BUY"),"PASS","FAIL")) -> PASS | D14: =IF(Scoring!AH14="","",IF(Scoring!AH14="OK","PASS","FAIL")) -> PASS | E14: =IF(Scoring!AI14="","",IF(Scoring!AI14="OK","PASS","FAIL — mandatory review required")) -> PASS | H14: =IF(OR(F14="",G14=""),"",IF(AND(F14="Y",G14="Y"),"Standard initial size","50% of normal initial size + 90-day technical review")) | K14: =IF(I14="","",IF(I14="N","PASS",IF(J14="Y","PASS — risk documented in thesis","FAIL — undocumented binary risk"))) | L14: =IF('Implied-Return Calculator'!T15="","",'Implied-Return Calculator'!T15) | M14: =IF('Implied-Return Calculator'!U15="","",'Implied-Return Calculator'!U15) | P14: =IF(OR(N14="",O14=""),"",IF(N14<=50,"PASS — within ceiling",IF(AND(O14>0.3,L14="PASS"),"PASS — growth+bear case exception met","FAIL — exceeds 50x, exception not met"))) | Q14: =IF(OR(C14="",D14="",E14="",K14="",L14="",M14="",P14=""),"",IF(AND(C14="PASS",D14="PASS",LEFT(E14,4)="PASS",LEFT(K14,4)="PASS",L14="PASS",M14="OK",LEFT(P14,4)="PASS"),"YES","NO — see failing rule(s)")) | R14: =IF(Q14="","",IF(Q14="YES","Initiate: "&H14,"DO NOT ENTER — resolve failing Entry Rule(s) above first"))
... A27: =IF(Scoring!A27="","",Scoring!A27) | B27: =IF(Scoring!B27="","",Scoring!B27) | C27: =IF(Scoring!AG27="","",IF(OR(Scoring!AG27="STRONG BUY",Scoring!AG27="BUY"),"PASS","FAIL")) | D27: =IF(Scoring!AH27="","",IF(Scoring!AH27="OK","PASS","FAIL")) | E27: =IF(Scoring!AI27="","",IF(Scoring!AI27="OK","PASS","FAIL — mandatory review required")) | H27: =IF(OR(F27="",G27=""),"",IF(AND(F27="Y",G27="Y"),"Standard initial size","50% of normal initial size + 90-day technical review")) | K27: =IF(I27="","",IF(I27="N","PASS",IF(J27="Y","PASS — risk documented in thesis","FAIL — undocumented binary risk"))) | L27: =IF('Implied-Return Calculator'!T28="","",'Implied-Return Calculator'!T28) | M27: =IF('Implied-Return Calculator'!U28="","",'Implied-Return Calculator'!U28) | P27: =IF(OR(N27="",O27=""),"",IF(N27<=50,"PASS — within ceiling",IF(AND(O27>0.3,L27="PASS"),"PASS — growth+bear case exception met","FAIL — exceeds 50x, exception not met"))) | Q27: =IF(OR(C27="",D27="",E27="",K27="",L27="",M27="",P27=""),"",IF(AND(C27="PASS",D27="PASS",LEFT(E27,4)="PASS",LEFT(K27,4)="PASS",L27="PASS",M27="OK",LEFT(P27,4)="PASS"),"YES","NO — see failing rule(s)")) | R27: =IF(Q27="","",IF(Q27="YES","Initiate: "&H27,"DO NOT ENTER — resolve failing Entry Rule(s) above first"))

Sheet Market Data
A1: Market Data — manual entry (blue cells). See note below on optional live refresh.
A2: Ticker | B2: Company | C2: Price ($) | D2: Volume | E2: Market Cap ($M) | F2: P/E | G2: 52-Wk Low | H2: 52-Wk High | I2: Div Yield (%)
A30: OPTIONAL LIVE REFRESH: Excel's built-in Stocks data type can auto-populate price, market cap, P/E, and
A31: 52-week range for a ticker you've converted to that data type (Data tab > Stocks, or type the ticker and
A32: use the data-type icon that appears). That feature depends on your Microsoft 365 subscription and an
A33: active internet connection, so it isn't pre-built into this sheet — set it up once per ticker if you want it,
A34: referencing cells like =A3.Price. Otherwise, enter values manually from Yahoo Finance, Google Finance,
A35: or your preferred source at each review.

Sheet Returns (Calc)
A1: Weekly return, calculated from Price History. Do not edit — formulas only.
A2: Week Ending | B2: ='Price History'!B2 -> ADBE | C2: ='Price History'!C2 -> ANET | D2: ='Price History'!D2 -> ASML | E2: ='Price History'!E2 -> AVGO | F2: ='Price History'!F2 -> CRWD | G2: ='Price History'!G2 -> KLAC | H2: ='Price History'!H2 -> MU | I2: ='Price History'!I2 -> NVDA | ... Q2: ='Price History'!Q2 -> Ticker 16
A3: ='Price History'!A4 -> 45156 | B3: =IF(OR('Price History'!B4="",'Price History'!B3="",'Price History'!B3=0),"",'Price History'!B4/'Price History'!B3-1) -> -0.00062936375 | C3: =IF(OR('Price History'!C4="",'Price History'!C3="",'Price History'!C3=0),"",'Price History'!C4/'Price History'!C3-1) -> 0.032007316 | D3: =IF(OR('Price History'!D4="",'Price History'!D3="",'Price History'!D3=0),"",'Price History'!D4/'Price History'!D3-1) -> -0.0097464414 | E3: =IF(OR('Price History'!E4="",'Price History'!E3="",'Price History'!E3=0),"",'Price History'!E4/'Price History'!E3-1) -> -0.0048204387 | F3: =IF(OR('Price History'!F4="",'Price History'!F3="",'Price History'!F3=0),"",'Price History'!F4/'Price History'!F3-1) -> -0.0097139773 | G3: =IF(OR('Price History'!G4="",'Price History'!G3="",'Price History'!G3=0),"",'Price History'!G4/'Price History'!G3-1) -> -0.0020876827 | H3: =IF(OR('Price History'!H4="",'Price History'!H3="",'Price History'!H3=0),"",'Price History'!H4/'Price History'!H3-1) -> -0.012117446 | I3: =IF(OR('Price History'!I4="",'Price History'!I3="",'Price History'!I3=0),"",'Price History'!I4/'Price History'!I3-1) -> 0.05997552 | ... Q3: =IF(OR('Price History'!Q4="",'Price History'!Q3="",'Price History'!Q3=0),"",'Price History'!Q4/'Price History'!Q3-1)
A4: ='Price History'!A5 -> 45163 | B4: =IF(OR('Price History'!B5="",'Price History'!B4="",'Price History'!B4=0),"",'Price History'!B5/'Price History'!B4-1) -> 0.033318245 | C4: =IF(OR('Price History'!C5="",'Price History'!C4="",'Price History'!C4=0),"",'Price History'!C5/'Price History'!C4-1) -> 0.0019937971 | D4: =IF(OR('Price History'!D5="",'Price History'!D4="",'Price History'!D4=0),"",'Price History'!D5/'Price History'!D4-1) -> -0.0065920986 | E4: =IF(OR('Price History'!E5="",'Price History'!E4="",'Price History'!E4=0),"",'Price History'!E5/'Price History'!E4-1) -> 0.031484621 | F4: =IF(OR('Price History'!F5="",'Price History'!F4="",'Price History'!F4=0),"",'Price History'!F5/'Price History'!F4-1) -> 0.019073569 | G4: =IF(OR('Price History'!G5="",'Price History'!G4="",'Price History'!G4=0),"",'Price History'!G5/'Price History'!G4-1) -> 0.0077405858 | H4: =IF(OR('Price History'!H5="",'Price History'!H4="",'Price History'!H4=0),"",'Price History'!H5/'Price History'!H4-1) -> 0.0020443466 | I4: =IF(OR('Price History'!I5="",'Price History'!I4="",'Price History'!I4=0),"",'Price History'!I5/'Price History'!I4-1) -> 0.062817552 | ... Q4: =IF(OR('Price History'!Q5="",'Price History'!Q4="",'Price History'!Q4=0),"",'Price History'!Q5/'Price History'!Q4-1)
A5: ='Price History'!A6 -> 45170 | B5: =IF(OR('Price History'!B6="",'Price History'!B5="",'Price History'!B5=0),"",'Price History'!B6/'Price History'!B5-1) -> 0.072658363 | C5: =IF(OR('Price History'!C6="",'Price History'!C5="",'Price History'!C5=0),"",'Price History'!C6/'Price History'!C5-1) -> 0.090868892 | D5: =IF(OR('Price History'!D6="",'Price History'!D5="",'Price History'!D5=0),"",'Price History'!D6/'Price History'!D5-1) -> 0.01768022 | E5: =IF(OR('Price History'!E6="",'Price History'!E5="",'Price History'!E5=0),"",'Price History'!E6/'Price History'!E5-1) -> 0.024301479 | F5: =IF(OR('Price History'!F6="",'Price History'!F5="",'Price History'!F5=0),"",'Price History'!F6/'Price History'!F5-1) -> 0.077807487 | G5: =IF(OR('Price History'!G6="",'Price History'!G5="",'Price History'!G5=0),"",'Price History'!G6/'Price History'!G5-1) -> 0.052522317 | H5: =IF(OR('Price History'!H6="",'Price History'!H5="",'Price History'!H5=0),"",'Price History'!H6/'Price History'!H5-1) -> 0.10467671 | I5: =IF(OR('Price History'!I6="",'Price History'!I5="",'Price History'!I5=0),"",'Price History'!I6/'Price History'!I5-1) -> 0.05410691 | ... Q5: =IF(OR('Price History'!Q6="",'Price History'!Q5="",'Price History'!Q5=0),"",'Price History'!Q6/'Price History'!Q5-1)
A6: ='Price History'!A7 -> 45177 | B6: =IF(OR('Price History'!B7="",'Price History'!B6="",'Price History'!B6=0),"",'Price History'!B7/'Price History'!B6-1) -> -0.0050602795 | C6: =IF(OR('Price History'!C7="",'Price History'!C6="",'Price History'!C6=0),"",'Price History'!C7/'Price History'!C6-1) -> -0.0044588569 | D6: =IF(OR('Price History'!D7="",'Price History'!D6="",'Price History'!D6=0),"",'Price History'!D7/'Price History'!D6-1) -> -0.052315402 | E6: =IF(OR('Price History'!E7="",'Price History'!E6="",'Price History'!E6=0),"",'Price History'!E7/'Price History'!E6-1) -> -0.017077364 | F6: =IF(OR('Price History'!F7="",'Price History'!F6="",'Price History'!F6=0),"",'Price History'!F7/'Price History'!F6-1) -> 0.042421235 | G6: =IF(OR('Price History'!G7="",'Price History'!G6="",'Price History'!G6=0),"",'Price History'!G7/'Price History'!G6-1) -> -0.018343195 | H6: =IF(OR('Price History'!H7="",'Price History'!H6="",'Price History'!H6=0),"",'Price History'!H7/'Price History'!H6-1) -> -0.0029833783 | I6: =IF(OR('Price History'!I7="",'Price History'!I6="",'Price History'!I6=0),"",'Price History'!I7/'Price History'!I6-1) -> -0.060606061 | ... Q6: =IF(OR('Price History'!Q7="",'Price History'!Q6="",'Price History'!Q6=0),"",'Price History'!Q7/'Price History'!Q6-1)
A7: ='Price History'!A8 -> 45184 | B7: =IF(OR('Price History'!B8="",'Price History'!B7="",'Price History'!B7=0),"",'Price History'!B8/'Price History'!B7-1) -> -0.056160326 | C7: =IF(OR('Price History'!C8="",'Price History'!C7="",'Price History'!C7=0),"",'Price History'!C8/'Price History'!C7-1) -> -0.05985342 | D7: =IF(OR('Price History'!D8="",'Price History'!D7="",'Price History'!D7=0),"",'Price History'!D8/'Price History'!D7-1) -> -0.049692607 | E7: =IF(OR('Price History'!E8="",'Price History'!E7="",'Price History'!E7=0),"",'Price History'!E8/'Price History'!E7-1) -> -0.0068796642 | F7: =IF(OR('Price History'!F8="",'Price History'!F7="",'Price History'!F7=0),"",'Price History'!F8/'Price History'!F7-1) -> -0.015706806 | G7: =IF(OR('Price History'!G8="",'Price History'!G7="",'Price History'!G7=0),"",'Price History'!G8/'Price History'!G7-1) -> -0.087402049 | H7: =IF(OR('Price History'!H8="",'Price History'!H7="",'Price History'!H7=0),"",'Price History'!H8/'Price History'!H7-1) -> -0.0042747221 | I7: =IF(OR('Price History'!I8="",'Price History'!I7="",'Price History'!I7=0),"",'Price History'!I8/'Price History'!I7-1) -> -0.036646917 | ... Q7: =IF(OR('Price History'!Q8="",'Price History'!Q7="",'Price History'!Q7=0),"",'Price History'!Q8/'Price History'!Q7-1)
A8: ='Price History'!A9 -> 45191 | B8: =IF(OR('Price History'!B9="",'Price History'!B8="",'Price History'!B8=0),"",'Price History'!B9/'Price History'!B8-1) -> -0.03023313 | C8: =IF(OR('Price History'!C9="",'Price History'!C8="",'Price History'!C8=0),"",'Price History'!C9/'Price History'!C8-1) -> -0.023603291 | D8: =IF(OR('Price History'!D9="",'Price History'!D8="",'Price History'!D8=0),"",'Price History'!D9/'Price History'!D8-1) -> -0.016022525 | E8: =IF(OR('Price History'!E9="",'Price History'!E8="",'Price History'!E8=0),"",'Price History'!E9/'Price History'!E8-1) -> -0.026535165 | F8: =IF(OR('Price History'!F9="",'Price History'!F8="",'Price History'!F8=0),"",'Price History'!F9/'Price History'!F8-1) -> -0.017408124 | G8: =IF(OR('Price History'!G9="",'Price History'!G8="",'Price History'!G8=0),"",'Price History'!G9/'Price History'!G8-1) -> -0.0052840159 | H8: =IF(OR('Price History'!H9="",'Price History'!H8="",'Price History'!H8=0),"",'Price History'!H9/'Price History'!H8-1) -> -0.014310246 | I8: =IF(OR('Price History'!I9="",'Price History'!I8="",'Price History'!I8=0),"",'Price History'!I9/'Price History'!I8-1) -> -0.052164009 | ... Q8: =IF(OR('Price History'!Q9="",'Price History'!Q8="",'Price History'!Q8=0),"",'Price History'!Q9/'Price History'!Q8-1)
A9: ='Price History'!A10 -> 45198 | B9: =IF(OR('Price History'!B10="",'Price History'!B9="",'Price History'!B9=0),"",'Price History'!B10/'Price History'!B9-1) -> -0.0058490934 | C9: =IF(OR('Price History'!C10="",'Price History'!C9="",'Price History'!C9=0),"",'Price History'!C10/'Price History'!C9-1) -> 0.019738301 | D9: =IF(OR('Price History'!D10="",'Price History'!D9="",'Price History'!D9=0),"",'Price History'!D10/'Price History'!D9-1) -> 0.0026571283 | E9: =IF(OR('Price History'!E10="",'Price History'!E9="",'Price History'!E9=0),"",'Price History'!E10/'Price History'!E9-1) -> 0.0018091907 | F9: =IF(OR('Price History'!F10="",'Price History'!F9="",'Price History'!F9=0),"",'Price History'!F10/'Price History'!F9-1) -> 0.029773622 | G9: =IF(OR('Price History'!G10="",'Price History'!G9="",'Price History'!G9=0),"",'Price History'!G10/'Price History'!G9-1) -> 0.015272244 | H9: =IF(OR('Price History'!H10="",'Price History'!H9="",'Price History'!H9=0),"",'Price History'!H10/'Price History'!H9-1) -> -0.012340302 | I9: =IF(OR('Price History'!I10="",'Price History'!I9="",'Price History'!I9=0),"",'Price History'!I10/'Price History'!I9-1) -> 0.045421774 | ... Q9: =IF(OR('Price History'!Q10="",'Price History'!Q9="",'Price History'!Q9=0),"",'Price History'!Q10/'Price History'!Q9-1)
A10: ='Price History'!A11 -> 45205 | B10: =IF(OR('Price History'!B11="",'Price History'!B10="",'Price History'!B10=0),"",'Price History'!B11/'Price History'!B10-1) -> 0.032908413 | C10: =IF(OR('Price History'!C11="",'Price History'!C10="",'Price History'!C10=0),"",'Price History'!C11/'Price History'!C10-1) -> 0.055023923 | D10: =IF(OR('Price History'!D11="",'Price History'!D10="",'Price History'!D10=0),"",'Price History'!D11/'Price History'!D10-1) -> 0.014779329 | E10: =IF(OR('Price History'!E11="",'Price History'!E10="",'Price History'!E10=0),"",'Price History'!E11/'Price History'!E10-1) -> 0.01769805 | F10: =IF(OR('Price History'!F11="",'Price History'!F10="",'Price History'!F10=0),"",'Price History'!F11/'Price History'!F10-1) -> 0.055436081 | G10: =IF(OR('Price History'!G11="",'Price History'!G10="",'Price History'!G10=0),"",'Price History'!G11/'Price History'!G10-1) -> 0.020492697 | H10: =IF(OR('Price History'!H11="",'Price History'!H10="",'Price History'!H10=0),"",'Price History'!H11/'Price History'!H10-1) -> 0.028369837 | I10: =IF(OR('Price History'!I11="",'Price History'!I10="",'Price History'!I10=0),"",'Price History'!I11/'Price History'!I10-1) -> 0.051954023 | ... Q10: =IF(OR('Price History'!Q11="",'Price History'!Q10="",'Price History'!Q10=0),"",'Price History'!Q11/'Price History'!Q10-1)
A11: ='Price History'!A12 -> 45212 | B11: =IF(OR('Price History'!B12="",'Price History'!B11="",'Price History'!B11=0),"",'Price History'!B12/'Price History'!B11-1) -> 0.041922989 | C11: =IF(OR('Price History'!C12="",'Price History'!C11="",'Price History'!C11=0),"",'Price History'!C12/'Price History'!C11-1) -> -0.021645022 | D11: =IF(OR('Price History'!D12="",'Price History'!D11="",'Price History'!D11=0),"",'Price History'!D12/'Price History'!D11-1) -> 0.0040009375 | E11: =IF(OR('Price History'!E12="",'Price History'!E11="",'Price History'!E11=0),"",'Price History'!E12/'Price History'!E11-1) -> 0.044836153 | F11: =IF(OR('Price History'!F12="",'Price History'!F11="",'Price History'!F11=0),"",'Price History'!F12/'Price History'!F11-1) -> 0.05116595 | G11: =IF(OR('Price History'!G12="",'Price History'!G11="",'Price History'!G11=0),"",'Price History'!G12/'Price History'!G11-1) -> 0.039948729 | H11: =IF(OR('Price History'!H12="",'Price History'!H11="",'Price History'!H11=0),"",'Price History'!H12/'Price History'!H11-1) -> -0.010720412 | I11: =IF(OR('Price History'!I12="",'Price History'!I11="",'Price History'!I11=0),"",'Price History'!I12/'Price History'!I11-1) -> -0.0065559441 | ... Q11: =IF(OR('Price History'!Q12="",'Price History'!Q11="",'Price History'!Q11=0),"",'Price History'!Q12/'Price History'!Q11-1)
A12: ='Price History'!A13 -> 45219 | B12: =IF(OR('Price History'!B13="",'Price History'!B12="",'Price History'!B12=0),"",'Price History'!B13/'Price History'!B12-1) -> -0.014213864 | C12: =IF(OR('Price History'!C13="",'Price History'!C12="",'Price History'!C12=0),"",'Price History'!C13/'Price History'!C12-1) -> -0.019595449 | D12: =IF(OR('Price History'!D13="",'Price History'!D12="",'Price History'!D12=0),"",'Price History'!D13/'Price History'!D12-1) -> -0.032763652 | E12: =IF(OR('Price History'!E13="",'Price History'!E12="",'Price History'!E12=0),"",'Price History'!E13/'Price History'!E12-1) -> -0.033514493 | F12: =IF(OR('Price History'!F13="",'Price History'!F12="",'Price History'!F12=0),"",'Price History'!F13/'Price History'!F12-1) -> -0.03747577 | G12: =IF(OR('Price History'!G13="",'Price History'!G12="",'Price History'!G12=0),"",'Price History'!G13/'Price History'!G12-1) -> -0.050123254 | H12: =IF(OR('Price History'!H13="",'Price History'!H12="",'Price History'!H12=0),"",'Price History'!H13/'Price History'!H12-1) -> -0.02875307 | I12: =IF(OR('Price History'!I13="",'Price History'!I12="",'Price History'!I12=0),"",'Price History'!I13/'Price History'!I12-1) -> -0.089529256 | ... Q12: =IF(OR('Price History'!Q13="",'Price History'!Q12="",'Price History'!Q12=0),"",'Price History'!Q13/'Price History'!Q12-1)
A13: ='Price History'!A14 -> 45226 | B13: =IF(OR('Price History'!B14="",'Price History'!B13="",'Price History'!B13=0),"",'Price History'!B14/'Price History'!B13-1) -> -0.060706891 | C13: =IF(OR('Price History'!C14="",'Price History'!C13="",'Price History'!C13=0),"",'Price History'!C14/'Price History'!C13-1) -> -0.053298947 | D13: =IF(OR('Price History'!D14="",'Price History'!D13="",'Price History'!D13=0),"",'Price History'!D14/'Price History'!D13-1) -> 0.017066023 | E13: =IF(OR('Price History'!E14="",'Price History'!E13="",'Price History'!E13=0),"",'Price History'!E14/'Price History'!E13-1) -> -0.017806935 | F13: =IF(OR('Price History'!F14="",'Price History'!F13="",'Price History'!F13=0),"",'Price History'!F14/'Price History'!F13-1) -> -0.033117028 | G13: =IF(OR('Price History'!G14="",'Price History'!G13="",'Price History'!G13=0),"",'Price History'!G14/'Price History'!G13-1) -> -0.0097318339 | H13: =IF(OR('Price History'!H14="",'Price History'!H13="",'Price History'!H13=0),"",'Price History'!H14/'Price History'!H13-1) -> -0.023356144 | I13: =IF(OR('Price History'!I14="",'Price History'!I13="",'Price History'!I13=0),"",'Price History'!I14/'Price History'!I13-1) -> -0.021502778 | ... Q13: =IF(OR('Price History'!Q14="",'Price History'!Q13="",'Price History'!Q13=0),"",'Price History'!Q14/'Price History'!Q13-1)
A14: ='Price History'!A15 -> 45233 | B14: =IF(OR('Price History'!B15="",'Price History'!B14="",'Price History'!B14=0),"",'Price History'!B15/'Price History'!B14-1) -> 0.10930489 | C14: =IF(OR('Price History'!C15="",'Price History'!C14="",'Price History'!C14=0),"",'Price History'!C15/'Price History'!C14-1) -> 0.20590238 | D14: =IF(OR('Price History'!D15="",'Price History'!D14="",'Price History'!D14=0),"",'Price History'!D15/'Price History'!D14-1) -> 0.088830508 | E14: =IF(OR('Price History'!E15="",'Price History'!E14="",'Price History'!E14=0),"",'Price History'!E15/'Price History'!E14-1) -> 0.05283874 | F14: =IF(OR('Price History'!F15="",'Price History'!F14="",'Price History'!F14=0),"",'Price History'!F15/'Price History'!F14-1) -> 0.089099745 | G14: =IF(OR('Price History'!G15="",'Price History'!G14="",'Price History'!G14=0),"",'Price History'!G15/'Price History'!G14-1) -> 0.091067919 | H14: =IF(OR('Price History'!H15="",'Price History'!H14="",'Price History'!H14=0),"",'Price History'!H15/'Price History'!H14-1) -> 0.10555979 | I14: =IF(OR('Price History'!I15="",'Price History'!I14="",'Price History'!I14=0),"",'Price History'!I15/'Price History'!I14-1) -> 0.11135802 | ... Q14: =IF(OR('Price History'!Q15="",'Price History'!Q14="",'Price History'!Q14=0),"",'Price History'!Q15/'Price History'!Q14-1)
... A161: ='Price History'!A162 -> 0 | B161: =IF(OR('Price History'!B162="",'Price History'!B161="",'Price History'!B161=0),"",'Price History'!B162/'Price History'!B161-1) | C161: =IF(OR('Price History'!C162="",'Price History'!C161="",'Price History'!C161=0),"",'Price History'!C162/'Price History'!C161-1) | D161: =IF(OR('Price History'!D162="",'Price History'!D161="",'Price History'!D161=0),"",'Price History'!D162/'Price History'!D161-1) | E161: =IF(OR('Price History'!E162="",'Price History'!E161="",'Price History'!E161=0),"",'Price History'!E162/'Price History'!E161-1) | F161: =IF(OR('Price History'!F162="",'Price History'!F161="",'Price History'!F161=0),"",'Price History'!F162/'Price History'!F161-1) | G161: =IF(OR('Price History'!G162="",'Price History'!G161="",'Price History'!G161=0),"",'Price History'!G162/'Price History'!G161-1) | H161: =IF(OR('Price History'!H162="",'Price History'!H161="",'Price History'!H161=0),"",'Price History'!H162/'Price History'!H161-1) | I161: =IF(OR('Price History'!I162="",'Price History'!I161="",'Price History'!I161=0),"",'Price History'!I162/'Price History'!I161-1) | ... Q161: =IF(OR('Price History'!Q162="",'Price History'!Q161="",'Price History'!Q161=0),"",'Price History'!Q162/'Price History'!Q161-1)

Sheet Correlation Matrix
A1: Pairwise correlation of weekly returns, 12-36 month window (Rule 36, Part 7). Recalculate quarterly.
A2: Ticker | B2: ='Returns (Calc)'!B2 -> ADBE | C2: ='Returns (Calc)'!C2 -> ANET | D2: ='Returns (Calc)'!D2 -> ASML | E2: ='Returns (Calc)'!E2 -> AVGO | F2: ='Returns (Calc)'!F2 -> CRWD | G2: ='Returns (Calc)'!G2 -> KLAC | H2: ='Returns (Calc)'!H2 -> MU | I2: ='Returns (Calc)'!I2 -> NVDA | ... Q2: ='Returns (Calc)'!Q2 -> Ticker 16 | R2: Positions >0.70 with
A3: ='Returns (Calc)'!B2 -> ADBE | B3: 1 | C3: =IFERROR(ROUND(CORREL('Returns (Calc)'!$B$3:$B$161,'Returns (Calc)'!$C$3:$C$161),2),"") -> 0.22 | D3: =IFERROR(ROUND(CORREL('Returns (Calc)'!$B$3:$B$161,'Returns (Calc)'!$D$3:$D$161),2),"") -> 0.03 | E3: =IFERROR(ROUND(CORREL('Returns (Calc)'!$B$3:$B$161,'Returns (Calc)'!$E$3:$E$161),2),"") -> 0.16 | F3: =IFERROR(ROUND(CORREL('Returns (Calc)'!$B$3:$B$161,'Returns (Calc)'!$F$3:$F$161),2),"") -> 0.42 | G3: =IFERROR(ROUND(CORREL('Returns (Calc)'!$B$3:$B$161,'Returns (Calc)'!$G$3:$G$161),2),"") -> -0.03 | H3: =IFERROR(ROUND(CORREL('Returns (Calc)'!$B$3:$B$161,'Returns (Calc)'!$H$3:$H$161),2),"") -> 0.07 | I3: =IFERROR(ROUND(CORREL('Returns (Calc)'!$B$3:$B$161,'Returns (Calc)'!$I$3:$I$161),2),"") -> 0.23 | J3: =IFERROR(ROUND(CORREL('Returns (Calc)'!$B$3:$B$161,'Returns (Calc)'!$J$3:$J$161),2),"") -> 0.19 | K3: =IFERROR(ROUND(CORREL('Returns (Calc)'!$B$3:$B$161,'Returns (Calc)'!$K$3:$K$161),2),"") -> 0.36 | L3: =IFERROR(ROUND(CORREL('Returns (Calc)'!$B$3:$B$161,'Returns (Calc)'!$L$3:$L$161),2),"") -> 0.17 | M3: =IFERROR(ROUND(CORREL('Returns (Calc)'!$B$3:$B$161,'Returns (Calc)'!$M$3:$M$161),2),"") -> 0.08 | N3: =IFERROR(ROUND(CORREL('Returns (Calc)'!$B$3:$B$161,'Returns (Calc)'!$N$3:$N$161),2),"") -> 0.13 | O3: =IFERROR(ROUND(CORREL('Returns (Calc)'!$B$3:$B$161,'Returns (Calc)'!$O$3:$O$161),2),"") | P3: =IFERROR(ROUND(CORREL('Returns (Calc)'!$B$3:$B$161,'Returns (Calc)'!$P$3:$P$161),2),"") | Q3: =IFERROR(ROUND(CORREL('Returns (Calc)'!$B$3:$B$161,'Returns (Calc)'!$Q$3:$Q$161),2),"") | R3: =COUNTIF(B3:Q3,">0.7")-1 -> 0
A4: ='Returns (Calc)'!C2 -> ANET | B4: =IFERROR(ROUND(CORREL('Returns (Calc)'!$C$3:$C$161,'Returns (Calc)'!$B$3:$B$161),2),"") -> 0.22 | C4: 1 | D4: =IFERROR(ROUND(CORREL('Returns (Calc)'!$C$3:$C$161,'Returns (Calc)'!$D$3:$D$161),2),"") -> 0.39 | E4: =IFERROR(ROUND(CORREL('Returns (Calc)'!$C$3:$C$161,'Returns (Calc)'!$E$3:$E$161),2),"") -> 0.59 | F4: =IFERROR(ROUND(CORREL('Returns (Calc)'!$C$3:$C$161,'Returns (Calc)'!$F$3:$F$161),2),"") -> 0.38 | G4: =IFERROR(ROUND(CORREL('Returns (Calc)'!$C$3:$C$161,'Returns (Calc)'!$G$3:$G$161),2),"") -> 0.44 | H4: =IFERROR(ROUND(CORREL('Returns (Calc)'!$C$3:$C$161,'Returns (Calc)'!$H$3:$H$161),2),"") -> 0.35 | I4: =IFERROR(ROUND(CORREL('Returns (Calc)'!$C$3:$C$161,'Returns (Calc)'!$I$3:$I$161),2),"") -> 0.53 | J4: =IFERROR(ROUND(CORREL('Returns (Calc)'!$C$3:$C$161,'Returns (Calc)'!$J$3:$J$161),2),"") -> 0.19 | K4: =IFERROR(ROUND(CORREL('Returns (Calc)'!$C$3:$C$161,'Returns (Calc)'!$K$3:$K$161),2),"") -> 0.34 | L4: =IFERROR(ROUND(CORREL('Returns (Calc)'!$C$3:$C$161,'Returns (Calc)'!$L$3:$L$161),2),"") -> 0.55 | M4: =IFERROR(ROUND(CORREL('Returns (Calc)'!$C$3:$C$161,'Returns (Calc)'!$M$3:$M$161),2),"") -> 0.59 | N4: =IFERROR(ROUND(CORREL('Returns (Calc)'!$C$3:$C$161,'Returns (Calc)'!$N$3:$N$161),2),"") -> 0.05 | O4: =IFERROR(ROUND(CORREL('Returns (Calc)'!$C$3:$C$161,'Returns (Calc)'!$O$3:$O$161),2),"") | P4: =IFERROR(ROUND(CORREL('Returns (Calc)'!$C$3:$C$161,'Returns (Calc)'!$P$3:$P$161),2),"") | Q4: =IFERROR(ROUND(CORREL('Returns (Calc)'!$C$3:$C$161,'Returns (Calc)'!$Q$3:$Q$161),2),"") | R4: =COUNTIF(B4:Q4,">0.7")-1 -> 0
A5: ='Returns (Calc)'!D2 -> ASML | B5: =IFERROR(ROUND(CORREL('Returns (Calc)'!$D$3:$D$161,'Returns (Calc)'!$B$3:$B$161),2),"") -> 0.03 | C5: =IFERROR(ROUND(CORREL('Returns (Calc)'!$D$3:$D$161,'Returns (Calc)'!$C$3:$C$161),2),"") -> 0.39 | D5: 1 | E5: =IFERROR(ROUND(CORREL('Returns (Calc)'!$D$3:$D$161,'Returns (Calc)'!$E$3:$E$161),2),"") -> 0.5 | F5: =IFERROR(ROUND(CORREL('Returns (Calc)'!$D$3:$D$161,'Returns (Calc)'!$F$3:$F$161),2),"") -> 0.33 | G5: =IFERROR(ROUND(CORREL('Returns (Calc)'!$D$3:$D$161,'Returns (Calc)'!$G$3:$G$161),2),"") -> 0.77 | H5: =IFERROR(ROUND(CORREL('Returns (Calc)'!$D$3:$D$161,'Returns (Calc)'!$H$3:$H$161),2),"") -> 0.6 | I5: =IFERROR(ROUND(CORREL('Returns (Calc)'!$D$3:$D$161,'Returns (Calc)'!$I$3:$I$161),2),"") -> 0.48 | J5: =IFERROR(ROUND(CORREL('Returns (Calc)'!$D$3:$D$161,'Returns (Calc)'!$J$3:$J$161),2),"") -> 0.29 | K5: =IFERROR(ROUND(CORREL('Returns (Calc)'!$D$3:$D$161,'Returns (Calc)'!$K$3:$K$161),2),"") -> 0.2 | L5: =IFERROR(ROUND(CORREL('Returns (Calc)'!$D$3:$D$161,'Returns (Calc)'!$L$3:$L$161),2),"") -> 0.63 | M5: =IFERROR(ROUND(CORREL('Returns (Calc)'!$D$3:$D$161,'Returns (Calc)'!$M$3:$M$161),2),"") -> 0.41 | N5: =IFERROR(ROUND(CORREL('Returns (Calc)'!$D$3:$D$161,'Returns (Calc)'!$N$3:$N$161),2),"") -> 0.12 | O5: =IFERROR(ROUND(CORREL('Returns (Calc)'!$D$3:$D$161,'Returns (Calc)'!$O$3:$O$161),2),"") | P5: =IFERROR(ROUND(CORREL('Returns (Calc)'!$D$3:$D$161,'Returns (Calc)'!$P$3:$P$161),2),"") | Q5: =IFERROR(ROUND(CORREL('Returns (Calc)'!$D$3:$D$161,'Returns (Calc)'!$Q$3:$Q$161),2),"") | R5: =COUNTIF(B5:Q5,">0.7")-1 -> 1
A6: ='Returns (Calc)'!E2 -> AVGO | B6: =IFERROR(ROUND(CORREL('Returns (Calc)'!$E$3:$E$161,'Returns (Calc)'!$B$3:$B$161),2),"") -> 0.16 | C6: =IFERROR(ROUND(CORREL('Returns (Calc)'!$E$3:$E$161,'Returns (Calc)'!$C$3:$C$161),2),"") -> 0.59 | D6: =IFERROR(ROUND(CORREL('Returns (Calc)'!$E$3:$E$161,'Returns (Calc)'!$D$3:$D$161),2),"") -> 0.5 | E6: 1 | F6: =IFERROR(ROUND(CORREL('Returns (Calc)'!$E$3:$E$161,'Returns (Calc)'!$F$3:$F$161),2),"") -> 0.4 | G6: =IFERROR(ROUND(CORREL('Returns (Calc)'!$E$3:$E$161,'Returns (Calc)'!$G$3:$G$161),2),"") -> 0.54 | H6: =IFERROR(ROUND(CORREL('Returns (Calc)'!$E$3:$E$161,'Returns (Calc)'!$H$3:$H$161),2),"") -> 0.5 | I6: =IFERROR(ROUND(CORREL('Returns (Calc)'!$E$3:$E$161,'Returns (Calc)'!$I$3:$I$161),2),"") -> 0.62 | J6: =IFERROR(ROUND(CORREL('Returns (Calc)'!$E$3:$E$161,'Returns (Calc)'!$J$3:$J$161),2),"") -> 0.23 | K6: =IFERROR(ROUND(CORREL('Returns (Calc)'!$E$3:$E$161,'Returns (Calc)'!$K$3:$K$161),2),"") -> 0.37 | L6: =IFERROR(ROUND(CORREL('Returns (Calc)'!$E$3:$E$161,'Returns (Calc)'!$L$3:$L$161),2),"") -> 0.63 | M6: =IFERROR(ROUND(CORREL('Returns (Calc)'!$E$3:$E$161,'Returns (Calc)'!$M$3:$M$161),2),"") -> 0.53 | N6: =IFERROR(ROUND(CORREL('Returns (Calc)'!$E$3:$E$161,'Returns (Calc)'!$N$3:$N$161),2),"") -> 0.16 | O6: =IFERROR(ROUND(CORREL('Returns (Calc)'!$E$3:$E$161,'Returns (Calc)'!$O$3:$O$161),2),"") | P6: =IFERROR(ROUND(CORREL('Returns (Calc)'!$E$3:$E$161,'Returns (Calc)'!$P$3:$P$161),2),"") | Q6: =IFERROR(ROUND(CORREL('Returns (Calc)'!$E$3:$E$161,'Returns (Calc)'!$Q$3:$Q$161),2),"") | R6: =COUNTIF(B6:Q6,">0.7")-1 -> 0
A7: ='Returns (Calc)'!F2 -> CRWD | B7: =IFERROR(ROUND(CORREL('Returns (Calc)'!$F$3:$F$161,'Returns (Calc)'!$B$3:$B$161),2),"") -> 0.42 | C7: =IFERROR(ROUND(CORREL('Returns (Calc)'!$F$3:$F$161,'Returns (Calc)'!$C$3:$C$161),2),"") -> 0.38 | D7: =IFERROR(ROUND(CORREL('Returns (Calc)'!$F$3:$F$161,'Returns (Calc)'!$D$3:$D$161),2),"") -> 0.33 | E7: =IFERROR(ROUND(CORREL('Returns (Calc)'!$F$3:$F$161,'Returns (Calc)'!$E$3:$E$161),2),"") -> 0.4 | F7: 1 | G7: =IFERROR(ROUND(CORREL('Returns (Calc)'!$F$3:$F$161,'Returns (Calc)'!$G$3:$G$161),2),"") -> 0.34 | H7: =IFERROR(ROUND(CORREL('Returns (Calc)'!$F$3:$F$161,'Returns (Calc)'!$H$3:$H$161),2),"") -> 0.34 | I7: =IFERROR(ROUND(CORREL('Returns (Calc)'!$F$3:$F$161,'Returns (Calc)'!$I$3:$I$161),2),"") -> 0.45 | J7: =IFERROR(ROUND(CORREL('Returns (Calc)'!$F$3:$F$161,'Returns (Calc)'!$J$3:$J$161),2),"") -> 0.12 | K7: =IFERROR(ROUND(CORREL('Returns (Calc)'!$F$3:$F$161,'Returns (Calc)'!$K$3:$K$161),2),"") -> 0.5 | L7: =IFERROR(ROUND(CORREL('Returns (Calc)'!$F$3:$F$161,'Returns (Calc)'!$L$3:$L$161),2),"") -> 0.39 | M7: =IFERROR(ROUND(CORREL('Returns (Calc)'!$F$3:$F$161,'Returns (Calc)'!$M$3:$M$161),2),"") -> 0.41 | N7: =IFERROR(ROUND(CORREL('Returns (Calc)'!$F$3:$F$161,'Returns (Calc)'!$N$3:$N$161),2),"") -> 0.21 | O7: =IFERROR(ROUND(CORREL('Returns (Calc)'!$F$3:$F$161,'Returns (Calc)'!$O$3:$O$161),2),"") | P7: =IFERROR(ROUND(CORREL('Returns (Calc)'!$F$3:$F$161,'Returns (Calc)'!$P$3:$P$161),2),"") | Q7: =IFERROR(ROUND(CORREL('Returns (Calc)'!$F$3:$F$161,'Returns (Calc)'!$Q$3:$Q$161),2),"") | R7: =COUNTIF(B7:Q7,">0.7")-1 -> 0
A8: ='Returns (Calc)'!G2 -> KLAC | B8: =IFERROR(ROUND(CORREL('Returns (Calc)'!$G$3:$G$161,'Returns (Calc)'!$B$3:$B$161),2),"") -> -0.03 | C8: =IFERROR(ROUND(CORREL('Returns (Calc)'!$G$3:$G$161,'Returns (Calc)'!$C$3:$C$161),2),"") -> 0.44 | D8: =IFERROR(ROUND(CORREL('Returns (Calc)'!$G$3:$G$161,'Returns (Calc)'!$D$3:$D$161),2),"") -> 0.77 | E8: =IFERROR(ROUND(CORREL('Returns (Calc)'!$G$3:$G$161,'Returns (Calc)'!$E$3:$E$161),2),"") -> 0.54 | F8: =IFERROR(ROUND(CORREL('Returns (Calc)'!$G$3:$G$161,'Returns (Calc)'!$F$3:$F$161),2),"") -> 0.34 | G8: 1 | H8: =IFERROR(ROUND(CORREL('Returns (Calc)'!$G$3:$G$161,'Returns (Calc)'!$H$3:$H$161),2),"") -> 0.6 | I8: =IFERROR(ROUND(CORREL('Returns (Calc)'!$G$3:$G$161,'Returns (Calc)'!$I$3:$I$161),2),"") -> 0.51 | J8: =IFERROR(ROUND(CORREL('Returns (Calc)'!$G$3:$G$161,'Returns (Calc)'!$J$3:$J$161),2),"") -> 0.29 | K8: =IFERROR(ROUND(CORREL('Returns (Calc)'!$G$3:$G$161,'Returns (Calc)'!$K$3:$K$161),2),"") -> 0.24 | L8: =IFERROR(ROUND(CORREL('Returns (Calc)'!$G$3:$G$161,'Returns (Calc)'!$L$3:$L$161),2),"") -> 0.61 | M8: =IFERROR(ROUND(CORREL('Returns (Calc)'!$G$3:$G$161,'Returns (Calc)'!$M$3:$M$161),2),"") -> 0.49 | N8: =IFERROR(ROUND(CORREL('Returns (Calc)'!$G$3:$G$161,'Returns (Calc)'!$N$3:$N$161),2),"") -> 0.18 | O8: =IFERROR(ROUND(CORREL('Returns (Calc)'!$G$3:$G$161,'Returns (Calc)'!$O$3:$O$161),2),"") | P8: =IFERROR(ROUND(CORREL('Returns (Calc)'!$G$3:$G$161,'Returns (Calc)'!$P$3:$P$161),2),"") | Q8: =IFERROR(ROUND(CORREL('Returns (Calc)'!$G$3:$G$161,'Returns (Calc)'!$Q$3:$Q$161),2),"") | R8: =COUNTIF(B8:Q8,">0.7")-1 -> 1
A9: ='Returns (Calc)'!H2 -> MU | B9: =IFERROR(ROUND(CORREL('Returns (Calc)'!$H$3:$H$161,'Returns (Calc)'!$B$3:$B$161),2),"") -> 0.07 | C9: =IFERROR(ROUND(CORREL('Returns (Calc)'!$H$3:$H$161,'Returns (Calc)'!$C$3:$C$161),2),"") -> 0.35 | D9: =IFERROR(ROUND(CORREL('Returns (Calc)'!$H$3:$H$161,'Returns (Calc)'!$D$3:$D$161),2),"") -> 0.6 | E9: =IFERROR(ROUND(CORREL('Returns (Calc)'!$H$3:$H$161,'Returns (Calc)'!$E$3:$E$161),2),"") -> 0.5 | F9: =IFERROR(ROUND(CORREL('Returns (Calc)'!$H$3:$H$161,'Returns (Calc)'!$F$3:$F$161),2),"") -> 0.34 | G9: =IFERROR(ROUND(CORREL('Returns (Calc)'!$H$3:$H$161,'Returns (Calc)'!$G$3:$G$161),2),"") -> 0.6 | H9: 1 | I9: =IFERROR(ROUND(CORREL('Returns (Calc)'!$H$3:$H$161,'Returns (Calc)'!$I$3:$I$161),2),"") -> 0.5 | J9: =IFERROR(ROUND(CORREL('Returns (Calc)'!$H$3:$H$161,'Returns (Calc)'!$J$3:$J$161),2),"") -> 0.21 | K9: =IFERROR(ROUND(CORREL('Returns (Calc)'!$H$3:$H$161,'Returns (Calc)'!$K$3:$K$161),2),"") -> 0.17 | L9: =IFERROR(ROUND(CORREL('Returns (Calc)'!$H$3:$H$161,'Returns (Calc)'!$L$3:$L$161),2),"") -> 0.55 | M9: =IFERROR(ROUND(CORREL('Returns (Calc)'!$H$3:$H$161,'Returns (Calc)'!$M$3:$M$161),2),"") -> 0.49 | N9: =IFERROR(ROUND(CORREL('Returns (Calc)'!$H$3:$H$161,'Returns (Calc)'!$N$3:$N$161),2),"") -> 0.18 | O9: =IFERROR(ROUND(CORREL('Returns (Calc)'!$H$3:$H$161,'Returns (Calc)'!$O$3:$O$161),2),"") | P9: =IFERROR(ROUND(CORREL('Returns (Calc)'!$H$3:$H$161,'Returns (Calc)'!$P$3:$P$161),2),"") | Q9: =IFERROR(ROUND(CORREL('Returns (Calc)'!$H$3:$H$161,'Returns (Calc)'!$Q$3:$Q$161),2),"") | R9: =COUNTIF(B9:Q9,">0.7")-1 -> 0
A10: ='Returns (Calc)'!I2 -> NVDA | B10: =IFERROR(ROUND(CORREL('Returns (Calc)'!$I$3:$I$161,'Returns (Calc)'!$B$3:$B$161),2),"") -> 0.23 | C10: =IFERROR(ROUND(CORREL('Returns (Calc)'!$I$3:$I$161,'Returns (Calc)'!$C$3:$C$161),2),"") -> 0.53 | D10: =IFERROR(ROUND(CORREL('Returns (Calc)'!$I$3:$I$161,'Returns (Calc)'!$D$3:$D$161),2),"") -> 0.48 | E10: =IFERROR(ROUND(CORREL('Returns (Calc)'!$I$3:$I$161,'Returns (Calc)'!$E$3:$E$161),2),"") -> 0.62 | F10: =IFERROR(ROUND(CORREL('Returns (Calc)'!$I$3:$I$161,'Returns (Calc)'!$F$3:$F$161),2),"") -> 0.45 | G10: =IFERROR(ROUND(CORREL('Returns (Calc)'!$I$3:$I$161,'Returns (Calc)'!$G$3:$G$161),2),"") -> 0.51 | H10: =IFERROR(ROUND(CORREL('Returns (Calc)'!$I$3:$I$161,'Returns (Calc)'!$H$3:$H$161),2),"") -> 0.5 | I10: 1 | J10: =IFERROR(ROUND(CORREL('Returns (Calc)'!$I$3:$I$161,'Returns (Calc)'!$J$3:$J$161),2),"") -> 0.19 | K10: =IFERROR(ROUND(CORREL('Returns (Calc)'!$I$3:$I$161,'Returns (Calc)'!$K$3:$K$161),2),"") -> 0.44 | L10: =IFERROR(ROUND(CORREL('Returns (Calc)'!$I$3:$I$161,'Returns (Calc)'!$L$3:$L$161),2),"") -> 0.64 | M10: =IFERROR(ROUND(CORREL('Returns (Calc)'!$I$3:$I$161,'Returns (Calc)'!$M$3:$M$161),2),"") -> 0.65 | N10: =IFERROR(ROUND(CORREL('Returns (Calc)'!$I$3:$I$161,'Returns (Calc)'!$N$3:$N$161),2),"") -> 0.14 | O10: =IFERROR(ROUND(CORREL('Returns (Calc)'!$I$3:$I$161,'Returns (Calc)'!$O$3:$O$161),2),"") | P10: =IFERROR(ROUND(CORREL('Returns (Calc)'!$I$3:$I$161,'Returns (Calc)'!$P$3:$P$161),2),"") | Q10: =IFERROR(ROUND(CORREL('Returns (Calc)'!$I$3:$I$161,'Returns (Calc)'!$Q$3:$Q$161),2),"") | R10: =COUNTIF(B10:Q10,">0.7")-1 -> 0
A11: ='Returns (Calc)'!J2 -> PLD | B11: =IFERROR(ROUND(CORREL('Returns (Calc)'!$J$3:$J$161,'Returns (Calc)'!$B$3:$B$161),2),"") -> 0.19 | C11: =IFERROR(ROUND(CORREL('Returns (Calc)'!$J$3:$J$161,'Returns (Calc)'!$C$3:$C$161),2),"") -> 0.19 | D11: =IFERROR(ROUND(CORREL('Returns (Calc)'!$J$3:$J$161,'Returns (Calc)'!$D$3:$D$161),2),"") -> 0.29 | E11: =IFERROR(ROUND(CORREL('Returns (Calc)'!$J$3:$J$161,'Returns (Calc)'!$E$3:$E$161),2),"") -> 0.23 | F11: =IFERROR(ROUND(CORREL('Returns (Calc)'!$J$3:$J$161,'Returns (Calc)'!$F$3:$F$161),2),"") -> 0.12 | G11: =IFERROR(ROUND(CORREL('Returns (Calc)'!$J$3:$J$161,'Returns (Calc)'!$G$3:$G$161),2),"") -> 0.29 | H11: =IFERROR(ROUND(CORREL('Returns (Calc)'!$J$3:$J$161,'Returns (Calc)'!$H$3:$H$161),2),"") -> 0.21 | I11: =IFERROR(ROUND(CORREL('Returns (Calc)'!$J$3:$J$161,'Returns (Calc)'!$I$3:$I$161),2),"") -> 0.19 | J11: 1 | K11: =IFERROR(ROUND(CORREL('Returns (Calc)'!$J$3:$J$161,'Returns (Calc)'!$K$3:$K$161),2),"") -> 0.16 | L11: =IFERROR(ROUND(CORREL('Returns (Calc)'!$J$3:$J$161,'Returns (Calc)'!$L$3:$L$161),2),"") -> 0.22 | M11: =IFERROR(ROUND(CORREL('Returns (Calc)'!$J$3:$J$161,'Returns (Calc)'!$M$3:$M$161),2),"") -> 0.16 | N11: =IFERROR(ROUND(CORREL('Returns (Calc)'!$J$3:$J$161,'Returns (Calc)'!$N$3:$N$161),2),"") -> 0.26 | O11: =IFERROR(ROUND(CORREL('Returns (Calc)'!$J$3:$J$161,'Returns (Calc)'!$O$3:$O$161),2),"") | P11: =IFERROR(ROUND(CORREL('Returns (Calc)'!$J$3:$J$161,'Returns (Calc)'!$P$3:$P$161),2),"") | Q11: =IFERROR(ROUND(CORREL('Returns (Calc)'!$J$3:$J$161,'Returns (Calc)'!$Q$3:$Q$161),2),"") | R11: =COUNTIF(B11:Q11,">0.7")-1 -> 0
A12: ='Returns (Calc)'!K2 -> PLTR | B12: =IFERROR(ROUND(CORREL('Returns (Calc)'!$K$3:$K$161,'Returns (Calc)'!$B$3:$B$161),2),"") -> 0.36 | C12: =IFERROR(ROUND(CORREL('Returns (Calc)'!$K$3:$K$161,'Returns (Calc)'!$C$3:$C$161),2),"") -> 0.34 | D12: =IFERROR(ROUND(CORREL('Returns (Calc)'!$K$3:$K$161,'Returns (Calc)'!$D$3:$D$161),2),"") -> 0.2 | E12: =IFERROR(ROUND(CORREL('Returns (Calc)'!$K$3:$K$161,'Returns (Calc)'!$E$3:$E$161),2),"") -> 0.37 | F12: =IFERROR(ROUND(CORREL('Returns (Calc)'!$K$3:$K$161,'Returns (Calc)'!$F$3:$F$161),2),"") -> 0.5 | G12: =IFERROR(ROUND(CORREL('Returns (Calc)'!$K$3:$K$161,'Returns (Calc)'!$G$3:$G$161),2),"") -> 0.24 | H12: =IFERROR(ROUND(CORREL('Returns (Calc)'!$K$3:$K$161,'Returns (Calc)'!$H$3:$H$161),2),"") -> 0.17 | I12: =IFERROR(ROUND(CORREL('Returns (Calc)'!$K$3:$K$161,'Returns (Calc)'!$I$3:$I$161),2),"") -> 0.44 | J12: =IFERROR(ROUND(CORREL('Returns (Calc)'!$K$3:$K$161,'Returns (Calc)'!$J$3:$J$161),2),"") -> 0.16 | K12: 1 | L12: =IFERROR(ROUND(CORREL('Returns (Calc)'!$K$3:$K$161,'Returns (Calc)'!$L$3:$L$161),2),"") -> 0.39 | M12: =IFERROR(ROUND(CORREL('Returns (Calc)'!$K$3:$K$161,'Returns (Calc)'!$M$3:$M$161),2),"") -> 0.32 | N12: =IFERROR(ROUND(CORREL('Returns (Calc)'!$K$3:$K$161,'Returns (Calc)'!$N$3:$N$161),2),"") -> 0.05 | O12: =IFERROR(ROUND(CORREL('Returns (Calc)'!$K$3:$K$161,'Returns (Calc)'!$O$3:$O$161),2),"") | P12: =IFERROR(ROUND(CORREL('Returns (Calc)'!$K$3:$K$161,'Returns (Calc)'!$P$3:$P$161),2),"") | Q12: =IFERROR(ROUND(CORREL('Returns (Calc)'!$K$3:$K$161,'Returns (Calc)'!$Q$3:$Q$161),2),"") | R12: =COUNTIF(B12:Q12,">0.7")-1 -> 0
A13: ='Returns (Calc)'!L2 -> TSM | B13: =IFERROR(ROUND(CORREL('Returns (Calc)'!$L$3:$L$161,'Returns (Calc)'!$B$3:$B$161),2),"") -> 0.17 | C13: =IFERROR(ROUND(CORREL('Returns (Calc)'!$L$3:$L$161,'Returns (Calc)'!$C$3:$C$161),2),"") -> 0.55 | D13: =IFERROR(ROUND(CORREL('Returns (Calc)'!$L$3:$L$161,'Returns (Calc)'!$D$3:$D$161),2),"") -> 0.63 | E13: =IFERROR(ROUND(CORREL('Returns (Calc)'!$L$3:$L$161,'Returns (Calc)'!$E$3:$E$161),2),"") -> 0.63 | F13: =IFERROR(ROUND(CORREL('Returns (Calc)'!$L$3:$L$161,'Returns (Calc)'!$F$3:$F$161),2),"") -> 0.39 | G13: =IFERROR(ROUND(CORREL('Returns (Calc)'!$L$3:$L$161,'Returns (Calc)'!$G$3:$G$161),2),"") -> 0.61 | H13: =IFERROR(ROUND(CORREL('Returns (Calc)'!$L$3:$L$161,'Returns (Calc)'!$H$3:$H$161),2),"") -> 0.55 | I13: =IFERROR(ROUND(CORREL('Returns (Calc)'!$L$3:$L$161,'Returns (Calc)'!$I$3:$I$161),2),"") -> 0.64 | J13: =IFERROR(ROUND(CORREL('Returns (Calc)'!$L$3:$L$161,'Returns (Calc)'!$J$3:$J$161),2),"") -> 0.22 | K13: =IFERROR(ROUND(CORREL('Returns (Calc)'!$L$3:$L$161,'Returns (Calc)'!$K$3:$K$161),2),"") -> 0.39 | L13: 1 | M13: =IFERROR(ROUND(CORREL('Returns (Calc)'!$L$3:$L$161,'Returns (Calc)'!$M$3:$M$161),2),"") -> 0.6 | N13: =IFERROR(ROUND(CORREL('Returns (Calc)'!$L$3:$L$161,'Returns (Calc)'!$N$3:$N$161),2),"") -> 0.16 | O13: =IFERROR(ROUND(CORREL('Returns (Calc)'!$L$3:$L$161,'Returns (Calc)'!$O$3:$O$161),2),"") | P13: =IFERROR(ROUND(CORREL('Returns (Calc)'!$L$3:$L$161,'Returns (Calc)'!$P$3:$P$161),2),"") | Q13: =IFERROR(ROUND(CORREL('Returns (Calc)'!$L$3:$L$161,'Returns (Calc)'!$Q$3:$Q$161),2),"") | R13: =COUNTIF(B13:Q13,">0.7")-1 -> 0
A14: ='Returns (Calc)'!M2 -> VRT | B14: =IFERROR(ROUND(CORREL('Returns (Calc)'!$M$3:$M$161,'Returns (Calc)'!$B$3:$B$161),2),"") -> 0.08 | C14: =IFERROR(ROUND(CORREL('Returns (Calc)'!$M$3:$M$161,'Returns (Calc)'!$C$3:$C$161),2),"") -> 0.59 | D14: =IFERROR(ROUND(CORREL('Returns (Calc)'!$M$3:$M$161,'Returns (Calc)'!$D$3:$D$161),2),"") -> 0.41 | E14: =IFERROR(ROUND(CORREL('Returns (Calc)'!$M$3:$M$161,'Returns (Calc)'!$E$3:$E$161),2),"") -> 0.53 | F14: =IFERROR(ROUND(CORREL('Returns (Calc)'!$M$3:$M$161,'Returns (Calc)'!$F$3:$F$161),2),"") -> 0.41 | G14: =IFERROR(ROUND(CORREL('Returns (Calc)'!$M$3:$M$161,'Returns (Calc)'!$G$3:$G$161),2),"") -> 0.49 | H14: =IFERROR(ROUND(CORREL('Returns (Calc)'!$M$3:$M$161,'Returns (Calc)'!$H$3:$H$161),2),"") -> 0.49 | I14: =IFERROR(ROUND(CORREL('Returns (Calc)'!$M$3:$M$161,'Returns (Calc)'!$I$3:$I$161),2),"") -> 0.65 | J14: =IFERROR(ROUND(CORREL('Returns (Calc)'!$M$3:$M$161,'Returns (Calc)'!$J$3:$J$161),2),"") -> 0.16 | K14: =IFERROR(ROUND(CORREL('Returns (Calc)'!$M$3:$M$161,'Returns (Calc)'!$K$3:$K$161),2),"") -> 0.32 | L14: =IFERROR(ROUND(CORREL('Returns (Calc)'!$M$3:$M$161,'Returns (Calc)'!$L$3:$L$161),2),"") -> 0.6 | M14: 1 | N14: =IFERROR(ROUND(CORREL('Returns (Calc)'!$M$3:$M$161,'Returns (Calc)'!$N$3:$N$161),2),"") -> 0.12 | O14: =IFERROR(ROUND(CORREL('Returns (Calc)'!$M$3:$M$161,'Returns (Calc)'!$O$3:$O$161),2),"") | P14: =IFERROR(ROUND(CORREL('Returns (Calc)'!$M$3:$M$161,'Returns (Calc)'!$P$3:$P$161),2),"") | Q14: =IFERROR(ROUND(CORREL('Returns (Calc)'!$M$3:$M$161,'Returns (Calc)'!$Q$3:$Q$161),2),"") | R14: =COUNTIF(B14:Q14,">0.7")-1 -> 0
A15: ='Returns (Calc)'!N2 -> VRTX | B15: =IFERROR(ROUND(CORREL('Returns (Calc)'!$N$3:$N$161,'Returns (Calc)'!$B$3:$B$161),2),"") -> 0.13 | C15: =IFERROR(ROUND(CORREL('Returns (Calc)'!$N$3:$N$161,'Returns (Calc)'!$C$3:$C$161),2),"") -> 0.05 | D15: =IFERROR(ROUND(CORREL('Returns (Calc)'!$N$3:$N$161,'Returns (Calc)'!$D$3:$D$161),2),"") -> 0.12 | E15: =IFERROR(ROUND(CORREL('Returns (Calc)'!$N$3:$N$161,'Returns (Calc)'!$E$3:$E$161),2),"") -> 0.16 | F15: =IFERROR(ROUND(CORREL('Returns (Calc)'!$N$3:$N$161,'Returns (Calc)'!$F$3:$F$161),2),"") -> 0.21 | G15: =IFERROR(ROUND(CORREL('Returns (Calc)'!$N$3:$N$161,'Returns (Calc)'!$G$3:$G$161),2),"") -> 0.18 | H15: =IFERROR(ROUND(CORREL('Returns (Calc)'!$N$3:$N$161,'Returns (Calc)'!$H$3:$H$161),2),"") -> 0.18 | I15: =IFERROR(ROUND(CORREL('Returns (Calc)'!$N$3:$N$161,'Returns (Calc)'!$I$3:$I$161),2),"") -> 0.14 | J15: =IFERROR(ROUND(CORREL('Returns (Calc)'!$N$3:$N$161,'Returns (Calc)'!$J$3:$J$161),2),"") -> 0.26 | K15: =IFERROR(ROUND(CORREL('Returns (Calc)'!$N$3:$N$161,'Returns (Calc)'!$K$3:$K$161),2),"") -> 0.05 | L15: =IFERROR(ROUND(CORREL('Returns (Calc)'!$N$3:$N$161,'Returns (Calc)'!$L$3:$L$161),2),"") -> 0.16 | M15: =IFERROR(ROUND(CORREL('Returns (Calc)'!$N$3:$N$161,'Returns (Calc)'!$M$3:$M$161),2),"") -> 0.12 | N15: 1 | O15: =IFERROR(ROUND(CORREL('Returns (Calc)'!$N$3:$N$161,'Returns (Calc)'!$O$3:$O$161),2),"") | P15: =IFERROR(ROUND(CORREL('Returns (Calc)'!$N$3:$N$161,'Returns (Calc)'!$P$3:$P$161),2),"") | Q15: =IFERROR(ROUND(CORREL('Returns (Calc)'!$N$3:$N$161,'Returns (Calc)'!$Q$3:$Q$161),2),"") | R15: =COUNTIF(B15:Q15,">0.7")-1 -> 0
A16: ='Returns (Calc)'!O2 -> Ticker 14 | B16: =IFERROR(ROUND(CORREL('Returns (Calc)'!$O$3:$O$161,'Returns (Calc)'!$B$3:$B$161),2),"") | C16: =IFERROR(ROUND(CORREL('Returns (Calc)'!$O$3:$O$161,'Returns (Calc)'!$C$3:$C$161),2),"") | D16: =IFERROR(ROUND(CORREL('Returns (Calc)'!$O$3:$O$161,'Returns (Calc)'!$D$3:$D$161),2),"") | E16: =IFERROR(ROUND(CORREL('Returns (Calc)'!$O$3:$O$161,'Returns (Calc)'!$E$3:$E$161),2),"") | F16: =IFERROR(ROUND(CORREL('Returns (Calc)'!$O$3:$O$161,'Returns (Calc)'!$F$3:$F$161),2),"") | G16: =IFERROR(ROUND(CORREL('Returns (Calc)'!$O$3:$O$161,'Returns (Calc)'!$G$3:$G$161),2),"") | H16: =IFERROR(ROUND(CORREL('Returns (Calc)'!$O$3:$O$161,'Returns (Calc)'!$H$3:$H$161),2),"") | I16: =IFERROR(ROUND(CORREL('Returns (Calc)'!$O$3:$O$161,'Returns (Calc)'!$I$3:$I$161),2),"") | J16: =IFERROR(ROUND(CORREL('Returns (Calc)'!$O$3:$O$161,'Returns (Calc)'!$J$3:$J$161),2),"") | K16: =IFERROR(ROUND(CORREL('Returns (Calc)'!$O$3:$O$161,'Returns (Calc)'!$K$3:$K$161),2),"") | L16: =IFERROR(ROUND(CORREL('Returns (Calc)'!$O$3:$O$161,'Returns (Calc)'!$L$3:$L$161),2),"") | M16: =IFERROR(ROUND(CORREL('Returns (Calc)'!$O$3:$O$161,'Returns (Calc)'!$M$3:$M$161),2),"") | N16: =IFERROR(ROUND(CORREL('Returns (Calc)'!$O$3:$O$161,'Returns (Calc)'!$N$3:$N$161),2),"") | O16: 1 | P16: =IFERROR(ROUND(CORREL('Returns (Calc)'!$O$3:$O$161,'Returns (Calc)'!$P$3:$P$161),2),"") | Q16: =IFERROR(ROUND(CORREL('Returns (Calc)'!$O$3:$O$161,'Returns (Calc)'!$Q$3:$Q$161),2),"") | R16: =COUNTIF(B16:Q16,">0.7")-1 -> 0
A17: ='Returns (Calc)'!P2 -> Ticker 15 | B17: =IFERROR(ROUND(CORREL('Returns (Calc)'!$P$3:$P$161,'Returns (Calc)'!$B$3:$B$161),2),"") | C17: =IFERROR(ROUND(CORREL('Returns (Calc)'!$P$3:$P$161,'Returns (Calc)'!$C$3:$C$161),2),"") | D17: =IFERROR(ROUND(CORREL('Returns (Calc)'!$P$3:$P$161,'Returns (Calc)'!$D$3:$D$161),2),"") | E17: =IFERROR(ROUND(CORREL('Returns (Calc)'!$P$3:$P$161,'Returns (Calc)'!$E$3:$E$161),2),"") | F17: =IFERROR(ROUND(CORREL('Returns (Calc)'!$P$3:$P$161,'Returns (Calc)'!$F$3:$F$161),2),"") | G17: =IFERROR(ROUND(CORREL('Returns (Calc)'!$P$3:$P$161,'Returns (Calc)'!$G$3:$G$161),2),"") | H17: =IFERROR(ROUND(CORREL('Returns (Calc)'!$P$3:$P$161,'Returns (Calc)'!$H$3:$H$161),2),"") | I17: =IFERROR(ROUND(CORREL('Returns (Calc)'!$P$3:$P$161,'Returns (Calc)'!$I$3:$I$161),2),"") | J17: =IFERROR(ROUND(CORREL('Returns (Calc)'!$P$3:$P$161,'Returns (Calc)'!$J$3:$J$161),2),"") | K17: =IFERROR(ROUND(CORREL('Returns (Calc)'!$P$3:$P$161,'Returns (Calc)'!$K$3:$K$161),2),"") | L17: =IFERROR(ROUND(CORREL('Returns (Calc)'!$P$3:$P$161,'Returns (Calc)'!$L$3:$L$161),2),"") | M17: =IFERROR(ROUND(CORREL('Returns (Calc)'!$P$3:$P$161,'Returns (Calc)'!$M$3:$M$161),2),"") | N17: =IFERROR(ROUND(CORREL('Returns (Calc)'!$P$3:$P$161,'Returns (Calc)'!$N$3:$N$161),2),"") | O17: =IFERROR(ROUND(CORREL('Returns (Calc)'!$P$3:$P$161,'Returns (Calc)'!$O$3:$O$161),2),"") | P17: 1 | Q17: =IFERROR(ROUND(CORREL('Returns (Calc)'!$P$3:$P$161,'Returns (Calc)'!$Q$3:$Q$161),2),"") | R17: =COUNTIF(B17:Q17,">0.7")-1 -> 0
A18: ='Returns (Calc)'!Q2 -> Ticker 16 | B18: =IFERROR(ROUND(CORREL('Returns (Calc)'!$Q$3:$Q$161,'Returns (Calc)'!$B$3:$B$161),2),"") | C18: =IFERROR(ROUND(CORREL('Returns (Calc)'!$Q$3:$Q$161,'Returns (Calc)'!$C$3:$C$161),2),"") | D18: =IFERROR(ROUND(CORREL('Returns (Calc)'!$Q$3:$Q$161,'Returns (Calc)'!$D$3:$D$161),2),"") | E18: =IFERROR(ROUND(CORREL('Returns (Calc)'!$Q$3:$Q$161,'Returns (Calc)'!$E$3:$E$161),2),"") | F18: =IFERROR(ROUND(CORREL('Returns (Calc)'!$Q$3:$Q$161,'Returns (Calc)'!$F$3:$F$161),2),"") | G18: =IFERROR(ROUND(CORREL('Returns (Calc)'!$Q$3:$Q$161,'Returns (Calc)'!$G$3:$G$161),2),"") | H18: =IFERROR(ROUND(CORREL('Returns (Calc)'!$Q$3:$Q$161,'Returns (Calc)'!$H$3:$H$161),2),"") | I18: =IFERROR(ROUND(CORREL('Returns (Calc)'!$Q$3:$Q$161,'Returns (Calc)'!$I$3:$I$161),2),"") | J18: =IFERROR(ROUND(CORREL('Returns (Calc)'!$Q$3:$Q$161,'Returns (Calc)'!$J$3:$J$161),2),"") | K18: =IFERROR(ROUND(CORREL('Returns (Calc)'!$Q$3:$Q$161,'Returns (Calc)'!$K$3:$K$161),2),"") | L18: =IFERROR(ROUND(CORREL('Returns (Calc)'!$Q$3:$Q$161,'Returns (Calc)'!$L$3:$L$161),2),"") | M18: =IFERROR(ROUND(CORREL('Returns (Calc)'!$Q$3:$Q$161,'Returns (Calc)'!$M$3:$M$161),2),"") | N18: =IFERROR(ROUND(CORREL('Returns (Calc)'!$Q$3:$Q$161,'Returns (Calc)'!$N$3:$N$161),2),"") | O18: =IFERROR(ROUND(CORREL('Returns (Calc)'!$Q$3:$Q$161,'Returns (Calc)'!$O$3:$O$161),2),"") | P18: =IFERROR(ROUND(CORREL('Returns (Calc)'!$Q$3:$Q$161,'Returns (Calc)'!$P$3:$P$161),2),"") | Q18: 1 | R18: =COUNTIF(B18:Q18,">0.7")-1 -> 0
A20: Positions exceeding cap (correlated >0.70 with 2+ other holdings): | B20: =COUNTIF(R3:R18,">1") -> 0
A21: Rule 36 status (no position may exceed 0.70 with more than one other holding): | B21: =IF(B20>0,"REVIEW REQUIRED","OK") -> OK

Sheet Portfolio Drawdown Log
A1: Portfolio-level drawdown tracking (Part 7, Rules 36-37). Enter Date and Portfolio Value; all other columns calculate automatically.
A2: Date | B2: Portfolio Value ($) | C2: Running Peak ($) | D2: Drawdown % | E2: Status | F2: Required Cash Floor | G2: New Position Initiation | H2: Notes
C3: =IF(B3="","",B3) | D3: =IF(OR(B3="",C3=""),"",B3/C3-1) | E3: =IF(D3="","",IF(D3>=-0.1,"Normal",IF(D3>=-0.2,"Elevated",IF(D3>=-0.3,"Severe","Critical")))) | F3: =IF(E3="","",IF(E3="Normal","5-15%",IF(E3="Elevated","15%",IF(E3="Severe","20%","25%")))) | G3: =IF(E3="","",IF(E3="Normal","Standard (score >=65)",IF(E3="Elevated","Restricted (score >=80 only)","Suspended")))
C4: =IF(B4="","",MAX(C3,B4)) | D4: =IF(OR(B4="",C4=""),"",B4/C4-1) | E4: =IF(D4="","",IF(D4>=-0.1,"Normal",IF(D4>=-0.2,"Elevated",IF(D4>=-0.3,"Severe","Critical")))) | F4: =IF(E4="","",IF(E4="Normal","5-15%",IF(E4="Elevated","15%",IF(E4="Severe","20%","25%")))) | G4: =IF(E4="","",IF(E4="Normal","Standard (score >=65)",IF(E4="Elevated","Restricted (score >=80 only)","Suspended")))
C5: =IF(B5="","",MAX(C4,B5)) | D5: =IF(OR(B5="",C5=""),"",B5/C5-1) | E5: =IF(D5="","",IF(D5>=-0.1,"Normal",IF(D5>=-0.2,"Elevated",IF(D5>=-0.3,"Severe","Critical")))) | F5: =IF(E5="","",IF(E5="Normal","5-15%",IF(E5="Elevated","15%",IF(E5="Severe","20%","25%")))) | G5: =IF(E5="","",IF(E5="Normal","Standard (score >=65)",IF(E5="Elevated","Restricted (score >=80 only)","Suspended")))
C6: =IF(B6="","",MAX(C5,B6)) | D6: =IF(OR(B6="",C6=""),"",B6/C6-1) | E6: =IF(D6="","",IF(D6>=-0.1,"Normal",IF(D6>=-0.2,"Elevated",IF(D6>=-0.3,"Severe","Critical")))) | F6: =IF(E6="","",IF(E6="Normal","5-15%",IF(E6="Elevated","15%",IF(E6="Severe","20%","25%")))) | G6: =IF(E6="","",IF(E6="Normal","Standard (score >=65)",IF(E6="Elevated","Restricted (score >=80 only)","Suspended")))
C7: =IF(B7="","",MAX(C6,B7)) | D7: =IF(OR(B7="",C7=""),"",B7/C7-1) | E7: =IF(D7="","",IF(D7>=-0.1,"Normal",IF(D7>=-0.2,"Elevated",IF(D7>=-0.3,"Severe","Critical")))) | F7: =IF(E7="","",IF(E7="Normal","5-15%",IF(E7="Elevated","15%",IF(E7="Severe","20%","25%")))) | G7: =IF(E7="","",IF(E7="Normal","Standard (score >=65)",IF(E7="Elevated","Restricted (score >=80 only)","Suspended")))
C8: =IF(B8="","",MAX(C7,B8)) | D8: =IF(OR(B8="",C8=""),"",B8/C8-1) | E8: =IF(D8="","",IF(D8>=-0.1,"Normal",IF(D8>=-0.2,"Elevated",IF(D8>=-0.3,"Severe","Critical")))) | F8: =IF(E8="","",IF(E8="Normal","5-15%",IF(E8="Elevated","15%",IF(E8="Severe","20%","25%")))) | G8: =IF(E8="","",IF(E8="Normal","Standard (score >=65)",IF(E8="Elevated","Restricted (score >=80 only)","Suspended")))
C9: =IF(B9="","",MAX(C8,B9)) | D9: =IF(OR(B9="",C9=""),"",B9/C9-1) | E9: =IF(D9="","",IF(D9>=-0.1,"Normal",IF(D9>=-0.2,"Elevated",IF(D9>=-0.3,"Severe","Critical")))) | F9: =IF(E9="","",IF(E9="Normal","5-15%",IF(E9="Elevated","15%",IF(E9="Severe","20%","25%")))) | G9: =IF(E9="","",IF(E9="Normal","Standard (score >=65)",IF(E9="Elevated","Restricted (score >=80 only)","Suspended")))
C10: =IF(B10="","",MAX(C9,B10)) | D10: =IF(OR(B10="",C10=""),"",B10/C10-1) | E10: =IF(D10="","",IF(D10>=-0.1,"Normal",IF(D10>=-0.2,"Elevated",IF(D10>=-0.3,"Severe","Critical")))) | F10: =IF(E10="","",IF(E10="Normal","5-15%",IF(E10="Elevated","15%",IF(E10="Severe","20%","25%")))) | G10: =IF(E10="","",IF(E10="Normal","Standard (score >=65)",IF(E10="Elevated","Restricted (score >=80 only)","Suspended")))
C11: =IF(B11="","",MAX(C10,B11)) | D11: =IF(OR(B11="",C11=""),"",B11/C11-1) | E11: =IF(D11="","",IF(D11>=-0.1,"Normal",IF(D11>=-0.2,"Elevated",IF(D11>=-0.3,"Severe","Critical")))) | F11: =IF(E11="","",IF(E11="Normal","5-15%",IF(E11="Elevated","15%",IF(E11="Severe","20%","25%")))) | G11: =IF(E11="","",IF(E11="Normal","Standard (score >=65)",IF(E11="Elevated","Restricted (score >=80 only)","Suspended")))
C12: =IF(B12="","",MAX(C11,B12)) | D12: =IF(OR(B12="",C12=""),"",B12/C12-1) | E12: =IF(D12="","",IF(D12>=-0.1,"Normal",IF(D12>=-0.2,"Elevated",IF(D12>=-0.3,"Severe","Critical")))) | F12: =IF(E12="","",IF(E12="Normal","5-15%",IF(E12="Elevated","15%",IF(E12="Severe","20%","25%")))) | G12: =IF(E12="","",IF(E12="Normal","Standard (score >=65)",IF(E12="Elevated","Restricted (score >=80 only)","Suspended")))
C13: =IF(B13="","",MAX(C12,B13)) | D13: =IF(OR(B13="",C13=""),"",B13/C13-1) | E13: =IF(D13="","",IF(D13>=-0.1,"Normal",IF(D13>=-0.2,"Elevated",IF(D13>=-0.3,"Severe","Critical")))) | F13: =IF(E13="","",IF(E13="Normal","5-15%",IF(E13="Elevated","15%",IF(E13="Severe","20%","25%")))) | G13: =IF(E13="","",IF(E13="Normal","Standard (score >=65)",IF(E13="Elevated","Restricted (score >=80 only)","Suspended")))
C14: =IF(B14="","",MAX(C13,B14)) | D14: =IF(OR(B14="",C14=""),"",B14/C14-1) | E14: =IF(D14="","",IF(D14>=-0.1,"Normal",IF(D14>=-0.2,"Elevated",IF(D14>=-0.3,"Severe","Critical")))) | F14: =IF(E14="","",IF(E14="Normal","5-15%",IF(E14="Elevated","15%",IF(E14="Severe","20%","25%")))) | G14: =IF(E14="","",IF(E14="Normal","Standard (score >=65)",IF(E14="Elevated","Restricted (score >=80 only)","Suspended")))
C15: =IF(B15="","",MAX(C14,B15)) | D15: =IF(OR(B15="",C15=""),"",B15/C15-1) | E15: =IF(D15="","",IF(D15>=-0.1,"Normal",IF(D15>=-0.2,"Elevated",IF(D15>=-0.3,"Severe","Critical")))) | F15: =IF(E15="","",IF(E15="Normal","5-15%",IF(E15="Elevated","15%",IF(E15="Severe","20%","25%")))) | G15: =IF(E15="","",IF(E15="Normal","Standard (score >=65)",IF(E15="Elevated","Restricted (score >=80 only)","Suspended")))
... C42: =IF(B42="","",MAX(C41,B42)) | D42: =IF(OR(B42="",C42=""),"",B42/C42-1) | E42: =IF(D42="","",IF(D42>=-0.1,"Normal",IF(D42>=-0.2,"Elevated",IF(D42>=-0.3,"Severe","Critical")))) | F42: =IF(E42="","",IF(E42="Normal","5-15%",IF(E42="Elevated","15%",IF(E42="Severe","20%","25%")))) | G42: =IF(E42="","",IF(E42="Normal","Standard (score >=65)",IF(E42="Elevated","Restricted (score >=80 only)","Suspended")))

Sheet Watch List Tracker
A1: Tracks every holding in Probationary Hold (50-64) or Exit Review (35-49) per Part 6. The 90-day deadline and its consequence are calculated automatically — this tab is what makes Rules 31-34 enforceable rather than a manual judgment call.
A2: Ticker | B2: Company | C2: Status (Probationary/ Exit Review) | D2: Entry Date (band entered) | E2: Entry Score | F2: Current Score | G2: Current Score Date | H2: Credible Remediation Plan? (Y/N) | I2: 90-Day Deadline | J2: Days Remaining | K2: Action Status | L2: Remediation Plan Notes
I3: =IF(D3="","",D3+90) | J3: =IF(I3="","",I3-TODAY()) | K3: =IF(OR(C3="",F3=""),"",IF(AND(C3="Exit Review",H3="N"),"NO CREDIBLE PLAN — SELL WITHIN 30 DAYS",IF(AND(C3="Probationary Hold",F3>=65),"RECOVERED — REMOVE FROM WATCH LIST",IF(AND(C3="Exit Review",F3>=50),"RECOVERED — MOVE TO PROBATIONARY HOLD",IF(J3<0,"DEADLINE PASSED — SELL WITHIN 30 DAYS",IF(J3<=14,"DEADLINE APPROACHING","ON TRACK"))))))
I4: =IF(D4="","",D4+90) | J4: =IF(I4="","",I4-TODAY()) | K4: =IF(OR(C4="",F4=""),"",IF(AND(C4="Exit Review",H4="N"),"NO CREDIBLE PLAN — SELL WITHIN 30 DAYS",IF(AND(C4="Probationary Hold",F4>=65),"RECOVERED — REMOVE FROM WATCH LIST",IF(AND(C4="Exit Review",F4>=50),"RECOVERED — MOVE TO PROBATIONARY HOLD",IF(J4<0,"DEADLINE PASSED — SELL WITHIN 30 DAYS",IF(J4<=14,"DEADLINE APPROACHING","ON TRACK"))))))
I5: =IF(D5="","",D5+90) | J5: =IF(I5="","",I5-TODAY()) | K5: =IF(OR(C5="",F5=""),"",IF(AND(C5="Exit Review",H5="N"),"NO CREDIBLE PLAN — SELL WITHIN 30 DAYS",IF(AND(C5="Probationary Hold",F5>=65),"RECOVERED — REMOVE FROM WATCH LIST",IF(AND(C5="Exit Review",F5>=50),"RECOVERED — MOVE TO PROBATIONARY HOLD",IF(J5<0,"DEADLINE PASSED — SELL WITHIN 30 DAYS",IF(J5<=14,"DEADLINE APPROACHING","ON TRACK"))))))
I6: =IF(D6="","",D6+90) | J6: =IF(I6="","",I6-TODAY()) | K6: =IF(OR(C6="",F6=""),"",IF(AND(C6="Exit Review",H6="N"),"NO CREDIBLE PLAN — SELL WITHIN 30 DAYS",IF(AND(C6="Probationary Hold",F6>=65),"RECOVERED — REMOVE FROM WATCH LIST",IF(AND(C6="Exit Review",F6>=50),"RECOVERED — MOVE TO PROBATIONARY HOLD",IF(J6<0,"DEADLINE PASSED — SELL WITHIN 30 DAYS",IF(J6<=14,"DEADLINE APPROACHING","ON TRACK"))))))
I7: =IF(D7="","",D7+90) | J7: =IF(I7="","",I7-TODAY()) | K7: =IF(OR(C7="",F7=""),"",IF(AND(C7="Exit Review",H7="N"),"NO CREDIBLE PLAN — SELL WITHIN 30 DAYS",IF(AND(C7="Probationary Hold",F7>=65),"RECOVERED — REMOVE FROM WATCH LIST",IF(AND(C7="Exit Review",F7>=50),"RECOVERED — MOVE TO PROBATIONARY HOLD",IF(J7<0,"DEADLINE PASSED — SELL WITHIN 30 DAYS",IF(J7<=14,"DEADLINE APPROACHING","ON TRACK"))))))
I8: =IF(D8="","",D8+90) | J8: =IF(I8="","",I8-TODAY()) | K8: =IF(OR(C8="",F8=""),"",IF(AND(C8="Exit Review",H8="N"),"NO CREDIBLE PLAN — SELL WITHIN 30 DAYS",IF(AND(C8="Probationary Hold",F8>=65),"RECOVERED — REMOVE FROM WATCH LIST",IF(AND(C8="Exit Review",F8>=50),"RECOVERED — MOVE TO PROBATIONARY HOLD",IF(J8<0,"DEADLINE PASSED — SELL WITHIN 30 DAYS",IF(J8<=14,"DEADLINE APPROACHING","ON TRACK"))))))
I9: =IF(D9="","",D9+90) | J9: =IF(I9="","",I9-TODAY()) | K9: =IF(OR(C9="",F9=""),"",IF(AND(C9="Exit Review",H9="N"),"NO CREDIBLE PLAN — SELL WITHIN 30 DAYS",IF(AND(C9="Probationary Hold",F9>=65),"RECOVERED — REMOVE FROM WATCH LIST",IF(AND(C9="Exit Review",F9>=50),"RECOVERED — MOVE TO PROBATIONARY HOLD",IF(J9<0,"DEADLINE PASSED — SELL WITHIN 30 DAYS",IF(J9<=14,"DEADLINE APPROACHING","ON TRACK"))))))
I10: =IF(D10="","",D10+90) | J10: =IF(I10="","",I10-TODAY()) | K10: =IF(OR(C10="",F10=""),"",IF(AND(C10="Exit Review",H10="N"),"NO CREDIBLE PLAN — SELL WITHIN 30 DAYS",IF(AND(C10="Probationary Hold",F10>=65),"RECOVERED — REMOVE FROM WATCH LIST",IF(AND(C10="Exit Review",F10>=50),"RECOVERED — MOVE TO PROBATIONARY HOLD",IF(J10<0,"DEADLINE PASSED — SELL WITHIN 30 DAYS",IF(J10<=14,"DEADLINE APPROACHING","ON TRACK"))))))
I11: =IF(D11="","",D11+90) | J11: =IF(I11="","",I11-TODAY()) | K11: =IF(OR(C11="",F11=""),"",IF(AND(C11="Exit Review",H11="N"),"NO CREDIBLE PLAN — SELL WITHIN 30 DAYS",IF(AND(C11="Probationary Hold",F11>=65),"RECOVERED — REMOVE FROM WATCH LIST",IF(AND(C11="Exit Review",F11>=50),"RECOVERED — MOVE TO PROBATIONARY HOLD",IF(J11<0,"DEADLINE PASSED — SELL WITHIN 30 DAYS",IF(J11<=14,"DEADLINE APPROACHING","ON TRACK"))))))
I12: =IF(D12="","",D12+90) | J12: =IF(I12="","",I12-TODAY()) | K12: =IF(OR(C12="",F12=""),"",IF(AND(C12="Exit Review",H12="N"),"NO CREDIBLE PLAN — SELL WITHIN 30 DAYS",IF(AND(C12="Probationary Hold",F12>=65),"RECOVERED — REMOVE FROM WATCH LIST",IF(AND(C12="Exit Review",F12>=50),"RECOVERED — MOVE TO PROBATIONARY HOLD",IF(J12<0,"DEADLINE PASSED — SELL WITHIN 30 DAYS",IF(J12<=14,"DEADLINE APPROACHING","ON TRACK"))))))
I13: =IF(D13="","",D13+90) | J13: =IF(I13="","",I13-TODAY()) | K13: =IF(OR(C13="",F13=""),"",IF(AND(C13="Exit Review",H13="N"),"NO CREDIBLE PLAN — SELL WITHIN 30 DAYS",IF(AND(C13="Probationary Hold",F13>=65),"RECOVERED — REMOVE FROM WATCH LIST",IF(AND(C13="Exit Review",F13>=50),"RECOVERED — MOVE TO PROBATIONARY HOLD",IF(J13<0,"DEADLINE PASSED — SELL WITHIN 30 DAYS",IF(J13<=14,"DEADLINE APPROACHING","ON TRACK"))))))
I14: =IF(D14="","",D14+90) | J14: =IF(I14="","",I14-TODAY()) | K14: =IF(OR(C14="",F14=""),"",IF(AND(C14="Exit Review",H14="N"),"NO CREDIBLE PLAN — SELL WITHIN 30 DAYS",IF(AND(C14="Probationary Hold",F14>=65),"RECOVERED — REMOVE FROM WATCH LIST",IF(AND(C14="Exit Review",F14>=50),"RECOVERED — MOVE TO PROBATIONARY HOLD",IF(J14<0,"DEADLINE PASSED — SELL WITHIN 30 DAYS",IF(J14<=14,"DEADLINE APPROACHING","ON TRACK"))))))
... I22: =IF(D22="","",D22+90) | J22: =IF(I22="","",I22-TODAY()) | K22: =IF(OR(C22="",F22=""),"",IF(AND(C22="Exit Review",H22="N"),"NO CREDIBLE PLAN — SELL WITHIN 30 DAYS",IF(AND(C22="Probationary Hold",F22>=65),"RECOVERED — REMOVE FROM WATCH LIST",IF(AND(C22="Exit Review",F22>=50),"RECOVERED — MOVE TO PROBATIONARY HOLD",IF(J22<0,"DEADLINE PASSED — SELL WITHIN 30 DAYS",IF(J22<=14,"DEADLINE APPROACHING","ON TRACK"))))))

Sheet Implied-Return Calculator
A1: Standardized Implied-Return Methodology (Rule 11, Part 4): Expected annualized return = [(Year-5 equity value + cumulative distributions) ÷ current equity value]^(1/5) − 1. Run Base, Bear, and Bull cases together (Rule 12) — exactly one gets the Likely tag.
D2: BASE CASE | I2: BEAR CASE | N2: BULL CASE | S2: RULE 11 / 12 CHECKS
A3: Ticker | B3: Company | C3: Current Price ($) | D3: Yr-5 FCF /sh ($) | E3: Terminal P/FCF | F3: Cum. Distrib/sh | G3: Implied Annual Return | H3: Tag (L/P/U) | I3: Yr-5 FCF /sh ($) | J3: Terminal P/FCF | K3: Cum. Distrib/sh | L3: Implied Annual Return | M3: Tag (L/P/U) | N3: Yr-5 FCF /sh ($) | O3: Terminal P/FCF | P3: Cum. Distrib/sh | Q3: Implied Annual Return | R3: Tag (L/P/U) | S3: Base>10%? | T3: Bear≥0%? | U3: Exactly 1 Likely?
G4: =IF(OR(C4="",D4="",E4="",F4=""),"",IFERROR(((D4*E4+F4)/C4)^(1/5)-1,"n/a")) | L4: =IF(OR(C4="",I4="",J4="",K4=""),"",IFERROR(((I4*J4+K4)/C4)^(1/5)-1,"n/a")) | Q4: =IF(OR(C4="",N4="",O4="",P4=""),"",IFERROR(((N4*O4+P4)/C4)^(1/5)-1,"n/a")) | S4: =IF(G4="","",IF(G4>0.1,"PASS","FAIL")) | T4: =IF(L4="","",IF(L4>=0,"PASS","FAIL")) | U4: =IF(COUNTA(H4,M4,R4)=0,"",IF((COUNTIF(H4,"Likely")+COUNTIF(M4,"Likely")+COUNTIF(R4,"Likely"))=1,"OK","CHECK TAGS"))
G5: =IF(OR(C5="",D5="",E5="",F5=""),"",IFERROR(((D5*E5+F5)/C5)^(1/5)-1,"n/a")) | L5: =IF(OR(C5="",I5="",J5="",K5=""),"",IFERROR(((I5*J5+K5)/C5)^(1/5)-1,"n/a")) | Q5: =IF(OR(C5="",N5="",O5="",P5=""),"",IFERROR(((N5*O5+P5)/C5)^(1/5)-1,"n/a")) | S5: =IF(G5="","",IF(G5>0.1,"PASS","FAIL")) | T5: =IF(L5="","",IF(L5>=0,"PASS","FAIL")) | U5: =IF(COUNTA(H5,M5,R5)=0,"",IF((COUNTIF(H5,"Likely")+COUNTIF(M5,"Likely")+COUNTIF(R5,"Likely"))=1,"OK","CHECK TAGS"))
G6: =IF(OR(C6="",D6="",E6="",F6=""),"",IFERROR(((D6*E6+F6)/C6)^(1/5)-1,"n/a")) | L6: =IF(OR(C6="",I6="",J6="",K6=""),"",IFERROR(((I6*J6+K6)/C6)^(1/5)-1,"n/a")) | Q6: =IF(OR(C6="",N6="",O6="",P6=""),"",IFERROR(((N6*O6+P6)/C6)^(1/5)-1,"n/a")) | S6: =IF(G6="","",IF(G6>0.1,"PASS","FAIL")) | T6: =IF(L6="","",IF(L6>=0,"PASS","FAIL")) | U6: =IF(COUNTA(H6,M6,R6)=0,"",IF((COUNTIF(H6,"Likely")+COUNTIF(M6,"Likely")+COUNTIF(R6,"Likely"))=1,"OK","CHECK TAGS"))
G7: =IF(OR(C7="",D7="",E7="",F7=""),"",IFERROR(((D7*E7+F7)/C7)^(1/5)-1,"n/a")) | L7: =IF(OR(C7="",I7="",J7="",K7=""),"",IFERROR(((I7*J7+K7)/C7)^(1/5)-1,"n/a")) | Q7: =IF(OR(C7="",N7="",O7="",P7=""),"",IFERROR(((N7*O7+P7)/C7)^(1/5)-1,"n/a")) | S7: =IF(G7="","",IF(G7>0.1,"PASS","FAIL")) | T7: =IF(L7="","",IF(L7>=0,"PASS","FAIL")) | U7: =IF(COUNTA(H7,M7,R7)=0,"",IF((COUNTIF(H7,"Likely")+COUNTIF(M7,"Likely")+COUNTIF(R7,"Likely"))=1,"OK","CHECK TAGS"))
G8: =IF(OR(C8="",D8="",E8="",F8=""),"",IFERROR(((D8*E8+F8)/C8)^(1/5)-1,"n/a")) | L8: =IF(OR(C8="",I8="",J8="",K8=""),"",IFERROR(((I8*J8+K8)/C8)^(1/5)-1,"n/a")) | Q8: =IF(OR(C8="",N8="",O8="",P8=""),"",IFERROR(((N8*O8+P8)/C8)^(1/5)-1,"n/a")) | S8: =IF(G8="","",IF(G8>0.1,"PASS","FAIL")) | T8: =IF(L8="","",IF(L8>=0,"PASS","FAIL")) | U8: =IF(COUNTA(H8,M8,R8)=0,"",IF((COUNTIF(H8,"Likely")+COUNTIF(M8,"Likely")+COUNTIF(R8,"Likely"))=1,"OK","CHECK TAGS"))
G9: =IF(OR(C9="",D9="",E9="",F9=""),"",IFERROR(((D9*E9+F9)/C9)^(1/5)-1,"n/a")) | L9: =IF(OR(C9="",I9="",J9="",K9=""),"",IFERROR(((I9*J9+K9)/C9)^(1/5)-1,"n/a")) | Q9: =IF(OR(C9="",N9="",O9="",P9=""),"",IFERROR(((N9*O9+P9)/C9)^(1/5)-1,"n/a")) | S9: =IF(G9="","",IF(G9>0.1,"PASS","FAIL")) | T9: =IF(L9="","",IF(L9>=0,"PASS","FAIL")) | U9: =IF(COUNTA(H9,M9,R9)=0,"",IF((COUNTIF(H9,"Likely")+COUNTIF(M9,"Likely")+COUNTIF(R9,"Likely"))=1,"OK","CHECK TAGS"))
G10: =IF(OR(C10="",D10="",E10="",F10=""),"",IFERROR(((D10*E10+F10)/C10)^(1/5)-1,"n/a")) | L10: =IF(OR(C10="",I10="",J10="",K10=""),"",IFERROR(((I10*J10+K10)/C10)^(1/5)-1,"n/a")) | Q10: =IF(OR(C10="",N10="",O10="",P10=""),"",IFERROR(((N10*O10+P10)/C10)^(1/5)-1,"n/a")) | S10: =IF(G10="","",IF(G10>0.1,"PASS","FAIL")) | T10: =IF(L10="","",IF(L10>=0,"PASS","FAIL")) | U10: =IF(COUNTA(H10,M10,R10)=0,"",IF((COUNTIF(H10,"Likely")+COUNTIF(M10,"Likely")+COUNTIF(R10,"Likely"))=1,"OK","CHECK TAGS"))
G11: =IF(OR(C11="",D11="",E11="",F11=""),"",IFERROR(((D11*E11+F11)/C11)^(1/5)-1,"n/a")) | L11: =IF(OR(C11="",I11="",J11="",K11=""),"",IFERROR(((I11*J11+K11)/C11)^(1/5)-1,"n/a")) | Q11: =IF(OR(C11="",N11="",O11="",P11=""),"",IFERROR(((N11*O11+P11)/C11)^(1/5)-1,"n/a")) | S11: =IF(G11="","",IF(G11>0.1,"PASS","FAIL")) | T11: =IF(L11="","",IF(L11>=0,"PASS","FAIL")) | U11: =IF(COUNTA(H11,M11,R11)=0,"",IF((COUNTIF(H11,"Likely")+COUNTIF(M11,"Likely")+COUNTIF(R11,"Likely"))=1,"OK","CHECK TAGS"))
G12: =IF(OR(C12="",D12="",E12="",F12=""),"",IFERROR(((D12*E12+F12)/C12)^(1/5)-1,"n/a")) | L12: =IF(OR(C12="",I12="",J12="",K12=""),"",IFERROR(((I12*J12+K12)/C12)^(1/5)-1,"n/a")) | Q12: =IF(OR(C12="",N12="",O12="",P12=""),"",IFERROR(((N12*O12+P12)/C12)^(1/5)-1,"n/a")) | S12: =IF(G12="","",IF(G12>0.1,"PASS","FAIL")) | T12: =IF(L12="","",IF(L12>=0,"PASS","FAIL")) | U12: =IF(COUNTA(H12,M12,R12)=0,"",IF((COUNTIF(H12,"Likely")+COUNTIF(M12,"Likely")+COUNTIF(R12,"Likely"))=1,"OK","CHECK TAGS"))
G13: =IF(OR(C13="",D13="",E13="",F13=""),"",IFERROR(((D13*E13+F13)/C13)^(1/5)-1,"n/a")) | L13: =IF(OR(C13="",I13="",J13="",K13=""),"",IFERROR(((I13*J13+K13)/C13)^(1/5)-1,"n/a")) | Q13: =IF(OR(C13="",N13="",O13="",P13=""),"",IFERROR(((N13*O13+P13)/C13)^(1/5)-1,"n/a")) | S13: =IF(G13="","",IF(G13>0.1,"PASS","FAIL")) | T13: =IF(L13="","",IF(L13>=0,"PASS","FAIL")) | U13: =IF(COUNTA(H13,M13,R13)=0,"",IF((COUNTIF(H13,"Likely")+COUNTIF(M13,"Likely")+COUNTIF(R13,"Likely"))=1,"OK","CHECK TAGS"))
G14: =IF(OR(C14="",D14="",E14="",F14=""),"",IFERROR(((D14*E14+F14)/C14)^(1/5)-1,"n/a")) | L14: =IF(OR(C14="",I14="",J14="",K14=""),"",IFERROR(((I14*J14+K14)/C14)^(1/5)-1,"n/a")) | Q14: =IF(OR(C14="",N14="",O14="",P14=""),"",IFERROR(((N14*O14+P14)/C14)^(1/5)-1,"n/a")) | S14: =IF(G14="","",IF(G14>0.1,"PASS","FAIL")) | T14: =IF(L14="","",IF(L14>=0,"PASS","FAIL")) | U14: =IF(COUNTA(H14,M14,R14)=0,"",IF((COUNTIF(H14,"Likely")+COUNTIF(M14,"Likely")+COUNTIF(R14,"Likely"))=1,"OK","CHECK TAGS"))
G15: =IF(OR(C15="",D15="",E15="",F15=""),"",IFERROR(((D15*E15+F15)/C15)^(1/5)-1,"n/a")) | L15: =IF(OR(C15="",I15="",J15="",K15=""),"",IFERROR(((I15*J15+K15)/C15)^(1/5)-1,"n/a")) | Q15: =IF(OR(C15="",N15="",O15="",P15=""),"",IFERROR(((N15*O15+P15)/C15)^(1/5)-1,"n/a")) | S15: =IF(G15="","",IF(G15>0.1,"PASS","FAIL")) | T15: =IF(L15="","",IF(L15>=0,"PASS","FAIL")) | U15: =IF(COUNTA(H15,M15,R15)=0,"",IF((COUNTIF(H15,"Likely")+COUNTIF(M15,"Likely")+COUNTIF(R15,"Likely"))=1,"OK","CHECK TAGS"))
... G23: =IF(OR(C23="",D23="",E23="",F23=""),"",IFERROR(((D23*E23+F23)/C23)^(1/5)-1,"n/a")) | L23: =IF(OR(C23="",I23="",J23="",K23=""),"",IFERROR(((I23*J23+K23)/C23)^(1/5)-1,"n/a")) | Q23: =IF(OR(C23="",N23="",O23="",P23=""),"",IFERROR(((N23*O23+P23)/C23)^(1/5)-1,"n/a")) | S23: =IF(G23="","",IF(G23>0.1,"PASS","FAIL")) | T23: =IF(L23="","",IF(L23>=0,"PASS","FAIL")) | U23: =IF(COUNTA(H23,M23,R23)=0,"",IF((COUNTIF(H23,"Likely")+COUNTIF(M23,"Likely")+COUNTIF(R23,"Likely"))=1,"OK","CHECK TAGS"))

Sheet Holding Monitor
A1: For positions actually held (not screening candidates). Tracks Part 6's ten sell triggers (Rules 21-30). Enter this-period and prior-period Tier 1 sub-scores to auto-detect the 'two consecutive periods' fundamental triggers; enter current valuation/position metrics for the rest. Any trigger firing without a Hold Through condition applying requires action within 30 days.
E2: FUNDAMENTAL TRIGGERS (Rules 21-25) — flags if declined 2 consecutive periods | T2: VALUATION / SIZING TRIGGERS (Rules 26-30)
A3: Ticker | B3: Company | C3: Position Pct | D3: Max Full Pct | E3: FCF Yield Prior | F3: FCF Yield Current | G3: Flag | H3: Moat Prior | I3: Moat Current | J3: Flag | K3: ROIC-WACC Spread Prior | L3: ROIC-WACC Spread Current | M3: Flag | N3: Mgmt Quality Prior | O3: Mgmt Quality Current | P3: Flag | Q3: Rev Growth Prior | R3: Rev Growth Current | S3: Flag | T3: Debt/FCF (>6x=trigger) | U3: P/FCF (>50x+gr<15%) | V3: FCF Growth % | W3: Implied Return (<7%=trigger) | X3: Current Tier | Y3: Prior Tier | Z3: Valuation Flags | AA3: Hold Through Applies? (Y/N) | AB3: Action Status
G4: =IF(OR(E4="",F4=""),"",IF(AND(E4<=2,F4<=2),"TRIGGER","OK")) | J4: =IF(OR(H4="",I4=""),"",IF(AND(H4<=2,I4<=2),"TRIGGER","OK")) | M4: =IF(OR(K4="",L4=""),"",IF(AND(K4<=2,L4<=2),"TRIGGER","OK")) | P4: =IF(OR(N4="",O4=""),"",IF(AND(N4<=2,O4<=2),"TRIGGER","OK")) | S4: =IF(OR(Q4="",R4=""),"",IF(AND(Q4<=2,R4<=2),"TRIGGER","OK")) | Z4: =IF(TRIM(IF(AND(T4<>"",T4>6),"Debt/FCF>6x; ","")&IF(AND(U4<>"",V4<>"",U4>50,V4<0.15),"P/FCF>50x+low growth; ","")&IF(AND(W4<>"",W4<0.07),"Implied return<7%; ","")&IF(AND(C4<>"",D4<>"",C4>D4),"Position>max; ","")&IF(AND(X4<>"",Y4<>"",X4<>Y4,OR(Y4="Strong Buy",Y4="Buy")),"Tier downgraded; ",""))="","OK",TRIM(IF(AND(T4<>"",T4>6),"Debt/FCF>6x; ","")&IF(AND(U4<>"",V4<>"",U4>50,V4<0.15),"P/FCF>50x+low growth; ","")&IF(AND(W4<>"",W4<0.07),"Implied return<7%; ","")&IF(AND(C4<>"",D4<>"",C4>D4),"Position>max; ","")&IF(AND(X4<>"",Y4<>"",X4<>Y4,OR(Y4="Strong Buy",Y4="Buy")),"Tier downgraded; ",""))) -> OK | AB4: =IF(COUNTA(G4,J4,M4,P4,S4)=0,"",IF(AA4="Y","Hold Through applies — monitor only",IF(OR((COUNTIF(G4,"TRIGGER")+COUNTIF(J4,"TRIGGER")+COUNTIF(M4,"TRIGGER")+COUNTIF(P4,"TRIGGER")+COUNTIF(S4,"TRIGGER"))>0,Z4<>"OK"),"ACTION REQUIRED WITHIN 30 DAYS","OK — no active trigger"))) -> OK — no active trigger
G5: =IF(OR(E5="",F5=""),"",IF(AND(E5<=2,F5<=2),"TRIGGER","OK")) | J5: =IF(OR(H5="",I5=""),"",IF(AND(H5<=2,I5<=2),"TRIGGER","OK")) | M5: =IF(OR(K5="",L5=""),"",IF(AND(K5<=2,L5<=2),"TRIGGER","OK")) | P5: =IF(OR(N5="",O5=""),"",IF(AND(N5<=2,O5<=2),"TRIGGER","OK")) | S5: =IF(OR(Q5="",R5=""),"",IF(AND(Q5<=2,R5<=2),"TRIGGER","OK")) | Z5: =IF(TRIM(IF(AND(T5<>"",T5>6),"Debt/FCF>6x; ","")&IF(AND(U5<>"",V5<>"",U5>50,V5<0.15),"P/FCF>50x+low growth; ","")&IF(AND(W5<>"",W5<0.07),"Implied return<7%; ","")&IF(AND(C5<>"",D5<>"",C5>D5),"Position>max; ","")&IF(AND(X5<>"",Y5<>"",X5<>Y5,OR(Y5="Strong Buy",Y5="Buy")),"Tier downgraded; ",""))="","OK",TRIM(IF(AND(T5<>"",T5>6),"Debt/FCF>6x; ","")&IF(AND(U5<>"",V5<>"",U5>50,V5<0.15),"P/FCF>50x+low growth; ","")&IF(AND(W5<>"",W5<0.07),"Implied return<7%; ","")&IF(AND(C5<>"",D5<>"",C5>D5),"Position>max; ","")&IF(AND(X5<>"",Y5<>"",X5<>Y5,OR(Y5="Strong Buy",Y5="Buy")),"Tier downgraded; ",""))) -> OK | AB5: =IF(COUNTA(G5,J5,M5,P5,S5)=0,"",IF(AA5="Y","Hold Through applies — monitor only",IF(OR((COUNTIF(G5,"TRIGGER")+COUNTIF(J5,"TRIGGER")+COUNTIF(M5,"TRIGGER")+COUNTIF(P5,"TRIGGER")+COUNTIF(S5,"TRIGGER"))>0,Z5<>"OK"),"ACTION REQUIRED WITHIN 30 DAYS","OK — no active trigger"))) -> OK — no active trigger
G6: =IF(OR(E6="",F6=""),"",IF(AND(E6<=2,F6<=2),"TRIGGER","OK")) | J6: =IF(OR(H6="",I6=""),"",IF(AND(H6<=2,I6<=2),"TRIGGER","OK")) | M6: =IF(OR(K6="",L6=""),"",IF(AND(K6<=2,L6<=2),"TRIGGER","OK")) | P6: =IF(OR(N6="",O6=""),"",IF(AND(N6<=2,O6<=2),"TRIGGER","OK")) | S6: =IF(OR(Q6="",R6=""),"",IF(AND(Q6<=2,R6<=2),"TRIGGER","OK")) | Z6: =IF(TRIM(IF(AND(T6<>"",T6>6),"Debt/FCF>6x; ","")&IF(AND(U6<>"",V6<>"",U6>50,V6<0.15),"P/FCF>50x+low growth; ","")&IF(AND(W6<>"",W6<0.07),"Implied return<7%; ","")&IF(AND(C6<>"",D6<>"",C6>D6),"Position>max; ","")&IF(AND(X6<>"",Y6<>"",X6<>Y6,OR(Y6="Strong Buy",Y6="Buy")),"Tier downgraded; ",""))="","OK",TRIM(IF(AND(T6<>"",T6>6),"Debt/FCF>6x; ","")&IF(AND(U6<>"",V6<>"",U6>50,V6<0.15),"P/FCF>50x+low growth; ","")&IF(AND(W6<>"",W6<0.07),"Implied return<7%; ","")&IF(AND(C6<>"",D6<>"",C6>D6),"Position>max; ","")&IF(AND(X6<>"",Y6<>"",X6<>Y6,OR(Y6="Strong Buy",Y6="Buy")),"Tier downgraded; ",""))) -> OK | AB6: =IF(COUNTA(G6,J6,M6,P6,S6)=0,"",IF(AA6="Y","Hold Through applies — monitor only",IF(OR((COUNTIF(G6,"TRIGGER")+COUNTIF(J6,"TRIGGER")+COUNTIF(M6,"TRIGGER")+COUNTIF(P6,"TRIGGER")+COUNTIF(S6,"TRIGGER"))>0,Z6<>"OK"),"ACTION REQUIRED WITHIN 30 DAYS","OK — no active trigger"))) -> OK — no active trigger
G7: =IF(OR(E7="",F7=""),"",IF(AND(E7<=2,F7<=2),"TRIGGER","OK")) | J7: =IF(OR(H7="",I7=""),"",IF(AND(H7<=2,I7<=2),"TRIGGER","OK")) | M7: =IF(OR(K7="",L7=""),"",IF(AND(K7<=2,L7<=2),"TRIGGER","OK")) | P7: =IF(OR(N7="",O7=""),"",IF(AND(N7<=2,O7<=2),"TRIGGER","OK")) | S7: =IF(OR(Q7="",R7=""),"",IF(AND(Q7<=2,R7<=2),"TRIGGER","OK")) | Z7: =IF(TRIM(IF(AND(T7<>"",T7>6),"Debt/FCF>6x; ","")&IF(AND(U7<>"",V7<>"",U7>50,V7<0.15),"P/FCF>50x+low growth; ","")&IF(AND(W7<>"",W7<0.07),"Implied return<7%; ","")&IF(AND(C7<>"",D7<>"",C7>D7),"Position>max; ","")&IF(AND(X7<>"",Y7<>"",X7<>Y7,OR(Y7="Strong Buy",Y7="Buy")),"Tier downgraded; ",""))="","OK",TRIM(IF(AND(T7<>"",T7>6),"Debt/FCF>6x; ","")&IF(AND(U7<>"",V7<>"",U7>50,V7<0.15),"P/FCF>50x+low growth; ","")&IF(AND(W7<>"",W7<0.07),"Implied return<7%; ","")&IF(AND(C7<>"",D7<>"",C7>D7),"Position>max; ","")&IF(AND(X7<>"",Y7<>"",X7<>Y7,OR(Y7="Strong Buy",Y7="Buy")),"Tier downgraded; ",""))) -> OK | AB7: =IF(COUNTA(G7,J7,M7,P7,S7)=0,"",IF(AA7="Y","Hold Through applies — monitor only",IF(OR((COUNTIF(G7,"TRIGGER")+COUNTIF(J7,"TRIGGER")+COUNTIF(M7,"TRIGGER")+COUNTIF(P7,"TRIGGER")+COUNTIF(S7,"TRIGGER"))>0,Z7<>"OK"),"ACTION REQUIRED WITHIN 30 DAYS","OK — no active trigger"))) -> OK — no active trigger
G8: =IF(OR(E8="",F8=""),"",IF(AND(E8<=2,F8<=2),"TRIGGER","OK")) | J8: =IF(OR(H8="",I8=""),"",IF(AND(H8<=2,I8<=2),"TRIGGER","OK")) | M8: =IF(OR(K8="",L8=""),"",IF(AND(K8<=2,L8<=2),"TRIGGER","OK")) | P8: =IF(OR(N8="",O8=""),"",IF(AND(N8<=2,O8<=2),"TRIGGER","OK")) | S8: =IF(OR(Q8="",R8=""),"",IF(AND(Q8<=2,R8<=2),"TRIGGER","OK")) | Z8: =IF(TRIM(IF(AND(T8<>"",T8>6),"Debt/FCF>6x; ","")&IF(AND(U8<>"",V8<>"",U8>50,V8<0.15),"P/FCF>50x+low growth; ","")&IF(AND(W8<>"",W8<0.07),"Implied return<7%; ","")&IF(AND(C8<>"",D8<>"",C8>D8),"Position>max; ","")&IF(AND(X8<>"",Y8<>"",X8<>Y8,OR(Y8="Strong Buy",Y8="Buy")),"Tier downgraded; ",""))="","OK",TRIM(IF(AND(T8<>"",T8>6),"Debt/FCF>6x; ","")&IF(AND(U8<>"",V8<>"",U8>50,V8<0.15),"P/FCF>50x+low growth; ","")&IF(AND(W8<>"",W8<0.07),"Implied return<7%; ","")&IF(AND(C8<>"",D8<>"",C8>D8),"Position>max; ","")&IF(AND(X8<>"",Y8<>"",X8<>Y8,OR(Y8="Strong Buy",Y8="Buy")),"Tier downgraded; ",""))) -> OK | AB8: =IF(COUNTA(G8,J8,M8,P8,S8)=0,"",IF(AA8="Y","Hold Through applies — monitor only",IF(OR((COUNTIF(G8,"TRIGGER")+COUNTIF(J8,"TRIGGER")+COUNTIF(M8,"TRIGGER")+COUNTIF(P8,"TRIGGER")+COUNTIF(S8,"TRIGGER"))>0,Z8<>"OK"),"ACTION REQUIRED WITHIN 30 DAYS","OK — no active trigger"))) -> OK — no active trigger
G9: =IF(OR(E9="",F9=""),"",IF(AND(E9<=2,F9<=2),"TRIGGER","OK")) | J9: =IF(OR(H9="",I9=""),"",IF(AND(H9<=2,I9<=2),"TRIGGER","OK")) | M9: =IF(OR(K9="",L9=""),"",IF(AND(K9<=2,L9<=2),"TRIGGER","OK")) | P9: =IF(OR(N9="",O9=""),"",IF(AND(N9<=2,O9<=2),"TRIGGER","OK")) | S9: =IF(OR(Q9="",R9=""),"",IF(AND(Q9<=2,R9<=2),"TRIGGER","OK")) | Z9: =IF(TRIM(IF(AND(T9<>"",T9>6),"Debt/FCF>6x; ","")&IF(AND(U9<>"",V9<>"",U9>50,V9<0.15),"P/FCF>50x+low growth; ","")&IF(AND(W9<>"",W9<0.07),"Implied return<7%; ","")&IF(AND(C9<>"",D9<>"",C9>D9),"Position>max; ","")&IF(AND(X9<>"",Y9<>"",X9<>Y9,OR(Y9="Strong Buy",Y9="Buy")),"Tier downgraded; ",""))="","OK",TRIM(IF(AND(T9<>"",T9>6),"Debt/FCF>6x; ","")&IF(AND(U9<>"",V9<>"",U9>50,V9<0.15),"P/FCF>50x+low growth; ","")&IF(AND(W9<>"",W9<0.07),"Implied return<7%; ","")&IF(AND(C9<>"",D9<>"",C9>D9),"Position>max; ","")&IF(AND(X9<>"",Y9<>"",X9<>Y9,OR(Y9="Strong Buy",Y9="Buy")),"Tier downgraded; ",""))) -> OK | AB9: =IF(COUNTA(G9,J9,M9,P9,S9)=0,"",IF(AA9="Y","Hold Through applies — monitor only",IF(OR((COUNTIF(G9,"TRIGGER")+COUNTIF(J9,"TRIGGER")+COUNTIF(M9,"TRIGGER")+COUNTIF(P9,"TRIGGER")+COUNTIF(S9,"TRIGGER"))>0,Z9<>"OK"),"ACTION REQUIRED WITHIN 30 DAYS","OK — no active trigger"))) -> OK — no active trigger
G10: =IF(OR(E10="",F10=""),"",IF(AND(E10<=2,F10<=2),"TRIGGER","OK")) | J10: =IF(OR(H10="",I10=""),"",IF(AND(H10<=2,I10<=2),"TRIGGER","OK")) | M10: =IF(OR(K10="",L10=""),"",IF(AND(K10<=2,L10<=2),"TRIGGER","OK")) | P10: =IF(OR(N10="",O10=""),"",IF(AND(N10<=2,O10<=2),"TRIGGER","OK")) | S10: =IF(OR(Q10="",R10=""),"",IF(AND(Q10<=2,R10<=2),"TRIGGER","OK")) | Z10: =IF(TRIM(IF(AND(T10<>"",T10>6),"Debt/FCF>6x; ","")&IF(AND(U10<>"",V10<>"",U10>50,V10<0.15),"P/FCF>50x+low growth; ","")&IF(AND(W10<>"",W10<0.07),"Implied return<7%; ","")&IF(AND(C10<>"",D10<>"",C10>D10),"Position>max; ","")&IF(AND(X10<>"",Y10<>"",X10<>Y10,OR(Y10="Strong Buy",Y10="Buy")),"Tier downgraded; ",""))="","OK",TRIM(IF(AND(T10<>"",T10>6),"Debt/FCF>6x; ","")&IF(AND(U10<>"",V10<>"",U10>50,V10<0.15),"P/FCF>50x+low growth; ","")&IF(AND(W10<>"",W10<0.07),"Implied return<7%; ","")&IF(AND(C10<>"",D10<>"",C10>D10),"Position>max; ","")&IF(AND(X10<>"",Y10<>"",X10<>Y10,OR(Y10="Strong Buy",Y10="Buy")),"Tier downgraded; ",""))) -> OK | AB10: =IF(COUNTA(G10,J10,M10,P10,S10)=0,"",IF(AA10="Y","Hold Through applies — monitor only",IF(OR((COUNTIF(G10,"TRIGGER")+COUNTIF(J10,"TRIGGER")+COUNTIF(M10,"TRIGGER")+COUNTIF(P10,"TRIGGER")+COUNTIF(S10,"TRIGGER"))>0,Z10<>"OK"),"ACTION REQUIRED WITHIN 30 DAYS","OK — no active trigger"))) -> OK — no active trigger
G11: =IF(OR(E11="",F11=""),"",IF(AND(E11<=2,F11<=2),"TRIGGER","OK")) | J11: =IF(OR(H11="",I11=""),"",IF(AND(H11<=2,I11<=2),"TRIGGER","OK")) | M11: =IF(OR(K11="",L11=""),"",IF(AND(K11<=2,L11<=2),"TRIGGER","OK")) | P11: =IF(OR(N11="",O11=""),"",IF(AND(N11<=2,O11<=2),"TRIGGER","OK")) | S11: =IF(OR(Q11="",R11=""),"",IF(AND(Q11<=2,R11<=2),"TRIGGER","OK")) | Z11: =IF(TRIM(IF(AND(T11<>"",T11>6),"Debt/FCF>6x; ","")&IF(AND(U11<>"",V11<>"",U11>50,V11<0.15),"P/FCF>50x+low growth; ","")&IF(AND(W11<>"",W11<0.07),"Implied return<7%; ","")&IF(AND(C11<>"",D11<>"",C11>D11),"Position>max; ","")&IF(AND(X11<>"",Y11<>"",X11<>Y11,OR(Y11="Strong Buy",Y11="Buy")),"Tier downgraded; ",""))="","OK",TRIM(IF(AND(T11<>"",T11>6),"Debt/FCF>6x; ","")&IF(AND(U11<>"",V11<>"",U11>50,V11<0.15),"P/FCF>50x+low growth; ","")&IF(AND(W11<>"",W11<0.07),"Implied return<7%; ","")&IF(AND(C11<>"",D11<>"",C11>D11),"Position>max; ","")&IF(AND(X11<>"",Y11<>"",X11<>Y11,OR(Y11="Strong Buy",Y11="Buy")),"Tier downgraded; ",""))) -> OK | AB11: =IF(COUNTA(G11,J11,M11,P11,S11)=0,"",IF(AA11="Y","Hold Through applies — monitor only",IF(OR((COUNTIF(G11,"TRIGGER")+COUNTIF(J11,"TRIGGER")+COUNTIF(M11,"TRIGGER")+COUNTIF(P11,"TRIGGER")+COUNTIF(S11,"TRIGGER"))>0,Z11<>"OK"),"ACTION REQUIRED WITHIN 30 DAYS","OK — no active trigger"))) -> OK — no active trigger
G12: =IF(OR(E12="",F12=""),"",IF(AND(E12<=2,F12<=2),"TRIGGER","OK")) | J12: =IF(OR(H12="",I12=""),"",IF(AND(H12<=2,I12<=2),"TRIGGER","OK")) | M12: =IF(OR(K12="",L12=""),"",IF(AND(K12<=2,L12<=2),"TRIGGER","OK")) | P12: =IF(OR(N12="",O12=""),"",IF(AND(N12<=2,O12<=2),"TRIGGER","OK")) | S12: =IF(OR(Q12="",R12=""),"",IF(AND(Q12<=2,R12<=2),"TRIGGER","OK")) | Z12: =IF(TRIM(IF(AND(T12<>"",T12>6),"Debt/FCF>6x; ","")&IF(AND(U12<>"",V12<>"",U12>50,V12<0.15),"P/FCF>50x+low growth; ","")&IF(AND(W12<>"",W12<0.07),"Implied return<7%; ","")&IF(AND(C12<>"",D12<>"",C12>D12),"Position>max; ","")&IF(AND(X12<>"",Y12<>"",X12<>Y12,OR(Y12="Strong Buy",Y12="Buy")),"Tier downgraded; ",""))="","OK",TRIM(IF(AND(T12<>"",T12>6),"Debt/FCF>6x; ","")&IF(AND(U12<>"",V12<>"",U12>50,V12<0.15),"P/FCF>50x+low growth; ","")&IF(AND(W12<>"",W12<0.07),"Implied return<7%; ","")&IF(AND(C12<>"",D12<>"",C12>D12),"Position>max; ","")&IF(AND(X12<>"",Y12<>"",X12<>Y12,OR(Y12="Strong Buy",Y12="Buy")),"Tier downgraded; ",""))) -> OK | AB12: =IF(COUNTA(G12,J12,M12,P12,S12)=0,"",IF(AA12="Y","Hold Through applies — monitor only",IF(OR((COUNTIF(G12,"TRIGGER")+COUNTIF(J12,"TRIGGER")+COUNTIF(M12,"TRIGGER")+COUNTIF(P12,"TRIGGER")+COUNTIF(S12,"TRIGGER"))>0,Z12<>"OK"),"ACTION REQUIRED WITHIN 30 DAYS","OK — no active trigger"))) -> OK — no active trigger
G13: =IF(OR(E13="",F13=""),"",IF(AND(E13<=2,F13<=2),"TRIGGER","OK")) | J13: =IF(OR(H13="",I13=""),"",IF(AND(H13<=2,I13<=2),"TRIGGER","OK")) | M13: =IF(OR(K13="",L13=""),"",IF(AND(K13<=2,L13<=2),"TRIGGER","OK")) | P13: =IF(OR(N13="",O13=""),"",IF(AND(N13<=2,O13<=2),"TRIGGER","OK")) | S13: =IF(OR(Q13="",R13=""),"",IF(AND(Q13<=2,R13<=2),"TRIGGER","OK")) | Z13: =IF(TRIM(IF(AND(T13<>"",T13>6),"Debt/FCF>6x; ","")&IF(AND(U13<>"",V13<>"",U13>50,V13<0.15),"P/FCF>50x+low growth; ","")&IF(AND(W13<>"",W13<0.07),"Implied return<7%; ","")&IF(AND(C13<>"",D13<>"",C13>D13),"Position>max; ","")&IF(AND(X13<>"",Y13<>"",X13<>Y13,OR(Y13="Strong Buy",Y13="Buy")),"Tier downgraded; ",""))="","OK",TRIM(IF(AND(T13<>"",T13>6),"Debt/FCF>6x; ","")&IF(AND(U13<>"",V13<>"",U13>50,V13<0.15),"P/FCF>50x+low growth; ","")&IF(AND(W13<>"",W13<0.07),"Implied return<7%; ","")&IF(AND(C13<>"",D13<>"",C13>D13),"Position>max; ","")&IF(AND(X13<>"",Y13<>"",X13<>Y13,OR(Y13="Strong Buy",Y13="Buy")),"Tier downgraded; ",""))) -> OK | AB13: =IF(COUNTA(G13,J13,M13,P13,S13)=0,"",IF(AA13="Y","Hold Through applies — monitor only",IF(OR((COUNTIF(G13,"TRIGGER")+COUNTIF(J13,"TRIGGER")+COUNTIF(M13,"TRIGGER")+COUNTIF(P13,"TRIGGER")+COUNTIF(S13,"TRIGGER"))>0,Z13<>"OK"),"ACTION REQUIRED WITHIN 30 DAYS","OK — no active trigger"))) -> OK — no active trigger
G14: =IF(OR(E14="",F14=""),"",IF(AND(E14<=2,F14<=2),"TRIGGER","OK")) | J14: =IF(OR(H14="",I14=""),"",IF(AND(H14<=2,I14<=2),"TRIGGER","OK")) | M14: =IF(OR(K14="",L14=""),"",IF(AND(K14<=2,L14<=2),"TRIGGER","OK")) | P14: =IF(OR(N14="",O14=""),"",IF(AND(N14<=2,O14<=2),"TRIGGER","OK")) | S14: =IF(OR(Q14="",R14=""),"",IF(AND(Q14<=2,R14<=2),"TRIGGER","OK")) | Z14: =IF(TRIM(IF(AND(T14<>"",T14>6),"Debt/FCF>6x; ","")&IF(AND(U14<>"",V14<>"",U14>50,V14<0.15),"P/FCF>50x+low growth; ","")&IF(AND(W14<>"",W14<0.07),"Implied return<7%; ","")&IF(AND(C14<>"",D14<>"",C14>D14),"Position>max; ","")&IF(AND(X14<>"",Y14<>"",X14<>Y14,OR(Y14="Strong Buy",Y14="Buy")),"Tier downgraded; ",""))="","OK",TRIM(IF(AND(T14<>"",T14>6),"Debt/FCF>6x; ","")&IF(AND(U14<>"",V14<>"",U14>50,V14<0.15),"P/FCF>50x+low growth; ","")&IF(AND(W14<>"",W14<0.07),"Implied return<7%; ","")&IF(AND(C14<>"",D14<>"",C14>D14),"Position>max; ","")&IF(AND(X14<>"",Y14<>"",X14<>Y14,OR(Y14="Strong Buy",Y14="Buy")),"Tier downgraded; ",""))) -> OK | AB14: =IF(COUNTA(G14,J14,M14,P14,S14)=0,"",IF(AA14="Y","Hold Through applies — monitor only",IF(OR((COUNTIF(G14,"TRIGGER")+COUNTIF(J14,"TRIGGER")+COUNTIF(M14,"TRIGGER")+COUNTIF(P14,"TRIGGER")+COUNTIF(S14,"TRIGGER"))>0,Z14<>"OK"),"ACTION REQUIRED WITHIN 30 DAYS","OK — no active trigger"))) -> OK — no active trigger
G15: =IF(OR(E15="",F15=""),"",IF(AND(E15<=2,F15<=2),"TRIGGER","OK")) | J15: =IF(OR(H15="",I15=""),"",IF(AND(H15<=2,I15<=2),"TRIGGER","OK")) | M15: =IF(OR(K15="",L15=""),"",IF(AND(K15<=2,L15<=2),"TRIGGER","OK")) | P15: =IF(OR(N15="",O15=""),"",IF(AND(N15<=2,O15<=2),"TRIGGER","OK")) | S15: =IF(OR(Q15="",R15=""),"",IF(AND(Q15<=2,R15<=2),"TRIGGER","OK")) | Z15: =IF(TRIM(IF(AND(T15<>"",T15>6),"Debt/FCF>6x; ","")&IF(AND(U15<>"",V15<>"",U15>50,V15<0.15),"P/FCF>50x+low growth; ","")&IF(AND(W15<>"",W15<0.07),"Implied return<7%; ","")&IF(AND(C15<>"",D15<>"",C15>D15),"Position>max; ","")&IF(AND(X15<>"",Y15<>"",X15<>Y15,OR(Y15="Strong Buy",Y15="Buy")),"Tier downgraded; ",""))="","OK",TRIM(IF(AND(T15<>"",T15>6),"Debt/FCF>6x; ","")&IF(AND(U15<>"",V15<>"",U15>50,V15<0.15),"P/FCF>50x+low growth; ","")&IF(AND(W15<>"",W15<0.07),"Implied return<7%; ","")&IF(AND(C15<>"",D15<>"",C15>D15),"Position>max; ","")&IF(AND(X15<>"",Y15<>"",X15<>Y15,OR(Y15="Strong Buy",Y15="Buy")),"Tier downgraded; ",""))) -> OK | AB15: =IF(COUNTA(G15,J15,M15,P15,S15)=0,"",IF(AA15="Y","Hold Through applies — monitor only",IF(OR((COUNTIF(G15,"TRIGGER")+COUNTIF(J15,"TRIGGER")+COUNTIF(M15,"TRIGGER")+COUNTIF(P15,"TRIGGER")+COUNTIF(S15,"TRIGGER"))>0,Z15<>"OK"),"ACTION REQUIRED WITHIN 30 DAYS","OK — no active trigger"))) -> OK — no active trigger
... G23: =IF(OR(E23="",F23=""),"",IF(AND(E23<=2,F23<=2),"TRIGGER","OK")) | J23: =IF(OR(H23="",I23=""),"",IF(AND(H23<=2,I23<=2),"TRIGGER","OK")) | M23: =IF(OR(K23="",L23=""),"",IF(AND(K23<=2,L23<=2),"TRIGGER","OK")) | P23: =IF(OR(N23="",O23=""),"",IF(AND(N23<=2,O23<=2),"TRIGGER","OK")) | S23: =IF(OR(Q23="",R23=""),"",IF(AND(Q23<=2,R23<=2),"TRIGGER","OK")) | Z23: =IF(TRIM(IF(AND(T23<>"",T23>6),"Debt/FCF>6x; ","")&IF(AND(U23<>"",V23<>"",U23>50,V23<0.15),"P/FCF>50x+low growth; ","")&IF(AND(W23<>"",W23<0.07),"Implied return<7%; ","")&IF(AND(C23<>"",D23<>"",C23>D23),"Position>max; ","")&IF(AND(X23<>"",Y23<>"",X23<>Y23,OR(Y23="Strong Buy",Y23="Buy")),"Tier downgraded; ",""))="","OK",TRIM(IF(AND(T23<>"",T23>6),"Debt/FCF>6x; ","")&IF(AND(U23<>"",V23<>"",U23>50,V23<0.15),"P/FCF>50x+low growth; ","")&IF(AND(W23<>"",W23<0.07),"Implied return<7%; ","")&IF(AND(C23<>"",D23<>"",C23>D23),"Position>max; ","")&IF(AND(X23<>"",Y23<>"",X23<>Y23,OR(Y23="Strong Buy",Y23="Buy")),"Tier downgraded; ",""))) -> OK | AB23: =IF(COUNTA(G23,J23,M23,P23,S23)=0,"",IF(AA23="Y","Hold Through applies — monitor only",IF(OR((COUNTIF(G23,"TRIGGER")+COUNTIF(J23,"TRIGGER")+COUNTIF(M23,"TRIGGER")+COUNTIF(P23,"TRIGGER")+COUNTIF(S23,"TRIGGER"))>0,Z23<>"OK"),"ACTION REQUIRED WITHIN 30 DAYS","OK — no active trigger"))) -> OK — no active trigger

Sheet Performance Tracking
A1: Every initiated position from entry date forward, per Part 9 — including still-held positions, not only exited ones (avoids the exit-only selection bias the System was specifically built to prevent). Feeds the Rule-46 cohort review once 10+ entries in a decision band reach five years.
A2: Ticker | B2: Company | C2: Entry Date | D2: Entry Price | E2: Entry Score | F2: Entry Confidence | G2: Entry Decision Band | H2: SPY Price at Entry | I2: Status (Held/Exited) | J2: Exit Date | K2: Exit Price | L2: Exit Reason | M2: Current/ Exit Price | N2: SPY Price (current/exit) | O2: Total Return Since Entry | P2: SPY Return Same Period | Q2: Excess Return
O3: =IF(OR(D3="",M3=""),"",M3/D3-1) | P3: =IF(OR(H3="",N3=""),"",N3/H3-1) | Q3: =IF(OR(O3="",P3=""),"",O3-P3)
O4: =IF(OR(D4="",M4=""),"",M4/D4-1) | P4: =IF(OR(H4="",N4=""),"",N4/H4-1) | Q4: =IF(OR(O4="",P4=""),"",O4-P4)
O5: =IF(OR(D5="",M5=""),"",M5/D5-1) | P5: =IF(OR(H5="",N5=""),"",N5/H5-1) | Q5: =IF(OR(O5="",P5=""),"",O5-P5)
O6: =IF(OR(D6="",M6=""),"",M6/D6-1) | P6: =IF(OR(H6="",N6=""),"",N6/H6-1) | Q6: =IF(OR(O6="",P6=""),"",O6-P6)
O7: =IF(OR(D7="",M7=""),"",M7/D7-1) | P7: =IF(OR(H7="",N7=""),"",N7/H7-1) | Q7: =IF(OR(O7="",P7=""),"",O7-P7)
O8: =IF(OR(D8="",M8=""),"",M8/D8-1) | P8: =IF(OR(H8="",N8=""),"",N8/H8-1) | Q8: =IF(OR(O8="",P8=""),"",O8-P8)
O9: =IF(OR(D9="",M9=""),"",M9/D9-1) | P9: =IF(OR(H9="",N9=""),"",N9/H9-1) | Q9: =IF(OR(O9="",P9=""),"",O9-P9)
O10: =IF(OR(D10="",M10=""),"",M10/D10-1) | P10: =IF(OR(H10="",N10=""),"",N10/H10-1) | Q10: =IF(OR(O10="",P10=""),"",O10-P10)
O11: =IF(OR(D11="",M11=""),"",M11/D11-1) | P11: =IF(OR(H11="",N11=""),"",N11/H11-1) | Q11: =IF(OR(O11="",P11=""),"",O11-P11)
O12: =IF(OR(D12="",M12=""),"",M12/D12-1) | P12: =IF(OR(H12="",N12=""),"",N12/H12-1) | Q12: =IF(OR(O12="",P12=""),"",O12-P12)
O13: =IF(OR(D13="",M13=""),"",M13/D13-1) | P13: =IF(OR(H13="",N13=""),"",N13/H13-1) | Q13: =IF(OR(O13="",P13=""),"",O13-P13)
O14: =IF(OR(D14="",M14=""),"",M14/D14-1) | P14: =IF(OR(H14="",N14=""),"",N14/H14-1) | Q14: =IF(OR(O14="",P14=""),"",O14-P14)
... O32: =IF(OR(D32="",M32=""),"",M32/D32-1) | P32: =IF(OR(H32="",N32=""),"",N32/H32-1) | Q32: =IF(OR(O32="",P32=""),"",O32-P32)
A34: Total Return Since Entry is a simple price return (excludes dividends unless you fold them into Current/Exit Price manually). At each annual review, snapshot the return here rather than trying to back-calculate historical 1/3/5-year prices Excel doesn't have.

Sheet Journal
A1: Freeform notes log — no required structure or length. Date and Ticker are there so you can sort or filter (Data > Filter, or click the column dropdown arrows) by symbol or date range. Leave Ticker blank for portfolio-level or general notes.
A2: Date | B2: Ticker | C2: Notes
A3: 46241 | B3: SFM | C3: Sold -- Rule 3 Avoid (same-store sales growth collapsed 11.5%->1.6% YoY, FCF margin compressed), small gain, no credible remediation path identified.
A4: 46241 | B4: TSLA | C4: Sold -- Rule 3 Avoid confirmed on 2nd consecutive scoring pass. FCF negative funding AI/robotics capex; not the profile this System rewards. Small gain.
A5: 46241 | B5: ONON | C5: Sold -- small position, clearing the deck rather than carrying a Tier 1 Avoid. Small gain, FCF trend declining despite strong revenue growth.
A6: 46241 | B6: VRTX | C6: RE-SCORED, NOT sold. Original Avoid call (8/6/26) was based on unreliable FCF data from MacroTrends. Reconstructed actual cash-flow-statement FCF: $3.19B (2024), $3.71B (2025), growing, ~31% margin -- 2023 was a one-year dip, not a trend. Corrected Composite = 75.6, BUY. Holding.
A7: 46241 | B7: SFM,TSLA,ONON | C7: Sells confirmed executed. Removed from Current Positions (qty/cost basis zeroed) and Monitor & Recheck Triggers (marked Closed). Sale proceeds shown as estimates using last known market price -- true up cash balances with next fresh account export.
A8: 46241 | B8: SFM,TSLA,ONON | C8: Confirmed actual proceeds: ONON -100sh $3,764.92 | SFM -65sh $5,601.58 | TSLA -15sh $4,783.25. Total $14,149.75 added to VMFXX. Combined portfolio now $700,739.19.

Sheet Schema Reference
A1: SCHEMA REFERENCE — for future programmatic access (Claude Code or otherwise)
A2: Every tab's structure documented in one place, so an agent reading this workbook doesn't have to reverse-engineer it. Tabs marked 'Table' below are registered Excel Tables (structured references, e.g. =CurrentPositionsTable[Ticker] work directly). Tabs marked 'Fixed range' have stable column positions but a merged multi-row header, so address by column letter + row number instead.
A4: Instructions
A5: Structure Type | B5: Table/Range Name | C5: Data Rows | D5: Key Reference
A6: Reference text (no data) | B6: n/a | C6: n/a | D6: How-to and rule reference. No structured data.
A8: Action Items
A9: Structure Type | B9: Table/Range Name | C9: Data Rows | D9: Key Reference
A10: Formulas pulling from other tabs | B10: n/a | C10: Rows 4-31, sections by row | D10: Read-only summary; do not write here, it recalculates from source tabs.
A12: Scoring
A13: Structure Type | B13: Table/Range Name | C13: Data Rows | D13: Key Reference
A14: Fixed range, 2-row merged header | B14: n/a (not a Table -- Tier1/2/3 group headers span multiple columns in row 1) | C14: Rows 3-27, cols A-AK | D14: Column map: A=Ticker,B=Company,C=Date. D-M=Tier1 (5 indicators x [Score,Conf]). N=Tier1WtdAvg,O=Tier1Contrib. P-W=Tier2 (4 x [Score,Conf]). X=Tier2Contrib. Y-AD=Tier3 (3 x [Score,Conf]). AE=Tier3Contrib. AF=Composite,AG=Decision. AH=Rule1,AI=Rule2,AJ=Rule3,AK=Rule4 flags.
A16: Market Data
A17: Structure Type | B17: Table/Range Name | C17: Data Rows | D17: Key Reference
A18: Fixed range, single header | B18: n/a | C18: Rows 3-27, cols A-I | D18: A=Ticker,B=Company,C=Price,D=Volume,E=MarketCap,F=P/E,G=52wkLow,H=52wkHigh,I=DivYield. Manual entry.
A20: Current Positions
A21: Structure Type | B21: Table/Range Name | C21: Data Rows | D21: Key Reference
A22: Table | B22: CurrentPositionsTable | C22: A2:M40 (JT ULTRA rows 3-14, Schwab rows 17-35; subtotal/total rows outside table range) | D22: A=Account,B=Ticker,C=Description,D=AssetClass,E=Quantity,F=Price,G=MarketValue,H=CostBasis,I=UnrealizedGL$,J=UnrealizedGL%,K=%ofAccount,L=%ofCombined,M=Classification. Tax-loss carryforward reference cells at O2/P2 (Short-term), O3/P3 (Long-term) -- outside the table.
A24: Monitor & Recheck Triggers
A25: Structure Type | B25: Table/Range Name | C25: Data Rows | D25: Key Reference
A26: Table | B26: MonitorTable | C26: A2:P42 | D26: A=Ticker,B=Category,C=LastScoreDate,D=LastComposite,E=LastT1WtdAvg,F=LastDecision,G=PriceAtLastScore,H=CurrentPrice,I=%PriceChange,J=EarningsDate,K=InsiderY/N,L=InsiderNote,M=AnalystShiftY/N,N=DaysSinceScore,O=RecheckStatus,P=Notes. Category values: Owned / Owned - Tier1 AVOID / Watch List / Tier-1 Avoid (external) / Near-Miss.
A28: Watch List Tracker
A29: Structure Type | B29: Table/Range Name | C29: Data Rows | D29: Key Reference
A30: Table | B30: WatchListTable | C30: A2:L22 | D30: A=Ticker,B=Company,C=Status,D=EntryDate,E=EntryScore,F=CurrentScore,G=CurrentScoreDate,H=CredibleRemediationPlan(Y/N),I=90DayDeadline,J=DaysRemaining,K=ActionStatus,L=Notes.
A32: Implied-Return Calculator
A33: Structure Type | B33: Table/Range Name | C33: Data Rows | D33: Key Reference
A34: Fixed range, 2-row merged header | B34: n/a (Base/Bear/Bull scenario groups span multiple columns in row 2) | C34: Rows 4-23, cols A-U | D34: A=Ticker,B=Company,C=Price. D-H=Base[FCF5,Mult,Dist,Return,Tag]. I-M=Bear[same]. N-R=Bull[same]. S=Base>10%check,T=Bear>=0%check,U=ExactlyOneLikelyCheck. Referenced by Entry Checklist with a +1 row offset (Entry Checklist row 3 = this tab's row 4, same ticker).
A36: Holding Monitor
A37: Structure Type | B37: Table/Range Name | C37: Data Rows | D37: Key Reference
A38: Fixed range, 2-row merged header | B38: n/a (Fundamental-trigger group header spans multiple columns in row 2) | C38: Rows 4-23, cols A-AB | D38: A=Ticker,B=Company,C=PositionPct,D=MaxFullPct. E-S=5 fundamental indicators x [Prior,Current,Flag]. T=Debt/FCF,U=P/FCF,V=FCFGrowth,W=ImpliedReturn,X=CurrentTier,Y=PriorTier,Z=ValuationFlags,AA=HoldThroughY/N,AB=ActionStatus.
A40: Performance Tracking
A41: Structure Type | B41: Table/Range Name | C41: Data Rows | D41: Key Reference
A42: Table | B42: PerformanceTrackingTable | C42: A2:Q34 | D42: A=Ticker,B=Company,C=EntryDate,D=EntryPrice,E=EntryScore,F=EntryConfidence,G=EntryBand,H=SPYatEntry,I=Status,J=ExitDate,K=ExitPrice,L=ExitReason,M=CurrentOrExitPrice,N=SPYcurrentOrExit,O=TotalReturn,P=SPYReturnSamePeriod,Q=ExcessReturn.
A44: Price History
A45: Structure Type | B45: Table/Range Name | C45: Data Rows | D45: Key Reference
A46: Fixed range, single header | B46: n/a | C46: Rows 3-162, cols A-Q (16 tickers) | D46: A=Week Ending, B-Q=up to 16 ticker columns. Weekly closes, week-ending Friday (Rule 36). 24-month target ~104 rows, 12-month minimum ~52 rows, 36-month max ~156 rows. Manual entry.
A48: Returns (Calc)
A49: Structure Type | B49: Table/Range Name | C49: Data Rows | D49: Key Reference
A50: Fixed range, formula-derived | B50: n/a | C50: Rows 3-161, cols A-Q | D50: Mirrors Price History layout; all cells are formulas computing week-over-week % return. Do not edit directly.
A52: Correlation Matrix
A53: Structure Type | B53: Table/Range Name | C53: Data Rows | D53: Key Reference
A54: Fixed range, formula-derived headers | B54: n/a | C54: Rows 3-18, cols A-Q | D54: 16x16 grid. Row 2 headers pull ticker names live from Returns (Calc) row 2 -- headers are blank until Price History is populated, which is why this was not converted to a Table. B20=violation count, B21=Rule 36 status (OK / REVIEW REQUIRED).
A56: Journal
A57: Structure Type | B57: Table/Range Name | C57: Data Rows | D57: Key Reference
A58: Table | B58: JournalTable | C58: A2:C302 | D58: A=Date,B=Ticker,C=Notes. Freeform; filter/sort via the Table's built-in header dropdowns.
