Workbook
Name MON_SignalsAsOf: 'Monitor & Recheck Triggers'!$Q$1
Name PT_AsOf: 'Performance Tracking'!$D$63
Name PT_Inception: 'Performance Tracking'!$D$67
Name PT_SPY_0805: 'Performance Tracking'!$D$65
Name PT_SPY_1231: 'Performance Tracking'!$D$66
Name PT_SPY_Now: 'Performance Tracking'!$D$64

Sheet Instructions
A1: THE LANDRY FAMILY EQUITY INVESTMENT OPERATING SYSTEM — STOCK SCORING & PORTFOLIO RISK WORKBOOK
A3: Companion workbook to Landry System v1.03. Aligned to: Version 1.03 (50 Hard Rules, Parts 1–12).
A4: If the Word document's rule numbers ever change in a future revision, check this line and the rule
A5: references throughout this workbook before relying on them.
A7: HOW TO USE THIS WORKBOOK
A8: 1. Market Data tab — enter or refresh price, volume, market cap, P/E, 52-week range, and dividend
A9: yield for each tracked ticker. Blue cells only. See that tab's note on optional live-data refresh.
A10: 2. Scoring tab — during a scoring session, enter each Tier 1/2/3 indicator's score (1–5) and Confidence
A11: tag (H/M/L) per Part 2's rubrics. The Composite Score, decision classification, and hard-rule flags
A12: (Rules 1–4) calculate automatically.
A13: 3. Dashboard tab — read-only summary of every tracked stock, sortable by Composite Score.
A14: 4. Price History / Returns (Calc) / Correlation Matrix tabs — enter weekly closing prices for current
... A61: Scoring tab, Tier 1 FCF indicators -- basis (policy 10/5/26, Open Items #31, Journal row 94): the scores of record are drafted from fiscal-year statements. At each quarterly review, and before acting on any Rule 1 / Rule 3 trip, Watch List or Exit Review deadline or Part 6 sell trigger, run `python -m landry.sec_ttm --holdings` (one name: `python -m landry.sec_ttm TICKER`) to compare every US-filer holding with its latest 10-Q. Re-score on trailing 12-month windows only where a hard-rule outcome or Decision band differs, in either direction; ASML, TSM, REITs and anything the tool lists as BY HAND are checked from the filings. A Part 10 adjustment for a one-time item (an acquisition, say) is Alan's to approve and is recorded in landry_addbacks.json and the score's adaptation field.

Sheet Action Items
A1: ACTION ITEMS — everything requiring your decision, pulled live from every other tab. Everything else in this workbook is reference; this is what to open.
A2: Refresh by opening the workbook (F9 recalculates); all cells below are live formulas, nothing here is typed.
A4: 1. WATCH LIST — Rules 32-36 (see Watch List Tracker tab for detail)
A5: Deadlines passed (sell required within 30 days): | E5: =COUNTIF('Watch List Tracker'!K3:K22,"*SELL WITHIN 30 DAYS*") -> 1
A6: Deadlines approaching (within 14 days): | E6: =COUNTIF('Watch List Tracker'!K3:K22,"DEADLINE APPROACHING") -> 0
A7: Recovered — ready to remove/reclassify: | E7: =COUNTIF('Watch List Tracker'!K3:K22,"*RECOVERED*") -> 0
A9: 2. ACTIVE SELL TRIGGERS — Rules 22-31 (see Holding Monitor tab for detail)
A10: Holdings with action required within 30 days: | E10: =COUNTIF('Holding Monitor'!AB4:AB23,"*ACTION REQUIRED*") -> 0
A11: Holdings under Hold Through (monitor only, no action): | E11: =COUNTIF('Holding Monitor'!AB4:AB23,"*Hold Through*") -> 0
A13: 3. CORRELATION CAP — Rule 38 (see Correlation Matrix tab for detail)
A14: Rule 38 status: | E14: ='Correlation Matrix'!J3 -> REVIEW REQUIRED
A15: Positions exceeding cap: | E15: ='Correlation Matrix'!J2 -> 11
A17: 4. PORTFOLIO DRAWDOWN STATUS — Rule 39 (see Portfolio Drawdown Log tab for detail)
A18: Most recent recorded status: | E18: =IFERROR(INDEX('Portfolio Drawdown Log'!E3:E42,COUNT('Portfolio Drawdown Log'!D3:D42)),"No entries yet") -> Normal
A19: Most recent drawdown %: | E19: =IFERROR(INDEX('Portfolio Drawdown Log'!D3:D42,COUNT('Portfolio Drawdown Log'!D3:D42)),"") -> -0.012866311
A20: Required cash floor at this level: | E20: =IFERROR(INDEX('Portfolio Drawdown Log'!F3:F42,COUNT('Portfolio Drawdown Log'!D3:D42)),"") -> 5-15%
A22: 5. CANDIDATE SCORING FLAGS — Rules 1-4 (see Scoring tab for detail)
A23: Candidates failing the Tier 1 floor, 3.0 (Rule 1): | E23: =COUNTIF(Scoring!AH3:AH60,"FAIL") -> 19
A24: Stocks flagged Avoid by Rule 3 (candidates and holdings): | E24: =COUNTIF(Scoring!AJ3:AJ60,"AVOID") -> 21
A25: Candidates flagged for mandatory Tier 1 review (Rule 2): | E25: =COUNTIF(Scoring!AI3:AI60,"REVIEW") -> 14
A26: Candidates capped at Buy despite Strong Buy score (Rule 4): | E26: =COUNTIF(Scoring!AK3:AK60,"CAP AT BUY") -> 0
A27: 6. ENTRY AUTHORIZATION — Rules 6-14 (see Entry Checklist tab for detail)
A28: Candidates NOT authorized to enter (failing one or more Entry Rules): | E28: =COUNTIF('Entry Checklist'!R3:R47,"NO*") -> 1
A29: Candidates authorized, staged at reduced size (50%, per Rules 9-10): | E29: =COUNTIF('Entry Checklist'!H3:H47,"*50%*") -> 0
A31: 7. PIOTROSKI CROSS-CHECKS -- RETIRED 9/11/26. Tested on an 8-ticker diagnostic batch, dropped as redundant for how this system is actually used (see Journal row 42-43). Historical data left in place at Scoring cols AN-AS as a record of the experiment; no longer live-tallied here.
A32: Candidates flagged LOW CONF on Accruals (CFO does not exceed Net Income): | E32: =COUNTIF(Scoring!AP3:AP60,"LOW CONF") -> 2
A33: Candidates with Debt/FCF trending up year-over-year: | E33: =COUNTIF(Scoring!AS3:AS60,"Increased") -> 5

Sheet Current Positions
A1: Combined current positions, both accounts, as of the 9/30/2026 statements (GE/NFLX bought 9/30, settled 10/1; prices refresh in Excel) -- JT ULTRA (Fidelity); Self-Directed, Chase — cash sweep custodied at Schwab, swept to VMFXX for yield. Source: uploaded brokerage exports + confirmed trade executions, aggregated by ticker. Update this tab at each quarterly/annual review; use it with Part 5 sizing modifiers and the Holding Monitor tab to prescribe classifications and follow-up actions. | O1: TAX-LOSS CARRYFORWARD (update annually)
A2: Account | B2: Ticker | C2: Description | D2: Asset Class | E2: Quantity | F2: Price ($) | G2: Market Value ($) | H2: Cost Basis ($) | I2: Unrealized G/L ($) | J2: Unrealized G/L (%) | K2: % of Acct | L2: % of Comb. Portfolio | M2: Classification / Notes (fill at review) | O2: Short-Term Loss Carryforward:
A3: JT ULTRA (Fidelity) | B3: ADBE | C3: Adobe Inc. | D3: Equity | E3: 65 | F3: =IF(IFERROR(INDEX('Monitor & Recheck Triggers'!$H$3:$H$51,MATCH($B3,'Monitor & Recheck Triggers'!$A$3:$A$51,0)),"")="",237.69,INDEX('Monitor & Recheck Triggers'!$H$3:$H$51,MATCH($B3,'Monitor & Recheck Triggers'!$A$3:$A$51,0))) -> 238.785 | G3: =E3*F3 -> 15521.025 | H3: 19163.84 | I3: =G3-H3 -> -3642.815 | J3: =IF(H3=0,"",G3/H3-1) -> -0.19008795 | K3: =IFERROR(G3/SUM(G3:G23),"") -> 0.037640147 | L3: =IFERROR(G3/(SUM(G3:G23,G27:G46)),"") -> 0.02129231 | M3: BOUGHT +20sh 8/7/26 @ $266.38 -- DCA tranche 1 diversifier add | O3: Long-Term Loss Carryforward:
A4: JT ULTRA (Fidelity) | B4: ANET | C4: Arista Networks | D4: Equity | E4: 70 | F4: =IF(IFERROR(INDEX('Monitor & Recheck Triggers'!$H$3:$H$51,MATCH($B4,'Monitor & Recheck Triggers'!$A$3:$A$51,0)),"")="",207.35,INDEX('Monitor & Recheck Triggers'!$H$3:$H$51,MATCH($B4,'Monitor & Recheck Triggers'!$A$3:$A$51,0))) -> 206.9 | G4: =E4*F4 -> 14483 | H4: 10182.2 | I4: =G4-H4 -> 4300.8 | J4: =IF(H4=0,"",G4/H4-1) -> 0.42238416 | K4: =IFERROR(G4/SUM(G3:G23),"") -> 0.035122826 | L4: =IFERROR(G4/(SUM(G3:G23,G27:G46)),"") -> 0.01986831
A5: JT ULTRA (Fidelity) | B5: ASML | C5: ASML Holding | D5: Equity | E5: 7 | F5: =IF(IFERROR(INDEX('Monitor & Recheck Triggers'!$H$3:$H$51,MATCH($B5,'Monitor & Recheck Triggers'!$A$3:$A$51,0)),"")="",1867.31,INDEX('Monitor & Recheck Triggers'!$H$3:$H$51,MATCH($B5,'Monitor & Recheck Triggers'!$A$3:$A$51,0))) -> 1859.86 | G5: =E5*F5 -> 13019.02 | H5: 9989.88 | I5: =G5-H5 -> 3029.14 | J5: =IF(H5=0,"",G5/H5-1) -> 0.30322086 | K5: =IFERROR(G5/SUM(G3:G23),"") -> 0.031572517 | L5: =IFERROR(G5/(SUM(G3:G23,G27:G46)),"") -> 0.017859968
A6: JT ULTRA (Fidelity) | B6: CRWD | C6: CrowdStrike Holdings | D6: Equity | E6: 40 | F6: =IF(IFERROR(INDEX('Monitor & Recheck Triggers'!$H$3:$H$51,MATCH($B6,'Monitor & Recheck Triggers'!$A$3:$A$51,0)),"")="",270.04,INDEX('Monitor & Recheck Triggers'!$H$3:$H$51,MATCH($B6,'Monitor & Recheck Triggers'!$A$3:$A$51,0))) -> 272.67 | G6: =E6*F6 -> 10906.8 | H6: 4991.35 | I6: =G6-H6 -> 5915.45 | J6: =IF(H6=0,"",G6/H6-1) -> 1.1851403 | K6: =IFERROR(G6/SUM(G3:G23),"") -> 0.026450158 | L6: =IFERROR(G6/(SUM(G3:G23,G27:G46)),"") -> 0.014962348
A7: JT ULTRA (Fidelity) | B7: KLAC | C7: KLA Corporation | D7: Equity | E7: 100 | F7: =IF(IFERROR(INDEX('Monitor & Recheck Triggers'!$H$3:$H$51,MATCH($B7,'Monitor & Recheck Triggers'!$A$3:$A$51,0)),"")="",206.89,INDEX('Monitor & Recheck Triggers'!$H$3:$H$51,MATCH($B7,'Monitor & Recheck Triggers'!$A$3:$A$51,0))) -> 206.85 | G7: =E7*F7 -> 20685 | H7: 15412.54 | I7: =G7-H7 -> 5272.46 | J7: =IF(H7=0,"",G7/H7-1) -> 0.34208897 | K7: =IFERROR(G7/SUM(G3:G23),"") -> 0.05016334 | L7: =IFERROR(G7/(SUM(G3:G23,G27:G46)),"") -> 0.02837644
A8: JT ULTRA (Fidelity) | B8: MU | C8: Micron Technology | D8: Equity | E8: 7 | F8: =IF(IFERROR(INDEX('Monitor & Recheck Triggers'!$H$3:$H$51,MATCH($B8,'Monitor & Recheck Triggers'!$A$3:$A$51,0)),"")="",1074.89,INDEX('Monitor & Recheck Triggers'!$H$3:$H$51,MATCH($B8,'Monitor & Recheck Triggers'!$A$3:$A$51,0))) -> 1063.96 | G8: =E8*F8 -> 7447.72 | H8: 5836.11 | I8: =G8-H8 -> 1611.61 | J8: =IF(H8=0,"",G8/H8-1) -> 0.27614456 | K8: =IFERROR(G8/SUM(G3:G23),"") -> 0.018061518 | L8: =IFERROR(G8/(SUM(G3:G23,G27:G46)),"") -> 0.010217055
A9: JT ULTRA (Fidelity) | B9: NVDA | C9: NVIDIA Corporation | D9: Equity | E9: 155 | F9: =IF(IFERROR(INDEX('Monitor & Recheck Triggers'!$H$3:$H$51,MATCH($B9,'Monitor & Recheck Triggers'!$A$3:$A$51,0)),"")="",233.95,INDEX('Monitor & Recheck Triggers'!$H$3:$H$51,MATCH($B9,'Monitor & Recheck Triggers'!$A$3:$A$51,0))) -> 238.9 | G9: =E9*F9 -> 37029.5 | H9: 26639.79 | I9: =G9-H9 -> 10389.71 | J9: =IF(H9=0,"",G9/H9-1) -> 0.3900072 | K9: =IFERROR(G9/SUM(G3:G23),"") -> 0.089800502 | L9: =IFERROR(G9/(SUM(G3:G23,G27:G46)),"") -> 0.050798424
A10: JT ULTRA (Fidelity) | B10: PLTR | C10: Palantir Technologies | D10: Equity | E10: 70 | F10: =IF(IFERROR(INDEX('Monitor & Recheck Triggers'!$H$3:$H$51,MATCH($B10,'Monitor & Recheck Triggers'!$A$3:$A$51,0)),"")="",188.75,INDEX('Monitor & Recheck Triggers'!$H$3:$H$51,MATCH($B10,'Monitor & Recheck Triggers'!$A$3:$A$51,0))) -> 189.4 | G10: =E10*F10 -> 13258 | H10: 11612.3 | I10: =G10-H10 -> 1645.7 | J10: =IF(H10=0,"",G10/H10-1) -> 0.14172042 | K10: =IFERROR(G10/SUM(G3:G23),"") -> 0.032152069 | L10: =IFERROR(G10/(SUM(G3:G23,G27:G46)),"") -> 0.01818781
A11: JT ULTRA (Fidelity) | B11: TSM | C11: Taiwan Semiconductor | D11: Equity | E11: 25 | F11: =IF(IFERROR(INDEX('Monitor & Recheck Triggers'!$H$3:$H$51,MATCH($B11,'Monitor & Recheck Triggers'!$A$3:$A$51,0)),"")="",472.78,INDEX('Monitor & Recheck Triggers'!$H$3:$H$51,MATCH($B11,'Monitor & Recheck Triggers'!$A$3:$A$51,0))) -> 485.8 | G11: =E11*F11 -> 12145 | H11: 6069.64 | I11: =G11-H11 -> 6075.36 | J11: =IF(H11=0,"",G11/H11-1) -> 1.0009424 | K11: =IFERROR(G11/SUM(G3:G23),"") -> 0.029452925 | L11: =IFERROR(G11/(SUM(G3:G23,G27:G46)),"") -> 0.016660956
A12: JT ULTRA (Fidelity) | B12: VRT | C12: Vertiv Holdings | D12: Equity | E12: 30 | F12: =IF(IFERROR(INDEX('Monitor & Recheck Triggers'!$H$3:$H$51,MATCH($B12,'Monitor & Recheck Triggers'!$A$3:$A$51,0)),"")="",252.18,INDEX('Monitor & Recheck Triggers'!$H$3:$H$51,MATCH($B12,'Monitor & Recheck Triggers'!$A$3:$A$51,0))) -> 253.62 | G12: =E12*F12 -> 7608.6 | H12: 7876.8 | I12: =G12-H12 -> -268.2 | J12: =IF(H12=0,"",G12/H12-1) -> -0.03404936 | K12: =IFERROR(G12/SUM(G3:G23),"") -> 0.01845167 | L12: =IFERROR(G12/(SUM(G3:G23,G27:G46)),"") -> 0.010437756
A13: JT ULTRA (Fidelity) | B13: V | C13: Visa Inc. | D13: Equity | E13: 50 | F13: =IF(IFERROR(INDEX('Monitor & Recheck Triggers'!$H$3:$H$51,MATCH($B13,'Monitor & Recheck Triggers'!$A$3:$A$51,0)),"")="",360.66,INDEX('Monitor & Recheck Triggers'!$H$3:$H$51,MATCH($B13,'Monitor & Recheck Triggers'!$A$3:$A$51,0))) -> 369.71 | G13: =E13*F13 -> 18485.5 | H13: 18448.63 | I13: =G13-H13 -> 36.87 | J13: =IF(H13=0,"",G13/H13-1) -> 0.0019985224 | K13: =IFERROR(G13/SUM(G3:G23),"") -> 0.044829317 | L13: =IFERROR(G13/(SUM(G3:G23,G27:G46)),"") -> 0.025359086 | M13: NEW position 9/8/26 -- DCA-TRANCHE-2, opened per Entry Checklist authorization (Composite 86.4, STRONG BUY). 2 lots: 25sh @ $368.38 + 25sh @ $369.565.
A14: JT ULTRA (Fidelity) | B14: FZDXX | C14: Fidelity Money Market Premium | D14: Cash | E14: 38154.18 | F14: 1 | G14: =E14*F14 -> 38154.18 | H14: 38154.18 | I14: =G14-H14 -> 0 | J14: =IF(H14=0,"",G14/H14-1) -> 0 | K14: =IFERROR(G14/SUM(G3:G23),"") -> 0.092527972 | L14: =IFERROR(G14/(SUM(G3:G23,G27:G46)),"") -> 0.052341301
A15: JT ULTRA (Fidelity) | B15: FZFXX | C15: Fidelity Core Money Market | D15: Cash | E15: 1174.01 | F15: 1 | G15: =E15*F15 -> 1174.01 | H15: 1174.01 | I15: =G15-H15 -> 0 | J15: =IF(H15=0,"",G15/H15-1) -> 0 | K15: =IFERROR(G15/SUM(G3:G23),"") -> 0.0028470999 | L15: =IFERROR(G15/(SUM(G3:G23,G27:G46)),"") -> 0.0016105499
A16: JT ULTRA (Fidelity) | B16: DVY | C16: iShares Select Dividend ETF | D16: Equity | E16: 150 | F16: =IF(IFERROR(INDEX('Monitor & Recheck Triggers'!$H$3:$H$51,MATCH($B16,'Monitor & Recheck Triggers'!$A$3:$A$51,0)),"")="",153.05,INDEX('Monitor & Recheck Triggers'!$H$3:$H$51,MATCH($B16,'Monitor & Recheck Triggers'!$A$3:$A$51,0))) -> 153.05 | G16: =E16*F16 -> 22957.5 | H16: 24518.25 | I16: =G16-H16 -> -1560.75 | J16: =IF(H16=0,"",G16/H16-1) -> -0.063656664 | K16: =IFERROR(G16/SUM(G3:G23),"") -> 0.055674395 | L16: =IFERROR(G16/(SUM(G3:G23,G27:G46)),"") -> 0.031493939 | M16: NEW position since 8/5/26 -- cash/dry powder per Alan 9/7/26, not a scored Landry position.
A17: JT ULTRA (Fidelity) | B17: VFLO | C17: VictoryShares Free Cash Flow ETF | D17: Equity | E17: 451.304 | F17: =IF(IFERROR(INDEX('Monitor & Recheck Triggers'!$H$3:$H$51,MATCH($B17,'Monitor & Recheck Triggers'!$A$3:$A$51,0)),"")="",51.82,INDEX('Monitor & Recheck Triggers'!$H$3:$H$51,MATCH($B17,'Monitor & Recheck Triggers'!$A$3:$A$51,0))) -> 51.82 | G17: =E17*F17 -> 23386.573 | H17: 24999.99 | I17: =G17-H17 -> -1613.4167 | J17: =IF(H17=0,"",G17/H17-1) -> -0.064536695 | K17: =IFERROR(G17/SUM(G3:G23),"") -> 0.056714944 | L17: =IFERROR(G17/(SUM(G3:G23,G27:G46)),"") -> 0.032082558 | M17: NEW to this account since 8/5/26 (already held in Self-Directed) -- cash/dry powder per Alan 9/7/26, not a scored Landry position.
A18: JT ULTRA (Fidelity) | B18: SCHD | C18: Schwab US Dividend Equity ETF | D18: Equity | E18: 700 | F18: =IF(IFERROR(INDEX('Monitor & Recheck Triggers'!$H$3:$H$51,MATCH($B18,'Monitor & Recheck Triggers'!$A$3:$A$51,0)),"")="",32.72,INDEX('Monitor & Recheck Triggers'!$H$3:$H$51,MATCH($B18,'Monitor & Recheck Triggers'!$A$3:$A$51,0))) -> 32.72 | G18: =E18*F18 -> 22904 | H18: 24377.5 | I18: =G18-H18 -> -1473.5 | J18: =IF(H18=0,"",G18/H18-1) -> -0.060445083 | K18: =IFERROR(G18/SUM(G3:G23),"") -> 0.055544652 | L18: =IFERROR(G18/(SUM(G3:G23,G27:G46)),"") -> 0.031420546 | M18: NEW position since 8/5/26 -- cash/dry powder per Alan 9/7/26, not a scored Landry position.
A19: JT ULTRA (Fidelity) | B19: VYM | C19: Vanguard High Dividend Yield ETF | D19: Equity | E19: 150 | F19: =IF(IFERROR(INDEX('Monitor & Recheck Triggers'!$H$3:$H$51,MATCH($B19,'Monitor & Recheck Triggers'!$A$3:$A$51,0)),"")="",156.46,INDEX('Monitor & Recheck Triggers'!$H$3:$H$51,MATCH($B19,'Monitor & Recheck Triggers'!$A$3:$A$51,0))) -> 156.46 | G19: =E19*F19 -> 23469 | H19: 24598.5 | I19: =G19-H19 -> -1129.5 | J19: =IF(H19=0,"",G19/H19-1) -> -0.045917434 | K19: =IFERROR(G19/SUM(G3:G23),"") -> 0.056914838 | L19: =IFERROR(G19/(SUM(G3:G23,G27:G46)),"") -> 0.032195634 | M19: NEW position since 8/5/26 -- cash/dry powder per Alan 9/7/26, not a scored Landry position.
A20: JT ULTRA (Fidelity) | B20: MLPI | C20: NEOS MLP & Energy Income ETF | D20: Equity | E20: 1000 | F20: =IF(IFERROR(INDEX('Monitor & Recheck Triggers'!$H$3:$H$51,MATCH($B20,'Monitor & Recheck Triggers'!$A$3:$A$51,0)),"")="",51.17,INDEX('Monitor & Recheck Triggers'!$H$3:$H$51,MATCH($B20,'Monitor & Recheck Triggers'!$A$3:$A$51,0))) -> 51.17 | G20: =E20*F20 -> 51170 | H20: 53709 | I20: =G20-H20 -> -2539 | J20: =IF(H20=0,"",G20/H20-1) -> -0.047273269 | K20: =IFERROR(G20/SUM(G3:G23),"") -> 0.12409273 | L20: =IFERROR(G20/(SUM(G3:G23,G27:G46)),"") -> 0.07019688 | M20: NEW position since 8/5/26 -- cash/dry powder per Alan 9/7/26, not a scored Landry position.
A21: JT ULTRA (Fidelity) | B21: SPMO | C21: Invesco S&P 500 Momentum ETF | D21: Equity | E21: 100 | F21: =IF(IFERROR(INDEX('Monitor & Recheck Triggers'!$H$3:$H$51,MATCH($B21,'Monitor & Recheck Triggers'!$A$3:$A$51,0)),"")="",153.23,INDEX('Monitor & Recheck Triggers'!$H$3:$H$51,MATCH($B21,'Monitor & Recheck Triggers'!$A$3:$A$51,0))) -> 153.23 | G21: =E21*F21 -> 15323 | H21: 14696.99 | I21: =G21-H21 -> 626.01 | J21: =IF(H21=0,"",G21/H21-1) -> 0.042594436 | K21: =IFERROR(G21/SUM(G3:G23),"") -> 0.037159916 | L21: =IFERROR(G21/(SUM(G3:G23,G27:G46)),"") -> 0.021020652 | M21: NEW to this account since 8/5/26 (already held in Self-Directed) -- cash/dry powder per Alan 9/7/26, not a scored Landry position.
A22: JT ULTRA (Fidelity) | B22: GE | C22: GE Aerospace | D22: Equity | E22: 75 | F22: =IF(IFERROR(INDEX('Monitor & Recheck Triggers'!$H$3:$H$51,MATCH($B22,'Monitor & Recheck Triggers'!$A$3:$A$51,0)),"")="",309.56,INDEX('Monitor & Recheck Triggers'!$H$3:$H$51,MATCH($B22,'Monitor & Recheck Triggers'!$A$3:$A$51,0))) -> 306.34 | G22: =E22*F22 -> 22975.5 | H22: 23603.25 | I22: =G22-H22 -> -627.75 | J22: =IF(H22=0,"",G22/H22-1) -> -0.026595914 | K22: =IFERROR(G22/SUM(G3:G23),"") -> 0.055718047 | L22: =IFERROR(G22/(SUM(G3:G23,G27:G46)),"") -> 0.031518632 | M22: NEW position 9/30/26 -- DCA-CATCHUP-1, opened per Composite 84.2 STRONG BUY (rescored 9/13/26, reconfirmed fresh 9/29/26, zero Tier 1 drift). 75sh @ $314.71.
A23: JT ULTRA (Fidelity) | B23: NFLX | C23: Netflix, Inc. | D23: Equity | E23: 300 | F23: =IF(IFERROR(INDEX('Monitor & Recheck Triggers'!$H$3:$H$51,MATCH($B23,'Monitor & Recheck Triggers'!$A$3:$A$51,0)),"")="",67.06,INDEX('Monitor & Recheck Triggers'!$H$3:$H$51,MATCH($B23,'Monitor & Recheck Triggers'!$A$3:$A$51,0))) -> 67.5 | G23: =E23*F23 -> 20250 | H23: 20938.5 | I23: =G23-H23 -> -688.5 | J23: =IF(H23=0,"",G23/H23-1) -> -0.032882012 | K23: =IFERROR(G23/SUM(G3:G23),"") -> 0.049108418 | L23: =IFERROR(G23/(SUM(G3:G23,G27:G46)),"") -> 0.027779691 | M23: NEW position 9/30/26 -- DCA-CATCHUP-1, opened per Composite 83.8 STRONG BUY (rescored 9/13/26, reconfirmed fresh 9/29/26, zero Tier 1 drift). 300sh @ $69.795.
A24: Positions | B24: =SUBTOTAL(103,B3:B23) -> 21 | C24: JT ULTRA (Fidelity) SUBTOTAL | G24: =SUM(G3:G23) -> 412352.93 | H24: =SUM(H3:H23) -> 386993.25 | I24: =SUM(I3:I23) -> 25359.678 | J24: =CurrentPositionsTable[[#This Row],[Unrealized G/L ($)]]/CurrentPositionsTable[[#This Row],[Cost Basis ($)]] -> 0.065530027 | K24: =SUM(K3:K23) -> 1 | L24: =SUM(L3:L23) -> 0.56568085
I25: Excluding Cash | J25: =I24/(H24-H14-H13) -> 0.076756695
A27: Self-Directed (Chase) | B27: VMFXX | C27: Vanguard Federal Money Market | D27: Cash | E27: 36854.47 | F27: 1 | G27: =E27*F27 -> 36854.47 | H27: 36854.47 | I27: =G27-H27 -> 0 | J27: =IF(H27=0,"",G27/H27-1) -> 0 | K27: =IFERROR(G27/SUM(G27:G46),"") -> 0.1164082 | L27: =IFERROR(G27/(SUM(G3:G23,G27:G46)),"") -> 0.050558311
A28: Self-Directed (Chase) | B28: JEPQ | C28: JPMorgan Nasdaq Equity Premium Income ETF | D28: Alt. Assets | E28: 850.35693 | F28: =IF(IFERROR(INDEX('Monitor & Recheck Triggers'!$H$3:$H$51,MATCH($B28,'Monitor & Recheck Triggers'!$A$3:$A$51,0)),"")="",61.04,INDEX('Monitor & Recheck Triggers'!$H$3:$H$51,MATCH($B28,'Monitor & Recheck Triggers'!$A$3:$A$51,0))) -> 61.04 | G28: =E28*F28 -> 51905.787 | H28: 43005.36 | I28: =G28-H28 -> 8900.427 | J28: =IF(H28=0,"",G28/H28-1) -> 0.20696088 | K28: =IFERROR(G28/SUM(G27:G46),"") -> 0.16394916 | L28: =IFERROR(G28/(SUM(G3:G23,G27:G46)),"") -> 0.071206259 | M28: Qty 840.4->850.4sh since 8/5, likely DRIP reinvestment. Reclassified as cash/dry powder per Alan 9/7/26, not a scored Landry position.
A29: Self-Directed (Chase) | B29: AVUV | C29: Avantis US Small Cap Value ETF | D29: Equity | E29: 400.00001 | F29: =IF(IFERROR(INDEX('Monitor & Recheck Triggers'!$H$3:$H$51,MATCH($B29,'Monitor & Recheck Triggers'!$A$3:$A$51,0)),"")="",120.03,INDEX('Monitor & Recheck Triggers'!$H$3:$H$51,MATCH($B29,'Monitor & Recheck Triggers'!$A$3:$A$51,0))) -> 120.03 | G29: =E29*F29 -> 48012.001 | H29: 45116.29 | I29: =G29-H29 -> 2895.7112 | J29: =IF(H29=0,"",G29/H29-1) -> 0.064183274 | K29: =IFERROR(G29/SUM(G27:G46),"") -> 0.15165028 | L29: =IFERROR(G29/(SUM(G3:G23,G27:G46)),"") -> 0.065864621 | M29: BOUGHT +193.58sh 8/7/26 @ $126.66 -- consolidation target from CALF
A30: Self-Directed (Chase) | B30: CALF | C30: Pacer US Small Cap Cash Cows ETF | D30: Equity | E30: 0 | F30: =IF(IFERROR(INDEX('Monitor & Recheck Triggers'!$H$3:$H$51,MATCH($B30,'Monitor & Recheck Triggers'!$A$3:$A$51,0)),"")="",56.12,INDEX('Monitor & Recheck Triggers'!$H$3:$H$51,MATCH($B30,'Monitor & Recheck Triggers'!$A$3:$A$51,0))) -> 56.12 | G30: =E30*F30 -> 0 | H30: 0 | I30: =G30-H30 -> 0 | J30: =IF(H30=0,"",G30/H30-1) | K30: =IFERROR(G30/SUM(G27:G46),"") -> 0 | L30: =IFERROR(G30/(SUM(G3:G23,G27:G46)),"") -> 0 | M30: SOLD 8/7/26 -- confirmed: -409.55sh, $23,016.52 proceeds. Consolidated into AVUV.
A31: Self-Directed (Chase) | B31: HELO | C31: JPMorgan Hedged Equity Laddered Overlay ETF | D31: Alt. Assets | E31: 500 | F31: =IF(IFERROR(INDEX('Monitor & Recheck Triggers'!$H$3:$H$51,MATCH($B31,'Monitor & Recheck Triggers'!$A$3:$A$51,0)),"")="",69.42,INDEX('Monitor & Recheck Triggers'!$H$3:$H$51,MATCH($B31,'Monitor & Recheck Triggers'!$A$3:$A$51,0))) -> 69.42 | G31: =E31*F31 -> 34710 | H31: 30666 | I31: =G31-H31 -> 4044 | J31: =IF(H31=0,"",G31/H31-1) -> 0.13187243 | K31: =IFERROR(G31/SUM(G27:G46),"") -> 0.1096347 | L31: =IFERROR(G31/(SUM(G3:G23,G27:G46)),"") -> 0.047616449 | M31: BOUGHT +200sh since 8/5 (300->500sh) -- expanding income sleeve. Reclassified as cash/dry powder per Alan 9/7/26, not a scored Landry position.
A32: Self-Directed (Chase) | B32: AVGO | C32: Broadcom Inc. | D32: Equity | E32: 35.07587 | F32: =IF(IFERROR(INDEX('Monitor & Recheck Triggers'!$H$3:$H$51,MATCH($B32,'Monitor & Recheck Triggers'!$A$3:$A$51,0)),"")="",355.14,INDEX('Monitor & Recheck Triggers'!$H$3:$H$51,MATCH($B32,'Monitor & Recheck Triggers'!$A$3:$A$51,0))) -> 362.51 | G32: =E32*F32 -> 12715.354 | H32: 12653.43 | I32: =G32-H32 -> 61.923634 | J32: =IF(H32=0,"",G32/H32-1) -> 0.004893822 | K32: =IFERROR(G32/SUM(G27:G46),"") -> 0.040162603 | L32: =IFERROR(G32/(SUM(G3:G23,G27:G46)),"") -> 0.017443388
A33: Self-Directed (Chase) | B33: NVDA | C33: NVIDIA Corporation | D33: Equity | E33: 59.02188 | F33: =IF(IFERROR(INDEX('Monitor & Recheck Triggers'!$H$3:$H$51,MATCH($B33,'Monitor & Recheck Triggers'!$A$3:$A$51,0)),"")="",233.95,INDEX('Monitor & Recheck Triggers'!$H$3:$H$51,MATCH($B33,'Monitor & Recheck Triggers'!$A$3:$A$51,0))) -> 238.9 | G33: =E33*F33 -> 14100.327 | H33: 11377.73 | I33: =G33-H33 -> 2722.5971 | J33: =IF(H33=0,"",G33/H33-1) -> 0.23929177 | K33: =IFERROR(G33/SUM(G27:G46),"") -> 0.044537168 | L33: =IFERROR(G33/(SUM(G3:G23,G27:G46)),"") -> 0.019343345
A34: Self-Directed (Chase) | B34: VRTX | C34: Vertex Pharmaceuticals | D34: Equity | E34: 65 | F34: =IF(IFERROR(INDEX('Monitor & Recheck Triggers'!$H$3:$H$51,MATCH($B34,'Monitor & Recheck Triggers'!$A$3:$A$51,0)),"")="",504.73,INDEX('Monitor & Recheck Triggers'!$H$3:$H$51,MATCH($B34,'Monitor & Recheck Triggers'!$A$3:$A$51,0))) -> 503.5 | G34: =E34*F34 -> 32727.5 | H34: 31479.64 | I34: =G34-H34 -> 1247.86 | J34: =IF(H34=0,"",G34/H34-1) -> 0.039640225 | K34: =IFERROR(G34/SUM(G27:G46),"") -> 0.10337279 | L34: =IFERROR(G34/(SUM(G3:G23,G27:G46)),"") -> 0.044896783 | M34: BOUGHT +15sh 9/8/26 @ ~$527.47 ($7,912.09) -- DCA-TRANCHE-2 diversifier add.
A35: Self-Directed (Chase) | B35: SPMO | C35: Invesco S&P 500 Momentum ETF | D35: Equity | E35: 76.93745 | F35: =IF(IFERROR(INDEX('Monitor & Recheck Triggers'!$H$3:$H$51,MATCH($B35,'Monitor & Recheck Triggers'!$A$3:$A$51,0)),"")="",153.23,INDEX('Monitor & Recheck Triggers'!$H$3:$H$51,MATCH($B35,'Monitor & Recheck Triggers'!$A$3:$A$51,0))) -> 153.23 | G35: =E35*F35 -> 11789.125 | H35: 9318.79 | I35: =G35-H35 -> 2470.3355 | J35: =IF(H35=0,"",G35/H35-1) -> 0.26509187 | K35: =IFERROR(G35/SUM(G27:G46),"") -> 0.037237027 | L35: =IFERROR(G35/(SUM(G3:G23,G27:G46)),"") -> 0.016172754
A36: Self-Directed (Chase) | B36: VFLO | C36: VictoryShares Free Cash Flow ETF | D36: Equity | E36: 200 | F36: =IF(IFERROR(INDEX('Monitor & Recheck Triggers'!$H$3:$H$51,MATCH($B36,'Monitor & Recheck Triggers'!$A$3:$A$51,0)),"")="",51.82,INDEX('Monitor & Recheck Triggers'!$H$3:$H$51,MATCH($B36,'Monitor & Recheck Triggers'!$A$3:$A$51,0))) -> 51.82 | G36: =E36*F36 -> 10364 | H36: 9257 | I36: =G36-H36 -> 1107 | J36: =IF(H36=0,"",G36/H36-1) -> 0.11958518 | K36: =IFERROR(G36/SUM(G27:G46),"") -> 0.032735638 | L36: =IFERROR(G36/(SUM(G3:G23,G27:G46)),"") -> 0.014217715
A37: Self-Directed (Chase) | B37: ANET | C37: Arista Networks | D37: Equity | E37: 50 | F37: =IF(IFERROR(INDEX('Monitor & Recheck Triggers'!$H$3:$H$51,MATCH($B37,'Monitor & Recheck Triggers'!$A$3:$A$51,0)),"")="",207.35,INDEX('Monitor & Recheck Triggers'!$H$3:$H$51,MATCH($B37,'Monitor & Recheck Triggers'!$A$3:$A$51,0))) -> 206.9 | G37: =E37*F37 -> 10345 | H37: 7394.5 | I37: =G37-H37 -> 2950.5 | J37: =IF(H37=0,"",G37/H37-1) -> 0.39901278 | K37: =IFERROR(G37/SUM(G27:G46),"") -> 0.032675625 | L37: =IFERROR(G37/(SUM(G3:G23,G27:G46)),"") -> 0.01419165
A38: Self-Directed (Chase) | B38: CRWD | C38: CrowdStrike Holdings | D38: Equity | E38: 45 | F38: =IF(IFERROR(INDEX('Monitor & Recheck Triggers'!$H$3:$H$51,MATCH($B38,'Monitor & Recheck Triggers'!$A$3:$A$51,0)),"")="",270.04,INDEX('Monitor & Recheck Triggers'!$H$3:$H$51,MATCH($B38,'Monitor & Recheck Triggers'!$A$3:$A$51,0))) -> 272.67 | G38: =E38*F38 -> 12270.15 | H38: 7099.31 | I38: =G38-H38 -> 5170.84 | J38: =IF(H38=0,"",G38/H38-1) -> 0.72835811 | K38: =IFERROR(G38/SUM(G27:G46),"") -> 0.038756387 | L38: =IFERROR(G38/(SUM(G3:G23,G27:G46)),"") -> 0.016832641
A39: Self-Directed (Chase) | B39: PLD | C39: Prologis Inc. | D39: Equity | E39: 125.44837 | F39: =IF(IFERROR(INDEX('Monitor & Recheck Triggers'!$H$3:$H$51,MATCH($B39,'Monitor & Recheck Triggers'!$A$3:$A$51,0)),"")="",128.91,INDEX('Monitor & Recheck Triggers'!$H$3:$H$51,MATCH($B39,'Monitor & Recheck Triggers'!$A$3:$A$51,0))) -> 128.08 | G39: =E39*F39 -> 16067.427 | H39: 16585.43 | I39: =G39-H39 -> -518.00277 | J39: =IF(H39=0,"",G39/H39-1) -> -0.031232399 | K39: =IFERROR(G39/SUM(G27:G46),"") -> 0.050750433 | L39: =IFERROR(G39/(SUM(G3:G23,G27:G46)),"") -> 0.022041885 | M39: BOUGHT +64sh 8/7/26 @ $139.92 -- DCA tranche 1 diversifier add
A40: Self-Directed (Chase) | B40: SFM | C40: Sprouts Farmers Market | D40: Equity | E40: 0 | F40: =IF(IFERROR(INDEX('Monitor & Recheck Triggers'!$H$3:$H$51,MATCH($B40,'Monitor & Recheck Triggers'!$A$3:$A$51,0)),"")="",86.07,INDEX('Monitor & Recheck Triggers'!$H$3:$H$51,MATCH($B40,'Monitor & Recheck Triggers'!$A$3:$A$51,0))) -> 64.92 | G40: =E40*F40 -> 0 | H40: 0 | I40: =G40-H40 -> 0 | J40: =IF(H40=0,"",G40/H40-1) | K40: =IFERROR(G40/SUM(G27:G46),"") -> 0 | L40: =IFERROR(G40/(SUM(G3:G23,G27:G46)),"") -> 0 | M40: SOLD 08/07/26 -- confirmed: -65 sh, $5,601.58 proceeds. Rule 3 Avoid. Proceeds added to VMFXX.
A41: Self-Directed (Chase) | B41: TSLA | C41: Tesla Inc. | D41: Equity | E41: 0 | F41: =IF(IFERROR(INDEX('Monitor & Recheck Triggers'!$H$3:$H$51,MATCH($B41,'Monitor & Recheck Triggers'!$A$3:$A$51,0)),"")="",327.35,INDEX('Monitor & Recheck Triggers'!$H$3:$H$51,MATCH($B41,'Monitor & Recheck Triggers'!$A$3:$A$51,0))) -> 378.73 | G41: =E41*F41 -> 0 | H41: 0 | I41: =G41-H41 -> 0 | J41: =IF(H41=0,"",G41/H41-1) | K41: =IFERROR(G41/SUM(G27:G46),"") -> 0 | L41: =IFERROR(G41/(SUM(G3:G23,G27:G46)),"") -> 0 | M41: SOLD 08/07/26 -- confirmed: -15 sh, $4,783.25 proceeds. Rule 3 Avoid. Proceeds added to VMFXX.
A42: Self-Directed (Chase) | B42: VGT | C42: Vanguard Information Technology ETF | D42: Equity | E42: 0 | F42: =IF(IFERROR(INDEX('Monitor & Recheck Triggers'!$H$3:$H$51,MATCH($B42,'Monitor & Recheck Triggers'!$A$3:$A$51,0)),"")="",120.16,INDEX('Monitor & Recheck Triggers'!$H$3:$H$51,MATCH($B42,'Monitor & Recheck Triggers'!$A$3:$A$51,0))) -> 120.16 | G42: =E42*F42 -> 0 | H42: 0 | I42: =G42-H42 -> 0 | J42: =IF(H42=0,"",G42/H42-1) | K42: =IFERROR(G42/SUM(G27:G46),"") -> 0 | L42: =IFERROR(G42/(SUM(G3:G23,G27:G46)),"") -> 0 | M42: SOLD 8/7/26 -- confirmed: -40.18sh, $4,851.48 proceeds. Worst correlation offender (5 violations), cleared per plan.
A43: Self-Directed (Chase) | B43: QACDS | C43: Schwab Cash Features (Sweep) | D43: Cash | E43: 10849.71 | F43: 1 | G43: =E43*F43 -> 10849.71 | H43: 10849.71 | I43: =G43-H43 -> 0 | J43: =IF(H43=0,"",G43/H43-1) -> 0 | K43: =IFERROR(G43/SUM(G27:G46),"") -> 0.034269798 | L43: =IFERROR(G43/(SUM(G3:G23,G27:G46)),"") -> 0.014884029
A44: Self-Directed (Chase) | B44: ONON | C44: On Holding AG | D44: Equity | E44: 0 | F44: =IF(IFERROR(INDEX('Monitor & Recheck Triggers'!$H$3:$H$51,MATCH($B44,'Monitor & Recheck Triggers'!$A$3:$A$51,0)),"")="",37.61,INDEX('Monitor & Recheck Triggers'!$H$3:$H$51,MATCH($B44,'Monitor & Recheck Triggers'!$A$3:$A$51,0))) -> 31.88 | G44: =E44*F44 -> 0 | H44: 0 | I44: =G44-H44 -> 0 | J44: =IF(H44=0,"",G44/H44-1) | K44: =IFERROR(G44/SUM(G27:G46),"") -> 0 | L44: =IFERROR(G44/(SUM(G3:G23,G27:G46)),"") -> 0 | M44: SOLD 08/07/26 -- confirmed: -100 sh, $3,764.92 proceeds. Rule 3 Avoid. Proceeds added to VMFXX.
A45: Self-Directed (Chase) | B45: PLTR | C45: Palantir Technologies | D45: Equity | E45: 20 | F45: =IF(IFERROR(INDEX('Monitor & Recheck Triggers'!$H$3:$H$51,MATCH($B45,'Monitor & Recheck Triggers'!$A$3:$A$51,0)),"")="",188.75,INDEX('Monitor & Recheck Triggers'!$H$3:$H$51,MATCH($B45,'Monitor & Recheck Triggers'!$A$3:$A$51,0))) -> 189.4 | G45: =E45*F45 -> 3788 | H45: 3178 | I45: =G45-H45 -> 610 | J45: =IF(H45=0,"",G45/H45-1) -> 0.19194462 | K45: =IFERROR(G45/SUM(G27:G46),"") -> 0.011964743 | L45: =IFERROR(G45/(SUM(G3:G23,G27:G46)),"") -> 0.0051965171
A46: Self-Directed (Chase) | B46: JEPI | C46: JPMorgan Equity Premium Income ETF | D46: Alternative Assets | E46: 180 | F46: =IF(IFERROR(INDEX('Monitor & Recheck Triggers'!$H$3:$H$51,MATCH($B46,'Monitor & Recheck Triggers'!$A$3:$A$51,0)),"")="",56.1,INDEX('Monitor & Recheck Triggers'!$H$3:$H$51,MATCH($B46,'Monitor & Recheck Triggers'!$A$3:$A$51,0))) -> 56.1 | G46: =E46*F46 -> 10098 | H46: 10500.57 | I46: =G46-H46 -> -402.57 | J46: =IF(H46=0,"",G46/H46-1) -> -0.038337919 | K46: =IFERROR(G46/SUM(G27:G46),"") -> 0.031895453 | L46: =IFERROR(G46/(SUM(G3:G23,G27:G46)),"") -> 0.013852806 | M46: NEW position since 8/5/26 -- cash/dry powder per Alan 9/7/26, not a scored Landry position.
A47: Positions | B47: =SUBTOTAL(103,B27:B46) -> 20 | C47: Self-Directed (Chase) SUBTOTAL | G47: =SUM(G27:G46) -> 316596.85 | H47: =SUM(H27:H46) -> 285336.23 | I47: =SUM(I27:I46) -> 31260.622 | J47: =CurrentPositionsTable[[#This Row],[Unrealized G/L ($)]]/CurrentPositionsTable[[#This Row],[Cost Basis ($)]] -> 0.10955714 | K47: =SUM(K27:K46) -> 1 | L47: =SUM(L27:L46) -> 0.43431915
I48: Excluding Cash | J48: =I47/(H47-H43-H27) -> 0.13155053
C50: COMBINED PORTFOLIO TOTAL | G50: =SUM(G3:G23)+SUM(G27:G46) -> 728949.78 | H50: =SUM(H3:H23)+SUM(H27:H46) -> 672329.48 | I50: =SUM(I3:I23)+SUM(I27:I46) -> 56620.3
C51: Cash / Cash Equivalents | G51: =SUM(G14:G21)+G27+G28+G29+G31+G35+G36+G43+G46 -> 413121.36 | H51: =SUM(H14:H21)+H27+H28+H29+H31+H35+H36+H43+H46 -> 401796.61 | I51: =G51-H51 -> 11324.747 | L51: =IFERROR(G51/G50,"") -> 0.566735 | M51: Actual cash (FZDXX+FZFXX+VMFXX+QACDS) + temporary yield-bearing cash buckets (AVUV, SPMO x2, VFLO x2, DVY, SCHD, VYM, MLPI, JEPQ, HELO, JEPI) held for liquidity/dry powder, not scored as long-term Landry positions. Policy confirmed by Alan 9/7/26. V (Visa) is NOT in this bucket -- it's a real, Entry-Checklist-authorized Landry position (Composite 86.4, STRONG BUY).
A52: NOTE: JT ULTRA's ASML/PLTR/MU quantities reflect trims already executed from the earlier rebalance session; SWAN is not currently held in this export (flagging in case that wasn't intentional). 9/7/26: refreshed both accounts from fresh Fidelity/Chase exports (as of 9/4/26 close). Alan confirmed the new/expanded positions (DVY, SCHD, VYM, MLPI, JEPI, plus additions to HELO/JEPQ and VFLO/SPMO now in both accounts) are a deliberate move of idle cash into better-paying temporary buckets -- no strategy change. See Journal and [[price_history_ownership]]/[[etf_scope_todo]] memory for context. 9/8/26: DCA-TRANCHE-2 executed. VRTX +15sh @ ~$527.47 ($7,912.09, Chase). V (Visa) opened new, 50sh across 2 lots ($9,209.50 + $9,239.13 = $18,448.63, Fidelity). PLD skipped this tranche -- Fidelity's Equity Summary Score (LSEG StarMine) showed Very Bearish (0.7/10) with 2 recent Sell opinions; traditional sell-side consensus stayed clean, but Alan chose to wait/watch rather than add. Total tranche $26,360.72 vs. $24,000 target. See Journal 9/8/26. 10/4/26: tied to the 9/30/26 statements (Fidelity X64-063711 $406,372.50; Chase 735-43693 $315,412.66). Every share count and cost basis already matched. Cash corrected: FZDXX 92,777.34 -> 38,154.18 (statement 82,695.93 less the $44,541.75 GE/NFLX buy that settled 10/1), FZFXX 0 -> 1,174.01, QACDS 1,853.89 -> 10,849.71; cash cost basis set equal to value (cash has no gain/loss -- this also clears the understated combined unrealized G/L). The old FZDXX figure had ignored September's outflows ($36,519.99 withdrawn, $18,448.63 of Visa buys). Prices are still the workbook's own (refresh in Excel), which is why the combined total here still reads about $10.4K above the statements. See Journal row 81.

Sheet Monitor & Recheck Triggers
A1: Recheck triggers for every name that's been scored, not just Watch List holdings. Current Price, Insider Activity, and Analyst Shift are Claude-populated (STOCKHISTORY formula + manual recalc for price; SEC EDGAR and yfinance consensus data for the other two, refreshed periodically, not live). Recheck Status calculates automatically from all signals together. For held positions, Last Score (cols C-G) mirrors the Scoring row -- `python -m landry monitor stamp` does it after any re-score or Decision change -- and the insider / analyst signals (K-N) are refreshed monthly with `python -m landry monitor refresh` (dated in Q1); `landry audit` holds both (Alan, 10/5/26). | P1: Insider / analyst signals refreshed | Q1: 46300
A2: Ticker | B2: Category | C2: Last Score Date | D2: Last Composite | E2: Last Tier 1 Wtd Avg | F2: Last Decision | G2: Price at Last Score | H2: Current Price | I2: % Price Change | J2: Next/Last Earnings Date | K2: Insider Activity? (Y/N) | L2: Insider Note | M2: Analyst Shift? (Y/N) | N2: Analyst Shift Note | O2: Days Since Last Score | P2: Recheck Status | Q2: Notes
A3: ADBE | B3: Owned | C3: 46295 | D3: 85.8 | E3: 4.57 | F3: STRONG BUY | G3: 239.94 | H3: {=IFERROR(INDEX(_xlfn.STOCKHISTORY(A3,TODAY()-5,TODAY(),0,0,1),ROWS(_xlfn.STOCKHISTORY(A3,TODAY()-5,TODAY(),0,0,1)),1),"")} -> 238.785 | I3: =IF(OR(G3="",H3=""),"",H3/G3-1) -> -0.0048137034 | J3: 46365 | K3: Y | L3: 2026-09-18: NARAYEN SHANTANU (Chair and CEO) sold $2,091,376, 2% of holding (+11 more in last 30d) | M3: N | O3: =IF(C3="","",TODAY()-C3) -> 6 | P3: =IF(A3="","",IF(O3>180,"DUE — STALE (>180 days)",IF(J3<>"",IF(ABS(J3-TODAY())<=7,"DUE — EARNINGS WINDOW",IF(I3<>"",IF(ABS(I3)>=0.2,"DUE — PRICE MOVE ±20%",IF(K3="Y","DUE — INSIDER ACTIVITY",IF(I3<>"",IF(ABS(I3)>=0.15,"WATCH — PRICE MOVE ±15%",IF(M3="Y","WATCH — ANALYST SHIFT","Monitor Only")),IF(M3="Y","WATCH — ANALYST SHIFT","Monitor Only")))),IF(K3="Y","DUE — INSIDER ACTIVITY",IF(I3<>"",IF(ABS(I3)>=0.15,"WATCH — PRICE MOVE ±15%",IF(M3="Y","WATCH — ANALYST SHIFT","Monitor Only")),IF(M3="Y","WATCH — ANALYST SHIFT","Monitor Only"))))),IF(I3<>"",IF(ABS(I3)>=0.2,"DUE — PRICE MOVE ±20%",IF(K3="Y","DUE — INSIDER ACTIVITY",IF(I3<>"",IF(ABS(I3)>=0.15,"WATCH — PRICE MOVE ±15%",IF(M3="Y","WATCH — ANALYST SHIFT","Monitor Only")),IF(M3="Y","WATCH — ANALYST SHIFT","Monitor Only")))),IF(K3="Y","DUE — INSIDER ACTIVITY",IF(I3<>"",IF(ABS(I3)>=0.15,"WATCH — PRICE MOVE ±15%",IF(M3="Y","WATCH — ANALYST SHIFT","Monitor Only")),IF(M3="Y","WATCH — ANALYST SHIFT","Monitor Only"))))))) -> DUE — INSIDER ACTIVITY
A4: ANET | B4: Owned | C4: 46278 | D4: 81 | E4: 4.29 | F4: STRONG BUY | G4: 199.59 | H4: {=IFERROR(INDEX(_xlfn.STOCKHISTORY(A4,TODAY()-5,TODAY(),0,0,1),ROWS(_xlfn.STOCKHISTORY(A4,TODAY()-5,TODAY(),0,0,1)),1),"")} -> 206.9 | I4: =IF(OR(G4="",H4=""),"",H4/G4-1) -> 0.036625081 | J4: 46329 | K4: Y | L4: 2026-09-29: Ullal Jayshree (CEO and Chairperson) sold $1,891,569, 0% of holding (+33 more in last 30d) | M4: N | O4: =IF(C4="","",TODAY()-C4) -> 23 | P4: =IF(A4="","",IF(O4>180,"DUE — STALE (>180 days)",IF(J4<>"",IF(ABS(J4-TODAY())<=7,"DUE — EARNINGS WINDOW",IF(I4<>"",IF(ABS(I4)>=0.2,"DUE — PRICE MOVE ±20%",IF(K4="Y","DUE — INSIDER ACTIVITY",IF(I4<>"",IF(ABS(I4)>=0.15,"WATCH — PRICE MOVE ±15%",IF(M4="Y","WATCH — ANALYST SHIFT","Monitor Only")),IF(M4="Y","WATCH — ANALYST SHIFT","Monitor Only")))),IF(K4="Y","DUE — INSIDER ACTIVITY",IF(I4<>"",IF(ABS(I4)>=0.15,"WATCH — PRICE MOVE ±15%",IF(M4="Y","WATCH — ANALYST SHIFT","Monitor Only")),IF(M4="Y","WATCH — ANALYST SHIFT","Monitor Only"))))),IF(I4<>"",IF(ABS(I4)>=0.2,"DUE — PRICE MOVE ±20%",IF(K4="Y","DUE — INSIDER ACTIVITY",IF(I4<>"",IF(ABS(I4)>=0.15,"WATCH — PRICE MOVE ±15%",IF(M4="Y","WATCH — ANALYST SHIFT","Monitor Only")),IF(M4="Y","WATCH — ANALYST SHIFT","Monitor Only")))),IF(K4="Y","DUE — INSIDER ACTIVITY",IF(I4<>"",IF(ABS(I4)>=0.15,"WATCH — PRICE MOVE ±15%",IF(M4="Y","WATCH — ANALYST SHIFT","Monitor Only")),IF(M4="Y","WATCH — ANALYST SHIFT","Monitor Only"))))))) -> DUE — INSIDER ACTIVITY
A5: ASML | B5: Owned | C5: 46278 | D5: 77.2 | E5: 3.86 | F5: BUY | G5: 1698.3 | H5: {=IFERROR(INDEX(_xlfn.STOCKHISTORY(A5,TODAY()-5,TODAY(),0,0,1),ROWS(_xlfn.STOCKHISTORY(A5,TODAY()-5,TODAY(),0,0,1)),1),"")} -> 1859.86 | I5: =IF(OR(G5="",H5=""),"",H5/G5-1) -> 0.095130425 | J5: 46309 | K5: N | M5: N | O5: =IF(C5="","",TODAY()-C5) -> 23 | P5: =IF(A5="","",IF(O5>180,"DUE — STALE (>180 days)",IF(J5<>"",IF(ABS(J5-TODAY())<=7,"DUE — EARNINGS WINDOW",IF(I5<>"",IF(ABS(I5)>=0.2,"DUE — PRICE MOVE ±20%",IF(K5="Y","DUE — INSIDER ACTIVITY",IF(I5<>"",IF(ABS(I5)>=0.15,"WATCH — PRICE MOVE ±15%",IF(M5="Y","WATCH — ANALYST SHIFT","Monitor Only")),IF(M5="Y","WATCH — ANALYST SHIFT","Monitor Only")))),IF(K5="Y","DUE — INSIDER ACTIVITY",IF(I5<>"",IF(ABS(I5)>=0.15,"WATCH — PRICE MOVE ±15%",IF(M5="Y","WATCH — ANALYST SHIFT","Monitor Only")),IF(M5="Y","WATCH — ANALYST SHIFT","Monitor Only"))))),IF(I5<>"",IF(ABS(I5)>=0.2,"DUE — PRICE MOVE ±20%",IF(K5="Y","DUE — INSIDER ACTIVITY",IF(I5<>"",IF(ABS(I5)>=0.15,"WATCH — PRICE MOVE ±15%",IF(M5="Y","WATCH — ANALYST SHIFT","Monitor Only")),IF(M5="Y","WATCH — ANALYST SHIFT","Monitor Only")))),IF(K5="Y","DUE — INSIDER ACTIVITY",IF(I5<>"",IF(ABS(I5)>=0.15,"WATCH — PRICE MOVE ±15%",IF(M5="Y","WATCH — ANALYST SHIFT","Monitor Only")),IF(M5="Y","WATCH — ANALYST SHIFT","Monitor Only"))))))) -> Monitor Only
A6: CRWD | B6: Owned | C6: 46278 | D6: 63.4 | E6: 3.5 | F6: AVOID | G6: 206.74 | H6: {=IFERROR(INDEX(_xlfn.STOCKHISTORY(A6,TODAY()-5,TODAY(),0,0,1),ROWS(_xlfn.STOCKHISTORY(A6,TODAY()-5,TODAY(),0,0,1)),1),"")} -> 272.67 | I6: =IF(OR(G6="",H6=""),"",H6/G6-1) -> 0.31890297 | J6: 46357 | K6: Y | L6: 2026-10-02: Sentonas Michael (PRESIDENT) sold $3,487,213, 1% of holding (+153 more in last 30d) | M6: N | O6: =IF(C6="","",TODAY()-C6) -> 23 | P6: =IF(A6="","",IF(O6>180,"DUE — STALE (>180 days)",IF(J6<>"",IF(ABS(J6-TODAY())<=7,"DUE — EARNINGS WINDOW",IF(I6<>"",IF(ABS(I6)>=0.2,"DUE — PRICE MOVE ±20%",IF(K6="Y","DUE — INSIDER ACTIVITY",IF(I6<>"",IF(ABS(I6)>=0.15,"WATCH — PRICE MOVE ±15%",IF(M6="Y","WATCH — ANALYST SHIFT","Monitor Only")),IF(M6="Y","WATCH — ANALYST SHIFT","Monitor Only")))),IF(K6="Y","DUE — INSIDER ACTIVITY",IF(I6<>"",IF(ABS(I6)>=0.15,"WATCH — PRICE MOVE ±15%",IF(M6="Y","WATCH — ANALYST SHIFT","Monitor Only")),IF(M6="Y","WATCH — ANALYST SHIFT","Monitor Only"))))),IF(I6<>"",IF(ABS(I6)>=0.2,"DUE — PRICE MOVE ±20%",IF(K6="Y","DUE — INSIDER ACTIVITY",IF(I6<>"",IF(ABS(I6)>=0.15,"WATCH — PRICE MOVE ±15%",IF(M6="Y","WATCH — ANALYST SHIFT","Monitor Only")),IF(M6="Y","WATCH — ANALYST SHIFT","Monitor Only")))),IF(K6="Y","DUE — INSIDER ACTIVITY",IF(I6<>"",IF(ABS(I6)>=0.15,"WATCH — PRICE MOVE ±15%",IF(M6="Y","WATCH — ANALYST SHIFT","Monitor Only")),IF(M6="Y","WATCH — ANALYST SHIFT","Monitor Only"))))))) -> DUE — PRICE MOVE ±20%
A7: KLAC | B7: Owned | C7: 46278 | D7: 72.6 | E7: 3.71 | F7: BUY | G7: 180.64 | H7: {=IFERROR(INDEX(_xlfn.STOCKHISTORY(A7,TODAY()-5,TODAY(),0,0,1),ROWS(_xlfn.STOCKHISTORY(A7,TODAY()-5,TODAY(),0,0,1)),1),"")} -> 206.85 | I7: =IF(OR(G7="",H7=""),"",H7/G7-1) -> 0.14509522 | J7: 46323 | K7: Y | L7: 2026-09-16: WALLACE RICHARD P (President and CEO) sold $12,378,626, 9% of holding | M7: N | O7: =IF(C7="","",TODAY()-C7) -> 23 | P7: =IF(A7="","",IF(O7>180,"DUE — STALE (>180 days)",IF(J7<>"",IF(ABS(J7-TODAY())<=7,"DUE — EARNINGS WINDOW",IF(I7<>"",IF(ABS(I7)>=0.2,"DUE — PRICE MOVE ±20%",IF(K7="Y","DUE — INSIDER ACTIVITY",IF(I7<>"",IF(ABS(I7)>=0.15,"WATCH — PRICE MOVE ±15%",IF(M7="Y","WATCH — ANALYST SHIFT","Monitor Only")),IF(M7="Y","WATCH — ANALYST SHIFT","Monitor Only")))),IF(K7="Y","DUE — INSIDER ACTIVITY",IF(I7<>"",IF(ABS(I7)>=0.15,"WATCH — PRICE MOVE ±15%",IF(M7="Y","WATCH — ANALYST SHIFT","Monitor Only")),IF(M7="Y","WATCH — ANALYST SHIFT","Monitor Only"))))),IF(I7<>"",IF(ABS(I7)>=0.2,"DUE — PRICE MOVE ±20%",IF(K7="Y","DUE — INSIDER ACTIVITY",IF(I7<>"",IF(ABS(I7)>=0.15,"WATCH — PRICE MOVE ±15%",IF(M7="Y","WATCH — ANALYST SHIFT","Monitor Only")),IF(M7="Y","WATCH — ANALYST SHIFT","Monitor Only")))),IF(K7="Y","DUE — INSIDER ACTIVITY",IF(I7<>"",IF(ABS(I7)>=0.15,"WATCH — PRICE MOVE ±15%",IF(M7="Y","WATCH — ANALYST SHIFT","Monitor Only")),IF(M7="Y","WATCH — ANALYST SHIFT","Monitor Only"))))))) -> DUE — INSIDER ACTIVITY
A8: MU | B8: Owned | C8: 46278 | D8: 67.8 | E8: 3.36 | F8: BUY | G8: 975.26 | H8: {=IFERROR(INDEX(_xlfn.STOCKHISTORY(A8,TODAY()-5,TODAY(),0,0,1),ROWS(_xlfn.STOCKHISTORY(A8,TODAY()-5,TODAY(),0,0,1)),1),"")} -> 1063.96 | I8: =IF(OR(G8="",H8=""),"",H8/G8-1) -> 0.090950106 | J8: 46379 | K8: N | M8: N | O8: =IF(C8="","",TODAY()-C8) -> 23 | P8: =IF(A8="","",IF(O8>180,"DUE — STALE (>180 days)",IF(J8<>"",IF(ABS(J8-TODAY())<=7,"DUE — EARNINGS WINDOW",IF(I8<>"",IF(ABS(I8)>=0.2,"DUE — PRICE MOVE ±20%",IF(K8="Y","DUE — INSIDER ACTIVITY",IF(I8<>"",IF(ABS(I8)>=0.15,"WATCH — PRICE MOVE ±15%",IF(M8="Y","WATCH — ANALYST SHIFT","Monitor Only")),IF(M8="Y","WATCH — ANALYST SHIFT","Monitor Only")))),IF(K8="Y","DUE — INSIDER ACTIVITY",IF(I8<>"",IF(ABS(I8)>=0.15,"WATCH — PRICE MOVE ±15%",IF(M8="Y","WATCH — ANALYST SHIFT","Monitor Only")),IF(M8="Y","WATCH — ANALYST SHIFT","Monitor Only"))))),IF(I8<>"",IF(ABS(I8)>=0.2,"DUE — PRICE MOVE ±20%",IF(K8="Y","DUE — INSIDER ACTIVITY",IF(I8<>"",IF(ABS(I8)>=0.15,"WATCH — PRICE MOVE ±15%",IF(M8="Y","WATCH — ANALYST SHIFT","Monitor Only")),IF(M8="Y","WATCH — ANALYST SHIFT","Monitor Only")))),IF(K8="Y","DUE — INSIDER ACTIVITY",IF(I8<>"",IF(ABS(I8)>=0.15,"WATCH — PRICE MOVE ±15%",IF(M8="Y","WATCH — ANALYST SHIFT","Monitor Only")),IF(M8="Y","WATCH — ANALYST SHIFT","Monitor Only"))))))) -> Monitor Only
A9: NVDA | B9: Owned | C9: 46278 | D9: 89.2 | E9: 4.29 | F9: STRONG BUY | G9: 218.29 | H9: {=IFERROR(INDEX(_xlfn.STOCKHISTORY(A9,TODAY()-5,TODAY(),0,0,1),ROWS(_xlfn.STOCKHISTORY(A9,TODAY()-5,TODAY(),0,0,1)),1),"")} -> 238.9 | I9: =IF(OR(G9="",H9=""),"",H9/G9-1) -> 0.094415686 | J9: 46343 | K9: Y | L9: 2026-09-23: Teter Timothy S. (EVP, General Counsel and Sec) sold $2,773,638, 0% of holding (+14 more in last 30d) | M9: N | O9: =IF(C9="","",TODAY()-C9) -> 23 | P9: =IF(A9="","",IF(O9>180,"DUE — STALE (>180 days)",IF(J9<>"",IF(ABS(J9-TODAY())<=7,"DUE — EARNINGS WINDOW",IF(I9<>"",IF(ABS(I9)>=0.2,"DUE — PRICE MOVE ±20%",IF(K9="Y","DUE — INSIDER ACTIVITY",IF(I9<>"",IF(ABS(I9)>=0.15,"WATCH — PRICE MOVE ±15%",IF(M9="Y","WATCH — ANALYST SHIFT","Monitor Only")),IF(M9="Y","WATCH — ANALYST SHIFT","Monitor Only")))),IF(K9="Y","DUE — INSIDER ACTIVITY",IF(I9<>"",IF(ABS(I9)>=0.15,"WATCH — PRICE MOVE ±15%",IF(M9="Y","WATCH — ANALYST SHIFT","Monitor Only")),IF(M9="Y","WATCH — ANALYST SHIFT","Monitor Only"))))),IF(I9<>"",IF(ABS(I9)>=0.2,"DUE — PRICE MOVE ±20%",IF(K9="Y","DUE — INSIDER ACTIVITY",IF(I9<>"",IF(ABS(I9)>=0.15,"WATCH — PRICE MOVE ±15%",IF(M9="Y","WATCH — ANALYST SHIFT","Monitor Only")),IF(M9="Y","WATCH — ANALYST SHIFT","Monitor Only")))),IF(K9="Y","DUE — INSIDER ACTIVITY",IF(I9<>"",IF(ABS(I9)>=0.15,"WATCH — PRICE MOVE ±15%",IF(M9="Y","WATCH — ANALYST SHIFT","Monitor Only")),IF(M9="Y","WATCH — ANALYST SHIFT","Monitor Only"))))))) -> DUE — INSIDER ACTIVITY
A10: PLTR | B10: Owned | C10: 46278 | D10: 76.2 | E10: 4.07 | F10: BUY | G10: 167.23 | H10: {=IFERROR(INDEX(_xlfn.STOCKHISTORY(A10,TODAY()-5,TODAY(),0,0,1),ROWS(_xlfn.STOCKHISTORY(A10,TODAY()-5,TODAY(),0,0,1)),1),"")} -> 189.4 | I10: =IF(OR(G10="",H10=""),"",H10/G10-1) -> 0.13257191 | J10: 46328 | K10: Y | L10: 2026-09-17: Moore Alexander D. (Director) sold $222,702, 0% of holding (+5 more in last 30d) | M10: N | O10: =IF(C10="","",TODAY()-C10) -> 23 | P10: =IF(A10="","",IF(O10>180,"DUE — STALE (>180 days)",IF(J10<>"",IF(ABS(J10-TODAY())<=7,"DUE — EARNINGS WINDOW",IF(I10<>"",IF(ABS(I10)>=0.2,"DUE — PRICE MOVE ±20%",IF(K10="Y","DUE — INSIDER ACTIVITY",IF(I10<>"",IF(ABS(I10)>=0.15,"WATCH — PRICE MOVE ±15%",IF(M10="Y","WATCH — ANALYST SHIFT","Monitor Only")),IF(M10="Y","WATCH — ANALYST SHIFT","Monitor Only")))),IF(K10="Y","DUE — INSIDER ACTIVITY",IF(I10<>"",IF(ABS(I10)>=0.15,"WATCH — PRICE MOVE ±15%",IF(M10="Y","WATCH — ANALYST SHIFT","Monitor Only")),IF(M10="Y","WATCH — ANALYST SHIFT","Monitor Only"))))),IF(I10<>"",IF(ABS(I10)>=0.2,"DUE — PRICE MOVE ±20%",IF(K10="Y","DUE — INSIDER ACTIVITY",IF(I10<>"",IF(ABS(I10)>=0.15,"WATCH — PRICE MOVE ±15%",IF(M10="Y","WATCH — ANALYST SHIFT","Monitor Only")),IF(M10="Y","WATCH — ANALYST SHIFT","Monitor Only")))),IF(K10="Y","DUE — INSIDER ACTIVITY",IF(I10<>"",IF(ABS(I10)>=0.15,"WATCH — PRICE MOVE ±15%",IF(M10="Y","WATCH — ANALYST SHIFT","Monitor Only")),IF(M10="Y","WATCH — ANALYST SHIFT","Monitor Only"))))))) -> DUE — INSIDER ACTIVITY
A11: TSM | B11: Owned | C11: 46278 | D11: 84 | E11: 4.21 | F11: STRONG BUY | G11: 433.24 | H11: {=IFERROR(INDEX(_xlfn.STOCKHISTORY(A11,TODAY()-5,TODAY(),0,0,1),ROWS(_xlfn.STOCKHISTORY(A11,TODAY()-5,TODAY(),0,0,1)),1),"")} -> 485.8 | I11: =IF(OR(G11="",H11=""),"",H11/G11-1) -> 0.12131844 | J11: 46310 | K11: Y | L11: 2026-09-09: Wu Yi-Huang (VP) bought $3,048, 33% of holding (+6 more in last 30d) | M11: N | O11: =IF(C11="","",TODAY()-C11) -> 23 | P11: =IF(A11="","",IF(O11>180,"DUE — STALE (>180 days)",IF(J11<>"",IF(ABS(J11-TODAY())<=7,"DUE — EARNINGS WINDOW",IF(I11<>"",IF(ABS(I11)>=0.2,"DUE — PRICE MOVE ±20%",IF(K11="Y","DUE — INSIDER ACTIVITY",IF(I11<>"",IF(ABS(I11)>=0.15,"WATCH — PRICE MOVE ±15%",IF(M11="Y","WATCH — ANALYST SHIFT","Monitor Only")),IF(M11="Y","WATCH — ANALYST SHIFT","Monitor Only")))),IF(K11="Y","DUE — INSIDER ACTIVITY",IF(I11<>"",IF(ABS(I11)>=0.15,"WATCH — PRICE MOVE ±15%",IF(M11="Y","WATCH — ANALYST SHIFT","Monitor Only")),IF(M11="Y","WATCH — ANALYST SHIFT","Monitor Only"))))),IF(I11<>"",IF(ABS(I11)>=0.2,"DUE — PRICE MOVE ±20%",IF(K11="Y","DUE — INSIDER ACTIVITY",IF(I11<>"",IF(ABS(I11)>=0.15,"WATCH — PRICE MOVE ±15%",IF(M11="Y","WATCH — ANALYST SHIFT","Monitor Only")),IF(M11="Y","WATCH — ANALYST SHIFT","Monitor Only")))),IF(K11="Y","DUE — INSIDER ACTIVITY",IF(I11<>"",IF(ABS(I11)>=0.15,"WATCH — PRICE MOVE ±15%",IF(M11="Y","WATCH — ANALYST SHIFT","Monitor Only")),IF(M11="Y","WATCH — ANALYST SHIFT","Monitor Only"))))))) -> DUE — INSIDER ACTIVITY
A12: VRT | B12: Owned | C12: 46278 | D12: 76.8 | E12: 3.93 | F12: BUY | G12: 257.06 | H12: {=IFERROR(INDEX(_xlfn.STOCKHISTORY(A12,TODAY()-5,TODAY(),0,0,1),ROWS(_xlfn.STOCKHISTORY(A12,TODAY()-5,TODAY(),0,0,1)),1),"")} -> 253.62 | I12: =IF(OR(G12="",H12=""),"",H12/G12-1) -> -0.01338209 | J12: 46316 | K12: N | M12: N | O12: =IF(C12="","",TODAY()-C12) -> 23 | P12: =IF(A12="","",IF(O12>180,"DUE — STALE (>180 days)",IF(J12<>"",IF(ABS(J12-TODAY())<=7,"DUE — EARNINGS WINDOW",IF(I12<>"",IF(ABS(I12)>=0.2,"DUE — PRICE MOVE ±20%",IF(K12="Y","DUE — INSIDER ACTIVITY",IF(I12<>"",IF(ABS(I12)>=0.15,"WATCH — PRICE MOVE ±15%",IF(M12="Y","WATCH — ANALYST SHIFT","Monitor Only")),IF(M12="Y","WATCH — ANALYST SHIFT","Monitor Only")))),IF(K12="Y","DUE — INSIDER ACTIVITY",IF(I12<>"",IF(ABS(I12)>=0.15,"WATCH — PRICE MOVE ±15%",IF(M12="Y","WATCH — ANALYST SHIFT","Monitor Only")),IF(M12="Y","WATCH — ANALYST SHIFT","Monitor Only"))))),IF(I12<>"",IF(ABS(I12)>=0.2,"DUE — PRICE MOVE ±20%",IF(K12="Y","DUE — INSIDER ACTIVITY",IF(I12<>"",IF(ABS(I12)>=0.15,"WATCH — PRICE MOVE ±15%",IF(M12="Y","WATCH — ANALYST SHIFT","Monitor Only")),IF(M12="Y","WATCH — ANALYST SHIFT","Monitor Only")))),IF(K12="Y","DUE — INSIDER ACTIVITY",IF(I12<>"",IF(ABS(I12)>=0.15,"WATCH — PRICE MOVE ±15%",IF(M12="Y","WATCH — ANALYST SHIFT","Monitor Only")),IF(M12="Y","WATCH — ANALYST SHIFT","Monitor Only"))))))) -> Monitor Only
A13: AVGO | B13: Owned | C13: 46300 | D13: 74.8 | E13: 3.64 | F13: BUY | G13: 355.14 | H13: {=IFERROR(INDEX(_xlfn.STOCKHISTORY(A13,TODAY()-5,TODAY(),0,0,1),ROWS(_xlfn.STOCKHISTORY(A13,TODAY()-5,TODAY(),0,0,1)),1),"")} -> 362.51 | I13: =IF(OR(G13="",H13=""),"",H13/G13-1) -> 0.020752379 | J13: 46365 | K13: Y | L13: 2026-09-25: SAMUELI HENRY (Director) sold $8,025,864, 0% of holding (+15 more in last 30d) | M13: N | O13: =IF(C13="","",TODAY()-C13) -> 1 | P13: =IF(A13="","",IF(O13>180,"DUE — STALE (>180 days)",IF(J13<>"",IF(ABS(J13-TODAY())<=7,"DUE — EARNINGS WINDOW",IF(I13<>"",IF(ABS(I13)>=0.2,"DUE — PRICE MOVE ±20%",IF(K13="Y","DUE — INSIDER ACTIVITY",IF(I13<>"",IF(ABS(I13)>=0.15,"WATCH — PRICE MOVE ±15%",IF(M13="Y","WATCH — ANALYST SHIFT","Monitor Only")),IF(M13="Y","WATCH — ANALYST SHIFT","Monitor Only")))),IF(K13="Y","DUE — INSIDER ACTIVITY",IF(I13<>"",IF(ABS(I13)>=0.15,"WATCH — PRICE MOVE ±15%",IF(M13="Y","WATCH — ANALYST SHIFT","Monitor Only")),IF(M13="Y","WATCH — ANALYST SHIFT","Monitor Only"))))),IF(I13<>"",IF(ABS(I13)>=0.2,"DUE — PRICE MOVE ±20%",IF(K13="Y","DUE — INSIDER ACTIVITY",IF(I13<>"",IF(ABS(I13)>=0.15,"WATCH — PRICE MOVE ±15%",IF(M13="Y","WATCH — ANALYST SHIFT","Monitor Only")),IF(M13="Y","WATCH — ANALYST SHIFT","Monitor Only")))),IF(K13="Y","DUE — INSIDER ACTIVITY",IF(I13<>"",IF(ABS(I13)>=0.15,"WATCH — PRICE MOVE ±15%",IF(M13="Y","WATCH — ANALYST SHIFT","Monitor Only")),IF(M13="Y","WATCH — ANALYST SHIFT","Monitor Only"))))))) -> DUE — INSIDER ACTIVITY | Q13: Re-scored 10/5/26 on the latest 10-Q figures (Journal row 92): Rule 3 cleared.
A14: PLD | B14: Owned | C14: 46295 | D14: 76 | E14: 3.93 | F14: BUY | G14: 129.84 | H14: {=IFERROR(INDEX(_xlfn.STOCKHISTORY(A14,TODAY()-5,TODAY(),0,0,1),ROWS(_xlfn.STOCKHISTORY(A14,TODAY()-5,TODAY(),0,0,1)),1),"")} -> 128.08 | I14: =IF(OR(G14="",H14=""),"",H14/G14-1) -> -0.013555145 | J14: 46310 | K14: N | M14: N | O14: =IF(C14="","",TODAY()-C14) -> 6 | P14: =IF(A14="","",IF(O14>180,"DUE — STALE (>180 days)",IF(J14<>"",IF(ABS(J14-TODAY())<=7,"DUE — EARNINGS WINDOW",IF(I14<>"",IF(ABS(I14)>=0.2,"DUE — PRICE MOVE ±20%",IF(K14="Y","DUE — INSIDER ACTIVITY",IF(I14<>"",IF(ABS(I14)>=0.15,"WATCH — PRICE MOVE ±15%",IF(M14="Y","WATCH — ANALYST SHIFT","Monitor Only")),IF(M14="Y","WATCH — ANALYST SHIFT","Monitor Only")))),IF(K14="Y","DUE — INSIDER ACTIVITY",IF(I14<>"",IF(ABS(I14)>=0.15,"WATCH — PRICE MOVE ±15%",IF(M14="Y","WATCH — ANALYST SHIFT","Monitor Only")),IF(M14="Y","WATCH — ANALYST SHIFT","Monitor Only"))))),IF(I14<>"",IF(ABS(I14)>=0.2,"DUE — PRICE MOVE ±20%",IF(K14="Y","DUE — INSIDER ACTIVITY",IF(I14<>"",IF(ABS(I14)>=0.15,"WATCH — PRICE MOVE ±15%",IF(M14="Y","WATCH — ANALYST SHIFT","Monitor Only")),IF(M14="Y","WATCH — ANALYST SHIFT","Monitor Only")))),IF(K14="Y","DUE — INSIDER ACTIVITY",IF(I14<>"",IF(ABS(I14)>=0.15,"WATCH — PRICE MOVE ±15%",IF(M14="Y","WATCH — ANALYST SHIFT","Monitor Only")),IF(M14="Y","WATCH — ANALYST SHIFT","Monitor Only"))))))) -> Monitor Only
A15: VRTX | B15: Owned | C15: 46300 | D15: 70.6 | E15: 3.43 | F15: BUY | G15: 504.73 | H15: {=IFERROR(INDEX(_xlfn.STOCKHISTORY(A15,TODAY()-5,TODAY(),0,0,1),ROWS(_xlfn.STOCKHISTORY(A15,TODAY()-5,TODAY(),0,0,1)),1),"")} -> 503.5 | I15: =IF(OR(G15="",H15=""),"",H15/G15-1) -> -0.0024369465 | J15: 46328 | K15: N | M15: N | O15: =IF(C15="","",TODAY()-C15) -> 1 | P15: =IF(A15="","",IF(O15>180,"DUE — STALE (>180 days)",IF(J15<>"",IF(ABS(J15-TODAY())<=7,"DUE — EARNINGS WINDOW",IF(I15<>"",IF(ABS(I15)>=0.2,"DUE — PRICE MOVE ±20%",IF(K15="Y","DUE — INSIDER ACTIVITY",IF(I15<>"",IF(ABS(I15)>=0.15,"WATCH — PRICE MOVE ±15%",IF(M15="Y","WATCH — ANALYST SHIFT","Monitor Only")),IF(M15="Y","WATCH — ANALYST SHIFT","Monitor Only")))),IF(K15="Y","DUE — INSIDER ACTIVITY",IF(I15<>"",IF(ABS(I15)>=0.15,"WATCH — PRICE MOVE ±15%",IF(M15="Y","WATCH — ANALYST SHIFT","Monitor Only")),IF(M15="Y","WATCH — ANALYST SHIFT","Monitor Only"))))),IF(I15<>"",IF(ABS(I15)>=0.2,"DUE — PRICE MOVE ±20%",IF(K15="Y","DUE — INSIDER ACTIVITY",IF(I15<>"",IF(ABS(I15)>=0.15,"WATCH — PRICE MOVE ±15%",IF(M15="Y","WATCH — ANALYST SHIFT","Monitor Only")),IF(M15="Y","WATCH — ANALYST SHIFT","Monitor Only")))),IF(K15="Y","DUE — INSIDER ACTIVITY",IF(I15<>"",IF(ABS(I15)>=0.15,"WATCH — PRICE MOVE ±15%",IF(M15="Y","WATCH — ANALYST SHIFT","Monitor Only")),IF(M15="Y","WATCH — ANALYST SHIFT","Monitor Only"))))))) -> Monitor Only | Q15: Re-scored 8/7/26: original Avoid was bad source data, corrected. See Journal. Re-scored 10/5/26 on the latest 10-Q figures (Journal row 92): Rule 3 cleared.
A16: AAP | B16: Tier-1 Avoid (external) | C16: 46246 | E16: 1.36 | G16: 53.52 | H16: {=IFERROR(INDEX(_xlfn.STOCKHISTORY(A16,TODAY()-5,TODAY(),0,0,1),ROWS(_xlfn.STOCKHISTORY(A16,TODAY()-5,TODAY(),0,0,1)),1),"")} -> 39.65 | I16: =IF(OR(G16="",H16=""),"",H16/G16-1) -> -0.25915546 | J16: 46331 | K16: N | M16: N | O16: =IF(C16="","",TODAY()-C16) -> 55 | P16: =IF(A16="","",IF(O16>180,"DUE — STALE (>180 days)",IF(J16<>"",IF(ABS(J16-TODAY())<=7,"DUE — EARNINGS WINDOW",IF(I16<>"",IF(ABS(I16)>=0.2,"DUE — PRICE MOVE ±20%",IF(K16="Y","DUE — INSIDER ACTIVITY",IF(I16<>"",IF(ABS(I16)>=0.15,"WATCH — PRICE MOVE ±15%",IF(M16="Y","WATCH — ANALYST SHIFT","Monitor Only")),IF(M16="Y","WATCH — ANALYST SHIFT","Monitor Only")))),IF(K16="Y","DUE — INSIDER ACTIVITY",IF(I16<>"",IF(ABS(I16)>=0.15,"WATCH — PRICE MOVE ±15%",IF(M16="Y","WATCH — ANALYST SHIFT","Monitor Only")),IF(M16="Y","WATCH — ANALYST SHIFT","Monitor Only"))))),IF(I16<>"",IF(ABS(I16)>=0.2,"DUE — PRICE MOVE ±20%",IF(K16="Y","DUE — INSIDER ACTIVITY",IF(I16<>"",IF(ABS(I16)>=0.15,"WATCH — PRICE MOVE ±15%",IF(M16="Y","WATCH — ANALYST SHIFT","Monitor Only")),IF(M16="Y","WATCH — ANALYST SHIFT","Monitor Only")))),IF(K16="Y","DUE — INSIDER ACTIVITY",IF(I16<>"",IF(ABS(I16)>=0.15,"WATCH — PRICE MOVE ±15%",IF(M16="Y","WATCH — ANALYST SHIFT","Monitor Only")),IF(M16="Y","WATCH — ANALYST SHIFT","Monitor Only"))))))) -> DUE — PRICE MOVE ±20%
A17: BABA | B17: Tier-1 Avoid (external) | C17: 46246 | E17: 2.79 | G17: 125.22 | H17: {=IFERROR(INDEX(_xlfn.STOCKHISTORY(A17,TODAY()-5,TODAY(),0,0,1),ROWS(_xlfn.STOCKHISTORY(A17,TODAY()-5,TODAY(),0,0,1)),1),"")} -> 110.8 | I17: =IF(OR(G17="",H17=""),"",H17/G17-1) -> -0.11515732 | J17: 46350 | K17: Y | L17: 2026-08-25: Tsai Joseph C (Other) bought $10,418,400, 1% of holding (+2 more in last 30d) | M17: N | O17: =IF(C17="","",TODAY()-C17) -> 55 | P17: =IF(A17="","",IF(O17>180,"DUE — STALE (>180 days)",IF(J17<>"",IF(ABS(J17-TODAY())<=7,"DUE — EARNINGS WINDOW",IF(I17<>"",IF(ABS(I17)>=0.2,"DUE — PRICE MOVE ±20%",IF(K17="Y","DUE — INSIDER ACTIVITY",IF(I17<>"",IF(ABS(I17)>=0.15,"WATCH — PRICE MOVE ±15%",IF(M17="Y","WATCH — ANALYST SHIFT","Monitor Only")),IF(M17="Y","WATCH — ANALYST SHIFT","Monitor Only")))),IF(K17="Y","DUE — INSIDER ACTIVITY",IF(I17<>"",IF(ABS(I17)>=0.15,"WATCH — PRICE MOVE ±15%",IF(M17="Y","WATCH — ANALYST SHIFT","Monitor Only")),IF(M17="Y","WATCH — ANALYST SHIFT","Monitor Only"))))),IF(I17<>"",IF(ABS(I17)>=0.2,"DUE — PRICE MOVE ±20%",IF(K17="Y","DUE — INSIDER ACTIVITY",IF(I17<>"",IF(ABS(I17)>=0.15,"WATCH — PRICE MOVE ±15%",IF(M17="Y","WATCH — ANALYST SHIFT","Monitor Only")),IF(M17="Y","WATCH — ANALYST SHIFT","Monitor Only")))),IF(K17="Y","DUE — INSIDER ACTIVITY",IF(I17<>"",IF(ABS(I17)>=0.15,"WATCH — PRICE MOVE ±15%",IF(M17="Y","WATCH — ANALYST SHIFT","Monitor Only")),IF(M17="Y","WATCH — ANALYST SHIFT","Monitor Only"))))))) -> DUE — INSIDER ACTIVITY
A18: CE | B18: Tier-1 Avoid (external) | C18: 46245 | E18: 1.79 | G18: 44.84 | H18: {=IFERROR(INDEX(_xlfn.STOCKHISTORY(A18,TODAY()-5,TODAY(),0,0,1),ROWS(_xlfn.STOCKHISTORY(A18,TODAY()-5,TODAY(),0,0,1)),1),"")} -> 45.53 | I18: =IF(OR(G18="",H18=""),"",H18/G18-1) -> 0.015388046 | J18: 46328 | K18: N | M18: N | O18: =IF(C18="","",TODAY()-C18) -> 56 | P18: =IF(A18="","",IF(O18>180,"DUE — STALE (>180 days)",IF(J18<>"",IF(ABS(J18-TODAY())<=7,"DUE — EARNINGS WINDOW",IF(I18<>"",IF(ABS(I18)>=0.2,"DUE — PRICE MOVE ±20%",IF(K18="Y","DUE — INSIDER ACTIVITY",IF(I18<>"",IF(ABS(I18)>=0.15,"WATCH — PRICE MOVE ±15%",IF(M18="Y","WATCH — ANALYST SHIFT","Monitor Only")),IF(M18="Y","WATCH — ANALYST SHIFT","Monitor Only")))),IF(K18="Y","DUE — INSIDER ACTIVITY",IF(I18<>"",IF(ABS(I18)>=0.15,"WATCH — PRICE MOVE ±15%",IF(M18="Y","WATCH — ANALYST SHIFT","Monitor Only")),IF(M18="Y","WATCH — ANALYST SHIFT","Monitor Only"))))),IF(I18<>"",IF(ABS(I18)>=0.2,"DUE — PRICE MOVE ±20%",IF(K18="Y","DUE — INSIDER ACTIVITY",IF(I18<>"",IF(ABS(I18)>=0.15,"WATCH — PRICE MOVE ±15%",IF(M18="Y","WATCH — ANALYST SHIFT","Monitor Only")),IF(M18="Y","WATCH — ANALYST SHIFT","Monitor Only")))),IF(K18="Y","DUE — INSIDER ACTIVITY",IF(I18<>"",IF(ABS(I18)>=0.15,"WATCH — PRICE MOVE ±15%",IF(M18="Y","WATCH — ANALYST SHIFT","Monitor Only")),IF(M18="Y","WATCH — ANALYST SHIFT","Monitor Only"))))))) -> Monitor Only
A19: CLF | B19: Tier-1 Avoid (external) | C19: 46245 | E19: 1.86 | G19: 12.41 | H19: {=IFERROR(INDEX(_xlfn.STOCKHISTORY(A19,TODAY()-5,TODAY(),0,0,1),ROWS(_xlfn.STOCKHISTORY(A19,TODAY()-5,TODAY(),0,0,1)),1),"")} -> 12.2 | I19: =IF(OR(G19="",H19=""),"",H19/G19-1) -> -0.016921837 | J19: 46314 | K19: N | M19: N | O19: =IF(C19="","",TODAY()-C19) -> 56 | P19: =IF(A19="","",IF(O19>180,"DUE — STALE (>180 days)",IF(J19<>"",IF(ABS(J19-TODAY())<=7,"DUE — EARNINGS WINDOW",IF(I19<>"",IF(ABS(I19)>=0.2,"DUE — PRICE MOVE ±20%",IF(K19="Y","DUE — INSIDER ACTIVITY",IF(I19<>"",IF(ABS(I19)>=0.15,"WATCH — PRICE MOVE ±15%",IF(M19="Y","WATCH — ANALYST SHIFT","Monitor Only")),IF(M19="Y","WATCH — ANALYST SHIFT","Monitor Only")))),IF(K19="Y","DUE — INSIDER ACTIVITY",IF(I19<>"",IF(ABS(I19)>=0.15,"WATCH — PRICE MOVE ±15%",IF(M19="Y","WATCH — ANALYST SHIFT","Monitor Only")),IF(M19="Y","WATCH — ANALYST SHIFT","Monitor Only"))))),IF(I19<>"",IF(ABS(I19)>=0.2,"DUE — PRICE MOVE ±20%",IF(K19="Y","DUE — INSIDER ACTIVITY",IF(I19<>"",IF(ABS(I19)>=0.15,"WATCH — PRICE MOVE ±15%",IF(M19="Y","WATCH — ANALYST SHIFT","Monitor Only")),IF(M19="Y","WATCH — ANALYST SHIFT","Monitor Only")))),IF(K19="Y","DUE — INSIDER ACTIVITY",IF(I19<>"",IF(ABS(I19)>=0.15,"WATCH — PRICE MOVE ±15%",IF(M19="Y","WATCH — ANALYST SHIFT","Monitor Only")),IF(M19="Y","WATCH — ANALYST SHIFT","Monitor Only"))))))) -> Monitor Only
A20: CMG | B20: Watch List | C20: 46245 | E20: 3.71 | G20: 32 | H20: {=IFERROR(INDEX(_xlfn.STOCKHISTORY(A20,TODAY()-5,TODAY(),0,0,1),ROWS(_xlfn.STOCKHISTORY(A20,TODAY()-5,TODAY(),0,0,1)),1),"")} -> 30.85 | I20: =IF(OR(G20="",H20=""),"",H20/G20-1) -> -0.0359375 | J20: 46323 | K20: N | M20: N | O20: =IF(C20="","",TODAY()-C20) -> 56 | P20: =IF(A20="","",IF(O20>180,"DUE — STALE (>180 days)",IF(J20<>"",IF(ABS(J20-TODAY())<=7,"DUE — EARNINGS WINDOW",IF(I20<>"",IF(ABS(I20)>=0.2,"DUE — PRICE MOVE ±20%",IF(K20="Y","DUE — INSIDER ACTIVITY",IF(I20<>"",IF(ABS(I20)>=0.15,"WATCH — PRICE MOVE ±15%",IF(M20="Y","WATCH — ANALYST SHIFT","Monitor Only")),IF(M20="Y","WATCH — ANALYST SHIFT","Monitor Only")))),IF(K20="Y","DUE — INSIDER ACTIVITY",IF(I20<>"",IF(ABS(I20)>=0.15,"WATCH — PRICE MOVE ±15%",IF(M20="Y","WATCH — ANALYST SHIFT","Monitor Only")),IF(M20="Y","WATCH — ANALYST SHIFT","Monitor Only"))))),IF(I20<>"",IF(ABS(I20)>=0.2,"DUE — PRICE MOVE ±20%",IF(K20="Y","DUE — INSIDER ACTIVITY",IF(I20<>"",IF(ABS(I20)>=0.15,"WATCH — PRICE MOVE ±15%",IF(M20="Y","WATCH — ANALYST SHIFT","Monitor Only")),IF(M20="Y","WATCH — ANALYST SHIFT","Monitor Only")))),IF(K20="Y","DUE — INSIDER ACTIVITY",IF(I20<>"",IF(ABS(I20)>=0.15,"WATCH — PRICE MOVE ±15%",IF(M20="Y","WATCH — ANALYST SHIFT","Monitor Only")),IF(M20="Y","WATCH — ANALYST SHIFT","Monitor Only"))))))) -> Monitor Only
A21: COST | B21: Watch List | C21: 46245 | D21: 77.4 | E21: 4.14 | F21: BUY | G21: 944.32 | H21: {=IFERROR(INDEX(_xlfn.STOCKHISTORY(A21,TODAY()-5,TODAY(),0,0,1),ROWS(_xlfn.STOCKHISTORY(A21,TODAY()-5,TODAY(),0,0,1)),1),"")} -> 923.52 | I21: =IF(OR(G21="",H21=""),"",H21/G21-1) -> -0.022026432 | J21: 46366 | K21: N | M21: N | O21: =IF(C21="","",TODAY()-C21) -> 56 | P21: =IF(A21="","",IF(O21>180,"DUE — STALE (>180 days)",IF(J21<>"",IF(ABS(J21-TODAY())<=7,"DUE — EARNINGS WINDOW",IF(I21<>"",IF(ABS(I21)>=0.2,"DUE — PRICE MOVE ±20%",IF(K21="Y","DUE — INSIDER ACTIVITY",IF(I21<>"",IF(ABS(I21)>=0.15,"WATCH — PRICE MOVE ±15%",IF(M21="Y","WATCH — ANALYST SHIFT","Monitor Only")),IF(M21="Y","WATCH — ANALYST SHIFT","Monitor Only")))),IF(K21="Y","DUE — INSIDER ACTIVITY",IF(I21<>"",IF(ABS(I21)>=0.15,"WATCH — PRICE MOVE ±15%",IF(M21="Y","WATCH — ANALYST SHIFT","Monitor Only")),IF(M21="Y","WATCH — ANALYST SHIFT","Monitor Only"))))),IF(I21<>"",IF(ABS(I21)>=0.2,"DUE — PRICE MOVE ±20%",IF(K21="Y","DUE — INSIDER ACTIVITY",IF(I21<>"",IF(ABS(I21)>=0.15,"WATCH — PRICE MOVE ±15%",IF(M21="Y","WATCH — ANALYST SHIFT","Monitor Only")),IF(M21="Y","WATCH — ANALYST SHIFT","Monitor Only")))),IF(K21="Y","DUE — INSIDER ACTIVITY",IF(I21<>"",IF(ABS(I21)>=0.15,"WATCH — PRICE MOVE ±15%",IF(M21="Y","WATCH — ANALYST SHIFT","Monitor Only")),IF(M21="Y","WATCH — ANALYST SHIFT","Monitor Only"))))))) -> Monitor Only
A22: CRK | B22: Tier-1 Avoid (external) | C22: 46245 | E22: 1.21 | G22: 14.39 | H22: {=IFERROR(INDEX(_xlfn.STOCKHISTORY(A22,TODAY()-5,TODAY(),0,0,1),ROWS(_xlfn.STOCKHISTORY(A22,TODAY()-5,TODAY(),0,0,1)),1),"")} -> 13.06 | I22: =IF(OR(G22="",H22=""),"",H22/G22-1) -> -0.092425295 | J22: 46328 | K22: N | M22: N | O22: =IF(C22="","",TODAY()-C22) -> 56 | P22: =IF(A22="","",IF(O22>180,"DUE — STALE (>180 days)",IF(J22<>"",IF(ABS(J22-TODAY())<=7,"DUE — EARNINGS WINDOW",IF(I22<>"",IF(ABS(I22)>=0.2,"DUE — PRICE MOVE ±20%",IF(K22="Y","DUE — INSIDER ACTIVITY",IF(I22<>"",IF(ABS(I22)>=0.15,"WATCH — PRICE MOVE ±15%",IF(M22="Y","WATCH — ANALYST SHIFT","Monitor Only")),IF(M22="Y","WATCH — ANALYST SHIFT","Monitor Only")))),IF(K22="Y","DUE — INSIDER ACTIVITY",IF(I22<>"",IF(ABS(I22)>=0.15,"WATCH — PRICE MOVE ±15%",IF(M22="Y","WATCH — ANALYST SHIFT","Monitor Only")),IF(M22="Y","WATCH — ANALYST SHIFT","Monitor Only"))))),IF(I22<>"",IF(ABS(I22)>=0.2,"DUE — PRICE MOVE ±20%",IF(K22="Y","DUE — INSIDER ACTIVITY",IF(I22<>"",IF(ABS(I22)>=0.15,"WATCH — PRICE MOVE ±15%",IF(M22="Y","WATCH — ANALYST SHIFT","Monitor Only")),IF(M22="Y","WATCH — ANALYST SHIFT","Monitor Only")))),IF(K22="Y","DUE — INSIDER ACTIVITY",IF(I22<>"",IF(ABS(I22)>=0.15,"WATCH — PRICE MOVE ±15%",IF(M22="Y","WATCH — ANALYST SHIFT","Monitor Only")),IF(M22="Y","WATCH — ANALYST SHIFT","Monitor Only"))))))) -> Monitor Only
A23: DEO | B23: Tier-1 Avoid (external) | C23: 46245 | E23: 2.36 | G23: 94.94 | H23: {=IFERROR(INDEX(_xlfn.STOCKHISTORY(A23,TODAY()-5,TODAY(),0,0,1),ROWS(_xlfn.STOCKHISTORY(A23,TODAY()-5,TODAY(),0,0,1)),1),"")} -> 83.97 | I23: =IF(OR(G23="",H23=""),"",H23/G23-1) -> -0.11554666 | J23: 46240 | K23: N | M23: N | O23: =IF(C23="","",TODAY()-C23) -> 56 | P23: =IF(A23="","",IF(O23>180,"DUE — STALE (>180 days)",IF(J23<>"",IF(ABS(J23-TODAY())<=7,"DUE — EARNINGS WINDOW",IF(I23<>"",IF(ABS(I23)>=0.2,"DUE — PRICE MOVE ±20%",IF(K23="Y","DUE — INSIDER ACTIVITY",IF(I23<>"",IF(ABS(I23)>=0.15,"WATCH — PRICE MOVE ±15%",IF(M23="Y","WATCH — ANALYST SHIFT","Monitor Only")),IF(M23="Y","WATCH — ANALYST SHIFT","Monitor Only")))),IF(K23="Y","DUE — INSIDER ACTIVITY",IF(I23<>"",IF(ABS(I23)>=0.15,"WATCH — PRICE MOVE ±15%",IF(M23="Y","WATCH — ANALYST SHIFT","Monitor Only")),IF(M23="Y","WATCH — ANALYST SHIFT","Monitor Only"))))),IF(I23<>"",IF(ABS(I23)>=0.2,"DUE — PRICE MOVE ±20%",IF(K23="Y","DUE — INSIDER ACTIVITY",IF(I23<>"",IF(ABS(I23)>=0.15,"WATCH — PRICE MOVE ±15%",IF(M23="Y","WATCH — ANALYST SHIFT","Monitor Only")),IF(M23="Y","WATCH — ANALYST SHIFT","Monitor Only")))),IF(K23="Y","DUE — INSIDER ACTIVITY",IF(I23<>"",IF(ABS(I23)>=0.15,"WATCH — PRICE MOVE ±15%",IF(M23="Y","WATCH — ANALYST SHIFT","Monitor Only")),IF(M23="Y","WATCH — ANALYST SHIFT","Monitor Only"))))))) -> Monitor Only
A24: DIS | B24: Tier-1 Avoid (external) | C24: 46258 | E24: 2.93 | G24: 110.61 | H24: {=IFERROR(INDEX(_xlfn.STOCKHISTORY(A24,TODAY()-5,TODAY(),0,0,1),ROWS(_xlfn.STOCKHISTORY(A24,TODAY()-5,TODAY(),0,0,1)),1),"")} -> 103.61 | I24: =IF(OR(G24="",H24=""),"",H24/G24-1) -> -0.063285417 | J24: 46338 | K24: Y | L24: 2026-08-20: Roeder Paul M (Sr EVP and Chief Comm Officer) sold $382,327, 100% of holding (+1 more in last 30d) | M24: N | O24: =IF(C24="","",TODAY()-C24) -> 43 | P24: =IF(A24="","",IF(O24>180,"DUE — STALE (>180 days)",IF(J24<>"",IF(ABS(J24-TODAY())<=7,"DUE — EARNINGS WINDOW",IF(I24<>"",IF(ABS(I24)>=0.2,"DUE — PRICE MOVE ±20%",IF(K24="Y","DUE — INSIDER ACTIVITY",IF(I24<>"",IF(ABS(I24)>=0.15,"WATCH — PRICE MOVE ±15%",IF(M24="Y","WATCH — ANALYST SHIFT","Monitor Only")),IF(M24="Y","WATCH — ANALYST SHIFT","Monitor Only")))),IF(K24="Y","DUE — INSIDER ACTIVITY",IF(I24<>"",IF(ABS(I24)>=0.15,"WATCH — PRICE MOVE ±15%",IF(M24="Y","WATCH — ANALYST SHIFT","Monitor Only")),IF(M24="Y","WATCH — ANALYST SHIFT","Monitor Only"))))),IF(I24<>"",IF(ABS(I24)>=0.2,"DUE — PRICE MOVE ±20%",IF(K24="Y","DUE — INSIDER ACTIVITY",IF(I24<>"",IF(ABS(I24)>=0.15,"WATCH — PRICE MOVE ±15%",IF(M24="Y","WATCH — ANALYST SHIFT","Monitor Only")),IF(M24="Y","WATCH — ANALYST SHIFT","Monitor Only")))),IF(K24="Y","DUE — INSIDER ACTIVITY",IF(I24<>"",IF(ABS(I24)>=0.15,"WATCH — PRICE MOVE ±15%",IF(M24="Y","WATCH — ANALYST SHIFT","Monitor Only")),IF(M24="Y","WATCH — ANALYST SHIFT","Monitor Only"))))))) -> DUE — INSIDER ACTIVITY
A25: DPZ | B25: Watch List | C25: 46245 | E25: 4.86 | G25: 357.34 | H25: {=IFERROR(INDEX(_xlfn.STOCKHISTORY(A25,TODAY()-5,TODAY(),0,0,1),ROWS(_xlfn.STOCKHISTORY(A25,TODAY()-5,TODAY(),0,0,1)),1),"")} -> 297.27 | I25: =IF(OR(G25="",H25=""),"",H25/G25-1) -> -0.16810321 | J25: 46308 | K25: N | M25: N | O25: =IF(C25="","",TODAY()-C25) -> 56 | P25: =IF(A25="","",IF(O25>180,"DUE — STALE (>180 days)",IF(J25<>"",IF(ABS(J25-TODAY())<=7,"DUE — EARNINGS WINDOW",IF(I25<>"",IF(ABS(I25)>=0.2,"DUE — PRICE MOVE ±20%",IF(K25="Y","DUE — INSIDER ACTIVITY",IF(I25<>"",IF(ABS(I25)>=0.15,"WATCH — PRICE MOVE ±15%",IF(M25="Y","WATCH — ANALYST SHIFT","Monitor Only")),IF(M25="Y","WATCH — ANALYST SHIFT","Monitor Only")))),IF(K25="Y","DUE — INSIDER ACTIVITY",IF(I25<>"",IF(ABS(I25)>=0.15,"WATCH — PRICE MOVE ±15%",IF(M25="Y","WATCH — ANALYST SHIFT","Monitor Only")),IF(M25="Y","WATCH — ANALYST SHIFT","Monitor Only"))))),IF(I25<>"",IF(ABS(I25)>=0.2,"DUE — PRICE MOVE ±20%",IF(K25="Y","DUE — INSIDER ACTIVITY",IF(I25<>"",IF(ABS(I25)>=0.15,"WATCH — PRICE MOVE ±15%",IF(M25="Y","WATCH — ANALYST SHIFT","Monitor Only")),IF(M25="Y","WATCH — ANALYST SHIFT","Monitor Only")))),IF(K25="Y","DUE — INSIDER ACTIVITY",IF(I25<>"",IF(ABS(I25)>=0.15,"WATCH — PRICE MOVE ±15%",IF(M25="Y","WATCH — ANALYST SHIFT","Monitor Only")),IF(M25="Y","WATCH — ANALYST SHIFT","Monitor Only"))))))) -> DUE — EARNINGS WINDOW
A26: EL | B26: Tier-1 Avoid (external) | C26: 46245 | E26: 2.14 | G26: 87.78 | H26: {=IFERROR(INDEX(_xlfn.STOCKHISTORY(A26,TODAY()-5,TODAY(),0,0,1),ROWS(_xlfn.STOCKHISTORY(A26,TODAY()-5,TODAY(),0,0,1)),1),"")} -> 93.3 | I26: =IF(OR(G26="",H26=""),"",H26/G26-1) -> 0.062884484 | J26: 46328 | K26: Y | L26: 2026-08-25: La Lande Rashida (Exec VP & General Counsel) sold $553,896, 100% of holding | M26: N | O26: =IF(C26="","",TODAY()-C26) -> 56 | P26: =IF(A26="","",IF(O26>180,"DUE — STALE (>180 days)",IF(J26<>"",IF(ABS(J26-TODAY())<=7,"DUE — EARNINGS WINDOW",IF(I26<>"",IF(ABS(I26)>=0.2,"DUE — PRICE MOVE ±20%",IF(K26="Y","DUE — INSIDER ACTIVITY",IF(I26<>"",IF(ABS(I26)>=0.15,"WATCH — PRICE MOVE ±15%",IF(M26="Y","WATCH — ANALYST SHIFT","Monitor Only")),IF(M26="Y","WATCH — ANALYST SHIFT","Monitor Only")))),IF(K26="Y","DUE — INSIDER ACTIVITY",IF(I26<>"",IF(ABS(I26)>=0.15,"WATCH — PRICE MOVE ±15%",IF(M26="Y","WATCH — ANALYST SHIFT","Monitor Only")),IF(M26="Y","WATCH — ANALYST SHIFT","Monitor Only"))))),IF(I26<>"",IF(ABS(I26)>=0.2,"DUE — PRICE MOVE ±20%",IF(K26="Y","DUE — INSIDER ACTIVITY",IF(I26<>"",IF(ABS(I26)>=0.15,"WATCH — PRICE MOVE ±15%",IF(M26="Y","WATCH — ANALYST SHIFT","Monitor Only")),IF(M26="Y","WATCH — ANALYST SHIFT","Monitor Only")))),IF(K26="Y","DUE — INSIDER ACTIVITY",IF(I26<>"",IF(ABS(I26)>=0.15,"WATCH — PRICE MOVE ±15%",IF(M26="Y","WATCH — ANALYST SHIFT","Monitor Only")),IF(M26="Y","WATCH — ANALYST SHIFT","Monitor Only"))))))) -> DUE — INSIDER ACTIVITY
A27: ET | B27: Watch List | C27: 46276 | E27: 3.07 | G27: 20.78 | H27: {=IFERROR(INDEX(_xlfn.STOCKHISTORY(A27,TODAY()-5,TODAY(),0,0,1),ROWS(_xlfn.STOCKHISTORY(A27,TODAY()-5,TODAY(),0,0,1)),1),"")} -> 20.72 | I27: =IF(OR(G27="",H27=""),"",H27/G27-1) -> -0.0028873917 | J27: 46329 | K27: Y | L27: 2026-08-20: WARREN KELCY L (Other) bought $7,487,721, 0% of holding (+2 more in last 30d) | M27: N | O27: =IF(C27="","",TODAY()-C27) -> 25 | P27: =IF(A27="","",IF(O27>180,"DUE — STALE (>180 days)",IF(J27<>"",IF(ABS(J27-TODAY())<=7,"DUE — EARNINGS WINDOW",IF(I27<>"",IF(ABS(I27)>=0.2,"DUE — PRICE MOVE ±20%",IF(K27="Y","DUE — INSIDER ACTIVITY",IF(I27<>"",IF(ABS(I27)>=0.15,"WATCH — PRICE MOVE ±15%",IF(M27="Y","WATCH — ANALYST SHIFT","Monitor Only")),IF(M27="Y","WATCH — ANALYST SHIFT","Monitor Only")))),IF(K27="Y","DUE — INSIDER ACTIVITY",IF(I27<>"",IF(ABS(I27)>=0.15,"WATCH — PRICE MOVE ±15%",IF(M27="Y","WATCH — ANALYST SHIFT","Monitor Only")),IF(M27="Y","WATCH — ANALYST SHIFT","Monitor Only"))))),IF(I27<>"",IF(ABS(I27)>=0.2,"DUE — PRICE MOVE ±20%",IF(K27="Y","DUE — INSIDER ACTIVITY",IF(I27<>"",IF(ABS(I27)>=0.15,"WATCH — PRICE MOVE ±15%",IF(M27="Y","WATCH — ANALYST SHIFT","Monitor Only")),IF(M27="Y","WATCH — ANALYST SHIFT","Monitor Only")))),IF(K27="Y","DUE — INSIDER ACTIVITY",IF(I27<>"",IF(ABS(I27)>=0.15,"WATCH — PRICE MOVE ±15%",IF(M27="Y","WATCH — ANALYST SHIFT","Monitor Only")),IF(M27="Y","WATCH — ANALYST SHIFT","Monitor Only"))))))) -> DUE — INSIDER ACTIVITY
A28: ETN | B28: Watch List | C28: 46247 | E28: 3.5 | G28: 453.33 | H28: {=IFERROR(INDEX(_xlfn.STOCKHISTORY(A28,TODAY()-5,TODAY(),0,0,1),ROWS(_xlfn.STOCKHISTORY(A28,TODAY()-5,TODAY(),0,0,1)),1),"")} -> 432.6 | I28: =IF(OR(G28="",H28=""),"",H28/G28-1) -> -0.045728277 | J28: 46329 | K28: Y | L28: 2026-08-13: Monesmith Heath B. (See Remarks below.) sold $8,261,224, 26% of holding (+1 more in last 30d) | M28: N | O28: =IF(C28="","",TODAY()-C28) -> 54 | P28: =IF(A28="","",IF(O28>180,"DUE — STALE (>180 days)",IF(J28<>"",IF(ABS(J28-TODAY())<=7,"DUE — EARNINGS WINDOW",IF(I28<>"",IF(ABS(I28)>=0.2,"DUE — PRICE MOVE ±20%",IF(K28="Y","DUE — INSIDER ACTIVITY",IF(I28<>"",IF(ABS(I28)>=0.15,"WATCH — PRICE MOVE ±15%",IF(M28="Y","WATCH — ANALYST SHIFT","Monitor Only")),IF(M28="Y","WATCH — ANALYST SHIFT","Monitor Only")))),IF(K28="Y","DUE — INSIDER ACTIVITY",IF(I28<>"",IF(ABS(I28)>=0.15,"WATCH — PRICE MOVE ±15%",IF(M28="Y","WATCH — ANALYST SHIFT","Monitor Only")),IF(M28="Y","WATCH — ANALYST SHIFT","Monitor Only"))))),IF(I28<>"",IF(ABS(I28)>=0.2,"DUE — PRICE MOVE ±20%",IF(K28="Y","DUE — INSIDER ACTIVITY",IF(I28<>"",IF(ABS(I28)>=0.15,"WATCH — PRICE MOVE ±15%",IF(M28="Y","WATCH — ANALYST SHIFT","Monitor Only")),IF(M28="Y","WATCH — ANALYST SHIFT","Monitor Only")))),IF(K28="Y","DUE — INSIDER ACTIVITY",IF(I28<>"",IF(ABS(I28)>=0.15,"WATCH — PRICE MOVE ±15%",IF(M28="Y","WATCH — ANALYST SHIFT","Monitor Only")),IF(M28="Y","WATCH — ANALYST SHIFT","Monitor Only"))))))) -> DUE — INSIDER ACTIVITY
A29: ETSY | B29: Watch List | C29: 46246 | E29: 3.43 | G29: 79.63 | H29: {=IFERROR(INDEX(_xlfn.STOCKHISTORY(A29,TODAY()-5,TODAY(),0,0,1),ROWS(_xlfn.STOCKHISTORY(A29,TODAY()-5,TODAY(),0,0,1)),1),"")} -> 70.89 | I29: =IF(OR(G29="",H29=""),"",H29/G29-1) -> -0.10975763 | J29: 46330 | K29: Y | L29: 2026-08-19: Buckley Merilee (CHIEF ACCOUNTING OFFICER) sold $18,850, 59% of holding (+9 more in last 30d) | M29: N | O29: =IF(C29="","",TODAY()-C29) -> 55 | P29: =IF(A29="","",IF(O29>180,"DUE — STALE (>180 days)",IF(J29<>"",IF(ABS(J29-TODAY())<=7,"DUE — EARNINGS WINDOW",IF(I29<>"",IF(ABS(I29)>=0.2,"DUE — PRICE MOVE ±20%",IF(K29="Y","DUE — INSIDER ACTIVITY",IF(I29<>"",IF(ABS(I29)>=0.15,"WATCH — PRICE MOVE ±15%",IF(M29="Y","WATCH — ANALYST SHIFT","Monitor Only")),IF(M29="Y","WATCH — ANALYST SHIFT","Monitor Only")))),IF(K29="Y","DUE — INSIDER ACTIVITY",IF(I29<>"",IF(ABS(I29)>=0.15,"WATCH — PRICE MOVE ±15%",IF(M29="Y","WATCH — ANALYST SHIFT","Monitor Only")),IF(M29="Y","WATCH — ANALYST SHIFT","Monitor Only"))))),IF(I29<>"",IF(ABS(I29)>=0.2,"DUE — PRICE MOVE ±20%",IF(K29="Y","DUE — INSIDER ACTIVITY",IF(I29<>"",IF(ABS(I29)>=0.15,"WATCH — PRICE MOVE ±15%",IF(M29="Y","WATCH — ANALYST SHIFT","Monitor Only")),IF(M29="Y","WATCH — ANALYST SHIFT","Monitor Only")))),IF(K29="Y","DUE — INSIDER ACTIVITY",IF(I29<>"",IF(ABS(I29)>=0.15,"WATCH — PRICE MOVE ±15%",IF(M29="Y","WATCH — ANALYST SHIFT","Monitor Only")),IF(M29="Y","WATCH — ANALYST SHIFT","Monitor Only"))))))) -> DUE — INSIDER ACTIVITY
A30: GE | B30: Owned | C30: 46278 | D30: 84.2 | E30: 4.14 | F30: STRONG BUY | G30: 323.66 | H30: {=IFERROR(INDEX(_xlfn.STOCKHISTORY(A30,TODAY()-5,TODAY(),0,0,1),ROWS(_xlfn.STOCKHISTORY(A30,TODAY()-5,TODAY(),0,0,1)),1),"")} -> 306.34 | I30: =IF(OR(G30="",H30=""),"",H30/G30-1) -> -0.053512946 | J30: 46315 | K30: N | M30: N | O30: =IF(C30="","",TODAY()-C30) -> 23 | P30: =IF(A30="","",IF(O30>180,"DUE — STALE (>180 days)",IF(J30<>"",IF(ABS(J30-TODAY())<=7,"DUE — EARNINGS WINDOW",IF(I30<>"",IF(ABS(I30)>=0.2,"DUE — PRICE MOVE ±20%",IF(K30="Y","DUE — INSIDER ACTIVITY",IF(I30<>"",IF(ABS(I30)>=0.15,"WATCH — PRICE MOVE ±15%",IF(M30="Y","WATCH — ANALYST SHIFT","Monitor Only")),IF(M30="Y","WATCH — ANALYST SHIFT","Monitor Only")))),IF(K30="Y","DUE — INSIDER ACTIVITY",IF(I30<>"",IF(ABS(I30)>=0.15,"WATCH — PRICE MOVE ±15%",IF(M30="Y","WATCH — ANALYST SHIFT","Monitor Only")),IF(M30="Y","WATCH — ANALYST SHIFT","Monitor Only"))))),IF(I30<>"",IF(ABS(I30)>=0.2,"DUE — PRICE MOVE ±20%",IF(K30="Y","DUE — INSIDER ACTIVITY",IF(I30<>"",IF(ABS(I30)>=0.15,"WATCH — PRICE MOVE ±15%",IF(M30="Y","WATCH — ANALYST SHIFT","Monitor Only")),IF(M30="Y","WATCH — ANALYST SHIFT","Monitor Only")))),IF(K30="Y","DUE — INSIDER ACTIVITY",IF(I30<>"",IF(ABS(I30)>=0.15,"WATCH — PRICE MOVE ±15%",IF(M30="Y","WATCH — ANALYST SHIFT","Monitor Only")),IF(M30="Y","WATCH — ANALYST SHIFT","Monitor Only"))))))) -> Monitor Only
A31: GOOS | B31: Tier-1 Avoid (external) | C31: 46246 | E31: 2.5 | G31: 8.64 | H31: {=IFERROR(INDEX(_xlfn.STOCKHISTORY(A31,TODAY()-5,TODAY(),0,0,1),ROWS(_xlfn.STOCKHISTORY(A31,TODAY()-5,TODAY(),0,0,1)),1),"")} -> 7.62 | I31: =IF(OR(G31="",H31=""),"",H31/G31-1) -> -0.11805556 | J31: 46331 | K31: N | O31: =IF(C31="","",TODAY()-C31) -> 55 | P31: =IF(A31="","",IF(O31>180,"DUE — STALE (>180 days)",IF(J31<>"",IF(ABS(J31-TODAY())<=7,"DUE — EARNINGS WINDOW",IF(I31<>"",IF(ABS(I31)>=0.2,"DUE — PRICE MOVE ±20%",IF(K31="Y","DUE — INSIDER ACTIVITY",IF(I31<>"",IF(ABS(I31)>=0.15,"WATCH — PRICE MOVE ±15%",IF(M31="Y","WATCH — ANALYST SHIFT","Monitor Only")),IF(M31="Y","WATCH — ANALYST SHIFT","Monitor Only")))),IF(K31="Y","DUE — INSIDER ACTIVITY",IF(I31<>"",IF(ABS(I31)>=0.15,"WATCH — PRICE MOVE ±15%",IF(M31="Y","WATCH — ANALYST SHIFT","Monitor Only")),IF(M31="Y","WATCH — ANALYST SHIFT","Monitor Only"))))),IF(I31<>"",IF(ABS(I31)>=0.2,"DUE — PRICE MOVE ±20%",IF(K31="Y","DUE — INSIDER ACTIVITY",IF(I31<>"",IF(ABS(I31)>=0.15,"WATCH — PRICE MOVE ±15%",IF(M31="Y","WATCH — ANALYST SHIFT","Monitor Only")),IF(M31="Y","WATCH — ANALYST SHIFT","Monitor Only")))),IF(K31="Y","DUE — INSIDER ACTIVITY",IF(I31<>"",IF(ABS(I31)>=0.15,"WATCH — PRICE MOVE ±15%",IF(M31="Y","WATCH — ANALYST SHIFT","Monitor Only")),IF(M31="Y","WATCH — ANALYST SHIFT","Monitor Only"))))))) -> Monitor Only
A32: HRL | B32: Tier-1 Avoid (external) | C32: 46245 | E32: 1.93 | G32: 24.3 | H32: {=IFERROR(INDEX(_xlfn.STOCKHISTORY(A32,TODAY()-5,TODAY(),0,0,1),ROWS(_xlfn.STOCKHISTORY(A32,TODAY()-5,TODAY(),0,0,1)),1),"")} -> 20.08 | I32: =IF(OR(G32="",H32=""),"",H32/G32-1) -> -0.17366255 | J32: 46261 | K32: N | M32: N | O32: =IF(C32="","",TODAY()-C32) -> 56 | P32: =IF(A32="","",IF(O32>180,"DUE — STALE (>180 days)",IF(J32<>"",IF(ABS(J32-TODAY())<=7,"DUE — EARNINGS WINDOW",IF(I32<>"",IF(ABS(I32)>=0.2,"DUE — PRICE MOVE ±20%",IF(K32="Y","DUE — INSIDER ACTIVITY",IF(I32<>"",IF(ABS(I32)>=0.15,"WATCH — PRICE MOVE ±15%",IF(M32="Y","WATCH — ANALYST SHIFT","Monitor Only")),IF(M32="Y","WATCH — ANALYST SHIFT","Monitor Only")))),IF(K32="Y","DUE — INSIDER ACTIVITY",IF(I32<>"",IF(ABS(I32)>=0.15,"WATCH — PRICE MOVE ±15%",IF(M32="Y","WATCH — ANALYST SHIFT","Monitor Only")),IF(M32="Y","WATCH — ANALYST SHIFT","Monitor Only"))))),IF(I32<>"",IF(ABS(I32)>=0.2,"DUE — PRICE MOVE ±20%",IF(K32="Y","DUE — INSIDER ACTIVITY",IF(I32<>"",IF(ABS(I32)>=0.15,"WATCH — PRICE MOVE ±15%",IF(M32="Y","WATCH — ANALYST SHIFT","Monitor Only")),IF(M32="Y","WATCH — ANALYST SHIFT","Monitor Only")))),IF(K32="Y","DUE — INSIDER ACTIVITY",IF(I32<>"",IF(ABS(I32)>=0.15,"WATCH — PRICE MOVE ±15%",IF(M32="Y","WATCH — ANALYST SHIFT","Monitor Only")),IF(M32="Y","WATCH — ANALYST SHIFT","Monitor Only"))))))) -> WATCH — PRICE MOVE ±15%
A33: LBRT | B33: Tier-1 Avoid (external) | C33: 46245 | E33: 2.07 | G33: 21.48 | H33: {=IFERROR(INDEX(_xlfn.STOCKHISTORY(A33,TODAY()-5,TODAY(),0,0,1),ROWS(_xlfn.STOCKHISTORY(A33,TODAY()-5,TODAY(),0,0,1)),1),"")} -> 19.59 | I33: =IF(OR(G33="",H33=""),"",H33/G33-1) -> -0.087988827 | J33: 46309 | K33: Y | L33: 2026-07-30: Murti Arjun N (Director) bought $250,009, 51% of holding | M33: N | O33: =IF(C33="","",TODAY()-C33) -> 56 | P33: =IF(A33="","",IF(O33>180,"DUE — STALE (>180 days)",IF(J33<>"",IF(ABS(J33-TODAY())<=7,"DUE — EARNINGS WINDOW",IF(I33<>"",IF(ABS(I33)>=0.2,"DUE — PRICE MOVE ±20%",IF(K33="Y","DUE — INSIDER ACTIVITY",IF(I33<>"",IF(ABS(I33)>=0.15,"WATCH — PRICE MOVE ±15%",IF(M33="Y","WATCH — ANALYST SHIFT","Monitor Only")),IF(M33="Y","WATCH — ANALYST SHIFT","Monitor Only")))),IF(K33="Y","DUE — INSIDER ACTIVITY",IF(I33<>"",IF(ABS(I33)>=0.15,"WATCH — PRICE MOVE ±15%",IF(M33="Y","WATCH — ANALYST SHIFT","Monitor Only")),IF(M33="Y","WATCH — ANALYST SHIFT","Monitor Only"))))),IF(I33<>"",IF(ABS(I33)>=0.2,"DUE — PRICE MOVE ±20%",IF(K33="Y","DUE — INSIDER ACTIVITY",IF(I33<>"",IF(ABS(I33)>=0.15,"WATCH — PRICE MOVE ±15%",IF(M33="Y","WATCH — ANALYST SHIFT","Monitor Only")),IF(M33="Y","WATCH — ANALYST SHIFT","Monitor Only")))),IF(K33="Y","DUE — INSIDER ACTIVITY",IF(I33<>"",IF(ABS(I33)>=0.15,"WATCH — PRICE MOVE ±15%",IF(M33="Y","WATCH — ANALYST SHIFT","Monitor Only")),IF(M33="Y","WATCH — ANALYST SHIFT","Monitor Only"))))))) -> DUE — INSIDER ACTIVITY
A34: LIN | B34: Watch List | C34: 46245 | E34: 4.5 | G34: 490.53 | H34: {=IFERROR(INDEX(_xlfn.STOCKHISTORY(A34,TODAY()-5,TODAY(),0,0,1),ROWS(_xlfn.STOCKHISTORY(A34,TODAY()-5,TODAY(),0,0,1)),1),"")} -> 0.44 | I34: =IF(OR(G34="",H34=""),"",H34/G34-1) -> -0.99910301 | J34: 46325 | K34: Y | L34: 2026-08-19: Reynolds Paula Rosput (Director) bought $47,912, 14% of holding | M34: N | O34: =IF(C34="","",TODAY()-C34) -> 56 | P34: =IF(A34="","",IF(O34>180,"DUE — STALE (>180 days)",IF(J34<>"",IF(ABS(J34-TODAY())<=7,"DUE — EARNINGS WINDOW",IF(I34<>"",IF(ABS(I34)>=0.2,"DUE — PRICE MOVE ±20%",IF(K34="Y","DUE — INSIDER ACTIVITY",IF(I34<>"",IF(ABS(I34)>=0.15,"WATCH — PRICE MOVE ±15%",IF(M34="Y","WATCH — ANALYST SHIFT","Monitor Only")),IF(M34="Y","WATCH — ANALYST SHIFT","Monitor Only")))),IF(K34="Y","DUE — INSIDER ACTIVITY",IF(I34<>"",IF(ABS(I34)>=0.15,"WATCH — PRICE MOVE ±15%",IF(M34="Y","WATCH — ANALYST SHIFT","Monitor Only")),IF(M34="Y","WATCH — ANALYST SHIFT","Monitor Only"))))),IF(I34<>"",IF(ABS(I34)>=0.2,"DUE — PRICE MOVE ±20%",IF(K34="Y","DUE — INSIDER ACTIVITY",IF(I34<>"",IF(ABS(I34)>=0.15,"WATCH — PRICE MOVE ±15%",IF(M34="Y","WATCH — ANALYST SHIFT","Monitor Only")),IF(M34="Y","WATCH — ANALYST SHIFT","Monitor Only")))),IF(K34="Y","DUE — INSIDER ACTIVITY",IF(I34<>"",IF(ABS(I34)>=0.15,"WATCH — PRICE MOVE ±15%",IF(M34="Y","WATCH — ANALYST SHIFT","Monitor Only")),IF(M34="Y","WATCH — ANALYST SHIFT","Monitor Only"))))))) -> DUE — PRICE MOVE ±20%
A35: NEE | B35: Tier-1 Avoid (external) | C35: 46245 | E35: 2.5 | G35: 85.74 | H35: {=IFERROR(INDEX(_xlfn.STOCKHISTORY(A35,TODAY()-5,TODAY(),0,0,1),ROWS(_xlfn.STOCKHISTORY(A35,TODAY()-5,TODAY(),0,0,1)),1),"")} -> 76.28 | I35: =IF(OR(G35="",H35=""),"",H35/G35-1) -> -0.11033357 | J35: 46322 | K35: N | M35: N | O35: =IF(C35="","",TODAY()-C35) -> 56 | P35: =IF(A35="","",IF(O35>180,"DUE — STALE (>180 days)",IF(J35<>"",IF(ABS(J35-TODAY())<=7,"DUE — EARNINGS WINDOW",IF(I35<>"",IF(ABS(I35)>=0.2,"DUE — PRICE MOVE ±20%",IF(K35="Y","DUE — INSIDER ACTIVITY",IF(I35<>"",IF(ABS(I35)>=0.15,"WATCH — PRICE MOVE ±15%",IF(M35="Y","WATCH — ANALYST SHIFT","Monitor Only")),IF(M35="Y","WATCH — ANALYST SHIFT","Monitor Only")))),IF(K35="Y","DUE — INSIDER ACTIVITY",IF(I35<>"",IF(ABS(I35)>=0.15,"WATCH — PRICE MOVE ±15%",IF(M35="Y","WATCH — ANALYST SHIFT","Monitor Only")),IF(M35="Y","WATCH — ANALYST SHIFT","Monitor Only"))))),IF(I35<>"",IF(ABS(I35)>=0.2,"DUE — PRICE MOVE ±20%",IF(K35="Y","DUE — INSIDER ACTIVITY",IF(I35<>"",IF(ABS(I35)>=0.15,"WATCH — PRICE MOVE ±15%",IF(M35="Y","WATCH — ANALYST SHIFT","Monitor Only")),IF(M35="Y","WATCH — ANALYST SHIFT","Monitor Only")))),IF(K35="Y","DUE — INSIDER ACTIVITY",IF(I35<>"",IF(ABS(I35)>=0.15,"WATCH — PRICE MOVE ±15%",IF(M35="Y","WATCH — ANALYST SHIFT","Monitor Only")),IF(M35="Y","WATCH — ANALYST SHIFT","Monitor Only"))))))) -> Monitor Only
A36: NFLX | B36: Owned | C36: 46278 | D36: 83.8 | E36: 4.21 | F36: STRONG BUY | G36: 77.4 | H36: {=IFERROR(INDEX(_xlfn.STOCKHISTORY(A36,TODAY()-5,TODAY(),0,0,1),ROWS(_xlfn.STOCKHISTORY(A36,TODAY()-5,TODAY(),0,0,1)),1),"")} -> 67.5 | I36: =IF(OR(G36="",H36=""),"",H36/G36-1) -> -0.12790698 | J36: 46315 | K36: Y | L36: 2026-09-10: BARTON RICHARD N (Director) sold $54,907, 23% of holding (+2 more in last 30d) | M36: N | O36: =IF(C36="","",TODAY()-C36) -> 23 | P36: =IF(A36="","",IF(O36>180,"DUE — STALE (>180 days)",IF(J36<>"",IF(ABS(J36-TODAY())<=7,"DUE — EARNINGS WINDOW",IF(I36<>"",IF(ABS(I36)>=0.2,"DUE — PRICE MOVE ±20%",IF(K36="Y","DUE — INSIDER ACTIVITY",IF(I36<>"",IF(ABS(I36)>=0.15,"WATCH — PRICE MOVE ±15%",IF(M36="Y","WATCH — ANALYST SHIFT","Monitor Only")),IF(M36="Y","WATCH — ANALYST SHIFT","Monitor Only")))),IF(K36="Y","DUE — INSIDER ACTIVITY",IF(I36<>"",IF(ABS(I36)>=0.15,"WATCH — PRICE MOVE ±15%",IF(M36="Y","WATCH — ANALYST SHIFT","Monitor Only")),IF(M36="Y","WATCH — ANALYST SHIFT","Monitor Only"))))),IF(I36<>"",IF(ABS(I36)>=0.2,"DUE — PRICE MOVE ±20%",IF(K36="Y","DUE — INSIDER ACTIVITY",IF(I36<>"",IF(ABS(I36)>=0.15,"WATCH — PRICE MOVE ±15%",IF(M36="Y","WATCH — ANALYST SHIFT","Monitor Only")),IF(M36="Y","WATCH — ANALYST SHIFT","Monitor Only")))),IF(K36="Y","DUE — INSIDER ACTIVITY",IF(I36<>"",IF(ABS(I36)>=0.15,"WATCH — PRICE MOVE ±15%",IF(M36="Y","WATCH — ANALYST SHIFT","Monitor Only")),IF(M36="Y","WATCH — ANALYST SHIFT","Monitor Only"))))))) -> DUE — INSIDER ACTIVITY
A37: NKE | B37: Tier-1 Avoid (external) | C37: 46246 | E37: 1.57 | G37: 40.51 | H37: {=IFERROR(INDEX(_xlfn.STOCKHISTORY(A37,TODAY()-5,TODAY(),0,0,1),ROWS(_xlfn.STOCKHISTORY(A37,TODAY()-5,TODAY(),0,0,1)),1),"")} -> 33.96 | I37: =IF(OR(G37="",H37=""),"",H37/G37-1) -> -0.16168847 | J37: 46373 | K37: Y | L37: 2026-08-11: Montagne Amy (PRESIDENT, NIKE) sold $204,657, 8% of holding (+1 more in last 30d) | M37: Y | N37: Consensus declined 0.19 (1-5 scale) over 3 months (3.39 -> 3.21, 39 analysts currently) | O37: =IF(C37="","",TODAY()-C37) -> 55 | P37: =IF(A37="","",IF(O37>180,"DUE — STALE (>180 days)",IF(J37<>"",IF(ABS(J37-TODAY())<=7,"DUE — EARNINGS WINDOW",IF(I37<>"",IF(ABS(I37)>=0.2,"DUE — PRICE MOVE ±20%",IF(K37="Y","DUE — INSIDER ACTIVITY",IF(I37<>"",IF(ABS(I37)>=0.15,"WATCH — PRICE MOVE ±15%",IF(M37="Y","WATCH — ANALYST SHIFT","Monitor Only")),IF(M37="Y","WATCH — ANALYST SHIFT","Monitor Only")))),IF(K37="Y","DUE — INSIDER ACTIVITY",IF(I37<>"",IF(ABS(I37)>=0.15,"WATCH — PRICE MOVE ±15%",IF(M37="Y","WATCH — ANALYST SHIFT","Monitor Only")),IF(M37="Y","WATCH — ANALYST SHIFT","Monitor Only"))))),IF(I37<>"",IF(ABS(I37)>=0.2,"DUE — PRICE MOVE ±20%",IF(K37="Y","DUE — INSIDER ACTIVITY",IF(I37<>"",IF(ABS(I37)>=0.15,"WATCH — PRICE MOVE ±15%",IF(M37="Y","WATCH — ANALYST SHIFT","Monitor Only")),IF(M37="Y","WATCH — ANALYST SHIFT","Monitor Only")))),IF(K37="Y","DUE — INSIDER ACTIVITY",IF(I37<>"",IF(ABS(I37)>=0.15,"WATCH — PRICE MOVE ±15%",IF(M37="Y","WATCH — ANALYST SHIFT","Monitor Only")),IF(M37="Y","WATCH — ANALYST SHIFT","Monitor Only"))))))) -> DUE — INSIDER ACTIVITY
A38: NOV | B38: Tier-1 Avoid (external) | C38: 46245 | E38: 2.64 | G38: 21.02 | H38: {=IFERROR(INDEX(_xlfn.STOCKHISTORY(A38,TODAY()-5,TODAY(),0,0,1),ROWS(_xlfn.STOCKHISTORY(A38,TODAY()-5,TODAY(),0,0,1)),1),"")} -> 19.51 | I38: =IF(OR(G38="",H38=""),"",H38/G38-1) -> -0.071836346 | J38: 46322 | K38: Y | L38: 2026-07-31: HARRISON DAVID D (Other) sold $184,301, 7% of holding | M38: Y | N38: Consensus improved 0.21 (1-5 scale) over 3 months (3.19 -> 3.40, 20 analysts currently) | O38: =IF(C38="","",TODAY()-C38) -> 56 | P38: =IF(A38="","",IF(O38>180,"DUE — STALE (>180 days)",IF(J38<>"",IF(ABS(J38-TODAY())<=7,"DUE — EARNINGS WINDOW",IF(I38<>"",IF(ABS(I38)>=0.2,"DUE — PRICE MOVE ±20%",IF(K38="Y","DUE — INSIDER ACTIVITY",IF(I38<>"",IF(ABS(I38)>=0.15,"WATCH — PRICE MOVE ±15%",IF(M38="Y","WATCH — ANALYST SHIFT","Monitor Only")),IF(M38="Y","WATCH — ANALYST SHIFT","Monitor Only")))),IF(K38="Y","DUE — INSIDER ACTIVITY",IF(I38<>"",IF(ABS(I38)>=0.15,"WATCH — PRICE MOVE ±15%",IF(M38="Y","WATCH — ANALYST SHIFT","Monitor Only")),IF(M38="Y","WATCH — ANALYST SHIFT","Monitor Only"))))),IF(I38<>"",IF(ABS(I38)>=0.2,"DUE — PRICE MOVE ±20%",IF(K38="Y","DUE — INSIDER ACTIVITY",IF(I38<>"",IF(ABS(I38)>=0.15,"WATCH — PRICE MOVE ±15%",IF(M38="Y","WATCH — ANALYST SHIFT","Monitor Only")),IF(M38="Y","WATCH — ANALYST SHIFT","Monitor Only")))),IF(K38="Y","DUE — INSIDER ACTIVITY",IF(I38<>"",IF(ABS(I38)>=0.15,"WATCH — PRICE MOVE ±15%",IF(M38="Y","WATCH — ANALYST SHIFT","Monitor Only")),IF(M38="Y","WATCH — ANALYST SHIFT","Monitor Only"))))))) -> DUE — INSIDER ACTIVITY
A39: ONON | B39: Tier-1 Avoid (external) | C39: 46240 | E39: 2.64 | G39: 37.34 | H39: {=IFERROR(INDEX(_xlfn.STOCKHISTORY(A39,TODAY()-5,TODAY(),0,0,1),ROWS(_xlfn.STOCKHISTORY(A39,TODAY()-5,TODAY(),0,0,1)),1),"")} -> 31.88 | I39: =IF(OR(G39="",H39=""),"",H39/G39-1) -> -0.14622389 | J39: 46337 | K39: Y | L39: 2026-08-17: Bernhard Olivier (Executive Officer) bought $1,993,790, 1% of holding (+1 more in last 30d) | M39: N | O39: =IF(C39="","",TODAY()-C39) -> 61 | P39: =IF(A39="","",IF(O39>180,"DUE — STALE (>180 days)",IF(J39<>"",IF(ABS(J39-TODAY())<=7,"DUE — EARNINGS WINDOW",IF(I39<>"",IF(ABS(I39)>=0.2,"DUE — PRICE MOVE ±20%",IF(K39="Y","DUE — INSIDER ACTIVITY",IF(I39<>"",IF(ABS(I39)>=0.15,"WATCH — PRICE MOVE ±15%",IF(M39="Y","WATCH — ANALYST SHIFT","Monitor Only")),IF(M39="Y","WATCH — ANALYST SHIFT","Monitor Only")))),IF(K39="Y","DUE — INSIDER ACTIVITY",IF(I39<>"",IF(ABS(I39)>=0.15,"WATCH — PRICE MOVE ±15%",IF(M39="Y","WATCH — ANALYST SHIFT","Monitor Only")),IF(M39="Y","WATCH — ANALYST SHIFT","Monitor Only"))))),IF(I39<>"",IF(ABS(I39)>=0.2,"DUE — PRICE MOVE ±20%",IF(K39="Y","DUE — INSIDER ACTIVITY",IF(I39<>"",IF(ABS(I39)>=0.15,"WATCH — PRICE MOVE ±15%",IF(M39="Y","WATCH — ANALYST SHIFT","Monitor Only")),IF(M39="Y","WATCH — ANALYST SHIFT","Monitor Only")))),IF(K39="Y","DUE — INSIDER ACTIVITY",IF(I39<>"",IF(ABS(I39)>=0.15,"WATCH — PRICE MOVE ±15%",IF(M39="Y","WATCH — ANALYST SHIFT","Monitor Only")),IF(M39="Y","WATCH — ANALYST SHIFT","Monitor Only"))))))) -> DUE — INSIDER ACTIVITY
A40: PG | B40: Watch List | C40: 46245 | E40: 4.21 | G40: 145.21 | H40: {=IFERROR(INDEX(_xlfn.STOCKHISTORY(A40,TODAY()-5,TODAY(),0,0,1),ROWS(_xlfn.STOCKHISTORY(A40,TODAY()-5,TODAY(),0,0,1)),1),"")} -> 145.94 | I40: =IF(OR(G40="",H40=""),"",H40/G40-1) -> 0.005027202 | J40: 46317 | K40: Y | L40: 2026-08-24: Janzaruk Matthew W. (SVP - Chief Accounting Officer) sold $52,141, 22% of holding (+12 more in last 30d) | M40: N | O40: =IF(C40="","",TODAY()-C40) -> 56 | P40: =IF(A40="","",IF(O40>180,"DUE — STALE (>180 days)",IF(J40<>"",IF(ABS(J40-TODAY())<=7,"DUE — EARNINGS WINDOW",IF(I40<>"",IF(ABS(I40)>=0.2,"DUE — PRICE MOVE ±20%",IF(K40="Y","DUE — INSIDER ACTIVITY",IF(I40<>"",IF(ABS(I40)>=0.15,"WATCH — PRICE MOVE ±15%",IF(M40="Y","WATCH — ANALYST SHIFT","Monitor Only")),IF(M40="Y","WATCH — ANALYST SHIFT","Monitor Only")))),IF(K40="Y","DUE — INSIDER ACTIVITY",IF(I40<>"",IF(ABS(I40)>=0.15,"WATCH — PRICE MOVE ±15%",IF(M40="Y","WATCH — ANALYST SHIFT","Monitor Only")),IF(M40="Y","WATCH — ANALYST SHIFT","Monitor Only"))))),IF(I40<>"",IF(ABS(I40)>=0.2,"DUE — PRICE MOVE ±20%",IF(K40="Y","DUE — INSIDER ACTIVITY",IF(I40<>"",IF(ABS(I40)>=0.15,"WATCH — PRICE MOVE ±15%",IF(M40="Y","WATCH — ANALYST SHIFT","Monitor Only")),IF(M40="Y","WATCH — ANALYST SHIFT","Monitor Only")))),IF(K40="Y","DUE — INSIDER ACTIVITY",IF(I40<>"",IF(ABS(I40)>=0.15,"WATCH — PRICE MOVE ±15%",IF(M40="Y","WATCH — ANALYST SHIFT","Monitor Only")),IF(M40="Y","WATCH — ANALYST SHIFT","Monitor Only"))))))) -> DUE — INSIDER ACTIVITY
A41: PH | B41: Watch List | C41: 46247 | E41: 3.29 | G41: 1058.87 | H41: {=IFERROR(INDEX(_xlfn.STOCKHISTORY(A41,TODAY()-5,TODAY(),0,0,1),ROWS(_xlfn.STOCKHISTORY(A41,TODAY()-5,TODAY(),0,0,1)),1),"")} -> 975.68 | I41: =IF(OR(G41="",H41=""),"",H41/G41-1) -> -0.078564885 | J41: 46331 | K41: Y | L41: 2026-08-19: Scott Patrick (VP & Pres-Fluid Conn. Grp.) sold $1,294,800, 25% of holding (+12 more in last 30d) | M41: N | O41: =IF(C41="","",TODAY()-C41) -> 54 | P41: =IF(A41="","",IF(O41>180,"DUE — STALE (>180 days)",IF(J41<>"",IF(ABS(J41-TODAY())<=7,"DUE — EARNINGS WINDOW",IF(I41<>"",IF(ABS(I41)>=0.2,"DUE — PRICE MOVE ±20%",IF(K41="Y","DUE — INSIDER ACTIVITY",IF(I41<>"",IF(ABS(I41)>=0.15,"WATCH — PRICE MOVE ±15%",IF(M41="Y","WATCH — ANALYST SHIFT","Monitor Only")),IF(M41="Y","WATCH — ANALYST SHIFT","Monitor Only")))),IF(K41="Y","DUE — INSIDER ACTIVITY",IF(I41<>"",IF(ABS(I41)>=0.15,"WATCH — PRICE MOVE ±15%",IF(M41="Y","WATCH — ANALYST SHIFT","Monitor Only")),IF(M41="Y","WATCH — ANALYST SHIFT","Monitor Only"))))),IF(I41<>"",IF(ABS(I41)>=0.2,"DUE — PRICE MOVE ±20%",IF(K41="Y","DUE — INSIDER ACTIVITY",IF(I41<>"",IF(ABS(I41)>=0.15,"WATCH — PRICE MOVE ±15%",IF(M41="Y","WATCH — ANALYST SHIFT","Monitor Only")),IF(M41="Y","WATCH — ANALYST SHIFT","Monitor Only")))),IF(K41="Y","DUE — INSIDER ACTIVITY",IF(I41<>"",IF(ABS(I41)>=0.15,"WATCH — PRICE MOVE ±15%",IF(M41="Y","WATCH — ANALYST SHIFT","Monitor Only")),IF(M41="Y","WATCH — ANALYST SHIFT","Monitor Only"))))))) -> DUE — INSIDER ACTIVITY
A42: PZZA | B42: Tier-1 Avoid (external) | C42: 46245 | E42: 1.36 | G42: 24.32 | H42: {=IFERROR(INDEX(_xlfn.STOCKHISTORY(A42,TODAY()-5,TODAY(),0,0,1),ROWS(_xlfn.STOCKHISTORY(A42,TODAY()-5,TODAY(),0,0,1)),1),"")} -> 19.54 | I42: =IF(OR(G42="",H42=""),"",H42/G42-1) -> -0.19654605 | J42: 46331 | K42: N | M42: Y | N42: Consensus declined 0.29 (1-5 scale) over 3 months (3.29 -> 3.00, 14 analysts currently) | O42: =IF(C42="","",TODAY()-C42) -> 56 | P42: =IF(A42="","",IF(O42>180,"DUE — STALE (>180 days)",IF(J42<>"",IF(ABS(J42-TODAY())<=7,"DUE — EARNINGS WINDOW",IF(I42<>"",IF(ABS(I42)>=0.2,"DUE — PRICE MOVE ±20%",IF(K42="Y","DUE — INSIDER ACTIVITY",IF(I42<>"",IF(ABS(I42)>=0.15,"WATCH — PRICE MOVE ±15%",IF(M42="Y","WATCH — ANALYST SHIFT","Monitor Only")),IF(M42="Y","WATCH — ANALYST SHIFT","Monitor Only")))),IF(K42="Y","DUE — INSIDER ACTIVITY",IF(I42<>"",IF(ABS(I42)>=0.15,"WATCH — PRICE MOVE ±15%",IF(M42="Y","WATCH — ANALYST SHIFT","Monitor Only")),IF(M42="Y","WATCH — ANALYST SHIFT","Monitor Only"))))),IF(I42<>"",IF(ABS(I42)>=0.2,"DUE — PRICE MOVE ±20%",IF(K42="Y","DUE — INSIDER ACTIVITY",IF(I42<>"",IF(ABS(I42)>=0.15,"WATCH — PRICE MOVE ±15%",IF(M42="Y","WATCH — ANALYST SHIFT","Monitor Only")),IF(M42="Y","WATCH — ANALYST SHIFT","Monitor Only")))),IF(K42="Y","DUE — INSIDER ACTIVITY",IF(I42<>"",IF(ABS(I42)>=0.15,"WATCH — PRICE MOVE ±15%",IF(M42="Y","WATCH — ANALYST SHIFT","Monitor Only")),IF(M42="Y","WATCH — ANALYST SHIFT","Monitor Only"))))))) -> WATCH — PRICE MOVE ±15%
A43: SFM | B43: Tier-1 Avoid (external) | C43: 46240 | E43: 1.86 | G43: 87.2 | H43: {=IFERROR(INDEX(_xlfn.STOCKHISTORY(A43,TODAY()-5,TODAY(),0,0,1),ROWS(_xlfn.STOCKHISTORY(A43,TODAY()-5,TODAY(),0,0,1)),1),"")} -> 64.92 | I43: =IF(OR(G43="",H43=""),"",H43/G43-1) -> -0.25550459 | J43: 46323 | K43: Y | L43: 2026-08-17: O'Leary Joseph D (Director) sold $214,440, 15% of holding (+2 more in last 30d) | M43: N | O43: =IF(C43="","",TODAY()-C43) -> 61 | P43: =IF(A43="","",IF(O43>180,"DUE — STALE (>180 days)",IF(J43<>"",IF(ABS(J43-TODAY())<=7,"DUE — EARNINGS WINDOW",IF(I43<>"",IF(ABS(I43)>=0.2,"DUE — PRICE MOVE ±20%",IF(K43="Y","DUE — INSIDER ACTIVITY",IF(I43<>"",IF(ABS(I43)>=0.15,"WATCH — PRICE MOVE ±15%",IF(M43="Y","WATCH — ANALYST SHIFT","Monitor Only")),IF(M43="Y","WATCH — ANALYST SHIFT","Monitor Only")))),IF(K43="Y","DUE — INSIDER ACTIVITY",IF(I43<>"",IF(ABS(I43)>=0.15,"WATCH — PRICE MOVE ±15%",IF(M43="Y","WATCH — ANALYST SHIFT","Monitor Only")),IF(M43="Y","WATCH — ANALYST SHIFT","Monitor Only"))))),IF(I43<>"",IF(ABS(I43)>=0.2,"DUE — PRICE MOVE ±20%",IF(K43="Y","DUE — INSIDER ACTIVITY",IF(I43<>"",IF(ABS(I43)>=0.15,"WATCH — PRICE MOVE ±15%",IF(M43="Y","WATCH — ANALYST SHIFT","Monitor Only")),IF(M43="Y","WATCH — ANALYST SHIFT","Monitor Only")))),IF(K43="Y","DUE — INSIDER ACTIVITY",IF(I43<>"",IF(ABS(I43)>=0.15,"WATCH — PRICE MOVE ±15%",IF(M43="Y","WATCH — ANALYST SHIFT","Monitor Only")),IF(M43="Y","WATCH — ANALYST SHIFT","Monitor Only"))))))) -> DUE — PRICE MOVE ±20%
A44: TSLA | B44: Tier-1 Avoid (external) | C44: 46240 | E44: 1.93 | G44: 319.53 | H44: {=IFERROR(INDEX(_xlfn.STOCKHISTORY(A44,TODAY()-5,TODAY(),0,0,1),ROWS(_xlfn.STOCKHISTORY(A44,TODAY()-5,TODAY(),0,0,1)),1),"")} -> 378.73 | I44: =IF(OR(G44="",H44=""),"",H44/G44-1) -> 0.18527212 | J44: 46316 | K44: N | M44: N | O44: =IF(C44="","",TODAY()-C44) -> 61 | P44: =IF(A44="","",IF(O44>180,"DUE — STALE (>180 days)",IF(J44<>"",IF(ABS(J44-TODAY())<=7,"DUE — EARNINGS WINDOW",IF(I44<>"",IF(ABS(I44)>=0.2,"DUE — PRICE MOVE ±20%",IF(K44="Y","DUE — INSIDER ACTIVITY",IF(I44<>"",IF(ABS(I44)>=0.15,"WATCH — PRICE MOVE ±15%",IF(M44="Y","WATCH — ANALYST SHIFT","Monitor Only")),IF(M44="Y","WATCH — ANALYST SHIFT","Monitor Only")))),IF(K44="Y","DUE — INSIDER ACTIVITY",IF(I44<>"",IF(ABS(I44)>=0.15,"WATCH — PRICE MOVE ±15%",IF(M44="Y","WATCH — ANALYST SHIFT","Monitor Only")),IF(M44="Y","WATCH — ANALYST SHIFT","Monitor Only"))))),IF(I44<>"",IF(ABS(I44)>=0.2,"DUE — PRICE MOVE ±20%",IF(K44="Y","DUE — INSIDER ACTIVITY",IF(I44<>"",IF(ABS(I44)>=0.15,"WATCH — PRICE MOVE ±15%",IF(M44="Y","WATCH — ANALYST SHIFT","Monitor Only")),IF(M44="Y","WATCH — ANALYST SHIFT","Monitor Only")))),IF(K44="Y","DUE — INSIDER ACTIVITY",IF(I44<>"",IF(ABS(I44)>=0.15,"WATCH — PRICE MOVE ±15%",IF(M44="Y","WATCH — ANALYST SHIFT","Monitor Only")),IF(M44="Y","WATCH — ANALYST SHIFT","Monitor Only"))))))) -> WATCH — PRICE MOVE ±15%
A45: V | B45: Owned | C45: 46278 | D45: 73.4 | E45: 3.64 | F45: BUY | G45: 370.45 | H45: {=IFERROR(INDEX(_xlfn.STOCKHISTORY(A45,TODAY()-5,TODAY(),0,0,1),ROWS(_xlfn.STOCKHISTORY(A45,TODAY()-5,TODAY(),0,0,1)),1),"")} -> 369.71 | I45: =IF(OR(G45="",H45=""),"",H45/G45-1) -> -0.0019975705 | J45: 46322 | K45: Y | L45: 2026-10-02: MCINERNEY RYAN (Chief Executive Officer) sold $2,108,009, 28% of holding (+1 more in last 30d) | M45: N | O45: =IF(C45="","",TODAY()-C45) -> 23 | P45: =IF(A45="","",IF(O45>180,"DUE — STALE (>180 days)",IF(J45<>"",IF(ABS(J45-TODAY())<=7,"DUE — EARNINGS WINDOW",IF(I45<>"",IF(ABS(I45)>=0.2,"DUE — PRICE MOVE ±20%",IF(K45="Y","DUE — INSIDER ACTIVITY",IF(I45<>"",IF(ABS(I45)>=0.15,"WATCH — PRICE MOVE ±15%",IF(M45="Y","WATCH — ANALYST SHIFT","Monitor Only")),IF(M45="Y","WATCH — ANALYST SHIFT","Monitor Only")))),IF(K45="Y","DUE — INSIDER ACTIVITY",IF(I45<>"",IF(ABS(I45)>=0.15,"WATCH — PRICE MOVE ±15%",IF(M45="Y","WATCH — ANALYST SHIFT","Monitor Only")),IF(M45="Y","WATCH — ANALYST SHIFT","Monitor Only"))))),IF(I45<>"",IF(ABS(I45)>=0.2,"DUE — PRICE MOVE ±20%",IF(K45="Y","DUE — INSIDER ACTIVITY",IF(I45<>"",IF(ABS(I45)>=0.15,"WATCH — PRICE MOVE ±15%",IF(M45="Y","WATCH — ANALYST SHIFT","Monitor Only")),IF(M45="Y","WATCH — ANALYST SHIFT","Monitor Only")))),IF(K45="Y","DUE — INSIDER ACTIVITY",IF(I45<>"",IF(ABS(I45)>=0.15,"WATCH — PRICE MOVE ±15%",IF(M45="Y","WATCH — ANALYST SHIFT","Monitor Only")),IF(M45="Y","WATCH — ANALYST SHIFT","Monitor Only"))))))) -> DUE — INSIDER ACTIVITY
A46: VFC | B46: Tier-1 Avoid (external) | C46: 46246 | E46: 2.86 | G46: 14.57 | H46: {=IFERROR(INDEX(_xlfn.STOCKHISTORY(A46,TODAY()-5,TODAY(),0,0,1),ROWS(_xlfn.STOCKHISTORY(A46,TODAY()-5,TODAY(),0,0,1)),1),"")} -> 14.27 | I46: =IF(OR(G46="",H46=""),"",H46/G46-1) -> -0.020590254 | J46: 46321 | K46: Y | L46: 2026-08-17: Carucci Richard (Director) bought $294,600, 6% of holding (+1 more in last 30d) | M46: N | O46: =IF(C46="","",TODAY()-C46) -> 55 | P46: =IF(A46="","",IF(O46>180,"DUE — STALE (>180 days)",IF(J46<>"",IF(ABS(J46-TODAY())<=7,"DUE — EARNINGS WINDOW",IF(I46<>"",IF(ABS(I46)>=0.2,"DUE — PRICE MOVE ±20%",IF(K46="Y","DUE — INSIDER ACTIVITY",IF(I46<>"",IF(ABS(I46)>=0.15,"WATCH — PRICE MOVE ±15%",IF(M46="Y","WATCH — ANALYST SHIFT","Monitor Only")),IF(M46="Y","WATCH — ANALYST SHIFT","Monitor Only")))),IF(K46="Y","DUE — INSIDER ACTIVITY",IF(I46<>"",IF(ABS(I46)>=0.15,"WATCH — PRICE MOVE ±15%",IF(M46="Y","WATCH — ANALYST SHIFT","Monitor Only")),IF(M46="Y","WATCH — ANALYST SHIFT","Monitor Only"))))),IF(I46<>"",IF(ABS(I46)>=0.2,"DUE — PRICE MOVE ±20%",IF(K46="Y","DUE — INSIDER ACTIVITY",IF(I46<>"",IF(ABS(I46)>=0.15,"WATCH — PRICE MOVE ±15%",IF(M46="Y","WATCH — ANALYST SHIFT","Monitor Only")),IF(M46="Y","WATCH — ANALYST SHIFT","Monitor Only")))),IF(K46="Y","DUE — INSIDER ACTIVITY",IF(I46<>"",IF(ABS(I46)>=0.15,"WATCH — PRICE MOVE ±15%",IF(M46="Y","WATCH — ANALYST SHIFT","Monitor Only")),IF(M46="Y","WATCH — ANALYST SHIFT","Monitor Only"))))))) -> DUE — INSIDER ACTIVITY
A47: YUM | B47: Watch List | C47: 46245 | E47: 4.29 | G47: 144.75 | H47: {=IFERROR(INDEX(_xlfn.STOCKHISTORY(A47,TODAY()-5,TODAY(),0,0,1),ROWS(_xlfn.STOCKHISTORY(A47,TODAY()-5,TODAY(),0,0,1)),1),"")} -> 136.97 | I47: =IF(OR(G47="",H47=""),"",H47/G47-1) -> -0.053747841 | J47: 46329 | K47: Y | L47: 2026-08-24: Skeans Tracy L (COO and CPO) sold $552,052, 100% of holding (+2 more in last 30d) | M47: N | O47: =IF(C47="","",TODAY()-C47) -> 56 | P47: =IF(A47="","",IF(O47>180,"DUE — STALE (>180 days)",IF(J47<>"",IF(ABS(J47-TODAY())<=7,"DUE — EARNINGS WINDOW",IF(I47<>"",IF(ABS(I47)>=0.2,"DUE — PRICE MOVE ±20%",IF(K47="Y","DUE — INSIDER ACTIVITY",IF(I47<>"",IF(ABS(I47)>=0.15,"WATCH — PRICE MOVE ±15%",IF(M47="Y","WATCH — ANALYST SHIFT","Monitor Only")),IF(M47="Y","WATCH — ANALYST SHIFT","Monitor Only")))),IF(K47="Y","DUE — INSIDER ACTIVITY",IF(I47<>"",IF(ABS(I47)>=0.15,"WATCH — PRICE MOVE ±15%",IF(M47="Y","WATCH — ANALYST SHIFT","Monitor Only")),IF(M47="Y","WATCH — ANALYST SHIFT","Monitor Only"))))),IF(I47<>"",IF(ABS(I47)>=0.2,"DUE — PRICE MOVE ±20%",IF(K47="Y","DUE — INSIDER ACTIVITY",IF(I47<>"",IF(ABS(I47)>=0.15,"WATCH — PRICE MOVE ±15%",IF(M47="Y","WATCH — ANALYST SHIFT","Monitor Only")),IF(M47="Y","WATCH — ANALYST SHIFT","Monitor Only")))),IF(K47="Y","DUE — INSIDER ACTIVITY",IF(I47<>"",IF(ABS(I47)>=0.15,"WATCH — PRICE MOVE ±15%",IF(M47="Y","WATCH — ANALYST SHIFT","Monitor Only")),IF(M47="Y","WATCH — ANALYST SHIFT","Monitor Only"))))))) -> DUE — INSIDER ACTIVITY
A48: KGS | B48: Watch List | C48: 46276 | E48: 4 | G48: 63.85 | H48: {=IFERROR(INDEX(_xlfn.STOCKHISTORY(A48,TODAY()-5,TODAY(),0,0,1),ROWS(_xlfn.STOCKHISTORY(A48,TODAY()-5,TODAY(),0,0,1)),1),"")} -> 53.56 | I48: =IF(OR(G48="",H48=""),"",H48/G48-1) -> -0.16115897 | J48: 46329 | K48: N | M48: N | O48: =IF(C48="","",TODAY()-C48) -> 25 | P48: =IF(A48="","",IF(O48>180,"DUE — STALE (>180 days)",IF(J48<>"",IF(ABS(J48-TODAY())<=7,"DUE — EARNINGS WINDOW",IF(I48<>"",IF(ABS(I48)>=0.2,"DUE — PRICE MOVE ±20%",IF(K48="Y","DUE — INSIDER ACTIVITY",IF(I48<>"",IF(ABS(I48)>=0.15,"WATCH — PRICE MOVE ±15%",IF(M48="Y","WATCH — ANALYST SHIFT","Monitor Only")),IF(M48="Y","WATCH — ANALYST SHIFT","Monitor Only")))),IF(K48="Y","DUE — INSIDER ACTIVITY",IF(I48<>"",IF(ABS(I48)>=0.15,"WATCH — PRICE MOVE ±15%",IF(M48="Y","WATCH — ANALYST SHIFT","Monitor Only")),IF(M48="Y","WATCH — ANALYST SHIFT","Monitor Only"))))),IF(I48<>"",IF(ABS(I48)>=0.2,"DUE — PRICE MOVE ±20%",IF(K48="Y","DUE — INSIDER ACTIVITY",IF(I48<>"",IF(ABS(I48)>=0.15,"WATCH — PRICE MOVE ±15%",IF(M48="Y","WATCH — ANALYST SHIFT","Monitor Only")),IF(M48="Y","WATCH — ANALYST SHIFT","Monitor Only")))),IF(K48="Y","DUE — INSIDER ACTIVITY",IF(I48<>"",IF(ABS(I48)>=0.15,"WATCH — PRICE MOVE ±15%",IF(M48="Y","WATCH — ANALYST SHIFT","Monitor Only")),IF(M48="Y","WATCH — ANALYST SHIFT","Monitor Only"))))))) -> WATCH — PRICE MOVE ±15% | Q48: Diversification candidate (Energy -- gas compression services, contract-based revenue, not upstream E&P). Fresh Tier 1 quant screen 9/11/26; Moat/Rev Visibility not yet assessed (Part 12).
A49: ABT | B49: Watch List | C49: 46278 | D49: 70.8 | E49: 3.5 | F49: BUY | G49: 101.95 | H49: {=IFERROR(INDEX(_xlfn.STOCKHISTORY(A49,TODAY()-5,TODAY(),0,0,1),ROWS(_xlfn.STOCKHISTORY(A49,TODAY()-5,TODAY(),0,0,1)),1),"")} -> 100.1 | I49: =IF(OR(G49="",H49=""),"",H49/G49-1) -> -0.01814615 | J49: 46316 | K49: N | M49: N | O49: =IF(C49="","",TODAY()-C49) -> 23 | P49: =IF(A49="","",IF(O49>180,"DUE — STALE (>180 days)",IF(J49<>"",IF(ABS(J49-TODAY())<=7,"DUE — EARNINGS WINDOW",IF(I49<>"",IF(ABS(I49)>=0.2,"DUE — PRICE MOVE ±20%",IF(K49="Y","DUE — INSIDER ACTIVITY",IF(I49<>"",IF(ABS(I49)>=0.15,"WATCH — PRICE MOVE ±15%",IF(M49="Y","WATCH — ANALYST SHIFT","Monitor Only")),IF(M49="Y","WATCH — ANALYST SHIFT","Monitor Only")))),IF(K49="Y","DUE — INSIDER ACTIVITY",IF(I49<>"",IF(ABS(I49)>=0.15,"WATCH — PRICE MOVE ±15%",IF(M49="Y","WATCH — ANALYST SHIFT","Monitor Only")),IF(M49="Y","WATCH — ANALYST SHIFT","Monitor Only"))))),IF(I49<>"",IF(ABS(I49)>=0.2,"DUE — PRICE MOVE ±20%",IF(K49="Y","DUE — INSIDER ACTIVITY",IF(I49<>"",IF(ABS(I49)>=0.15,"WATCH — PRICE MOVE ±15%",IF(M49="Y","WATCH — ANALYST SHIFT","Monitor Only")),IF(M49="Y","WATCH — ANALYST SHIFT","Monitor Only")))),IF(K49="Y","DUE — INSIDER ACTIVITY",IF(I49<>"",IF(ABS(I49)>=0.15,"WATCH — PRICE MOVE ±15%",IF(M49="Y","WATCH — ANALYST SHIFT","Monitor Only")),IF(M49="Y","WATCH — ANALYST SHIFT","Monitor Only"))))))) -> Monitor Only | Q49: Bench candidate (Healthcare / Medical Devices). Scored 9/13/26: BUY 70.8, Tier 1 avg 3.50. Relative Strength=1 -> Rule 5 review before any purchase. Added to Monitor 10/4/26 (Open Items #28).
A50: SLB | B50: Watch List | C50: 46278 | D50: 72.4 | E50: 3.5 | F50: BUY | G50: 56.06 | H50: {=IFERROR(INDEX(_xlfn.STOCKHISTORY(A50,TODAY()-5,TODAY(),0,0,1),ROWS(_xlfn.STOCKHISTORY(A50,TODAY()-5,TODAY(),0,0,1)),1),"")} -> 50.28 | I50: =IF(OR(G50="",H50=""),"",H50/G50-1) -> -0.10310382 | J50: 46318 | K50: N | M50: N | O50: =IF(C50="","",TODAY()-C50) -> 23 | P50: =IF(A50="","",IF(O50>180,"DUE — STALE (>180 days)",IF(J50<>"",IF(ABS(J50-TODAY())<=7,"DUE — EARNINGS WINDOW",IF(I50<>"",IF(ABS(I50)>=0.2,"DUE — PRICE MOVE ±20%",IF(K50="Y","DUE — INSIDER ACTIVITY",IF(I50<>"",IF(ABS(I50)>=0.15,"WATCH — PRICE MOVE ±15%",IF(M50="Y","WATCH — ANALYST SHIFT","Monitor Only")),IF(M50="Y","WATCH — ANALYST SHIFT","Monitor Only")))),IF(K50="Y","DUE — INSIDER ACTIVITY",IF(I50<>"",IF(ABS(I50)>=0.15,"WATCH — PRICE MOVE ±15%",IF(M50="Y","WATCH — ANALYST SHIFT","Monitor Only")),IF(M50="Y","WATCH — ANALYST SHIFT","Monitor Only"))))),IF(I50<>"",IF(ABS(I50)>=0.2,"DUE — PRICE MOVE ±20%",IF(K50="Y","DUE — INSIDER ACTIVITY",IF(I50<>"",IF(ABS(I50)>=0.15,"WATCH — PRICE MOVE ±15%",IF(M50="Y","WATCH — ANALYST SHIFT","Monitor Only")),IF(M50="Y","WATCH — ANALYST SHIFT","Monitor Only")))),IF(K50="Y","DUE — INSIDER ACTIVITY",IF(I50<>"",IF(ABS(I50)>=0.15,"WATCH — PRICE MOVE ±15%",IF(M50="Y","WATCH — ANALYST SHIFT","Monitor Only")),IF(M50="Y","WATCH — ANALYST SHIFT","Monitor Only"))))))) -> Monitor Only | Q50: Bench candidate (Energy / Oil & Gas Equipment & Services). Scored 9/13/26: BUY 72.4, Tier 1 avg 3.50. Added to Monitor 10/4/26 (Open Items #28).
A51: VEEV | B51: Watch List | C51: 46297 | D51: 81.6 | E51: 4.29 | F51: STRONG BUY | G51: 273.33 | H51: {=IFERROR(INDEX(_xlfn.STOCKHISTORY(A51,TODAY()-5,TODAY(),0,0,1),ROWS(_xlfn.STOCKHISTORY(A51,TODAY()-5,TODAY(),0,0,1)),1),"")} -> 283.45 | I51: =IF(OR(G51="",H51=""),"",H51/G51-1) -> 0.037024842 | J51: 46351 | K51: Y | L51: 2026-09-16: Schwenger Thomas D. (Pres. & Chief Customer Officer) sold $265,200, 5% of holding (+1 more in last 30d) | M51: N | O51: =IF(C51="","",TODAY()-C51) -> 4 | P51: =IF(A51="","",IF(O51>180,"DUE — STALE (>180 days)",IF(J51<>"",IF(ABS(J51-TODAY())<=7,"DUE — EARNINGS WINDOW",IF(I51<>"",IF(ABS(I51)>=0.2,"DUE — PRICE MOVE ±20%",IF(K51="Y","DUE — INSIDER ACTIVITY",IF(I51<>"",IF(ABS(I51)>=0.15,"WATCH — PRICE MOVE ±15%",IF(M51="Y","WATCH — ANALYST SHIFT","Monitor Only")),IF(M51="Y","WATCH — ANALYST SHIFT","Monitor Only")))),IF(K51="Y","DUE — INSIDER ACTIVITY",IF(I51<>"",IF(ABS(I51)>=0.15,"WATCH — PRICE MOVE ±15%",IF(M51="Y","WATCH — ANALYST SHIFT","Monitor Only")),IF(M51="Y","WATCH — ANALYST SHIFT","Monitor Only"))))),IF(I51<>"",IF(ABS(I51)>=0.2,"DUE — PRICE MOVE ±20%",IF(K51="Y","DUE — INSIDER ACTIVITY",IF(I51<>"",IF(ABS(I51)>=0.15,"WATCH — PRICE MOVE ±15%",IF(M51="Y","WATCH — ANALYST SHIFT","Monitor Only")),IF(M51="Y","WATCH — ANALYST SHIFT","Monitor Only")))),IF(K51="Y","DUE — INSIDER ACTIVITY",IF(I51<>"",IF(ABS(I51)>=0.15,"WATCH — PRICE MOVE ±15%",IF(M51="Y","WATCH — ANALYST SHIFT","Monitor Only")),IF(M51="Y","WATCH — ANALYST SHIFT","Monitor Only"))))))) -> DUE — INSIDER ACTIVITY | Q51: Bench candidate (Healthcare / Health Information Services). Scored 10/2/26: STRONG BUY 81.6, Tier 1 avg 4.29. Moat 4 approved; Alan leans 3 (78.6, BUY) -- re-evaluate at purchase (Open Items #24). Q3 earnings 11/18/26 (Fidelity, unconfirmed; yfinance says 11/25) is the natural re-check point, not a hold-off. Added to Monitor 10/4/26 (Open Items #28).

Sheet Price History
A1: Weekly closing price ($), week-ending Friday, dividend-adjusted so week-over-week changes are total returns (Rule 38: 24-month target, 12-month minimum, 36-month max). One column per held position (ex-cash sweeps): keep it current with `python -m landry prices` (status / append / rebuild / add TICKER).
A2: Week Ending | B2: ADBE | C2: ANET | D2: ASML | E2: AVGO | F2: CRWD | G2: KLAC | H2: MU | I2: NVDA | J2: PLD | K2: PLTR | L2: TSM | M2: VRT | N2: VRTX | O2: AVUV | P2: DVY | Q2: HELO | R2: JEPQ | S2: SPMO | T2: VFLO | U2: SCHD | V2: V | W2: VYM | X2: MLPI | Y2: JEPI | Z2: GE | AA2: NFLX
A3: 45184 | B3: 528.89 | C3: 46.18 | D3: 582.01 | E3: 82 | F3: 41.36 | G3: 44.35 | H3: 69.11 | I3: 43.77 | J3: 111.84 | K3: 15.33 | L3: 85.75 | M3: 38.02 | N3: 348.9 | O3: 75.31 | P3: 100.59 | R3: 34.48 | S3: 57.63 | T3: 25.24 | U3: 21.8 | V3: 235.63 | W3: 98.59 | Y3: 43.23 | Z3: 90.68 | AA3: 39.69
A4: 45191 | B4: 512.9 | C4: 45.08 | D4: 572.69 | E4: 80.26 | F4: 40.64 | G4: 44.12 | H4: 68.12 | I4: 41.49 | J4: 103.57 | K4: 14.13 | L4: 82.28 | M4: 36.31 | N4: 349.53 | O4: 73.11 | P4: 98.44 | R4: 33.55 | S4: 56.23 | T4: 24.87 | U4: 21.3 | V4: 229.78 | W4: 96.44 | Y4: 42.42 | Z4: 87.35 | AA4: 37.98
A5: 45198 | B5: 509.9 | C5: 45.98 | D5: 574.21 | E5: 80.41 | F5: 41.85 | G5: 44.79 | H5: 67.28 | I5: 43.37 | J5: 101.88 | K5: 16 | L5: 83.49 | M5: 37.06 | N5: 347.74 | O5: 74.31 | P5: 96.59 | Q5: 48.9 | R5: 33.57 | S5: 56.06 | T5: 24.94 | U5: 21.14 | V5: 224.82 | W5: 95.21 | Y5: 41.95 | Z5: 86.86 | AA5: 37.76
A6: 45205 | B6: 526.68 | C6: 48.51 | D6: 582.69 | E6: 81.83 | F6: 44.17 | G6: 45.7 | H6: 69.3 | I6: 45.63 | J6: 98.88 | K6: 16.61 | L6: 85.79 | M6: 39.62 | N6: 360.62 | O6: 72.07 | P6: 94.44 | Q6: 49.06 | R6: 34.01 | S6: 56.68 | T6: 24.47 | U6: 20.8 | V6: 229.74 | W6: 93.36 | Y6: 41.8 | Z6: 87.59 | AA6: 38.15
A7: 45212 | B7: 548.76 | C7: 47.46 | D7: 585.03 | E7: 85.5 | F7: 46.43 | G7: 47.54 | H7: 68.56 | I7: 45.33 | J7: 99.56 | K7: 17.36 | L7: 86.92 | M7: 38.95 | N7: 371 | O7: 72.26 | P7: 95.73 | Q7: 49.23 | R7: 34.1 | S7: 57 | T7: 24.82 | U7: 21.01 | V7: 232.31 | W7: 94.42 | Y7: 42.16 | Z7: 85.94 | AA7: 35.57
A8: 45219 | B8: 540.96 | C8: 46.53 | D8: 565.86 | E8: 82.64 | F8: 44.69 | G8: 45.16 | H8: 66.59 | I8: 41.26 | J8: 93 | K8: 16.11 | L8: 87.73 | M8: 36.6 | N8: 361.86 | O8: 71.05 | P8: 93.91 | Q8: 48.67 | R8: 33.43 | S8: 55.35 | T8: 24.51 | U8: 20.7 | V8: 228.12 | W8: 93.27 | Y8: 41.54 | Z8: 83.35 | AA8: 40.1
A9: 45226 | B9: 508.12 | C9: 44.05 | D9: 575.52 | E9: 81.16 | F9: 43.21 | G9: 44.72 | H9: 65.03 | I9: 40.38 | J9: 88.36 | K9: 15.07 | L9: 82.62 | M9: 36.28 | N9: 355.28 | O9: 69.95 | P9: 92.4 | Q9: 47.83 | R9: 32.73 | S9: 54.23 | T9: 23.7 | U9: 19.99 | V9: 224.1 | W9: 90.96 | Y9: 40.62 | Z9: 83.56 | AA9: 39.79
A10: 45233 | B10: 563.66 | C10: 53.12 | D10: 628.24 | E10: 85.45 | F10: 47.06 | G10: 48.79 | H10: 71.9 | I10: 44.87 | J10: 96.74 | K10: 18.89 | L10: 88.19 | M10: 40.28 | N10: 376.2 | O10: 74.96 | P10: 97.82 | Q10: 49.76 | R10: 34.61 | S10: 57.4 | T10: 25.09 | U10: 20.99 | V10: 238.11 | W10: 95.67 | Y10: 42.55 | Z10: 85.58 | AA10: 43.24
A11: 45240 | B11: 597.22 | C11: 51.71 | D11: 646.7 | E11: 92.69 | F11: 49.08 | G11: 52.17 | H11: 74.65 | I11: 48.19 | J11: 94.93 | K11: 19.67 | L11: 93.62 | M11: 41.67 | N11: 373.65 | O11: 72.4 | P11: 95.61 | Q11: 50.26 | R11: 35.33 | S11: 59.09 | T11: 24.93 | U11: 20.75 | V11: 240.23 | W11: 94.59 | Y11: 42.72 | Z11: 90.57 | AA11: 44.72
A12: 45247 | B12: 602.66 | C12: 53.66 | D12: 670.96 | E12: 94.65 | F12: 51.77 | G12: 53.32 | H12: 76.83 | I12: 49.15 | J12: 99.94 | K12: 20.49 | L12: 95.68 | M12: 43.12 | N12: 350.5 | O12: 76.42 | P12: 99 | Q12: 50.91 | R12: 35.66 | S12: 60.37 | T12: 25.57 | U12: 21.25 | V12: 244.45 | W12: 97.01 | Y12: 43.09 | Z12: 94.23 | AA12: 46.59
A13: 45254 | B13: 619.43 | C13: 54.6 | D13: 675.94 | E13: 94.76 | F13: 52.67 | G13: 54.41 | H13: 76.15 | I13: 47.63 | J13: 101.69 | K13: 19.2 | L13: 94 | M13: 42.52 | N13: 353.04 | O13: 76.43 | P13: 99.35 | Q13: 51.13 | R13: 35.85 | S13: 60.7 | T13: 25.75 | U13: 21.45 | V13: 249.1 | W13: 97.69 | Y13: 43.42 | Z13: 94.27 | AA13: 47.96
A14: 45261 | B14: 612.47 | C14: 54.16 | D14: 676.94 | E14: 90.03 | F14: 58.76 | G14: 53.76 | H14: 75.22 | I14: 46.63 | J14: 107.37 | K14: 20.27 | L14: 94.69 | M14: 44.97 | N14: 351.16 | O14: 78.99 | P14: 102.26 | Q14: 51.18 | R14: 35.92 | S14: 60.57 | T14: 26.1 | U14: 21.85 | V14: 251.2 | W14: 99.38 | Y14: 43.62 | Z14: 96.25 | AA14: 46.57
A15: 45268 | B15: 610.01 | C15: 56.01 | D15: 681.07 | E15: 91.41 | F15: 60.64 | G15: 52.33 | H15: 74.26 | I15: 47.37 | J15: 108.82 | K15: 17.77 | L15: 96.42 | M15: 46.98 | N15: 350.15 | O15: 79.65 | P15: 102.48 | Q15: 51.37 | R15: 36.18 | S15: 60.79 | T15: 26.33 | U15: 21.89 | V15: 250.51 | W15: 99.15 | Y15: 43.49 | Z15: 94.75 | AA15: 45.38
A16: 45275 | B16: 584.68 | C16: 58.9 | D16: 736.36 | E16: 109.37 | F16: 65.02 | G16: 57.29 | H16: 80.64 | I16: 48.75 | J16: 122.68 | K16: 18.2 | L16: 98.99 | M16: 47.57 | N16: 410.68 | O16: 84.02 | P16: 105.54 | Q16: 51.84 | R16: 36.73 | S16: 62.87 | T16: 27.06 | U16: 22.77 | V16: 252.75 | W16: 102.56 | Y16: 44.02 | Z16: 96.83 | AA16: 47.21
... A120: 46003 | B120: 356.43 | C120: 124.76 | D120: 1075.68 | E120: 357.27 | F120: 126.19 | G120: 118.95 | H120: 240.9 | I120: 174.61 | J120: 126.22 | K120: 183.57 | L120: 289.76 | M120: 161.16 | N120: 452.04 | O120: 103.74 | P120: 139.19 | Q120: 65.88 | R120: 52.69 | S120: 118.1 | T120: 39.44 | U120: 27.02 | V120: 345.75 | W120: 142.52 | Y120: 53.98 | Z120: 298.66 | AA120: 95.19
A121: 46010 | B121: 355.86 | C121: 131.12 | D121: 1050.97 | E121: 337.85 | F121: 120.32 | G121: 124.11 | H121: 265.66 | I121: 180.57 | J121: 124.32 | K121: 193.38 | L121: 286.7 | M121: 159.71 | N121: 456.2 | O121: 102.8 | P121: 138.55 | Q121: 66.03 | R121: 53.08 | S121: 118.53 | T121: 39.27 | U121: 26.8 | V121: 347.17 | W121: 140.83 | X121: 44.15 | Y121: 53.8 | Z121: 306.03 | AA121: 94.39
A122: 46017 | B122: 353.8 | C122: 131.84 | D122: 1067.62 | E122: 350.2 | F122: 120.3 | G122: 127.49 | H122: 284.51 | I122: 190.09 | J122: 125.76 | K122: 188.71 | L122: 300.48 | M122: 167.46 | N122: 462.9 | O122: 102.71 | P122: 139.28 | Q122: 66.73 | R122: 53.74 | S122: 120.66 | T122: 39.53 | U122: 26.98 | V122: 352.88 | W122: 142.56 | X122: 44.85 | Y122: 54.25 | Z122: 313.93 | AA122: 94.47
A123: 46024 | B123: 333.3 | C123: 133.6 | D123: 1158.22 | E123: 345.71 | F123: 113.39 | G123: 126.98 | H123: 315.24 | I123: 188.41 | J123: 126.1 | K123: 167.86 | L123: 317.12 | M123: 175.49 | N123: 452.13 | O123: 102.14 | P123: 139.29 | Q123: 66.18 | R123: 53.12 | S123: 118.96 | T123: 39.16 | U123: 27.06 | V123: 344.41 | W123: 142.24 | X123: 45.31 | Y123: 53.99 | Z123: 319.88 | AA123: 90.99
A124: 46031 | B124: 333.95 | C124: 122.89 | D124: 1267.79 | E124: 343.08 | F124: 117.65 | G124: 139.48 | H124: 344.89 | I124: 184.43 | J124: 126.44 | K124: 177.49 | L124: 321.11 | M124: 163.47 | N124: 463.86 | O124: 106.31 | P124: 142.21 | Q124: 66.78 | R124: 54.1 | S124: 119.31 | T124: 40.17 | U124: 27.86 | V124: 347.68 | W124: 144.69 | X124: 44.4 | Y124: 54.87 | Z124: 320.72 | AA124: 89.46
A125: 46038 | B125: 296.12 | C125: 129.83 | D125: 1352.07 | E125: 349.78 | F125: 113.47 | G125: 156.2 | H125: 362.54 | I125: 185.8 | J125: 130.16 | K125: 170.96 | L125: 339.73 | M125: 176.81 | N125: 441.36 | O125: 107.48 | P125: 144.06 | Q125: 66.48 | R125: 53.88 | S125: 119.28 | T125: 39.35 | U125: 28.21 | V125: 326.34 | W125: 146.28 | X125: 45.69 | Y125: 55.02 | Z125: 324.24 | AA125: 88
A126: 46045 | B126: 301.07 | C126: 136.34 | D126: 1382.4 | E126: 318.3 | F126: 113.12 | G126: 150.72 | H126: 399.42 | I126: 187.23 | J126: 124.24 | K126: 169.6 | L126: 332.26 | M126: 182.36 | N126: 468.41 | O126: 107.46 | P126: 144.42 | Q126: 66.46 | R126: 54.16 | S126: 117.22 | T126: 39.6 | U126: 28.44 | V126: 324.23 | W126: 145.12 | X126: 46.75 | Y126: 54.99 | Z126: 293.08 | AA126: 86.12
A127: 46052 | B127: 293.25 | C127: 141.74 | D127: 1416.2 | E127: 329.48 | F127: 110.35 | G127: 142.27 | H127: 414.64 | I127: 190.68 | J127: 127.57 | K127: 146.59 | L127: 327.98 | M127: 186.05 | N127: 469.9 | O127: 108.24 | P127: 146.93 | Q127: 66.7 | R127: 54.35 | S127: 119.15 | T127: 39.21 | U127: 29.1 | V127: 319.91 | W127: 147.35 | X127: 47.61 | Y127: 55.16 | Z127: 305.96 | AA127: 83.49
A128: 46059 | B128: 268.38 | C128: 137.49 | D128: 1406.25 | E128: 331.1 | F128: 98.88 | G128: 143.76 | H128: 394.46 | I128: 184.98 | J128: 133.82 | K128: 135.9 | L128: 346.13 | M128: 195.44 | N128: 477.92 | O128: 114.1 | P128: 151.79 | Q128: 66.89 | R128: 53.51 | S128: 119.12 | T128: 40.17 | U128: 30.71 | V128: 329.6 | W128: 152.76 | X128: 48.53 | Y128: 56.01 | Z128: 320.13 | AA128: 82.2
A129: 46066 | B129: 263.97 | C129: 141.59 | D129: 1401.73 | E129: 323.39 | F129: 107.41 | G129: 145.87 | H129: 411.42 | I129: 182.38 | J129: 135.79 | K129: 131.41 | L129: 363.5 | M129: 234.37 | N129: 491.47 | O129: 113.81 | P129: 154.23 | Q129: 66.31 | R129: 53.01 | S129: 117.54 | T129: 40 | U129: 30.85 | V129: 312.85 | W129: 152.66 | X129: 50.42 | Y129: 56.19 | Z129: 314.56 | AA129: 76.87
A130: 46073 | B130: 258.61 | C130: 132.79 | D130: 1464.49 | E130: 330.83 | F130: 97.15 | G130: 149.24 | H130: 427.92 | I130: 189.38 | J130: 138.27 | K130: 135.24 | L130: 367.65 | M130: 243.58 | N130: 476.9 | O130: 114.45 | P130: 153.13 | Q130: 66.76 | R130: 53.6 | S130: 119.24 | T130: 40.08 | U130: 30.85 | V130: 319.69 | W130: 152.85 | X130: 50.57 | Y130: 56.37 | Z130: 342.29 | AA130: 78.67
A131: 46080 | B131: 262.41 | C131: 133.5 | D131: 1445.53 | E131: 317.8 | F131: 93 | G131: 152.09 | H131: 412.13 | I131: 176.78 | J131: 139.31 | K131: 137.19 | L131: 371.66 | M131: 254.71 | N131: 496.83 | O131: 111.91 | P131: 152.62 | Q131: 66.38 | R131: 53.5 | S131: 118.76 | T131: 40.22 | U131: 31.01 | V131: 318.89 | W131: 152.35 | X131: 51.08 | Y131: 56.73 | Z131: 341.34 | AA131: 96.24
A132: 46087 | B132: 283.62 | C132: 132.89 | D132: 1288.32 | E132: 328.67 | F132: 107.25 | G132: 134.13 | H132: 370.09 | I132: 177.4 | J132: 131.46 | K132: 157.16 | L132: 336.25 | M132: 241.61 | N132: 456.69 | O132: 107.62 | P132: 148.85 | Q132: 65.63 | R132: 52.86 | S132: 117.53 | T132: 39.85 | U132: 30.38 | V132: 316.12 | W132: 148.11 | X132: 51.59 | Y132: 55.36 | Z132: 322.24 | AA132: 99.02
... A162: 46297 | B162: 237.69 | C162: 207.35 | D162: 1867.31 | E162: 355.14 | F162: 270.04 | G162: 206.89 | H162: 1074.89 | I162: 233.95 | J162: 128.91 | K162: 188.75 | L162: 472.78 | M162: 252.18 | N162: 504.73 | O162: 120.03 | P162: 153.05 | Q162: 69.42 | R162: 61.04 | S162: 153.23 | T162: 51.82 | U162: 32.72 | V162: 360.66 | W162: 156.46 | X162: 51.17 | Y162: 56.1 | Z162: 309.56 | AA162: 67.06
A165: =COUNT(A3:A163) -> 160 | B165: Weeks

Sheet Dashboard
A1: Ticker | B1: Company | C1: Date Scored | D1: Tier 1 Wtd Avg | E1: Composite Score | F1: Decision | G1: Rule 1 | H1: Rule 2 | I1: Rule 3 | J1: Rule 4
A2: =IF(Scoring!A3="","",Scoring!A3) -> ADBE | B2: =IF(Scoring!B3="","",Scoring!B3) -> Adobe Inc. | C2: =IF(Scoring!C3="","",Scoring!C3) -> 46295 | D2: =IF(Scoring!N3="","",Scoring!N3) -> 4.5714286 | E2: =IF(Scoring!AF3="","",Scoring!AF3) -> 85.8 | F2: =IF(Scoring!AG3<>"",Scoring!AG3,IF(Scoring!AH3="OK","PENDING","")) -> STRONG BUY | G2: =IF(Scoring!AH3="","",Scoring!AH3) -> OK | H2: =IF(Scoring!AI3="","",Scoring!AI3) -> OK | I2: =IF(Scoring!AJ3="","",Scoring!AJ3) -> OK | J2: =IF(Scoring!AK3="","",Scoring!AK3) -> OK
A3: =IF(Scoring!A4="","",Scoring!A4) -> NVDA | B3: =IF(Scoring!B4="","",Scoring!B4) -> NVIDIA Corporation | C3: =IF(Scoring!C4="","",Scoring!C4) -> 46278 | D3: =IF(Scoring!N4="","",Scoring!N4) -> 4.2857143 | E3: =IF(Scoring!AF4="","",Scoring!AF4) -> 89.2 | F3: =IF(Scoring!AG4<>"",Scoring!AG4,IF(Scoring!AH4="OK","PENDING","")) -> STRONG BUY | G3: =IF(Scoring!AH4="","",Scoring!AH4) -> OK | H3: =IF(Scoring!AI4="","",Scoring!AI4) -> OK | I3: =IF(Scoring!AJ4="","",Scoring!AJ4) -> OK | J3: =IF(Scoring!AK4="","",Scoring!AK4) -> OK
A4: =IF(Scoring!A5="","",Scoring!A5) -> ANET | B4: =IF(Scoring!B5="","",Scoring!B5) -> Arista Networks | C4: =IF(Scoring!C5="","",Scoring!C5) -> 46278 | D4: =IF(Scoring!N5="","",Scoring!N5) -> 4.2857143 | E4: =IF(Scoring!AF5="","",Scoring!AF5) -> 81 | F4: =IF(Scoring!AG5<>"",Scoring!AG5,IF(Scoring!AH5="OK","PENDING","")) -> STRONG BUY | G4: =IF(Scoring!AH5="","",Scoring!AH5) -> OK | H4: =IF(Scoring!AI5="","",Scoring!AI5) -> OK | I4: =IF(Scoring!AJ5="","",Scoring!AJ5) -> OK | J4: =IF(Scoring!AK5="","",Scoring!AK5) -> OK
A5: =IF(Scoring!A6="","",Scoring!A6) -> VEEV | B5: =IF(Scoring!B6="","",Scoring!B6) -> Veeva Systems Inc. | C5: =IF(Scoring!C6="","",Scoring!C6) -> 46297 | D5: =IF(Scoring!N6="","",Scoring!N6) -> 4.2857143 | E5: =IF(Scoring!AF6="","",Scoring!AF6) -> 81.6 | F5: =IF(Scoring!AG6<>"",Scoring!AG6,IF(Scoring!AH6="OK","PENDING","")) -> STRONG BUY | G5: =IF(Scoring!AH6="","",Scoring!AH6) -> OK | H5: =IF(Scoring!AI6="","",Scoring!AI6) -> OK | I5: =IF(Scoring!AJ6="","",Scoring!AJ6) -> OK | J5: =IF(Scoring!AK6="","",Scoring!AK6) -> OK
A6: =IF(Scoring!A7="","",Scoring!A7) -> TSM | B6: =IF(Scoring!B7="","",Scoring!B7) -> Taiwan Semiconductor Mfg. | C6: =IF(Scoring!C7="","",Scoring!C7) -> 46278 | D6: =IF(Scoring!N7="","",Scoring!N7) -> 4.2142857 | E6: =IF(Scoring!AF7="","",Scoring!AF7) -> 84 | F6: =IF(Scoring!AG7<>"",Scoring!AG7,IF(Scoring!AH7="OK","PENDING","")) -> STRONG BUY | G6: =IF(Scoring!AH7="","",Scoring!AH7) -> OK | H6: =IF(Scoring!AI7="","",Scoring!AI7) -> OK | I6: =IF(Scoring!AJ7="","",Scoring!AJ7) -> OK | J6: =IF(Scoring!AK7="","",Scoring!AK7) -> OK
A7: =IF(Scoring!A8="","",Scoring!A8) -> NFLX | B7: =IF(Scoring!B8="","",Scoring!B8) -> Netflix, Inc. | C7: =IF(Scoring!C8="","",Scoring!C8) -> 46278 | D7: =IF(Scoring!N8="","",Scoring!N8) -> 4.2142857 | E7: =IF(Scoring!AF8="","",Scoring!AF8) -> 83.8 | F7: =IF(Scoring!AG8<>"",Scoring!AG8,IF(Scoring!AH8="OK","PENDING","")) -> STRONG BUY | G7: =IF(Scoring!AH8="","",Scoring!AH8) -> OK | H7: =IF(Scoring!AI8="","",Scoring!AI8) -> OK | I7: =IF(Scoring!AJ8="","",Scoring!AJ8) -> OK | J7: =IF(Scoring!AK8="","",Scoring!AK8) -> OK
A8: =IF(Scoring!A9="","",Scoring!A9) -> COST | B8: =IF(Scoring!B9="","",Scoring!B9) -> Costco Wholesale Corp. | C8: =IF(Scoring!C9="","",Scoring!C9) -> 46245 | D8: =IF(Scoring!N9="","",Scoring!N9) -> 4.1428571 | E8: =IF(Scoring!AF9="","",Scoring!AF9) -> 77.4 | F8: =IF(Scoring!AG9<>"",Scoring!AG9,IF(Scoring!AH9="OK","PENDING","")) -> BUY | G8: =IF(Scoring!AH9="","",Scoring!AH9) -> OK | H8: =IF(Scoring!AI9="","",Scoring!AI9) -> OK | I8: =IF(Scoring!AJ9="","",Scoring!AJ9) -> OK | J8: =IF(Scoring!AK9="","",Scoring!AK9) -> OK
A9: =IF(Scoring!A10="","",Scoring!A10) -> GE | B9: =IF(Scoring!B10="","",Scoring!B10) -> GE Aerospace | C9: =IF(Scoring!C10="","",Scoring!C10) -> 46278 | D9: =IF(Scoring!N10="","",Scoring!N10) -> 4.1428571 | E9: =IF(Scoring!AF10="","",Scoring!AF10) -> 84.2 | F9: =IF(Scoring!AG10<>"",Scoring!AG10,IF(Scoring!AH10="OK","PENDING","")) -> STRONG BUY | G9: =IF(Scoring!AH10="","",Scoring!AH10) -> OK | H9: =IF(Scoring!AI10="","",Scoring!AI10) -> OK | I9: =IF(Scoring!AJ10="","",Scoring!AJ10) -> OK | J9: =IF(Scoring!AK10="","",Scoring!AK10) -> OK
A10: =IF(Scoring!A11="","",Scoring!A11) -> PLTR | B10: =IF(Scoring!B11="","",Scoring!B11) -> Palantir Technologies | C10: =IF(Scoring!C11="","",Scoring!C11) -> 46278 | D10: =IF(Scoring!N11="","",Scoring!N11) -> 4.0714286 | E10: =IF(Scoring!AF11="","",Scoring!AF11) -> 76.2 | F10: =IF(Scoring!AG11<>"",Scoring!AG11,IF(Scoring!AH11="OK","PENDING","")) -> BUY | G10: =IF(Scoring!AH11="","",Scoring!AH11) -> OK | H10: =IF(Scoring!AI11="","",Scoring!AI11) -> OK | I10: =IF(Scoring!AJ11="","",Scoring!AJ11) -> OK | J10: =IF(Scoring!AK11="","",Scoring!AK11) -> OK
A11: =IF(Scoring!A12="","",Scoring!A12) -> PG | B11: =IF(Scoring!B12="","",Scoring!B12) -> Procter & Gamble Co. | C11: =IF(Scoring!C12="","",Scoring!C12) -> 46278 | D11: =IF(Scoring!N12="","",Scoring!N12) -> 4 | E11: =IF(Scoring!AF12="","",Scoring!AF12) | F11: =IF(Scoring!AG12<>"",Scoring!AG12,IF(Scoring!AH12="OK","PENDING","")) -> PENDING | G11: =IF(Scoring!AH12="","",Scoring!AH12) -> OK | H11: =IF(Scoring!AI12="","",Scoring!AI12) -> OK | I11: =IF(Scoring!AJ12="","",Scoring!AJ12) -> OK | J11: =IF(Scoring!AK12="","",Scoring!AK12) -> OK
A12: =IF(Scoring!A13="","",Scoring!A13) -> KGS | B12: =IF(Scoring!B13="","",Scoring!B13) -> Kodiak Gas Services, Inc. | C12: =IF(Scoring!C13="","",Scoring!C13) -> 46276 | D12: =IF(Scoring!N13="","",Scoring!N13) -> 4 | E12: =IF(Scoring!AF13="","",Scoring!AF13) | F12: =IF(Scoring!AG13<>"",Scoring!AG13,IF(Scoring!AH13="OK","PENDING","")) -> PENDING | G12: =IF(Scoring!AH13="","",Scoring!AH13) -> OK | H12: =IF(Scoring!AI13="","",Scoring!AI13) -> OK | I12: =IF(Scoring!AJ13="","",Scoring!AJ13) -> OK | J12: =IF(Scoring!AK13="","",Scoring!AK13) -> OK
A13: =IF(Scoring!A14="","",Scoring!A14) -> PLD | B13: =IF(Scoring!B14="","",Scoring!B14) -> Prologis Inc. (REIT-adapted) | C13: =IF(Scoring!C14="","",Scoring!C14) -> 46295 | D13: =IF(Scoring!N14="","",Scoring!N14) -> 3.9285714 | E13: =IF(Scoring!AF14="","",Scoring!AF14) -> 76 | F13: =IF(Scoring!AG14<>"",Scoring!AG14,IF(Scoring!AH14="OK","PENDING","")) -> BUY | G13: =IF(Scoring!AH14="","",Scoring!AH14) -> OK | H13: =IF(Scoring!AI14="","",Scoring!AI14) -> OK | I13: =IF(Scoring!AJ14="","",Scoring!AJ14) -> OK | J13: =IF(Scoring!AK14="","",Scoring!AK14) -> OK
... A50: =IF(Scoring!A51="","",Scoring!A51) -> CRK | B50: =IF(Scoring!B51="","",Scoring!B51) -> Comstock Resources Inc. | C50: =IF(Scoring!C51="","",Scoring!C51) -> 46245 | D50: =IF(Scoring!N51="","",Scoring!N51) -> 1.2142857 | E50: =IF(Scoring!AF51="","",Scoring!AF51) | F50: =IF(Scoring!AG51<>"",Scoring!AG51,IF(Scoring!AH51="OK","PENDING","")) | G50: =IF(Scoring!AH51="","",Scoring!AH51) -> FAIL | H50: =IF(Scoring!AI51="","",Scoring!AI51) -> REVIEW | I50: =IF(Scoring!AJ51="","",Scoring!AJ51) -> AVOID | J50: =IF(Scoring!AK51="","",Scoring!AK51) -> OK
A51: This tab mirrors the Scoring tab automatically — do not type here. You can sort this tab directly (Data > Sort by Composite Score); Excel moves whole rows, so each row's links stay correct.
A52: =SUBTOTAL(103,A2:A50) -> 30 | B52: Tickers

Sheet Scoring
D1: TIER 1 — 70% of Decision | P1: TIER 2 — 25% of Decision | Y1: TIER 3 — 5% of Decision | AH1: RULE FLAGS (1–4) | AL1: CLASSIFICATION | AN1: PIOTROSKI-DERIVED CROSS-CHECKS (confidence-tagging inputs only — do not feed Composite Score)
A2: Ticker | B2: Company | C2: Date Scored | D2: FCF Yield & Trend (20%) Score | E2: Conf (H/M/L) | F2: Rev Growth Consist. (15%) Score | G2: Conf (H/M/L) | H2: Moat Quality (15%) Score | I2: Conf (H/M/L) | J2: Rev Visibility (10%) Score | K2: Conf (H/M/L) | L2: FCF Margin Trend (10%) Score | M2: Confidence (H/M/L) | N2: Tier 1 Wtd Avg (÷0.70) | O2: Tier 1 Contrib. | P2: Mgmt Quality & Cap Alloc (8%) Score | Q2: Conf (H/M/L) | R2: ROIC vs WACC (6%) Score | S2: Conf (H/M/L) | T2: Rel Strength vs SPY (3%) Score | U2: Conf (H/M/L) | V2: Valuation Multiples (8%) Score | W2: Conf (H/M/L) | X2: Tier 2 Contrib. | Y2: Technical Trend (2%) Score | Z2: Conf (H/M/L) | AA2: Analyst Consensus (2%) Score | AB2: Conf (H/M/L) | AC2: Volume & Accum. (1%) Score | AD2: Conf (H/M/L) | AE2: Tier 3 Contrib. | AF2: Composite Score | AG2: Decision | AH2: Rule 1 Tier1<3.0 | AI2: Rule 2 Any=1 | AJ2: Rule 3 2+≤2= Avoid | AK2: Rule 4 2+Low= Cap Buy | AL2: Sector | AM2: Industry | AN2: CFO ($) | AO2: Net Income ($) | AP2: Accruals Check | AQ2: Debt/FCF (current) | AR2: Debt/FCF (prior yr) | AS2: Leverage Trajectory
A3: ADBE | B3: Adobe Inc. | C3: 46295 | D3: 5 | E3: M | F3: 4 | G3: M | H3: 4 | I3: M | J3: 5 | K3: H | L3: 5 | M3: M | N3: =IF(COUNT(D3,F3,H3,J3,L3)=0,"",(D3*0.2+F3*0.15+H3*0.15+J3*0.1+L3*0.1)/(IF(D3<>"",0.2,0)+IF(F3<>"",0.15,0)+IF(H3<>"",0.15,0)+IF(J3<>"",0.1,0)+IF(L3<>"",0.1,0))) -> 4.5714286 | O3: =IF(COUNT(D3,F3,H3,J3,L3)=0,"",D3*0.2+F3*0.15+H3*0.15+J3*0.1+L3*0.1) -> 3.2 | P3: 3 | Q3: M | R3: 5 | S3: H | T3: 1 | U3: H | V3: 5 | W3: H | X3: =IF(COUNT(P3,R3,T3,V3)=0,"",P3*0.08+R3*0.06+T3*0.03+V3*0.08) -> 0.97 | Y3: 2 | Z3: M | AA3: 3 | AB3: M | AC3: 2 | AD3: L | AE3: =IF(COUNT(Y3,AA3,AC3)=0,"",Y3*0.02+AA3*0.02+AC3*0.01) -> 0.12 | AF3: =IF(OR(COUNT(D3,F3,H3,J3,L3)<5,COUNT(P3,R3,T3,V3)<4,COUNT(Y3,AA3,AC3)<3),"",(O3+X3+AE3)*20) -> 85.8 | AG3: =IF(AF3="","",IF(AJ3="AVOID","AVOID",IF(AF3>=80,IF(AH3="FAIL","WATCH LIST",IF(AK3="CAP AT BUY","BUY","STRONG BUY")),IF(AF3>=65,IF(AH3="FAIL","WATCH LIST","BUY"),IF(AF3>=50,"WATCH LIST",IF(AF3>=35,"AVOID","PASS")))))) -> STRONG BUY | AH3: =IF(N3="","",IF(N3<3,"FAIL","OK")) -> OK | AI3: =IF(COUNT(D3:L3)=0,"",IF(COUNTIF(D3:L3,1)>0,"REVIEW","OK")) -> OK | AJ3: =IF(COUNT(D3:L3)=0,"",IF(COUNTIF(D3:L3,"<=2")>=2,"AVOID","OK")) -> OK | AK3: =IF(COUNTA(E3:M3)=0,"",IF(COUNTIF(E3:M3,"L")>=2,"CAP AT BUY","OK")) -> OK | AL3: Technology | AM3: Software - Application | AP3: =IF(OR(AN3="",AO3=""),"",IF(AN3>AO3,"OK","LOW CONF")) | AS3: =IF(OR(AQ3="",AR3=""),"",IF(AQ3<AR3,"Decreased",IF(AQ3>AR3,"Increased","Flat")))
A4: NVDA | B4: NVIDIA Corporation | C4: 46278 | D4: 3 | E4: M | F4: 5 | G4: M | H4: 5 | I4: H | J4: 4 | K4: H | L4: 5 | M4: M | N4: =IF(COUNT(D4,F4,H4,J4,L4)=0,"",(D4*0.2+F4*0.15+H4*0.15+J4*0.1+L4*0.1)/(IF(D4<>"",0.2,0)+IF(F4<>"",0.15,0)+IF(H4<>"",0.15,0)+IF(J4<>"",0.1,0)+IF(L4<>"",0.1,0))) -> 4.2857143 | O4: =IF(COUNT(D4,F4,H4,J4,L4)=0,"",D4*0.2+F4*0.15+H4*0.15+J4*0.1+L4*0.1) -> 3 | P4: 5 | Q4: H | R4: 5 | S4: H | T4: 5 | U4: H | V4: 5 | W4: M | X4: =IF(COUNT(P4,R4,T4,V4)=0,"",P4*0.08+R4*0.06+T4*0.03+V4*0.08) -> 1.25 | Y4: 4 | Z4: M | AA4: 5 | AB4: M | AC4: 3 | AD4: L | AE4: =IF(COUNT(Y4,AA4,AC4)=0,"",Y4*0.02+AA4*0.02+AC4*0.01) -> 0.21 | AF4: =IF(OR(COUNT(D4,F4,H4,J4,L4)<5,COUNT(P4,R4,T4,V4)<4,COUNT(Y4,AA4,AC4)<3),"",(O4+X4+AE4)*20) -> 89.2 | AG4: =IF(AF4="","",IF(AJ4="AVOID","AVOID",IF(AF4>=80,IF(AH4="FAIL","WATCH LIST",IF(AK4="CAP AT BUY","BUY","STRONG BUY")),IF(AF4>=65,IF(AH4="FAIL","WATCH LIST","BUY"),IF(AF4>=50,"WATCH LIST",IF(AF4>=35,"AVOID","PASS")))))) -> STRONG BUY | AH4: =IF(N4="","",IF(N4<3,"FAIL","OK")) -> OK | AI4: =IF(COUNT(D4:L4)=0,"",IF(COUNTIF(D4:L4,1)>0,"REVIEW","OK")) -> OK | AJ4: =IF(COUNT(D4:L4)=0,"",IF(COUNTIF(D4:L4,"<=2")>=2,"AVOID","OK")) -> OK | AK4: =IF(COUNTA(E4:M4)=0,"",IF(COUNTIF(E4:M4,"L")>=2,"CAP AT BUY","OK")) -> OK | AL4: Technology | AM4: Semiconductors | AP4: =IF(OR(AN4="",AO4=""),"",IF(AN4>AO4,"OK","LOW CONF")) | AS4: =IF(OR(AQ4="",AR4=""),"",IF(AQ4<AR4,"Decreased",IF(AQ4>AR4,"Increased","Flat")))
A5: ANET | B5: Arista Networks | C5: 46278 | D5: 3 | E5: M | F5: 5 | G5: M | H5: 5 | I5: H | J5: 4 | K5: M | L5: 5 | M5: M | N5: =IF(COUNT(D5,F5,H5,J5,L5)=0,"",(D5*0.2+F5*0.15+H5*0.15+J5*0.1+L5*0.1)/(IF(D5<>"",0.2,0)+IF(F5<>"",0.15,0)+IF(H5<>"",0.15,0)+IF(J5<>"",0.1,0)+IF(L5<>"",0.1,0))) -> 4.2857143 | O5: =IF(COUNT(D5,F5,H5,J5,L5)=0,"",D5*0.2+F5*0.15+H5*0.15+J5*0.1+L5*0.1) -> 3 | P5: 4 | Q5: H | R5: 5 | S5: H | T5: 5 | U5: M | V5: 1 | W5: H | X5: =IF(COUNT(P5,R5,T5,V5)=0,"",P5*0.08+R5*0.06+T5*0.03+V5*0.08) -> 0.85 | Y5: 4 | Z5: M | AA5: 5 | AB5: H | AC5: 2 | AD5: M | AE5: =IF(COUNT(Y5,AA5,AC5)=0,"",Y5*0.02+AA5*0.02+AC5*0.01) -> 0.2 | AF5: =IF(OR(COUNT(D5,F5,H5,J5,L5)<5,COUNT(P5,R5,T5,V5)<4,COUNT(Y5,AA5,AC5)<3),"",(O5+X5+AE5)*20) -> 81 | AG5: =IF(AF5="","",IF(AJ5="AVOID","AVOID",IF(AF5>=80,IF(AH5="FAIL","WATCH LIST",IF(AK5="CAP AT BUY","BUY","STRONG BUY")),IF(AF5>=65,IF(AH5="FAIL","WATCH LIST","BUY"),IF(AF5>=50,"WATCH LIST",IF(AF5>=35,"AVOID","PASS")))))) -> STRONG BUY | AH5: =IF(N5="","",IF(N5<3,"FAIL","OK")) -> OK | AI5: =IF(COUNT(D5:L5)=0,"",IF(COUNTIF(D5:L5,1)>0,"REVIEW","OK")) -> OK | AJ5: =IF(COUNT(D5:L5)=0,"",IF(COUNTIF(D5:L5,"<=2")>=2,"AVOID","OK")) -> OK | AK5: =IF(COUNTA(E5:M5)=0,"",IF(COUNTIF(E5:M5,"L")>=2,"CAP AT BUY","OK")) -> OK | AL5: Technology | AM5: Computer Hardware | AP5: =IF(OR(AN5="",AO5=""),"",IF(AN5>AO5,"OK","LOW CONF")) | AS5: =IF(OR(AQ5="",AR5=""),"",IF(AQ5<AR5,"Decreased",IF(AQ5>AR5,"Increased","Flat")))
A6: VEEV | B6: Veeva Systems Inc. | C6: 46297 | D6: 4 | E6: M | F6: 4 | G6: M | H6: 4 | I6: M | J6: 5 | K6: M | L6: 5 | M6: M | N6: =IF(COUNT(D6,F6,H6,J6,L6)=0,"",(D6*0.2+F6*0.15+H6*0.15+J6*0.1+L6*0.1)/(IF(D6<>"",0.2,0)+IF(F6<>"",0.15,0)+IF(H6<>"",0.15,0)+IF(J6<>"",0.1,0)+IF(L6<>"",0.1,0))) -> 4.2857143 | O6: =IF(COUNT(D6,F6,H6,J6,L6)=0,"",D6*0.2+F6*0.15+H6*0.15+J6*0.1+L6*0.1) -> 3 | P6: 4 | Q6: M | R6: 2 | S6: L | T6: 4 | U6: M | V6: 4 | W6: M | X6: =IF(COUNT(P6,R6,T6,V6)=0,"",P6*0.08+R6*0.06+T6*0.03+V6*0.08) -> 0.88 | Y6: 5 | Z6: M | AA6: 4 | AB6: M | AC6: 2 | AD6: M | AE6: =IF(COUNT(Y6,AA6,AC6)=0,"",Y6*0.02+AA6*0.02+AC6*0.01) -> 0.2 | AF6: =IF(OR(COUNT(D6,F6,H6,J6,L6)<5,COUNT(P6,R6,T6,V6)<4,COUNT(Y6,AA6,AC6)<3),"",(O6+X6+AE6)*20) -> 81.6 | AG6: =IF(AF6="","",IF(AJ6="AVOID","AVOID",IF(AF6>=80,IF(AH6="FAIL","WATCH LIST",IF(AK6="CAP AT BUY","BUY","STRONG BUY")),IF(AF6>=65,IF(AH6="FAIL","WATCH LIST","BUY"),IF(AF6>=50,"WATCH LIST",IF(AF6>=35,"AVOID","PASS")))))) -> STRONG BUY | AH6: =IF(N6="","",IF(N6<3,"FAIL","OK")) -> OK | AI6: =IF(COUNT(D6:L6)=0,"",IF(COUNTIF(D6:L6,1)>0,"REVIEW","OK")) -> OK | AJ6: =IF(COUNT(D6:L6)=0,"",IF(COUNTIF(D6:L6,"<=2")>=2,"AVOID","OK")) -> OK | AK6: =IF(COUNTA(E6:M6)=0,"",IF(COUNTIF(E6:M6,"L")>=2,"CAP AT BUY","OK")) -> OK | AL6: Healthcare | AM6: Health Information Services | AP6: =IF(OR(AN6="",AO6=""),"",IF(AN6>AO6,"OK","LOW CONF")) | AS6: =IF(OR(AQ6="",AR6=""),"",IF(AQ6<AR6,"Decreased",IF(AQ6>AR6,"Increased","Flat")))
A7: TSM | B7: Taiwan Semiconductor Mfg. | C7: 46278 | D7: 5 | E7: M | F7: 2 | G7: M | H7: 5 | I7: H | J7: 4 | K7: M | L7: 5 | M7: M | N7: =IF(COUNT(D7,F7,H7,J7,L7)=0,"",(D7*0.2+F7*0.15+H7*0.15+J7*0.1+L7*0.1)/(IF(D7<>"",0.2,0)+IF(F7<>"",0.15,0)+IF(H7<>"",0.15,0)+IF(J7<>"",0.1,0)+IF(L7<>"",0.1,0))) -> 4.2142857 | O7: =IF(COUNT(D7,F7,H7,J7,L7)=0,"",D7*0.2+F7*0.15+H7*0.15+J7*0.1+L7*0.1) -> 2.95 | P7: 4 | Q7: H | R7: 5 | S7: H | T7: 4 | U7: M | V7: 4 | W7: M | X7: =IF(COUNT(P7,R7,T7,V7)=0,"",P7*0.08+R7*0.06+T7*0.03+V7*0.08) -> 1.06 | Y7: 3 | Z7: M | AA7: 5 | AB7: H | AC7: 3 | AD7: L | AE7: =IF(COUNT(Y7,AA7,AC7)=0,"",Y7*0.02+AA7*0.02+AC7*0.01) -> 0.19 | AF7: =IF(OR(COUNT(D7,F7,H7,J7,L7)<5,COUNT(P7,R7,T7,V7)<4,COUNT(Y7,AA7,AC7)<3),"",(O7+X7+AE7)*20) -> 84 | AG7: =IF(AF7="","",IF(AJ7="AVOID","AVOID",IF(AF7>=80,IF(AH7="FAIL","WATCH LIST",IF(AK7="CAP AT BUY","BUY","STRONG BUY")),IF(AF7>=65,IF(AH7="FAIL","WATCH LIST","BUY"),IF(AF7>=50,"WATCH LIST",IF(AF7>=35,"AVOID","PASS")))))) -> STRONG BUY | AH7: =IF(N7="","",IF(N7<3,"FAIL","OK")) -> OK | AI7: =IF(COUNT(D7:L7)=0,"",IF(COUNTIF(D7:L7,1)>0,"REVIEW","OK")) -> OK | AJ7: =IF(COUNT(D7:L7)=0,"",IF(COUNTIF(D7:L7,"<=2")>=2,"AVOID","OK")) -> OK | AK7: =IF(COUNTA(E7:M7)=0,"",IF(COUNTIF(E7:M7,"L")>=2,"CAP AT BUY","OK")) -> OK | AL7: Technology | AM7: Semiconductors | AP7: =IF(OR(AN7="",AO7=""),"",IF(AN7>AO7,"OK","LOW CONF")) | AS7: =IF(OR(AQ7="",AR7=""),"",IF(AQ7<AR7,"Decreased",IF(AQ7>AR7,"Increased","Flat")))
A8: NFLX | B8: Netflix, Inc. | C8: 46278 | D8: 4 | E8: M | F8: 4 | G8: M | H8: 5 | I8: M | J8: 4 | K8: M | L8: 4 | M8: M | N8: =IF(COUNT(D8,F8,H8,J8,L8)=0,"",(D8*0.2+F8*0.15+H8*0.15+J8*0.1+L8*0.1)/(IF(D8<>"",0.2,0)+IF(F8<>"",0.15,0)+IF(H8<>"",0.15,0)+IF(J8<>"",0.1,0)+IF(L8<>"",0.1,0))) -> 4.2142857 | O8: =IF(COUNT(D8,F8,H8,J8,L8)=0,"",D8*0.2+F8*0.15+H8*0.15+J8*0.1+L8*0.1) -> 2.95 | P8: 5 | Q8: H | R8: 5 | S8: L | T8: 1 | U8: M | V8: 4 | W8: M | X8: =IF(COUNT(P8,R8,T8,V8)=0,"",P8*0.08+R8*0.06+T8*0.03+V8*0.08) -> 1.05 | Y8: 4 | Z8: M | AA8: 4 | AB8: M | AC8: 3 | AD8: M | AE8: =IF(COUNT(Y8,AA8,AC8)=0,"",Y8*0.02+AA8*0.02+AC8*0.01) -> 0.19 | AF8: =IF(OR(COUNT(D8,F8,H8,J8,L8)<5,COUNT(P8,R8,T8,V8)<4,COUNT(Y8,AA8,AC8)<3),"",(O8+X8+AE8)*20) -> 83.8 | AG8: =IF(AF8="","",IF(AJ8="AVOID","AVOID",IF(AF8>=80,IF(AH8="FAIL","WATCH LIST",IF(AK8="CAP AT BUY","BUY","STRONG BUY")),IF(AF8>=65,IF(AH8="FAIL","WATCH LIST","BUY"),IF(AF8>=50,"WATCH LIST",IF(AF8>=35,"AVOID","PASS")))))) -> STRONG BUY | AH8: =IF(N8="","",IF(N8<3,"FAIL","OK")) -> OK | AI8: =IF(COUNT(D8:L8)=0,"",IF(COUNTIF(D8:L8,1)>0,"REVIEW","OK")) -> OK | AJ8: =IF(COUNT(D8:L8)=0,"",IF(COUNTIF(D8:L8,"<=2")>=2,"AVOID","OK")) -> OK | AK8: =IF(COUNTA(E8:M8)=0,"",IF(COUNTIF(E8:M8,"L")>=2,"CAP AT BUY","OK")) -> OK | AL8: Communication Services | AM8: Entertainment | AP8: =IF(OR(AN8="",AO8=""),"",IF(AN8>AO8,"OK","LOW CONF")) | AS8: =IF(OR(AQ8="",AR8=""),"",IF(AQ8<AR8,"Decreased",IF(AQ8>AR8,"Increased","Flat")))
A9: COST | B9: Costco Wholesale Corp. | C9: 46245 | D9: 3 | E9: M | F9: 5 | G9: H | H9: 5 | I9: H | J9: 4 | K9: M | L9: 4 | M9: H | N9: =IF(COUNT(D9,F9,H9,J9,L9)=0,"",(D9*0.2+F9*0.15+H9*0.15+J9*0.1+L9*0.1)/(IF(D9<>"",0.2,0)+IF(F9<>"",0.15,0)+IF(H9<>"",0.15,0)+IF(J9<>"",0.1,0)+IF(L9<>"",0.1,0))) -> 4.1428571 | O9: =IF(COUNT(D9,F9,H9,J9,L9)=0,"",D9*0.2+F9*0.15+H9*0.15+J9*0.1+L9*0.1) -> 2.9 | P9: 3 | Q9: L | R9: 5 | S9: H | T9: 5 | U9: H | V9: 1 | W9: H | X9: =IF(COUNT(P9,R9,T9,V9)=0,"",P9*0.08+R9*0.06+T9*0.03+V9*0.08) -> 0.77 | Y9: 4 | Z9: M | AA9: 4 | AB9: M | AC9: 4 | AD9: M | AE9: =IF(COUNT(Y9,AA9,AC9)=0,"",Y9*0.02+AA9*0.02+AC9*0.01) -> 0.2 | AF9: =IF(OR(COUNT(D9,F9,H9,J9,L9)<5,COUNT(P9,R9,T9,V9)<4,COUNT(Y9,AA9,AC9)<3),"",(O9+X9+AE9)*20) -> 77.4 | AG9: =IF(AF9="","",IF(AJ9="AVOID","AVOID",IF(AF9>=80,IF(AH9="FAIL","WATCH LIST",IF(AK9="CAP AT BUY","BUY","STRONG BUY")),IF(AF9>=65,IF(AH9="FAIL","WATCH LIST","BUY"),IF(AF9>=50,"WATCH LIST",IF(AF9>=35,"AVOID","PASS")))))) -> BUY | AH9: =IF(N9="","",IF(N9<3,"FAIL","OK")) -> OK | AI9: =IF(COUNT(D9:L9)=0,"",IF(COUNTIF(D9:L9,1)>0,"REVIEW","OK")) -> OK | AJ9: =IF(COUNT(D9:L9)=0,"",IF(COUNTIF(D9:L9,"<=2")>=2,"AVOID","OK")) -> OK | AK9: =IF(COUNTA(E9:M9)=0,"",IF(COUNTIF(E9:M9,"L")>=2,"CAP AT BUY","OK")) -> OK | AL9: Consumer Defensive | AM9: Discount Stores | AP9: =IF(OR(AN9="",AO9=""),"",IF(AN9>AO9,"OK","LOW CONF")) | AS9: =IF(OR(AQ9="",AR9=""),"",IF(AQ9<AR9,"Decreased",IF(AQ9>AR9,"Increased","Flat")))
A10: GE | B10: GE Aerospace | C10: 46278 | D10: 4 | E10: M | F10: 5 | G10: M | H10: 5 | I10: M | J10: 4 | K10: M | L10: 2 | M10: M | N10: =IF(COUNT(D10,F10,H10,J10,L10)=0,"",(D10*0.2+F10*0.15+H10*0.15+J10*0.1+L10*0.1)/(IF(D10<>"",0.2,0)+IF(F10<>"",0.15,0)+IF(H10<>"",0.15,0)+IF(J10<>"",0.1,0)+IF(L10<>"",0.1,0))) -> 4.1428571 | O10: =IF(COUNT(D10,F10,H10,J10,L10)=0,"",D10*0.2+F10*0.15+H10*0.15+J10*0.1+L10*0.1) -> 2.9 | P10: 5 | Q10: H | R10: 5 | S10: L | T10: 3 | U10: M | V10: 4 | W10: M | X10: =IF(COUNT(P10,R10,T10,V10)=0,"",P10*0.08+R10*0.06+T10*0.03+V10*0.08) -> 1.11 | Y10: 5 | Z10: M | AA10: 4 | AB10: M | AC10: 2 | AD10: M | AE10: =IF(COUNT(Y10,AA10,AC10)=0,"",Y10*0.02+AA10*0.02+AC10*0.01) -> 0.2 | AF10: =IF(OR(COUNT(D10,F10,H10,J10,L10)<5,COUNT(P10,R10,T10,V10)<4,COUNT(Y10,AA10,AC10)<3),"",(O10+X10+AE10)*20) -> 84.2 | AG10: =IF(AF10="","",IF(AJ10="AVOID","AVOID",IF(AF10>=80,IF(AH10="FAIL","WATCH LIST",IF(AK10="CAP AT BUY","BUY","STRONG BUY")),IF(AF10>=65,IF(AH10="FAIL","WATCH LIST","BUY"),IF(AF10>=50,"WATCH LIST",IF(AF10>=35,"AVOID","PASS")))))) -> STRONG BUY | AH10: =IF(N10="","",IF(N10<3,"FAIL","OK")) -> OK | AI10: =IF(COUNT(D10:L10)=0,"",IF(COUNTIF(D10:L10,1)>0,"REVIEW","OK")) -> OK | AJ10: =IF(COUNT(D10:L10)=0,"",IF(COUNTIF(D10:L10,"<=2")>=2,"AVOID","OK")) -> OK | AK10: =IF(COUNTA(E10:M10)=0,"",IF(COUNTIF(E10:M10,"L")>=2,"CAP AT BUY","OK")) -> OK | AL10: Industrials | AM10: Aerospace & Defense | AP10: =IF(OR(AN10="",AO10=""),"",IF(AN10>AO10,"OK","LOW CONF")) | AS10: =IF(OR(AQ10="",AR10=""),"",IF(AQ10<AR10,"Decreased",IF(AQ10>AR10,"Increased","Flat")))
A11: PLTR | B11: Palantir Technologies | C11: 46278 | D11: 3 | E11: M | F11: 4 | G11: M | H11: 5 | I11: M | J11: 4 | K11: M | L11: 5 | M11: M | N11: =IF(COUNT(D11,F11,H11,J11,L11)=0,"",(D11*0.2+F11*0.15+H11*0.15+J11*0.1+L11*0.1)/(IF(D11<>"",0.2,0)+IF(F11<>"",0.15,0)+IF(H11<>"",0.15,0)+IF(J11<>"",0.1,0)+IF(L11<>"",0.1,0))) -> 4.0714286 | O11: =IF(COUNT(D11,F11,H11,J11,L11)=0,"",D11*0.2+F11*0.15+H11*0.15+J11*0.1+L11*0.1) -> 2.85 | P11: 3 | Q11: M | R11: 5 | S11: H | T11: 3 | U11: M | V11: 2 | W11: M | X11: =IF(COUNT(P11,R11,T11,V11)=0,"",P11*0.08+R11*0.06+T11*0.03+V11*0.08) -> 0.79 | Y11: 3 | Z11: L | AA11: 4 | AB11: M | AC11: 3 | AD11: L | AE11: =IF(COUNT(Y11,AA11,AC11)=0,"",Y11*0.02+AA11*0.02+AC11*0.01) -> 0.17 | AF11: =IF(OR(COUNT(D11,F11,H11,J11,L11)<5,COUNT(P11,R11,T11,V11)<4,COUNT(Y11,AA11,AC11)<3),"",(O11+X11+AE11)*20) -> 76.2 | AG11: =IF(AF11="","",IF(AJ11="AVOID","AVOID",IF(AF11>=80,IF(AH11="FAIL","WATCH LIST",IF(AK11="CAP AT BUY","BUY","STRONG BUY")),IF(AF11>=65,IF(AH11="FAIL","WATCH LIST","BUY"),IF(AF11>=50,"WATCH LIST",IF(AF11>=35,"AVOID","PASS")))))) -> BUY | AH11: =IF(N11="","",IF(N11<3,"FAIL","OK")) -> OK | AI11: =IF(COUNT(D11:L11)=0,"",IF(COUNTIF(D11:L11,1)>0,"REVIEW","OK")) -> OK | AJ11: =IF(COUNT(D11:L11)=0,"",IF(COUNTIF(D11:L11,"<=2")>=2,"AVOID","OK")) -> OK | AK11: =IF(COUNTA(E11:M11)=0,"",IF(COUNTIF(E11:M11,"L")>=2,"CAP AT BUY","OK")) -> OK | AL11: Technology | AM11: Software - Infrastructure | AP11: =IF(OR(AN11="",AO11=""),"",IF(AN11>AO11,"OK","LOW CONF")) | AS11: =IF(OR(AQ11="",AR11=""),"",IF(AQ11<AR11,"Decreased",IF(AQ11>AR11,"Increased","Flat")))
A12: PG | B12: Procter & Gamble Co. | C12: 46278 | D12: 4 | E12: M | F12: 3 | G12: M | H12: 5 | I12: H | J12: 4 | K12: M | L12: 4 | M12: M | N12: =IF(COUNT(D12,F12,H12,J12,L12)=0,"",(D12*0.2+F12*0.15+H12*0.15+J12*0.1+L12*0.1)/(IF(D12<>"",0.2,0)+IF(F12<>"",0.15,0)+IF(H12<>"",0.15,0)+IF(J12<>"",0.1,0)+IF(L12<>"",0.1,0))) -> 4 | O12: =IF(COUNT(D12,F12,H12,J12,L12)=0,"",D12*0.2+F12*0.15+H12*0.15+J12*0.1+L12*0.1) -> 2.8 | X12: =IF(COUNT(P12,R12,T12,V12)=0,"",P12*0.08+R12*0.06+T12*0.03+V12*0.08) | AE12: =IF(COUNT(Y12,AA12,AC12)=0,"",Y12*0.02+AA12*0.02+AC12*0.01) | AF12: =IF(OR(COUNT(D12,F12,H12,J12,L12)<5,COUNT(P12,R12,T12,V12)<4,COUNT(Y12,AA12,AC12)<3),"",(O12+X12+AE12)*20) | AG12: =IF(AF12="","",IF(AJ12="AVOID","AVOID",IF(AF12>=80,IF(AH12="FAIL","WATCH LIST",IF(AK12="CAP AT BUY","BUY","STRONG BUY")),IF(AF12>=65,IF(AH12="FAIL","WATCH LIST","BUY"),IF(AF12>=50,"WATCH LIST",IF(AF12>=35,"AVOID","PASS")))))) | AH12: =IF(N12="","",IF(N12<3,"FAIL","OK")) -> OK | AI12: =IF(COUNT(D12:L12)=0,"",IF(COUNTIF(D12:L12,1)>0,"REVIEW","OK")) -> OK | AJ12: =IF(COUNT(D12:L12)=0,"",IF(COUNTIF(D12:L12,"<=2")>=2,"AVOID","OK")) -> OK | AK12: =IF(COUNTA(E12:M12)=0,"",IF(COUNTIF(E12:M12,"L")>=2,"CAP AT BUY","OK")) -> OK | AL12: Consumer Defensive | AM12: Household & Personal Products | AP12: =IF(OR(AN12="",AO12=""),"",IF(AN12>AO12,"OK","LOW CONF")) | AS12: =IF(OR(AQ12="",AR12=""),"",IF(AQ12<AR12,"Decreased",IF(AQ12>AR12,"Increased","Flat")))
A13: KGS | B13: Kodiak Gas Services, Inc. | C13: 46276 | D13: 4 | E13: M | F13: 4 | G13: M | L13: 4 | M13: M | N13: =IF(COUNT(D13,F13,H13,J13,L13)=0,"",(D13*0.2+F13*0.15+H13*0.15+J13*0.1+L13*0.1)/(IF(D13<>"",0.2,0)+IF(F13<>"",0.15,0)+IF(H13<>"",0.15,0)+IF(J13<>"",0.1,0)+IF(L13<>"",0.1,0))) -> 4 | O13: =IF(COUNT(D13,F13,H13,J13,L13)=0,"",D13*0.2+F13*0.15+H13*0.15+J13*0.1+L13*0.1) -> 1.8 | X13: =IF(COUNT(P13,R13,T13,V13)=0,"",P13*0.08+R13*0.06+T13*0.03+V13*0.08) | AE13: =IF(COUNT(Y13,AA13,AC13)=0,"",Y13*0.02+AA13*0.02+AC13*0.01) | AF13: =IF(OR(COUNT(D13,F13,H13,J13,L13)<5,COUNT(P13,R13,T13,V13)<4,COUNT(Y13,AA13,AC13)<3),"",(O13+X13+AE13)*20) | AG13: =IF(AF13="","",IF(AJ13="AVOID","AVOID",IF(AF13>=80,IF(AH13="FAIL","WATCH LIST",IF(AK13="CAP AT BUY","BUY","STRONG BUY")),IF(AF13>=65,IF(AH13="FAIL","WATCH LIST","BUY"),IF(AF13>=50,"WATCH LIST",IF(AF13>=35,"AVOID","PASS")))))) | AH13: =IF(N13="","",IF(N13<3,"FAIL","OK")) -> OK | AI13: =IF(COUNT(D13:L13)=0,"",IF(COUNTIF(D13:L13,1)>0,"REVIEW","OK")) -> OK | AJ13: =IF(COUNT(D13:L13)=0,"",IF(COUNTIF(D13:L13,"<=2")>=2,"AVOID","OK")) -> OK | AK13: =IF(COUNTA(E13:M13)=0,"",IF(COUNTIF(E13:M13,"L")>=2,"CAP AT BUY","OK")) -> OK | AL13: Energy | AM13: Oil & Gas Equipment & Services | AP13: =IF(OR(AN13="",AO13=""),"",IF(AN13>AO13,"OK","LOW CONF")) | AS13: =IF(OR(AQ13="",AR13=""),"",IF(AQ13<AR13,"Decreased",IF(AQ13>AR13,"Increased","Flat")))
A14: PLD | B14: Prologis Inc. (REIT-adapted) | C14: 46295 | D14: 4 | E14: M | F14: 2 | G14: L | H14: 5 | I14: H | J14: 4 | K14: M | L14: 5 | M14: H | N14: =IF(COUNT(D14,F14,H14,J14,L14)=0,"",(D14*0.2+F14*0.15+H14*0.15+J14*0.1+L14*0.1)/(IF(D14<>"",0.2,0)+IF(F14<>"",0.15,0)+IF(H14<>"",0.15,0)+IF(J14<>"",0.1,0)+IF(L14<>"",0.1,0))) -> 3.9285714 | O14: =IF(COUNT(D14,F14,H14,J14,L14)=0,"",D14*0.2+F14*0.15+H14*0.15+J14*0.1+L14*0.1) -> 2.75 | P14: 5 | Q14: H | R14: 3 | S14: L | T14: 4 | U14: L | V14: 2 | W14: H | X14: =IF(COUNT(P14,R14,T14,V14)=0,"",P14*0.08+R14*0.06+T14*0.03+V14*0.08) -> 0.86 | Y14: 4 | Z14: L | AA14: 4 | AB14: M | AC14: 3 | AD14: L | AE14: =IF(COUNT(Y14,AA14,AC14)=0,"",Y14*0.02+AA14*0.02+AC14*0.01) -> 0.19 | AF14: =IF(OR(COUNT(D14,F14,H14,J14,L14)<5,COUNT(P14,R14,T14,V14)<4,COUNT(Y14,AA14,AC14)<3),"",(O14+X14+AE14)*20) -> 76 | AG14: =IF(AF14="","",IF(AJ14="AVOID","AVOID",IF(AF14>=80,IF(AH14="FAIL","WATCH LIST",IF(AK14="CAP AT BUY","BUY","STRONG BUY")),IF(AF14>=65,IF(AH14="FAIL","WATCH LIST","BUY"),IF(AF14>=50,"WATCH LIST",IF(AF14>=35,"AVOID","PASS")))))) -> BUY | AH14: =IF(N14="","",IF(N14<3,"FAIL","OK")) -> OK | AI14: =IF(COUNT(D14:L14)=0,"",IF(COUNTIF(D14:L14,1)>0,"REVIEW","OK")) -> OK | AJ14: =IF(COUNT(D14:L14)=0,"",IF(COUNTIF(D14:L14,"<=2")>=2,"AVOID","OK")) -> OK | AK14: =IF(COUNTA(E14:M14)=0,"",IF(COUNTIF(E14:M14,"L")>=2,"CAP AT BUY","OK")) -> OK | AL14: Real Estate | AM14: REIT - Industrial | AP14: =IF(OR(AN14="",AO14=""),"",IF(AN14>AO14,"OK","LOW CONF")) | AS14: =IF(OR(AQ14="",AR14=""),"",IF(AQ14<AR14,"Decreased",IF(AQ14>AR14,"Increased","Flat")))
A15: VRT | B15: Vertiv Holdings | C15: 46278 | D15: 3 | E15: M | F15: 5 | G15: M | H15: 4 | I15: M | J15: 4 | K15: M | L15: 4 | M15: M | N15: =IF(COUNT(D15,F15,H15,J15,L15)=0,"",(D15*0.2+F15*0.15+H15*0.15+J15*0.1+L15*0.1)/(IF(D15<>"",0.2,0)+IF(F15<>"",0.15,0)+IF(H15<>"",0.15,0)+IF(J15<>"",0.1,0)+IF(L15<>"",0.1,0))) -> 3.9285714 | O15: =IF(COUNT(D15,F15,H15,J15,L15)=0,"",D15*0.2+F15*0.15+H15*0.15+J15*0.1+L15*0.1) -> 2.75 | P15: 4 | Q15: M | R15: 5 | S15: H | T15: 4 | U15: M | V15: 2 | W15: M | X15: =IF(COUNT(P15,R15,T15,V15)=0,"",P15*0.08+R15*0.06+T15*0.03+V15*0.08) -> 0.9 | Y15: 4 | Z15: M | AA15: 4 | AB15: M | AC15: 3 | AD15: L | AE15: =IF(COUNT(Y15,AA15,AC15)=0,"",Y15*0.02+AA15*0.02+AC15*0.01) -> 0.19 | AF15: =IF(OR(COUNT(D15,F15,H15,J15,L15)<5,COUNT(P15,R15,T15,V15)<4,COUNT(Y15,AA15,AC15)<3),"",(O15+X15+AE15)*20) -> 76.8 | AG15: =IF(AF15="","",IF(AJ15="AVOID","AVOID",IF(AF15>=80,IF(AH15="FAIL","WATCH LIST",IF(AK15="CAP AT BUY","BUY","STRONG BUY")),IF(AF15>=65,IF(AH15="FAIL","WATCH LIST","BUY"),IF(AF15>=50,"WATCH LIST",IF(AF15>=35,"AVOID","PASS")))))) -> BUY | AH15: =IF(N15="","",IF(N15<3,"FAIL","OK")) -> OK | AI15: =IF(COUNT(D15:L15)=0,"",IF(COUNTIF(D15:L15,1)>0,"REVIEW","OK")) -> OK | AJ15: =IF(COUNT(D15:L15)=0,"",IF(COUNTIF(D15:L15,"<=2")>=2,"AVOID","OK")) -> OK | AK15: =IF(COUNTA(E15:M15)=0,"",IF(COUNTIF(E15:M15,"L")>=2,"CAP AT BUY","OK")) -> OK | AL15: Industrials | AM15: Electrical Equipment & Parts | AN15: 2113800000 | AO15: 1332800000 | AP15: =IF(OR(AN15="",AO15=""),"",IF(AN15>AO15,"OK","LOW CONF")) -> OK | AQ15: 1.71 | AR15: 2.771 | AS15: =IF(OR(AQ15="",AR15=""),"",IF(AQ15<AR15,"Decreased",IF(AQ15>AR15,"Increased","Flat"))) -> Decreased
A16: DPZ | B16: Domino's Pizza Inc. | C16: 46278 | D16: 5 | E16: M | F16: 2 | G16: M | H16: 5 | I16: H | J16: 4 | K16: H | L16: 3 | M16: M | N16: =IF(COUNT(D16,F16,H16,J16,L16)=0,"",(D16*0.2+F16*0.15+H16*0.15+J16*0.1+L16*0.1)/(IF(D16<>"",0.2,0)+IF(F16<>"",0.15,0)+IF(H16<>"",0.15,0)+IF(J16<>"",0.1,0)+IF(L16<>"",0.1,0))) -> 3.9285714 | O16: =IF(COUNT(D16,F16,H16,J16,L16)=0,"",D16*0.2+F16*0.15+H16*0.15+J16*0.1+L16*0.1) -> 2.75 | X16: =IF(COUNT(P16,R16,T16,V16)=0,"",P16*0.08+R16*0.06+T16*0.03+V16*0.08) | AE16: =IF(COUNT(Y16,AA16,AC16)=0,"",Y16*0.02+AA16*0.02+AC16*0.01) | AF16: =IF(OR(COUNT(D16,F16,H16,J16,L16)<5,COUNT(P16,R16,T16,V16)<4,COUNT(Y16,AA16,AC16)<3),"",(O16+X16+AE16)*20) | AG16: =IF(AF16="","",IF(AJ16="AVOID","AVOID",IF(AF16>=80,IF(AH16="FAIL","WATCH LIST",IF(AK16="CAP AT BUY","BUY","STRONG BUY")),IF(AF16>=65,IF(AH16="FAIL","WATCH LIST","BUY"),IF(AF16>=50,"WATCH LIST",IF(AF16>=35,"AVOID","PASS")))))) | AH16: =IF(N16="","",IF(N16<3,"FAIL","OK")) -> OK | AI16: =IF(COUNT(D16:L16)=0,"",IF(COUNTIF(D16:L16,1)>0,"REVIEW","OK")) -> OK | AJ16: =IF(COUNT(D16:L16)=0,"",IF(COUNTIF(D16:L16,"<=2")>=2,"AVOID","OK")) -> OK | AK16: =IF(COUNTA(E16:M16)=0,"",IF(COUNTIF(E16:M16,"L")>=2,"CAP AT BUY","OK")) -> OK | AL16: Consumer Cyclical | AM16: Restaurants | AP16: =IF(OR(AN16="",AO16=""),"",IF(AN16>AO16,"OK","LOW CONF")) | AS16: =IF(OR(AQ16="",AR16=""),"",IF(AQ16<AR16,"Decreased",IF(AQ16>AR16,"Increased","Flat")))
A17: ASML | B17: ASML Holding | C17: 46278 | D17: 3 | E17: M | F17: 3 | G17: M | H17: 5 | I17: H | J17: 4 | K17: M | L17: 5 | M17: M | N17: =IF(COUNT(D17,F17,H17,J17,L17)=0,"",(D17*0.2+F17*0.15+H17*0.15+J17*0.1+L17*0.1)/(IF(D17<>"",0.2,0)+IF(F17<>"",0.15,0)+IF(H17<>"",0.15,0)+IF(J17<>"",0.1,0)+IF(L17<>"",0.1,0))) -> 3.8571429 | O17: =IF(COUNT(D17,F17,H17,J17,L17)=0,"",D17*0.2+F17*0.15+H17*0.15+J17*0.1+L17*0.1) -> 2.7 | P17: 4 | Q17: M | R17: 5 | S17: H | T17: 5 | U17: H | V17: 2 | W17: M | X17: =IF(COUNT(P17,R17,T17,V17)=0,"",P17*0.08+R17*0.06+T17*0.03+V17*0.08) -> 0.93 | Y17: 5 | Z17: M | AA17: 5 | AB17: H | AC17: 3 | AD17: L | AE17: =IF(COUNT(Y17,AA17,AC17)=0,"",Y17*0.02+AA17*0.02+AC17*0.01) -> 0.23 | AF17: =IF(OR(COUNT(D17,F17,H17,J17,L17)<5,COUNT(P17,R17,T17,V17)<4,COUNT(Y17,AA17,AC17)<3),"",(O17+X17+AE17)*20) -> 77.2 | AG17: =IF(AF17="","",IF(AJ17="AVOID","AVOID",IF(AF17>=80,IF(AH17="FAIL","WATCH LIST",IF(AK17="CAP AT BUY","BUY","STRONG BUY")),IF(AF17>=65,IF(AH17="FAIL","WATCH LIST","BUY"),IF(AF17>=50,"WATCH LIST",IF(AF17>=35,"AVOID","PASS")))))) -> BUY | AH17: =IF(N17="","",IF(N17<3,"FAIL","OK")) -> OK | AI17: =IF(COUNT(D17:L17)=0,"",IF(COUNTIF(D17:L17,1)>0,"REVIEW","OK")) -> OK | AJ17: =IF(COUNT(D17:L17)=0,"",IF(COUNTIF(D17:L17,"<=2")>=2,"AVOID","OK")) -> OK | AK17: =IF(COUNTA(E17:M17)=0,"",IF(COUNTIF(E17:M17,"L")>=2,"CAP AT BUY","OK")) -> OK | AL17: Technology | AM17: Semiconductor Equipment & Materials | AP17: =IF(OR(AN17="",AO17=""),"",IF(AN17>AO17,"OK","LOW CONF")) | AS17: =IF(OR(AQ17="",AR17=""),"",IF(AQ17<AR17,"Decreased",IF(AQ17>AR17,"Increased","Flat")))
A18: YUM | B18: Yum! Brands Inc. | C18: 46278 | D18: 4 | E18: M | F18: 3 | G18: M | H18: 4 | I18: M | J18: 4 | K18: H | L18: 4 | M18: M | N18: =IF(COUNT(D18,F18,H18,J18,L18)=0,"",(D18*0.2+F18*0.15+H18*0.15+J18*0.1+L18*0.1)/(IF(D18<>"",0.2,0)+IF(F18<>"",0.15,0)+IF(H18<>"",0.15,0)+IF(J18<>"",0.1,0)+IF(L18<>"",0.1,0))) -> 3.7857143 | O18: =IF(COUNT(D18,F18,H18,J18,L18)=0,"",D18*0.2+F18*0.15+H18*0.15+J18*0.1+L18*0.1) -> 2.65 | X18: =IF(COUNT(P18,R18,T18,V18)=0,"",P18*0.08+R18*0.06+T18*0.03+V18*0.08) | AE18: =IF(COUNT(Y18,AA18,AC18)=0,"",Y18*0.02+AA18*0.02+AC18*0.01) | AF18: =IF(OR(COUNT(D18,F18,H18,J18,L18)<5,COUNT(P18,R18,T18,V18)<4,COUNT(Y18,AA18,AC18)<3),"",(O18+X18+AE18)*20) | AG18: =IF(AF18="","",IF(AJ18="AVOID","AVOID",IF(AF18>=80,IF(AH18="FAIL","WATCH LIST",IF(AK18="CAP AT BUY","BUY","STRONG BUY")),IF(AF18>=65,IF(AH18="FAIL","WATCH LIST","BUY"),IF(AF18>=50,"WATCH LIST",IF(AF18>=35,"AVOID","PASS")))))) | AH18: =IF(N18="","",IF(N18<3,"FAIL","OK")) -> OK | AI18: =IF(COUNT(D18:L18)=0,"",IF(COUNTIF(D18:L18,1)>0,"REVIEW","OK")) -> OK | AJ18: =IF(COUNT(D18:L18)=0,"",IF(COUNTIF(D18:L18,"<=2")>=2,"AVOID","OK")) -> OK | AK18: =IF(COUNTA(E18:M18)=0,"",IF(COUNTIF(E18:M18,"L")>=2,"CAP AT BUY","OK")) -> OK | AL18: Consumer Cyclical | AM18: Restaurants | AP18: =IF(OR(AN18="",AO18=""),"",IF(AN18>AO18,"OK","LOW CONF")) | AS18: =IF(OR(AQ18="",AR18=""),"",IF(AQ18<AR18,"Decreased",IF(AQ18>AR18,"Increased","Flat")))
A19: KLAC | B19: KLA Corporation | C19: 46278 | D19: 3 | E19: M | F19: 3 | G19: M | H19: 5 | I19: H | J19: 3 | K19: M | L19: 5 | M19: M | N19: =IF(COUNT(D19,F19,H19,J19,L19)=0,"",(D19*0.2+F19*0.15+H19*0.15+J19*0.1+L19*0.1)/(IF(D19<>"",0.2,0)+IF(F19<>"",0.15,0)+IF(H19<>"",0.15,0)+IF(J19<>"",0.1,0)+IF(L19<>"",0.1,0))) -> 3.7142857 | O19: =IF(COUNT(D19,F19,H19,J19,L19)=0,"",D19*0.2+F19*0.15+H19*0.15+J19*0.1+L19*0.1) -> 2.6 | P19: 4 | Q19: H | R19: 5 | S19: H | T19: 3 | U19: M | V19: 2 | W19: M | X19: =IF(COUNT(P19,R19,T19,V19)=0,"",P19*0.08+R19*0.06+T19*0.03+V19*0.08) -> 0.87 | Y19: 2 | Z19: M | AA19: 5 | AB19: H | AC19: 2 | AD19: L | AE19: =IF(COUNT(Y19,AA19,AC19)=0,"",Y19*0.02+AA19*0.02+AC19*0.01) -> 0.16 | AF19: =IF(OR(COUNT(D19,F19,H19,J19,L19)<5,COUNT(P19,R19,T19,V19)<4,COUNT(Y19,AA19,AC19)<3),"",(O19+X19+AE19)*20) -> 72.6 | AG19: =IF(AF19="","",IF(AJ19="AVOID","AVOID",IF(AF19>=80,IF(AH19="FAIL","WATCH LIST",IF(AK19="CAP AT BUY","BUY","STRONG BUY")),IF(AF19>=65,IF(AH19="FAIL","WATCH LIST","BUY"),IF(AF19>=50,"WATCH LIST",IF(AF19>=35,"AVOID","PASS")))))) -> BUY | AH19: =IF(N19="","",IF(N19<3,"FAIL","OK")) -> OK | AI19: =IF(COUNT(D19:L19)=0,"",IF(COUNTIF(D19:L19,1)>0,"REVIEW","OK")) -> OK | AJ19: =IF(COUNT(D19:L19)=0,"",IF(COUNTIF(D19:L19,"<=2")>=2,"AVOID","OK")) -> OK | AK19: =IF(COUNTA(E19:M19)=0,"",IF(COUNTIF(E19:M19,"L")>=2,"CAP AT BUY","OK")) -> OK | AL19: Technology | AM19: Semiconductor Equipment & Materials | AN19: 4143079000 | AO19: 4830771000 | AP19: =IF(OR(AN19="",AO19=""),"",IF(AN19>AO19,"OK","LOW CONF")) -> LOW CONF | AQ19: 1.633 | AR19: 1.625 | AS19: =IF(OR(AQ19="",AR19=""),"",IF(AQ19<AR19,"Decreased",IF(AQ19>AR19,"Increased","Flat"))) -> Increased
A20: CMG | B20: Chipotle Mexican Grill | C20: 46245 | D20: 4 | E20: H | F20: 4 | G20: H | H20: 4 | I20: H | J20: 3 | K20: M | L20: 3 | M20: H | N20: =IF(COUNT(D20,F20,H20,J20,L20)=0,"",(D20*0.2+F20*0.15+H20*0.15+J20*0.1+L20*0.1)/(IF(D20<>"",0.2,0)+IF(F20<>"",0.15,0)+IF(H20<>"",0.15,0)+IF(J20<>"",0.1,0)+IF(L20<>"",0.1,0))) -> 3.7142857 | O20: =IF(COUNT(D20,F20,H20,J20,L20)=0,"",D20*0.2+F20*0.15+H20*0.15+J20*0.1+L20*0.1) -> 2.6 | X20: =IF(COUNT(P20,R20,T20,V20)=0,"",P20*0.08+R20*0.06+T20*0.03+V20*0.08) | AE20: =IF(COUNT(Y20,AA20,AC20)=0,"",Y20*0.02+AA20*0.02+AC20*0.01) | AF20: =IF(OR(COUNT(D20,F20,H20,J20,L20)<5,COUNT(P20,R20,T20,V20)<4,COUNT(Y20,AA20,AC20)<3),"",(O20+X20+AE20)*20) | AG20: =IF(AF20="","",IF(AJ20="AVOID","AVOID",IF(AF20>=80,IF(AH20="FAIL","WATCH LIST",IF(AK20="CAP AT BUY","BUY","STRONG BUY")),IF(AF20>=65,IF(AH20="FAIL","WATCH LIST","BUY"),IF(AF20>=50,"WATCH LIST",IF(AF20>=35,"AVOID","PASS")))))) | AH20: =IF(N20="","",IF(N20<3,"FAIL","OK")) -> OK | AI20: =IF(COUNT(D20:L20)=0,"",IF(COUNTIF(D20:L20,1)>0,"REVIEW","OK")) -> OK | AJ20: =IF(COUNT(D20:L20)=0,"",IF(COUNTIF(D20:L20,"<=2")>=2,"AVOID","OK")) -> OK | AK20: =IF(COUNTA(E20:M20)=0,"",IF(COUNTIF(E20:M20,"L")>=2,"CAP AT BUY","OK")) -> OK | AL20: Consumer Cyclical | AM20: Restaurants | AP20: =IF(OR(AN20="",AO20=""),"",IF(AN20>AO20,"OK","LOW CONF")) | AS20: =IF(OR(AQ20="",AR20=""),"",IF(AQ20<AR20,"Decreased",IF(AQ20>AR20,"Increased","Flat")))
A21: AVGO | B21: Broadcom Inc. | C21: 46300 | D21: 3 | E21: M | F21: 4 | G21: M | H21: 5 | I21: H | J21: 4 | K21: M | L21: 2 | M21: M | N21: =IF(COUNT(D21,F21,H21,J21,L21)=0,"",(D21*0.2+F21*0.15+H21*0.15+J21*0.1+L21*0.1)/(IF(D21<>"",0.2,0)+IF(F21<>"",0.15,0)+IF(H21<>"",0.15,0)+IF(J21<>"",0.1,0)+IF(L21<>"",0.1,0))) -> 3.6428571 | O21: =IF(COUNT(D21,F21,H21,J21,L21)=0,"",D21*0.2+F21*0.15+H21*0.15+J21*0.1+L21*0.1) -> 2.55 | P21: 4 | Q21: H | R21: 4 | S21: L | T21: 4 | U21: M | V21: 4 | W21: M | X21: =IF(COUNT(P21,R21,T21,V21)=0,"",P21*0.08+R21*0.06+T21*0.03+V21*0.08) -> 1 | Y21: 3 | Z21: M | AA21: 5 | AB21: H | AC21: 3 | AD21: M | AE21: =IF(COUNT(Y21,AA21,AC21)=0,"",Y21*0.02+AA21*0.02+AC21*0.01) -> 0.19 | AF21: =IF(OR(COUNT(D21,F21,H21,J21,L21)<5,COUNT(P21,R21,T21,V21)<4,COUNT(Y21,AA21,AC21)<3),"",(O21+X21+AE21)*20) -> 74.8 | AG21: =IF(AF21="","",IF(AJ21="AVOID","AVOID",IF(AF21>=80,IF(AH21="FAIL","WATCH LIST",IF(AK21="CAP AT BUY","BUY","STRONG BUY")),IF(AF21>=65,IF(AH21="FAIL","WATCH LIST","BUY"),IF(AF21>=50,"WATCH LIST",IF(AF21>=35,"AVOID","PASS")))))) -> BUY | AH21: =IF(N21="","",IF(N21<3,"FAIL","OK")) -> OK | AI21: =IF(COUNT(D21:L21)=0,"",IF(COUNTIF(D21:L21,1)>0,"REVIEW","OK")) -> OK | AJ21: =IF(COUNT(D21:L21)=0,"",IF(COUNTIF(D21:L21,"<=2")>=2,"AVOID","OK")) -> OK | AK21: =IF(COUNTA(E21:M21)=0,"",IF(COUNTIF(E21:M21,"L")>=2,"CAP AT BUY","OK")) -> OK | AL21: Technology | AM21: Semiconductors | AP21: =IF(OR(AN21="",AO21=""),"",IF(AN21>AO21,"OK","LOW CONF")) | AS21: =IF(OR(AQ21="",AR21=""),"",IF(AQ21<AR21,"Decreased",IF(AQ21>AR21,"Increased","Flat")))
A22: V | B22: Visa Inc. | C22: 46278 | D22: 3 | E22: M | F22: 4 | G22: M | H22: 5 | I22: H | J22: 4 | K22: M | L22: 2 | M22: M | N22: =IF(COUNT(D22,F22,H22,J22,L22)=0,"",(D22*0.2+F22*0.15+H22*0.15+J22*0.1+L22*0.1)/(IF(D22<>"",0.2,0)+IF(F22<>"",0.15,0)+IF(H22<>"",0.15,0)+IF(J22<>"",0.1,0)+IF(L22<>"",0.1,0))) -> 3.6428571 | O22: =IF(COUNT(D22,F22,H22,J22,L22)=0,"",D22*0.2+F22*0.15+H22*0.15+J22*0.1+L22*0.1) -> 2.55 | P22: 4 | Q22: M | R22: 5 | S22: H | T22: 3 | U22: M | V22: 3 | W22: M | X22: =IF(COUNT(P22,R22,T22,V22)=0,"",P22*0.08+R22*0.06+T22*0.03+V22*0.08) -> 0.95 | Y22: 3 | Z22: M | AA22: 4 | AB22: M | AC22: 3 | AD22: L | AE22: =IF(COUNT(Y22,AA22,AC22)=0,"",Y22*0.02+AA22*0.02+AC22*0.01) -> 0.17 | AF22: =IF(OR(COUNT(D22,F22,H22,J22,L22)<5,COUNT(P22,R22,T22,V22)<4,COUNT(Y22,AA22,AC22)<3),"",(O22+X22+AE22)*20) -> 73.4 | AG22: =IF(AF22="","",IF(AJ22="AVOID","AVOID",IF(AF22>=80,IF(AH22="FAIL","WATCH LIST",IF(AK22="CAP AT BUY","BUY","STRONG BUY")),IF(AF22>=65,IF(AH22="FAIL","WATCH LIST","BUY"),IF(AF22>=50,"WATCH LIST",IF(AF22>=35,"AVOID","PASS")))))) -> BUY | AH22: =IF(N22="","",IF(N22<3,"FAIL","OK")) -> OK | AI22: =IF(COUNT(D22:L22)=0,"",IF(COUNTIF(D22:L22,1)>0,"REVIEW","OK")) -> OK | AJ22: =IF(COUNT(D22:L22)=0,"",IF(COUNTIF(D22:L22,"<=2")>=2,"AVOID","OK")) -> OK | AK22: =IF(COUNTA(E22:M22)=0,"",IF(COUNTIF(E22:M22,"L")>=2,"CAP AT BUY","OK")) -> OK | AL22: Financial Services | AM22: Credit Services | AN22: 23059000000 | AO22: 20058000000 | AP22: =IF(OR(AN22="",AO22=""),"",IF(AN22>AO22,"OK","LOW CONF")) -> OK | AQ22: 1.167 | AR22: 1.115 | AS22: =IF(OR(AQ22="",AR22=""),"",IF(AQ22<AR22,"Decreased",IF(AQ22>AR22,"Increased","Flat"))) -> Increased
A23: CRWD | B23: CrowdStrike Holdings | C23: 46278 | D23: 2 | E23: M | F23: 5 | G23: M | H23: 4 | I23: M | J23: 5 | K23: H | L23: 2 | M23: M | N23: =IF(COUNT(D23,F23,H23,J23,L23)=0,"",(D23*0.2+F23*0.15+H23*0.15+J23*0.1+L23*0.1)/(IF(D23<>"",0.2,0)+IF(F23<>"",0.15,0)+IF(H23<>"",0.15,0)+IF(J23<>"",0.1,0)+IF(L23<>"",0.1,0))) -> 3.5 | O23: =IF(COUNT(D23,F23,H23,J23,L23)=0,"",D23*0.2+F23*0.15+H23*0.15+J23*0.1+L23*0.1) -> 2.45 | P23: 3 | Q23: M | R23: 2 | S23: M | T23: 4 | U23: H | V23: 1 | W23: H | X23: =IF(COUNT(P23,R23,T23,V23)=0,"",P23*0.08+R23*0.06+T23*0.03+V23*0.08) -> 0.56 | Y23: 4 | Z23: M | AA23: 3 | AB23: M | AC23: 2 | AD23: M | AE23: =IF(COUNT(Y23,AA23,AC23)=0,"",Y23*0.02+AA23*0.02+AC23*0.01) -> 0.16 | AF23: =IF(OR(COUNT(D23,F23,H23,J23,L23)<5,COUNT(P23,R23,T23,V23)<4,COUNT(Y23,AA23,AC23)<3),"",(O23+X23+AE23)*20) -> 63.4 | AG23: =IF(AF23="","",IF(AJ23="AVOID","AVOID",IF(AF23>=80,IF(AH23="FAIL","WATCH LIST",IF(AK23="CAP AT BUY","BUY","STRONG BUY")),IF(AF23>=65,IF(AH23="FAIL","WATCH LIST","BUY"),IF(AF23>=50,"WATCH LIST",IF(AF23>=35,"AVOID","PASS")))))) -> AVOID | AH23: =IF(N23="","",IF(N23<3,"FAIL","OK")) -> OK | AI23: =IF(COUNT(D23:L23)=0,"",IF(COUNTIF(D23:L23,1)>0,"REVIEW","OK")) -> OK | AJ23: =IF(COUNT(D23:L23)=0,"",IF(COUNTIF(D23:L23,"<=2")>=2,"AVOID","OK")) -> AVOID | AK23: =IF(COUNTA(E23:M23)=0,"",IF(COUNTIF(E23:M23,"L")>=2,"CAP AT BUY","OK")) -> OK | AL23: Technology | AM23: Software - Infrastructure | AP23: =IF(OR(AN23="",AO23=""),"",IF(AN23>AO23,"OK","LOW CONF")) | AS23: =IF(OR(AQ23="",AR23=""),"",IF(AQ23<AR23,"Decreased",IF(AQ23>AR23,"Increased","Flat")))
A24: ETN | B24: Eaton Corporation plc | C24: 46247 | D24: 4 | E24: M | F24: 3 | G24: M | H24: 4 | I24: M | J24: 3 | K24: M | L24: 3 | M24: M | N24: =IF(COUNT(D24,F24,H24,J24,L24)=0,"",(D24*0.2+F24*0.15+H24*0.15+J24*0.1+L24*0.1)/(IF(D24<>"",0.2,0)+IF(F24<>"",0.15,0)+IF(H24<>"",0.15,0)+IF(J24<>"",0.1,0)+IF(L24<>"",0.1,0))) -> 3.5 | O24: =IF(COUNT(D24,F24,H24,J24,L24)=0,"",D24*0.2+F24*0.15+H24*0.15+J24*0.1+L24*0.1) -> 2.45 | X24: =IF(COUNT(P24,R24,T24,V24)=0,"",P24*0.08+R24*0.06+T24*0.03+V24*0.08) | AA24: 4 | AB24: M | AE24: =IF(COUNT(Y24,AA24,AC24)=0,"",Y24*0.02+AA24*0.02+AC24*0.01) -> 0.08 | AF24: =IF(OR(COUNT(D24,F24,H24,J24,L24)<5,COUNT(P24,R24,T24,V24)<4,COUNT(Y24,AA24,AC24)<3),"",(O24+X24+AE24)*20) | AG24: =IF(AF24="","",IF(AJ24="AVOID","AVOID",IF(AF24>=80,IF(AH24="FAIL","WATCH LIST",IF(AK24="CAP AT BUY","BUY","STRONG BUY")),IF(AF24>=65,IF(AH24="FAIL","WATCH LIST","BUY"),IF(AF24>=50,"WATCH LIST",IF(AF24>=35,"AVOID","PASS")))))) | AH24: =IF(N24="","",IF(N24<3,"FAIL","OK")) -> OK | AI24: =IF(COUNT(D24:L24)=0,"",IF(COUNTIF(D24:L24,1)>0,"REVIEW","OK")) -> OK | AJ24: =IF(COUNT(D24:L24)=0,"",IF(COUNTIF(D24:L24,"<=2")>=2,"AVOID","OK")) -> OK | AK24: =IF(COUNTA(E24:M24)=0,"",IF(COUNTIF(E24:M24,"L")>=2,"CAP AT BUY","OK")) -> OK | AL24: Industrials | AM24: Specialty Industrial Machinery | AP24: =IF(OR(AN24="",AO24=""),"",IF(AN24>AO24,"OK","LOW CONF")) | AS24: =IF(OR(AQ24="",AR24=""),"",IF(AQ24<AR24,"Decreased",IF(AQ24>AR24,"Increased","Flat")))
A25: ABT | B25: Abbott Laboratories | C25: 46278 | D25: 3 | E25: M | F25: 2 | G25: M | H25: 5 | I25: H | J25: 4 | K25: M | L25: 4 | M25: M | N25: =IF(COUNT(D25,F25,H25,J25,L25)=0,"",(D25*0.2+F25*0.15+H25*0.15+J25*0.1+L25*0.1)/(IF(D25<>"",0.2,0)+IF(F25<>"",0.15,0)+IF(H25<>"",0.15,0)+IF(J25<>"",0.1,0)+IF(L25<>"",0.1,0))) -> 3.5 | O25: =IF(COUNT(D25,F25,H25,J25,L25)=0,"",D25*0.2+F25*0.15+H25*0.15+J25*0.1+L25*0.1) -> 2.45 | P25: 5 | Q25: H | R25: 3 | S25: L | T25: 1 | U25: M | V25: 4 | W25: M | X25: =IF(COUNT(P25,R25,T25,V25)=0,"",P25*0.08+R25*0.06+T25*0.03+V25*0.08) -> 0.93 | Y25: 2 | Z25: M | AA25: 5 | AB25: M | AC25: 2 | AD25: M | AE25: =IF(COUNT(Y25,AA25,AC25)=0,"",Y25*0.02+AA25*0.02+AC25*0.01) -> 0.16 | AF25: =IF(OR(COUNT(D25,F25,H25,J25,L25)<5,COUNT(P25,R25,T25,V25)<4,COUNT(Y25,AA25,AC25)<3),"",(O25+X25+AE25)*20) -> 70.8 | AG25: =IF(AF25="","",IF(AJ25="AVOID","AVOID",IF(AF25>=80,IF(AH25="FAIL","WATCH LIST",IF(AK25="CAP AT BUY","BUY","STRONG BUY")),IF(AF25>=65,IF(AH25="FAIL","WATCH LIST","BUY"),IF(AF25>=50,"WATCH LIST",IF(AF25>=35,"AVOID","PASS")))))) -> BUY | AH25: =IF(N25="","",IF(N25<3,"FAIL","OK")) -> OK | AI25: =IF(COUNT(D25:L25)=0,"",IF(COUNTIF(D25:L25,1)>0,"REVIEW","OK")) -> OK | AJ25: =IF(COUNT(D25:L25)=0,"",IF(COUNTIF(D25:L25,"<=2")>=2,"AVOID","OK")) -> OK | AK25: =IF(COUNTA(E25:M25)=0,"",IF(COUNTIF(E25:M25,"L")>=2,"CAP AT BUY","OK")) -> OK | AL25: Healthcare | AM25: Medical Devices | AP25: =IF(OR(AN25="",AO25=""),"",IF(AN25>AO25,"OK","LOW CONF")) | AS25: =IF(OR(AQ25="",AR25=""),"",IF(AQ25<AR25,"Decreased",IF(AQ25>AR25,"Increased","Flat")))
A26: SLB | B26: SLB N.V. | C26: 46278 | D26: 4 | E26: M | F26: 3 | G26: M | H26: 4 | I26: M | J26: 3 | K26: M | L26: 3 | M26: M | N26: =IF(COUNT(D26,F26,H26,J26,L26)=0,"",(D26*0.2+F26*0.15+H26*0.15+J26*0.1+L26*0.1)/(IF(D26<>"",0.2,0)+IF(F26<>"",0.15,0)+IF(H26<>"",0.15,0)+IF(J26<>"",0.1,0)+IF(L26<>"",0.1,0))) -> 3.5 | O26: =IF(COUNT(D26,F26,H26,J26,L26)=0,"",D26*0.2+F26*0.15+H26*0.15+J26*0.1+L26*0.1) -> 2.45 | P26: 4 | Q26: M | R26: 3 | S26: L | T26: 5 | U26: M | V26: 4 | W26: M | X26: =IF(COUNT(P26,R26,T26,V26)=0,"",P26*0.08+R26*0.06+T26*0.03+V26*0.08) -> 0.97 | Y26: 5 | Z26: M | AA26: 4 | AB26: M | AC26: 2 | AD26: M | AE26: =IF(COUNT(Y26,AA26,AC26)=0,"",Y26*0.02+AA26*0.02+AC26*0.01) -> 0.2 | AF26: =IF(OR(COUNT(D26,F26,H26,J26,L26)<5,COUNT(P26,R26,T26,V26)<4,COUNT(Y26,AA26,AC26)<3),"",(O26+X26+AE26)*20) -> 72.4 | AG26: =IF(AF26="","",IF(AJ26="AVOID","AVOID",IF(AF26>=80,IF(AH26="FAIL","WATCH LIST",IF(AK26="CAP AT BUY","BUY","STRONG BUY")),IF(AF26>=65,IF(AH26="FAIL","WATCH LIST","BUY"),IF(AF26>=50,"WATCH LIST",IF(AF26>=35,"AVOID","PASS")))))) -> BUY | AH26: =IF(N26="","",IF(N26<3,"FAIL","OK")) -> OK | AI26: =IF(COUNT(D26:L26)=0,"",IF(COUNTIF(D26:L26,1)>0,"REVIEW","OK")) -> OK | AJ26: =IF(COUNT(D26:L26)=0,"",IF(COUNTIF(D26:L26,"<=2")>=2,"AVOID","OK")) -> OK | AK26: =IF(COUNTA(E26:M26)=0,"",IF(COUNTIF(E26:M26,"L")>=2,"CAP AT BUY","OK")) -> OK | AL26: Energy | AM26: Oil & Gas Equipment & Services | AP26: =IF(OR(AN26="",AO26=""),"",IF(AN26>AO26,"OK","LOW CONF")) | AS26: =IF(OR(AQ26="",AR26=""),"",IF(AQ26<AR26,"Decreased",IF(AQ26>AR26,"Increased","Flat")))
A27: VRTX | B27: Vertex Pharmaceuticals | C27: 46300 | D27: 3 | E27: M | F27: 4 | G27: M | H27: 4 | I27: M | J27: 4 | K27: M | L27: 2 | M27: M | N27: =IF(COUNT(D27,F27,H27,J27,L27)=0,"",(D27*0.2+F27*0.15+H27*0.15+J27*0.1+L27*0.1)/(IF(D27<>"",0.2,0)+IF(F27<>"",0.15,0)+IF(H27<>"",0.15,0)+IF(J27<>"",0.1,0)+IF(L27<>"",0.1,0))) -> 3.4285714 | O27: =IF(COUNT(D27,F27,H27,J27,L27)=0,"",D27*0.2+F27*0.15+H27*0.15+J27*0.1+L27*0.1) -> 2.4 | P27: 3 | Q27: M | R27: 4 | S27: M | T27: 4 | U27: M | V27: 4 | W27: M | X27: =IF(COUNT(P27,R27,T27,V27)=0,"",P27*0.08+R27*0.06+T27*0.03+V27*0.08) -> 0.92 | Y27: 4 | Z27: M | AA27: 5 | AB27: H | AC27: 3 | AD27: L | AE27: =IF(COUNT(Y27,AA27,AC27)=0,"",Y27*0.02+AA27*0.02+AC27*0.01) -> 0.21 | AF27: =IF(OR(COUNT(D27,F27,H27,J27,L27)<5,COUNT(P27,R27,T27,V27)<4,COUNT(Y27,AA27,AC27)<3),"",(O27+X27+AE27)*20) -> 70.6 | AG27: =IF(AF27="","",IF(AJ27="AVOID","AVOID",IF(AF27>=80,IF(AH27="FAIL","WATCH LIST",IF(AK27="CAP AT BUY","BUY","STRONG BUY")),IF(AF27>=65,IF(AH27="FAIL","WATCH LIST","BUY"),IF(AF27>=50,"WATCH LIST",IF(AF27>=35,"AVOID","PASS")))))) -> BUY | AH27: =IF(N27="","",IF(N27<3,"FAIL","OK")) -> OK | AI27: =IF(COUNT(D27:L27)=0,"",IF(COUNTIF(D27:L27,1)>0,"REVIEW","OK")) -> OK | AJ27: =IF(COUNT(D27:L27)=0,"",IF(COUNTIF(D27:L27,"<=2")>=2,"AVOID","OK")) -> OK | AK27: =IF(COUNTA(E27:M27)=0,"",IF(COUNTIF(E27:M27,"L")>=2,"CAP AT BUY","OK")) -> OK | AL27: Healthcare | AM27: Biotechnology | AN27: 3631400000 | AO27: 3953200000 | AP27: =IF(OR(AN27="",AO27=""),"",IF(AN27>AO27,"OK","LOW CONF")) -> LOW CONF | AQ27: 0.636 | AR27: -1.784 | AS27: =IF(OR(AQ27="",AR27=""),"",IF(AQ27<AR27,"Decreased",IF(AQ27>AR27,"Increased","Flat"))) -> Increased
A28: ETSY | B28: Etsy Inc. | C28: 46246 | D28: 4 | E28: H | F28: 3 | G28: H | H28: 3 | I28: M | J28: 3 | K28: M | L28: 4 | M28: H | N28: =IF(COUNT(D28,F28,H28,J28,L28)=0,"",(D28*0.2+F28*0.15+H28*0.15+J28*0.1+L28*0.1)/(IF(D28<>"",0.2,0)+IF(F28<>"",0.15,0)+IF(H28<>"",0.15,0)+IF(J28<>"",0.1,0)+IF(L28<>"",0.1,0))) -> 3.4285714 | O28: =IF(COUNT(D28,F28,H28,J28,L28)=0,"",D28*0.2+F28*0.15+H28*0.15+J28*0.1+L28*0.1) -> 2.4 | X28: =IF(COUNT(P28,R28,T28,V28)=0,"",P28*0.08+R28*0.06+T28*0.03+V28*0.08) | AE28: =IF(COUNT(Y28,AA28,AC28)=0,"",Y28*0.02+AA28*0.02+AC28*0.01) | AF28: =IF(OR(COUNT(D28,F28,H28,J28,L28)<5,COUNT(P28,R28,T28,V28)<4,COUNT(Y28,AA28,AC28)<3),"",(O28+X28+AE28)*20) | AG28: =IF(AF28="","",IF(AJ28="AVOID","AVOID",IF(AF28>=80,IF(AH28="FAIL","WATCH LIST",IF(AK28="CAP AT BUY","BUY","STRONG BUY")),IF(AF28>=65,IF(AH28="FAIL","WATCH LIST","BUY"),IF(AF28>=50,"WATCH LIST",IF(AF28>=35,"AVOID","PASS")))))) | AH28: =IF(N28="","",IF(N28<3,"FAIL","OK")) -> OK | AI28: =IF(COUNT(D28:L28)=0,"",IF(COUNTIF(D28:L28,1)>0,"REVIEW","OK")) -> OK | AJ28: =IF(COUNT(D28:L28)=0,"",IF(COUNTIF(D28:L28,"<=2")>=2,"AVOID","OK")) -> OK | AK28: =IF(COUNTA(E28:M28)=0,"",IF(COUNTIF(E28:M28,"L")>=2,"CAP AT BUY","OK")) -> OK | AL28: Consumer Cyclical | AM28: Internet Retail | AP28: =IF(OR(AN28="",AO28=""),"",IF(AN28>AO28,"OK","LOW CONF")) | AS28: =IF(OR(AQ28="",AR28=""),"",IF(AQ28<AR28,"Decreased",IF(AQ28>AR28,"Increased","Flat")))
A29: MU | B29: Micron Technology | C29: 46278 | D29: 3 | E29: M | F29: 3 | G29: M | H29: 4 | I29: H | J29: 5 | K29: H | L29: 2 | M29: M | N29: =IF(COUNT(D29,F29,H29,J29,L29)=0,"",(D29*0.2+F29*0.15+H29*0.15+J29*0.1+L29*0.1)/(IF(D29<>"",0.2,0)+IF(F29<>"",0.15,0)+IF(H29<>"",0.15,0)+IF(J29<>"",0.1,0)+IF(L29<>"",0.1,0))) -> 3.3571429 | O29: =IF(COUNT(D29,F29,H29,J29,L29)=0,"",D29*0.2+F29*0.15+H29*0.15+J29*0.1+L29*0.1) -> 2.35 | P29: 4 | Q29: M | R29: 5 | S29: M | T29: 5 | U29: H | V29: 1 | W29: H | X29: =IF(COUNT(P29,R29,T29,V29)=0,"",P29*0.08+R29*0.06+T29*0.03+V29*0.08) -> 0.85 | Y29: 5 | Z29: H | AA29: 3 | AB29: M | AC29: 3 | AD29: L | AE29: =IF(COUNT(Y29,AA29,AC29)=0,"",Y29*0.02+AA29*0.02+AC29*0.01) -> 0.19 | AF29: =IF(OR(COUNT(D29,F29,H29,J29,L29)<5,COUNT(P29,R29,T29,V29)<4,COUNT(Y29,AA29,AC29)<3),"",(O29+X29+AE29)*20) -> 67.8 | AG29: =IF(AF29="","",IF(AJ29="AVOID","AVOID",IF(AF29>=80,IF(AH29="FAIL","WATCH LIST",IF(AK29="CAP AT BUY","BUY","STRONG BUY")),IF(AF29>=65,IF(AH29="FAIL","WATCH LIST","BUY"),IF(AF29>=50,"WATCH LIST",IF(AF29>=35,"AVOID","PASS")))))) -> BUY | AH29: =IF(N29="","",IF(N29<3,"FAIL","OK")) -> OK | AI29: =IF(COUNT(D29:L29)=0,"",IF(COUNTIF(D29:L29,1)>0,"REVIEW","OK")) -> OK | AJ29: =IF(COUNT(D29:L29)=0,"",IF(COUNTIF(D29:L29,"<=2")>=2,"AVOID","OK")) -> OK | AK29: =IF(COUNTA(E29:M29)=0,"",IF(COUNTIF(E29:M29,"L")>=2,"CAP AT BUY","OK")) -> OK | AL29: Technology | AM29: Semiconductors | AN29: 17525000000 | AO29: 8539000000 | AP29: =IF(OR(AN29="",AO29=""),"",IF(AN29>AO29,"OK","LOW CONF")) -> OK | AQ29: 9.159 | AR29: 115.76 | AS29: =IF(OR(AQ29="",AR29=""),"",IF(AQ29<AR29,"Decreased",IF(AQ29>AR29,"Increased","Flat"))) -> Decreased
A30: PH | B30: Parker-Hannifin Corporation | C30: 46247 | D30: 4 | E30: M | F30: 3 | G30: M | H30: 3 | I30: M | J30: 2 | K30: M | L30: 4 | M30: M | N30: =IF(COUNT(D30,F30,H30,J30,L30)=0,"",(D30*0.2+F30*0.15+H30*0.15+J30*0.1+L30*0.1)/(IF(D30<>"",0.2,0)+IF(F30<>"",0.15,0)+IF(H30<>"",0.15,0)+IF(J30<>"",0.1,0)+IF(L30<>"",0.1,0))) -> 3.2857143 | O30: =IF(COUNT(D30,F30,H30,J30,L30)=0,"",D30*0.2+F30*0.15+H30*0.15+J30*0.1+L30*0.1) -> 2.3 | X30: =IF(COUNT(P30,R30,T30,V30)=0,"",P30*0.08+R30*0.06+T30*0.03+V30*0.08) | AA30: 4 | AB30: M | AE30: =IF(COUNT(Y30,AA30,AC30)=0,"",Y30*0.02+AA30*0.02+AC30*0.01) -> 0.08 | AF30: =IF(OR(COUNT(D30,F30,H30,J30,L30)<5,COUNT(P30,R30,T30,V30)<4,COUNT(Y30,AA30,AC30)<3),"",(O30+X30+AE30)*20) | AG30: =IF(AF30="","",IF(AJ30="AVOID","AVOID",IF(AF30>=80,IF(AH30="FAIL","WATCH LIST",IF(AK30="CAP AT BUY","BUY","STRONG BUY")),IF(AF30>=65,IF(AH30="FAIL","WATCH LIST","BUY"),IF(AF30>=50,"WATCH LIST",IF(AF30>=35,"AVOID","PASS")))))) | AH30: =IF(N30="","",IF(N30<3,"FAIL","OK")) -> OK | AI30: =IF(COUNT(D30:L30)=0,"",IF(COUNTIF(D30:L30,1)>0,"REVIEW","OK")) -> OK | AJ30: =IF(COUNT(D30:L30)=0,"",IF(COUNTIF(D30:L30,"<=2")>=2,"AVOID","OK")) -> OK | AK30: =IF(COUNTA(E30:M30)=0,"",IF(COUNTIF(E30:M30,"L")>=2,"CAP AT BUY","OK")) -> OK | AL30: Industrials | AM30: Specialty Industrial Machinery | AP30: =IF(OR(AN30="",AO30=""),"",IF(AN30>AO30,"OK","LOW CONF")) | AS30: =IF(OR(AQ30="",AR30=""),"",IF(AQ30<AR30,"Decreased",IF(AQ30>AR30,"Increased","Flat")))
A31: ET | B31: Energy Transfer LP | C31: 46276 | D31: 4 | E31: M | F31: 1 | G31: M | H31: 4 | I31: M | J31: 4 | K31: M | L31: 2 | M31: M | N31: =IF(COUNT(D31,F31,H31,J31,L31)=0,"",(D31*0.2+F31*0.15+H31*0.15+J31*0.1+L31*0.1)/(IF(D31<>"",0.2,0)+IF(F31<>"",0.15,0)+IF(H31<>"",0.15,0)+IF(J31<>"",0.1,0)+IF(L31<>"",0.1,0))) -> 3.0714286 | O31: =IF(COUNT(D31,F31,H31,J31,L31)=0,"",D31*0.2+F31*0.15+H31*0.15+J31*0.1+L31*0.1) -> 2.15 | X31: =IF(COUNT(P31,R31,T31,V31)=0,"",P31*0.08+R31*0.06+T31*0.03+V31*0.08) | AE31: =IF(COUNT(Y31,AA31,AC31)=0,"",Y31*0.02+AA31*0.02+AC31*0.01) | AF31: =IF(OR(COUNT(D31,F31,H31,J31,L31)<5,COUNT(P31,R31,T31,V31)<4,COUNT(Y31,AA31,AC31)<3),"",(O31+X31+AE31)*20) | AG31: =IF(AF31="","",IF(AJ31="AVOID","AVOID",IF(AF31>=80,IF(AH31="FAIL","WATCH LIST",IF(AK31="CAP AT BUY","BUY","STRONG BUY")),IF(AF31>=65,IF(AH31="FAIL","WATCH LIST","BUY"),IF(AF31>=50,"WATCH LIST",IF(AF31>=35,"AVOID","PASS")))))) | AH31: =IF(N31="","",IF(N31<3,"FAIL","OK")) -> OK | AI31: =IF(COUNT(D31:L31)=0,"",IF(COUNTIF(D31:L31,1)>0,"REVIEW","OK")) -> REVIEW | AJ31: =IF(COUNT(D31:L31)=0,"",IF(COUNTIF(D31:L31,"<=2")>=2,"AVOID","OK")) -> AVOID | AK31: =IF(COUNTA(E31:M31)=0,"",IF(COUNTIF(E31:M31,"L")>=2,"CAP AT BUY","OK")) -> OK | AL31: Energy | AM31: Oil & Gas Midstream | AP31: =IF(OR(AN31="",AO31=""),"",IF(AN31>AO31,"OK","LOW CONF")) | AS31: =IF(OR(AQ31="",AR31=""),"",IF(AQ31<AR31,"Decreased",IF(AQ31>AR31,"Increased","Flat")))
A32: LIN | B32: Linde plc | C32: 46276 | D32: 2 | E32: M | F32: 2 | G32: M | H32: 5 | I32: H | J32: 5 | K32: H | L32: 2 | M32: M | N32: =IF(COUNT(D32,F32,H32,J32,L32)=0,"",(D32*0.2+F32*0.15+H32*0.15+J32*0.1+L32*0.1)/(IF(D32<>"",0.2,0)+IF(F32<>"",0.15,0)+IF(H32<>"",0.15,0)+IF(J32<>"",0.1,0)+IF(L32<>"",0.1,0))) -> 3.0714286 | O32: =IF(COUNT(D32,F32,H32,J32,L32)=0,"",D32*0.2+F32*0.15+H32*0.15+J32*0.1+L32*0.1) -> 2.15 | X32: =IF(COUNT(P32,R32,T32,V32)=0,"",P32*0.08+R32*0.06+T32*0.03+V32*0.08) | AE32: =IF(COUNT(Y32,AA32,AC32)=0,"",Y32*0.02+AA32*0.02+AC32*0.01) | AF32: =IF(OR(COUNT(D32,F32,H32,J32,L32)<5,COUNT(P32,R32,T32,V32)<4,COUNT(Y32,AA32,AC32)<3),"",(O32+X32+AE32)*20) | AG32: =IF(AF32="","",IF(AJ32="AVOID","AVOID",IF(AF32>=80,IF(AH32="FAIL","WATCH LIST",IF(AK32="CAP AT BUY","BUY","STRONG BUY")),IF(AF32>=65,IF(AH32="FAIL","WATCH LIST","BUY"),IF(AF32>=50,"WATCH LIST",IF(AF32>=35,"AVOID","PASS")))))) | AH32: =IF(N32="","",IF(N32<3,"FAIL","OK")) -> OK | AI32: =IF(COUNT(D32:L32)=0,"",IF(COUNTIF(D32:L32,1)>0,"REVIEW","OK")) -> OK | AJ32: =IF(COUNT(D32:L32)=0,"",IF(COUNTIF(D32:L32,"<=2")>=2,"AVOID","OK")) -> AVOID | AK32: =IF(COUNTA(E32:M32)=0,"",IF(COUNTIF(E32:M32,"L")>=2,"CAP AT BUY","OK")) -> OK | AL32: Basic Materials | AM32: Specialty Chemicals | AP32: =IF(OR(AN32="",AO32=""),"",IF(AN32>AO32,"OK","LOW CONF")) | AS32: =IF(OR(AQ32="",AR32=""),"",IF(AQ32<AR32,"Decreased",IF(AQ32>AR32,"Increased","Flat")))
A33: DIS | B33: The Walt Disney Company | C33: 46258 | D33: 4 | E33: M | F33: 2 | G33: M | H33: 3 | I33: M | J33: 2 | K33: M | L33: 3 | M33: M | N33: =IF(COUNT(D33,F33,H33,J33,L33)=0,"",(D33*0.2+F33*0.15+H33*0.15+J33*0.1+L33*0.1)/(IF(D33<>"",0.2,0)+IF(F33<>"",0.15,0)+IF(H33<>"",0.15,0)+IF(J33<>"",0.1,0)+IF(L33<>"",0.1,0))) -> 2.9285714 | O33: =IF(COUNT(D33,F33,H33,J33,L33)=0,"",D33*0.2+F33*0.15+H33*0.15+J33*0.1+L33*0.1) -> 2.05 | X33: =IF(COUNT(P33,R33,T33,V33)=0,"",P33*0.08+R33*0.06+T33*0.03+V33*0.08) | AE33: =IF(COUNT(Y33,AA33,AC33)=0,"",Y33*0.02+AA33*0.02+AC33*0.01) | AF33: =IF(OR(COUNT(D33,F33,H33,J33,L33)<5,COUNT(P33,R33,T33,V33)<4,COUNT(Y33,AA33,AC33)<3),"",(O33+X33+AE33)*20) | AG33: =IF(AF33="","",IF(AJ33="AVOID","AVOID",IF(AF33>=80,IF(AH33="FAIL","WATCH LIST",IF(AK33="CAP AT BUY","BUY","STRONG BUY")),IF(AF33>=65,IF(AH33="FAIL","WATCH LIST","BUY"),IF(AF33>=50,"WATCH LIST",IF(AF33>=35,"AVOID","PASS")))))) | AH33: =IF(N33="","",IF(N33<3,"FAIL","OK")) -> FAIL | AI33: =IF(COUNT(D33:L33)=0,"",IF(COUNTIF(D33:L33,1)>0,"REVIEW","OK")) -> OK | AJ33: =IF(COUNT(D33:L33)=0,"",IF(COUNTIF(D33:L33,"<=2")>=2,"AVOID","OK")) -> AVOID | AK33: =IF(COUNTA(E33:M33)=0,"",IF(COUNTIF(E33:M33,"L")>=2,"CAP AT BUY","OK")) -> OK | AL33: Communication Services | AM33: Entertainment | AP33: =IF(OR(AN33="",AO33=""),"",IF(AN33>AO33,"OK","LOW CONF")) | AS33: =IF(OR(AQ33="",AR33=""),"",IF(AQ33<AR33,"Decreased",IF(AQ33>AR33,"Increased","Flat")))
A34: VFC | B34: V.F. Corporation | C34: 46246 | D34: 3 | E34: M | F34: 3 | G34: M | H34: 3 | I34: M | J34: 2 | K34: M | L34: 3 | M34: M | N34: =IF(COUNT(D34,F34,H34,J34,L34)=0,"",(D34*0.2+F34*0.15+H34*0.15+J34*0.1+L34*0.1)/(IF(D34<>"",0.2,0)+IF(F34<>"",0.15,0)+IF(H34<>"",0.15,0)+IF(J34<>"",0.1,0)+IF(L34<>"",0.1,0))) -> 2.8571429 | O34: =IF(COUNT(D34,F34,H34,J34,L34)=0,"",D34*0.2+F34*0.15+H34*0.15+J34*0.1+L34*0.1) -> 2 | X34: =IF(COUNT(P34,R34,T34,V34)=0,"",P34*0.08+R34*0.06+T34*0.03+V34*0.08) | AE34: =IF(COUNT(Y34,AA34,AC34)=0,"",Y34*0.02+AA34*0.02+AC34*0.01) | AF34: =IF(OR(COUNT(D34,F34,H34,J34,L34)<5,COUNT(P34,R34,T34,V34)<4,COUNT(Y34,AA34,AC34)<3),"",(O34+X34+AE34)*20) | AG34: =IF(AF34="","",IF(AJ34="AVOID","AVOID",IF(AF34>=80,IF(AH34="FAIL","WATCH LIST",IF(AK34="CAP AT BUY","BUY","STRONG BUY")),IF(AF34>=65,IF(AH34="FAIL","WATCH LIST","BUY"),IF(AF34>=50,"WATCH LIST",IF(AF34>=35,"AVOID","PASS")))))) | AH34: =IF(N34="","",IF(N34<3,"FAIL","OK")) -> FAIL | AI34: =IF(COUNT(D34:L34)=0,"",IF(COUNTIF(D34:L34,1)>0,"REVIEW","OK")) -> OK | AJ34: =IF(COUNT(D34:L34)=0,"",IF(COUNTIF(D34:L34,"<=2")>=2,"AVOID","OK")) -> OK | AK34: =IF(COUNTA(E34:M34)=0,"",IF(COUNTIF(E34:M34,"L")>=2,"CAP AT BUY","OK")) -> OK | AL34: Consumer Cyclical | AM34: Apparel Manufacturing | AP34: =IF(OR(AN34="",AO34=""),"",IF(AN34>AO34,"OK","LOW CONF")) | AS34: =IF(OR(AQ34="",AR34=""),"",IF(AQ34<AR34,"Decreased",IF(AQ34>AR34,"Increased","Flat")))
A35: BABA | B35: Alibaba Group Holding Ltd. | C35: 46246 | D35: 2 | E35: M | F35: 3 | G35: H | H35: 4 | I35: M | J35: 3 | K35: M | L35: 2 | M35: H | N35: =IF(COUNT(D35,F35,H35,J35,L35)=0,"",(D35*0.2+F35*0.15+H35*0.15+J35*0.1+L35*0.1)/(IF(D35<>"",0.2,0)+IF(F35<>"",0.15,0)+IF(H35<>"",0.15,0)+IF(J35<>"",0.1,0)+IF(L35<>"",0.1,0))) -> 2.7857143 | O35: =IF(COUNT(D35,F35,H35,J35,L35)=0,"",D35*0.2+F35*0.15+H35*0.15+J35*0.1+L35*0.1) -> 1.95 | X35: =IF(COUNT(P35,R35,T35,V35)=0,"",P35*0.08+R35*0.06+T35*0.03+V35*0.08) | AE35: =IF(COUNT(Y35,AA35,AC35)=0,"",Y35*0.02+AA35*0.02+AC35*0.01) | AF35: =IF(OR(COUNT(D35,F35,H35,J35,L35)<5,COUNT(P35,R35,T35,V35)<4,COUNT(Y35,AA35,AC35)<3),"",(O35+X35+AE35)*20) | AG35: =IF(AF35="","",IF(AJ35="AVOID","AVOID",IF(AF35>=80,IF(AH35="FAIL","WATCH LIST",IF(AK35="CAP AT BUY","BUY","STRONG BUY")),IF(AF35>=65,IF(AH35="FAIL","WATCH LIST","BUY"),IF(AF35>=50,"WATCH LIST",IF(AF35>=35,"AVOID","PASS")))))) | AH35: =IF(N35="","",IF(N35<3,"FAIL","OK")) -> FAIL | AI35: =IF(COUNT(D35:L35)=0,"",IF(COUNTIF(D35:L35,1)>0,"REVIEW","OK")) -> OK | AJ35: =IF(COUNT(D35:L35)=0,"",IF(COUNTIF(D35:L35,"<=2")>=2,"AVOID","OK")) -> AVOID | AK35: =IF(COUNTA(E35:M35)=0,"",IF(COUNTIF(E35:M35,"L")>=2,"CAP AT BUY","OK")) -> OK | AL35: Consumer Cyclical | AM35: Internet Retail | AP35: =IF(OR(AN35="",AO35=""),"",IF(AN35>AO35,"OK","LOW CONF")) | AS35: =IF(OR(AQ35="",AR35=""),"",IF(AQ35<AR35,"Decreased",IF(AQ35>AR35,"Increased","Flat")))
A36: NOV | B36: NOV Inc. | C36: 46245 | D36: 3 | E36: M | F36: 2 | G36: H | H36: 3 | I36: M | J36: 3 | K36: M | L36: 2 | M36: H | N36: =IF(COUNT(D36,F36,H36,J36,L36)=0,"",(D36*0.2+F36*0.15+H36*0.15+J36*0.1+L36*0.1)/(IF(D36<>"",0.2,0)+IF(F36<>"",0.15,0)+IF(H36<>"",0.15,0)+IF(J36<>"",0.1,0)+IF(L36<>"",0.1,0))) -> 2.6428571 | O36: =IF(COUNT(D36,F36,H36,J36,L36)=0,"",D36*0.2+F36*0.15+H36*0.15+J36*0.1+L36*0.1) -> 1.85 | X36: =IF(COUNT(P36,R36,T36,V36)=0,"",P36*0.08+R36*0.06+T36*0.03+V36*0.08) | AE36: =IF(COUNT(Y36,AA36,AC36)=0,"",Y36*0.02+AA36*0.02+AC36*0.01) | AF36: =IF(OR(COUNT(D36,F36,H36,J36,L36)<5,COUNT(P36,R36,T36,V36)<4,COUNT(Y36,AA36,AC36)<3),"",(O36+X36+AE36)*20) | AG36: =IF(AF36="","",IF(AJ36="AVOID","AVOID",IF(AF36>=80,IF(AH36="FAIL","WATCH LIST",IF(AK36="CAP AT BUY","BUY","STRONG BUY")),IF(AF36>=65,IF(AH36="FAIL","WATCH LIST","BUY"),IF(AF36>=50,"WATCH LIST",IF(AF36>=35,"AVOID","PASS")))))) | AH36: =IF(N36="","",IF(N36<3,"FAIL","OK")) -> FAIL | AI36: =IF(COUNT(D36:L36)=0,"",IF(COUNTIF(D36:L36,1)>0,"REVIEW","OK")) -> OK | AJ36: =IF(COUNT(D36:L36)=0,"",IF(COUNTIF(D36:L36,"<=2")>=2,"AVOID","OK")) -> AVOID | AK36: =IF(COUNTA(E36:M36)=0,"",IF(COUNTIF(E36:M36,"L")>=2,"CAP AT BUY","OK")) -> OK | AL36: Energy | AM36: Oil & Gas Equipment & Services | AP36: =IF(OR(AN36="",AO36=""),"",IF(AN36>AO36,"OK","LOW CONF")) | AS36: =IF(OR(AQ36="",AR36=""),"",IF(AQ36<AR36,"Decreased",IF(AQ36>AR36,"Increased","Flat")))
A37: ONON | B37: On Holding AG | C37: 46240 | D37: 2 | E37: M | F37: 4 | G37: H | H37: 3 | I37: M | J37: 2 | K37: M | L37: 2 | M37: H | N37: =IF(COUNT(D37,F37,H37,J37,L37)=0,"",(D37*0.2+F37*0.15+H37*0.15+J37*0.1+L37*0.1)/(IF(D37<>"",0.2,0)+IF(F37<>"",0.15,0)+IF(H37<>"",0.15,0)+IF(J37<>"",0.1,0)+IF(L37<>"",0.1,0))) -> 2.6428571 | O37: =IF(COUNT(D37,F37,H37,J37,L37)=0,"",D37*0.2+F37*0.15+H37*0.15+J37*0.1+L37*0.1) -> 1.85 | X37: =IF(COUNT(P37,R37,T37,V37)=0,"",P37*0.08+R37*0.06+T37*0.03+V37*0.08) | AE37: =IF(COUNT(Y37,AA37,AC37)=0,"",Y37*0.02+AA37*0.02+AC37*0.01) | AF37: =IF(OR(COUNT(D37,F37,H37,J37,L37)<5,COUNT(P37,R37,T37,V37)<4,COUNT(Y37,AA37,AC37)<3),"",(O37+X37+AE37)*20) | AG37: =IF(AF37="","",IF(AJ37="AVOID","AVOID",IF(AF37>=80,IF(AH37="FAIL","WATCH LIST",IF(AK37="CAP AT BUY","BUY","STRONG BUY")),IF(AF37>=65,IF(AH37="FAIL","WATCH LIST","BUY"),IF(AF37>=50,"WATCH LIST",IF(AF37>=35,"AVOID","PASS")))))) | AH37: =IF(N37="","",IF(N37<3,"FAIL","OK")) -> FAIL | AI37: =IF(COUNT(D37:L37)=0,"",IF(COUNTIF(D37:L37,1)>0,"REVIEW","OK")) -> OK | AJ37: =IF(COUNT(D37:L37)=0,"",IF(COUNTIF(D37:L37,"<=2")>=2,"AVOID","OK")) -> AVOID | AK37: =IF(COUNTA(E37:M37)=0,"",IF(COUNTIF(E37:M37,"L")>=2,"CAP AT BUY","OK")) -> OK | AL37: Consumer Cyclical | AM37: Footwear & Accessories | AN37: 359500000 | AO37: 203700000 | AP37: =IF(OR(AN37="",AO37=""),"",IF(AN37>AO37,"OK","LOW CONF")) -> OK | AQ37: 1.857 | AR37: 0.78 | AS37: =IF(OR(AQ37="",AR37=""),"",IF(AQ37<AR37,"Decreased",IF(AQ37>AR37,"Increased","Flat"))) -> Increased
A38: NEE | B38: NextEra Energy Inc. | C38: 46245 | D38: 1 | E38: H | F38: 3 | G38: M | H38: 4 | I38: M | J38: 4 | K38: M | L38: 1 | M38: H | N38: =IF(COUNT(D38,F38,H38,J38,L38)=0,"",(D38*0.2+F38*0.15+H38*0.15+J38*0.1+L38*0.1)/(IF(D38<>"",0.2,0)+IF(F38<>"",0.15,0)+IF(H38<>"",0.15,0)+IF(J38<>"",0.1,0)+IF(L38<>"",0.1,0))) -> 2.5 | O38: =IF(COUNT(D38,F38,H38,J38,L38)=0,"",D38*0.2+F38*0.15+H38*0.15+J38*0.1+L38*0.1) -> 1.75 | X38: =IF(COUNT(P38,R38,T38,V38)=0,"",P38*0.08+R38*0.06+T38*0.03+V38*0.08) | AE38: =IF(COUNT(Y38,AA38,AC38)=0,"",Y38*0.02+AA38*0.02+AC38*0.01) | AF38: =IF(OR(COUNT(D38,F38,H38,J38,L38)<5,COUNT(P38,R38,T38,V38)<4,COUNT(Y38,AA38,AC38)<3),"",(O38+X38+AE38)*20) | AG38: =IF(AF38="","",IF(AJ38="AVOID","AVOID",IF(AF38>=80,IF(AH38="FAIL","WATCH LIST",IF(AK38="CAP AT BUY","BUY","STRONG BUY")),IF(AF38>=65,IF(AH38="FAIL","WATCH LIST","BUY"),IF(AF38>=50,"WATCH LIST",IF(AF38>=35,"AVOID","PASS")))))) | AH38: =IF(N38="","",IF(N38<3,"FAIL","OK")) -> FAIL | AI38: =IF(COUNT(D38:L38)=0,"",IF(COUNTIF(D38:L38,1)>0,"REVIEW","OK")) -> REVIEW | AJ38: =IF(COUNT(D38:L38)=0,"",IF(COUNTIF(D38:L38,"<=2")>=2,"AVOID","OK")) -> AVOID | AK38: =IF(COUNTA(E38:M38)=0,"",IF(COUNTIF(E38:M38,"L")>=2,"CAP AT BUY","OK")) -> OK | AL38: Utilities | AM38: Utilities - Regulated Electric | AP38: =IF(OR(AN38="",AO38=""),"",IF(AN38>AO38,"OK","LOW CONF")) | AS38: =IF(OR(AQ38="",AR38=""),"",IF(AQ38<AR38,"Decreased",IF(AQ38>AR38,"Increased","Flat")))
A39: GOOS | B39: Canada Goose Holdings | C39: 46246 | D39: 2 | E39: L | F39: 4 | G39: H | H39: 3 | I39: M | J39: 2 | K39: M | L39: 1 | M39: H | N39: =IF(COUNT(D39,F39,H39,J39,L39)=0,"",(D39*0.2+F39*0.15+H39*0.15+J39*0.1+L39*0.1)/(IF(D39<>"",0.2,0)+IF(F39<>"",0.15,0)+IF(H39<>"",0.15,0)+IF(J39<>"",0.1,0)+IF(L39<>"",0.1,0))) -> 2.5 | O39: =IF(COUNT(D39,F39,H39,J39,L39)=0,"",D39*0.2+F39*0.15+H39*0.15+J39*0.1+L39*0.1) -> 1.75 | X39: =IF(COUNT(P39,R39,T39,V39)=0,"",P39*0.08+R39*0.06+T39*0.03+V39*0.08) | AE39: =IF(COUNT(Y39,AA39,AC39)=0,"",Y39*0.02+AA39*0.02+AC39*0.01) | AF39: =IF(OR(COUNT(D39,F39,H39,J39,L39)<5,COUNT(P39,R39,T39,V39)<4,COUNT(Y39,AA39,AC39)<3),"",(O39+X39+AE39)*20) | AG39: =IF(AF39="","",IF(AJ39="AVOID","AVOID",IF(AF39>=80,IF(AH39="FAIL","WATCH LIST",IF(AK39="CAP AT BUY","BUY","STRONG BUY")),IF(AF39>=65,IF(AH39="FAIL","WATCH LIST","BUY"),IF(AF39>=50,"WATCH LIST",IF(AF39>=35,"AVOID","PASS")))))) | AH39: =IF(N39="","",IF(N39<3,"FAIL","OK")) -> FAIL | AI39: =IF(COUNT(D39:L39)=0,"",IF(COUNTIF(D39:L39,1)>0,"REVIEW","OK")) -> REVIEW | AJ39: =IF(COUNT(D39:L39)=0,"",IF(COUNTIF(D39:L39,"<=2")>=2,"AVOID","OK")) -> AVOID | AK39: =IF(COUNTA(E39:M39)=0,"",IF(COUNTIF(E39:M39,"L")>=2,"CAP AT BUY","OK")) -> OK | AL39: Consumer Cyclical | AM39: Apparel Manufacturing | AP39: =IF(OR(AN39="",AO39=""),"",IF(AN39>AO39,"OK","LOW CONF")) | AS39: =IF(OR(AQ39="",AR39=""),"",IF(AQ39<AR39,"Decreased",IF(AQ39>AR39,"Increased","Flat")))
A40: DEO | B40: Diageo plc | C40: 46245 | D40: 2 | E40: M | F40: 2 | G40: M | H40: 3 | I40: M | J40: 3 | K40: M | L40: 2 | M40: H | N40: =IF(COUNT(D40,F40,H40,J40,L40)=0,"",(D40*0.2+F40*0.15+H40*0.15+J40*0.1+L40*0.1)/(IF(D40<>"",0.2,0)+IF(F40<>"",0.15,0)+IF(H40<>"",0.15,0)+IF(J40<>"",0.1,0)+IF(L40<>"",0.1,0))) -> 2.3571429 | O40: =IF(COUNT(D40,F40,H40,J40,L40)=0,"",D40*0.2+F40*0.15+H40*0.15+J40*0.1+L40*0.1) -> 1.65 | X40: =IF(COUNT(P40,R40,T40,V40)=0,"",P40*0.08+R40*0.06+T40*0.03+V40*0.08) | AE40: =IF(COUNT(Y40,AA40,AC40)=0,"",Y40*0.02+AA40*0.02+AC40*0.01) | AF40: =IF(OR(COUNT(D40,F40,H40,J40,L40)<5,COUNT(P40,R40,T40,V40)<4,COUNT(Y40,AA40,AC40)<3),"",(O40+X40+AE40)*20) | AG40: =IF(AF40="","",IF(AJ40="AVOID","AVOID",IF(AF40>=80,IF(AH40="FAIL","WATCH LIST",IF(AK40="CAP AT BUY","BUY","STRONG BUY")),IF(AF40>=65,IF(AH40="FAIL","WATCH LIST","BUY"),IF(AF40>=50,"WATCH LIST",IF(AF40>=35,"AVOID","PASS")))))) | AH40: =IF(N40="","",IF(N40<3,"FAIL","OK")) -> FAIL | AI40: =IF(COUNT(D40:L40)=0,"",IF(COUNTIF(D40:L40,1)>0,"REVIEW","OK")) -> OK | AJ40: =IF(COUNT(D40:L40)=0,"",IF(COUNTIF(D40:L40,"<=2")>=2,"AVOID","OK")) -> AVOID | AK40: =IF(COUNTA(E40:M40)=0,"",IF(COUNTIF(E40:M40,"L")>=2,"CAP AT BUY","OK")) -> OK | AL40: Consumer Defensive | AM40: Beverages - Wineries & Distilleries | AP40: =IF(OR(AN40="",AO40=""),"",IF(AN40>AO40,"OK","LOW CONF")) | AS40: =IF(OR(AQ40="",AR40=""),"",IF(AQ40<AR40,"Decreased",IF(AQ40>AR40,"Increased","Flat")))
A41: EL | B41: Estee Lauder Companies | C41: 46245 | D41: 2 | E41: M | F41: 1 | G41: H | H41: 3 | I41: M | J41: 2 | K41: M | L41: 3 | M41: M | N41: =IF(COUNT(D41,F41,H41,J41,L41)=0,"",(D41*0.2+F41*0.15+H41*0.15+J41*0.1+L41*0.1)/(IF(D41<>"",0.2,0)+IF(F41<>"",0.15,0)+IF(H41<>"",0.15,0)+IF(J41<>"",0.1,0)+IF(L41<>"",0.1,0))) -> 2.1428571 | O41: =IF(COUNT(D41,F41,H41,J41,L41)=0,"",D41*0.2+F41*0.15+H41*0.15+J41*0.1+L41*0.1) -> 1.5 | X41: =IF(COUNT(P41,R41,T41,V41)=0,"",P41*0.08+R41*0.06+T41*0.03+V41*0.08) | AE41: =IF(COUNT(Y41,AA41,AC41)=0,"",Y41*0.02+AA41*0.02+AC41*0.01) | AF41: =IF(OR(COUNT(D41,F41,H41,J41,L41)<5,COUNT(P41,R41,T41,V41)<4,COUNT(Y41,AA41,AC41)<3),"",(O41+X41+AE41)*20) | AG41: =IF(AF41="","",IF(AJ41="AVOID","AVOID",IF(AF41>=80,IF(AH41="FAIL","WATCH LIST",IF(AK41="CAP AT BUY","BUY","STRONG BUY")),IF(AF41>=65,IF(AH41="FAIL","WATCH LIST","BUY"),IF(AF41>=50,"WATCH LIST",IF(AF41>=35,"AVOID","PASS")))))) | AH41: =IF(N41="","",IF(N41<3,"FAIL","OK")) -> FAIL | AI41: =IF(COUNT(D41:L41)=0,"",IF(COUNTIF(D41:L41,1)>0,"REVIEW","OK")) -> REVIEW | AJ41: =IF(COUNT(D41:L41)=0,"",IF(COUNTIF(D41:L41,"<=2")>=2,"AVOID","OK")) -> AVOID | AK41: =IF(COUNTA(E41:M41)=0,"",IF(COUNTIF(E41:M41,"L")>=2,"CAP AT BUY","OK")) -> OK | AL41: Consumer Defensive | AM41: Household & Personal Products | AP41: =IF(OR(AN41="",AO41=""),"",IF(AN41>AO41,"OK","LOW CONF")) | AS41: =IF(OR(AQ41="",AR41=""),"",IF(AQ41<AR41,"Decreased",IF(AQ41>AR41,"Increased","Flat")))
A42: LBRT | B42: Liberty Energy Inc. | C42: 46245 | D42: 2 | E42: L | F42: 2 | G42: M | H42: 3 | I42: M | J42: 2 | K42: M | L42: 1 | M42: H | N42: =IF(COUNT(D42,F42,H42,J42,L42)=0,"",(D42*0.2+F42*0.15+H42*0.15+J42*0.1+L42*0.1)/(IF(D42<>"",0.2,0)+IF(F42<>"",0.15,0)+IF(H42<>"",0.15,0)+IF(J42<>"",0.1,0)+IF(L42<>"",0.1,0))) -> 2.0714286 | O42: =IF(COUNT(D42,F42,H42,J42,L42)=0,"",D42*0.2+F42*0.15+H42*0.15+J42*0.1+L42*0.1) -> 1.45 | X42: =IF(COUNT(P42,R42,T42,V42)=0,"",P42*0.08+R42*0.06+T42*0.03+V42*0.08) | AE42: =IF(COUNT(Y42,AA42,AC42)=0,"",Y42*0.02+AA42*0.02+AC42*0.01) | AF42: =IF(OR(COUNT(D42,F42,H42,J42,L42)<5,COUNT(P42,R42,T42,V42)<4,COUNT(Y42,AA42,AC42)<3),"",(O42+X42+AE42)*20) | AG42: =IF(AF42="","",IF(AJ42="AVOID","AVOID",IF(AF42>=80,IF(AH42="FAIL","WATCH LIST",IF(AK42="CAP AT BUY","BUY","STRONG BUY")),IF(AF42>=65,IF(AH42="FAIL","WATCH LIST","BUY"),IF(AF42>=50,"WATCH LIST",IF(AF42>=35,"AVOID","PASS")))))) | AH42: =IF(N42="","",IF(N42<3,"FAIL","OK")) -> FAIL | AI42: =IF(COUNT(D42:L42)=0,"",IF(COUNTIF(D42:L42,1)>0,"REVIEW","OK")) -> REVIEW | AJ42: =IF(COUNT(D42:L42)=0,"",IF(COUNTIF(D42:L42,"<=2")>=2,"AVOID","OK")) -> AVOID | AK42: =IF(COUNTA(E42:M42)=0,"",IF(COUNTIF(E42:M42,"L")>=2,"CAP AT BUY","OK")) -> OK | AL42: Energy | AM42: Oil & Gas Equipment & Services | AP42: =IF(OR(AN42="",AO42=""),"",IF(AN42>AO42,"OK","LOW CONF")) | AS42: =IF(OR(AQ42="",AR42=""),"",IF(AQ42<AR42,"Decreased",IF(AQ42>AR42,"Increased","Flat")))
A43: TSLA | B43: Tesla Inc. | C43: 46240 | D43: 1 | E43: H | F43: 2 | G43: M | H43: 3 | I43: M | J43: 3 | K43: M | L43: 1 | M43: H | N43: =IF(COUNT(D43,F43,H43,J43,L43)=0,"",(D43*0.2+F43*0.15+H43*0.15+J43*0.1+L43*0.1)/(IF(D43<>"",0.2,0)+IF(F43<>"",0.15,0)+IF(H43<>"",0.15,0)+IF(J43<>"",0.1,0)+IF(L43<>"",0.1,0))) -> 1.9285714 | O43: =IF(COUNT(D43,F43,H43,J43,L43)=0,"",D43*0.2+F43*0.15+H43*0.15+J43*0.1+L43*0.1) -> 1.35 | X43: =IF(COUNT(P43,R43,T43,V43)=0,"",P43*0.08+R43*0.06+T43*0.03+V43*0.08) | AE43: =IF(COUNT(Y43,AA43,AC43)=0,"",Y43*0.02+AA43*0.02+AC43*0.01) | AF43: =IF(OR(COUNT(D43,F43,H43,J43,L43)<5,COUNT(P43,R43,T43,V43)<4,COUNT(Y43,AA43,AC43)<3),"",(O43+X43+AE43)*20) | AG43: =IF(AF43="","",IF(AJ43="AVOID","AVOID",IF(AF43>=80,IF(AH43="FAIL","WATCH LIST",IF(AK43="CAP AT BUY","BUY","STRONG BUY")),IF(AF43>=65,IF(AH43="FAIL","WATCH LIST","BUY"),IF(AF43>=50,"WATCH LIST",IF(AF43>=35,"AVOID","PASS")))))) | AH43: =IF(N43="","",IF(N43<3,"FAIL","OK")) -> FAIL | AI43: =IF(COUNT(D43:L43)=0,"",IF(COUNTIF(D43:L43,1)>0,"REVIEW","OK")) -> REVIEW | AJ43: =IF(COUNT(D43:L43)=0,"",IF(COUNTIF(D43:L43,"<=2")>=2,"AVOID","OK")) -> AVOID | AK43: =IF(COUNTA(E43:M43)=0,"",IF(COUNTIF(E43:M43,"L")>=2,"CAP AT BUY","OK")) -> OK | AL43: Consumer Cyclical | AM43: Auto Manufacturers | AN43: 14747000000 | AO43: 3794000000 | AP43: =IF(OR(AN43="",AO43=""),"",IF(AN43>AO43,"OK","LOW CONF")) -> OK | AQ43: 2.366 | AR43: 3.804 | AS43: =IF(OR(AQ43="",AR43=""),"",IF(AQ43<AR43,"Decreased",IF(AQ43>AR43,"Increased","Flat"))) -> Decreased
A44: HRL | B44: Hormel Foods Corp. | C44: 46245 | D44: 1 | E44: H | F44: 2 | G44: M | H44: 3 | I44: M | J44: 3 | K44: M | L44: 1 | M44: H | N44: =IF(COUNT(D44,F44,H44,J44,L44)=0,"",(D44*0.2+F44*0.15+H44*0.15+J44*0.1+L44*0.1)/(IF(D44<>"",0.2,0)+IF(F44<>"",0.15,0)+IF(H44<>"",0.15,0)+IF(J44<>"",0.1,0)+IF(L44<>"",0.1,0))) -> 1.9285714 | O44: =IF(COUNT(D44,F44,H44,J44,L44)=0,"",D44*0.2+F44*0.15+H44*0.15+J44*0.1+L44*0.1) -> 1.35 | X44: =IF(COUNT(P44,R44,T44,V44)=0,"",P44*0.08+R44*0.06+T44*0.03+V44*0.08) | AE44: =IF(COUNT(Y44,AA44,AC44)=0,"",Y44*0.02+AA44*0.02+AC44*0.01) | AF44: =IF(OR(COUNT(D44,F44,H44,J44,L44)<5,COUNT(P44,R44,T44,V44)<4,COUNT(Y44,AA44,AC44)<3),"",(O44+X44+AE44)*20) | AG44: =IF(AF44="","",IF(AJ44="AVOID","AVOID",IF(AF44>=80,IF(AH44="FAIL","WATCH LIST",IF(AK44="CAP AT BUY","BUY","STRONG BUY")),IF(AF44>=65,IF(AH44="FAIL","WATCH LIST","BUY"),IF(AF44>=50,"WATCH LIST",IF(AF44>=35,"AVOID","PASS")))))) | AH44: =IF(N44="","",IF(N44<3,"FAIL","OK")) -> FAIL | AI44: =IF(COUNT(D44:L44)=0,"",IF(COUNTIF(D44:L44,1)>0,"REVIEW","OK")) -> REVIEW | AJ44: =IF(COUNT(D44:L44)=0,"",IF(COUNTIF(D44:L44,"<=2")>=2,"AVOID","OK")) -> AVOID | AK44: =IF(COUNTA(E44:M44)=0,"",IF(COUNTIF(E44:M44,"L")>=2,"CAP AT BUY","OK")) -> OK | AL44: Consumer Defensive | AM44: Packaged Foods | AP44: =IF(OR(AN44="",AO44=""),"",IF(AN44>AO44,"OK","LOW CONF")) | AS44: =IF(OR(AQ44="",AR44=""),"",IF(AQ44<AR44,"Decreased",IF(AQ44>AR44,"Increased","Flat")))
A45: SFM | B45: Sprouts Farmers Market | C45: 46240 | D45: 2 | E45: M | F45: 2 | G45: M | H45: 2 | I45: M | J45: 2 | K45: M | L45: 1 | M45: H | N45: =IF(COUNT(D45,F45,H45,J45,L45)=0,"",(D45*0.2+F45*0.15+H45*0.15+J45*0.1+L45*0.1)/(IF(D45<>"",0.2,0)+IF(F45<>"",0.15,0)+IF(H45<>"",0.15,0)+IF(J45<>"",0.1,0)+IF(L45<>"",0.1,0))) -> 1.8571429 | O45: =IF(COUNT(D45,F45,H45,J45,L45)=0,"",D45*0.2+F45*0.15+H45*0.15+J45*0.1+L45*0.1) -> 1.3 | X45: =IF(COUNT(P45,R45,T45,V45)=0,"",P45*0.08+R45*0.06+T45*0.03+V45*0.08) | AE45: =IF(COUNT(Y45,AA45,AC45)=0,"",Y45*0.02+AA45*0.02+AC45*0.01) | AF45: =IF(OR(COUNT(D45,F45,H45,J45,L45)<5,COUNT(P45,R45,T45,V45)<4,COUNT(Y45,AA45,AC45)<3),"",(O45+X45+AE45)*20) | AG45: =IF(AF45="","",IF(AJ45="AVOID","AVOID",IF(AF45>=80,IF(AH45="FAIL","WATCH LIST",IF(AK45="CAP AT BUY","BUY","STRONG BUY")),IF(AF45>=65,IF(AH45="FAIL","WATCH LIST","BUY"),IF(AF45>=50,"WATCH LIST",IF(AF45>=35,"AVOID","PASS")))))) | AH45: =IF(N45="","",IF(N45<3,"FAIL","OK")) -> FAIL | AI45: =IF(COUNT(D45:L45)=0,"",IF(COUNTIF(D45:L45,1)>0,"REVIEW","OK")) -> REVIEW | AJ45: =IF(COUNT(D45:L45)=0,"",IF(COUNTIF(D45:L45,"<=2")>=2,"AVOID","OK")) -> AVOID | AK45: =IF(COUNTA(E45:M45)=0,"",IF(COUNTIF(E45:M45,"L")>=2,"CAP AT BUY","OK")) -> OK | AL45: Consumer Defensive | AM45: Grocery Stores | AN45: 715998000 | AO45: 523670000 | AP45: =IF(OR(AN45="",AO45=""),"",IF(AN45>AO45,"OK","LOW CONF")) -> OK | AQ45: 4.155 | AR45: 4.048 | AS45: =IF(OR(AQ45="",AR45=""),"",IF(AQ45<AR45,"Decreased",IF(AQ45>AR45,"Increased","Flat"))) -> Increased
A46: CLF | B46: Cleveland-Cliffs Inc. | C46: 46245 | D46: 2 | E46: H | F46: 2 | G46: M | H46: 2 | I46: M | J46: 2 | K46: M | L46: 1 | M46: H | N46: =IF(COUNT(D46,F46,H46,J46,L46)=0,"",(D46*0.2+F46*0.15+H46*0.15+J46*0.1+L46*0.1)/(IF(D46<>"",0.2,0)+IF(F46<>"",0.15,0)+IF(H46<>"",0.15,0)+IF(J46<>"",0.1,0)+IF(L46<>"",0.1,0))) -> 1.8571429 | O46: =IF(COUNT(D46,F46,H46,J46,L46)=0,"",D46*0.2+F46*0.15+H46*0.15+J46*0.1+L46*0.1) -> 1.3 | X46: =IF(COUNT(P46,R46,T46,V46)=0,"",P46*0.08+R46*0.06+T46*0.03+V46*0.08) | AE46: =IF(COUNT(Y46,AA46,AC46)=0,"",Y46*0.02+AA46*0.02+AC46*0.01) | AF46: =IF(OR(COUNT(D46,F46,H46,J46,L46)<5,COUNT(P46,R46,T46,V46)<4,COUNT(Y46,AA46,AC46)<3),"",(O46+X46+AE46)*20) | AG46: =IF(AF46="","",IF(AJ46="AVOID","AVOID",IF(AF46>=80,IF(AH46="FAIL","WATCH LIST",IF(AK46="CAP AT BUY","BUY","STRONG BUY")),IF(AF46>=65,IF(AH46="FAIL","WATCH LIST","BUY"),IF(AF46>=50,"WATCH LIST",IF(AF46>=35,"AVOID","PASS")))))) | AH46: =IF(N46="","",IF(N46<3,"FAIL","OK")) -> FAIL | AI46: =IF(COUNT(D46:L46)=0,"",IF(COUNTIF(D46:L46,1)>0,"REVIEW","OK")) -> REVIEW | AJ46: =IF(COUNT(D46:L46)=0,"",IF(COUNTIF(D46:L46,"<=2")>=2,"AVOID","OK")) -> AVOID | AK46: =IF(COUNTA(E46:M46)=0,"",IF(COUNTIF(E46:M46,"L")>=2,"CAP AT BUY","OK")) -> OK | AL46: Basic Materials | AM46: Steel | AP46: =IF(OR(AN46="",AO46=""),"",IF(AN46>AO46,"OK","LOW CONF")) | AS46: =IF(OR(AQ46="",AR46=""),"",IF(AQ46<AR46,"Decreased",IF(AQ46>AR46,"Increased","Flat")))
A47: CE | B47: Celanese Corp. | C47: 46245 | D47: 2 | E47: M | F47: 1 | G47: H | H47: 2 | I47: M | J47: 2 | K47: M | L47: 2 | M47: M | N47: =IF(COUNT(D47,F47,H47,J47,L47)=0,"",(D47*0.2+F47*0.15+H47*0.15+J47*0.1+L47*0.1)/(IF(D47<>"",0.2,0)+IF(F47<>"",0.15,0)+IF(H47<>"",0.15,0)+IF(J47<>"",0.1,0)+IF(L47<>"",0.1,0))) -> 1.7857143 | O47: =IF(COUNT(D47,F47,H47,J47,L47)=0,"",D47*0.2+F47*0.15+H47*0.15+J47*0.1+L47*0.1) -> 1.25 | X47: =IF(COUNT(P47,R47,T47,V47)=0,"",P47*0.08+R47*0.06+T47*0.03+V47*0.08) | AE47: =IF(COUNT(Y47,AA47,AC47)=0,"",Y47*0.02+AA47*0.02+AC47*0.01) | AF47: =IF(OR(COUNT(D47,F47,H47,J47,L47)<5,COUNT(P47,R47,T47,V47)<4,COUNT(Y47,AA47,AC47)<3),"",(O47+X47+AE47)*20) | AG47: =IF(AF47="","",IF(AJ47="AVOID","AVOID",IF(AF47>=80,IF(AH47="FAIL","WATCH LIST",IF(AK47="CAP AT BUY","BUY","STRONG BUY")),IF(AF47>=65,IF(AH47="FAIL","WATCH LIST","BUY"),IF(AF47>=50,"WATCH LIST",IF(AF47>=35,"AVOID","PASS")))))) | AH47: =IF(N47="","",IF(N47<3,"FAIL","OK")) -> FAIL | AI47: =IF(COUNT(D47:L47)=0,"",IF(COUNTIF(D47:L47,1)>0,"REVIEW","OK")) -> REVIEW | AJ47: =IF(COUNT(D47:L47)=0,"",IF(COUNTIF(D47:L47,"<=2")>=2,"AVOID","OK")) -> AVOID | AK47: =IF(COUNTA(E47:M47)=0,"",IF(COUNTIF(E47:M47,"L")>=2,"CAP AT BUY","OK")) -> OK | AL47: Basic Materials | AM47: Chemicals | AP47: =IF(OR(AN47="",AO47=""),"",IF(AN47>AO47,"OK","LOW CONF")) | AS47: =IF(OR(AQ47="",AR47=""),"",IF(AQ47<AR47,"Decreased",IF(AQ47>AR47,"Increased","Flat")))
A48: NKE | B48: Nike Inc. | C48: 46246 | D48: 1 | E48: H | F48: 1 | G48: H | H48: 3 | I48: M | J48: 2 | K48: M | L48: 1 | M48: H | N48: =IF(COUNT(D48,F48,H48,J48,L48)=0,"",(D48*0.2+F48*0.15+H48*0.15+J48*0.1+L48*0.1)/(IF(D48<>"",0.2,0)+IF(F48<>"",0.15,0)+IF(H48<>"",0.15,0)+IF(J48<>"",0.1,0)+IF(L48<>"",0.1,0))) -> 1.5714286 | O48: =IF(COUNT(D48,F48,H48,J48,L48)=0,"",D48*0.2+F48*0.15+H48*0.15+J48*0.1+L48*0.1) -> 1.1 | X48: =IF(COUNT(P48,R48,T48,V48)=0,"",P48*0.08+R48*0.06+T48*0.03+V48*0.08) | AE48: =IF(COUNT(Y48,AA48,AC48)=0,"",Y48*0.02+AA48*0.02+AC48*0.01) | AF48: =IF(OR(COUNT(D48,F48,H48,J48,L48)<5,COUNT(P48,R48,T48,V48)<4,COUNT(Y48,AA48,AC48)<3),"",(O48+X48+AE48)*20) | AG48: =IF(AF48="","",IF(AJ48="AVOID","AVOID",IF(AF48>=80,IF(AH48="FAIL","WATCH LIST",IF(AK48="CAP AT BUY","BUY","STRONG BUY")),IF(AF48>=65,IF(AH48="FAIL","WATCH LIST","BUY"),IF(AF48>=50,"WATCH LIST",IF(AF48>=35,"AVOID","PASS")))))) | AH48: =IF(N48="","",IF(N48<3,"FAIL","OK")) -> FAIL | AI48: =IF(COUNT(D48:L48)=0,"",IF(COUNTIF(D48:L48,1)>0,"REVIEW","OK")) -> REVIEW | AJ48: =IF(COUNT(D48:L48)=0,"",IF(COUNTIF(D48:L48,"<=2")>=2,"AVOID","OK")) -> AVOID | AK48: =IF(COUNTA(E48:M48)=0,"",IF(COUNTIF(E48:M48,"L")>=2,"CAP AT BUY","OK")) -> OK | AL48: Consumer Cyclical | AM48: Footwear & Accessories | AP48: =IF(OR(AN48="",AO48=""),"",IF(AN48>AO48,"OK","LOW CONF")) | AS48: =IF(OR(AQ48="",AR48=""),"",IF(AQ48<AR48,"Decreased",IF(AQ48>AR48,"Increased","Flat")))
A49: PZZA | B49: Papa John's Intl. | C49: 46245 | D49: 1 | E49: H | F49: 1 | G49: H | H49: 2 | I49: M | J49: 2 | K49: M | L49: 1 | M49: H | N49: =IF(COUNT(D49,F49,H49,J49,L49)=0,"",(D49*0.2+F49*0.15+H49*0.15+J49*0.1+L49*0.1)/(IF(D49<>"",0.2,0)+IF(F49<>"",0.15,0)+IF(H49<>"",0.15,0)+IF(J49<>"",0.1,0)+IF(L49<>"",0.1,0))) -> 1.3571429 | O49: =IF(COUNT(D49,F49,H49,J49,L49)=0,"",D49*0.2+F49*0.15+H49*0.15+J49*0.1+L49*0.1) -> 0.95 | X49: =IF(COUNT(P49,R49,T49,V49)=0,"",P49*0.08+R49*0.06+T49*0.03+V49*0.08) | AE49: =IF(COUNT(Y49,AA49,AC49)=0,"",Y49*0.02+AA49*0.02+AC49*0.01) | AF49: =IF(OR(COUNT(D49,F49,H49,J49,L49)<5,COUNT(P49,R49,T49,V49)<4,COUNT(Y49,AA49,AC49)<3),"",(O49+X49+AE49)*20) | AG49: =IF(AF49="","",IF(AJ49="AVOID","AVOID",IF(AF49>=80,IF(AH49="FAIL","WATCH LIST",IF(AK49="CAP AT BUY","BUY","STRONG BUY")),IF(AF49>=65,IF(AH49="FAIL","WATCH LIST","BUY"),IF(AF49>=50,"WATCH LIST",IF(AF49>=35,"AVOID","PASS")))))) | AH49: =IF(N49="","",IF(N49<3,"FAIL","OK")) -> FAIL | AI49: =IF(COUNT(D49:L49)=0,"",IF(COUNTIF(D49:L49,1)>0,"REVIEW","OK")) -> REVIEW | AJ49: =IF(COUNT(D49:L49)=0,"",IF(COUNTIF(D49:L49,"<=2")>=2,"AVOID","OK")) -> AVOID | AK49: =IF(COUNTA(E49:M49)=0,"",IF(COUNTIF(E49:M49,"L")>=2,"CAP AT BUY","OK")) -> OK | AL49: Consumer Cyclical | AM49: Restaurants | AP49: =IF(OR(AN49="",AO49=""),"",IF(AN49>AO49,"OK","LOW CONF")) | AS49: =IF(OR(AQ49="",AR49=""),"",IF(AQ49<AR49,"Decreased",IF(AQ49>AR49,"Increased","Flat")))
A50: AAP | B50: Advance Auto Parts Inc. | C50: 46246 | D50: 1 | E50: H | F50: 1 | G50: H | H50: 2 | I50: M | J50: 2 | K50: M | L50: 1 | M50: H | N50: =IF(COUNT(D50,F50,H50,J50,L50)=0,"",(D50*0.2+F50*0.15+H50*0.15+J50*0.1+L50*0.1)/(IF(D50<>"",0.2,0)+IF(F50<>"",0.15,0)+IF(H50<>"",0.15,0)+IF(J50<>"",0.1,0)+IF(L50<>"",0.1,0))) -> 1.3571429 | O50: =IF(COUNT(D50,F50,H50,J50,L50)=0,"",D50*0.2+F50*0.15+H50*0.15+J50*0.1+L50*0.1) -> 0.95 | X50: =IF(COUNT(P50,R50,T50,V50)=0,"",P50*0.08+R50*0.06+T50*0.03+V50*0.08) | AE50: =IF(COUNT(Y50,AA50,AC50)=0,"",Y50*0.02+AA50*0.02+AC50*0.01) | AF50: =IF(OR(COUNT(D50,F50,H50,J50,L50)<5,COUNT(P50,R50,T50,V50)<4,COUNT(Y50,AA50,AC50)<3),"",(O50+X50+AE50)*20) | AG50: =IF(AF50="","",IF(AJ50="AVOID","AVOID",IF(AF50>=80,IF(AH50="FAIL","WATCH LIST",IF(AK50="CAP AT BUY","BUY","STRONG BUY")),IF(AF50>=65,IF(AH50="FAIL","WATCH LIST","BUY"),IF(AF50>=50,"WATCH LIST",IF(AF50>=35,"AVOID","PASS")))))) | AH50: =IF(N50="","",IF(N50<3,"FAIL","OK")) -> FAIL | AI50: =IF(COUNT(D50:L50)=0,"",IF(COUNTIF(D50:L50,1)>0,"REVIEW","OK")) -> REVIEW | AJ50: =IF(COUNT(D50:L50)=0,"",IF(COUNTIF(D50:L50,"<=2")>=2,"AVOID","OK")) -> AVOID | AK50: =IF(COUNTA(E50:M50)=0,"",IF(COUNTIF(E50:M50,"L")>=2,"CAP AT BUY","OK")) -> OK | AL50: Consumer Cyclical | AM50: Auto Parts | AP50: =IF(OR(AN50="",AO50=""),"",IF(AN50>AO50,"OK","LOW CONF")) | AS50: =IF(OR(AQ50="",AR50=""),"",IF(AQ50<AR50,"Decreased",IF(AQ50>AR50,"Increased","Flat")))
A51: CRK | B51: Comstock Resources Inc. | C51: 46245 | D51: 1 | E51: H | F51: 1 | G51: H | H51: 2 | I51: M | J51: 1 | K51: H | L51: 1 | M51: H | N51: =IF(COUNT(D51,F51,H51,J51,L51)=0,"",(D51*0.2+F51*0.15+H51*0.15+J51*0.1+L51*0.1)/(IF(D51<>"",0.2,0)+IF(F51<>"",0.15,0)+IF(H51<>"",0.15,0)+IF(J51<>"",0.1,0)+IF(L51<>"",0.1,0))) -> 1.2142857 | O51: =IF(COUNT(D51,F51,H51,J51,L51)=0,"",D51*0.2+F51*0.15+H51*0.15+J51*0.1+L51*0.1) -> 0.85 | X51: =IF(COUNT(P51,R51,T51,V51)=0,"",P51*0.08+R51*0.06+T51*0.03+V51*0.08) | AE51: =IF(COUNT(Y51,AA51,AC51)=0,"",Y51*0.02+AA51*0.02+AC51*0.01) | AF51: =IF(OR(COUNT(D51,F51,H51,J51,L51)<5,COUNT(P51,R51,T51,V51)<4,COUNT(Y51,AA51,AC51)<3),"",(O51+X51+AE51)*20) | AG51: =IF(AF51="","",IF(AJ51="AVOID","AVOID",IF(AF51>=80,IF(AH51="FAIL","WATCH LIST",IF(AK51="CAP AT BUY","BUY","STRONG BUY")),IF(AF51>=65,IF(AH51="FAIL","WATCH LIST","BUY"),IF(AF51>=50,"WATCH LIST",IF(AF51>=35,"AVOID","PASS")))))) | AH51: =IF(N51="","",IF(N51<3,"FAIL","OK")) -> FAIL | AI51: =IF(COUNT(D51:L51)=0,"",IF(COUNTIF(D51:L51,1)>0,"REVIEW","OK")) -> REVIEW | AJ51: =IF(COUNT(D51:L51)=0,"",IF(COUNTIF(D51:L51,"<=2")>=2,"AVOID","OK")) -> AVOID | AK51: =IF(COUNTA(E51:M51)=0,"",IF(COUNTIF(E51:M51,"L")>=2,"CAP AT BUY","OK")) -> OK | AL51: Energy | AM51: Oil & Gas E&P | AP51: =IF(OR(AN51="",AO51=""),"",IF(AN51>AO51,"OK","LOW CONF")) | AS51: =IF(OR(AQ51="",AR51=""),"",IF(AQ51<AR51,"Decreased",IF(AQ51>AR51,"Increased","Flat")))
