Workbook

Sheet Instructions
A1: THE LANDRY FAMILY EQUITY INVESTMENT OPERATING SYSTEM — STOCK SCORING & PORTFOLIO RISK WORKBOOK
A3: Companion workbook to Landry System v1.03. Aligned to: Version 1.03 (50 Hard Rules, Parts 1–12).
A4: If the Word document's rule numbers ever change in a future revision, check this line and the rule
A5: references throughout this workbook before relying on them.
A7: HOW TO USE THIS WORKBOOK
A8: 1. Market Data tab — enter or refresh price, volume, market cap, P/E, 52-week range, and dividend
A9: yield for each tracked ticker. Blue cells only. See that tab's note on optional live-data refresh.
A10: 2. Scoring tab — during a scoring session, enter each Tier 1/2/3 indicator's score (1–5) and Confidence
A11: tag (H/M/L) per Part 2's rubrics. The Composite Score, decision classification, and hard-rule flags
A12: (Rules 1–4) calculate automatically.
A13: 3. Dashboard tab — read-only summary of every tracked stock, sortable by Composite Score.
A14: 4. Price History / Returns (Calc) / Correlation Matrix tabs — enter weekly closing prices for current
... A59: a partial current week resamples to a misleading "Friday" label before Friday actually happens.

Sheet Action Items
A1: ACTION ITEMS — everything requiring your decision, pulled live from every other tab. Everything else in this workbook is reference; this is what to open.
A2: Refresh by opening the workbook (F9 recalculates); all cells below are live formulas, nothing here is typed.
A4: 1. WATCH LIST — Rules 31-34 (see Watch List Tracker tab for detail)
A5: Deadlines passed (sell required within 30 days): | E5: =COUNTIF('Watch List Tracker'!K3:K22,"*SELL WITHIN 30 DAYS*") -> 0
A6: Deadlines approaching (within 14 days): | E6: =COUNTIF('Watch List Tracker'!K3:K22,"DEADLINE APPROACHING") -> 0
A7: Recovered — ready to remove/reclassify: | E7: =COUNTIF('Watch List Tracker'!K3:K22,"*RECOVERED*") -> 0
A9: 2. ACTIVE SELL TRIGGERS — Rules 21-30 (see Holding Monitor tab for detail)
A10: Holdings with action required within 30 days: | E10: =COUNTIF('Holding Monitor'!AB4:AB23,"*ACTION REQUIRED*") -> 0
A11: Holdings under Hold Through (monitor only, no action): | E11: =COUNTIF('Holding Monitor'!AB4:AB23,"*Hold Through*") -> 0
A13: 3. CORRELATION CAP — Rule 36 (see Correlation Matrix tab for detail)
A14: Rule 36 status: | E14: ='Correlation Matrix'!J3 -> REVIEW REQUIRED
A15: Positions exceeding cap: | E15: ='Correlation Matrix'!J2 -> 5
A17: 4. PORTFOLIO DRAWDOWN STATUS — Rule 37 (see Portfolio Drawdown Log tab for detail)
A18: Most recent recorded status: | E18: =IFERROR(INDEX('Portfolio Drawdown Log'!E3:E42,COUNT('Portfolio Drawdown Log'!D3:D42)),"No entries yet") -> Normal
A19: Most recent drawdown %: | E19: =IFERROR(INDEX('Portfolio Drawdown Log'!D3:D42,COUNT('Portfolio Drawdown Log'!D3:D42)),"") -> 0
A20: Required cash floor at this level: | E20: =IFERROR(INDEX('Portfolio Drawdown Log'!F3:F42,COUNT('Portfolio Drawdown Log'!D3:D42)),"") -> 5-15%
A22: 5. CANDIDATE SCORING FLAGS — Rules 1-4 (see Scoring tab for detail)
A23: Candidates failing the Tier 1 floor, 3.0 (Rule 1): | E23: =COUNTIF(Scoring!AH3:AH60,"FAIL") -> 19
A24: Candidates auto-classified Avoid (Rule 3): | E24: =COUNTIF(Scoring!AJ3:AJ60,"AVOID") -> 23
A25: Candidates flagged for mandatory Tier 1 review (Rule 2): | E25: =COUNTIF(Scoring!AI3:AI60,"REVIEW") -> 14
A26: Candidates capped at Buy despite Strong Buy score (Rule 4): | E26: =COUNTIF(Scoring!AK3:AK60,"CAP AT BUY") -> 0
A27: 6. ENTRY AUTHORIZATION — Rules 5-13 (see Entry Checklist tab for detail)
A28: Candidates NOT authorized to enter (failing one or more Entry Rules): | E28: =COUNTIF('Entry Checklist'!R3:R47,"NO*") -> 1
A29: Candidates authorized, staged at reduced size (50%, per Rules 8-9): | E29: =COUNTIF('Entry Checklist'!H3:H47,"*50%*") -> 0
A31: 7. PIOTROSKI CROSS-CHECKS -- RETIRED 9/11/26. Tested on an 8-ticker diagnostic batch, dropped as redundant for how this system is actually used (see Journal row 42-43). Historical data left in place at Scoring cols AN-AS as a record of the experiment; no longer live-tallied here.
A32: Candidates flagged LOW CONF on Accruals (CFO does not exceed Net Income): | E32: =COUNTIF(Scoring!AP3:AP60,"LOW CONF") -> 2
A33: Candidates with Debt/FCF trending up year-over-year: | E33: =COUNTIF(Scoring!AS3:AS60,"Increased") -> 5

Sheet Current Positions
A1: Combined current positions, both accounts, as of 09/08/2026 (DCA-TRANCHE-2 executed) -- JT ULTRA (Fidelity); Self-Directed, Chase — cash sweep custodied at Schwab, swept to VMFXX for yield. Source: uploaded brokerage exports + confirmed trade executions, aggregated by ticker. Update this tab at each quarterly/annual review; use it with Part 5 sizing modifiers and the Holding Monitor tab to prescribe classifications and follow-up actions. | O1: TAX-LOSS CARRYFORWARD (update annually)
A2: Account | B2: Ticker | C2: Description | D2: Asset Class | E2: Quantity | F2: Price ($) | G2: Market Value ($) | H2: Cost Basis ($) | I2: Unrealized G/L ($) | J2: Unrealized G/L (%) | K2: % of Account | L2: % of Combined Portfolio | M2: Classification / Notes (fill at review) | O2: Short-Term Loss Carryforward:
A3: JT ULTRA (Fidelity) | B3: ADBE | C3: Adobe Inc. | D3: Equity | E3: 65 | F3: =IF(IFERROR(INDEX('Monitor & Recheck Triggers'!$H$3:$H$48,MATCH($B3,'Monitor & Recheck Triggers'!$A$3:$A$48,0)),"")="",266.51,INDEX('Monitor & Recheck Triggers'!$H$3:$H$48,MATCH($B3,'Monitor & Recheck Triggers'!$A$3:$A$48,0))) -> 266.51 | G3: =E3*F3 -> 17323.15 | H3: 19163.84 | I3: =G3-H3 -> -1840.69 | J3: =IF(H3=0,"",G3/H3-1) -> -0.096050165 | K3: =IFERROR(G3/SUM(G3:G23),"") -> 0.037012962 | L3: =IFERROR(G3/(SUM(G3:G23,G27:G46)),"") -> 0.022304598 | M3: BOUGHT +20sh 8/7/26 @ $266.38 -- DCA tranche 1 diversifier add | O3: Long-Term Loss Carryforward:
A4: JT ULTRA (Fidelity) | B4: ANET | C4: Arista Networks | D4: Equity | E4: 70 | F4: =IF(IFERROR(INDEX('Monitor & Recheck Triggers'!$H$3:$H$48,MATCH($B4,'Monitor & Recheck Triggers'!$A$3:$A$48,0)),"")="",193.78,INDEX('Monitor & Recheck Triggers'!$H$3:$H$48,MATCH($B4,'Monitor & Recheck Triggers'!$A$3:$A$48,0))) -> 193.78 | G4: =E4*F4 -> 13564.6 | H4: 10182.2 | I4: =G4-H4 -> 3382.4 | J4: =IF(H4=0,"",G4/H4-1) -> 0.33218754 | K4: =IFERROR(G4/SUM(G3:G23),"") -> 0.028982375 | L4: =IFERROR(G4/(SUM(G3:G23,G27:G46)),"") -> 0.017465239
A5: JT ULTRA (Fidelity) | B5: ASML | C5: ASML Holding | D5: Equity | E5: 7 | F5: =IF(IFERROR(INDEX('Monitor & Recheck Triggers'!$H$3:$H$48,MATCH($B5,'Monitor & Recheck Triggers'!$A$3:$A$48,0)),"")="",1714.88,INDEX('Monitor & Recheck Triggers'!$H$3:$H$48,MATCH($B5,'Monitor & Recheck Triggers'!$A$3:$A$48,0))) -> 1714.88 | G5: =E5*F5 -> 12004.16 | H5: 9989.88 | I5: =G5-H5 -> 2014.28 | J5: =IF(H5=0,"",G5/H5-1) -> 0.20163205 | K5: =IFERROR(G5/SUM(G3:G23),"") -> 0.02564831 | L5: =IFERROR(G5/(SUM(G3:G23,G27:G46)),"") -> 0.015456079
A6: JT ULTRA (Fidelity) | B6: CRWD | C6: CrowdStrike Holdings | D6: Equity | E6: 40 | F6: =IF(IFERROR(INDEX('Monitor & Recheck Triggers'!$H$3:$H$48,MATCH($B6,'Monitor & Recheck Triggers'!$A$3:$A$48,0)),"")="",213.1,INDEX('Monitor & Recheck Triggers'!$H$3:$H$48,MATCH($B6,'Monitor & Recheck Triggers'!$A$3:$A$48,0))) -> 213.1 | G6: =E6*F6 -> 8524 | H6: 4991.35 | I6: =G6-H6 -> 3532.65 | J6: =IF(H6=0,"",G6/H6-1) -> 0.70775442 | K6: =IFERROR(G6/SUM(G3:G23),"") -> 0.018212536 | L6: =IFERROR(G6/(SUM(G3:G23,G27:G46)),"") -> 0.010975163
A7: JT ULTRA (Fidelity) | B7: KLAC | C7: KLA Corporation | D7: Equity | E7: 100 | F7: =IF(IFERROR(INDEX('Monitor & Recheck Triggers'!$H$3:$H$48,MATCH($B7,'Monitor & Recheck Triggers'!$A$3:$A$48,0)),"")="",185.6,INDEX('Monitor & Recheck Triggers'!$H$3:$H$48,MATCH($B7,'Monitor & Recheck Triggers'!$A$3:$A$48,0))) -> 185.6 | G7: =E7*F7 -> 18560 | H7: 15412.54 | I7: =G7-H7 -> 3147.46 | J7: =IF(H7=0,"",G7/H7-1) -> 0.20421423 | K7: =IFERROR(G7/SUM(G3:G23),"") -> 0.039655639 | L7: =IFERROR(G7/(SUM(G3:G23,G27:G46)),"") -> 0.023897117
A8: JT ULTRA (Fidelity) | B8: MU | C8: Micron Technology | D8: Equity | E8: 7 | F8: =IF(IFERROR(INDEX('Monitor & Recheck Triggers'!$H$3:$H$48,MATCH($B8,'Monitor & Recheck Triggers'!$A$3:$A$48,0)),"")="",1016.59,INDEX('Monitor & Recheck Triggers'!$H$3:$H$48,MATCH($B8,'Monitor & Recheck Triggers'!$A$3:$A$48,0))) -> 1016.59 | G8: =E8*F8 -> 7116.13 | H8: 5836.11 | I8: =G8-H8 -> 1280.02 | J8: =IF(H8=0,"",G8/H8-1) -> 0.2193276 | K8: =IFERROR(G8/SUM(G3:G23),"") -> 0.015204455 | L8: =IFERROR(G8/(SUM(G3:G23,G27:G46)),"") -> 0.0091624457
A9: JT ULTRA (Fidelity) | B9: NVDA | C9: NVIDIA Corporation | D9: Equity | E9: 155 | F9: =IF(IFERROR(INDEX('Monitor & Recheck Triggers'!$H$3:$H$48,MATCH($B9,'Monitor & Recheck Triggers'!$A$3:$A$48,0)),"")="",230.36,INDEX('Monitor & Recheck Triggers'!$H$3:$H$48,MATCH($B9,'Monitor & Recheck Triggers'!$A$3:$A$48,0))) -> 230.36 | G9: =E9*F9 -> 35705.8 | H9: 26639.79 | I9: =G9-H9 -> 9066.01 | J9: =IF(H9=0,"",G9/H9-1) -> 0.34031837 | K9: =IFERROR(G9/SUM(G3:G23),"") -> 0.076289672 | L9: =IFERROR(G9/(SUM(G3:G23,G27:G46)),"") -> 0.045973367
A10: JT ULTRA (Fidelity) | B10: PLTR | C10: Palantir Technologies | D10: Equity | E10: 70 | F10: =IF(IFERROR(INDEX('Monitor & Recheck Triggers'!$H$3:$H$48,MATCH($B10,'Monitor & Recheck Triggers'!$A$3:$A$48,0)),"")="",174.33,INDEX('Monitor & Recheck Triggers'!$H$3:$H$48,MATCH($B10,'Monitor & Recheck Triggers'!$A$3:$A$48,0))) -> 174.33 | G10: =E10*F10 -> 12203.1 | H10: 11612.3 | I10: =G10-H10 -> 590.8 | J10: =IF(H10=0,"",G10/H10-1) -> 0.050877087 | K10: =IFERROR(G10/SUM(G3:G23),"") -> 0.026073369 | L10: =IFERROR(G10/(SUM(G3:G23,G27:G46)),"") -> 0.015712226
A11: JT ULTRA (Fidelity) | B11: TSM | C11: Taiwan Semiconductor | D11: Equity | E11: 25 | F11: =IF(IFERROR(INDEX('Monitor & Recheck Triggers'!$H$3:$H$48,MATCH($B11,'Monitor & Recheck Triggers'!$A$3:$A$48,0)),"")="",428.91,INDEX('Monitor & Recheck Triggers'!$H$3:$H$48,MATCH($B11,'Monitor & Recheck Triggers'!$A$3:$A$48,0))) -> 428.91 | G11: =E11*F11 -> 10722.75 | H11: 6069.64 | I11: =G11-H11 -> 4653.11 | J11: =IF(H11=0,"",G11/H11-1) -> 0.76662043 | K11: =IFERROR(G11/SUM(G3:G23),"") -> 0.022910426 | L11: =IFERROR(G11/(SUM(G3:G23,G27:G46)),"") -> 0.013806186
A12: JT ULTRA (Fidelity) | B12: VRT | C12: Vertiv Holdings | D12: Equity | E12: 30 | F12: =IF(IFERROR(INDEX('Monitor & Recheck Triggers'!$H$3:$H$48,MATCH($B12,'Monitor & Recheck Triggers'!$A$3:$A$48,0)),"")="",280.53,INDEX('Monitor & Recheck Triggers'!$H$3:$H$48,MATCH($B12,'Monitor & Recheck Triggers'!$A$3:$A$48,0))) -> 280.53 | G12: =E12*F12 -> 8415.9 | H12: 7876.8 | I12: =G12-H12 -> 539.1 | J12: =IF(H12=0,"",G12/H12-1) -> 0.068441499 | K12: =IFERROR(G12/SUM(G3:G23),"") -> 0.017981567 | L12: =IFERROR(G12/(SUM(G3:G23,G27:G46)),"") -> 0.010835978
A13: JT ULTRA (Fidelity) | B13: V | C13: Visa Inc. | D13: Equity | E13: 50 | F13: =IF(IFERROR(INDEX('Monitor & Recheck Triggers'!$H$3:$H$48,MATCH($B13,'Monitor & Recheck Triggers'!$A$3:$A$48,0)),"")="",367.68,INDEX('Monitor & Recheck Triggers'!$H$3:$H$48,MATCH($B13,'Monitor & Recheck Triggers'!$A$3:$A$48,0))) -> 367.68 | G13: =E13*F13 -> 18384 | H13: 18448.63 | I13: =G13-H13 -> -64.63 | J13: =IF(H13=0,"",G13/H13-1) -> -0.0035032412 | K13: =IFERROR(G13/SUM(G3:G23),"") -> 0.039279594 | L13: =IFERROR(G13/(SUM(G3:G23,G27:G46)),"") -> 0.023670506 | M13: NEW position 9/8/26 -- DCA-TRANCHE-2, opened per Entry Checklist authorization (Composite 86.4, STRONG BUY). 2 lots: 25sh @ $368.38 + 25sh @ $369.565.
A14: JT ULTRA (Fidelity) | B14: FZDXX | C14: Fidelity Money Market Premium | D14: Cash | E14: 92777.34 | F14: 1 | G14: =E14*F14 -> 92777.34 | H14: 137296.09 | I14: =G14-H14 -> -44518.75 | J14: =IF(H14=0,"",G14/H14-1) -> -0.32425359 | K14: =IFERROR(G14/SUM(G3:G23),"") -> 0.19822978 | L14: =IFERROR(G14/(SUM(G3:G23,G27:G46)),"") -> 0.11945641
A15: JT ULTRA (Fidelity) | B15: FZFXX | C15: Fidelity Core Money Market | D15: Cash | E15: 0 | F15: 1 | G15: =E15*F15 -> 0 | H15: 23 | I15: =G15-H15 -> -23 | J15: =IF(H15=0,"",G15/H15-1) -> -1 | K15: =IFERROR(G15/SUM(G3:G23),"") -> 0 | L15: =IFERROR(G15/(SUM(G3:G23,G27:G46)),"") -> 0
A16: JT ULTRA (Fidelity) | B16: DVY | C16: iShares Select Dividend ETF | D16: Equity | E16: 150 | F16: =IF(IFERROR(INDEX('Monitor & Recheck Triggers'!$H$3:$H$48,MATCH($B16,'Monitor & Recheck Triggers'!$A$3:$A$48,0)),"")="",164.25,INDEX('Monitor & Recheck Triggers'!$H$3:$H$48,MATCH($B16,'Monitor & Recheck Triggers'!$A$3:$A$48,0))) -> 164.25 | G16: =E16*F16 -> 24637.5 | H16: 24518.25 | I16: =G16-H16 -> 119.25 | J16: =IF(H16=0,"",G16/H16-1) -> 0.004863724 | K16: =IFERROR(G16/SUM(G3:G23),"") -> 0.052640938 | L16: =IFERROR(G16/(SUM(G3:G23,G27:G46)),"") -> 0.031722264 | M16: NEW position since 8/5/26 -- cash/dry powder per Alan 9/7/26, not a scored Landry position.
A17: JT ULTRA (Fidelity) | B17: VFLO | C17: VictoryShares Free Cash Flow ETF | D17: Equity | E17: 451.304 | F17: =IF(IFERROR(INDEX('Monitor & Recheck Triggers'!$H$3:$H$48,MATCH($B17,'Monitor & Recheck Triggers'!$A$3:$A$48,0)),"")="",55.29,INDEX('Monitor & Recheck Triggers'!$H$3:$H$48,MATCH($B17,'Monitor & Recheck Triggers'!$A$3:$A$48,0))) -> 55.29 | G17: =E17*F17 -> 24952.598 | H17: 24999.99 | I17: =G17-H17 -> -47.39184 | J17: =IF(H17=0,"",G17/H17-1) -> -0.0018956744 | K17: =IFERROR(G17/SUM(G3:G23),"") -> 0.053314182 | L17: =IFERROR(G17/(SUM(G3:G23,G27:G46)),"") -> 0.032127972 | M17: NEW to this account since 8/5/26 (already held in Self-Directed) -- cash/dry powder per Alan 9/7/26, not a scored Landry position.
A18: JT ULTRA (Fidelity) | B18: SCHD | C18: Schwab US Dividend Equity ETF | D18: Equity | E18: 700 | F18: =IF(IFERROR(INDEX('Monitor & Recheck Triggers'!$H$3:$H$48,MATCH($B18,'Monitor & Recheck Triggers'!$A$3:$A$48,0)),"")="",34.8,INDEX('Monitor & Recheck Triggers'!$H$3:$H$48,MATCH($B18,'Monitor & Recheck Triggers'!$A$3:$A$48,0))) -> 34.8 | G18: =E18*F18 -> 24360 | H18: 24377.5 | I18: =G18-H18 -> -17.5 | J18: =IF(H18=0,"",G18/H18-1) -> -0.00071787509 | K18: =IFERROR(G18/SUM(G3:G23),"") -> 0.052048026 | L18: =IFERROR(G18/(SUM(G3:G23,G27:G46)),"") -> 0.031364966 | M18: NEW position since 8/5/26 -- cash/dry powder per Alan 9/7/26, not a scored Landry position.
A19: JT ULTRA (Fidelity) | B19: VYM | C19: Vanguard High Dividend Yield ETF | D19: Equity | E19: 150 | F19: =IF(IFERROR(INDEX('Monitor & Recheck Triggers'!$H$3:$H$48,MATCH($B19,'Monitor & Recheck Triggers'!$A$3:$A$48,0)),"")="",164.23,INDEX('Monitor & Recheck Triggers'!$H$3:$H$48,MATCH($B19,'Monitor & Recheck Triggers'!$A$3:$A$48,0))) -> 164.23 | G19: =E19*F19 -> 24634.5 | H19: 24598.5 | I19: =G19-H19 -> 36 | J19: =IF(H19=0,"",G19/H19-1) -> 0.0014635039 | K19: =IFERROR(G19/SUM(G3:G23),"") -> 0.052634528 | L19: =IFERROR(G19/(SUM(G3:G23,G27:G46)),"") -> 0.031718401 | M19: NEW position since 8/5/26 -- cash/dry powder per Alan 9/7/26, not a scored Landry position.
A20: JT ULTRA (Fidelity) | B20: MLPI | C20: NEOS MLP & Energy Income ETF | D20: Equity | E20: 1000 | F20: =IF(IFERROR(INDEX('Monitor & Recheck Triggers'!$H$3:$H$48,MATCH($B20,'Monitor & Recheck Triggers'!$A$3:$A$48,0)),"")="",54.63,INDEX('Monitor & Recheck Triggers'!$H$3:$H$48,MATCH($B20,'Monitor & Recheck Triggers'!$A$3:$A$48,0))) -> 54.63 | G20: =E20*F20 -> 54630 | H20: 53709 | I20: =G20-H20 -> 921 | J20: =IF(H20=0,"",G20/H20-1) -> 0.017147964 | K20: =IFERROR(G20/SUM(G3:G23),"") -> 0.11672347 | L20: =IFERROR(G20/(SUM(G3:G23,G27:G46)),"") -> 0.070339413 | M20: NEW position since 8/5/26 -- cash/dry powder per Alan 9/7/26, not a scored Landry position.
A21: JT ULTRA (Fidelity) | B21: SPMO | C21: Invesco S&P 500 Momentum ETF | D21: Equity | E21: 100 | F21: =IF(IFERROR(INDEX('Monitor & Recheck Triggers'!$H$3:$H$48,MATCH($B21,'Monitor & Recheck Triggers'!$A$3:$A$48,0)),"")="",149.72,INDEX('Monitor & Recheck Triggers'!$H$3:$H$48,MATCH($B21,'Monitor & Recheck Triggers'!$A$3:$A$48,0))) -> 149.72 | G21: =E21*F21 -> 14972 | H21: 14696.99 | I21: =G21-H21 -> 275.01 | J21: =IF(H21=0,"",G21/H21-1) -> 0.018711995 | K21: =IFERROR(G21/SUM(G3:G23),"") -> 0.031989452 | L21: =IFERROR(G21/(SUM(G3:G23,G27:G46)),"") -> 0.019277351 | M21: NEW to this account since 8/5/26 (already held in Self-Directed) -- cash/dry powder per Alan 9/7/26, not a scored Landry position.
A22: JT ULTRA (Fidelity) | B22: GE | C22: GE Aerospace | D22: Equity | E22: 75 | F22: =IF(IFERROR(INDEX('Monitor & Recheck Triggers'!$H$3:$H$48,MATCH($B22,'Monitor & Recheck Triggers'!$A$3:$A$48,0)),"")="",314.71,INDEX('Monitor & Recheck Triggers'!$H$3:$H$48,MATCH($B22,'Monitor & Recheck Triggers'!$A$3:$A$48,0))) -> 314.71 | G22: =E22*F22 -> 23603.25 | H22: 23603.25 | I22: =G22-H22 -> 0 | J22: =IF(H22=0,"",G22/H22-1) -> 0 | K22: =IFERROR(G22/SUM(G3:G23),"") -> 0.05043114 | L22: =IFERROR(G22/(SUM(G3:G23,G27:G46)),"") -> 0.030390605 | M22: NEW position 9/30/26 -- DCA-CATCHUP-1, opened per Composite 84.2 STRONG BUY (rescored 9/13/26, reconfirmed fresh 9/29/26, zero Tier 1 drift). 75sh @ $314.71.
A23: JT ULTRA (Fidelity) | B23: NFLX | C23: Netflix, Inc. | D23: Equity | E23: 300 | F23: =IF(IFERROR(INDEX('Monitor & Recheck Triggers'!$H$3:$H$48,MATCH($B23,'Monitor & Recheck Triggers'!$A$3:$A$48,0)),"")="",69.795,INDEX('Monitor & Recheck Triggers'!$H$3:$H$48,MATCH($B23,'Monitor & Recheck Triggers'!$A$3:$A$48,0))) -> 69.795 | G23: =E23*F23 -> 20938.5 | H23: 20938.5 | I23: =G23-H23 -> 0 | J23: =IF(H23=0,"",G23/H23-1) -> 0 | K23: =IFERROR(G23/SUM(G3:G23),"") -> 0.044737586 | L23: =IFERROR(G23/(SUM(G3:G23,G27:G46)),"") -> 0.026959579 | M23: NEW position 9/30/26 -- DCA-CATCHUP-1, opened per Composite 83.8 STRONG BUY (rescored 9/13/26, reconfirmed fresh 9/29/26, zero Tier 1 drift). 300sh @ $69.795.
A24: Positions | B24: =SUBTOTAL(103,B3:B23) -> 21 | C24: JT ULTRA (Fidelity) SUBTOTAL | G24: =SUM(G3:G23) -> 468029.28 | H24: =SUM(H3:H23) -> 484984.15 | I24: =SUM(I3:I23) -> -16954.872 | J24: =CurrentPositionsTable[[#This Row],[Unrealized G/L ($)]]/CurrentPositionsTable[[#This Row],[Cost Basis ($)]] -> -0.034959641 | K24: =SUM(K3:K23) -> 1 | L24: =SUM(L3:L23) -> 0.60261587
I25: Excluding Cash | J25: =I24/(H24-H14-H13) -> -0.051497088
A27: Self-Directed (Chase) | B27: VMFXX | C27: Vanguard Federal Money Market | D27: Cash | E27: 36854.47 | F27: 1 | G27: =E27*F27 -> 36854.47 | H27: 36854.47 | I27: =G27-H27 -> 0 | J27: =IF(H27=0,"",G27/H27-1) -> 0 | K27: =IFERROR(G27/SUM(G27:G46),"") -> 0.11941178 | L27: =IFERROR(G27/(SUM(G3:G23,G27:G46)),"") -> 0.047452348
A28: Self-Directed (Chase) | B28: JEPQ | C28: JPMorgan Nasdaq Equity Premium Income ETF | D28: Alternative Assets | E28: 850.35693 | F28: =IF(IFERROR(INDEX('Monitor & Recheck Triggers'!$H$3:$H$48,MATCH($B28,'Monitor & Recheck Triggers'!$A$3:$A$48,0)),"")="",59.87,INDEX('Monitor & Recheck Triggers'!$H$3:$H$48,MATCH($B28,'Monitor & Recheck Triggers'!$A$3:$A$48,0))) -> 59.87 | G28: =E28*F28 -> 50910.869 | H28: 43005.36 | I28: =G28-H28 -> 7905.5094 | J28: =IF(H28=0,"",G28/H28-1) -> 0.18382614 | K28: =IFERROR(G28/SUM(G27:G46),"") -> 0.16495578 | L28: =IFERROR(G28/(SUM(G3:G23,G27:G46)),"") -> 0.065550809 | M28: Qty 840.4->850.4sh since 8/5, likely DRIP reinvestment. Reclassified as cash/dry powder per Alan 9/7/26, not a scored Landry position.
A29: Self-Directed (Chase) | B29: AVUV | C29: Avantis US Small Cap Value ETF | D29: Equity | E29: 400.00001 | F29: =IF(IFERROR(INDEX('Monitor & Recheck Triggers'!$H$3:$H$48,MATCH($B29,'Monitor & Recheck Triggers'!$A$3:$A$48,0)),"")="",126.93,INDEX('Monitor & Recheck Triggers'!$H$3:$H$48,MATCH($B29,'Monitor & Recheck Triggers'!$A$3:$A$48,0))) -> 126.93 | G29: =E29*F29 -> 50772.001 | H29: 45116.29 | I29: =G29-H29 -> 5655.7113 | J29: =IF(H29=0,"",G29/H29-1) -> 0.12535852 | K29: =IFERROR(G29/SUM(G27:G46),"") -> 0.16450583 | L29: =IFERROR(G29/(SUM(G3:G23,G27:G46)),"") -> 0.065372007 | M29: BOUGHT +193.58sh 8/7/26 @ $126.66 -- consolidation target from CALF
A30: Self-Directed (Chase) | B30: CALF | C30: Pacer US Small Cap Cash Cows ETF | D30: Equity | E30: 0 | F30: =IF(IFERROR(INDEX('Monitor & Recheck Triggers'!$H$3:$H$48,MATCH($B30,'Monitor & Recheck Triggers'!$A$3:$A$48,0)),"")="",56.12,INDEX('Monitor & Recheck Triggers'!$H$3:$H$48,MATCH($B30,'Monitor & Recheck Triggers'!$A$3:$A$48,0))) -> 56.12 | G30: =E30*F30 -> 0 | H30: 0 | I30: =G30-H30 -> 0 | J30: =IF(H30=0,"",G30/H30-1) | K30: =IFERROR(G30/SUM(G27:G46),"") -> 0 | L30: =IFERROR(G30/(SUM(G3:G23,G27:G46)),"") -> 0 | M30: SOLD 8/7/26 -- confirmed: -409.55sh, $23,016.52 proceeds. Consolidated into AVUV.
A31: Self-Directed (Chase) | B31: HELO | C31: JPMorgan Hedged Equity Laddered Overlay ETF | D31: Alternative Assets | E31: 500 | F31: =IF(IFERROR(INDEX('Monitor & Recheck Triggers'!$H$3:$H$48,MATCH($B31,'Monitor & Recheck Triggers'!$A$3:$A$48,0)),"")="",69.72,INDEX('Monitor & Recheck Triggers'!$H$3:$H$48,MATCH($B31,'Monitor & Recheck Triggers'!$A$3:$A$48,0))) -> 69.72 | G31: =E31*F31 -> 34860 | H31: 30666 | I31: =G31-H31 -> 4194 | J31: =IF(H31=0,"",G31/H31-1) -> 0.13676384 | K31: =IFERROR(G31/SUM(G27:G46),"") -> 0.11294952 | L31: =IFERROR(G31/(SUM(G3:G23,G27:G46)),"") -> 0.044884348 | M31: BOUGHT +200sh since 8/5 (300->500sh) -- expanding income sleeve. Reclassified as cash/dry powder per Alan 9/7/26, not a scored Landry position.
A32: Self-Directed (Chase) | B32: AVGO | C32: Broadcom Inc. | D32: Equity | E32: 35.07587 | F32: =IF(IFERROR(INDEX('Monitor & Recheck Triggers'!$H$3:$H$48,MATCH($B32,'Monitor & Recheck Triggers'!$A$3:$A$48,0)),"")="",357.895,INDEX('Monitor & Recheck Triggers'!$H$3:$H$48,MATCH($B32,'Monitor & Recheck Triggers'!$A$3:$A$48,0))) -> 357.895 | G32: =E32*F32 -> 12553.478 | H32: 12653.43 | I32: =G32-H32 -> -99.951506 | J32: =IF(H32=0,"",G32/H32-1) -> -0.007899163 | K32: =IFERROR(G32/SUM(G27:G46),"") -> 0.040674395 | L32: =IFERROR(G32/(SUM(G3:G23,G27:G46)),"") -> 0.016163359
A33: Self-Directed (Chase) | B33: NVDA | C33: NVIDIA Corporation | D33: Equity | E33: 59.02188 | F33: =IF(IFERROR(INDEX('Monitor & Recheck Triggers'!$H$3:$H$48,MATCH($B33,'Monitor & Recheck Triggers'!$A$3:$A$48,0)),"")="",230.36,INDEX('Monitor & Recheck Triggers'!$H$3:$H$48,MATCH($B33,'Monitor & Recheck Triggers'!$A$3:$A$48,0))) -> 230.36 | G33: =E33*F33 -> 13596.28 | H33: 11377.73 | I33: =G33-H33 -> 2218.5503 | J33: =IF(H33=0,"",G33/H33-1) -> 0.19499059 | K33: =IFERROR(G33/SUM(G27:G46),"") -> 0.044053166 | L33: =IFERROR(G33/(SUM(G3:G23,G27:G46)),"") -> 0.017506029
A34: Self-Directed (Chase) | B34: VRTX | C34: Vertex Pharmaceuticals | D34: Equity | E34: 65 | F34: =IF(IFERROR(INDEX('Monitor & Recheck Triggers'!$H$3:$H$48,MATCH($B34,'Monitor & Recheck Triggers'!$A$3:$A$48,0)),"")="",528.64,INDEX('Monitor & Recheck Triggers'!$H$3:$H$48,MATCH($B34,'Monitor & Recheck Triggers'!$A$3:$A$48,0))) -> 528.64 | G34: =E34*F34 -> 34361.6 | H34: 31479.64 | I34: =G34-H34 -> 2881.96 | J34: =IF(H34=0,"",G34/H34-1) -> 0.091549967 | K34: =IFERROR(G34/SUM(G27:G46),"") -> 0.11133466 | L34: =IFERROR(G34/(SUM(G3:G23,G27:G46)),"") -> 0.044242628 | M34: BOUGHT +15sh 9/8/26 @ ~$527.47 ($7,912.09) -- DCA-TRANCHE-2 diversifier add.
A35: Self-Directed (Chase) | B35: SPMO | C35: Invesco S&P 500 Momentum ETF | D35: Equity | E35: 76.93745 | F35: =IF(IFERROR(INDEX('Monitor & Recheck Triggers'!$H$3:$H$48,MATCH($B35,'Monitor & Recheck Triggers'!$A$3:$A$48,0)),"")="",149.72,INDEX('Monitor & Recheck Triggers'!$H$3:$H$48,MATCH($B35,'Monitor & Recheck Triggers'!$A$3:$A$48,0))) -> 149.72 | G35: =E35*F35 -> 11519.075 | H35: 9318.79 | I35: =G35-H35 -> 2200.285 | J35: =IF(H35=0,"",G35/H35-1) -> 0.23611274 | K35: =IFERROR(G35/SUM(G27:G46),"") -> 0.037322835 | L35: =IFERROR(G35/(SUM(G3:G23,G27:G46)),"") -> 0.014831502
A36: Self-Directed (Chase) | B36: VFLO | C36: VictoryShares Free Cash Flow ETF | D36: Equity | E36: 200 | F36: =IF(IFERROR(INDEX('Monitor & Recheck Triggers'!$H$3:$H$48,MATCH($B36,'Monitor & Recheck Triggers'!$A$3:$A$48,0)),"")="",55.29,INDEX('Monitor & Recheck Triggers'!$H$3:$H$48,MATCH($B36,'Monitor & Recheck Triggers'!$A$3:$A$48,0))) -> 55.29 | G36: =E36*F36 -> 11058 | H36: 9257 | I36: =G36-H36 -> 1801 | J36: =IF(H36=0,"",G36/H36-1) -> 0.19455547 | K36: =IFERROR(G36/SUM(G27:G46),"") -> 0.03582891 | L36: =IFERROR(G36/(SUM(G3:G23,G27:G46)),"") -> 0.014237841
A37: Self-Directed (Chase) | B37: ANET | C37: Arista Networks | D37: Equity | E37: 50 | F37: =IF(IFERROR(INDEX('Monitor & Recheck Triggers'!$H$3:$H$48,MATCH($B37,'Monitor & Recheck Triggers'!$A$3:$A$48,0)),"")="",193.78,INDEX('Monitor & Recheck Triggers'!$H$3:$H$48,MATCH($B37,'Monitor & Recheck Triggers'!$A$3:$A$48,0))) -> 193.78 | G37: =E37*F37 -> 9689 | H37: 7394.5 | I37: =G37-H37 -> 2294.5 | J37: =IF(H37=0,"",G37/H37-1) -> 0.31029819 | K37: =IFERROR(G37/SUM(G27:G46),"") -> 0.031393228 | L37: =IFERROR(G37/(SUM(G3:G23,G27:G46)),"") -> 0.012475171
A38: Self-Directed (Chase) | B38: CRWD | C38: CrowdStrike Holdings | D38: Equity | E38: 45 | F38: =IF(IFERROR(INDEX('Monitor & Recheck Triggers'!$H$3:$H$48,MATCH($B38,'Monitor & Recheck Triggers'!$A$3:$A$48,0)),"")="",213.1,INDEX('Monitor & Recheck Triggers'!$H$3:$H$48,MATCH($B38,'Monitor & Recheck Triggers'!$A$3:$A$48,0))) -> 213.1 | G38: =E38*F38 -> 9589.5 | H38: 7099.31 | I38: =G38-H38 -> 2490.19 | J38: =IF(H38=0,"",G38/H38-1) -> 0.35076507 | K38: =IFERROR(G38/SUM(G27:G46),"") -> 0.031070839 | L38: =IFERROR(G38/(SUM(G3:G23,G27:G46)),"") -> 0.012347058
A39: Self-Directed (Chase) | B39: PLD | C39: Prologis Inc. | D39: Equity | E39: 125.44837 | F39: =IF(IFERROR(INDEX('Monitor & Recheck Triggers'!$H$3:$H$48,MATCH($B39,'Monitor & Recheck Triggers'!$A$3:$A$48,0)),"")="",137.34,INDEX('Monitor & Recheck Triggers'!$H$3:$H$48,MATCH($B39,'Monitor & Recheck Triggers'!$A$3:$A$48,0))) -> 137.34 | G39: =E39*F39 -> 17229.079 | H39: 16585.43 | I39: =G39-H39 -> 643.64914 | J39: =IF(H39=0,"",G39/H39-1) -> 0.038808107 | K39: =IFERROR(G39/SUM(G27:G46),"") -> 0.05582376 | L39: =IFERROR(G39/(SUM(G3:G23,G27:G46)),"") -> 0.022183476 | M39: BOUGHT +64sh 8/7/26 @ $139.92 -- DCA tranche 1 diversifier add
A40: Self-Directed (Chase) | B40: SFM | C40: Sprouts Farmers Market | D40: Equity | E40: 0 | F40: =IF(IFERROR(INDEX('Monitor & Recheck Triggers'!$H$3:$H$48,MATCH($B40,'Monitor & Recheck Triggers'!$A$3:$A$48,0)),"")="",86.07,INDEX('Monitor & Recheck Triggers'!$H$3:$H$48,MATCH($B40,'Monitor & Recheck Triggers'!$A$3:$A$48,0))) -> 86.07 | G40: =E40*F40 -> 0 | H40: 0 | I40: =G40-H40 -> 0 | J40: =IF(H40=0,"",G40/H40-1) | K40: =IFERROR(G40/SUM(G27:G46),"") -> 0 | L40: =IFERROR(G40/(SUM(G3:G23,G27:G46)),"") -> 0 | M40: SOLD 08/07/26 -- confirmed: -65 sh, $5,601.58 proceeds. Rule 3 Avoid. Proceeds added to VMFXX.
A41: Self-Directed (Chase) | B41: TSLA | C41: Tesla Inc. | D41: Equity | E41: 0 | F41: =IF(IFERROR(INDEX('Monitor & Recheck Triggers'!$H$3:$H$48,MATCH($B41,'Monitor & Recheck Triggers'!$A$3:$A$48,0)),"")="",327.35,INDEX('Monitor & Recheck Triggers'!$H$3:$H$48,MATCH($B41,'Monitor & Recheck Triggers'!$A$3:$A$48,0))) -> 327.35 | G41: =E41*F41 -> 0 | H41: 0 | I41: =G41-H41 -> 0 | J41: =IF(H41=0,"",G41/H41-1) | K41: =IFERROR(G41/SUM(G27:G46),"") -> 0 | L41: =IFERROR(G41/(SUM(G3:G23,G27:G46)),"") -> 0 | M41: SOLD 08/07/26 -- confirmed: -15 sh, $4,783.25 proceeds. Rule 3 Avoid. Proceeds added to VMFXX.
A42: Self-Directed (Chase) | B42: VGT | C42: Vanguard Information Technology ETF | D42: Equity | E42: 0 | F42: =IF(IFERROR(INDEX('Monitor & Recheck Triggers'!$H$3:$H$48,MATCH($B42,'Monitor & Recheck Triggers'!$A$3:$A$48,0)),"")="",120.16,INDEX('Monitor & Recheck Triggers'!$H$3:$H$48,MATCH($B42,'Monitor & Recheck Triggers'!$A$3:$A$48,0))) -> 120.16 | G42: =E42*F42 -> 0 | H42: 0 | I42: =G42-H42 -> 0 | J42: =IF(H42=0,"",G42/H42-1) | K42: =IFERROR(G42/SUM(G27:G46),"") -> 0 | L42: =IFERROR(G42/(SUM(G3:G23,G27:G46)),"") -> 0 | M42: SOLD 8/7/26 -- confirmed: -40.18sh, $4,851.48 proceeds. Worst correlation offender (5 violations), cleared per plan.
A43: Self-Directed (Chase) | B43: QACDS | C43: Schwab Cash Features (Sweep) | D43: Cash | E43: 1853.89 | F43: 1 | G43: =E43*F43 -> 1853.89 | H43: 1853.89 | I43: =G43-H43 -> 0 | J43: =IF(H43=0,"",G43/H43-1) -> 0 | K43: =IFERROR(G43/SUM(G27:G46),"") -> 0.0060067696 | L43: =IFERROR(G43/(SUM(G3:G23,G27:G46)),"") -> 0.002386995
A44: Self-Directed (Chase) | B44: ONON | C44: On Holding AG | D44: Equity | E44: 0 | F44: =IF(IFERROR(INDEX('Monitor & Recheck Triggers'!$H$3:$H$48,MATCH($B44,'Monitor & Recheck Triggers'!$A$3:$A$48,0)),"")="",37.61,INDEX('Monitor & Recheck Triggers'!$H$3:$H$48,MATCH($B44,'Monitor & Recheck Triggers'!$A$3:$A$48,0))) -> 37.61 | G44: =E44*F44 -> 0 | H44: 0 | I44: =G44-H44 -> 0 | J44: =IF(H44=0,"",G44/H44-1) | K44: =IFERROR(G44/SUM(G27:G46),"") -> 0 | L44: =IFERROR(G44/(SUM(G3:G23,G27:G46)),"") -> 0 | M44: SOLD 08/07/26 -- confirmed: -100 sh, $3,764.92 proceeds. Rule 3 Avoid. Proceeds added to VMFXX.
A45: Self-Directed (Chase) | B45: PLTR | C45: Palantir Technologies | D45: Equity | E45: 20 | F45: =IF(IFERROR(INDEX('Monitor & Recheck Triggers'!$H$3:$H$48,MATCH($B45,'Monitor & Recheck Triggers'!$A$3:$A$48,0)),"")="",174.33,INDEX('Monitor & Recheck Triggers'!$H$3:$H$48,MATCH($B45,'Monitor & Recheck Triggers'!$A$3:$A$48,0))) -> 174.33 | G45: =E45*F45 -> 3486.6 | H45: 3178 | I45: =G45-H45 -> 308.6 | J45: =IF(H45=0,"",G45/H45-1) -> 0.097105098 | K45: =IFERROR(G45/SUM(G27:G46),"") -> 0.011296896 | L45: =IFERROR(G45/(SUM(G3:G23,G27:G46)),"") -> 0.0044892074
A46: Self-Directed (Chase) | B46: JEPI | C46: JPMorgan Equity Premium Income ETF | D46: Alternative Assets | E46: 180 | F46: =IF(IFERROR(INDEX('Monitor & Recheck Triggers'!$H$3:$H$48,MATCH($B46,'Monitor & Recheck Triggers'!$A$3:$A$48,0)),"")="",57.22,INDEX('Monitor & Recheck Triggers'!$H$3:$H$48,MATCH($B46,'Monitor & Recheck Triggers'!$A$3:$A$48,0))) -> 57.22 | G46: =E46*F46 -> 10299.6 | H46: 10500.57 | I46: =G46-H46 -> -200.97 | J46: =IF(H46=0,"",G46/H46-1) -> -0.019138961 | K46: =IFERROR(G46/SUM(G27:G46),"") -> 0.033371626 | L46: =IFERROR(G46/(SUM(G3:G23,G27:G46)),"") -> 0.013261355 | M46: NEW position since 8/5/26 -- cash/dry powder per Alan 9/7/26, not a scored Landry position.
A47: Positions | B47: =SUBTOTAL(103,B27:B46) -> 15 | C47: Self-Directed (Chase) SUBTOTAL | G47: =SUM(G27:G46) -> 308633.44 | H47: =SUM(H27:H46) -> 276340.41 | I47: =SUM(I27:I46) -> 32293.034 | J47: =CurrentPositionsTable[[#This Row],[Unrealized G/L ($)]]/CurrentPositionsTable[[#This Row],[Cost Basis ($)]] -> 0.11685961 | K47: =SUM(K27:K46) -> 1 | L47: =SUM(L27:L46) -> 0.39738413
I48: Excluding Cash | J48: =I45/(H45-H41-H25) -> 0.097105098
C51: Cash / Cash Equivalents | G51: =SUM(G14:G21)+G25+G26+G27+G29+G33+G34+G41+G44 -> 396548.29 | H51: =SUM(H14:H21)+H25+H26+H27+H29+H33+H34+H41+H44 -> 429047.45 | I51: =G49-H49 -> 0 | L51: =IFERROR(G49/G48,"") | M51: Actual cash (FZDXX+FZFXX+VMFXX+QACDS) + temporary yield-bearing cash buckets (AVUV, SPMO x2, VFLO x2, DVY, SCHD, VYM, MLPI, JEPQ, HELO, JEPI) held for liquidity/dry powder, not scored as long-term Landry positions. Policy confirmed by Alan 9/7/26. V (Visa) is NOT in this bucket -- it's a real, Entry-Checklist-authorized Landry position (Composite 86.4, STRONG BUY).
A52: NOTE: JT ULTRA's ASML/PLTR/MU quantities reflect trims already executed from the earlier rebalance session; SWAN is not currently held in this export (flagging in case that wasn't intentional). 9/7/26: refreshed both accounts from fresh Fidelity/Chase exports (as of 9/4/26 close). Alan confirmed the new/expanded positions (DVY, SCHD, VYM, MLPI, JEPI, plus additions to HELO/JEPQ and VFLO/SPMO now in both accounts) are a deliberate move of idle cash into better-paying temporary buckets -- no strategy change. See Journal and [[price_history_ownership]]/[[etf_scope_todo]] memory for context. 9/8/26: DCA-TRANCHE-2 executed. VRTX +15sh @ ~$527.47 ($7,912.09, Chase). V (Visa) opened new, 50sh across 2 lots ($9,209.50 + $9,239.13 = $18,448.63, Fidelity). PLD skipped this tranche -- Fidelity's Equity Summary Score (LSEG StarMine) showed Very Bearish (0.7/10) with 2 recent Sell opinions; traditional sell-side consensus stayed clean, but Alan chose to wait/watch rather than add. Total tranche $26,360.72 vs. $24,000 target. See Journal 9/8/26.

Sheet Monitor & Recheck Triggers
A1: Recheck triggers for every name that's been scored, not just Watch List holdings. Current Price, Insider Activity, and Analyst Shift are Claude-populated (STOCKHISTORY formula + manual recalc for price; SEC EDGAR and yfinance consensus data for the other two, refreshed periodically, not live). Recheck Status calculates automatically from all signals together.
A2: Ticker | B2: Category | C2: Last Score Date | D2: Last Composite | E2: Last Tier 1 Wtd Avg | F2: Last Decision | G2: Price at Last Score | H2: Current Price | I2: % Price Change | J2: Next/Last Earnings Date | K2: Insider Activity? (Y/N) | L2: Insider Note | M2: Analyst Shift? (Y/N) | N2: Analyst Shift Note | O2: Days Since Last Score | P2: Recheck Status | Q2: Notes
A3: ADBE | B3: Owned | C3: 46240 | D3: 85.8 | E3: 4.57 | F3: STRONG BUY | G3: 259.32 | H3: {=IFERROR(INDEX(_xlfn.stockhistory(A3,TODAY()-5,TODAY(),0,0,1),ROWS(_xlfn.stockhistory(A3,TODAY()-5,TODAY(),0,0,1)),1),"")} | I3: =IF(OR(G3="",H3=""),"",H3/G3-1) | J3: 46275 | K3: N | M3: N | O3: =IF(C3="","",TODAY()-C3) -> 55 | P3: =IF(A3="","",IF(O3>180,"DUE — STALE (>180 days)",IF(J3<>"",IF(ABS(J3-TODAY())<=7,"DUE — EARNINGS WINDOW",IF(I3<>"",IF(ABS(I3)>=0.2,"DUE — PRICE MOVE ±20%",IF(K3="Y","DUE — INSIDER ACTIVITY",IF(I3<>"",IF(ABS(I3)>=0.15,"WATCH — PRICE MOVE ±15%",IF(M3="Y","WATCH — ANALYST SHIFT","Monitor Only")),IF(M3="Y","WATCH — ANALYST SHIFT","Monitor Only")))),IF(K3="Y","DUE — INSIDER ACTIVITY",IF(I3<>"",IF(ABS(I3)>=0.15,"WATCH — PRICE MOVE ±15%",IF(M3="Y","WATCH — ANALYST SHIFT","Monitor Only")),IF(M3="Y","WATCH — ANALYST SHIFT","Monitor Only"))))),IF(I3<>"",IF(ABS(I3)>=0.2,"DUE — PRICE MOVE ±20%",IF(K3="Y","DUE — INSIDER ACTIVITY",IF(I3<>"",IF(ABS(I3)>=0.15,"WATCH — PRICE MOVE ±15%",IF(M3="Y","WATCH — ANALYST SHIFT","Monitor Only")),IF(M3="Y","WATCH — ANALYST SHIFT","Monitor Only")))),IF(K3="Y","DUE — INSIDER ACTIVITY",IF(I3<>"",IF(ABS(I3)>=0.15,"WATCH — PRICE MOVE ±15%",IF(M3="Y","WATCH — ANALYST SHIFT","Monitor Only")),IF(M3="Y","WATCH — ANALYST SHIFT","Monitor Only"))))))) -> Monitor Only
A4: ANET | B4: Owned | C4: 46240 | D4: 85 | E4: 4.57 | F4: STRONG BUY | G4: 190.51 | H4: {=IFERROR(INDEX(_xlfn.stockhistory(A4,TODAY()-5,TODAY(),0,0,1),ROWS(_xlfn.stockhistory(A4,TODAY()-5,TODAY(),0,0,1)),1),"")} | I4: =IF(OR(G4="",H4=""),"",H4/G4-1) | J4: 46329 | K4: Y | L4: 2026-09-03: Breithaupt Chantelle Yvette (Senior Vice President, CFO) sold $119,811, 1% of holding (+55 more in last 30d) | M4: N | O4: =IF(C4="","",TODAY()-C4) -> 55 | P4: =IF(A4="","",IF(O4>180,"DUE — STALE (>180 days)",IF(J4<>"",IF(ABS(J4-TODAY())<=7,"DUE — EARNINGS WINDOW",IF(I4<>"",IF(ABS(I4)>=0.2,"DUE — PRICE MOVE ±20%",IF(K4="Y","DUE — INSIDER ACTIVITY",IF(I4<>"",IF(ABS(I4)>=0.15,"WATCH — PRICE MOVE ±15%",IF(M4="Y","WATCH — ANALYST SHIFT","Monitor Only")),IF(M4="Y","WATCH — ANALYST SHIFT","Monitor Only")))),IF(K4="Y","DUE — INSIDER ACTIVITY",IF(I4<>"",IF(ABS(I4)>=0.15,"WATCH — PRICE MOVE ±15%",IF(M4="Y","WATCH — ANALYST SHIFT","Monitor Only")),IF(M4="Y","WATCH — ANALYST SHIFT","Monitor Only"))))),IF(I4<>"",IF(ABS(I4)>=0.2,"DUE — PRICE MOVE ±20%",IF(K4="Y","DUE — INSIDER ACTIVITY",IF(I4<>"",IF(ABS(I4)>=0.15,"WATCH — PRICE MOVE ±15%",IF(M4="Y","WATCH — ANALYST SHIFT","Monitor Only")),IF(M4="Y","WATCH — ANALYST SHIFT","Monitor Only")))),IF(K4="Y","DUE — INSIDER ACTIVITY",IF(I4<>"",IF(ABS(I4)>=0.15,"WATCH — PRICE MOVE ±15%",IF(M4="Y","WATCH — ANALYST SHIFT","Monitor Only")),IF(M4="Y","WATCH — ANALYST SHIFT","Monitor Only"))))))) -> DUE — INSIDER ACTIVITY
A5: ASML | B5: Owned | C5: 46240 | D5: 73.2 | E5: 3.57 | F5: BUY | G5: 1678.22 | H5: {=IFERROR(INDEX(_xlfn.stockhistory(A5,TODAY()-5,TODAY(),0,0,1),ROWS(_xlfn.stockhistory(A5,TODAY()-5,TODAY(),0,0,1)),1),"")} | I5: =IF(OR(G5="",H5=""),"",H5/G5-1) | J5: 46309 | K5: N | M5: N | O5: =IF(C5="","",TODAY()-C5) -> 55 | P5: =IF(A5="","",IF(O5>180,"DUE — STALE (>180 days)",IF(J5<>"",IF(ABS(J5-TODAY())<=7,"DUE — EARNINGS WINDOW",IF(I5<>"",IF(ABS(I5)>=0.2,"DUE — PRICE MOVE ±20%",IF(K5="Y","DUE — INSIDER ACTIVITY",IF(I5<>"",IF(ABS(I5)>=0.15,"WATCH — PRICE MOVE ±15%",IF(M5="Y","WATCH — ANALYST SHIFT","Monitor Only")),IF(M5="Y","WATCH — ANALYST SHIFT","Monitor Only")))),IF(K5="Y","DUE — INSIDER ACTIVITY",IF(I5<>"",IF(ABS(I5)>=0.15,"WATCH — PRICE MOVE ±15%",IF(M5="Y","WATCH — ANALYST SHIFT","Monitor Only")),IF(M5="Y","WATCH — ANALYST SHIFT","Monitor Only"))))),IF(I5<>"",IF(ABS(I5)>=0.2,"DUE — PRICE MOVE ±20%",IF(K5="Y","DUE — INSIDER ACTIVITY",IF(I5<>"",IF(ABS(I5)>=0.15,"WATCH — PRICE MOVE ±15%",IF(M5="Y","WATCH — ANALYST SHIFT","Monitor Only")),IF(M5="Y","WATCH — ANALYST SHIFT","Monitor Only")))),IF(K5="Y","DUE — INSIDER ACTIVITY",IF(I5<>"",IF(ABS(I5)>=0.15,"WATCH — PRICE MOVE ±15%",IF(M5="Y","WATCH — ANALYST SHIFT","Monitor Only")),IF(M5="Y","WATCH — ANALYST SHIFT","Monitor Only"))))))) -> Monitor Only
A6: CRWD | B6: Owned | C6: 46240 | D6: 70.4 | E6: 4 | F6: BUY | G6: 211.22 | H6: {=IFERROR(INDEX(_xlfn.stockhistory(A6,TODAY()-5,TODAY(),0,0,1),ROWS(_xlfn.stockhistory(A6,TODAY()-5,TODAY(),0,0,1)),1),"")} | I6: =IF(OR(G6="",H6=""),"",H6/G6-1) | J6: 46357 | K6: Y | L6: 2026-09-04: Kurtz George (PRESIDENT AND CEO) sold $472,759, 0% of holding (+126 more in last 30d) | M6: N | O6: =IF(C6="","",TODAY()-C6) -> 55 | P6: =IF(A6="","",IF(O6>180,"DUE — STALE (>180 days)",IF(J6<>"",IF(ABS(J6-TODAY())<=7,"DUE — EARNINGS WINDOW",IF(I6<>"",IF(ABS(I6)>=0.2,"DUE — PRICE MOVE ±20%",IF(K6="Y","DUE — INSIDER ACTIVITY",IF(I6<>"",IF(ABS(I6)>=0.15,"WATCH — PRICE MOVE ±15%",IF(M6="Y","WATCH — ANALYST SHIFT","Monitor Only")),IF(M6="Y","WATCH — ANALYST SHIFT","Monitor Only")))),IF(K6="Y","DUE — INSIDER ACTIVITY",IF(I6<>"",IF(ABS(I6)>=0.15,"WATCH — PRICE MOVE ±15%",IF(M6="Y","WATCH — ANALYST SHIFT","Monitor Only")),IF(M6="Y","WATCH — ANALYST SHIFT","Monitor Only"))))),IF(I6<>"",IF(ABS(I6)>=0.2,"DUE — PRICE MOVE ±20%",IF(K6="Y","DUE — INSIDER ACTIVITY",IF(I6<>"",IF(ABS(I6)>=0.15,"WATCH — PRICE MOVE ±15%",IF(M6="Y","WATCH — ANALYST SHIFT","Monitor Only")),IF(M6="Y","WATCH — ANALYST SHIFT","Monitor Only")))),IF(K6="Y","DUE — INSIDER ACTIVITY",IF(I6<>"",IF(ABS(I6)>=0.15,"WATCH — PRICE MOVE ±15%",IF(M6="Y","WATCH — ANALYST SHIFT","Monitor Only")),IF(M6="Y","WATCH — ANALYST SHIFT","Monitor Only"))))))) -> DUE — INSIDER ACTIVITY
A7: KLAC | B7: Owned | C7: 46240 | D7: 68.6 | E7: 3.43 | F7: BUY | G7: 192.8 | H7: {=IFERROR(INDEX(_xlfn.stockhistory(A7,TODAY()-5,TODAY(),0,0,1),ROWS(_xlfn.stockhistory(A7,TODAY()-5,TODAY(),0,0,1)),1),"")} | I7: =IF(OR(G7="",H7=""),"",H7/G7-1) | J7: 46323 | K7: Y | L7: 2026-08-14: Lorig Brian (EVP, KLA Global Services) sold $12,401,634, 43% of holding (+7 more in last 30d) | M7: N | O7: =IF(C7="","",TODAY()-C7) -> 55 | P7: =IF(A7="","",IF(O7>180,"DUE — STALE (>180 days)",IF(J7<>"",IF(ABS(J7-TODAY())<=7,"DUE — EARNINGS WINDOW",IF(I7<>"",IF(ABS(I7)>=0.2,"DUE — PRICE MOVE ±20%",IF(K7="Y","DUE — INSIDER ACTIVITY",IF(I7<>"",IF(ABS(I7)>=0.15,"WATCH — PRICE MOVE ±15%",IF(M7="Y","WATCH — ANALYST SHIFT","Monitor Only")),IF(M7="Y","WATCH — ANALYST SHIFT","Monitor Only")))),IF(K7="Y","DUE — INSIDER ACTIVITY",IF(I7<>"",IF(ABS(I7)>=0.15,"WATCH — PRICE MOVE ±15%",IF(M7="Y","WATCH — ANALYST SHIFT","Monitor Only")),IF(M7="Y","WATCH — ANALYST SHIFT","Monitor Only"))))),IF(I7<>"",IF(ABS(I7)>=0.2,"DUE — PRICE MOVE ±20%",IF(K7="Y","DUE — INSIDER ACTIVITY",IF(I7<>"",IF(ABS(I7)>=0.15,"WATCH — PRICE MOVE ±15%",IF(M7="Y","WATCH — ANALYST SHIFT","Monitor Only")),IF(M7="Y","WATCH — ANALYST SHIFT","Monitor Only")))),IF(K7="Y","DUE — INSIDER ACTIVITY",IF(I7<>"",IF(ABS(I7)>=0.15,"WATCH — PRICE MOVE ±15%",IF(M7="Y","WATCH — ANALYST SHIFT","Monitor Only")),IF(M7="Y","WATCH — ANALYST SHIFT","Monitor Only"))))))) -> DUE — INSIDER ACTIVITY
A8: MU | B8: Owned | C8: 46240 | D8: 71.8 | E8: 3.64 | F8: BUY | G8: 893.19 | H8: {=IFERROR(INDEX(_xlfn.stockhistory(A8,TODAY()-5,TODAY(),0,0,1),ROWS(_xlfn.stockhistory(A8,TODAY()-5,TODAY(),0,0,1)),1),"")} | I8: =IF(OR(G8="",H8=""),"",H8/G8-1) | J8: 46295 | K8: Y | L8: 2026-08-25: MEHROTRA SANJAY (President and CEO) sold $138,116, 0% of holding (+26 more in last 30d) | M8: N | O8: =IF(C8="","",TODAY()-C8) -> 55 | P8: =IF(A8="","",IF(O8>180,"DUE — STALE (>180 days)",IF(J8<>"",IF(ABS(J8-TODAY())<=7,"DUE — EARNINGS WINDOW",IF(I8<>"",IF(ABS(I8)>=0.2,"DUE — PRICE MOVE ±20%",IF(K8="Y","DUE — INSIDER ACTIVITY",IF(I8<>"",IF(ABS(I8)>=0.15,"WATCH — PRICE MOVE ±15%",IF(M8="Y","WATCH — ANALYST SHIFT","Monitor Only")),IF(M8="Y","WATCH — ANALYST SHIFT","Monitor Only")))),IF(K8="Y","DUE — INSIDER ACTIVITY",IF(I8<>"",IF(ABS(I8)>=0.15,"WATCH — PRICE MOVE ±15%",IF(M8="Y","WATCH — ANALYST SHIFT","Monitor Only")),IF(M8="Y","WATCH — ANALYST SHIFT","Monitor Only"))))),IF(I8<>"",IF(ABS(I8)>=0.2,"DUE — PRICE MOVE ±20%",IF(K8="Y","DUE — INSIDER ACTIVITY",IF(I8<>"",IF(ABS(I8)>=0.15,"WATCH — PRICE MOVE ±15%",IF(M8="Y","WATCH — ANALYST SHIFT","Monitor Only")),IF(M8="Y","WATCH — ANALYST SHIFT","Monitor Only")))),IF(K8="Y","DUE — INSIDER ACTIVITY",IF(I8<>"",IF(ABS(I8)>=0.15,"WATCH — PRICE MOVE ±15%",IF(M8="Y","WATCH — ANALYST SHIFT","Monitor Only")),IF(M8="Y","WATCH — ANALYST SHIFT","Monitor Only"))))))) -> DUE — EARNINGS WINDOW
A9: NVDA | B9: Owned | C9: 46240 | D9: 93.2 | E9: 4.57 | F9: STRONG BUY | G9: 211.87 | H9: {=IFERROR(INDEX(_xlfn.stockhistory(A9,TODAY()-5,TODAY(),0,0,1),ROWS(_xlfn.stockhistory(A9,TODAY()-5,TODAY(),0,0,1)),1),"")} | I9: =IF(OR(G9="",H9=""),"",H9/G9-1) | J9: 46343 | K9: Y | L9: 2026-09-02: STEVENS MARK A (Director) sold $98,470,906, 9% of holding (+9 more in last 30d) | M9: N | O9: =IF(C9="","",TODAY()-C9) -> 55 | P9: =IF(A9="","",IF(O9>180,"DUE — STALE (>180 days)",IF(J9<>"",IF(ABS(J9-TODAY())<=7,"DUE — EARNINGS WINDOW",IF(I9<>"",IF(ABS(I9)>=0.2,"DUE — PRICE MOVE ±20%",IF(K9="Y","DUE — INSIDER ACTIVITY",IF(I9<>"",IF(ABS(I9)>=0.15,"WATCH — PRICE MOVE ±15%",IF(M9="Y","WATCH — ANALYST SHIFT","Monitor Only")),IF(M9="Y","WATCH — ANALYST SHIFT","Monitor Only")))),IF(K9="Y","DUE — INSIDER ACTIVITY",IF(I9<>"",IF(ABS(I9)>=0.15,"WATCH — PRICE MOVE ±15%",IF(M9="Y","WATCH — ANALYST SHIFT","Monitor Only")),IF(M9="Y","WATCH — ANALYST SHIFT","Monitor Only"))))),IF(I9<>"",IF(ABS(I9)>=0.2,"DUE — PRICE MOVE ±20%",IF(K9="Y","DUE — INSIDER ACTIVITY",IF(I9<>"",IF(ABS(I9)>=0.15,"WATCH — PRICE MOVE ±15%",IF(M9="Y","WATCH — ANALYST SHIFT","Monitor Only")),IF(M9="Y","WATCH — ANALYST SHIFT","Monitor Only")))),IF(K9="Y","DUE — INSIDER ACTIVITY",IF(I9<>"",IF(ABS(I9)>=0.15,"WATCH — PRICE MOVE ±15%",IF(M9="Y","WATCH — ANALYST SHIFT","Monitor Only")),IF(M9="Y","WATCH — ANALYST SHIFT","Monitor Only"))))))) -> DUE — INSIDER ACTIVITY
A10: PLTR | B10: Owned | C10: 46240 | D10: 75.2 | E10: 4 | F10: BUY | G10: 162.66 | H10: {=IFERROR(INDEX(_xlfn.stockhistory(A10,TODAY()-5,TODAY(),0,0,1),ROWS(_xlfn.stockhistory(A10,TODAY()-5,TODAY(),0,0,1)),1),"")} | I10: =IF(OR(G10="",H10=""),"",H10/G10-1) | J10: 46328 | K10: Y | L10: 2026-09-03: Stat Lauren Elaina Friedman (Director) sold $244,915, 2% of holding (+20 more in last 30d) | M10: N | O10: =IF(C10="","",TODAY()-C10) -> 55 | P10: =IF(A10="","",IF(O10>180,"DUE — STALE (>180 days)",IF(J10<>"",IF(ABS(J10-TODAY())<=7,"DUE — EARNINGS WINDOW",IF(I10<>"",IF(ABS(I10)>=0.2,"DUE — PRICE MOVE ±20%",IF(K10="Y","DUE — INSIDER ACTIVITY",IF(I10<>"",IF(ABS(I10)>=0.15,"WATCH — PRICE MOVE ±15%",IF(M10="Y","WATCH — ANALYST SHIFT","Monitor Only")),IF(M10="Y","WATCH — ANALYST SHIFT","Monitor Only")))),IF(K10="Y","DUE — INSIDER ACTIVITY",IF(I10<>"",IF(ABS(I10)>=0.15,"WATCH — PRICE MOVE ±15%",IF(M10="Y","WATCH — ANALYST SHIFT","Monitor Only")),IF(M10="Y","WATCH — ANALYST SHIFT","Monitor Only"))))),IF(I10<>"",IF(ABS(I10)>=0.2,"DUE — PRICE MOVE ±20%",IF(K10="Y","DUE — INSIDER ACTIVITY",IF(I10<>"",IF(ABS(I10)>=0.15,"WATCH — PRICE MOVE ±15%",IF(M10="Y","WATCH — ANALYST SHIFT","Monitor Only")),IF(M10="Y","WATCH — ANALYST SHIFT","Monitor Only")))),IF(K10="Y","DUE — INSIDER ACTIVITY",IF(I10<>"",IF(ABS(I10)>=0.15,"WATCH — PRICE MOVE ±15%",IF(M10="Y","WATCH — ANALYST SHIFT","Monitor Only")),IF(M10="Y","WATCH — ANALYST SHIFT","Monitor Only"))))))) -> DUE — INSIDER ACTIVITY
A11: TSM | B11: Owned | C11: 46240 | D11: 81 | E11: 4 | F11: STRONG BUY | G11: 414 | H11: {=IFERROR(INDEX(_xlfn.stockhistory(A11,TODAY()-5,TODAY(),0,0,1),ROWS(_xlfn.stockhistory(A11,TODAY()-5,TODAY(),0,0,1)),1),"")} | I11: =IF(OR(G11="",H11=""),"",H11/G11-1) | J11: 46310 | K11: Y | L11: 2026-09-04: Fang Shu-Hua (SVP and GC) bought $77,090, 16% of holding (+11 more in last 30d) | M11: N | O11: =IF(C11="","",TODAY()-C11) -> 55 | P11: =IF(A11="","",IF(O11>180,"DUE — STALE (>180 days)",IF(J11<>"",IF(ABS(J11-TODAY())<=7,"DUE — EARNINGS WINDOW",IF(I11<>"",IF(ABS(I11)>=0.2,"DUE — PRICE MOVE ±20%",IF(K11="Y","DUE — INSIDER ACTIVITY",IF(I11<>"",IF(ABS(I11)>=0.15,"WATCH — PRICE MOVE ±15%",IF(M11="Y","WATCH — ANALYST SHIFT","Monitor Only")),IF(M11="Y","WATCH — ANALYST SHIFT","Monitor Only")))),IF(K11="Y","DUE — INSIDER ACTIVITY",IF(I11<>"",IF(ABS(I11)>=0.15,"WATCH — PRICE MOVE ±15%",IF(M11="Y","WATCH — ANALYST SHIFT","Monitor Only")),IF(M11="Y","WATCH — ANALYST SHIFT","Monitor Only"))))),IF(I11<>"",IF(ABS(I11)>=0.2,"DUE — PRICE MOVE ±20%",IF(K11="Y","DUE — INSIDER ACTIVITY",IF(I11<>"",IF(ABS(I11)>=0.15,"WATCH — PRICE MOVE ±15%",IF(M11="Y","WATCH — ANALYST SHIFT","Monitor Only")),IF(M11="Y","WATCH — ANALYST SHIFT","Monitor Only")))),IF(K11="Y","DUE — INSIDER ACTIVITY",IF(I11<>"",IF(ABS(I11)>=0.15,"WATCH — PRICE MOVE ±15%",IF(M11="Y","WATCH — ANALYST SHIFT","Monitor Only")),IF(M11="Y","WATCH — ANALYST SHIFT","Monitor Only"))))))) -> DUE — INSIDER ACTIVITY
A12: VRT | B12: Owned | C12: 46240 | D12: 82.8 | E12: 4.36 | F12: STRONG BUY | G12: 277.94 | H12: {=IFERROR(INDEX(_xlfn.stockhistory(A12,TODAY()-5,TODAY(),0,0,1),ROWS(_xlfn.stockhistory(A12,TODAY()-5,TODAY(),0,0,1)),1),"")} | I12: =IF(OR(G12="",H12=""),"",H12/G12-1) | J12: 46316 | K12: Y | L12: 2026-09-02: MONSER EDWARD L (Director) sold $219,497, 3% of holding (+7 more in last 30d) | M12: N | O12: =IF(C12="","",TODAY()-C12) -> 55 | P12: =IF(A12="","",IF(O12>180,"DUE — STALE (>180 days)",IF(J12<>"",IF(ABS(J12-TODAY())<=7,"DUE — EARNINGS WINDOW",IF(I12<>"",IF(ABS(I12)>=0.2,"DUE — PRICE MOVE ±20%",IF(K12="Y","DUE — INSIDER ACTIVITY",IF(I12<>"",IF(ABS(I12)>=0.15,"WATCH — PRICE MOVE ±15%",IF(M12="Y","WATCH — ANALYST SHIFT","Monitor Only")),IF(M12="Y","WATCH — ANALYST SHIFT","Monitor Only")))),IF(K12="Y","DUE — INSIDER ACTIVITY",IF(I12<>"",IF(ABS(I12)>=0.15,"WATCH — PRICE MOVE ±15%",IF(M12="Y","WATCH — ANALYST SHIFT","Monitor Only")),IF(M12="Y","WATCH — ANALYST SHIFT","Monitor Only"))))),IF(I12<>"",IF(ABS(I12)>=0.2,"DUE — PRICE MOVE ±20%",IF(K12="Y","DUE — INSIDER ACTIVITY",IF(I12<>"",IF(ABS(I12)>=0.15,"WATCH — PRICE MOVE ±15%",IF(M12="Y","WATCH — ANALYST SHIFT","Monitor Only")),IF(M12="Y","WATCH — ANALYST SHIFT","Monitor Only")))),IF(K12="Y","DUE — INSIDER ACTIVITY",IF(I12<>"",IF(ABS(I12)>=0.15,"WATCH — PRICE MOVE ±15%",IF(M12="Y","WATCH — ANALYST SHIFT","Monitor Only")),IF(M12="Y","WATCH — ANALYST SHIFT","Monitor Only"))))))) -> DUE — INSIDER ACTIVITY
A13: AVGO | B13: Owned | C13: 46240 | D13: 80.8 | E13: 4.07 | F13: STRONG BUY | G13: 418.16 | H13: {=IFERROR(INDEX(_xlfn.stockhistory(A13,TODAY()-5,TODAY(),0,0,1),ROWS(_xlfn.stockhistory(A13,TODAY()-5,TODAY(),0,0,1)),1),"")} | I13: =IF(OR(G13="",H13=""),"",H13/G13-1) | J13: 46267 | K13: N | M13: N | O13: =IF(C13="","",TODAY()-C13) -> 55 | P13: =IF(A13="","",IF(O13>180,"DUE — STALE (>180 days)",IF(J13<>"",IF(ABS(J13-TODAY())<=7,"DUE — EARNINGS WINDOW",IF(I13<>"",IF(ABS(I13)>=0.2,"DUE — PRICE MOVE ±20%",IF(K13="Y","DUE — INSIDER ACTIVITY",IF(I13<>"",IF(ABS(I13)>=0.15,"WATCH — PRICE MOVE ±15%",IF(M13="Y","WATCH — ANALYST SHIFT","Monitor Only")),IF(M13="Y","WATCH — ANALYST SHIFT","Monitor Only")))),IF(K13="Y","DUE — INSIDER ACTIVITY",IF(I13<>"",IF(ABS(I13)>=0.15,"WATCH — PRICE MOVE ±15%",IF(M13="Y","WATCH — ANALYST SHIFT","Monitor Only")),IF(M13="Y","WATCH — ANALYST SHIFT","Monitor Only"))))),IF(I13<>"",IF(ABS(I13)>=0.2,"DUE — PRICE MOVE ±20%",IF(K13="Y","DUE — INSIDER ACTIVITY",IF(I13<>"",IF(ABS(I13)>=0.15,"WATCH — PRICE MOVE ±15%",IF(M13="Y","WATCH — ANALYST SHIFT","Monitor Only")),IF(M13="Y","WATCH — ANALYST SHIFT","Monitor Only")))),IF(K13="Y","DUE — INSIDER ACTIVITY",IF(I13<>"",IF(ABS(I13)>=0.15,"WATCH — PRICE MOVE ±15%",IF(M13="Y","WATCH — ANALYST SHIFT","Monitor Only")),IF(M13="Y","WATCH — ANALYST SHIFT","Monitor Only"))))))) -> Monitor Only
A14: PLD | B14: Owned | C14: 46240 | D14: 82 | E14: 4.36 | F14: STRONG BUY | G14: 139.06 | H14: {=IFERROR(INDEX(_xlfn.stockhistory(A14,TODAY()-5,TODAY(),0,0,1),ROWS(_xlfn.stockhistory(A14,TODAY()-5,TODAY(),0,0,1)),1),"")} | I14: =IF(OR(G14="",H14=""),"",H14/G14-1) | J14: 46310 | K14: N | M14: N | O14: =IF(C14="","",TODAY()-C14) -> 55 | P14: =IF(A14="","",IF(O14>180,"DUE — STALE (>180 days)",IF(J14<>"",IF(ABS(J14-TODAY())<=7,"DUE — EARNINGS WINDOW",IF(I14<>"",IF(ABS(I14)>=0.2,"DUE — PRICE MOVE ±20%",IF(K14="Y","DUE — INSIDER ACTIVITY",IF(I14<>"",IF(ABS(I14)>=0.15,"WATCH — PRICE MOVE ±15%",IF(M14="Y","WATCH — ANALYST SHIFT","Monitor Only")),IF(M14="Y","WATCH — ANALYST SHIFT","Monitor Only")))),IF(K14="Y","DUE — INSIDER ACTIVITY",IF(I14<>"",IF(ABS(I14)>=0.15,"WATCH — PRICE MOVE ±15%",IF(M14="Y","WATCH — ANALYST SHIFT","Monitor Only")),IF(M14="Y","WATCH — ANALYST SHIFT","Monitor Only"))))),IF(I14<>"",IF(ABS(I14)>=0.2,"DUE — PRICE MOVE ±20%",IF(K14="Y","DUE — INSIDER ACTIVITY",IF(I14<>"",IF(ABS(I14)>=0.15,"WATCH — PRICE MOVE ±15%",IF(M14="Y","WATCH — ANALYST SHIFT","Monitor Only")),IF(M14="Y","WATCH — ANALYST SHIFT","Monitor Only")))),IF(K14="Y","DUE — INSIDER ACTIVITY",IF(I14<>"",IF(ABS(I14)>=0.15,"WATCH — PRICE MOVE ±15%",IF(M14="Y","WATCH — ANALYST SHIFT","Monitor Only")),IF(M14="Y","WATCH — ANALYST SHIFT","Monitor Only"))))))) -> Monitor Only
A15: VRTX | B15: Owned | C15: 46241 | D15: 75.6 | E15: 3.79 | F15: BUY | G15: 478.7 | H15: {=IFERROR(INDEX(_xlfn.stockhistory(A15,TODAY()-5,TODAY(),0,0,1),ROWS(_xlfn.stockhistory(A15,TODAY()-5,TODAY(),0,0,1)),1),"")} | I15: =IF(OR(G15="",H15=""),"",H15/G15-1) | J15: 46328 | K15: N | M15: N | O15: =IF(C15="","",TODAY()-C15) -> 54 | P15: =IF(A15="","",IF(O15>180,"DUE — STALE (>180 days)",IF(J15<>"",IF(ABS(J15-TODAY())<=7,"DUE — EARNINGS WINDOW",IF(I15<>"",IF(ABS(I15)>=0.2,"DUE — PRICE MOVE ±20%",IF(K15="Y","DUE — INSIDER ACTIVITY",IF(I15<>"",IF(ABS(I15)>=0.15,"WATCH — PRICE MOVE ±15%",IF(M15="Y","WATCH — ANALYST SHIFT","Monitor Only")),IF(M15="Y","WATCH — ANALYST SHIFT","Monitor Only")))),IF(K15="Y","DUE — INSIDER ACTIVITY",IF(I15<>"",IF(ABS(I15)>=0.15,"WATCH — PRICE MOVE ±15%",IF(M15="Y","WATCH — ANALYST SHIFT","Monitor Only")),IF(M15="Y","WATCH — ANALYST SHIFT","Monitor Only"))))),IF(I15<>"",IF(ABS(I15)>=0.2,"DUE — PRICE MOVE ±20%",IF(K15="Y","DUE — INSIDER ACTIVITY",IF(I15<>"",IF(ABS(I15)>=0.15,"WATCH — PRICE MOVE ±15%",IF(M15="Y","WATCH — ANALYST SHIFT","Monitor Only")),IF(M15="Y","WATCH — ANALYST SHIFT","Monitor Only")))),IF(K15="Y","DUE — INSIDER ACTIVITY",IF(I15<>"",IF(ABS(I15)>=0.15,"WATCH — PRICE MOVE ±15%",IF(M15="Y","WATCH — ANALYST SHIFT","Monitor Only")),IF(M15="Y","WATCH — ANALYST SHIFT","Monitor Only"))))))) -> Monitor Only | Q15: Re-scored 8/7/26: original Avoid was bad source data, corrected. See Journal.
A16: AAP | B16: Tier-1 Avoid (external) | C16: 46246 | E16: 1.36 | G16: 53.52 | H16: {=IFERROR(INDEX(_xlfn.stockhistory(A16,TODAY()-5,TODAY(),0,0,1),ROWS(_xlfn.stockhistory(A16,TODAY()-5,TODAY(),0,0,1)),1),"")} | I16: =IF(OR(G16="",H16=""),"",H16/G16-1) | J16: 46331 | K16: N | M16: N | O16: =IF(C16="","",TODAY()-C16) -> 49 | P16: =IF(A16="","",IF(O16>180,"DUE — STALE (>180 days)",IF(J16<>"",IF(ABS(J16-TODAY())<=7,"DUE — EARNINGS WINDOW",IF(I16<>"",IF(ABS(I16)>=0.2,"DUE — PRICE MOVE ±20%",IF(K16="Y","DUE — INSIDER ACTIVITY",IF(I16<>"",IF(ABS(I16)>=0.15,"WATCH — PRICE MOVE ±15%",IF(M16="Y","WATCH — ANALYST SHIFT","Monitor Only")),IF(M16="Y","WATCH — ANALYST SHIFT","Monitor Only")))),IF(K16="Y","DUE — INSIDER ACTIVITY",IF(I16<>"",IF(ABS(I16)>=0.15,"WATCH — PRICE MOVE ±15%",IF(M16="Y","WATCH — ANALYST SHIFT","Monitor Only")),IF(M16="Y","WATCH — ANALYST SHIFT","Monitor Only"))))),IF(I16<>"",IF(ABS(I16)>=0.2,"DUE — PRICE MOVE ±20%",IF(K16="Y","DUE — INSIDER ACTIVITY",IF(I16<>"",IF(ABS(I16)>=0.15,"WATCH — PRICE MOVE ±15%",IF(M16="Y","WATCH — ANALYST SHIFT","Monitor Only")),IF(M16="Y","WATCH — ANALYST SHIFT","Monitor Only")))),IF(K16="Y","DUE — INSIDER ACTIVITY",IF(I16<>"",IF(ABS(I16)>=0.15,"WATCH — PRICE MOVE ±15%",IF(M16="Y","WATCH — ANALYST SHIFT","Monitor Only")),IF(M16="Y","WATCH — ANALYST SHIFT","Monitor Only"))))))) -> Monitor Only
A17: BABA | B17: Tier-1 Avoid (external) | C17: 46246 | E17: 2.79 | G17: 125.22 | H17: {=IFERROR(INDEX(_xlfn.stockhistory(A17,TODAY()-5,TODAY(),0,0,1),ROWS(_xlfn.stockhistory(A17,TODAY()-5,TODAY(),0,0,1)),1),"")} | I17: =IF(OR(G17="",H17=""),"",H17/G17-1) | J17: 46350 | K17: Y | L17: 2026-08-25: Tsai Joseph C (Other) bought $10,418,400, 1% of holding (+2 more in last 30d) | M17: N | O17: =IF(C17="","",TODAY()-C17) -> 49 | P17: =IF(A17="","",IF(O17>180,"DUE — STALE (>180 days)",IF(J17<>"",IF(ABS(J17-TODAY())<=7,"DUE — EARNINGS WINDOW",IF(I17<>"",IF(ABS(I17)>=0.2,"DUE — PRICE MOVE ±20%",IF(K17="Y","DUE — INSIDER ACTIVITY",IF(I17<>"",IF(ABS(I17)>=0.15,"WATCH — PRICE MOVE ±15%",IF(M17="Y","WATCH — ANALYST SHIFT","Monitor Only")),IF(M17="Y","WATCH — ANALYST SHIFT","Monitor Only")))),IF(K17="Y","DUE — INSIDER ACTIVITY",IF(I17<>"",IF(ABS(I17)>=0.15,"WATCH — PRICE MOVE ±15%",IF(M17="Y","WATCH — ANALYST SHIFT","Monitor Only")),IF(M17="Y","WATCH — ANALYST SHIFT","Monitor Only"))))),IF(I17<>"",IF(ABS(I17)>=0.2,"DUE — PRICE MOVE ±20%",IF(K17="Y","DUE — INSIDER ACTIVITY",IF(I17<>"",IF(ABS(I17)>=0.15,"WATCH — PRICE MOVE ±15%",IF(M17="Y","WATCH — ANALYST SHIFT","Monitor Only")),IF(M17="Y","WATCH — ANALYST SHIFT","Monitor Only")))),IF(K17="Y","DUE — INSIDER ACTIVITY",IF(I17<>"",IF(ABS(I17)>=0.15,"WATCH — PRICE MOVE ±15%",IF(M17="Y","WATCH — ANALYST SHIFT","Monitor Only")),IF(M17="Y","WATCH — ANALYST SHIFT","Monitor Only"))))))) -> DUE — INSIDER ACTIVITY
A18: CE | B18: Tier-1 Avoid (external) | C18: 46245 | E18: 1.79 | G18: 44.84 | H18: {=IFERROR(INDEX(_xlfn.stockhistory(A18,TODAY()-5,TODAY(),0,0,1),ROWS(_xlfn.stockhistory(A18,TODAY()-5,TODAY(),0,0,1)),1),"")} | I18: =IF(OR(G18="",H18=""),"",H18/G18-1) | J18: 46331 | K18: N | M18: N | O18: =IF(C18="","",TODAY()-C18) -> 50 | P18: =IF(A18="","",IF(O18>180,"DUE — STALE (>180 days)",IF(J18<>"",IF(ABS(J18-TODAY())<=7,"DUE — EARNINGS WINDOW",IF(I18<>"",IF(ABS(I18)>=0.2,"DUE — PRICE MOVE ±20%",IF(K18="Y","DUE — INSIDER ACTIVITY",IF(I18<>"",IF(ABS(I18)>=0.15,"WATCH — PRICE MOVE ±15%",IF(M18="Y","WATCH — ANALYST SHIFT","Monitor Only")),IF(M18="Y","WATCH — ANALYST SHIFT","Monitor Only")))),IF(K18="Y","DUE — INSIDER ACTIVITY",IF(I18<>"",IF(ABS(I18)>=0.15,"WATCH — PRICE MOVE ±15%",IF(M18="Y","WATCH — ANALYST SHIFT","Monitor Only")),IF(M18="Y","WATCH — ANALYST SHIFT","Monitor Only"))))),IF(I18<>"",IF(ABS(I18)>=0.2,"DUE — PRICE MOVE ±20%",IF(K18="Y","DUE — INSIDER ACTIVITY",IF(I18<>"",IF(ABS(I18)>=0.15,"WATCH — PRICE MOVE ±15%",IF(M18="Y","WATCH — ANALYST SHIFT","Monitor Only")),IF(M18="Y","WATCH — ANALYST SHIFT","Monitor Only")))),IF(K18="Y","DUE — INSIDER ACTIVITY",IF(I18<>"",IF(ABS(I18)>=0.15,"WATCH — PRICE MOVE ±15%",IF(M18="Y","WATCH — ANALYST SHIFT","Monitor Only")),IF(M18="Y","WATCH — ANALYST SHIFT","Monitor Only"))))))) -> Monitor Only
A19: CLF | B19: Tier-1 Avoid (external) | C19: 46245 | E19: 1.86 | G19: 12.41 | H19: {=IFERROR(INDEX(_xlfn.stockhistory(A19,TODAY()-5,TODAY(),0,0,1),ROWS(_xlfn.stockhistory(A19,TODAY()-5,TODAY(),0,0,1)),1),"")} | I19: =IF(OR(G19="",H19=""),"",H19/G19-1) | J19: 46314 | K19: N | M19: N | O19: =IF(C19="","",TODAY()-C19) -> 50 | P19: =IF(A19="","",IF(O19>180,"DUE — STALE (>180 days)",IF(J19<>"",IF(ABS(J19-TODAY())<=7,"DUE — EARNINGS WINDOW",IF(I19<>"",IF(ABS(I19)>=0.2,"DUE — PRICE MOVE ±20%",IF(K19="Y","DUE — INSIDER ACTIVITY",IF(I19<>"",IF(ABS(I19)>=0.15,"WATCH — PRICE MOVE ±15%",IF(M19="Y","WATCH — ANALYST SHIFT","Monitor Only")),IF(M19="Y","WATCH — ANALYST SHIFT","Monitor Only")))),IF(K19="Y","DUE — INSIDER ACTIVITY",IF(I19<>"",IF(ABS(I19)>=0.15,"WATCH — PRICE MOVE ±15%",IF(M19="Y","WATCH — ANALYST SHIFT","Monitor Only")),IF(M19="Y","WATCH — ANALYST SHIFT","Monitor Only"))))),IF(I19<>"",IF(ABS(I19)>=0.2,"DUE — PRICE MOVE ±20%",IF(K19="Y","DUE — INSIDER ACTIVITY",IF(I19<>"",IF(ABS(I19)>=0.15,"WATCH — PRICE MOVE ±15%",IF(M19="Y","WATCH — ANALYST SHIFT","Monitor Only")),IF(M19="Y","WATCH — ANALYST SHIFT","Monitor Only")))),IF(K19="Y","DUE — INSIDER ACTIVITY",IF(I19<>"",IF(ABS(I19)>=0.15,"WATCH — PRICE MOVE ±15%",IF(M19="Y","WATCH — ANALYST SHIFT","Monitor Only")),IF(M19="Y","WATCH — ANALYST SHIFT","Monitor Only"))))))) -> Monitor Only
A20: CMG | B20: Watch List | C20: 46245 | E20: 3.71 | G20: 32 | H20: {=IFERROR(INDEX(_xlfn.stockhistory(A20,TODAY()-5,TODAY(),0,0,1),ROWS(_xlfn.stockhistory(A20,TODAY()-5,TODAY(),0,0,1)),1),"")} | I20: =IF(OR(G20="",H20=""),"",H20/G20-1) | J20: 46330 | K20: N | M20: N | O20: =IF(C20="","",TODAY()-C20) -> 50 | P20: =IF(A20="","",IF(O20>180,"DUE — STALE (>180 days)",IF(J20<>"",IF(ABS(J20-TODAY())<=7,"DUE — EARNINGS WINDOW",IF(I20<>"",IF(ABS(I20)>=0.2,"DUE — PRICE MOVE ±20%",IF(K20="Y","DUE — INSIDER ACTIVITY",IF(I20<>"",IF(ABS(I20)>=0.15,"WATCH — PRICE MOVE ±15%",IF(M20="Y","WATCH — ANALYST SHIFT","Monitor Only")),IF(M20="Y","WATCH — ANALYST SHIFT","Monitor Only")))),IF(K20="Y","DUE — INSIDER ACTIVITY",IF(I20<>"",IF(ABS(I20)>=0.15,"WATCH — PRICE MOVE ±15%",IF(M20="Y","WATCH — ANALYST SHIFT","Monitor Only")),IF(M20="Y","WATCH — ANALYST SHIFT","Monitor Only"))))),IF(I20<>"",IF(ABS(I20)>=0.2,"DUE — PRICE MOVE ±20%",IF(K20="Y","DUE — INSIDER ACTIVITY",IF(I20<>"",IF(ABS(I20)>=0.15,"WATCH — PRICE MOVE ±15%",IF(M20="Y","WATCH — ANALYST SHIFT","Monitor Only")),IF(M20="Y","WATCH — ANALYST SHIFT","Monitor Only")))),IF(K20="Y","DUE — INSIDER ACTIVITY",IF(I20<>"",IF(ABS(I20)>=0.15,"WATCH — PRICE MOVE ±15%",IF(M20="Y","WATCH — ANALYST SHIFT","Monitor Only")),IF(M20="Y","WATCH — ANALYST SHIFT","Monitor Only"))))))) -> Monitor Only
A21: COST | B21: Watch List | C21: 46245 | D21: 77.4 | E21: 4.14 | F21: BUY | G21: 944.32 | H21: {=IFERROR(INDEX(_xlfn.stockhistory(A21,TODAY()-5,TODAY(),0,0,1),ROWS(_xlfn.stockhistory(A21,TODAY()-5,TODAY(),0,0,1)),1),"")} | I21: =IF(OR(G21="",H21=""),"",H21/G21-1) | J21: 46289 | K21: N | M21: N | O21: =IF(C21="","",TODAY()-C21) -> 50 | P21: =IF(A21="","",IF(O21>180,"DUE — STALE (>180 days)",IF(J21<>"",IF(ABS(J21-TODAY())<=7,"DUE — EARNINGS WINDOW",IF(I21<>"",IF(ABS(I21)>=0.2,"DUE — PRICE MOVE ±20%",IF(K21="Y","DUE — INSIDER ACTIVITY",IF(I21<>"",IF(ABS(I21)>=0.15,"WATCH — PRICE MOVE ±15%",IF(M21="Y","WATCH — ANALYST SHIFT","Monitor Only")),IF(M21="Y","WATCH — ANALYST SHIFT","Monitor Only")))),IF(K21="Y","DUE — INSIDER ACTIVITY",IF(I21<>"",IF(ABS(I21)>=0.15,"WATCH — PRICE MOVE ±15%",IF(M21="Y","WATCH — ANALYST SHIFT","Monitor Only")),IF(M21="Y","WATCH — ANALYST SHIFT","Monitor Only"))))),IF(I21<>"",IF(ABS(I21)>=0.2,"DUE — PRICE MOVE ±20%",IF(K21="Y","DUE — INSIDER ACTIVITY",IF(I21<>"",IF(ABS(I21)>=0.15,"WATCH — PRICE MOVE ±15%",IF(M21="Y","WATCH — ANALYST SHIFT","Monitor Only")),IF(M21="Y","WATCH — ANALYST SHIFT","Monitor Only")))),IF(K21="Y","DUE — INSIDER ACTIVITY",IF(I21<>"",IF(ABS(I21)>=0.15,"WATCH — PRICE MOVE ±15%",IF(M21="Y","WATCH — ANALYST SHIFT","Monitor Only")),IF(M21="Y","WATCH — ANALYST SHIFT","Monitor Only"))))))) -> DUE — EARNINGS WINDOW
A22: CRK | B22: Tier-1 Avoid (external) | C22: 46245 | E22: 1.21 | G22: 14.39 | H22: {=IFERROR(INDEX(_xlfn.stockhistory(A22,TODAY()-5,TODAY(),0,0,1),ROWS(_xlfn.stockhistory(A22,TODAY()-5,TODAY(),0,0,1)),1),"")} | I22: =IF(OR(G22="",H22=""),"",H22/G22-1) | J22: 46328 | K22: N | M22: N | O22: =IF(C22="","",TODAY()-C22) -> 50 | P22: =IF(A22="","",IF(O22>180,"DUE — STALE (>180 days)",IF(J22<>"",IF(ABS(J22-TODAY())<=7,"DUE — EARNINGS WINDOW",IF(I22<>"",IF(ABS(I22)>=0.2,"DUE — PRICE MOVE ±20%",IF(K22="Y","DUE — INSIDER ACTIVITY",IF(I22<>"",IF(ABS(I22)>=0.15,"WATCH — PRICE MOVE ±15%",IF(M22="Y","WATCH — ANALYST SHIFT","Monitor Only")),IF(M22="Y","WATCH — ANALYST SHIFT","Monitor Only")))),IF(K22="Y","DUE — INSIDER ACTIVITY",IF(I22<>"",IF(ABS(I22)>=0.15,"WATCH — PRICE MOVE ±15%",IF(M22="Y","WATCH — ANALYST SHIFT","Monitor Only")),IF(M22="Y","WATCH — ANALYST SHIFT","Monitor Only"))))),IF(I22<>"",IF(ABS(I22)>=0.2,"DUE — PRICE MOVE ±20%",IF(K22="Y","DUE — INSIDER ACTIVITY",IF(I22<>"",IF(ABS(I22)>=0.15,"WATCH — PRICE MOVE ±15%",IF(M22="Y","WATCH — ANALYST SHIFT","Monitor Only")),IF(M22="Y","WATCH — ANALYST SHIFT","Monitor Only")))),IF(K22="Y","DUE — INSIDER ACTIVITY",IF(I22<>"",IF(ABS(I22)>=0.15,"WATCH — PRICE MOVE ±15%",IF(M22="Y","WATCH — ANALYST SHIFT","Monitor Only")),IF(M22="Y","WATCH — ANALYST SHIFT","Monitor Only"))))))) -> Monitor Only
A23: DEO | B23: Tier-1 Avoid (external) | C23: 46245 | E23: 2.36 | G23: 94.94 | H23: {=IFERROR(INDEX(_xlfn.stockhistory(A23,TODAY()-5,TODAY(),0,0,1),ROWS(_xlfn.stockhistory(A23,TODAY()-5,TODAY(),0,0,1)),1),"")} | I23: =IF(OR(G23="",H23=""),"",H23/G23-1) | J23: 46240 | K23: N | M23: N | O23: =IF(C23="","",TODAY()-C23) -> 50 | P23: =IF(A23="","",IF(O23>180,"DUE — STALE (>180 days)",IF(J23<>"",IF(ABS(J23-TODAY())<=7,"DUE — EARNINGS WINDOW",IF(I23<>"",IF(ABS(I23)>=0.2,"DUE — PRICE MOVE ±20%",IF(K23="Y","DUE — INSIDER ACTIVITY",IF(I23<>"",IF(ABS(I23)>=0.15,"WATCH — PRICE MOVE ±15%",IF(M23="Y","WATCH — ANALYST SHIFT","Monitor Only")),IF(M23="Y","WATCH — ANALYST SHIFT","Monitor Only")))),IF(K23="Y","DUE — INSIDER ACTIVITY",IF(I23<>"",IF(ABS(I23)>=0.15,"WATCH — PRICE MOVE ±15%",IF(M23="Y","WATCH — ANALYST SHIFT","Monitor Only")),IF(M23="Y","WATCH — ANALYST SHIFT","Monitor Only"))))),IF(I23<>"",IF(ABS(I23)>=0.2,"DUE — PRICE MOVE ±20%",IF(K23="Y","DUE — INSIDER ACTIVITY",IF(I23<>"",IF(ABS(I23)>=0.15,"WATCH — PRICE MOVE ±15%",IF(M23="Y","WATCH — ANALYST SHIFT","Monitor Only")),IF(M23="Y","WATCH — ANALYST SHIFT","Monitor Only")))),IF(K23="Y","DUE — INSIDER ACTIVITY",IF(I23<>"",IF(ABS(I23)>=0.15,"WATCH — PRICE MOVE ±15%",IF(M23="Y","WATCH — ANALYST SHIFT","Monitor Only")),IF(M23="Y","WATCH — ANALYST SHIFT","Monitor Only"))))))) -> Monitor Only
A24: DIS | B24: Tier-1 Avoid (external) | C24: 46258 | E24: 2.93 | G24: 110.61 | H24: {=IFERROR(INDEX(_xlfn.stockhistory(A24,TODAY()-5,TODAY(),0,0,1),ROWS(_xlfn.stockhistory(A24,TODAY()-5,TODAY(),0,0,1)),1),"")} | I24: =IF(OR(G24="",H24=""),"",H24/G24-1) | J24: 46338 | K24: Y | L24: 2026-08-20: Roeder Paul M (Sr EVP and Chief Comm Officer) sold $382,327, 100% of holding (+1 more in last 30d) | M24: N | O24: =IF(C24="","",TODAY()-C24) -> 37 | P24: =IF(A24="","",IF(O24>180,"DUE — STALE (>180 days)",IF(J24<>"",IF(ABS(J24-TODAY())<=7,"DUE — EARNINGS WINDOW",IF(I24<>"",IF(ABS(I24)>=0.2,"DUE — PRICE MOVE ±20%",IF(K24="Y","DUE — INSIDER ACTIVITY",IF(I24<>"",IF(ABS(I24)>=0.15,"WATCH — PRICE MOVE ±15%",IF(M24="Y","WATCH — ANALYST SHIFT","Monitor Only")),IF(M24="Y","WATCH — ANALYST SHIFT","Monitor Only")))),IF(K24="Y","DUE — INSIDER ACTIVITY",IF(I24<>"",IF(ABS(I24)>=0.15,"WATCH — PRICE MOVE ±15%",IF(M24="Y","WATCH — ANALYST SHIFT","Monitor Only")),IF(M24="Y","WATCH — ANALYST SHIFT","Monitor Only"))))),IF(I24<>"",IF(ABS(I24)>=0.2,"DUE — PRICE MOVE ±20%",IF(K24="Y","DUE — INSIDER ACTIVITY",IF(I24<>"",IF(ABS(I24)>=0.15,"WATCH — PRICE MOVE ±15%",IF(M24="Y","WATCH — ANALYST SHIFT","Monitor Only")),IF(M24="Y","WATCH — ANALYST SHIFT","Monitor Only")))),IF(K24="Y","DUE — INSIDER ACTIVITY",IF(I24<>"",IF(ABS(I24)>=0.15,"WATCH — PRICE MOVE ±15%",IF(M24="Y","WATCH — ANALYST SHIFT","Monitor Only")),IF(M24="Y","WATCH — ANALYST SHIFT","Monitor Only"))))))) -> DUE — INSIDER ACTIVITY
A25: DPZ | B25: Watch List | C25: 46245 | E25: 4.86 | G25: 357.34 | H25: {=IFERROR(INDEX(_xlfn.stockhistory(A25,TODAY()-5,TODAY(),0,0,1),ROWS(_xlfn.stockhistory(A25,TODAY()-5,TODAY(),0,0,1)),1),"")} | I25: =IF(OR(G25="",H25=""),"",H25/G25-1) | J25: 46308 | K25: N | M25: N | O25: =IF(C25="","",TODAY()-C25) -> 50 | P25: =IF(A25="","",IF(O25>180,"DUE — STALE (>180 days)",IF(J25<>"",IF(ABS(J25-TODAY())<=7,"DUE — EARNINGS WINDOW",IF(I25<>"",IF(ABS(I25)>=0.2,"DUE — PRICE MOVE ±20%",IF(K25="Y","DUE — INSIDER ACTIVITY",IF(I25<>"",IF(ABS(I25)>=0.15,"WATCH — PRICE MOVE ±15%",IF(M25="Y","WATCH — ANALYST SHIFT","Monitor Only")),IF(M25="Y","WATCH — ANALYST SHIFT","Monitor Only")))),IF(K25="Y","DUE — INSIDER ACTIVITY",IF(I25<>"",IF(ABS(I25)>=0.15,"WATCH — PRICE MOVE ±15%",IF(M25="Y","WATCH — ANALYST SHIFT","Monitor Only")),IF(M25="Y","WATCH — ANALYST SHIFT","Monitor Only"))))),IF(I25<>"",IF(ABS(I25)>=0.2,"DUE — PRICE MOVE ±20%",IF(K25="Y","DUE — INSIDER ACTIVITY",IF(I25<>"",IF(ABS(I25)>=0.15,"WATCH — PRICE MOVE ±15%",IF(M25="Y","WATCH — ANALYST SHIFT","Monitor Only")),IF(M25="Y","WATCH — ANALYST SHIFT","Monitor Only")))),IF(K25="Y","DUE — INSIDER ACTIVITY",IF(I25<>"",IF(ABS(I25)>=0.15,"WATCH — PRICE MOVE ±15%",IF(M25="Y","WATCH — ANALYST SHIFT","Monitor Only")),IF(M25="Y","WATCH — ANALYST SHIFT","Monitor Only"))))))) -> Monitor Only
A26: EL | B26: Tier-1 Avoid (external) | C26: 46245 | E26: 2.14 | G26: 87.78 | H26: {=IFERROR(INDEX(_xlfn.stockhistory(A26,TODAY()-5,TODAY(),0,0,1),ROWS(_xlfn.stockhistory(A26,TODAY()-5,TODAY(),0,0,1)),1),"")} | I26: =IF(OR(G26="",H26=""),"",H26/G26-1) | J26: 46328 | K26: Y | L26: 2026-08-25: La Lande Rashida (Exec VP & General Counsel) sold $553,896, 100% of holding | M26: N | O26: =IF(C26="","",TODAY()-C26) -> 50 | P26: =IF(A26="","",IF(O26>180,"DUE — STALE (>180 days)",IF(J26<>"",IF(ABS(J26-TODAY())<=7,"DUE — EARNINGS WINDOW",IF(I26<>"",IF(ABS(I26)>=0.2,"DUE — PRICE MOVE ±20%",IF(K26="Y","DUE — INSIDER ACTIVITY",IF(I26<>"",IF(ABS(I26)>=0.15,"WATCH — PRICE MOVE ±15%",IF(M26="Y","WATCH — ANALYST SHIFT","Monitor Only")),IF(M26="Y","WATCH — ANALYST SHIFT","Monitor Only")))),IF(K26="Y","DUE — INSIDER ACTIVITY",IF(I26<>"",IF(ABS(I26)>=0.15,"WATCH — PRICE MOVE ±15%",IF(M26="Y","WATCH — ANALYST SHIFT","Monitor Only")),IF(M26="Y","WATCH — ANALYST SHIFT","Monitor Only"))))),IF(I26<>"",IF(ABS(I26)>=0.2,"DUE — PRICE MOVE ±20%",IF(K26="Y","DUE — INSIDER ACTIVITY",IF(I26<>"",IF(ABS(I26)>=0.15,"WATCH — PRICE MOVE ±15%",IF(M26="Y","WATCH — ANALYST SHIFT","Monitor Only")),IF(M26="Y","WATCH — ANALYST SHIFT","Monitor Only")))),IF(K26="Y","DUE — INSIDER ACTIVITY",IF(I26<>"",IF(ABS(I26)>=0.15,"WATCH — PRICE MOVE ±15%",IF(M26="Y","WATCH — ANALYST SHIFT","Monitor Only")),IF(M26="Y","WATCH — ANALYST SHIFT","Monitor Only"))))))) -> DUE — INSIDER ACTIVITY
A27: ET | B27: Watch List | C27: 46276 | E27: 3.07 | G27: 20.78 | H27: {=IFERROR(INDEX(_xlfn.stockhistory(A27,TODAY()-5,TODAY(),0,0,1),ROWS(_xlfn.stockhistory(A27,TODAY()-5,TODAY(),0,0,1)),1),"")} | I27: =IF(OR(G27="",H27=""),"",H27/G27-1) | J27: 46330 | K27: Y | L27: 2026-08-20: WARREN KELCY L (Other) bought $7,487,721, 0% of holding (+2 more in last 30d) | M27: N | O27: =IF(C27="","",TODAY()-C27) -> 19 | P27: =IF(A27="","",IF(O27>180,"DUE — STALE (>180 days)",IF(J27<>"",IF(ABS(J27-TODAY())<=7,"DUE — EARNINGS WINDOW",IF(I27<>"",IF(ABS(I27)>=0.2,"DUE — PRICE MOVE ±20%",IF(K27="Y","DUE — INSIDER ACTIVITY",IF(I27<>"",IF(ABS(I27)>=0.15,"WATCH — PRICE MOVE ±15%",IF(M27="Y","WATCH — ANALYST SHIFT","Monitor Only")),IF(M27="Y","WATCH — ANALYST SHIFT","Monitor Only")))),IF(K27="Y","DUE — INSIDER ACTIVITY",IF(I27<>"",IF(ABS(I27)>=0.15,"WATCH — PRICE MOVE ±15%",IF(M27="Y","WATCH — ANALYST SHIFT","Monitor Only")),IF(M27="Y","WATCH — ANALYST SHIFT","Monitor Only"))))),IF(I27<>"",IF(ABS(I27)>=0.2,"DUE — PRICE MOVE ±20%",IF(K27="Y","DUE — INSIDER ACTIVITY",IF(I27<>"",IF(ABS(I27)>=0.15,"WATCH — PRICE MOVE ±15%",IF(M27="Y","WATCH — ANALYST SHIFT","Monitor Only")),IF(M27="Y","WATCH — ANALYST SHIFT","Monitor Only")))),IF(K27="Y","DUE — INSIDER ACTIVITY",IF(I27<>"",IF(ABS(I27)>=0.15,"WATCH — PRICE MOVE ±15%",IF(M27="Y","WATCH — ANALYST SHIFT","Monitor Only")),IF(M27="Y","WATCH — ANALYST SHIFT","Monitor Only"))))))) -> DUE — INSIDER ACTIVITY
A28: ETN | B28: Watch List | C28: 46247 | E28: 3.5 | G28: 453.33 | H28: {=IFERROR(INDEX(_xlfn.stockhistory(A28,TODAY()-5,TODAY(),0,0,1),ROWS(_xlfn.stockhistory(A28,TODAY()-5,TODAY(),0,0,1)),1),"")} | I28: =IF(OR(G28="",H28=""),"",H28/G28-1) | J28: 46329 | K28: Y | L28: 2026-08-13: Monesmith Heath B. (See Remarks below.) sold $8,261,224, 26% of holding (+1 more in last 30d) | M28: N | O28: =IF(C28="","",TODAY()-C28) -> 48 | P28: =IF(A28="","",IF(O28>180,"DUE — STALE (>180 days)",IF(J28<>"",IF(ABS(J28-TODAY())<=7,"DUE — EARNINGS WINDOW",IF(I28<>"",IF(ABS(I28)>=0.2,"DUE — PRICE MOVE ±20%",IF(K28="Y","DUE — INSIDER ACTIVITY",IF(I28<>"",IF(ABS(I28)>=0.15,"WATCH — PRICE MOVE ±15%",IF(M28="Y","WATCH — ANALYST SHIFT","Monitor Only")),IF(M28="Y","WATCH — ANALYST SHIFT","Monitor Only")))),IF(K28="Y","DUE — INSIDER ACTIVITY",IF(I28<>"",IF(ABS(I28)>=0.15,"WATCH — PRICE MOVE ±15%",IF(M28="Y","WATCH — ANALYST SHIFT","Monitor Only")),IF(M28="Y","WATCH — ANALYST SHIFT","Monitor Only"))))),IF(I28<>"",IF(ABS(I28)>=0.2,"DUE — PRICE MOVE ±20%",IF(K28="Y","DUE — INSIDER ACTIVITY",IF(I28<>"",IF(ABS(I28)>=0.15,"WATCH — PRICE MOVE ±15%",IF(M28="Y","WATCH — ANALYST SHIFT","Monitor Only")),IF(M28="Y","WATCH — ANALYST SHIFT","Monitor Only")))),IF(K28="Y","DUE — INSIDER ACTIVITY",IF(I28<>"",IF(ABS(I28)>=0.15,"WATCH — PRICE MOVE ±15%",IF(M28="Y","WATCH — ANALYST SHIFT","Monitor Only")),IF(M28="Y","WATCH — ANALYST SHIFT","Monitor Only"))))))) -> DUE — INSIDER ACTIVITY
A29: ETSY | B29: Watch List | C29: 46246 | E29: 3.43 | G29: 79.63 | H29: {=IFERROR(INDEX(_xlfn.stockhistory(A29,TODAY()-5,TODAY(),0,0,1),ROWS(_xlfn.stockhistory(A29,TODAY()-5,TODAY(),0,0,1)),1),"")} | I29: =IF(OR(G29="",H29=""),"",H29/G29-1) | J29: 46330 | K29: Y | L29: 2026-08-19: Buckley Merilee (CHIEF ACCOUNTING OFFICER) sold $18,850, 59% of holding (+9 more in last 30d) | M29: N | O29: =IF(C29="","",TODAY()-C29) -> 49 | P29: =IF(A29="","",IF(O29>180,"DUE — STALE (>180 days)",IF(J29<>"",IF(ABS(J29-TODAY())<=7,"DUE — EARNINGS WINDOW",IF(I29<>"",IF(ABS(I29)>=0.2,"DUE — PRICE MOVE ±20%",IF(K29="Y","DUE — INSIDER ACTIVITY",IF(I29<>"",IF(ABS(I29)>=0.15,"WATCH — PRICE MOVE ±15%",IF(M29="Y","WATCH — ANALYST SHIFT","Monitor Only")),IF(M29="Y","WATCH — ANALYST SHIFT","Monitor Only")))),IF(K29="Y","DUE — INSIDER ACTIVITY",IF(I29<>"",IF(ABS(I29)>=0.15,"WATCH — PRICE MOVE ±15%",IF(M29="Y","WATCH — ANALYST SHIFT","Monitor Only")),IF(M29="Y","WATCH — ANALYST SHIFT","Monitor Only"))))),IF(I29<>"",IF(ABS(I29)>=0.2,"DUE — PRICE MOVE ±20%",IF(K29="Y","DUE — INSIDER ACTIVITY",IF(I29<>"",IF(ABS(I29)>=0.15,"WATCH — PRICE MOVE ±15%",IF(M29="Y","WATCH — ANALYST SHIFT","Monitor Only")),IF(M29="Y","WATCH — ANALYST SHIFT","Monitor Only")))),IF(K29="Y","DUE — INSIDER ACTIVITY",IF(I29<>"",IF(ABS(I29)>=0.15,"WATCH — PRICE MOVE ±15%",IF(M29="Y","WATCH — ANALYST SHIFT","Monitor Only")),IF(M29="Y","WATCH — ANALYST SHIFT","Monitor Only"))))))) -> DUE — INSIDER ACTIVITY
A30: GE | B30: Owned | C30: 46247 | E30: 3.86 | G30: 360.64 | H30: {=IFERROR(INDEX(_xlfn.stockhistory(A30,TODAY()-5,TODAY(),0,0,1),ROWS(_xlfn.stockhistory(A30,TODAY()-5,TODAY(),0,0,1)),1),"")} | I30: =IF(OR(G30="",H30=""),"",H30/G30-1) | J30: 46315 | K30: Y | L30: 2026-08-12: Giglietti Robert M. (Vice President) sold $1,976,639, 18% of holding (+7 more in last 30d) | M30: N | O30: =IF(C30="","",TODAY()-C30) -> 48 | P30: =IF(A30="","",IF(O30>180,"DUE — STALE (>180 days)",IF(J30<>"",IF(ABS(J30-TODAY())<=7,"DUE — EARNINGS WINDOW",IF(I30<>"",IF(ABS(I30)>=0.2,"DUE — PRICE MOVE ±20%",IF(K30="Y","DUE — INSIDER ACTIVITY",IF(I30<>"",IF(ABS(I30)>=0.15,"WATCH — PRICE MOVE ±15%",IF(M30="Y","WATCH — ANALYST SHIFT","Monitor Only")),IF(M30="Y","WATCH — ANALYST SHIFT","Monitor Only")))),IF(K30="Y","DUE — INSIDER ACTIVITY",IF(I30<>"",IF(ABS(I30)>=0.15,"WATCH — PRICE MOVE ±15%",IF(M30="Y","WATCH — ANALYST SHIFT","Monitor Only")),IF(M30="Y","WATCH — ANALYST SHIFT","Monitor Only"))))),IF(I30<>"",IF(ABS(I30)>=0.2,"DUE — PRICE MOVE ±20%",IF(K30="Y","DUE — INSIDER ACTIVITY",IF(I30<>"",IF(ABS(I30)>=0.15,"WATCH — PRICE MOVE ±15%",IF(M30="Y","WATCH — ANALYST SHIFT","Monitor Only")),IF(M30="Y","WATCH — ANALYST SHIFT","Monitor Only")))),IF(K30="Y","DUE — INSIDER ACTIVITY",IF(I30<>"",IF(ABS(I30)>=0.15,"WATCH — PRICE MOVE ±15%",IF(M30="Y","WATCH — ANALYST SHIFT","Monitor Only")),IF(M30="Y","WATCH — ANALYST SHIFT","Monitor Only"))))))) -> DUE — INSIDER ACTIVITY
A31: GOOS | B31: Tier-1 Avoid (external) | C31: 46246 | E31: 2.5 | G31: 8.64 | H31: {=IFERROR(INDEX(_xlfn.stockhistory(A31,TODAY()-5,TODAY(),0,0,1),ROWS(_xlfn.stockhistory(A31,TODAY()-5,TODAY(),0,0,1)),1),"")} | I31: =IF(OR(G31="",H31=""),"",H31/G31-1) | J31: 46331 | K31: N | O31: =IF(C31="","",TODAY()-C31) -> 49 | P31: =IF(A31="","",IF(O31>180,"DUE — STALE (>180 days)",IF(J31<>"",IF(ABS(J31-TODAY())<=7,"DUE — EARNINGS WINDOW",IF(I31<>"",IF(ABS(I31)>=0.2,"DUE — PRICE MOVE ±20%",IF(K31="Y","DUE — INSIDER ACTIVITY",IF(I31<>"",IF(ABS(I31)>=0.15,"WATCH — PRICE MOVE ±15%",IF(M31="Y","WATCH — ANALYST SHIFT","Monitor Only")),IF(M31="Y","WATCH — ANALYST SHIFT","Monitor Only")))),IF(K31="Y","DUE — INSIDER ACTIVITY",IF(I31<>"",IF(ABS(I31)>=0.15,"WATCH — PRICE MOVE ±15%",IF(M31="Y","WATCH — ANALYST SHIFT","Monitor Only")),IF(M31="Y","WATCH — ANALYST SHIFT","Monitor Only"))))),IF(I31<>"",IF(ABS(I31)>=0.2,"DUE — PRICE MOVE ±20%",IF(K31="Y","DUE — INSIDER ACTIVITY",IF(I31<>"",IF(ABS(I31)>=0.15,"WATCH — PRICE MOVE ±15%",IF(M31="Y","WATCH — ANALYST SHIFT","Monitor Only")),IF(M31="Y","WATCH — ANALYST SHIFT","Monitor Only")))),IF(K31="Y","DUE — INSIDER ACTIVITY",IF(I31<>"",IF(ABS(I31)>=0.15,"WATCH — PRICE MOVE ±15%",IF(M31="Y","WATCH — ANALYST SHIFT","Monitor Only")),IF(M31="Y","WATCH — ANALYST SHIFT","Monitor Only"))))))) -> Monitor Only
A32: HRL | B32: Tier-1 Avoid (external) | C32: 46245 | E32: 1.93 | G32: 24.3 | H32: {=IFERROR(INDEX(_xlfn.stockhistory(A32,TODAY()-5,TODAY(),0,0,1),ROWS(_xlfn.stockhistory(A32,TODAY()-5,TODAY(),0,0,1)),1),"")} | I32: =IF(OR(G32="",H32=""),"",H32/G32-1) | J32: 46261 | K32: N | M32: N | O32: =IF(C32="","",TODAY()-C32) -> 50 | P32: =IF(A32="","",IF(O32>180,"DUE — STALE (>180 days)",IF(J32<>"",IF(ABS(J32-TODAY())<=7,"DUE — EARNINGS WINDOW",IF(I32<>"",IF(ABS(I32)>=0.2,"DUE — PRICE MOVE ±20%",IF(K32="Y","DUE — INSIDER ACTIVITY",IF(I32<>"",IF(ABS(I32)>=0.15,"WATCH — PRICE MOVE ±15%",IF(M32="Y","WATCH — ANALYST SHIFT","Monitor Only")),IF(M32="Y","WATCH — ANALYST SHIFT","Monitor Only")))),IF(K32="Y","DUE — INSIDER ACTIVITY",IF(I32<>"",IF(ABS(I32)>=0.15,"WATCH — PRICE MOVE ±15%",IF(M32="Y","WATCH — ANALYST SHIFT","Monitor Only")),IF(M32="Y","WATCH — ANALYST SHIFT","Monitor Only"))))),IF(I32<>"",IF(ABS(I32)>=0.2,"DUE — PRICE MOVE ±20%",IF(K32="Y","DUE — INSIDER ACTIVITY",IF(I32<>"",IF(ABS(I32)>=0.15,"WATCH — PRICE MOVE ±15%",IF(M32="Y","WATCH — ANALYST SHIFT","Monitor Only")),IF(M32="Y","WATCH — ANALYST SHIFT","Monitor Only")))),IF(K32="Y","DUE — INSIDER ACTIVITY",IF(I32<>"",IF(ABS(I32)>=0.15,"WATCH — PRICE MOVE ±15%",IF(M32="Y","WATCH — ANALYST SHIFT","Monitor Only")),IF(M32="Y","WATCH — ANALYST SHIFT","Monitor Only"))))))) -> Monitor Only
A33: LBRT | B33: Tier-1 Avoid (external) | C33: 46245 | E33: 2.07 | G33: 21.48 | H33: {=IFERROR(INDEX(_xlfn.stockhistory(A33,TODAY()-5,TODAY(),0,0,1),ROWS(_xlfn.stockhistory(A33,TODAY()-5,TODAY(),0,0,1)),1),"")} | I33: =IF(OR(G33="",H33=""),"",H33/G33-1) | J33: 46309 | K33: Y | L33: 2026-07-30: Murti Arjun N (Director) bought $250,009, 51% of holding | M33: N | O33: =IF(C33="","",TODAY()-C33) -> 50 | P33: =IF(A33="","",IF(O33>180,"DUE — STALE (>180 days)",IF(J33<>"",IF(ABS(J33-TODAY())<=7,"DUE — EARNINGS WINDOW",IF(I33<>"",IF(ABS(I33)>=0.2,"DUE — PRICE MOVE ±20%",IF(K33="Y","DUE — INSIDER ACTIVITY",IF(I33<>"",IF(ABS(I33)>=0.15,"WATCH — PRICE MOVE ±15%",IF(M33="Y","WATCH — ANALYST SHIFT","Monitor Only")),IF(M33="Y","WATCH — ANALYST SHIFT","Monitor Only")))),IF(K33="Y","DUE — INSIDER ACTIVITY",IF(I33<>"",IF(ABS(I33)>=0.15,"WATCH — PRICE MOVE ±15%",IF(M33="Y","WATCH — ANALYST SHIFT","Monitor Only")),IF(M33="Y","WATCH — ANALYST SHIFT","Monitor Only"))))),IF(I33<>"",IF(ABS(I33)>=0.2,"DUE — PRICE MOVE ±20%",IF(K33="Y","DUE — INSIDER ACTIVITY",IF(I33<>"",IF(ABS(I33)>=0.15,"WATCH — PRICE MOVE ±15%",IF(M33="Y","WATCH — ANALYST SHIFT","Monitor Only")),IF(M33="Y","WATCH — ANALYST SHIFT","Monitor Only")))),IF(K33="Y","DUE — INSIDER ACTIVITY",IF(I33<>"",IF(ABS(I33)>=0.15,"WATCH — PRICE MOVE ±15%",IF(M33="Y","WATCH — ANALYST SHIFT","Monitor Only")),IF(M33="Y","WATCH — ANALYST SHIFT","Monitor Only"))))))) -> DUE — INSIDER ACTIVITY
A34: LIN | B34: Watch List | C34: 46245 | E34: 4.5 | G34: 490.53 | H34: {=IFERROR(INDEX(_xlfn.stockhistory(A34,TODAY()-5,TODAY(),0,0,1),ROWS(_xlfn.stockhistory(A34,TODAY()-5,TODAY(),0,0,1)),1),"")} | I34: =IF(OR(G34="",H34=""),"",H34/G34-1) | J34: 46325 | K34: Y | L34: 2026-08-19: Reynolds Paula Rosput (Director) bought $47,912, 14% of holding | M34: N | O34: =IF(C34="","",TODAY()-C34) -> 50 | P34: =IF(A34="","",IF(O34>180,"DUE — STALE (>180 days)",IF(J34<>"",IF(ABS(J34-TODAY())<=7,"DUE — EARNINGS WINDOW",IF(I34<>"",IF(ABS(I34)>=0.2,"DUE — PRICE MOVE ±20%",IF(K34="Y","DUE — INSIDER ACTIVITY",IF(I34<>"",IF(ABS(I34)>=0.15,"WATCH — PRICE MOVE ±15%",IF(M34="Y","WATCH — ANALYST SHIFT","Monitor Only")),IF(M34="Y","WATCH — ANALYST SHIFT","Monitor Only")))),IF(K34="Y","DUE — INSIDER ACTIVITY",IF(I34<>"",IF(ABS(I34)>=0.15,"WATCH — PRICE MOVE ±15%",IF(M34="Y","WATCH — ANALYST SHIFT","Monitor Only")),IF(M34="Y","WATCH — ANALYST SHIFT","Monitor Only"))))),IF(I34<>"",IF(ABS(I34)>=0.2,"DUE — PRICE MOVE ±20%",IF(K34="Y","DUE — INSIDER ACTIVITY",IF(I34<>"",IF(ABS(I34)>=0.15,"WATCH — PRICE MOVE ±15%",IF(M34="Y","WATCH — ANALYST SHIFT","Monitor Only")),IF(M34="Y","WATCH — ANALYST SHIFT","Monitor Only")))),IF(K34="Y","DUE — INSIDER ACTIVITY",IF(I34<>"",IF(ABS(I34)>=0.15,"WATCH — PRICE MOVE ±15%",IF(M34="Y","WATCH — ANALYST SHIFT","Monitor Only")),IF(M34="Y","WATCH — ANALYST SHIFT","Monitor Only"))))))) -> DUE — INSIDER ACTIVITY
A35: NEE | B35: Tier-1 Avoid (external) | C35: 46245 | E35: 2.5 | G35: 85.74 | H35: {=IFERROR(INDEX(_xlfn.stockhistory(A35,TODAY()-5,TODAY(),0,0,1),ROWS(_xlfn.stockhistory(A35,TODAY()-5,TODAY(),0,0,1)),1),"")} | I35: =IF(OR(G35="",H35=""),"",H35/G35-1) | J35: 46322 | K35: N | M35: N | O35: =IF(C35="","",TODAY()-C35) -> 50 | P35: =IF(A35="","",IF(O35>180,"DUE — STALE (>180 days)",IF(J35<>"",IF(ABS(J35-TODAY())<=7,"DUE — EARNINGS WINDOW",IF(I35<>"",IF(ABS(I35)>=0.2,"DUE — PRICE MOVE ±20%",IF(K35="Y","DUE — INSIDER ACTIVITY",IF(I35<>"",IF(ABS(I35)>=0.15,"WATCH — PRICE MOVE ±15%",IF(M35="Y","WATCH — ANALYST SHIFT","Monitor Only")),IF(M35="Y","WATCH — ANALYST SHIFT","Monitor Only")))),IF(K35="Y","DUE — INSIDER ACTIVITY",IF(I35<>"",IF(ABS(I35)>=0.15,"WATCH — PRICE MOVE ±15%",IF(M35="Y","WATCH — ANALYST SHIFT","Monitor Only")),IF(M35="Y","WATCH — ANALYST SHIFT","Monitor Only"))))),IF(I35<>"",IF(ABS(I35)>=0.2,"DUE — PRICE MOVE ±20%",IF(K35="Y","DUE — INSIDER ACTIVITY",IF(I35<>"",IF(ABS(I35)>=0.15,"WATCH — PRICE MOVE ±15%",IF(M35="Y","WATCH — ANALYST SHIFT","Monitor Only")),IF(M35="Y","WATCH — ANALYST SHIFT","Monitor Only")))),IF(K35="Y","DUE — INSIDER ACTIVITY",IF(I35<>"",IF(ABS(I35)>=0.15,"WATCH — PRICE MOVE ±15%",IF(M35="Y","WATCH — ANALYST SHIFT","Monitor Only")),IF(M35="Y","WATCH — ANALYST SHIFT","Monitor Only"))))))) -> Monitor Only
A36: NFLX | B36: Owned | C36: 46258 | E36: 4.21 | G36: 80.01 | H36: {=IFERROR(INDEX(_xlfn.stockhistory(A36,TODAY()-5,TODAY(),0,0,1),ROWS(_xlfn.stockhistory(A36,TODAY()-5,TODAY(),0,0,1)),1),"")} | I36: =IF(OR(G36="",H36=""),"",H36/G36-1) | J36: 46315 | K36: Y | L36: 2026-08-10: Neumann Spencer Adam (Chief Financial Officer) sold $700,907, 11% of holding (+6 more in last 30d) | M36: N | O36: =IF(C36="","",TODAY()-C36) -> 37 | P36: =IF(A36="","",IF(O36>180,"DUE — STALE (>180 days)",IF(J36<>"",IF(ABS(J36-TODAY())<=7,"DUE — EARNINGS WINDOW",IF(I36<>"",IF(ABS(I36)>=0.2,"DUE — PRICE MOVE ±20%",IF(K36="Y","DUE — INSIDER ACTIVITY",IF(I36<>"",IF(ABS(I36)>=0.15,"WATCH — PRICE MOVE ±15%",IF(M36="Y","WATCH — ANALYST SHIFT","Monitor Only")),IF(M36="Y","WATCH — ANALYST SHIFT","Monitor Only")))),IF(K36="Y","DUE — INSIDER ACTIVITY",IF(I36<>"",IF(ABS(I36)>=0.15,"WATCH — PRICE MOVE ±15%",IF(M36="Y","WATCH — ANALYST SHIFT","Monitor Only")),IF(M36="Y","WATCH — ANALYST SHIFT","Monitor Only"))))),IF(I36<>"",IF(ABS(I36)>=0.2,"DUE — PRICE MOVE ±20%",IF(K36="Y","DUE — INSIDER ACTIVITY",IF(I36<>"",IF(ABS(I36)>=0.15,"WATCH — PRICE MOVE ±15%",IF(M36="Y","WATCH — ANALYST SHIFT","Monitor Only")),IF(M36="Y","WATCH — ANALYST SHIFT","Monitor Only")))),IF(K36="Y","DUE — INSIDER ACTIVITY",IF(I36<>"",IF(ABS(I36)>=0.15,"WATCH — PRICE MOVE ±15%",IF(M36="Y","WATCH — ANALYST SHIFT","Monitor Only")),IF(M36="Y","WATCH — ANALYST SHIFT","Monitor Only"))))))) -> DUE — INSIDER ACTIVITY
A37: NKE | B37: Tier-1 Avoid (external) | C37: 46246 | E37: 1.57 | G37: 40.51 | H37: {=IFERROR(INDEX(_xlfn.stockhistory(A37,TODAY()-5,TODAY(),0,0,1),ROWS(_xlfn.stockhistory(A37,TODAY()-5,TODAY(),0,0,1)),1),"")} | I37: =IF(OR(G37="",H37=""),"",H37/G37-1) | J37: 46294 | K37: Y | L37: 2026-08-11: Montagne Amy (PRESIDENT, NIKE) sold $204,657, 8% of holding (+1 more in last 30d) | M37: Y | N37: Consensus declined 0.19 (1-5 scale) over 3 months (3.39 -> 3.21, 39 analysts currently) | O37: =IF(C37="","",TODAY()-C37) -> 49 | P37: =IF(A37="","",IF(O37>180,"DUE — STALE (>180 days)",IF(J37<>"",IF(ABS(J37-TODAY())<=7,"DUE — EARNINGS WINDOW",IF(I37<>"",IF(ABS(I37)>=0.2,"DUE — PRICE MOVE ±20%",IF(K37="Y","DUE — INSIDER ACTIVITY",IF(I37<>"",IF(ABS(I37)>=0.15,"WATCH — PRICE MOVE ±15%",IF(M37="Y","WATCH — ANALYST SHIFT","Monitor Only")),IF(M37="Y","WATCH — ANALYST SHIFT","Monitor Only")))),IF(K37="Y","DUE — INSIDER ACTIVITY",IF(I37<>"",IF(ABS(I37)>=0.15,"WATCH — PRICE MOVE ±15%",IF(M37="Y","WATCH — ANALYST SHIFT","Monitor Only")),IF(M37="Y","WATCH — ANALYST SHIFT","Monitor Only"))))),IF(I37<>"",IF(ABS(I37)>=0.2,"DUE — PRICE MOVE ±20%",IF(K37="Y","DUE — INSIDER ACTIVITY",IF(I37<>"",IF(ABS(I37)>=0.15,"WATCH — PRICE MOVE ±15%",IF(M37="Y","WATCH — ANALYST SHIFT","Monitor Only")),IF(M37="Y","WATCH — ANALYST SHIFT","Monitor Only")))),IF(K37="Y","DUE — INSIDER ACTIVITY",IF(I37<>"",IF(ABS(I37)>=0.15,"WATCH — PRICE MOVE ±15%",IF(M37="Y","WATCH — ANALYST SHIFT","Monitor Only")),IF(M37="Y","WATCH — ANALYST SHIFT","Monitor Only"))))))) -> DUE — EARNINGS WINDOW
A38: NOV | B38: Tier-1 Avoid (external) | C38: 46245 | E38: 2.64 | G38: 21.02 | H38: {=IFERROR(INDEX(_xlfn.stockhistory(A38,TODAY()-5,TODAY(),0,0,1),ROWS(_xlfn.stockhistory(A38,TODAY()-5,TODAY(),0,0,1)),1),"")} | I38: =IF(OR(G38="",H38=""),"",H38/G38-1) | J38: 46321 | K38: Y | L38: 2026-07-31: HARRISON DAVID D (Other) sold $184,301, 7% of holding | M38: Y | N38: Consensus improved 0.21 (1-5 scale) over 3 months (3.19 -> 3.40, 20 analysts currently) | O38: =IF(C38="","",TODAY()-C38) -> 50 | P38: =IF(A38="","",IF(O38>180,"DUE — STALE (>180 days)",IF(J38<>"",IF(ABS(J38-TODAY())<=7,"DUE — EARNINGS WINDOW",IF(I38<>"",IF(ABS(I38)>=0.2,"DUE — PRICE MOVE ±20%",IF(K38="Y","DUE — INSIDER ACTIVITY",IF(I38<>"",IF(ABS(I38)>=0.15,"WATCH — PRICE MOVE ±15%",IF(M38="Y","WATCH — ANALYST SHIFT","Monitor Only")),IF(M38="Y","WATCH — ANALYST SHIFT","Monitor Only")))),IF(K38="Y","DUE — INSIDER ACTIVITY",IF(I38<>"",IF(ABS(I38)>=0.15,"WATCH — PRICE MOVE ±15%",IF(M38="Y","WATCH — ANALYST SHIFT","Monitor Only")),IF(M38="Y","WATCH — ANALYST SHIFT","Monitor Only"))))),IF(I38<>"",IF(ABS(I38)>=0.2,"DUE — PRICE MOVE ±20%",IF(K38="Y","DUE — INSIDER ACTIVITY",IF(I38<>"",IF(ABS(I38)>=0.15,"WATCH — PRICE MOVE ±15%",IF(M38="Y","WATCH — ANALYST SHIFT","Monitor Only")),IF(M38="Y","WATCH — ANALYST SHIFT","Monitor Only")))),IF(K38="Y","DUE — INSIDER ACTIVITY",IF(I38<>"",IF(ABS(I38)>=0.15,"WATCH — PRICE MOVE ±15%",IF(M38="Y","WATCH — ANALYST SHIFT","Monitor Only")),IF(M38="Y","WATCH — ANALYST SHIFT","Monitor Only"))))))) -> DUE — INSIDER ACTIVITY
A39: ONON | B39: Tier-1 Avoid (external) | C39: 46240 | E39: 2.64 | G39: 37.34 | H39: {=IFERROR(INDEX(_xlfn.stockhistory(A39,TODAY()-5,TODAY(),0,0,1),ROWS(_xlfn.stockhistory(A39,TODAY()-5,TODAY(),0,0,1)),1),"")} | I39: =IF(OR(G39="",H39=""),"",H39/G39-1) | J39: 46337 | K39: Y | L39: 2026-08-17: Bernhard Olivier (Executive Officer) bought $1,993,790, 1% of holding (+1 more in last 30d) | M39: N | O39: =IF(C39="","",TODAY()-C39) -> 55 | P39: =IF(A39="","",IF(O39>180,"DUE — STALE (>180 days)",IF(J39<>"",IF(ABS(J39-TODAY())<=7,"DUE — EARNINGS WINDOW",IF(I39<>"",IF(ABS(I39)>=0.2,"DUE — PRICE MOVE ±20%",IF(K39="Y","DUE — INSIDER ACTIVITY",IF(I39<>"",IF(ABS(I39)>=0.15,"WATCH — PRICE MOVE ±15%",IF(M39="Y","WATCH — ANALYST SHIFT","Monitor Only")),IF(M39="Y","WATCH — ANALYST SHIFT","Monitor Only")))),IF(K39="Y","DUE — INSIDER ACTIVITY",IF(I39<>"",IF(ABS(I39)>=0.15,"WATCH — PRICE MOVE ±15%",IF(M39="Y","WATCH — ANALYST SHIFT","Monitor Only")),IF(M39="Y","WATCH — ANALYST SHIFT","Monitor Only"))))),IF(I39<>"",IF(ABS(I39)>=0.2,"DUE — PRICE MOVE ±20%",IF(K39="Y","DUE — INSIDER ACTIVITY",IF(I39<>"",IF(ABS(I39)>=0.15,"WATCH — PRICE MOVE ±15%",IF(M39="Y","WATCH — ANALYST SHIFT","Monitor Only")),IF(M39="Y","WATCH — ANALYST SHIFT","Monitor Only")))),IF(K39="Y","DUE — INSIDER ACTIVITY",IF(I39<>"",IF(ABS(I39)>=0.15,"WATCH — PRICE MOVE ±15%",IF(M39="Y","WATCH — ANALYST SHIFT","Monitor Only")),IF(M39="Y","WATCH — ANALYST SHIFT","Monitor Only"))))))) -> DUE — INSIDER ACTIVITY
A40: PG | B40: Watch List | C40: 46245 | E40: 4.21 | G40: 145.21 | H40: {=IFERROR(INDEX(_xlfn.stockhistory(A40,TODAY()-5,TODAY(),0,0,1),ROWS(_xlfn.stockhistory(A40,TODAY()-5,TODAY(),0,0,1)),1),"")} | I40: =IF(OR(G40="",H40=""),"",H40/G40-1) | J40: 46317 | K40: Y | L40: 2026-08-24: Janzaruk Matthew W. (SVP - Chief Accounting Officer) sold $52,141, 22% of holding (+12 more in last 30d) | M40: N | O40: =IF(C40="","",TODAY()-C40) -> 50 | P40: =IF(A40="","",IF(O40>180,"DUE — STALE (>180 days)",IF(J40<>"",IF(ABS(J40-TODAY())<=7,"DUE — EARNINGS WINDOW",IF(I40<>"",IF(ABS(I40)>=0.2,"DUE — PRICE MOVE ±20%",IF(K40="Y","DUE — INSIDER ACTIVITY",IF(I40<>"",IF(ABS(I40)>=0.15,"WATCH — PRICE MOVE ±15%",IF(M40="Y","WATCH — ANALYST SHIFT","Monitor Only")),IF(M40="Y","WATCH — ANALYST SHIFT","Monitor Only")))),IF(K40="Y","DUE — INSIDER ACTIVITY",IF(I40<>"",IF(ABS(I40)>=0.15,"WATCH — PRICE MOVE ±15%",IF(M40="Y","WATCH — ANALYST SHIFT","Monitor Only")),IF(M40="Y","WATCH — ANALYST SHIFT","Monitor Only"))))),IF(I40<>"",IF(ABS(I40)>=0.2,"DUE — PRICE MOVE ±20%",IF(K40="Y","DUE — INSIDER ACTIVITY",IF(I40<>"",IF(ABS(I40)>=0.15,"WATCH — PRICE MOVE ±15%",IF(M40="Y","WATCH — ANALYST SHIFT","Monitor Only")),IF(M40="Y","WATCH — ANALYST SHIFT","Monitor Only")))),IF(K40="Y","DUE — INSIDER ACTIVITY",IF(I40<>"",IF(ABS(I40)>=0.15,"WATCH — PRICE MOVE ±15%",IF(M40="Y","WATCH — ANALYST SHIFT","Monitor Only")),IF(M40="Y","WATCH — ANALYST SHIFT","Monitor Only"))))))) -> DUE — INSIDER ACTIVITY
A41: PH | B41: Watch List | C41: 46247 | E41: 3.29 | G41: 1058.87 | H41: {=IFERROR(INDEX(_xlfn.stockhistory(A41,TODAY()-5,TODAY(),0,0,1),ROWS(_xlfn.stockhistory(A41,TODAY()-5,TODAY(),0,0,1)),1),"")} | I41: =IF(OR(G41="",H41=""),"",H41/G41-1) | J41: 46331 | K41: Y | L41: 2026-08-19: Scott Patrick (VP & Pres-Fluid Conn. Grp.) sold $1,294,800, 25% of holding (+12 more in last 30d) | M41: N | O41: =IF(C41="","",TODAY()-C41) -> 48 | P41: =IF(A41="","",IF(O41>180,"DUE — STALE (>180 days)",IF(J41<>"",IF(ABS(J41-TODAY())<=7,"DUE — EARNINGS WINDOW",IF(I41<>"",IF(ABS(I41)>=0.2,"DUE — PRICE MOVE ±20%",IF(K41="Y","DUE — INSIDER ACTIVITY",IF(I41<>"",IF(ABS(I41)>=0.15,"WATCH — PRICE MOVE ±15%",IF(M41="Y","WATCH — ANALYST SHIFT","Monitor Only")),IF(M41="Y","WATCH — ANALYST SHIFT","Monitor Only")))),IF(K41="Y","DUE — INSIDER ACTIVITY",IF(I41<>"",IF(ABS(I41)>=0.15,"WATCH — PRICE MOVE ±15%",IF(M41="Y","WATCH — ANALYST SHIFT","Monitor Only")),IF(M41="Y","WATCH — ANALYST SHIFT","Monitor Only"))))),IF(I41<>"",IF(ABS(I41)>=0.2,"DUE — PRICE MOVE ±20%",IF(K41="Y","DUE — INSIDER ACTIVITY",IF(I41<>"",IF(ABS(I41)>=0.15,"WATCH — PRICE MOVE ±15%",IF(M41="Y","WATCH — ANALYST SHIFT","Monitor Only")),IF(M41="Y","WATCH — ANALYST SHIFT","Monitor Only")))),IF(K41="Y","DUE — INSIDER ACTIVITY",IF(I41<>"",IF(ABS(I41)>=0.15,"WATCH — PRICE MOVE ±15%",IF(M41="Y","WATCH — ANALYST SHIFT","Monitor Only")),IF(M41="Y","WATCH — ANALYST SHIFT","Monitor Only"))))))) -> DUE — INSIDER ACTIVITY
A42: PZZA | B42: Tier-1 Avoid (external) | C42: 46245 | E42: 1.36 | G42: 24.32 | H42: {=IFERROR(INDEX(_xlfn.stockhistory(A42,TODAY()-5,TODAY(),0,0,1),ROWS(_xlfn.stockhistory(A42,TODAY()-5,TODAY(),0,0,1)),1),"")} | I42: =IF(OR(G42="",H42=""),"",H42/G42-1) | J42: 46331 | K42: N | M42: Y | N42: Consensus declined 0.29 (1-5 scale) over 3 months (3.29 -> 3.00, 14 analysts currently) | O42: =IF(C42="","",TODAY()-C42) -> 50 | P42: =IF(A42="","",IF(O42>180,"DUE — STALE (>180 days)",IF(J42<>"",IF(ABS(J42-TODAY())<=7,"DUE — EARNINGS WINDOW",IF(I42<>"",IF(ABS(I42)>=0.2,"DUE — PRICE MOVE ±20%",IF(K42="Y","DUE — INSIDER ACTIVITY",IF(I42<>"",IF(ABS(I42)>=0.15,"WATCH — PRICE MOVE ±15%",IF(M42="Y","WATCH — ANALYST SHIFT","Monitor Only")),IF(M42="Y","WATCH — ANALYST SHIFT","Monitor Only")))),IF(K42="Y","DUE — INSIDER ACTIVITY",IF(I42<>"",IF(ABS(I42)>=0.15,"WATCH — PRICE MOVE ±15%",IF(M42="Y","WATCH — ANALYST SHIFT","Monitor Only")),IF(M42="Y","WATCH — ANALYST SHIFT","Monitor Only"))))),IF(I42<>"",IF(ABS(I42)>=0.2,"DUE — PRICE MOVE ±20%",IF(K42="Y","DUE — INSIDER ACTIVITY",IF(I42<>"",IF(ABS(I42)>=0.15,"WATCH — PRICE MOVE ±15%",IF(M42="Y","WATCH — ANALYST SHIFT","Monitor Only")),IF(M42="Y","WATCH — ANALYST SHIFT","Monitor Only")))),IF(K42="Y","DUE — INSIDER ACTIVITY",IF(I42<>"",IF(ABS(I42)>=0.15,"WATCH — PRICE MOVE ±15%",IF(M42="Y","WATCH — ANALYST SHIFT","Monitor Only")),IF(M42="Y","WATCH — ANALYST SHIFT","Monitor Only"))))))) -> WATCH — ANALYST SHIFT
A43: SFM | B43: Tier-1 Avoid (external) | C43: 46240 | E43: 1.86 | G43: 87.2 | H43: {=IFERROR(INDEX(_xlfn.stockhistory(A43,TODAY()-5,TODAY(),0,0,1),ROWS(_xlfn.stockhistory(A43,TODAY()-5,TODAY(),0,0,1)),1),"")} | I43: =IF(OR(G43="",H43=""),"",H43/G43-1) | J43: 46323 | K43: Y | L43: 2026-08-17: O'Leary Joseph D (Director) sold $214,440, 15% of holding (+2 more in last 30d) | M43: N | O43: =IF(C43="","",TODAY()-C43) -> 55 | P43: =IF(A43="","",IF(O43>180,"DUE — STALE (>180 days)",IF(J43<>"",IF(ABS(J43-TODAY())<=7,"DUE — EARNINGS WINDOW",IF(I43<>"",IF(ABS(I43)>=0.2,"DUE — PRICE MOVE ±20%",IF(K43="Y","DUE — INSIDER ACTIVITY",IF(I43<>"",IF(ABS(I43)>=0.15,"WATCH — PRICE MOVE ±15%",IF(M43="Y","WATCH — ANALYST SHIFT","Monitor Only")),IF(M43="Y","WATCH — ANALYST SHIFT","Monitor Only")))),IF(K43="Y","DUE — INSIDER ACTIVITY",IF(I43<>"",IF(ABS(I43)>=0.15,"WATCH — PRICE MOVE ±15%",IF(M43="Y","WATCH — ANALYST SHIFT","Monitor Only")),IF(M43="Y","WATCH — ANALYST SHIFT","Monitor Only"))))),IF(I43<>"",IF(ABS(I43)>=0.2,"DUE — PRICE MOVE ±20%",IF(K43="Y","DUE — INSIDER ACTIVITY",IF(I43<>"",IF(ABS(I43)>=0.15,"WATCH — PRICE MOVE ±15%",IF(M43="Y","WATCH — ANALYST SHIFT","Monitor Only")),IF(M43="Y","WATCH — ANALYST SHIFT","Monitor Only")))),IF(K43="Y","DUE — INSIDER ACTIVITY",IF(I43<>"",IF(ABS(I43)>=0.15,"WATCH — PRICE MOVE ±15%",IF(M43="Y","WATCH — ANALYST SHIFT","Monitor Only")),IF(M43="Y","WATCH — ANALYST SHIFT","Monitor Only"))))))) -> DUE — INSIDER ACTIVITY
A44: TSLA | B44: Tier-1 Avoid (external) | C44: 46240 | E44: 1.93 | G44: 319.53 | H44: {=IFERROR(INDEX(_xlfn.stockhistory(A44,TODAY()-5,TODAY(),0,0,1),ROWS(_xlfn.stockhistory(A44,TODAY()-5,TODAY(),0,0,1)),1),"")} | I44: =IF(OR(G44="",H44=""),"",H44/G44-1) | J44: 46316 | K44: N | M44: N | O44: =IF(C44="","",TODAY()-C44) -> 55 | P44: =IF(A44="","",IF(O44>180,"DUE — STALE (>180 days)",IF(J44<>"",IF(ABS(J44-TODAY())<=7,"DUE — EARNINGS WINDOW",IF(I44<>"",IF(ABS(I44)>=0.2,"DUE — PRICE MOVE ±20%",IF(K44="Y","DUE — INSIDER ACTIVITY",IF(I44<>"",IF(ABS(I44)>=0.15,"WATCH — PRICE MOVE ±15%",IF(M44="Y","WATCH — ANALYST SHIFT","Monitor Only")),IF(M44="Y","WATCH — ANALYST SHIFT","Monitor Only")))),IF(K44="Y","DUE — INSIDER ACTIVITY",IF(I44<>"",IF(ABS(I44)>=0.15,"WATCH — PRICE MOVE ±15%",IF(M44="Y","WATCH — ANALYST SHIFT","Monitor Only")),IF(M44="Y","WATCH — ANALYST SHIFT","Monitor Only"))))),IF(I44<>"",IF(ABS(I44)>=0.2,"DUE — PRICE MOVE ±20%",IF(K44="Y","DUE — INSIDER ACTIVITY",IF(I44<>"",IF(ABS(I44)>=0.15,"WATCH — PRICE MOVE ±15%",IF(M44="Y","WATCH — ANALYST SHIFT","Monitor Only")),IF(M44="Y","WATCH — ANALYST SHIFT","Monitor Only")))),IF(K44="Y","DUE — INSIDER ACTIVITY",IF(I44<>"",IF(ABS(I44)>=0.15,"WATCH — PRICE MOVE ±15%",IF(M44="Y","WATCH — ANALYST SHIFT","Monitor Only")),IF(M44="Y","WATCH — ANALYST SHIFT","Monitor Only"))))))) -> Monitor Only
A45: V | B45: Owned | C45: 46245 | D45: 86.4 | E45: 4.57 | F45: STRONG BUY | G45: 362.82 | H45: {=IFERROR(INDEX(_xlfn.stockhistory(A45,TODAY()-5,TODAY(),0,0,1),ROWS(_xlfn.stockhistory(A45,TODAY()-5,TODAY(),0,0,1)),1),"")} | I45: =IF(OR(G45="",H45=""),"",H45/G45-1) | J45: 46322 | K45: Y | L45: 2026-09-02: MCINERNEY RYAN (Chief Executive Officer) sold $2,230,444, 28% of holding (+3 more in last 30d) | M45: N | O45: =IF(C45="","",TODAY()-C45) -> 50 | P45: =IF(A45="","",IF(O45>180,"DUE — STALE (>180 days)",IF(J45<>"",IF(ABS(J45-TODAY())<=7,"DUE — EARNINGS WINDOW",IF(I45<>"",IF(ABS(I45)>=0.2,"DUE — PRICE MOVE ±20%",IF(K45="Y","DUE — INSIDER ACTIVITY",IF(I45<>"",IF(ABS(I45)>=0.15,"WATCH — PRICE MOVE ±15%",IF(M45="Y","WATCH — ANALYST SHIFT","Monitor Only")),IF(M45="Y","WATCH — ANALYST SHIFT","Monitor Only")))),IF(K45="Y","DUE — INSIDER ACTIVITY",IF(I45<>"",IF(ABS(I45)>=0.15,"WATCH — PRICE MOVE ±15%",IF(M45="Y","WATCH — ANALYST SHIFT","Monitor Only")),IF(M45="Y","WATCH — ANALYST SHIFT","Monitor Only"))))),IF(I45<>"",IF(ABS(I45)>=0.2,"DUE — PRICE MOVE ±20%",IF(K45="Y","DUE — INSIDER ACTIVITY",IF(I45<>"",IF(ABS(I45)>=0.15,"WATCH — PRICE MOVE ±15%",IF(M45="Y","WATCH — ANALYST SHIFT","Monitor Only")),IF(M45="Y","WATCH — ANALYST SHIFT","Monitor Only")))),IF(K45="Y","DUE — INSIDER ACTIVITY",IF(I45<>"",IF(ABS(I45)>=0.15,"WATCH — PRICE MOVE ±15%",IF(M45="Y","WATCH — ANALYST SHIFT","Monitor Only")),IF(M45="Y","WATCH — ANALYST SHIFT","Monitor Only"))))))) -> DUE — INSIDER ACTIVITY
A46: VFC | B46: Tier-1 Avoid (external) | C46: 46246 | E46: 2.86 | G46: 14.57 | H46: {=IFERROR(INDEX(_xlfn.stockhistory(A46,TODAY()-5,TODAY(),0,0,1),ROWS(_xlfn.stockhistory(A46,TODAY()-5,TODAY(),0,0,1)),1),"")} | I46: =IF(OR(G46="",H46=""),"",H46/G46-1) | J46: 46321 | K46: Y | L46: 2026-08-17: Carucci Richard (Director) bought $294,600, 6% of holding (+1 more in last 30d) | M46: N | O46: =IF(C46="","",TODAY()-C46) -> 49 | P46: =IF(A46="","",IF(O46>180,"DUE — STALE (>180 days)",IF(J46<>"",IF(ABS(J46-TODAY())<=7,"DUE — EARNINGS WINDOW",IF(I46<>"",IF(ABS(I46)>=0.2,"DUE — PRICE MOVE ±20%",IF(K46="Y","DUE — INSIDER ACTIVITY",IF(I46<>"",IF(ABS(I46)>=0.15,"WATCH — PRICE MOVE ±15%",IF(M46="Y","WATCH — ANALYST SHIFT","Monitor Only")),IF(M46="Y","WATCH — ANALYST SHIFT","Monitor Only")))),IF(K46="Y","DUE — INSIDER ACTIVITY",IF(I46<>"",IF(ABS(I46)>=0.15,"WATCH — PRICE MOVE ±15%",IF(M46="Y","WATCH — ANALYST SHIFT","Monitor Only")),IF(M46="Y","WATCH — ANALYST SHIFT","Monitor Only"))))),IF(I46<>"",IF(ABS(I46)>=0.2,"DUE — PRICE MOVE ±20%",IF(K46="Y","DUE — INSIDER ACTIVITY",IF(I46<>"",IF(ABS(I46)>=0.15,"WATCH — PRICE MOVE ±15%",IF(M46="Y","WATCH — ANALYST SHIFT","Monitor Only")),IF(M46="Y","WATCH — ANALYST SHIFT","Monitor Only")))),IF(K46="Y","DUE — INSIDER ACTIVITY",IF(I46<>"",IF(ABS(I46)>=0.15,"WATCH — PRICE MOVE ±15%",IF(M46="Y","WATCH — ANALYST SHIFT","Monitor Only")),IF(M46="Y","WATCH — ANALYST SHIFT","Monitor Only"))))))) -> DUE — INSIDER ACTIVITY
A47: YUM | B47: Watch List | C47: 46245 | E47: 4.29 | G47: 144.75 | H47: {=IFERROR(INDEX(_xlfn.stockhistory(A47,TODAY()-5,TODAY(),0,0,1),ROWS(_xlfn.stockhistory(A47,TODAY()-5,TODAY(),0,0,1)),1),"")} | I47: =IF(OR(G47="",H47=""),"",H47/G47-1) | J47: 46329 | K47: Y | L47: 2026-08-24: Skeans Tracy L (COO and CPO) sold $552,052, 100% of holding (+2 more in last 30d) | M47: N | O47: =IF(C47="","",TODAY()-C47) -> 50 | P47: =IF(A47="","",IF(O47>180,"DUE — STALE (>180 days)",IF(J47<>"",IF(ABS(J47-TODAY())<=7,"DUE — EARNINGS WINDOW",IF(I47<>"",IF(ABS(I47)>=0.2,"DUE — PRICE MOVE ±20%",IF(K47="Y","DUE — INSIDER ACTIVITY",IF(I47<>"",IF(ABS(I47)>=0.15,"WATCH — PRICE MOVE ±15%",IF(M47="Y","WATCH — ANALYST SHIFT","Monitor Only")),IF(M47="Y","WATCH — ANALYST SHIFT","Monitor Only")))),IF(K47="Y","DUE — INSIDER ACTIVITY",IF(I47<>"",IF(ABS(I47)>=0.15,"WATCH — PRICE MOVE ±15%",IF(M47="Y","WATCH — ANALYST SHIFT","Monitor Only")),IF(M47="Y","WATCH — ANALYST SHIFT","Monitor Only"))))),IF(I47<>"",IF(ABS(I47)>=0.2,"DUE — PRICE MOVE ±20%",IF(K47="Y","DUE — INSIDER ACTIVITY",IF(I47<>"",IF(ABS(I47)>=0.15,"WATCH — PRICE MOVE ±15%",IF(M47="Y","WATCH — ANALYST SHIFT","Monitor Only")),IF(M47="Y","WATCH — ANALYST SHIFT","Monitor Only")))),IF(K47="Y","DUE — INSIDER ACTIVITY",IF(I47<>"",IF(ABS(I47)>=0.15,"WATCH — PRICE MOVE ±15%",IF(M47="Y","WATCH — ANALYST SHIFT","Monitor Only")),IF(M47="Y","WATCH — ANALYST SHIFT","Monitor Only"))))))) -> DUE — INSIDER ACTIVITY
A48: KGS | B48: Watch List | C48: 46276 | E48: 4 | G48: 63.85 | H48: {=IFERROR(INDEX(_xlfn.stockhistory(A48,TODAY()-5,TODAY(),0,0,1),ROWS(_xlfn.stockhistory(A48,TODAY()-5,TODAY(),0,0,1)),1),"")} | I48: =IF(OR(G48="",H48=""),"",H48/G48-1) | J48: 46329 | K48: N | M48: N | O48: =IF(C48="","",TODAY()-C48) -> 19 | P48: =IF(A48="","",IF(O48>180,"DUE — STALE (>180 days)",IF(J48<>"",IF(ABS(J48-TODAY())<=7,"DUE — EARNINGS WINDOW",IF(I48<>"",IF(ABS(I48)>=0.2,"DUE — PRICE MOVE ±20%",IF(K48="Y","DUE — INSIDER ACTIVITY",IF(I48<>"",IF(ABS(I48)>=0.15,"WATCH — PRICE MOVE ±15%",IF(M48="Y","WATCH — ANALYST SHIFT","Monitor Only")),IF(M48="Y","WATCH — ANALYST SHIFT","Monitor Only")))),IF(K48="Y","DUE — INSIDER ACTIVITY",IF(I48<>"",IF(ABS(I48)>=0.15,"WATCH — PRICE MOVE ±15%",IF(M48="Y","WATCH — ANALYST SHIFT","Monitor Only")),IF(M48="Y","WATCH — ANALYST SHIFT","Monitor Only"))))),IF(I48<>"",IF(ABS(I48)>=0.2,"DUE — PRICE MOVE ±20%",IF(K48="Y","DUE — INSIDER ACTIVITY",IF(I48<>"",IF(ABS(I48)>=0.15,"WATCH — PRICE MOVE ±15%",IF(M48="Y","WATCH — ANALYST SHIFT","Monitor Only")),IF(M48="Y","WATCH — ANALYST SHIFT","Monitor Only")))),IF(K48="Y","DUE — INSIDER ACTIVITY",IF(I48<>"",IF(ABS(I48)>=0.15,"WATCH — PRICE MOVE ±15%",IF(M48="Y","WATCH — ANALYST SHIFT","Monitor Only")),IF(M48="Y","WATCH — ANALYST SHIFT","Monitor Only"))))))) -> Monitor Only | Q48: Diversification candidate (Energy -- gas compression services, contract-based revenue, not upstream E&P). Fresh Tier 1 quant screen 9/11/26; Moat/Rev Visibility not yet assessed (Part 12).

Sheet Price History
A1: Weekly closing price ($), week-ending Friday (Rule 36: weekly total returns, 24-month target, 12-month minimum, 36-month max). 20 slots: 13 stocks + 7 held ETFs + headroom.
A2: Week Ending | B2: ADBE | C2: ANET | D2: ASML | E2: AVGO | F2: AVUV | G2: CRWD | H2: DVY | I2: KLAC | J2: MU | K2: NVDA | L2: PLD | M2: PLTR | N2: SCHD | O2: SPMO | P2: TSM | Q2: V | R2: JEPQ | S2: SPMO | T2: VFLO | V2: V
A3: 45184 | B3: 528.89 | C3: 46.18 | D3: 582.01 | E3: 82 | F3: 75.31 | G3: 41.36 | H3: 100.59 | I3: 44.35 | J3: 69.11 | K3: 43.77 | L3: 111.84 | M3: 15.33 | N3: 21.8 | O3: 57.63 | P3: 85.75 | Q3: 235.63 | R3: 47.82 | S3: 58.54 | T3: 26.91
A4: 45191 | B4: 512.9 | C4: 45.08 | D4: 572.69 | E4: 80.26 | F4: 73.11 | G4: 40.64 | H4: 98.44 | I4: 44.12 | J4: 68.12 | K4: 41.49 | L4: 103.57 | M4: 14.13 | N4: 21.3 | O4: 56.23 | P4: 82.28 | Q4: 229.78 | R4: 46.93 | S4: 58.05 | T4: 26.19
A5: 45198 | B5: 509.9 | C5: 45.98 | D5: 574.21 | E5: 80.41 | F5: 74.31 | G5: 41.85 | H5: 96.59 | I5: 44.79 | J5: 67.28 | K5: 43.37 | L5: 101.88 | M5: 16 | N5: 21.14 | O5: 56.06 | P5: 83.49 | Q5: 224.82 | R5: 47.68 | S5: 57.89 | T5: 25.98
A6: 45205 | B6: 526.68 | C6: 48.51 | D6: 582.69 | E6: 81.83 | F6: 72.07 | G6: 44.17 | H6: 94.44 | I6: 45.7 | J6: 69.3 | K6: 45.63 | L6: 98.88 | M6: 16.61 | N6: 20.8 | O6: 56.68 | P6: 85.79 | Q6: 229.74 | R6: 48.55 | S6: 58.82 | T6: 26.66
A7: 45212 | B7: 548.76 | C7: 47.46 | D7: 585.03 | E7: 85.5 | F7: 72.26 | G7: 46.43 | H7: 95.73 | I7: 47.54 | J7: 68.56 | K7: 45.33 | L7: 99.56 | M7: 17.36 | N7: 21.01 | O7: 57 | P7: 86.92 | Q7: 232.31 | R7: 48.23 | S7: 59.17 | T7: 26.47 | V7: 241.71
A8: 45219 | B8: 540.96 | C8: 46.53 | D8: 565.86 | E8: 82.64 | F8: 71.05 | G8: 44.69 | H8: 93.91 | I8: 45.16 | J8: 66.59 | K8: 41.26 | L8: 93 | M8: 16.11 | N8: 20.7 | O8: 55.35 | P8: 87.73 | Q8: 228.12 | R8: 48.21 | S8: 59.17 | T8: 26.3 | V8: 235.63
A9: 45226 | B9: 508.12 | C9: 44.05 | D9: 575.52 | E9: 81.16 | F9: 69.95 | G9: 43.21 | H9: 92.4 | I9: 44.72 | J9: 65.03 | K9: 40.38 | L9: 88.36 | M9: 15.07 | N9: 19.99 | O9: 54.23 | P9: 82.62 | Q9: 224.1 | R9: 46.91 | S9: 57.46 | T9: 25.91 | V9: 229.78
A10: 45233 | B10: 563.66 | C10: 53.12 | D10: 628.24 | E10: 85.45 | F10: 74.96 | G10: 47.06 | H10: 97.82 | I10: 48.79 | J10: 71.9 | K10: 44.87 | L10: 96.74 | M10: 18.89 | N10: 20.99 | O10: 57.4 | P10: 88.19 | Q10: 238.11 | R10: 46.93 | S10: 57.28 | T10: 25.98 | V10: 224.82
A11: 45240 | B11: 597.22 | C11: 51.71 | D11: 646.7 | E11: 92.69 | F11: 72.4 | G11: 49.08 | H11: 95.61 | I11: 52.17 | J11: 74.65 | K11: 48.19 | L11: 94.93 | M11: 19.67 | N11: 20.75 | O11: 59.09 | P11: 93.62 | Q11: 240.23 | R11: 47.13 | S11: 57.92 | T11: 25.5 | V11: 229.74
A12: 45247 | B12: 602.66 | C12: 53.66 | D12: 670.96 | E12: 94.65 | F12: 76.42 | G12: 51.77 | H12: 99 | I12: 53.32 | J12: 76.83 | K12: 49.15 | L12: 99.94 | M12: 20.49 | N12: 21.25 | O12: 60.37 | P12: 95.68 | Q12: 244.45 | R12: 47.26 | S12: 58.25 | T12: 25.83 | V12: 232.31
A13: 45254 | B13: 619.43 | C13: 54.6 | D13: 675.94 | E13: 94.76 | F13: 76.43 | G13: 52.67 | H13: 99.35 | I13: 54.41 | J13: 76.15 | K13: 47.63 | L13: 101.69 | M13: 19.2 | N13: 21.45 | O13: 60.7 | P13: 94 | Q13: 249.1 | R13: 46.32 | S13: 56.56 | T13: 25.5 | V13: 228.12
A14: 45261 | B14: 612.47 | C14: 54.16 | D14: 676.94 | E14: 90.03 | F14: 78.99 | G14: 58.76 | H14: 102.26 | I14: 53.76 | J14: 75.22 | K14: 46.63 | L14: 107.37 | M14: 20.27 | N14: 21.85 | O14: 60.57 | P14: 94.69 | Q14: 251.2 | R14: 45.36 | S14: 55.42 | T14: 24.66 | V14: 224.1
A15: 45268 | B15: 610.01 | C15: 56.01 | D15: 681.07 | E15: 91.41 | F15: 79.65 | G15: 60.64 | H15: 102.48 | I15: 52.33 | J15: 74.26 | K15: 47.37 | L15: 108.82 | M15: 17.77 | N15: 21.89 | O15: 60.79 | P15: 96.42 | Q15: 250.51 | R15: 47.52 | S15: 58.65 | T15: 26.11 | V15: 238.11
A16: 45275 | B16: 584.68 | C16: 58.9 | D16: 736.36 | E16: 109.37 | F16: 84.02 | G16: 65.02 | H16: 105.54 | I16: 57.29 | J16: 80.64 | K16: 48.75 | L16: 122.68 | M16: 18.2 | N16: 22.77 | O16: 62.87 | P16: 98.99 | Q16: 252.75 | R16: 48.51 | S16: 60.38 | T16: 25.93 | V16: 240.23
A17: 45282 | B17: 598.75 | C17: 59.56 | D17: 735.94 | E17: 109.11 | F17: 86.35 | G17: 63.91 | H17: 105.82 | I17: 57.05 | J17: 85.68 | K17: 48.69 | L17: 120.98 | M17: 17.41 | N17: 22.89 | O17: 63.81 | P17: 99.57 | Q17: 253.14 | R17: 48.97 | S17: 61.69 | T17: 26.59 | V17: 244.45
A18: 45289 | B18: 596.6 | C18: 58.88 | D18: 740.23 | E18: 108.56 | F18: 86.03 | G18: 63.83 | H18: 106.25 | I18: 56.92 | J18: 84.65 | K18: 49.38 | L18: 121.8 | M18: 17.17 | N18: 22.98 | O18: 64.26 | P18: 100.4 | Q18: 255.02 | R18: 49.23 | S18: 62.03 | T18: 26.78 | V18: 249.1
... A35: 45408 | B35: 477.56 | C35: 66.18 | D35: 902.15 | E35: 131.27 | F35: 86.75 | G35: 76.02 | H35: 109.47 | I35: 69.31 | J35: 114.02 | K35: 87.49 | L35: 95.79 | M35: 22.52 | N35: 23.57 | O35: 75.73 | P35: 134.05 | Q35: 269.4 | R35: 54.26 | S35: 80.83 | T35: 31.91 | V35: 277.98
A36: 45415 | B36: 486.18 | C36: 68.6 | D36: 885.13 | E36: 124.83 | F36: 87.34 | G36: 77.55 | H36: 110.81 | I36: 68.36 | J36: 113.88 | K36: 88.54 | L36: 97.47 | M36: 23.33 | N36: 23.72 | O36: 76.47 | P36: 137.21 | Q36: 263.49 | R36: 54.24 | S36: 80.22 | T36: 32.41
A37: 45422 | B37: 482.29 | C37: 78.51 | D37: 913.26 | E37: 130.17 | F37: 88.85 | G37: 80.19 | H37: 113.55 | I37: 70.49 | J37: 120.38 | K37: 89.62 | L37: 98.95 | M37: 20.6 | N37: 24.12 | O37: 78.17 | P37: 144.67 | Q37: 275.51 | R37: 53.59 | S37: 80.45 | T37: 32.33 | V37: 271.97
A38: 45429 | B38: 483.43 | C38: 79.97 | D38: 908.04 | E38: 136.27 | F38: 89.83 | G38: 86.48 | H38: 114.93 | I38: 73.52 | J38: 124.4 | K38: 92.22 | L38: 102.64 | M38: 21.76 | N38: 24.36 | O38: 79.35 | P38: 147.02 | Q38: 275.39 | R38: 53.4 | S38: 79.32 | T38: 31.49 | V38: 270.82
A39: 45436 | B39: 475.43 | C39: 76.64 | D39: 938.72 | E39: 137.5 | F39: 88.5 | G39: 87.87 | H39: 112.58 | I39: 76.61 | J39: 128.57 | K39: 106.17 | L39: 96.42 | M39: 21.01 | N39: 23.76 | O39: 80.9 | P39: 155.08 | Q39: 269.87 | R39: 50.84 | S39: 74.81 | T39: 30.93 | V39: 264.75
A40: 45443 | B40: 444.76 | C40: 74.41 | D40: 942.77 | E40: 129.75 | F40: 89.45 | G40: 78.42 | H40: 113.76 | I40: 74.69 | J40: 124.11 | K40: 109.32 | L40: 101.71 | M40: 21.68 | N40: 23.9 | O40: 80.01 | P40: 146.4 | Q40: 267.88 | R40: 52.66 | S40: 77.06 | T40: 31.32 | V40: 269.4
A41: 45450 | B41: 465.43 | C41: 74.2 | D41: 1009.6 | E41: 137.38 | F41: 86.4 | G41: 87.28 | H41: 111.46 | I41: 75.61 | J41: 130.01 | K41: 120.54 | L41: 101.44 | M41: 23.31 | N41: 23.69 | O41: 82.44 | P41: 159.34 | Q41: 273.98 | R41: 52.75 | S41: 77.82 | T41: 30.83 | V41: 263.49
A42: 45457 | B42: 525.31 | C42: 82.12 | D42: 1009.09 | E42: 169.45 | F42: 84.34 | G42: 96.36 | H42: 109.58 | I42: 81.11 | J42: 140.35 | K42: 131.52 | L42: 103.36 | M42: 23.57 | N42: 23.36 | O42: 85.92 | P42: 167.73 | Q42: 266.11 | R42: 53.48 | S42: 79.55 | T42: 31.51 | V42: 275.51
A43: 45464 | B43: 533.44 | C43: 84.34 | D43: 1017.63 | E43: 161.99 | F43: 85.25 | G43: 95.16 | H43: 111.09 | I43: 80.29 | J43: 138.55 | K43: 126.22 | L43: 101.57 | M43: 23.84 | N43: 23.76 | O43: 85.85 | P43: 169.14 | Q43: 270.59 | R43: 54.12 | S43: 80.75 | T43: 31.8 | V43: 275.39
A44: 45471 | B44: 555.54 | C44: 87.62 | D44: 1004.01 | E44: 157.3 | F44: 86.67 | G44: 95.8 | H44: 111.42 | I44: 81.08 | J44: 130.59 | K44: 123.2 | L44: 104.27 | M44: 25.33 | N44: 23.9 | O44: 86.01 | P44: 169 | Q44: 258.05 | R44: 54.38 | S44: 82.32 | T44: 31.26 | V44: 269.87
A45: 45478 | B45: 578.34 | C45: 91.54 | D45: 1054.81 | E45: 166.88 | F45: 85.24 | G45: 97.42 | H45: 110.51 | I45: 84.1 | J45: 130.66 | K45: 125.48 | L45: 106.27 | M45: 27.23 | N45: 23.68 | O45: 88.68 | P45: 178.9 | Q45: 265.81 | R45: 54.19 | S45: 81.42 | T45: 31.62 | V45: 267.88
A46: 45485 | B46: 559.05 | C46: 90.47 | D46: 1065.4 | E46: 166.62 | F46: 89.99 | G46: 92.83 | H46: 115.16 | I46: 84.34 | J46: 132.72 | K46: 128.88 | L46: 111.55 | M46: 28.07 | N46: 24.48 | O46: 88.5 | P46: 182.16 | Q46: 261.27 | R46: 54.49 | S46: 83.89 | T46: 30.95 | V46: 273.98
A47: 45492 | B47: 551 | C47: 82.64 | D47: 878.98 | E47: 154.16 | F47: 92.37 | G47: 76.24 | H47: 116.79 | I47: 74.98 | J47: 113.55 | K47: 117.6 | L47: 114.9 | M47: 28.58 | N47: 24.93 | O47: 84.92 | P47: 161.18 | Q47: 260.99 | R47: 55.18 | S47: 87.43 | T47: 30.82 | V47: 266.11
A48: 45499 | B48: 542.44 | C48: 79.8 | D48: 872.13 | E48: 148.56 | F48: 95.72 | G48: 64.04 | H48: 119.26 | I48: 77.43 | J48: 108.73 | K48: 112.75 | L48: 113.9 | M48: 27.18 | N48: 25.35 | O48: 83.32 | P48: 157.46 | Q48: 255.09 | R48: 55.24 | S48: 87.36 | T48: 31.12 | V48: 270.59
... A90: 45793 | B90: 417.13 | C90: 96.42 | D90: 741.32 | E90: 226 | F90: 88.72 | G90: 109.82 | H90: 126.84 | I90: 78.33 | J90: 97.75 | K90: 135.06 | L90: 105.23 | M90: 129.52 | N90: 25.21 | O90: 103.95 | P90: 190.88 | Q90: 361.59 | R90: 49.54 | S90: 89.82 | T90: 31.56 | V90: 329.63
A91: 45800 | B91: 407.69 | C91: 91.2 | D91: 725.86 | E91: 226.11 | F91: 85.17 | G91: 113.9 | H91: 123.56 | I91: 75.15 | J91: 93.13 | K91: 130.96 | L91: 99.04 | M91: 123.31 | N91: 24.53 | O91: 101.63 | P91: 188.68 | Q91: 350.12 | R91: 48.74 | S91: 88.26 | T91: 31.78
A92: 45807 | B92: 415.09 | C92: 86.64 | D92: 730.1 | E92: 239.31 | F92: 86.17 | G92: 117.84 | H92: 124.36 | I92: 75.12 | J92: 94.22 | K92: 134.79 | L92: 103.38 | M92: 131.78 | N92: 24.8 | O92: 104.1 | P92: 190 | Q92: 361.66 | R92: 51.09 | S92: 94.02 | T92: 32.83 | V92: 331.38
A93: 45814 | B93: 416.92 | C93: 97.25 | D93: 746.2 | E93: 244.11 | F93: 87.76 | G93: 117.1 | H93: 124.82 | I93: 80.19 | J93: 108.28 | K93: 141.36 | L93: 103.56 | M93: 127.72 | N93: 25.15 | O93: 105.65 | P93: 201.66 | Q93: 366.64 | R93: 51.49 | S93: 97.8 | T93: 33.46 | V93: 343.67
A94: 45821 | B94: 391.68 | C94: 92.35 | D94: 754.11 | E94: 245.86 | F94: 87.23 | G94: 120.15 | H94: 124.38 | I94: 86.11 | J94: 115.31 | K94: 141.62 | L94: 102.12 | M94: 137.4 | N94: 25.49 | O94: 104.9 | P94: 208.23 | Q94: 349.44 | R94: 51.63 | S94: 98.48 | T94: 33.4 | V94: 348.55
A95: 45828 | B95: 376.92 | C95: 86.25 | D95: 749.68 | E95: 247.72 | F95: 87.38 | G95: 119.07 | H95: 124.75 | I95: 84.36 | J95: 123.29 | K95: 143.5 | L95: 101.57 | M95: 137.3 | N95: 25.3 | O95: 105.64 | P95: 206.66 | Q95: 335.29 | R95: 52.52 | S95: 105.2 | T95: 34.84 | V95: 361.59
A96: 45835 | B96: 385.83 | C96: 99.39 | D96: 788.74 | E96: 266.9 | F96: 89.61 | G96: 124.83 | H96: 126.47 | I96: 88.32 | J96: 124.44 | K96: 157.36 | L96: 101.5 | M96: 130.74 | N96: 25.25 | O96: 110.73 | P96: 225.46 | Q96: 345.24 | R96: 52.04 | S96: 102.85 | T96: 33.63 | V96: 350.12
A97: 45842 | B97: 379.31 | C97: 102.52 | D97: 787.3 | E97: 272.68 | F97: 93.34 | G97: 128.52 | H97: 130.79 | I97: 91.76 | J97: 121.98 | K97: 158.95 | L97: 103.81 | M97: 134.36 | N97: 26.17 | O97: 111.39 | P97: 231.61 | Q97: 355.39 | R97: 52.63 | S97: 105.35 | T97: 33.89 | V97: 361.66
A98: 45849 | B98: 363.35 | C98: 108.57 | D98: 794.67 | E98: 271.89 | F98: 93.22 | G98: 119.61 | H98: 130.35 | I98: 91.76 | J98: 124.33 | K98: 164.52 | L98: 104.91 | M98: 142.1 | N98: 26.15 | O98: 111.05 | P98: 227.27 | Q98: 344.56 | R98: 52.7 | S98: 106.92 | T98: 34.69 | V98: 366.64
A99: 45856 | B99: 365.79 | C99: 111.78 | D99: 727.93 | E99: 280.77 | F99: 92.12 | G99: 118.99 | H99: 129.8 | I99: 92.41 | J99: 114.21 | K99: 171.99 | L99: 102.61 | M99: 153.52 | N99: 25.86 | O99: 112.7 | P99: 237.13 | Q99: 345.67 | R99: 52.59 | S99: 106.16 | T99: 35.07 | V99: 349.44
A100: 45863 | B100: 370.74 | C100: 114.28 | D100: 704.81 | E100: 287.55 | F100: 93.48 | G100: 116.98 | H100: 132.16 | I100: 89.53 | J100: 111.08 | K100: 173.08 | L100: 105.99 | M100: 158.8 | N100: 26.14 | O100: 113.89 | P100: 242.26 | Q100: 353.59 | R100: 52.75 | S100: 106.91 | T100: 35.03 | V100: 335.29
A101: 45870 | B101: 347.8 | C101: 117.57 | D101: 685.31 | E101: 286.02 | F101: 88.78 | G101: 111.67 | H101: 128.19 | I101: 88 | J101: 104.71 | K101: 173.3 | L101: 100.82 | M101: 154.27 | N101: 25.24 | O101: 112.1 | P101: 232.01 | Q101: 336.07 | R101: 54.27 | S101: 111.84 | T101: 35.33 | V101: 345.24
A102: 45877 | B102: 341.05 | C102: 139.18 | D102: 717.59 | E102: 302.2 | F102: 90.85 | G102: 106.12 | H102: 130.26 | I102: 90.79 | J102: 118.7 | K102: 182.25 | L102: 101.56 | M102: 186.96 | N102: 25.72 | O102: 116.02 | P102: 238.54 | Q102: 333.52 | R102: 54.16 | S102: 112.51 | T102: 35.77
A103: 45884 | B103: 354.85 | C103: 137.3 | D103: 737.3 | E103: 303.56 | F103: 93.56 | G103: 106.97 | H103: 132.26 | I103: 86.84 | J103: 120.68 | K103: 180.01 | L103: 102.43 | M103: 177.17 | N103: 26.15 | O103: 116.14 | P103: 235.63 | Q103: 341.74 | R103: 54.36 | S103: 112.17 | T103: 35.84 | V103: 344.56
A104: 45891 | B104: 362.09 | C104: 133.25 | D104: 749.95 | E104: 291.33 | F104: 97.28 | G104: 105.14 | H104: 136.08 | I104: 86.56 | J104: 117.49 | K104: 177.55 | L104: 107.9 | M104: 158.74 | N104: 26.75 | O104: 115.35 | P104: 229.82 | Q104: 347.26 | R104: 54.69 | S104: 113.83 | T104: 35.08 | V104: 345.67
A105: 45898 | B105: 356.7 | C105: 136.55 | D105: 737.76 | E105: 294.69 | F105: 98.1 | G105: 105.93 | H105: 135.78 | I105: 86.73 | J105: 118.82 | K105: 173.75 | L105: 109.34 | M105: 156.71 | N105: 26.72 | O105: 115.32 | P105: 227.73 | Q105: 348.99 | R105: 55.08 | S105: 115.03 | T105: 35.85 | V105: 353.59
A106: 45905 | B106: 348.97 | C106: 142.85 | D106: 776.58 | E106: 331.85 | F106: 99.17 | G106: 104.41 | H106: 135.66 | I106: 90.02 | J106: 131.16 | K106: 166.61 | L106: 109.22 | M106: 153.11 | N106: 26.45 | O106: 115.89 | P106: 240.1 | Q106: 340.5 | R106: 53.81 | S106: 113.23 | T106: 34.35 | V106: 336.07
A107: 45912 | B107: 349.36 | C107: 139.39 | D107: 808.54 | E107: 356.6 | F107: 98.38 | G107: 109.03 | H107: 135.84 | I107: 95.88 | J107: 156.98 | K107: 177.4 | L107: 110.85 | M107: 171.43 | N107: 26.3 | O107: 119.28 | P107: 255.81 | Q107: 336.74 | R107: 55.32 | S107: 117.19 | T107: 34.69 | V107: 333.52
A108: 45919 | B108: 365.9 | C108: 149.61 | D108: 926.05 | E108: 341.81 | F108: 98.94 | G108: 125.64 | H108: 135.46 | I108: 103.92 | J108: 162.47 | K108: 176.25 | L108: 110.05 | M108: 182.39 | N108: 26.15 | O108: 120.72 | P108: 262.1 | Q108: 338.9 | R108: 55.8 | S108: 117.31 | T108: 36.06 | V108: 341.74
A109: 45926 | B109: 360.37 | C109: 142.5 | D109: 945.29 | E109: 332.06 | F109: 99.24 | G109: 120.36 | H109: 136.5 | I109: 105.86 | J109: 157.02 | K109: 177.76 | L109: 110.71 | M109: 177.57 | N109: 26.29 | O109: 119.57 | P109: 270.5 | Q109: 334.69 | R109: 55.67 | S109: 116.51 | T109: 36.99 | V109: 347.26
A110: 45933 | B110: 346.74 | C110: 145.5 | D110: 1025.47 | E110: 335.87 | F110: 99.35 | G110: 122.47 | H110: 138.19 | I110: 109.56 | J110: 187.65 | K110: 187.17 | L110: 113.5 | M110: 173.07 | N110: 26.48 | O110: 119.08 | P110: 289.13 | Q110: 347.06 | R110: 55.68 | S110: 116.48 | T110: 37.33 | V110: 348.99
A111: 45940 | B111: 337.51 | C111: 154.1 | D111: 930.06 | E111: 322.23 | F111: 93.95 | G111: 123.42 | H111: 133.41 | I111: 97.75 | J111: 181.42 | K111: 182.72 | L111: 107.84 | M111: 175.44 | N111: 25.64 | O111: 117.51 | P111: 277.72 | Q111: 340.92 | R111: 55.78 | S111: 117.05 | T111: 37.61 | V111: 340.5
A112: 45947 | B112: 333.26 | C112: 143.1 | D112: 1022.53 | E112: 346.75 | F112: 95.79 | G112: 121.16 | H112: 135.37 | I112: 110.07 | J112: 202.18 | K112: 182.78 | L112: 120.3 | M112: 178.15 | N112: 25.88 | O112: 119.41 | P112: 291.99 | Q112: 339.18 | R112: 56.54 | S112: 120.48 | T112: 37.5 | V112: 336.74
A113: 45954 | B113: 353.52 | C113: 153.82 | D113: 1026.34 | E113: 351.52 | F113: 98.61 | G113: 131.83 | H113: 137.67 | I113: 117.65 | J113: 218.81 | K113: 185.81 | L113: 122.58 | M113: 184.63 | N113: 26.11 | O113: 120.69 | P113: 291.87 | Q113: 344.62 | R113: 57.16 | S113: 121.93 | T113: 37.45 | V113: 338.9
A114: 45961 | B114: 340.31 | C114: 157.69 | D114: 1054.17 | E114: 366.9 | F114: 96.52 | G114: 135.75 | H114: 134.39 | I114: 120.23 | J114: 223.55 | K114: 202.01 | L114: 120.31 | M114: 200.47 | N114: 25.84 | O114: 120.68 | P114: 297.28 | Q114: 338.04 | R114: 57.25 | S114: 120.58 | T114: 37.74 | V114: 334.69
... A140: 46143 | B140: 250.71 | C140: 172.7 | D140: 1425.18 | E140: 419.85 | F140: 119.13 | G140: 113.91 | H140: 152.16 | I140: 172.21 | J140: 542.13 | K140: 198 | L140: 139.29 | M140: 144.07 | N140: 31.36 | O140: 134 | P140: 395.68 | Q140: 326.74 | R140: 54.13 | S140: 110.31 | T140: 38.75 | V140: 294.36
A141: 46150 | B141: 253.04 | C141: 141.77 | D141: 1589.96 | E141: 428.54 | F141: 119.01 | G141: 131.94 | H141: 149.85 | I141: 186.47 | J141: 746.7 | K141: 214.71 | L141: 141.92 | M141: 137.8 | N141: 31.12 | O141: 143.36 | P141: 409.62 | Q141: 317.54 | R141: 55.59 | S141: 114.74 | T141: 39.84
A142: 46157 | B142: 247.6 | C142: 141.97 | D142: 1499.87 | E142: 423.75 | F142: 116.44 | G142: 148.52 | H142: 148.55 | I142: 180 | J142: 724.55 | K142: 224.81 | L142: 138.42 | M142: 133.99 | N142: 31.22 | O142: 143.03 | P142: 402.33 | Q142: 325.15 | R142: 57.62 | S142: 123.34 | T142: 39.64 | V142: 303.17
A143: 46164 | B143: 244.76 | C143: 154.03 | D143: 1630.79 | E143: 412.73 | F143: 119.2 | G143: 165.87 | H143: 153.27 | I143: 188.62 | J143: 750.88 | K143: 214.84 | L143: 143.71 | M143: 136.88 | N143: 32.31 | O143: 144.48 | P143: 402.5 | Q143: 328.27 | R143: 58.66 | S143: 128.3 | T143: 41.76 | V143: 315.78
A144: 46171 | B144: 259.21 | C144: 159.47 | D144: 1610.68 | E144: 445.25 | F144: 119.22 | G144: 182.75 | H144: 152.49 | I144: 191.95 | J144: 970.85 | K144: 210.66 | L144: 141.31 | M144: 156.54 | N144: 31.99 | O144: 150.11 | P144: 416.36 | Q144: 325.75 | R144: 58.99 | S144: 131.52 | T144: 41.52 | V144: 308.21
A145: 46178 | B145: 251.44 | C145: 154.27 | D145: 1639.62 | E145: 384.42 | F145: 118.87 | G145: 167.76 | H145: 152.92 | I145: 192.7 | J145: 863.88 | K145: 204.87 | L145: 142.37 | M145: 135.53 | N145: 31.79 | O145: 143.82 | P145: 413.09 | Q145: 322.97 | R145: 58.86 | S145: 134.42 | T145: 42.59 | V145: 326.74
A146: 46185 | B146: 204.02 | C146: 163.24 | D146: 1861.14 | E146: 380.77 | F146: 123.97 | G146: 170.7 | H146: 156.3 | I146: 254.25 | J146: 981.46 | K146: 204.96 | L146: 146.51 | M146: 127.99 | N146: 32.3 | O146: 152 | P146: 422.8 | Q146: 321.79 | R146: 59.61 | S146: 143.81 | T146: 43.62 | V146: 317.54
A147: 46192 | B147: 195.16 | C147: 169.67 | D147: 1927.19 | E147: 409.95 | F147: 121.6 | G147: 171.21 | H147: 152.05 | I147: 259.27 | J147: 1133.82 | K147: 210.45 | L147: 139.43 | M147: 128.47 | N147: 31.36 | O147: 159.39 | P147: 460.88 | Q147: 326.63 | R147: 59.77 | S147: 143.48 | T147: 42.5 | V147: 325.15
A148: 46199 | B148: 202.73 | C148: 157.6 | D148: 1792.3 | E148: 364.36 | F148: 124.53 | G148: 175.27 | H148: 156.87 | I148: 248.36 | J148: 1132.16 | K148: 192.31 | L148: 138.87 | M148: 112.93 | N148: 31.84 | O148: 153.95 | P148: 431.19 | Q148: 335.61 | R148: 60.21 | S148: 144.94 | T148: 44.18 | V148: 328.27
A149: 46206 | B149: 219.72 | C149: 159.99 | D149: 1767.03 | E149: 359.79 | F149: 123.11 | G149: 193.98 | H149: 157.78 | I149: 235.28 | J149: 975.41 | K149: 194.61 | L149: 138.33 | M149: 129.3 | N149: 32.13 | O149: 150.58 | P149: 433 | Q149: 361.46 | R149: 61.15 | S149: 150.59 | T149: 46.57 | V149: 325.75
A150: 46213 | B150: 223.64 | C150: 186.96 | D150: 1795 | E150: 399.24 | F150: 123.55 | G150: 187.18 | H150: 158.15 | I150: 231.26 | J150: 979.3 | K150: 210.72 | L150: 139.76 | M150: 126.79 | N150: 32.14 | O150: 153.5 | P150: 432.95 | Q150: 348.32 | R150: 58.9 | S150: 144.28 | T150: 46.05 | V150: 322.97
A151: 46220 | B151: 237.25 | C151: 168.61 | D151: 1745.32 | E151: 370.16 | F151: 124.94 | G151: 203.08 | H151: 160.51 | I151: 212.51 | J151: 848.95 | K151: 202.58 | L151: 148.61 | M151: 132.38 | N151: 32.65 | O151: 143.66 | P151: 397.3 | Q151: 357.9 | R151: 59.86 | S151: 152.48 | T151: 46.29 | V151: 321.79
A152: 46227 | B152: 225.11 | C152: 173.99 | D152: 1754.82 | E152: 381.23 | F152: 124.87 | G152: 183.28 | H152: 161.66 | I152: 210.28 | J152: 920.95 | K152: 206.61 | L152: 146.47 | M152: 122.92 | N152: 33.03 | O152: 146.27 | P152: 402.33 | Q152: 355.08 | R152: 61.34 | S152: 159.9 | T152: 45.25
A153: 46234 | B153: 250.41 | C153: 180.35 | D153: 1629 | E153: 388.57 | F153: 124.87 | G153: 190.86 | H153: 159.89 | I153: 182.61 | J153: 823.03 | K153: 200.53 | L153: 143.47 | M153: 123.06 | N153: 33.21 | O153: 143.6 | P153: 403.17 | Q153: 365.45 | R153: 59.42 | S153: 154.2 | T153: 46.19 | V153: 335.61
A154: 46241 | B154: 265.21 | C154: 188.67 | D154: 1740.99 | E154: 426.98 | F154: 126.47 | G154: 214.42 | H154: 160.58 | I154: 197.89 | J154: 877.57 | K154: 223.71 | L154: 139.06 | M154: 172.01 | N154: 33.63 | O154: 149.45 | P154: 418.92 | Q154: 361.83 | R154: 59.39 | S154: 150.83 | T154: 47
A155: 46248 | B155: 264.02 | C155: 198.82 | D155: 1844.08 | E155: 392.28 | F155: 128.31 | G155: 216.95 | H155: 164.15 | I155: 203.49 | J155: 971.66 | K155: 224.91 | L155: 139.92 | M155: 174.04 | N155: 34.25 | O155: 153.06 | P155: 425.21 | Q155: 364.15 | R155: 60.51 | S155: 153.75 | T155: 47.39 | V155: 348.32
A156: 46255 | B156: 275.3 | C156: 188.65 | D156: 1763.76 | E156: 367.78 | F156: 126.04 | G156: 191.95 | H156: 162.75 | I156: 183.99 | J156: 966.78 | K156: 214.48 | L156: 140.68 | M156: 179.94 | N156: 34.83 | O156: 148.49 | P156: 417.83 | Q156: 371.04 | R156: 58.51 | S156: 143.89 | T156: 47.8 | V156: 357.9
A157: 46262 | B157: 291.52 | C157: 195.38 | D157: 1696.16 | E157: 368.12 | F157: 125.16 | G157: 218.4 | H157: 162.46 | I157: 175.54 | J157: 932.86 | K157: 217.31 | L157: 139.59 | M157: 186.29 | N157: 34.62 | O157: 146.54 | P157: 416.4 | Q157: 381.6 | R157: 57.96 | S157: 146.51 | T157: 48.14 | V157: 355.08
A158: 46269 | B158: 266.51 | C158: 193.78 | D158: 1714.88 | E158: 357.25 | F158: 126.52 | G158: 213.1 | H158: 162.91 | I158: 185.6 | J158: 1016.59 | K158: 230.1 | L158: 136.26 | M158: 174.33 | N158: 34.52 | O158: 149.48 | P158: 427.76 | Q158: 375.07 | R158: 58.25 | S158: 143.83 | T158: 49.74 | V158: 365.45
A159: 46276 | B159: 252.23 | C159: 199.59 | D159: 1698.3 | E159: 361.33 | F159: 124.5 | G159: 206.74 | H159: 161.03 | I159: 180.64 | J159: 975.26 | K159: 218.29 | L159: 134.68 | M159: 167.23 | N159: 33.85 | O159: 148.07 | P159: 432.08 | Q159: 370.45 | R159: 59.74 | S159: 149.69 | T159: 51.46 | V159: 361.83
A160: 46283 | B160: 248.92 | C160: 199.39 | D160: 1679.92 | E160: 356.96 | F160: 121.96 | G160: 237.65 | H160: 158.24 | I160: 176.99 | J160: 1015.8 | K160: 222.27 | L160: 134.84 | M160: 177.64 | N160: 33.41 | O160: 148.97 | P160: 434.67 | Q160: 368.29 | R160: 60.53 | S160: 153.31 | T160: 53.71 | V160: 364.15
A161: 46290 | B161: 235.47 | C161: 206.55 | D161: 1743.94 | E161: 352.81 | F161: 120.41 | G161: 252.13 | H161: 154.73 | I161: 187.92 | J161: 1082.28 | K161: 225.07 | L161: 133.05 | M161: 189.67 | N161: 33.21 | O161: 152.92 | P161: 450.61 | Q161: 367.38 | R161: 59.84 | S161: 148.73 | T161: 55.45 | V161: 371.04
A162: 46297 | B162: 231.01 | C162: 204.92 | D162: 1771.41 | E162: 349.57 | F162: 119.55 | G162: 259.25 | H162: 153.65 | I162: 189.17 | J162: 1053.98 | K162: 228.86 | L162: 132.44 | M162: 187.48 | N162: 33.01 | O162: 151.18 | P162: 452.88 | Q162: 367.74 | R162: 59.47 | S162: 146.78 | T162: 55.66 | V162: 381.6
A163: 46269 | B163: 266.51 | C163: 193.78 | D163: 1714.88 | E163: 357.9 | F163: 213.1 | G163: 185.6 | H163: 1016.59 | I163: 230.36 | J163: 137.34 | K163: 174.33 | L163: 428.91 | M163: 280.53 | N163: 546.12 | O163: 126.93 | Q163: 69.72 | R163: 59.87 | S163: 149.72 | T163: 55.29 | V163: 375.07
A165: =COUNT(A3:A163) -> 161 | B165: Weeks

Sheet Dashboard
A1: Ticker | B1: Company | C1: Date Scored | D1: Tier 1 Wtd Avg | E1: Composite Score | F1: Decision | G1: Rule 1 | H1: Rule 2 | I1: Rule 3 | J1: Rule 4
A2: =IF(Scoring!A3="","",Scoring!A3) -> MU | B2: =IF(Scoring!B3="","",Scoring!B3) -> Micron Technology | C2: =IF(Scoring!C3="","",Scoring!C3) -> 46295 | D2: =IF(Scoring!N3="","",Scoring!N3) -> 3.3571429 | E2: =IF(Scoring!AF3="","",Scoring!AF3) -> 67.8 | F2: =IF(Scoring!AG3<>"",Scoring!AG3,IF(Scoring!AH3="OK","PENDING","")) -> BUY | G2: =IF(Scoring!AH3="","",Scoring!AH3) -> OK | H2: =IF(Scoring!AI3="","",Scoring!AI3) -> OK | I2: =IF(Scoring!AJ3="","",Scoring!AJ3) -> OK | J2: =IF(Scoring!AK3="","",Scoring!AK3) -> OK
A3: =IF(Scoring!A4="","",Scoring!A4) -> AVGO | B3: =IF(Scoring!B4="","",Scoring!B4) -> Broadcom Inc. | C3: =IF(Scoring!C4="","",Scoring!C4) -> 46295 | D3: =IF(Scoring!N4="","",Scoring!N4) -> 3.1428571 | E3: =IF(Scoring!AF4="","",Scoring!AF4) -> 67.8 | F3: =IF(Scoring!AG4<>"",Scoring!AG4,IF(Scoring!AH4="OK","PENDING","")) -> BUY | G3: =IF(Scoring!AH4="","",Scoring!AH4) -> OK | H3: =IF(Scoring!AI4="","",Scoring!AI4) -> OK | I3: =IF(Scoring!AJ4="","",Scoring!AJ4) -> AVOID | J3: =IF(Scoring!AK4="","",Scoring!AK4) -> OK
A4: =IF(Scoring!A5="","",Scoring!A5) -> PLTR | B4: =IF(Scoring!B5="","",Scoring!B5) -> Palantir Technologies | C4: =IF(Scoring!C5="","",Scoring!C5) -> 46295 | D4: =IF(Scoring!N5="","",Scoring!N5) -> 4.0714286 | E4: =IF(Scoring!AF5="","",Scoring!AF5) -> 76.2 | F4: =IF(Scoring!AG5<>"",Scoring!AG5,IF(Scoring!AH5="OK","PENDING","")) -> BUY | G4: =IF(Scoring!AH5="","",Scoring!AH5) -> OK | H4: =IF(Scoring!AI5="","",Scoring!AI5) -> OK | I4: =IF(Scoring!AJ5="","",Scoring!AJ5) -> OK | J4: =IF(Scoring!AK5="","",Scoring!AK5) -> OK
A5: =IF(Scoring!A6="","",Scoring!A6) -> NVDA | B5: =IF(Scoring!B6="","",Scoring!B6) -> NVIDIA Corporation | C5: =IF(Scoring!C6="","",Scoring!C6) -> 46295 | D5: =IF(Scoring!N6="","",Scoring!N6) -> 4.2857143 | E5: =IF(Scoring!AF6="","",Scoring!AF6) -> 89.2 | F5: =IF(Scoring!AG6<>"",Scoring!AG6,IF(Scoring!AH6="OK","PENDING","")) -> STRONG BUY | G5: =IF(Scoring!AH6="","",Scoring!AH6) -> OK | H5: =IF(Scoring!AI6="","",Scoring!AI6) -> OK | I5: =IF(Scoring!AJ6="","",Scoring!AJ6) -> OK | J5: =IF(Scoring!AK6="","",Scoring!AK6) -> OK
A6: =IF(Scoring!A7="","",Scoring!A7) -> VRTX | B6: =IF(Scoring!B7="","",Scoring!B7) -> Vertex Pharmaceuticals | C6: =IF(Scoring!C7="","",Scoring!C7) -> 46295 | D6: =IF(Scoring!N7="","",Scoring!N7) -> 3.1428571 | E6: =IF(Scoring!AF7="","",Scoring!AF7) -> 66.6 | F6: =IF(Scoring!AG7<>"",Scoring!AG7,IF(Scoring!AH7="OK","PENDING","")) -> BUY | G6: =IF(Scoring!AH7="","",Scoring!AH7) -> OK | H6: =IF(Scoring!AI7="","",Scoring!AI7) -> OK | I6: =IF(Scoring!AJ7="","",Scoring!AJ7) -> AVOID | J6: =IF(Scoring!AK7="","",Scoring!AK7) -> OK
A7: =IF(Scoring!A8="","",Scoring!A8) -> PLD | B7: =IF(Scoring!B8="","",Scoring!B8) -> Prologis Inc. (REIT-adapted) | C7: =IF(Scoring!C8="","",Scoring!C8) -> 46295 | D7: =IF(Scoring!N8="","",Scoring!N8) -> 3.9285714 | E7: =IF(Scoring!AF8="","",Scoring!AF8) -> 76 | F7: =IF(Scoring!AG8<>"",Scoring!AG8,IF(Scoring!AH8="OK","PENDING","")) -> BUY | G7: =IF(Scoring!AH8="","",Scoring!AH8) -> OK | H7: =IF(Scoring!AI8="","",Scoring!AI8) -> OK | I7: =IF(Scoring!AJ8="","",Scoring!AJ8) -> OK | J7: =IF(Scoring!AK8="","",Scoring!AK8) -> OK
A8: =IF(Scoring!A9="","",Scoring!A9) -> SFM | B8: =IF(Scoring!B9="","",Scoring!B9) -> Sprouts Farmers Market | C8: =IF(Scoring!C9="","",Scoring!C9) -> 46240 | D8: =IF(Scoring!N9="","",Scoring!N9) -> 1.8571429 | E8: =IF(Scoring!AF9="","",Scoring!AF9) | F8: =IF(Scoring!AG9<>"",Scoring!AG9,IF(Scoring!AH9="OK","PENDING","")) | G8: =IF(Scoring!AH9="","",Scoring!AH9) -> FAIL | H8: =IF(Scoring!AI9="","",Scoring!AI9) -> REVIEW | I8: =IF(Scoring!AJ9="","",Scoring!AJ9) -> AVOID | J8: =IF(Scoring!AK9="","",Scoring!AK9) -> OK
A9: =IF(Scoring!A10="","",Scoring!A10) -> ONON | B9: =IF(Scoring!B10="","",Scoring!B10) -> On Holding AG | C9: =IF(Scoring!C10="","",Scoring!C10) -> 46240 | D9: =IF(Scoring!N10="","",Scoring!N10) -> 2.6428571 | E9: =IF(Scoring!AF10="","",Scoring!AF10) | F9: =IF(Scoring!AG10<>"",Scoring!AG10,IF(Scoring!AH10="OK","PENDING","")) | G9: =IF(Scoring!AH10="","",Scoring!AH10) -> FAIL | H9: =IF(Scoring!AI10="","",Scoring!AI10) -> OK | I9: =IF(Scoring!AJ10="","",Scoring!AJ10) -> AVOID | J9: =IF(Scoring!AK10="","",Scoring!AK10) -> OK
A10: =IF(Scoring!A11="","",Scoring!A11) -> TSLA | B10: =IF(Scoring!B11="","",Scoring!B11) -> Tesla Inc. | C10: =IF(Scoring!C11="","",Scoring!C11) -> 46240 | D10: =IF(Scoring!N11="","",Scoring!N11) -> 1.9285714 | E10: =IF(Scoring!AF11="","",Scoring!AF11) | F10: =IF(Scoring!AG11<>"",Scoring!AG11,IF(Scoring!AH11="OK","PENDING","")) | G10: =IF(Scoring!AH11="","",Scoring!AH11) -> FAIL | H10: =IF(Scoring!AI11="","",Scoring!AI11) -> REVIEW | I10: =IF(Scoring!AJ11="","",Scoring!AJ11) -> AVOID | J10: =IF(Scoring!AK11="","",Scoring!AK11) -> OK
A11: =IF(Scoring!A12="","",Scoring!A12) -> ADBE | B11: =IF(Scoring!B12="","",Scoring!B12) -> Adobe Inc. | C11: =IF(Scoring!C12="","",Scoring!C12) -> 46295 | D11: =IF(Scoring!N12="","",Scoring!N12) -> 4.5714286 | E11: =IF(Scoring!AF12="","",Scoring!AF12) -> 85.8 | F11: =IF(Scoring!AG12<>"",Scoring!AG12,IF(Scoring!AH12="OK","PENDING","")) -> STRONG BUY | G11: =IF(Scoring!AH12="","",Scoring!AH12) -> OK | H11: =IF(Scoring!AI12="","",Scoring!AI12) -> OK | I11: =IF(Scoring!AJ12="","",Scoring!AJ12) -> OK | J11: =IF(Scoring!AK12="","",Scoring!AK12) -> OK
A12: =IF(Scoring!A13="","",Scoring!A13) -> ANET | B12: =IF(Scoring!B13="","",Scoring!B13) -> Arista Networks | C12: =IF(Scoring!C13="","",Scoring!C13) -> 46295 | D12: =IF(Scoring!N13="","",Scoring!N13) -> 4.2857143 | E12: =IF(Scoring!AF13="","",Scoring!AF13) -> 81 | F12: =IF(Scoring!AG13<>"",Scoring!AG13,IF(Scoring!AH13="OK","PENDING","")) -> STRONG BUY | G12: =IF(Scoring!AH13="","",Scoring!AH13) -> OK | H12: =IF(Scoring!AI13="","",Scoring!AI13) -> OK | I12: =IF(Scoring!AJ13="","",Scoring!AJ13) -> OK | J12: =IF(Scoring!AK13="","",Scoring!AK13) -> OK
A13: =IF(Scoring!A14="","",Scoring!A14) -> ASML | B13: =IF(Scoring!B14="","",Scoring!B14) -> ASML Holding | C13: =IF(Scoring!C14="","",Scoring!C14) -> 46295 | D13: =IF(Scoring!N14="","",Scoring!N14) -> 3.8571429 | E13: =IF(Scoring!AF14="","",Scoring!AF14) -> 77.2 | F13: =IF(Scoring!AG14<>"",Scoring!AG14,IF(Scoring!AH14="OK","PENDING","")) -> BUY | G13: =IF(Scoring!AH14="","",Scoring!AH14) -> OK | H13: =IF(Scoring!AI14="","",Scoring!AI14) -> OK | I13: =IF(Scoring!AJ14="","",Scoring!AJ14) -> OK | J13: =IF(Scoring!AK14="","",Scoring!AK14) -> OK
... A49: =IF(Scoring!A50="","",Scoring!A50) -> SLB | B49: =IF(Scoring!B50="","",Scoring!B50) -> SLB N.V. | C49: =IF(Scoring!C50="","",Scoring!C50) -> 46295 | D49: =IF(Scoring!N50="","",Scoring!N50) -> 3.5 | E49: =IF(Scoring!AF50="","",Scoring!AF50) -> 72.4 | F49: =IF(Scoring!AG50<>"",Scoring!AG50,IF(Scoring!AH50="OK","PENDING","")) -> BUY | G49: =IF(Scoring!AH50="","",Scoring!AH50) -> OK | H49: =IF(Scoring!AI50="","",Scoring!AI50) -> OK | I49: =IF(Scoring!AJ50="","",Scoring!AJ50) -> OK | J49: =IF(Scoring!AK50="","",Scoring!AK50) -> OK
A51: This tab mirrors the Scoring tab automatically — do not type here. You can sort this tab directly (Data > Sort by Composite Score); Excel moves whole rows, so each row's links stay correct.
A52: =SUBTOTAL(103,A2:A50) -> 29 | B52: Tickers

Sheet Scoring
D1: TIER 1 — 70% of Decision | P1: TIER 2 — 25% of Decision | Y1: TIER 3 — 5% of Decision | AH1: RULE FLAGS (1–4) | AL1: CLASSIFICATION | AN1: PIOTROSKI-DERIVED CROSS-CHECKS (confidence-tagging inputs only — do not feed Composite Score)
A2: Ticker | B2: Company | C2: Date Scored | D2: FCF Yield & Trend (20%) Score | E2: Conf (H/M/L) | F2: Rev Growth Consist. (15%) Score | G2: Conf (H/M/L) | H2: Moat Quality (15%) Score | I2: Conf (H/M/L) | J2: Rev Visibility (10%) Score | K2: Conf (H/M/L) | L2: FCF Margin Trend (10%) Score | M2: Confidence (H/M/L) | N2: Tier 1 Wtd Avg (÷0.70) | O2: Tier 1 Contrib. | P2: Mgmt Quality & Cap Alloc (8%) Score | Q2: Conf (H/M/L) | R2: ROIC vs WACC (6%) Score | S2: Conf (H/M/L) | T2: Rel Strength vs SPY (3%) Score | U2: Conf (H/M/L) | V2: Valuation Multiples (8%) Score | W2: Conf (H/M/L) | X2: Tier 2 Contrib. | Y2: Technical Trend (2%) Score | Z2: Conf (H/M/L) | AA2: Analyst Consensus (2%) Score | AB2: Conf (H/M/L) | AC2: Volume & Accum. (1%) Score | AD2: Conf (H/M/L) | AE2: Tier 3 Contrib. | AF2: Composite Score | AG2: Decision | AH2: Rule 1 Tier1<3.0 | AI2: Rule 2 Any=1 | AJ2: Rule 3 2+≤2= Avoid | AK2: Rule 4 2+Low= Cap Buy | AL2: Sector | AM2: Industry | AN2: CFO ($) | AO2: Net Income ($) | AP2: Accruals Check | AQ2: Debt/FCF (current) | AR2: Debt/FCF (prior yr) | AS2: Leverage Trajectory
A3: MU | B3: Micron Technology | C3: 46295 | D3: 3 | E3: M | F3: 3 | G3: M | H3: 4 | I3: H | J3: 5 | K3: H | L3: 2 | M3: M | N3: =IF(COUNT(D3,F3,H3,J3,L3)=0,"",(D3*0.2+F3*0.15+H3*0.15+J3*0.1+L3*0.1)/(IF(D3<>"",0.2,0)+IF(F3<>"",0.15,0)+IF(H3<>"",0.15,0)+IF(J3<>"",0.1,0)+IF(L3<>"",0.1,0))) -> 3.3571429 | O3: =IF(COUNT(D3,F3,H3,J3,L3)=0,"",D3*0.2+F3*0.15+H3*0.15+J3*0.1+L3*0.1) -> 2.35 | P3: 4 | Q3: M | R3: 5 | S3: M | T3: 5 | U3: H | V3: 1 | W3: H | X3: =IF(COUNT(P3,R3,T3,V3)=0,"",P3*0.08+R3*0.06+T3*0.03+V3*0.08) -> 0.85 | Y3: 5 | Z3: H | AA3: 3 | AB3: M | AC3: 3 | AD3: L | AE3: =IF(COUNT(Y3,AA3,AC3)=0,"",Y3*0.02+AA3*0.02+AC3*0.01) -> 0.19 | AF3: =IF(OR(COUNT(D3,F3,H3,J3,L3)<5,COUNT(P3,R3,T3,V3)<4,COUNT(Y3,AA3,AC3)<3),"",(O3+X3+AE3)*20) -> 67.8 | AG3: =IF(AF3="","",IF(AF3>=80,"STRONG BUY",IF(AF3>=65,"BUY",IF(AF3>=50,"WATCH LIST",IF(AF3>=35,"AVOID","PASS"))))) -> BUY | AH3: =IF(N3="","",IF(N3<3,"FAIL","OK")) -> OK | AI3: =IF(COUNT(D3:L3)=0,"",IF(COUNTIF(D3:L3,1)>0,"REVIEW","OK")) -> OK | AJ3: =IF(COUNT(D3:L3)=0,"",IF(COUNTIF(D3:L3,"<=2")>=2,"AVOID","OK")) -> OK | AK3: =IF(COUNTA(E3:M3)=0,"",IF(COUNTIF(E3:M3,"L")>=2,"CAP AT BUY","OK")) -> OK | AL3: Technology | AM3: Semiconductors | AN3: 17525000000 | AO3: 8539000000 | AP3: =IF(OR(AN3="",AO3=""),"",IF(AN3>AO3,"OK","LOW CONF")) -> OK | AQ3: 9.159 | AR3: 115.76 | AS3: =IF(OR(AQ3="",AR3=""),"",IF(AQ3<AR3,"Decreased",IF(AQ3>AR3,"Increased","Flat"))) -> Decreased
A4: AVGO | B4: Broadcom Inc. | C4: 46295 | D4: 2 | E4: M | F4: 3 | G4: M | H4: 5 | I4: H | J4: 4 | K4: M | L4: 2 | M4: M | N4: =IF(COUNT(D4,F4,H4,J4,L4)=0,"",(D4*0.2+F4*0.15+H4*0.15+J4*0.1+L4*0.1)/(IF(D4<>"",0.2,0)+IF(F4<>"",0.15,0)+IF(H4<>"",0.15,0)+IF(J4<>"",0.1,0)+IF(L4<>"",0.1,0))) -> 3.1428571 | O4: =IF(COUNT(D4,F4,H4,J4,L4)=0,"",D4*0.2+F4*0.15+H4*0.15+J4*0.1+L4*0.1) -> 2.2 | P4: 4 | Q4: H | R4: 4 | S4: L | T4: 4 | U4: M | V4: 4 | W4: M | X4: =IF(COUNT(P4,R4,T4,V4)=0,"",P4*0.08+R4*0.06+T4*0.03+V4*0.08) -> 1 | Y4: 3 | Z4: M | AA4: 5 | AB4: H | AC4: 3 | AD4: M | AE4: =IF(COUNT(Y4,AA4,AC4)=0,"",Y4*0.02+AA4*0.02+AC4*0.01) -> 0.19 | AF4: =IF(OR(COUNT(D4,F4,H4,J4,L4)<5,COUNT(P4,R4,T4,V4)<4,COUNT(Y4,AA4,AC4)<3),"",(O4+X4+AE4)*20) -> 67.8 | AG4: =IF(AF4="","",IF(AF4>=80,"STRONG BUY",IF(AF4>=65,"BUY",IF(AF4>=50,"WATCH LIST",IF(AF4>=35,"AVOID","PASS"))))) -> BUY | AH4: =IF(N4="","",IF(N4<3,"FAIL","OK")) -> OK | AI4: =IF(COUNT(D4:L4)=0,"",IF(COUNTIF(D4:L4,1)>0,"REVIEW","OK")) -> OK | AJ4: =IF(COUNT(D4:L4)=0,"",IF(COUNTIF(D4:L4,"<=2")>=2,"AVOID","OK")) -> AVOID | AK4: =IF(COUNTA(E4:M4)=0,"",IF(COUNTIF(E4:M4,"L")>=2,"CAP AT BUY","OK")) -> OK | AL4: Technology | AM4: Semiconductors | AP4: =IF(OR(AN4="",AO4=""),"",IF(AN4>AO4,"OK","LOW CONF")) | AS4: =IF(OR(AQ4="",AR4=""),"",IF(AQ4<AR4,"Decreased",IF(AQ4>AR4,"Increased","Flat")))
A5: PLTR | B5: Palantir Technologies | C5: 46295 | D5: 3 | E5: M | F5: 4 | G5: M | H5: 5 | I5: M | J5: 4 | K5: M | L5: 5 | M5: M | N5: =IF(COUNT(D5,F5,H5,J5,L5)=0,"",(D5*0.2+F5*0.15+H5*0.15+J5*0.1+L5*0.1)/(IF(D5<>"",0.2,0)+IF(F5<>"",0.15,0)+IF(H5<>"",0.15,0)+IF(J5<>"",0.1,0)+IF(L5<>"",0.1,0))) -> 4.0714286 | O5: =IF(COUNT(D5,F5,H5,J5,L5)=0,"",D5*0.2+F5*0.15+H5*0.15+J5*0.1+L5*0.1) -> 2.85 | P5: 3 | Q5: M | R5: 5 | S5: H | T5: 3 | U5: M | V5: 2 | W5: M | X5: =IF(COUNT(P5,R5,T5,V5)=0,"",P5*0.08+R5*0.06+T5*0.03+V5*0.08) -> 0.79 | Y5: 3 | Z5: L | AA5: 4 | AB5: M | AC5: 3 | AD5: L | AE5: =IF(COUNT(Y5,AA5,AC5)=0,"",Y5*0.02+AA5*0.02+AC5*0.01) -> 0.17 | AF5: =IF(OR(COUNT(D5,F5,H5,J5,L5)<5,COUNT(P5,R5,T5,V5)<4,COUNT(Y5,AA5,AC5)<3),"",(O5+X5+AE5)*20) -> 76.2 | AG5: =IF(AF5="","",IF(AF5>=80,"STRONG BUY",IF(AF5>=65,"BUY",IF(AF5>=50,"WATCH LIST",IF(AF5>=35,"AVOID","PASS"))))) -> BUY | AH5: =IF(N5="","",IF(N5<3,"FAIL","OK")) -> OK | AI5: =IF(COUNT(D5:L5)=0,"",IF(COUNTIF(D5:L5,1)>0,"REVIEW","OK")) -> OK | AJ5: =IF(COUNT(D5:L5)=0,"",IF(COUNTIF(D5:L5,"<=2")>=2,"AVOID","OK")) -> OK | AK5: =IF(COUNTA(E5:M5)=0,"",IF(COUNTIF(E5:M5,"L")>=2,"CAP AT BUY","OK")) -> OK | AL5: Technology | AM5: Software - Infrastructure | AP5: =IF(OR(AN5="",AO5=""),"",IF(AN5>AO5,"OK","LOW CONF")) | AS5: =IF(OR(AQ5="",AR5=""),"",IF(AQ5<AR5,"Decreased",IF(AQ5>AR5,"Increased","Flat")))
A6: NVDA | B6: NVIDIA Corporation | C6: 46295 | D6: 3 | E6: M | F6: 5 | G6: M | H6: 5 | I6: H | J6: 4 | K6: H | L6: 5 | M6: M | N6: =IF(COUNT(D6,F6,H6,J6,L6)=0,"",(D6*0.2+F6*0.15+H6*0.15+J6*0.1+L6*0.1)/(IF(D6<>"",0.2,0)+IF(F6<>"",0.15,0)+IF(H6<>"",0.15,0)+IF(J6<>"",0.1,0)+IF(L6<>"",0.1,0))) -> 4.2857143 | O6: =IF(COUNT(D6,F6,H6,J6,L6)=0,"",D6*0.2+F6*0.15+H6*0.15+J6*0.1+L6*0.1) -> 3 | P6: 5 | Q6: H | R6: 5 | S6: H | T6: 5 | U6: H | V6: 5 | W6: M | X6: =IF(COUNT(P6,R6,T6,V6)=0,"",P6*0.08+R6*0.06+T6*0.03+V6*0.08) -> 1.25 | Y6: 4 | Z6: M | AA6: 5 | AB6: M | AC6: 3 | AD6: L | AE6: =IF(COUNT(Y6,AA6,AC6)=0,"",Y6*0.02+AA6*0.02+AC6*0.01) -> 0.21 | AF6: =IF(OR(COUNT(D6,F6,H6,J6,L6)<5,COUNT(P6,R6,T6,V6)<4,COUNT(Y6,AA6,AC6)<3),"",(O6+X6+AE6)*20) -> 89.2 | AG6: =IF(AF6="","",IF(AF6>=80,"STRONG BUY",IF(AF6>=65,"BUY",IF(AF6>=50,"WATCH LIST",IF(AF6>=35,"AVOID","PASS"))))) -> STRONG BUY | AH6: =IF(N6="","",IF(N6<3,"FAIL","OK")) -> OK | AI6: =IF(COUNT(D6:L6)=0,"",IF(COUNTIF(D6:L6,1)>0,"REVIEW","OK")) -> OK | AJ6: =IF(COUNT(D6:L6)=0,"",IF(COUNTIF(D6:L6,"<=2")>=2,"AVOID","OK")) -> OK | AK6: =IF(COUNTA(E6:M6)=0,"",IF(COUNTIF(E6:M6,"L")>=2,"CAP AT BUY","OK")) -> OK | AL6: Technology | AM6: Semiconductors | AP6: =IF(OR(AN6="",AO6=""),"",IF(AN6>AO6,"OK","LOW CONF")) | AS6: =IF(OR(AQ6="",AR6=""),"",IF(AQ6<AR6,"Decreased",IF(AQ6>AR6,"Increased","Flat")))
A7: VRTX | B7: Vertex Pharmaceuticals | C7: 46295 | D7: 2 | E7: M | F7: 4 | G7: M | H7: 4 | I7: M | J7: 4 | K7: M | L7: 2 | M7: M | N7: =IF(COUNT(D7,F7,H7,J7,L7)=0,"",(D7*0.2+F7*0.15+H7*0.15+J7*0.1+L7*0.1)/(IF(D7<>"",0.2,0)+IF(F7<>"",0.15,0)+IF(H7<>"",0.15,0)+IF(J7<>"",0.1,0)+IF(L7<>"",0.1,0))) -> 3.1428571 | O7: =IF(COUNT(D7,F7,H7,J7,L7)=0,"",D7*0.2+F7*0.15+H7*0.15+J7*0.1+L7*0.1) -> 2.2 | P7: 3 | Q7: M | R7: 4 | S7: M | T7: 4 | U7: M | V7: 4 | W7: M | X7: =IF(COUNT(P7,R7,T7,V7)=0,"",P7*0.08+R7*0.06+T7*0.03+V7*0.08) -> 0.92 | Y7: 4 | Z7: M | AA7: 5 | AB7: H | AC7: 3 | AD7: L | AE7: =IF(COUNT(Y7,AA7,AC7)=0,"",Y7*0.02+AA7*0.02+AC7*0.01) -> 0.21 | AF7: =IF(OR(COUNT(D7,F7,H7,J7,L7)<5,COUNT(P7,R7,T7,V7)<4,COUNT(Y7,AA7,AC7)<3),"",(O7+X7+AE7)*20) -> 66.6 | AG7: =IF(AF7="","",IF(AF7>=80,"STRONG BUY",IF(AF7>=65,"BUY",IF(AF7>=50,"WATCH LIST",IF(AF7>=35,"AVOID","PASS"))))) -> BUY | AH7: =IF(N7="","",IF(N7<3,"FAIL","OK")) -> OK | AI7: =IF(COUNT(D7:L7)=0,"",IF(COUNTIF(D7:L7,1)>0,"REVIEW","OK")) -> OK | AJ7: =IF(COUNT(D7:L7)=0,"",IF(COUNTIF(D7:L7,"<=2")>=2,"AVOID","OK")) -> AVOID | AK7: =IF(COUNTA(E7:M7)=0,"",IF(COUNTIF(E7:M7,"L")>=2,"CAP AT BUY","OK")) -> OK | AL7: Healthcare | AM7: Biotechnology | AN7: 3631400000 | AO7: 3953200000 | AP7: =IF(OR(AN7="",AO7=""),"",IF(AN7>AO7,"OK","LOW CONF")) -> LOW CONF | AQ7: 0.636 | AR7: -1.784 | AS7: =IF(OR(AQ7="",AR7=""),"",IF(AQ7<AR7,"Decreased",IF(AQ7>AR7,"Increased","Flat"))) -> Increased
A8: PLD | B8: Prologis Inc. (REIT-adapted) | C8: 46295 | D8: 4 | E8: M | F8: 2 | G8: L | H8: 5 | I8: H | J8: 4 | K8: M | L8: 5 | M8: H | N8: =IF(COUNT(D8,F8,H8,J8,L8)=0,"",(D8*0.2+F8*0.15+H8*0.15+J8*0.1+L8*0.1)/(IF(D8<>"",0.2,0)+IF(F8<>"",0.15,0)+IF(H8<>"",0.15,0)+IF(J8<>"",0.1,0)+IF(L8<>"",0.1,0))) -> 3.9285714 | O8: =IF(COUNT(D8,F8,H8,J8,L8)=0,"",D8*0.2+F8*0.15+H8*0.15+J8*0.1+L8*0.1) -> 2.75 | P8: 5 | Q8: H | R8: 3 | S8: L | T8: 4 | U8: L | V8: 2 | W8: H | X8: =IF(COUNT(P8,R8,T8,V8)=0,"",P8*0.08+R8*0.06+T8*0.03+V8*0.08) -> 0.86 | Y8: 4 | Z8: L | AA8: 4 | AB8: M | AC8: 3 | AD8: L | AE8: =IF(COUNT(Y8,AA8,AC8)=0,"",Y8*0.02+AA8*0.02+AC8*0.01) -> 0.19 | AF8: =IF(OR(COUNT(D8,F8,H8,J8,L8)<5,COUNT(P8,R8,T8,V8)<4,COUNT(Y8,AA8,AC8)<3),"",(O8+X8+AE8)*20) -> 76 | AG8: =IF(AF8="","",IF(AF8>=80,"STRONG BUY",IF(AF8>=65,"BUY",IF(AF8>=50,"WATCH LIST",IF(AF8>=35,"AVOID","PASS"))))) -> BUY | AH8: =IF(N8="","",IF(N8<3,"FAIL","OK")) -> OK | AI8: =IF(COUNT(D8:L8)=0,"",IF(COUNTIF(D8:L8,1)>0,"REVIEW","OK")) -> OK | AJ8: =IF(COUNT(D8:L8)=0,"",IF(COUNTIF(D8:L8,"<=2")>=2,"AVOID","OK")) -> OK | AK8: =IF(COUNTA(E8:M8)=0,"",IF(COUNTIF(E8:M8,"L")>=2,"CAP AT BUY","OK")) -> OK | AL8: Real Estate | AM8: REIT - Industrial | AP8: =IF(OR(AN8="",AO8=""),"",IF(AN8>AO8,"OK","LOW CONF")) | AS8: =IF(OR(AQ8="",AR8=""),"",IF(AQ8<AR8,"Decreased",IF(AQ8>AR8,"Increased","Flat")))
A9: SFM | B9: Sprouts Farmers Market | C9: 46240 | D9: 2 | E9: M | F9: 2 | G9: M | H9: 2 | I9: M | J9: 2 | K9: M | L9: 1 | M9: H | N9: =IF(COUNT(D9,F9,H9,J9,L9)=0,"",(D9*0.2+F9*0.15+H9*0.15+J9*0.1+L9*0.1)/(IF(D9<>"",0.2,0)+IF(F9<>"",0.15,0)+IF(H9<>"",0.15,0)+IF(J9<>"",0.1,0)+IF(L9<>"",0.1,0))) -> 1.8571429 | O9: =IF(COUNT(D9,F9,H9,J9,L9)=0,"",D9*0.2+F9*0.15+H9*0.15+J9*0.1+L9*0.1) -> 1.3 | X9: =IF(COUNT(P9,R9,T9,V9)=0,"",P9*0.08+R9*0.06+T9*0.03+V9*0.08) | AE9: =IF(COUNT(Y9,AA9,AC9)=0,"",Y9*0.02+AA9*0.02+AC9*0.01) | AF9: =IF(OR(COUNT(D9,F9,H9,J9,L9)<5,COUNT(P9,R9,T9,V9)<4,COUNT(Y9,AA9,AC9)<3),"",(O9+X9+AE9)*20) | AG9: =IF(AF9="","",IF(AF9>=80,"STRONG BUY",IF(AF9>=65,"BUY",IF(AF9>=50,"WATCH LIST",IF(AF9>=35,"AVOID","PASS"))))) | AH9: =IF(N9="","",IF(N9<3,"FAIL","OK")) -> FAIL | AI9: =IF(COUNT(D9:L9)=0,"",IF(COUNTIF(D9:L9,1)>0,"REVIEW","OK")) -> REVIEW | AJ9: =IF(COUNT(D9:L9)=0,"",IF(COUNTIF(D9:L9,"<=2")>=2,"AVOID","OK")) -> AVOID | AK9: =IF(COUNTA(E9:M9)=0,"",IF(COUNTIF(E9:M9,"L")>=2,"CAP AT BUY","OK")) -> OK | AL9: Consumer Defensive | AM9: Grocery Stores | AN9: 715998000 | AO9: 523670000 | AP9: =IF(OR(AN9="",AO9=""),"",IF(AN9>AO9,"OK","LOW CONF")) -> OK | AQ9: 4.155 | AR9: 4.048 | AS9: =IF(OR(AQ9="",AR9=""),"",IF(AQ9<AR9,"Decreased",IF(AQ9>AR9,"Increased","Flat"))) -> Increased
A10: ONON | B10: On Holding AG | C10: 46240 | D10: 2 | E10: M | F10: 4 | G10: H | H10: 3 | I10: M | J10: 2 | K10: M | L10: 2 | M10: H | N10: =IF(COUNT(D10,F10,H10,J10,L10)=0,"",(D10*0.2+F10*0.15+H10*0.15+J10*0.1+L10*0.1)/(IF(D10<>"",0.2,0)+IF(F10<>"",0.15,0)+IF(H10<>"",0.15,0)+IF(J10<>"",0.1,0)+IF(L10<>"",0.1,0))) -> 2.6428571 | O10: =IF(COUNT(D10,F10,H10,J10,L10)=0,"",D10*0.2+F10*0.15+H10*0.15+J10*0.1+L10*0.1) -> 1.85 | X10: =IF(COUNT(P10,R10,T10,V10)=0,"",P10*0.08+R10*0.06+T10*0.03+V10*0.08) | AE10: =IF(COUNT(Y10,AA10,AC10)=0,"",Y10*0.02+AA10*0.02+AC10*0.01) | AF10: =IF(OR(COUNT(D10,F10,H10,J10,L10)<5,COUNT(P10,R10,T10,V10)<4,COUNT(Y10,AA10,AC10)<3),"",(O10+X10+AE10)*20) | AG10: =IF(AF10="","",IF(AF10>=80,"STRONG BUY",IF(AF10>=65,"BUY",IF(AF10>=50,"WATCH LIST",IF(AF10>=35,"AVOID","PASS"))))) | AH10: =IF(N10="","",IF(N10<3,"FAIL","OK")) -> FAIL | AI10: =IF(COUNT(D10:L10)=0,"",IF(COUNTIF(D10:L10,1)>0,"REVIEW","OK")) -> OK | AJ10: =IF(COUNT(D10:L10)=0,"",IF(COUNTIF(D10:L10,"<=2")>=2,"AVOID","OK")) -> AVOID | AK10: =IF(COUNTA(E10:M10)=0,"",IF(COUNTIF(E10:M10,"L")>=2,"CAP AT BUY","OK")) -> OK | AL10: Consumer Cyclical | AM10: Footwear & Accessories | AN10: 359500000 | AO10: 203700000 | AP10: =IF(OR(AN10="",AO10=""),"",IF(AN10>AO10,"OK","LOW CONF")) -> OK | AQ10: 1.857 | AR10: 0.78 | AS10: =IF(OR(AQ10="",AR10=""),"",IF(AQ10<AR10,"Decreased",IF(AQ10>AR10,"Increased","Flat"))) -> Increased
A11: TSLA | B11: Tesla Inc. | C11: 46240 | D11: 1 | E11: H | F11: 2 | G11: M | H11: 3 | I11: M | J11: 3 | K11: M | L11: 1 | M11: H | N11: =IF(COUNT(D11,F11,H11,J11,L11)=0,"",(D11*0.2+F11*0.15+H11*0.15+J11*0.1+L11*0.1)/(IF(D11<>"",0.2,0)+IF(F11<>"",0.15,0)+IF(H11<>"",0.15,0)+IF(J11<>"",0.1,0)+IF(L11<>"",0.1,0))) -> 1.9285714 | O11: =IF(COUNT(D11,F11,H11,J11,L11)=0,"",D11*0.2+F11*0.15+H11*0.15+J11*0.1+L11*0.1) -> 1.35 | X11: =IF(COUNT(P11,R11,T11,V11)=0,"",P11*0.08+R11*0.06+T11*0.03+V11*0.08) | AE11: =IF(COUNT(Y11,AA11,AC11)=0,"",Y11*0.02+AA11*0.02+AC11*0.01) | AF11: =IF(OR(COUNT(D11,F11,H11,J11,L11)<5,COUNT(P11,R11,T11,V11)<4,COUNT(Y11,AA11,AC11)<3),"",(O11+X11+AE11)*20) | AG11: =IF(AF11="","",IF(AF11>=80,"STRONG BUY",IF(AF11>=65,"BUY",IF(AF11>=50,"WATCH LIST",IF(AF11>=35,"AVOID","PASS"))))) | AH11: =IF(N11="","",IF(N11<3,"FAIL","OK")) -> FAIL | AI11: =IF(COUNT(D11:L11)=0,"",IF(COUNTIF(D11:L11,1)>0,"REVIEW","OK")) -> REVIEW | AJ11: =IF(COUNT(D11:L11)=0,"",IF(COUNTIF(D11:L11,"<=2")>=2,"AVOID","OK")) -> AVOID | AK11: =IF(COUNTA(E11:M11)=0,"",IF(COUNTIF(E11:M11,"L")>=2,"CAP AT BUY","OK")) -> OK | AL11: Consumer Cyclical | AM11: Auto Manufacturers | AN11: 14747000000 | AO11: 3794000000 | AP11: =IF(OR(AN11="",AO11=""),"",IF(AN11>AO11,"OK","LOW CONF")) -> OK | AQ11: 2.366 | AR11: 3.804 | AS11: =IF(OR(AQ11="",AR11=""),"",IF(AQ11<AR11,"Decreased",IF(AQ11>AR11,"Increased","Flat"))) -> Decreased
A12: ADBE | B12: Adobe Inc. | C12: 46295 | D12: 5 | E12: M | F12: 4 | G12: M | H12: 4 | I12: M | J12: 5 | K12: H | L12: 5 | M12: M | N12: =IF(COUNT(D12,F12,H12,J12,L12)=0,"",(D12*0.2+F12*0.15+H12*0.15+J12*0.1+L12*0.1)/(IF(D12<>"",0.2,0)+IF(F12<>"",0.15,0)+IF(H12<>"",0.15,0)+IF(J12<>"",0.1,0)+IF(L12<>"",0.1,0))) -> 4.5714286 | O12: =IF(COUNT(D12,F12,H12,J12,L12)=0,"",D12*0.2+F12*0.15+H12*0.15+J12*0.1+L12*0.1) -> 3.2 | P12: 3 | Q12: M | R12: 5 | S12: H | T12: 1 | U12: H | V12: 5 | W12: H | X12: =IF(COUNT(P12,R12,T12,V12)=0,"",P12*0.08+R12*0.06+T12*0.03+V12*0.08) -> 0.97 | Y12: 2 | Z12: M | AA12: 3 | AB12: M | AC12: 2 | AD12: L | AE12: =IF(COUNT(Y12,AA12,AC12)=0,"",Y12*0.02+AA12*0.02+AC12*0.01) -> 0.12 | AF12: =IF(OR(COUNT(D12,F12,H12,J12,L12)<5,COUNT(P12,R12,T12,V12)<4,COUNT(Y12,AA12,AC12)<3),"",(O12+X12+AE12)*20) -> 85.8 | AG12: =IF(AF12="","",IF(AF12>=80,"STRONG BUY",IF(AF12>=65,"BUY",IF(AF12>=50,"WATCH LIST",IF(AF12>=35,"AVOID","PASS"))))) -> STRONG BUY | AH12: =IF(N12="","",IF(N12<3,"FAIL","OK")) -> OK | AI12: =IF(COUNT(D12:L12)=0,"",IF(COUNTIF(D12:L12,1)>0,"REVIEW","OK")) -> OK | AJ12: =IF(COUNT(D12:L12)=0,"",IF(COUNTIF(D12:L12,"<=2")>=2,"AVOID","OK")) -> OK | AK12: =IF(COUNTA(E12:M12)=0,"",IF(COUNTIF(E12:M12,"L")>=2,"CAP AT BUY","OK")) -> OK | AL12: Technology | AM12: Software - Application | AP12: =IF(OR(AN12="",AO12=""),"",IF(AN12>AO12,"OK","LOW CONF")) | AS12: =IF(OR(AQ12="",AR12=""),"",IF(AQ12<AR12,"Decreased",IF(AQ12>AR12,"Increased","Flat")))
A13: ANET | B13: Arista Networks | C13: 46295 | D13: 3 | E13: M | F13: 5 | G13: M | H13: 5 | I13: H | J13: 4 | K13: M | L13: 5 | M13: M | N13: =IF(COUNT(D13,F13,H13,J13,L13)=0,"",(D13*0.2+F13*0.15+H13*0.15+J13*0.1+L13*0.1)/(IF(D13<>"",0.2,0)+IF(F13<>"",0.15,0)+IF(H13<>"",0.15,0)+IF(J13<>"",0.1,0)+IF(L13<>"",0.1,0))) -> 4.2857143 | O13: =IF(COUNT(D13,F13,H13,J13,L13)=0,"",D13*0.2+F13*0.15+H13*0.15+J13*0.1+L13*0.1) -> 3 | P13: 4 | Q13: H | R13: 5 | S13: H | T13: 5 | U13: M | V13: 1 | W13: H | X13: =IF(COUNT(P13,R13,T13,V13)=0,"",P13*0.08+R13*0.06+T13*0.03+V13*0.08) -> 0.85 | Y13: 4 | Z13: M | AA13: 5 | AB13: H | AC13: 2 | AD13: M | AE13: =IF(COUNT(Y13,AA13,AC13)=0,"",Y13*0.02+AA13*0.02+AC13*0.01) -> 0.2 | AF13: =IF(OR(COUNT(D13,F13,H13,J13,L13)<5,COUNT(P13,R13,T13,V13)<4,COUNT(Y13,AA13,AC13)<3),"",(O13+X13+AE13)*20) -> 81 | AG13: =IF(AF13="","",IF(AF13>=80,"STRONG BUY",IF(AF13>=65,"BUY",IF(AF13>=50,"WATCH LIST",IF(AF13>=35,"AVOID","PASS"))))) -> STRONG BUY | AH13: =IF(N13="","",IF(N13<3,"FAIL","OK")) -> OK | AI13: =IF(COUNT(D13:L13)=0,"",IF(COUNTIF(D13:L13,1)>0,"REVIEW","OK")) -> OK | AJ13: =IF(COUNT(D13:L13)=0,"",IF(COUNTIF(D13:L13,"<=2")>=2,"AVOID","OK")) -> OK | AK13: =IF(COUNTA(E13:M13)=0,"",IF(COUNTIF(E13:M13,"L")>=2,"CAP AT BUY","OK")) -> OK | AL13: Technology | AM13: Computer Hardware | AP13: =IF(OR(AN13="",AO13=""),"",IF(AN13>AO13,"OK","LOW CONF")) | AS13: =IF(OR(AQ13="",AR13=""),"",IF(AQ13<AR13,"Decreased",IF(AQ13>AR13,"Increased","Flat")))
A14: ASML | B14: ASML Holding | C14: 46295 | D14: 3 | E14: M | F14: 3 | G14: M | H14: 5 | I14: H | J14: 4 | K14: M | L14: 5 | M14: M | N14: =IF(COUNT(D14,F14,H14,J14,L14)=0,"",(D14*0.2+F14*0.15+H14*0.15+J14*0.1+L14*0.1)/(IF(D14<>"",0.2,0)+IF(F14<>"",0.15,0)+IF(H14<>"",0.15,0)+IF(J14<>"",0.1,0)+IF(L14<>"",0.1,0))) -> 3.8571429 | O14: =IF(COUNT(D14,F14,H14,J14,L14)=0,"",D14*0.2+F14*0.15+H14*0.15+J14*0.1+L14*0.1) -> 2.7 | P14: 4 | Q14: M | R14: 5 | S14: H | T14: 5 | U14: H | V14: 2 | W14: M | X14: =IF(COUNT(P14,R14,T14,V14)=0,"",P14*0.08+R14*0.06+T14*0.03+V14*0.08) -> 0.93 | Y14: 5 | Z14: M | AA14: 5 | AB14: H | AC14: 3 | AD14: L | AE14: =IF(COUNT(Y14,AA14,AC14)=0,"",Y14*0.02+AA14*0.02+AC14*0.01) -> 0.23 | AF14: =IF(OR(COUNT(D14,F14,H14,J14,L14)<5,COUNT(P14,R14,T14,V14)<4,COUNT(Y14,AA14,AC14)<3),"",(O14+X14+AE14)*20) -> 77.2 | AG14: =IF(AF14="","",IF(AF14>=80,"STRONG BUY",IF(AF14>=65,"BUY",IF(AF14>=50,"WATCH LIST",IF(AF14>=35,"AVOID","PASS"))))) -> BUY | AH14: =IF(N14="","",IF(N14<3,"FAIL","OK")) -> OK | AI14: =IF(COUNT(D14:L14)=0,"",IF(COUNTIF(D14:L14,1)>0,"REVIEW","OK")) -> OK | AJ14: =IF(COUNT(D14:L14)=0,"",IF(COUNTIF(D14:L14,"<=2")>=2,"AVOID","OK")) -> OK | AK14: =IF(COUNTA(E14:M14)=0,"",IF(COUNTIF(E14:M14,"L")>=2,"CAP AT BUY","OK")) -> OK | AL14: Technology | AM14: Semiconductor Equipment & Materials | AP14: =IF(OR(AN14="",AO14=""),"",IF(AN14>AO14,"OK","LOW CONF")) | AS14: =IF(OR(AQ14="",AR14=""),"",IF(AQ14<AR14,"Decreased",IF(AQ14>AR14,"Increased","Flat")))
A15: CRWD | B15: CrowdStrike Holdings | C15: 46295 | D15: 2 | E15: M | F15: 5 | G15: M | H15: 4 | I15: M | J15: 5 | K15: H | L15: 2 | M15: M | N15: =IF(COUNT(D15,F15,H15,J15,L15)=0,"",(D15*0.2+F15*0.15+H15*0.15+J15*0.1+L15*0.1)/(IF(D15<>"",0.2,0)+IF(F15<>"",0.15,0)+IF(H15<>"",0.15,0)+IF(J15<>"",0.1,0)+IF(L15<>"",0.1,0))) -> 3.5 | O15: =IF(COUNT(D15,F15,H15,J15,L15)=0,"",D15*0.2+F15*0.15+H15*0.15+J15*0.1+L15*0.1) -> 2.45 | P15: 3 | Q15: M | R15: 2 | S15: M | T15: 4 | U15: H | V15: 1 | W15: H | X15: =IF(COUNT(P15,R15,T15,V15)=0,"",P15*0.08+R15*0.06+T15*0.03+V15*0.08) -> 0.56 | Y15: 4 | Z15: M | AA15: 3 | AB15: M | AC15: 2 | AD15: M | AE15: =IF(COUNT(Y15,AA15,AC15)=0,"",Y15*0.02+AA15*0.02+AC15*0.01) -> 0.16 | AF15: =IF(OR(COUNT(D15,F15,H15,J15,L15)<5,COUNT(P15,R15,T15,V15)<4,COUNT(Y15,AA15,AC15)<3),"",(O15+X15+AE15)*20) -> 63.4 | AG15: =IF(AF15="","",IF(AF15>=80,"STRONG BUY",IF(AF15>=65,"BUY",IF(AF15>=50,"WATCH LIST",IF(AF15>=35,"AVOID","PASS"))))) -> WATCH LIST | AH15: =IF(N15="","",IF(N15<3,"FAIL","OK")) -> OK | AI15: =IF(COUNT(D15:L15)=0,"",IF(COUNTIF(D15:L15,1)>0,"REVIEW","OK")) -> OK | AJ15: =IF(COUNT(D15:L15)=0,"",IF(COUNTIF(D15:L15,"<=2")>=2,"AVOID","OK")) -> AVOID | AK15: =IF(COUNTA(E15:M15)=0,"",IF(COUNTIF(E15:M15,"L")>=2,"CAP AT BUY","OK")) -> OK | AL15: Technology | AM15: Software - Infrastructure | AP15: =IF(OR(AN15="",AO15=""),"",IF(AN15>AO15,"OK","LOW CONF")) | AS15: =IF(OR(AQ15="",AR15=""),"",IF(AQ15<AR15,"Decreased",IF(AQ15>AR15,"Increased","Flat")))
A16: KLAC | B16: KLA Corporation | C16: 46295 | D16: 3 | E16: M | F16: 3 | G16: M | H16: 5 | I16: H | J16: 3 | K16: M | L16: 5 | M16: M | N16: =IF(COUNT(D16,F16,H16,J16,L16)=0,"",(D16*0.2+F16*0.15+H16*0.15+J16*0.1+L16*0.1)/(IF(D16<>"",0.2,0)+IF(F16<>"",0.15,0)+IF(H16<>"",0.15,0)+IF(J16<>"",0.1,0)+IF(L16<>"",0.1,0))) -> 3.7142857 | O16: =IF(COUNT(D16,F16,H16,J16,L16)=0,"",D16*0.2+F16*0.15+H16*0.15+J16*0.1+L16*0.1) -> 2.6 | P16: 4 | Q16: H | R16: 5 | S16: H | T16: 3 | U16: M | V16: 2 | W16: M | X16: =IF(COUNT(P16,R16,T16,V16)=0,"",P16*0.08+R16*0.06+T16*0.03+V16*0.08) -> 0.87 | Y16: 2 | Z16: M | AA16: 5 | AB16: H | AC16: 2 | AD16: L | AE16: =IF(COUNT(Y16,AA16,AC16)=0,"",Y16*0.02+AA16*0.02+AC16*0.01) -> 0.16 | AF16: =IF(OR(COUNT(D16,F16,H16,J16,L16)<5,COUNT(P16,R16,T16,V16)<4,COUNT(Y16,AA16,AC16)<3),"",(O16+X16+AE16)*20) -> 72.6 | AG16: =IF(AF16="","",IF(AF16>=80,"STRONG BUY",IF(AF16>=65,"BUY",IF(AF16>=50,"WATCH LIST",IF(AF16>=35,"AVOID","PASS"))))) -> BUY | AH16: =IF(N16="","",IF(N16<3,"FAIL","OK")) -> OK | AI16: =IF(COUNT(D16:L16)=0,"",IF(COUNTIF(D16:L16,1)>0,"REVIEW","OK")) -> OK | AJ16: =IF(COUNT(D16:L16)=0,"",IF(COUNTIF(D16:L16,"<=2")>=2,"AVOID","OK")) -> OK | AK16: =IF(COUNTA(E16:M16)=0,"",IF(COUNTIF(E16:M16,"L")>=2,"CAP AT BUY","OK")) -> OK | AL16: Technology | AM16: Semiconductor Equipment & Materials | AN16: 4143079000 | AO16: 4830771000 | AP16: =IF(OR(AN16="",AO16=""),"",IF(AN16>AO16,"OK","LOW CONF")) -> LOW CONF | AQ16: 1.633 | AR16: 1.625 | AS16: =IF(OR(AQ16="",AR16=""),"",IF(AQ16<AR16,"Decreased",IF(AQ16>AR16,"Increased","Flat"))) -> Increased
A17: TSM | B17: Taiwan Semiconductor Mfg. | C17: 46295 | D17: 5 | E17: M | F17: 2 | G17: M | H17: 5 | I17: H | J17: 4 | K17: M | L17: 5 | M17: M | N17: =IF(COUNT(D17,F17,H17,J17,L17)=0,"",(D17*0.2+F17*0.15+H17*0.15+J17*0.1+L17*0.1)/(IF(D17<>"",0.2,0)+IF(F17<>"",0.15,0)+IF(H17<>"",0.15,0)+IF(J17<>"",0.1,0)+IF(L17<>"",0.1,0))) -> 4.2142857 | O17: =IF(COUNT(D17,F17,H17,J17,L17)=0,"",D17*0.2+F17*0.15+H17*0.15+J17*0.1+L17*0.1) -> 2.95 | P17: 4 | Q17: H | R17: 5 | S17: H | T17: 4 | U17: M | V17: 4 | W17: M | X17: =IF(COUNT(P17,R17,T17,V17)=0,"",P17*0.08+R17*0.06+T17*0.03+V17*0.08) -> 1.06 | Y17: 3 | Z17: M | AA17: 5 | AB17: H | AC17: 3 | AD17: L | AE17: =IF(COUNT(Y17,AA17,AC17)=0,"",Y17*0.02+AA17*0.02+AC17*0.01) -> 0.19 | AF17: =IF(OR(COUNT(D17,F17,H17,J17,L17)<5,COUNT(P17,R17,T17,V17)<4,COUNT(Y17,AA17,AC17)<3),"",(O17+X17+AE17)*20) -> 84 | AG17: =IF(AF17="","",IF(AF17>=80,"STRONG BUY",IF(AF17>=65,"BUY",IF(AF17>=50,"WATCH LIST",IF(AF17>=35,"AVOID","PASS"))))) -> STRONG BUY | AH17: =IF(N17="","",IF(N17<3,"FAIL","OK")) -> OK | AI17: =IF(COUNT(D17:L17)=0,"",IF(COUNTIF(D17:L17,1)>0,"REVIEW","OK")) -> OK | AJ17: =IF(COUNT(D17:L17)=0,"",IF(COUNTIF(D17:L17,"<=2")>=2,"AVOID","OK")) -> OK | AK17: =IF(COUNTA(E17:M17)=0,"",IF(COUNTIF(E17:M17,"L")>=2,"CAP AT BUY","OK")) -> OK | AL17: Technology | AM17: Semiconductors | AP17: =IF(OR(AN17="",AO17=""),"",IF(AN17>AO17,"OK","LOW CONF")) | AS17: =IF(OR(AQ17="",AR17=""),"",IF(AQ17<AR17,"Decreased",IF(AQ17>AR17,"Increased","Flat")))
A18: VRT | B18: Vertiv Holdings | C18: 46295 | D18: 3 | E18: M | F18: 5 | G18: M | H18: 4 | I18: M | J18: 4 | K18: M | L18: 4 | M18: M | N18: =IF(COUNT(D18,F18,H18,J18,L18)=0,"",(D18*0.2+F18*0.15+H18*0.15+J18*0.1+L18*0.1)/(IF(D18<>"",0.2,0)+IF(F18<>"",0.15,0)+IF(H18<>"",0.15,0)+IF(J18<>"",0.1,0)+IF(L18<>"",0.1,0))) -> 3.9285714 | O18: =IF(COUNT(D18,F18,H18,J18,L18)=0,"",D18*0.2+F18*0.15+H18*0.15+J18*0.1+L18*0.1) -> 2.75 | P18: 4 | Q18: M | R18: 5 | S18: H | T18: 4 | U18: M | V18: 2 | W18: M | X18: =IF(COUNT(P18,R18,T18,V18)=0,"",P18*0.08+R18*0.06+T18*0.03+V18*0.08) -> 0.9 | Y18: 4 | Z18: M | AA18: 4 | AB18: M | AC18: 3 | AD18: L | AE18: =IF(COUNT(Y18,AA18,AC18)=0,"",Y18*0.02+AA18*0.02+AC18*0.01) -> 0.19 | AF18: =IF(OR(COUNT(D18,F18,H18,J18,L18)<5,COUNT(P18,R18,T18,V18)<4,COUNT(Y18,AA18,AC18)<3),"",(O18+X18+AE18)*20) -> 76.8 | AG18: =IF(AF18="","",IF(AF18>=80,"STRONG BUY",IF(AF18>=65,"BUY",IF(AF18>=50,"WATCH LIST",IF(AF18>=35,"AVOID","PASS"))))) -> BUY | AH18: =IF(N18="","",IF(N18<3,"FAIL","OK")) -> OK | AI18: =IF(COUNT(D18:L18)=0,"",IF(COUNTIF(D18:L18,1)>0,"REVIEW","OK")) -> OK | AJ18: =IF(COUNT(D18:L18)=0,"",IF(COUNTIF(D18:L18,"<=2")>=2,"AVOID","OK")) -> OK | AK18: =IF(COUNTA(E18:M18)=0,"",IF(COUNTIF(E18:M18,"L")>=2,"CAP AT BUY","OK")) -> OK | AL18: Industrials | AM18: Electrical Equipment & Parts | AN18: 2113800000 | AO18: 1332800000 | AP18: =IF(OR(AN18="",AO18=""),"",IF(AN18>AO18,"OK","LOW CONF")) -> OK | AQ18: 1.71 | AR18: 2.771 | AS18: =IF(OR(AQ18="",AR18=""),"",IF(AQ18<AR18,"Decreased",IF(AQ18>AR18,"Increased","Flat"))) -> Decreased
A19: COST | B19: Costco Wholesale Corp. | C19: 46245 | D19: 3 | E19: M | F19: 5 | G19: H | H19: 5 | I19: H | J19: 4 | K19: M | L19: 4 | M19: H | N19: =IF(COUNT(D19,F19,H19,J19,L19)=0,"",(D19*0.2+F19*0.15+H19*0.15+J19*0.1+L19*0.1)/(IF(D19<>"",0.2,0)+IF(F19<>"",0.15,0)+IF(H19<>"",0.15,0)+IF(J19<>"",0.1,0)+IF(L19<>"",0.1,0))) -> 4.1428571 | O19: =IF(COUNT(D19,F19,H19,J19,L19)=0,"",D19*0.2+F19*0.15+H19*0.15+J19*0.1+L19*0.1) -> 2.9 | P19: 3 | Q19: L | R19: 5 | S19: H | T19: 5 | U19: H | V19: 1 | W19: H | X19: =IF(COUNT(P19,R19,T19,V19)=0,"",P19*0.08+R19*0.06+T19*0.03+V19*0.08) -> 0.77 | Y19: 4 | Z19: M | AA19: 4 | AB19: M | AC19: 4 | AD19: M | AE19: =IF(COUNT(Y19,AA19,AC19)=0,"",Y19*0.02+AA19*0.02+AC19*0.01) -> 0.2 | AF19: =IF(OR(COUNT(D19,F19,H19,J19,L19)<5,COUNT(P19,R19,T19,V19)<4,COUNT(Y19,AA19,AC19)<3),"",(O19+X19+AE19)*20) -> 77.4 | AG19: =IF(AF19="","",IF(AF19>=80,"STRONG BUY",IF(AF19>=65,"BUY",IF(AF19>=50,"WATCH LIST",IF(AF19>=35,"AVOID","PASS"))))) -> BUY | AH19: =IF(N19="","",IF(N19<3,"FAIL","OK")) -> OK | AI19: =IF(COUNT(D19:L19)=0,"",IF(COUNTIF(D19:L19,1)>0,"REVIEW","OK")) -> OK | AJ19: =IF(COUNT(D19:L19)=0,"",IF(COUNTIF(D19:L19,"<=2")>=2,"AVOID","OK")) -> OK | AK19: =IF(COUNTA(E19:M19)=0,"",IF(COUNTIF(E19:M19,"L")>=2,"CAP AT BUY","OK")) -> OK | AL19: Consumer Defensive | AM19: Discount Stores | AP19: =IF(OR(AN19="",AO19=""),"",IF(AN19>AO19,"OK","LOW CONF")) | AS19: =IF(OR(AQ19="",AR19=""),"",IF(AQ19<AR19,"Decreased",IF(AQ19>AR19,"Increased","Flat")))
A20: V | B20: Visa Inc. | C20: 46295 | D20: 3 | E20: M | F20: 4 | G20: M | H20: 5 | I20: H | J20: 4 | K20: M | L20: 2 | M20: M | N20: =IF(COUNT(D20,F20,H20,J20,L20)=0,"",(D20*0.2+F20*0.15+H20*0.15+J20*0.1+L20*0.1)/(IF(D20<>"",0.2,0)+IF(F20<>"",0.15,0)+IF(H20<>"",0.15,0)+IF(J20<>"",0.1,0)+IF(L20<>"",0.1,0))) -> 3.6428571 | O20: =IF(COUNT(D20,F20,H20,J20,L20)=0,"",D20*0.2+F20*0.15+H20*0.15+J20*0.1+L20*0.1) -> 2.55 | P20: 4 | Q20: M | R20: 5 | S20: H | T20: 3 | U20: M | V20: 3 | W20: M | X20: =IF(COUNT(P20,R20,T20,V20)=0,"",P20*0.08+R20*0.06+T20*0.03+V20*0.08) -> 0.95 | Y20: 3 | Z20: M | AA20: 4 | AB20: M | AC20: 3 | AD20: L | AE20: =IF(COUNT(Y20,AA20,AC20)=0,"",Y20*0.02+AA20*0.02+AC20*0.01) -> 0.17 | AF20: =IF(OR(COUNT(D20,F20,H20,J20,L20)<5,COUNT(P20,R20,T20,V20)<4,COUNT(Y20,AA20,AC20)<3),"",(O20+X20+AE20)*20) -> 73.4 | AG20: =IF(AF20="","",IF(AF20>=80,"STRONG BUY",IF(AF20>=65,"BUY",IF(AF20>=50,"WATCH LIST",IF(AF20>=35,"AVOID","PASS"))))) -> BUY | AH20: =IF(N20="","",IF(N20<3,"FAIL","OK")) -> OK | AI20: =IF(COUNT(D20:L20)=0,"",IF(COUNTIF(D20:L20,1)>0,"REVIEW","OK")) -> OK | AJ20: =IF(COUNT(D20:L20)=0,"",IF(COUNTIF(D20:L20,"<=2")>=2,"AVOID","OK")) -> OK | AK20: =IF(COUNTA(E20:M20)=0,"",IF(COUNTIF(E20:M20,"L")>=2,"CAP AT BUY","OK")) -> OK | AL20: Financial Services | AM20: Credit Services | AN20: 23059000000 | AO20: 20058000000 | AP20: =IF(OR(AN20="",AO20=""),"",IF(AN20>AO20,"OK","LOW CONF")) -> OK | AQ20: 1.167 | AR20: 1.115 | AS20: =IF(OR(AQ20="",AR20=""),"",IF(AQ20<AR20,"Decreased",IF(AQ20>AR20,"Increased","Flat"))) -> Increased
A21: NEE | B21: NextEra Energy Inc. | C21: 46245 | D21: 1 | E21: H | F21: 3 | G21: M | H21: 4 | I21: M | J21: 4 | K21: M | L21: 1 | M21: H | N21: =IF(COUNT(D21,F21,H21,J21,L21)=0,"",(D21*0.2+F21*0.15+H21*0.15+J21*0.1+L21*0.1)/(IF(D21<>"",0.2,0)+IF(F21<>"",0.15,0)+IF(H21<>"",0.15,0)+IF(J21<>"",0.1,0)+IF(L21<>"",0.1,0))) -> 2.5 | O21: =IF(COUNT(D21,F21,H21,J21,L21)=0,"",D21*0.2+F21*0.15+H21*0.15+J21*0.1+L21*0.1) -> 1.75 | X21: =IF(COUNT(P21,R21,T21,V21)=0,"",P21*0.08+R21*0.06+T21*0.03+V21*0.08) | AE21: =IF(COUNT(Y21,AA21,AC21)=0,"",Y21*0.02+AA21*0.02+AC21*0.01) | AF21: =IF(OR(COUNT(D21,F21,H21,J21,L21)<5,COUNT(P21,R21,T21,V21)<4,COUNT(Y21,AA21,AC21)<3),"",(O21+X21+AE21)*20) | AG21: =IF(AF21="","",IF(AF21>=80,"STRONG BUY",IF(AF21>=65,"BUY",IF(AF21>=50,"WATCH LIST",IF(AF21>=35,"AVOID","PASS"))))) | AH21: =IF(N21="","",IF(N21<3,"FAIL","OK")) -> FAIL | AI21: =IF(COUNT(D21:L21)=0,"",IF(COUNTIF(D21:L21,1)>0,"REVIEW","OK")) -> REVIEW | AJ21: =IF(COUNT(D21:L21)=0,"",IF(COUNTIF(D21:L21,"<=2")>=2,"AVOID","OK")) -> AVOID | AK21: =IF(COUNTA(E21:M21)=0,"",IF(COUNTIF(E21:M21,"L")>=2,"CAP AT BUY","OK")) -> OK | AL21: Utilities | AM21: Utilities - Regulated Electric | AP21: =IF(OR(AN21="",AO21=""),"",IF(AN21>AO21,"OK","LOW CONF")) | AS21: =IF(OR(AQ21="",AR21=""),"",IF(AQ21<AR21,"Decreased",IF(AQ21>AR21,"Increased","Flat")))
A22: CRK | B22: Comstock Resources Inc. | C22: 46245 | D22: 1 | E22: H | F22: 1 | G22: H | H22: 2 | I22: M | J22: 1 | K22: H | L22: 1 | M22: H | N22: =IF(COUNT(D22,F22,H22,J22,L22)=0,"",(D22*0.2+F22*0.15+H22*0.15+J22*0.1+L22*0.1)/(IF(D22<>"",0.2,0)+IF(F22<>"",0.15,0)+IF(H22<>"",0.15,0)+IF(J22<>"",0.1,0)+IF(L22<>"",0.1,0))) -> 1.2142857 | O22: =IF(COUNT(D22,F22,H22,J22,L22)=0,"",D22*0.2+F22*0.15+H22*0.15+J22*0.1+L22*0.1) -> 0.85 | X22: =IF(COUNT(P22,R22,T22,V22)=0,"",P22*0.08+R22*0.06+T22*0.03+V22*0.08) | AE22: =IF(COUNT(Y22,AA22,AC22)=0,"",Y22*0.02+AA22*0.02+AC22*0.01) | AF22: =IF(OR(COUNT(D22,F22,H22,J22,L22)<5,COUNT(P22,R22,T22,V22)<4,COUNT(Y22,AA22,AC22)<3),"",(O22+X22+AE22)*20) | AG22: =IF(AF22="","",IF(AF22>=80,"STRONG BUY",IF(AF22>=65,"BUY",IF(AF22>=50,"WATCH LIST",IF(AF22>=35,"AVOID","PASS"))))) | AH22: =IF(N22="","",IF(N22<3,"FAIL","OK")) -> FAIL | AI22: =IF(COUNT(D22:L22)=0,"",IF(COUNTIF(D22:L22,1)>0,"REVIEW","OK")) -> REVIEW | AJ22: =IF(COUNT(D22:L22)=0,"",IF(COUNTIF(D22:L22,"<=2")>=2,"AVOID","OK")) -> AVOID | AK22: =IF(COUNTA(E22:M22)=0,"",IF(COUNTIF(E22:M22,"L")>=2,"CAP AT BUY","OK")) -> OK | AL22: Energy | AM22: Oil & Gas E&P | AP22: =IF(OR(AN22="",AO22=""),"",IF(AN22>AO22,"OK","LOW CONF")) | AS22: =IF(OR(AQ22="",AR22=""),"",IF(AQ22<AR22,"Decreased",IF(AQ22>AR22,"Increased","Flat")))
A23: ET | B23: Energy Transfer LP | C23: 46276 | D23: 4 | E23: M | F23: 1 | G23: M | H23: 4 | I23: M | J23: 4 | K23: M | L23: 2 | M23: M | N23: =IF(COUNT(D23,F23,H23,J23,L23)=0,"",(D23*0.2+F23*0.15+H23*0.15+J23*0.1+L23*0.1)/(IF(D23<>"",0.2,0)+IF(F23<>"",0.15,0)+IF(H23<>"",0.15,0)+IF(J23<>"",0.1,0)+IF(L23<>"",0.1,0))) -> 3.0714286 | O23: =IF(COUNT(D23,F23,H23,J23,L23)=0,"",D23*0.2+F23*0.15+H23*0.15+J23*0.1+L23*0.1) -> 2.15 | X23: =IF(COUNT(P23,R23,T23,V23)=0,"",P23*0.08+R23*0.06+T23*0.03+V23*0.08) | AE23: =IF(COUNT(Y23,AA23,AC23)=0,"",Y23*0.02+AA23*0.02+AC23*0.01) | AF23: =IF(OR(COUNT(D23,F23,H23,J23,L23)<5,COUNT(P23,R23,T23,V23)<4,COUNT(Y23,AA23,AC23)<3),"",(O23+X23+AE23)*20) | AG23: =IF(AF23="","",IF(AF23>=80,"STRONG BUY",IF(AF23>=65,"BUY",IF(AF23>=50,"WATCH LIST",IF(AF23>=35,"AVOID","PASS"))))) | AH23: =IF(N23="","",IF(N23<3,"FAIL","OK")) -> OK | AI23: =IF(COUNT(D23:L23)=0,"",IF(COUNTIF(D23:L23,1)>0,"REVIEW","OK")) -> REVIEW | AJ23: =IF(COUNT(D23:L23)=0,"",IF(COUNTIF(D23:L23,"<=2")>=2,"AVOID","OK")) -> AVOID | AK23: =IF(COUNTA(E23:M23)=0,"",IF(COUNTIF(E23:M23,"L")>=2,"CAP AT BUY","OK")) -> OK | AL23: Energy | AM23: Oil & Gas Midstream | AP23: =IF(OR(AN23="",AO23=""),"",IF(AN23>AO23,"OK","LOW CONF")) | AS23: =IF(OR(AQ23="",AR23=""),"",IF(AQ23<AR23,"Decreased",IF(AQ23>AR23,"Increased","Flat")))
A24: LBRT | B24: Liberty Energy Inc. | C24: 46245 | D24: 2 | E24: L | F24: 2 | G24: M | H24: 3 | I24: M | J24: 2 | K24: M | L24: 1 | M24: H | N24: =IF(COUNT(D24,F24,H24,J24,L24)=0,"",(D24*0.2+F24*0.15+H24*0.15+J24*0.1+L24*0.1)/(IF(D24<>"",0.2,0)+IF(F24<>"",0.15,0)+IF(H24<>"",0.15,0)+IF(J24<>"",0.1,0)+IF(L24<>"",0.1,0))) -> 2.0714286 | O24: =IF(COUNT(D24,F24,H24,J24,L24)=0,"",D24*0.2+F24*0.15+H24*0.15+J24*0.1+L24*0.1) -> 1.45 | X24: =IF(COUNT(P24,R24,T24,V24)=0,"",P24*0.08+R24*0.06+T24*0.03+V24*0.08) | AE24: =IF(COUNT(Y24,AA24,AC24)=0,"",Y24*0.02+AA24*0.02+AC24*0.01) | AF24: =IF(OR(COUNT(D24,F24,H24,J24,L24)<5,COUNT(P24,R24,T24,V24)<4,COUNT(Y24,AA24,AC24)<3),"",(O24+X24+AE24)*20) | AG24: =IF(AF24="","",IF(AF24>=80,"STRONG BUY",IF(AF24>=65,"BUY",IF(AF24>=50,"WATCH LIST",IF(AF24>=35,"AVOID","PASS"))))) | AH24: =IF(N24="","",IF(N24<3,"FAIL","OK")) -> FAIL | AI24: =IF(COUNT(D24:L24)=0,"",IF(COUNTIF(D24:L24,1)>0,"REVIEW","OK")) -> REVIEW | AJ24: =IF(COUNT(D24:L24)=0,"",IF(COUNTIF(D24:L24,"<=2")>=2,"AVOID","OK")) -> AVOID | AK24: =IF(COUNTA(E24:M24)=0,"",IF(COUNTIF(E24:M24,"L")>=2,"CAP AT BUY","OK")) -> OK | AL24: Energy | AM24: Oil & Gas Equipment & Services | AP24: =IF(OR(AN24="",AO24=""),"",IF(AN24>AO24,"OK","LOW CONF")) | AS24: =IF(OR(AQ24="",AR24=""),"",IF(AQ24<AR24,"Decreased",IF(AQ24>AR24,"Increased","Flat")))
A25: NOV | B25: NOV Inc. | C25: 46245 | D25: 3 | E25: M | F25: 2 | G25: H | H25: 3 | I25: M | J25: 3 | K25: M | L25: 2 | M25: H | N25: =IF(COUNT(D25,F25,H25,J25,L25)=0,"",(D25*0.2+F25*0.15+H25*0.15+J25*0.1+L25*0.1)/(IF(D25<>"",0.2,0)+IF(F25<>"",0.15,0)+IF(H25<>"",0.15,0)+IF(J25<>"",0.1,0)+IF(L25<>"",0.1,0))) -> 2.6428571 | O25: =IF(COUNT(D25,F25,H25,J25,L25)=0,"",D25*0.2+F25*0.15+H25*0.15+J25*0.1+L25*0.1) -> 1.85 | X25: =IF(COUNT(P25,R25,T25,V25)=0,"",P25*0.08+R25*0.06+T25*0.03+V25*0.08) | AE25: =IF(COUNT(Y25,AA25,AC25)=0,"",Y25*0.02+AA25*0.02+AC25*0.01) | AF25: =IF(OR(COUNT(D25,F25,H25,J25,L25)<5,COUNT(P25,R25,T25,V25)<4,COUNT(Y25,AA25,AC25)<3),"",(O25+X25+AE25)*20) | AG25: =IF(AF25="","",IF(AF25>=80,"STRONG BUY",IF(AF25>=65,"BUY",IF(AF25>=50,"WATCH LIST",IF(AF25>=35,"AVOID","PASS"))))) | AH25: =IF(N25="","",IF(N25<3,"FAIL","OK")) -> FAIL | AI25: =IF(COUNT(D25:L25)=0,"",IF(COUNTIF(D25:L25,1)>0,"REVIEW","OK")) -> OK | AJ25: =IF(COUNT(D25:L25)=0,"",IF(COUNTIF(D25:L25,"<=2")>=2,"AVOID","OK")) -> AVOID | AK25: =IF(COUNTA(E25:M25)=0,"",IF(COUNTIF(E25:M25,"L")>=2,"CAP AT BUY","OK")) -> OK | AL25: Energy | AM25: Oil & Gas Equipment & Services | AP25: =IF(OR(AN25="",AO25=""),"",IF(AN25>AO25,"OK","LOW CONF")) | AS25: =IF(OR(AQ25="",AR25=""),"",IF(AQ25<AR25,"Decreased",IF(AQ25>AR25,"Increased","Flat")))
A26: CE | B26: Celanese Corp. | C26: 46245 | D26: 2 | E26: M | F26: 1 | G26: H | H26: 2 | I26: M | J26: 2 | K26: M | L26: 2 | M26: M | N26: =IF(COUNT(D26,F26,H26,J26,L26)=0,"",(D26*0.2+F26*0.15+H26*0.15+J26*0.1+L26*0.1)/(IF(D26<>"",0.2,0)+IF(F26<>"",0.15,0)+IF(H26<>"",0.15,0)+IF(J26<>"",0.1,0)+IF(L26<>"",0.1,0))) -> 1.7857143 | O26: =IF(COUNT(D26,F26,H26,J26,L26)=0,"",D26*0.2+F26*0.15+H26*0.15+J26*0.1+L26*0.1) -> 1.25 | X26: =IF(COUNT(P26,R26,T26,V26)=0,"",P26*0.08+R26*0.06+T26*0.03+V26*0.08) | AE26: =IF(COUNT(Y26,AA26,AC26)=0,"",Y26*0.02+AA26*0.02+AC26*0.01) | AF26: =IF(OR(COUNT(D26,F26,H26,J26,L26)<5,COUNT(P26,R26,T26,V26)<4,COUNT(Y26,AA26,AC26)<3),"",(O26+X26+AE26)*20) | AG26: =IF(AF26="","",IF(AF26>=80,"STRONG BUY",IF(AF26>=65,"BUY",IF(AF26>=50,"WATCH LIST",IF(AF26>=35,"AVOID","PASS"))))) | AH26: =IF(N26="","",IF(N26<3,"FAIL","OK")) -> FAIL | AI26: =IF(COUNT(D26:L26)=0,"",IF(COUNTIF(D26:L26,1)>0,"REVIEW","OK")) -> REVIEW | AJ26: =IF(COUNT(D26:L26)=0,"",IF(COUNTIF(D26:L26,"<=2")>=2,"AVOID","OK")) -> AVOID | AK26: =IF(COUNTA(E26:M26)=0,"",IF(COUNTIF(E26:M26,"L")>=2,"CAP AT BUY","OK")) -> OK | AL26: Basic Materials | AM26: Chemicals | AP26: =IF(OR(AN26="",AO26=""),"",IF(AN26>AO26,"OK","LOW CONF")) | AS26: =IF(OR(AQ26="",AR26=""),"",IF(AQ26<AR26,"Decreased",IF(AQ26>AR26,"Increased","Flat")))
A27: CLF | B27: Cleveland-Cliffs Inc. | C27: 46245 | D27: 2 | E27: H | F27: 2 | G27: M | H27: 2 | I27: M | J27: 2 | K27: M | L27: 1 | M27: H | N27: =IF(COUNT(D27,F27,H27,J27,L27)=0,"",(D27*0.2+F27*0.15+H27*0.15+J27*0.1+L27*0.1)/(IF(D27<>"",0.2,0)+IF(F27<>"",0.15,0)+IF(H27<>"",0.15,0)+IF(J27<>"",0.1,0)+IF(L27<>"",0.1,0))) -> 1.8571429 | O27: =IF(COUNT(D27,F27,H27,J27,L27)=0,"",D27*0.2+F27*0.15+H27*0.15+J27*0.1+L27*0.1) -> 1.3 | X27: =IF(COUNT(P27,R27,T27,V27)=0,"",P27*0.08+R27*0.06+T27*0.03+V27*0.08) | AE27: =IF(COUNT(Y27,AA27,AC27)=0,"",Y27*0.02+AA27*0.02+AC27*0.01) | AF27: =IF(OR(COUNT(D27,F27,H27,J27,L27)<5,COUNT(P27,R27,T27,V27)<4,COUNT(Y27,AA27,AC27)<3),"",(O27+X27+AE27)*20) | AG27: =IF(AF27="","",IF(AF27>=80,"STRONG BUY",IF(AF27>=65,"BUY",IF(AF27>=50,"WATCH LIST",IF(AF27>=35,"AVOID","PASS"))))) | AH27: =IF(N27="","",IF(N27<3,"FAIL","OK")) -> FAIL | AI27: =IF(COUNT(D27:L27)=0,"",IF(COUNTIF(D27:L27,1)>0,"REVIEW","OK")) -> REVIEW | AJ27: =IF(COUNT(D27:L27)=0,"",IF(COUNTIF(D27:L27,"<=2")>=2,"AVOID","OK")) -> AVOID | AK27: =IF(COUNTA(E27:M27)=0,"",IF(COUNTIF(E27:M27,"L")>=2,"CAP AT BUY","OK")) -> OK | AL27: Basic Materials | AM27: Steel | AP27: =IF(OR(AN27="",AO27=""),"",IF(AN27>AO27,"OK","LOW CONF")) | AS27: =IF(OR(AQ27="",AR27=""),"",IF(AQ27<AR27,"Decreased",IF(AQ27>AR27,"Increased","Flat")))
A28: LIN | B28: Linde plc | C28: 46276 | D28: 2 | E28: M | F28: 2 | G28: M | H28: 5 | I28: H | J28: 5 | K28: H | L28: 2 | M28: M | N28: =IF(COUNT(D28,F28,H28,J28,L28)=0,"",(D28*0.2+F28*0.15+H28*0.15+J28*0.1+L28*0.1)/(IF(D28<>"",0.2,0)+IF(F28<>"",0.15,0)+IF(H28<>"",0.15,0)+IF(J28<>"",0.1,0)+IF(L28<>"",0.1,0))) -> 3.0714286 | O28: =IF(COUNT(D28,F28,H28,J28,L28)=0,"",D28*0.2+F28*0.15+H28*0.15+J28*0.1+L28*0.1) -> 2.15 | X28: =IF(COUNT(P28,R28,T28,V28)=0,"",P28*0.08+R28*0.06+T28*0.03+V28*0.08) | AE28: =IF(COUNT(Y28,AA28,AC28)=0,"",Y28*0.02+AA28*0.02+AC28*0.01) | AF28: =IF(OR(COUNT(D28,F28,H28,J28,L28)<5,COUNT(P28,R28,T28,V28)<4,COUNT(Y28,AA28,AC28)<3),"",(O28+X28+AE28)*20) | AG28: =IF(AF28="","",IF(AF28>=80,"STRONG BUY",IF(AF28>=65,"BUY",IF(AF28>=50,"WATCH LIST",IF(AF28>=35,"AVOID","PASS"))))) | AH28: =IF(N28="","",IF(N28<3,"FAIL","OK")) -> OK | AI28: =IF(COUNT(D28:L28)=0,"",IF(COUNTIF(D28:L28,1)>0,"REVIEW","OK")) -> OK | AJ28: =IF(COUNT(D28:L28)=0,"",IF(COUNTIF(D28:L28,"<=2")>=2,"AVOID","OK")) -> AVOID | AK28: =IF(COUNTA(E28:M28)=0,"",IF(COUNTIF(E28:M28,"L")>=2,"CAP AT BUY","OK")) -> OK | AL28: Basic Materials | AM28: Specialty Chemicals | AP28: =IF(OR(AN28="",AO28=""),"",IF(AN28>AO28,"OK","LOW CONF")) | AS28: =IF(OR(AQ28="",AR28=""),"",IF(AQ28<AR28,"Decreased",IF(AQ28>AR28,"Increased","Flat")))
A29: DEO | B29: Diageo plc | C29: 46245 | D29: 2 | E29: M | F29: 2 | G29: M | H29: 3 | I29: M | J29: 3 | K29: M | L29: 2 | M29: H | N29: =IF(COUNT(D29,F29,H29,J29,L29)=0,"",(D29*0.2+F29*0.15+H29*0.15+J29*0.1+L29*0.1)/(IF(D29<>"",0.2,0)+IF(F29<>"",0.15,0)+IF(H29<>"",0.15,0)+IF(J29<>"",0.1,0)+IF(L29<>"",0.1,0))) -> 2.3571429 | O29: =IF(COUNT(D29,F29,H29,J29,L29)=0,"",D29*0.2+F29*0.15+H29*0.15+J29*0.1+L29*0.1) -> 1.65 | X29: =IF(COUNT(P29,R29,T29,V29)=0,"",P29*0.08+R29*0.06+T29*0.03+V29*0.08) | AE29: =IF(COUNT(Y29,AA29,AC29)=0,"",Y29*0.02+AA29*0.02+AC29*0.01) | AF29: =IF(OR(COUNT(D29,F29,H29,J29,L29)<5,COUNT(P29,R29,T29,V29)<4,COUNT(Y29,AA29,AC29)<3),"",(O29+X29+AE29)*20) | AG29: =IF(AF29="","",IF(AF29>=80,"STRONG BUY",IF(AF29>=65,"BUY",IF(AF29>=50,"WATCH LIST",IF(AF29>=35,"AVOID","PASS"))))) | AH29: =IF(N29="","",IF(N29<3,"FAIL","OK")) -> FAIL | AI29: =IF(COUNT(D29:L29)=0,"",IF(COUNTIF(D29:L29,1)>0,"REVIEW","OK")) -> OK | AJ29: =IF(COUNT(D29:L29)=0,"",IF(COUNTIF(D29:L29,"<=2")>=2,"AVOID","OK")) -> AVOID | AK29: =IF(COUNTA(E29:M29)=0,"",IF(COUNTIF(E29:M29,"L")>=2,"CAP AT BUY","OK")) -> OK | AL29: Consumer Defensive | AM29: Beverages - Wineries & Distilleries | AP29: =IF(OR(AN29="",AO29=""),"",IF(AN29>AO29,"OK","LOW CONF")) | AS29: =IF(OR(AQ29="",AR29=""),"",IF(AQ29<AR29,"Decreased",IF(AQ29>AR29,"Increased","Flat")))
A30: EL | B30: Estee Lauder Companies | C30: 46245 | D30: 2 | E30: M | F30: 1 | G30: H | H30: 3 | I30: M | J30: 2 | K30: M | L30: 3 | M30: M | N30: =IF(COUNT(D30,F30,H30,J30,L30)=0,"",(D30*0.2+F30*0.15+H30*0.15+J30*0.1+L30*0.1)/(IF(D30<>"",0.2,0)+IF(F30<>"",0.15,0)+IF(H30<>"",0.15,0)+IF(J30<>"",0.1,0)+IF(L30<>"",0.1,0))) -> 2.1428571 | O30: =IF(COUNT(D30,F30,H30,J30,L30)=0,"",D30*0.2+F30*0.15+H30*0.15+J30*0.1+L30*0.1) -> 1.5 | X30: =IF(COUNT(P30,R30,T30,V30)=0,"",P30*0.08+R30*0.06+T30*0.03+V30*0.08) | AE30: =IF(COUNT(Y30,AA30,AC30)=0,"",Y30*0.02+AA30*0.02+AC30*0.01) | AF30: =IF(OR(COUNT(D30,F30,H30,J30,L30)<5,COUNT(P30,R30,T30,V30)<4,COUNT(Y30,AA30,AC30)<3),"",(O30+X30+AE30)*20) | AG30: =IF(AF30="","",IF(AF30>=80,"STRONG BUY",IF(AF30>=65,"BUY",IF(AF30>=50,"WATCH LIST",IF(AF30>=35,"AVOID","PASS"))))) | AH30: =IF(N30="","",IF(N30<3,"FAIL","OK")) -> FAIL | AI30: =IF(COUNT(D30:L30)=0,"",IF(COUNTIF(D30:L30,1)>0,"REVIEW","OK")) -> REVIEW | AJ30: =IF(COUNT(D30:L30)=0,"",IF(COUNTIF(D30:L30,"<=2")>=2,"AVOID","OK")) -> AVOID | AK30: =IF(COUNTA(E30:M30)=0,"",IF(COUNTIF(E30:M30,"L")>=2,"CAP AT BUY","OK")) -> OK | AL30: Consumer Defensive | AM30: Household & Personal Products | AP30: =IF(OR(AN30="",AO30=""),"",IF(AN30>AO30,"OK","LOW CONF")) | AS30: =IF(OR(AQ30="",AR30=""),"",IF(AQ30<AR30,"Decreased",IF(AQ30>AR30,"Increased","Flat")))
A31: HRL | B31: Hormel Foods Corp. | C31: 46245 | D31: 1 | E31: H | F31: 2 | G31: M | H31: 3 | I31: M | J31: 3 | K31: M | L31: 1 | M31: H | N31: =IF(COUNT(D31,F31,H31,J31,L31)=0,"",(D31*0.2+F31*0.15+H31*0.15+J31*0.1+L31*0.1)/(IF(D31<>"",0.2,0)+IF(F31<>"",0.15,0)+IF(H31<>"",0.15,0)+IF(J31<>"",0.1,0)+IF(L31<>"",0.1,0))) -> 1.9285714 | O31: =IF(COUNT(D31,F31,H31,J31,L31)=0,"",D31*0.2+F31*0.15+H31*0.15+J31*0.1+L31*0.1) -> 1.35 | X31: =IF(COUNT(P31,R31,T31,V31)=0,"",P31*0.08+R31*0.06+T31*0.03+V31*0.08) | AE31: =IF(COUNT(Y31,AA31,AC31)=0,"",Y31*0.02+AA31*0.02+AC31*0.01) | AF31: =IF(OR(COUNT(D31,F31,H31,J31,L31)<5,COUNT(P31,R31,T31,V31)<4,COUNT(Y31,AA31,AC31)<3),"",(O31+X31+AE31)*20) | AG31: =IF(AF31="","",IF(AF31>=80,"STRONG BUY",IF(AF31>=65,"BUY",IF(AF31>=50,"WATCH LIST",IF(AF31>=35,"AVOID","PASS"))))) | AH31: =IF(N31="","",IF(N31<3,"FAIL","OK")) -> FAIL | AI31: =IF(COUNT(D31:L31)=0,"",IF(COUNTIF(D31:L31,1)>0,"REVIEW","OK")) -> REVIEW | AJ31: =IF(COUNT(D31:L31)=0,"",IF(COUNTIF(D31:L31,"<=2")>=2,"AVOID","OK")) -> AVOID | AK31: =IF(COUNTA(E31:M31)=0,"",IF(COUNTIF(E31:M31,"L")>=2,"CAP AT BUY","OK")) -> OK | AL31: Consumer Defensive | AM31: Packaged Foods | AP31: =IF(OR(AN31="",AO31=""),"",IF(AN31>AO31,"OK","LOW CONF")) | AS31: =IF(OR(AQ31="",AR31=""),"",IF(AQ31<AR31,"Decreased",IF(AQ31>AR31,"Increased","Flat")))
A32: PG | B32: Procter & Gamble Co. | C32: 46295 | D32: 4 | E32: M | F32: 3 | G32: M | H32: 5 | I32: H | J32: 4 | K32: M | L32: 4 | M32: M | N32: =IF(COUNT(D32,F32,H32,J32,L32)=0,"",(D32*0.2+F32*0.15+H32*0.15+J32*0.1+L32*0.1)/(IF(D32<>"",0.2,0)+IF(F32<>"",0.15,0)+IF(H32<>"",0.15,0)+IF(J32<>"",0.1,0)+IF(L32<>"",0.1,0))) -> 4 | O32: =IF(COUNT(D32,F32,H32,J32,L32)=0,"",D32*0.2+F32*0.15+H32*0.15+J32*0.1+L32*0.1) -> 2.8 | X32: =IF(COUNT(P32,R32,T32,V32)=0,"",P32*0.08+R32*0.06+T32*0.03+V32*0.08) | AE32: =IF(COUNT(Y32,AA32,AC32)=0,"",Y32*0.02+AA32*0.02+AC32*0.01) | AF32: =IF(OR(COUNT(D32,F32,H32,J32,L32)<5,COUNT(P32,R32,T32,V32)<4,COUNT(Y32,AA32,AC32)<3),"",(O32+X32+AE32)*20) | AG32: =IF(AF32="","",IF(AF32>=80,"STRONG BUY",IF(AF32>=65,"BUY",IF(AF32>=50,"WATCH LIST",IF(AF32>=35,"AVOID","PASS"))))) | AH32: =IF(N32="","",IF(N32<3,"FAIL","OK")) -> OK | AI32: =IF(COUNT(D32:L32)=0,"",IF(COUNTIF(D32:L32,1)>0,"REVIEW","OK")) -> OK | AJ32: =IF(COUNT(D32:L32)=0,"",IF(COUNTIF(D32:L32,"<=2")>=2,"AVOID","OK")) -> OK | AK32: =IF(COUNTA(E32:M32)=0,"",IF(COUNTIF(E32:M32,"L")>=2,"CAP AT BUY","OK")) -> OK | AL32: Consumer Defensive | AM32: Household & Personal Products | AP32: =IF(OR(AN32="",AO32=""),"",IF(AN32>AO32,"OK","LOW CONF")) | AS32: =IF(OR(AQ32="",AR32=""),"",IF(AQ32<AR32,"Decreased",IF(AQ32>AR32,"Increased","Flat")))
... A42: ETSY | B42: Etsy Inc. | C42: 46246 | D42: 4 | E42: H | F42: 3 | G42: H | H42: 3 | I42: M | J42: 3 | K42: M | L42: 4 | M42: H | N42: =IF(COUNT(D42,F42,H42,J42,L42)=0,"",(D42*0.2+F42*0.15+H42*0.15+J42*0.1+L42*0.1)/(IF(D42<>"",0.2,0)+IF(F42<>"",0.15,0)+IF(H42<>"",0.15,0)+IF(J42<>"",0.1,0)+IF(L42<>"",0.1,0))) -> 3.4285714 | O42: =IF(COUNT(D42,F42,H42,J42,L42)=0,"",D42*0.2+F42*0.15+H42*0.15+J42*0.1+L42*0.1) -> 2.4 | X42: =IF(COUNT(P42,R42,T42,V42)=0,"",P42*0.08+R42*0.06+T42*0.03+V42*0.08) | AE42: =IF(COUNT(Y42,AA42,AC42)=0,"",Y42*0.02+AA42*0.02+AC42*0.01) | AF42: =IF(OR(COUNT(D42,F42,H42,J42,L42)<5,COUNT(P42,R42,T42,V42)<4,COUNT(Y42,AA42,AC42)<3),"",(O42+X42+AE42)*20) | AG42: =IF(AF42="","",IF(AF42>=80,"STRONG BUY",IF(AF42>=65,"BUY",IF(AF42>=50,"WATCH LIST",IF(AF42>=35,"AVOID","PASS"))))) | AH42: =IF(N42="","",IF(N42<3,"FAIL","OK")) -> OK | AI42: =IF(COUNT(D42:L42)=0,"",IF(COUNTIF(D42:L42,1)>0,"REVIEW","OK")) -> OK | AJ42: =IF(COUNT(D42:L42)=0,"",IF(COUNTIF(D42:L42,"<=2")>=2,"AVOID","OK")) -> OK | AK42: =IF(COUNTA(E42:M42)=0,"",IF(COUNTIF(E42:M42,"L")>=2,"CAP AT BUY","OK")) -> OK | AL42: Consumer Cyclical | AM42: Internet Retail | AP42: =IF(OR(AN42="",AO42=""),"",IF(AN42>AO42,"OK","LOW CONF")) | AS42: =IF(OR(AQ42="",AR42=""),"",IF(AQ42<AR42,"Decreased",IF(AQ42>AR42,"Increased","Flat")))
A43: GE | B43: GE Aerospace | C43: 46295 | D43: 4 | E43: M | F43: 5 | G43: M | H43: 5 | I43: M | J43: 4 | K43: M | L43: 2 | M43: M | N43: =IF(COUNT(D43,F43,H43,J43,L43)=0,"",(D43*0.2+F43*0.15+H43*0.15+J43*0.1+L43*0.1)/(IF(D43<>"",0.2,0)+IF(F43<>"",0.15,0)+IF(H43<>"",0.15,0)+IF(J43<>"",0.1,0)+IF(L43<>"",0.1,0))) -> 4.1428571 | O43: =IF(COUNT(D43,F43,H43,J43,L43)=0,"",D43*0.2+F43*0.15+H43*0.15+J43*0.1+L43*0.1) -> 2.9 | P43: 5 | Q43: H | R43: 5 | S43: L | T43: 3 | U43: M | V43: 4 | W43: M | X43: =IF(COUNT(P43,R43,T43,V43)=0,"",P43*0.08+R43*0.06+T43*0.03+V43*0.08) -> 1.11 | Y43: 5 | Z43: M | AA43: 4 | AB43: M | AC43: 2 | AD43: M | AE43: =IF(COUNT(Y43,AA43,AC43)=0,"",Y43*0.02+AA43*0.02+AC43*0.01) -> 0.2 | AF43: =IF(OR(COUNT(D43,F43,H43,J43,L43)<5,COUNT(P43,R43,T43,V43)<4,COUNT(Y43,AA43,AC43)<3),"",(O43+X43+AE43)*20) -> 84.2 | AG43: =IF(AF43="","",IF(AF43>=80,"STRONG BUY",IF(AF43>=65,"BUY",IF(AF43>=50,"WATCH LIST",IF(AF43>=35,"AVOID","PASS"))))) -> STRONG BUY | AH43: =IF(N43="","",IF(N43<3,"FAIL","OK")) -> OK | AI43: =IF(COUNT(D43:L43)=0,"",IF(COUNTIF(D43:L43,1)>0,"REVIEW","OK")) -> OK | AJ43: =IF(COUNT(D43:L43)=0,"",IF(COUNTIF(D43:L43,"<=2")>=2,"AVOID","OK")) -> OK | AK43: =IF(COUNTA(E43:M43)=0,"",IF(COUNTIF(E43:M43,"L")>=2,"CAP AT BUY","OK")) -> OK | AL43: Industrials | AM43: Aerospace & Defense | AP43: =IF(OR(AN43="",AO43=""),"",IF(AN43>AO43,"OK","LOW CONF")) | AS43: =IF(OR(AQ43="",AR43=""),"",IF(AQ43<AR43,"Decreased",IF(AQ43>AR43,"Increased","Flat")))
A44: PH | B44: Parker-Hannifin Corporation | C44: 46247 | D44: 4 | E44: M | F44: 3 | G44: M | H44: 3 | I44: M | J44: 2 | K44: M | L44: 4 | M44: M | N44: =IF(COUNT(D44,F44,H44,J44,L44)=0,"",(D44*0.2+F44*0.15+H44*0.15+J44*0.1+L44*0.1)/(IF(D44<>"",0.2,0)+IF(F44<>"",0.15,0)+IF(H44<>"",0.15,0)+IF(J44<>"",0.1,0)+IF(L44<>"",0.1,0))) -> 3.2857143 | O44: =IF(COUNT(D44,F44,H44,J44,L44)=0,"",D44*0.2+F44*0.15+H44*0.15+J44*0.1+L44*0.1) -> 2.3 | X44: =IF(COUNT(P44,R44,T44,V44)=0,"",P44*0.08+R44*0.06+T44*0.03+V44*0.08) | AA44: 4 | AB44: M | AE44: =IF(COUNT(Y44,AA44,AC44)=0,"",Y44*0.02+AA44*0.02+AC44*0.01) -> 0.08 | AF44: =IF(OR(COUNT(D44,F44,H44,J44,L44)<5,COUNT(P44,R44,T44,V44)<4,COUNT(Y44,AA44,AC44)<3),"",(O44+X44+AE44)*20) | AG44: =IF(AF44="","",IF(AF44>=80,"STRONG BUY",IF(AF44>=65,"BUY",IF(AF44>=50,"WATCH LIST",IF(AF44>=35,"AVOID","PASS"))))) | AH44: =IF(N44="","",IF(N44<3,"FAIL","OK")) -> OK | AI44: =IF(COUNT(D44:L44)=0,"",IF(COUNTIF(D44:L44,1)>0,"REVIEW","OK")) -> OK | AJ44: =IF(COUNT(D44:L44)=0,"",IF(COUNTIF(D44:L44,"<=2")>=2,"AVOID","OK")) -> OK | AK44: =IF(COUNTA(E44:M44)=0,"",IF(COUNTIF(E44:M44,"L")>=2,"CAP AT BUY","OK")) -> OK | AL44: Industrials | AM44: Specialty Industrial Machinery | AP44: =IF(OR(AN44="",AO44=""),"",IF(AN44>AO44,"OK","LOW CONF")) | AS44: =IF(OR(AQ44="",AR44=""),"",IF(AQ44<AR44,"Decreased",IF(AQ44>AR44,"Increased","Flat")))
A45: ETN | B45: Eaton Corporation plc | C45: 46247 | D45: 4 | E45: M | F45: 3 | G45: M | H45: 4 | I45: M | J45: 3 | K45: M | L45: 3 | M45: M | N45: =IF(COUNT(D45,F45,H45,J45,L45)=0,"",(D45*0.2+F45*0.15+H45*0.15+J45*0.1+L45*0.1)/(IF(D45<>"",0.2,0)+IF(F45<>"",0.15,0)+IF(H45<>"",0.15,0)+IF(J45<>"",0.1,0)+IF(L45<>"",0.1,0))) -> 3.5 | O45: =IF(COUNT(D45,F45,H45,J45,L45)=0,"",D45*0.2+F45*0.15+H45*0.15+J45*0.1+L45*0.1) -> 2.45 | X45: =IF(COUNT(P45,R45,T45,V45)=0,"",P45*0.08+R45*0.06+T45*0.03+V45*0.08) | AA45: 4 | AB45: M | AE45: =IF(COUNT(Y45,AA45,AC45)=0,"",Y45*0.02+AA45*0.02+AC45*0.01) -> 0.08 | AF45: =IF(OR(COUNT(D45,F45,H45,J45,L45)<5,COUNT(P45,R45,T45,V45)<4,COUNT(Y45,AA45,AC45)<3),"",(O45+X45+AE45)*20) | AG45: =IF(AF45="","",IF(AF45>=80,"STRONG BUY",IF(AF45>=65,"BUY",IF(AF45>=50,"WATCH LIST",IF(AF45>=35,"AVOID","PASS"))))) | AH45: =IF(N45="","",IF(N45<3,"FAIL","OK")) -> OK | AI45: =IF(COUNT(D45:L45)=0,"",IF(COUNTIF(D45:L45,1)>0,"REVIEW","OK")) -> OK | AJ45: =IF(COUNT(D45:L45)=0,"",IF(COUNTIF(D45:L45,"<=2")>=2,"AVOID","OK")) -> OK | AK45: =IF(COUNTA(E45:M45)=0,"",IF(COUNTIF(E45:M45,"L")>=2,"CAP AT BUY","OK")) -> OK | AL45: Industrials | AM45: Specialty Industrial Machinery | AP45: =IF(OR(AN45="",AO45=""),"",IF(AN45>AO45,"OK","LOW CONF")) | AS45: =IF(OR(AQ45="",AR45=""),"",IF(AQ45<AR45,"Decreased",IF(AQ45>AR45,"Increased","Flat")))
A46: DIS | B46: The Walt Disney Company | C46: 46258 | D46: 4 | E46: M | F46: 2 | G46: M | H46: 3 | I46: M | J46: 2 | K46: M | L46: 3 | M46: M | N46: =IF(COUNT(D46,F46,H46,J46,L46)=0,"",(D46*0.2+F46*0.15+H46*0.15+J46*0.1+L46*0.1)/(IF(D46<>"",0.2,0)+IF(F46<>"",0.15,0)+IF(H46<>"",0.15,0)+IF(J46<>"",0.1,0)+IF(L46<>"",0.1,0))) -> 2.9285714 | O46: =IF(COUNT(D46,F46,H46,J46,L46)=0,"",D46*0.2+F46*0.15+H46*0.15+J46*0.1+L46*0.1) -> 2.05 | X46: =IF(COUNT(P46,R46,T46,V46)=0,"",P46*0.08+R46*0.06+T46*0.03+V46*0.08) | AE46: =IF(COUNT(Y46,AA46,AC46)=0,"",Y46*0.02+AA46*0.02+AC46*0.01) | AF46: =IF(OR(COUNT(D46,F46,H46,J46,L46)<5,COUNT(P46,R46,T46,V46)<4,COUNT(Y46,AA46,AC46)<3),"",(O46+X46+AE46)*20) | AG46: =IF(AF46="","",IF(AF46>=80,"STRONG BUY",IF(AF46>=65,"BUY",IF(AF46>=50,"WATCH LIST",IF(AF46>=35,"AVOID","PASS"))))) | AH46: =IF(N46="","",IF(N46<3,"FAIL","OK")) -> FAIL | AI46: =IF(COUNT(D46:L46)=0,"",IF(COUNTIF(D46:L46,1)>0,"REVIEW","OK")) -> OK | AJ46: =IF(COUNT(D46:L46)=0,"",IF(COUNTIF(D46:L46,"<=2")>=2,"AVOID","OK")) -> AVOID | AK46: =IF(COUNTA(E46:M46)=0,"",IF(COUNTIF(E46:M46,"L")>=2,"CAP AT BUY","OK")) -> OK | AL46: Communication Services | AM46: Entertainment | AP46: =IF(OR(AN46="",AO46=""),"",IF(AN46>AO46,"OK","LOW CONF")) | AS46: =IF(OR(AQ46="",AR46=""),"",IF(AQ46<AR46,"Decreased",IF(AQ46>AR46,"Increased","Flat")))
A47: NFLX | B47: Netflix, Inc. | C47: 46295 | D47: 4 | E47: M | F47: 4 | G47: M | H47: 5 | I47: M | J47: 4 | K47: M | L47: 4 | M47: M | N47: =IF(COUNT(D47,F47,H47,J47,L47)=0,"",(D47*0.2+F47*0.15+H47*0.15+J47*0.1+L47*0.1)/(IF(D47<>"",0.2,0)+IF(F47<>"",0.15,0)+IF(H47<>"",0.15,0)+IF(J47<>"",0.1,0)+IF(L47<>"",0.1,0))) -> 4.2142857 | O47: =IF(COUNT(D47,F47,H47,J47,L47)=0,"",D47*0.2+F47*0.15+H47*0.15+J47*0.1+L47*0.1) -> 2.95 | P47: 5 | Q47: H | R47: 5 | S47: L | T47: 1 | U47: M | V47: 4 | W47: M | X47: =IF(COUNT(P47,R47,T47,V47)=0,"",P47*0.08+R47*0.06+T47*0.03+V47*0.08) -> 1.05 | Y47: 4 | Z47: M | AA47: 4 | AB47: M | AC47: 3 | AD47: M | AE47: =IF(COUNT(Y47,AA47,AC47)=0,"",Y47*0.02+AA47*0.02+AC47*0.01) -> 0.19 | AF47: =IF(OR(COUNT(D47,F47,H47,J47,L47)<5,COUNT(P47,R47,T47,V47)<4,COUNT(Y47,AA47,AC47)<3),"",(O47+X47+AE47)*20) -> 83.8 | AG47: =IF(AF47="","",IF(AF47>=80,"STRONG BUY",IF(AF47>=65,"BUY",IF(AF47>=50,"WATCH LIST",IF(AF47>=35,"AVOID","PASS"))))) -> STRONG BUY | AH47: =IF(N47="","",IF(N47<3,"FAIL","OK")) -> OK | AI47: =IF(COUNT(D47:L47)=0,"",IF(COUNTIF(D47:L47,1)>0,"REVIEW","OK")) -> OK | AJ47: =IF(COUNT(D47:L47)=0,"",IF(COUNTIF(D47:L47,"<=2")>=2,"AVOID","OK")) -> OK | AK47: =IF(COUNTA(E47:M47)=0,"",IF(COUNTIF(E47:M47,"L")>=2,"CAP AT BUY","OK")) -> OK | AL47: Communication Services | AM47: Entertainment | AP47: =IF(OR(AN47="",AO47=""),"",IF(AN47>AO47,"OK","LOW CONF")) | AS47: =IF(OR(AQ47="",AR47=""),"",IF(AQ47<AR47,"Decreased",IF(AQ47>AR47,"Increased","Flat")))
A48: KGS | B48: Kodiak Gas Services, Inc. | C48: 46276 | D48: 4 | E48: M | F48: 4 | G48: M | L48: 4 | M48: M | N48: =IF(COUNT(D48,F48,H48,J48,L48)=0,"",(D48*0.2+F48*0.15+H48*0.15+J48*0.1+L48*0.1)/(IF(D48<>"",0.2,0)+IF(F48<>"",0.15,0)+IF(H48<>"",0.15,0)+IF(J48<>"",0.1,0)+IF(L48<>"",0.1,0))) -> 4 | O48: =IF(COUNT(D48,F48,H48,J48,L48)=0,"",D48*0.2+F48*0.15+H48*0.15+J48*0.1+L48*0.1) -> 1.8 | X48: =IF(COUNT(P48,R48,T48,V48)=0,"",P48*0.08+R48*0.06+T48*0.03+V48*0.08) | AE48: =IF(COUNT(Y48,AA48,AC48)=0,"",Y48*0.02+AA48*0.02+AC48*0.01) | AF48: =IF(OR(COUNT(D48,F48,H48,J48,L48)<5,COUNT(P48,R48,T48,V48)<4,COUNT(Y48,AA48,AC48)<3),"",(O48+X48+AE48)*20) | AG48: =IF(AF48="","",IF(AF48>=80,"STRONG BUY",IF(AF48>=65,"BUY",IF(AF48>=50,"WATCH LIST",IF(AF48>=35,"AVOID","PASS"))))) | AH48: =IF(N48="","",IF(N48<3,"FAIL","OK")) -> OK | AI48: =IF(COUNT(D48:L48)=0,"",IF(COUNTIF(D48:L48,1)>0,"REVIEW","OK")) -> OK | AJ48: =IF(COUNT(D48:L48)=0,"",IF(COUNTIF(D48:L48,"<=2")>=2,"AVOID","OK")) -> OK | AK48: =IF(COUNTA(E48:M48)=0,"",IF(COUNTIF(E48:M48,"L")>=2,"CAP AT BUY","OK")) -> OK | AL48: Energy | AM48: Oil & Gas Equipment & Services | AP48: =IF(OR(AN48="",AO48=""),"",IF(AN48>AO48,"OK","LOW CONF")) | AS48: =IF(OR(AQ48="",AR48=""),"",IF(AQ48<AR48,"Decreased",IF(AQ48>AR48,"Increased","Flat")))
A49: ABT | B49: Abbott Laboratories | C49: 46295 | D49: 3 | E49: M | F49: 2 | G49: M | H49: 5 | I49: H | J49: 4 | K49: M | L49: 4 | M49: M | N49: =IF(COUNT(D49,F49,H49,J49,L49)=0,"",(D49*0.2+F49*0.15+H49*0.15+J49*0.1+L49*0.1)/(IF(D49<>"",0.2,0)+IF(F49<>"",0.15,0)+IF(H49<>"",0.15,0)+IF(J49<>"",0.1,0)+IF(L49<>"",0.1,0))) -> 3.5 | O49: =IF(COUNT(D49,F49,H49,J49,L49)=0,"",D49*0.2+F49*0.15+H49*0.15+J49*0.1+L49*0.1) -> 2.45 | P49: 5 | Q49: H | R49: 3 | S49: L | T49: 1 | U49: M | V49: 4 | W49: M | X49: =IF(COUNT(P49,R49,T49,V49)=0,"",P49*0.08+R49*0.06+T49*0.03+V49*0.08) -> 0.93 | Y49: 2 | Z49: M | AA49: 5 | AB49: M | AC49: 2 | AD49: M | AE49: =IF(COUNT(Y49,AA49,AC49)=0,"",Y49*0.02+AA49*0.02+AC49*0.01) -> 0.16 | AF49: =IF(OR(COUNT(D49,F49,H49,J49,L49)<5,COUNT(P49,R49,T49,V49)<4,COUNT(Y49,AA49,AC49)<3),"",(O49+X49+AE49)*20) -> 70.8 | AG49: =IF(AF49="","",IF(AF49>=80,"STRONG BUY",IF(AF49>=65,"BUY",IF(AF49>=50,"WATCH LIST",IF(AF49>=35,"AVOID","PASS"))))) -> BUY | AH49: =IF(N49="","",IF(N49<3,"FAIL","OK")) -> OK | AI49: =IF(COUNT(D49:L49)=0,"",IF(COUNTIF(D49:L49,1)>0,"REVIEW","OK")) -> OK | AJ49: =IF(COUNT(D49:L49)=0,"",IF(COUNTIF(D49:L49,"<=2")>=2,"AVOID","OK")) -> OK | AK49: =IF(COUNTA(E49:M49)=0,"",IF(COUNTIF(E49:M49,"L")>=2,"CAP AT BUY","OK")) -> OK | AL49: Healthcare | AM49: Medical Devices | AP49: =IF(OR(AN49="",AO49=""),"",IF(AN49>AO49,"OK","LOW CONF")) | AS49: =IF(OR(AQ49="",AR49=""),"",IF(AQ49<AR49,"Decreased",IF(AQ49>AR49,"Increased","Flat")))
A50: SLB | B50: SLB N.V. | C50: 46295 | D50: 4 | E50: M | F50: 3 | G50: M | H50: 4 | I50: M | J50: 3 | K50: M | L50: 3 | M50: M | N50: =IF(COUNT(D50,F50,H50,J50,L50)=0,"",(D50*0.2+F50*0.15+H50*0.15+J50*0.1+L50*0.1)/(IF(D50<>"",0.2,0)+IF(F50<>"",0.15,0)+IF(H50<>"",0.15,0)+IF(J50<>"",0.1,0)+IF(L50<>"",0.1,0))) -> 3.5 | O50: =IF(COUNT(D50,F50,H50,J50,L50)=0,"",D50*0.2+F50*0.15+H50*0.15+J50*0.1+L50*0.1) -> 2.45 | P50: 4 | Q50: M | R50: 3 | S50: L | T50: 5 | U50: M | V50: 4 | W50: M | X50: =IF(COUNT(P50,R50,T50,V50)=0,"",P50*0.08+R50*0.06+T50*0.03+V50*0.08) -> 0.97 | Y50: 5 | Z50: M | AA50: 4 | AB50: M | AC50: 2 | AD50: M | AE50: =IF(COUNT(Y50,AA50,AC50)=0,"",Y50*0.02+AA50*0.02+AC50*0.01) -> 0.2 | AF50: =IF(OR(COUNT(D50,F50,H50,J50,L50)<5,COUNT(P50,R50,T50,V50)<4,COUNT(Y50,AA50,AC50)<3),"",(O50+X50+AE50)*20) -> 72.4 | AG50: =IF(AF50="","",IF(AF50>=80,"STRONG BUY",IF(AF50>=65,"BUY",IF(AF50>=50,"WATCH LIST",IF(AF50>=35,"AVOID","PASS"))))) -> BUY | AH50: =IF(N50="","",IF(N50<3,"FAIL","OK")) -> OK | AI50: =IF(COUNT(D50:L50)=0,"",IF(COUNTIF(D50:L50,1)>0,"REVIEW","OK")) -> OK | AJ50: =IF(COUNT(D50:L50)=0,"",IF(COUNTIF(D50:L50,"<=2")>=2,"AVOID","OK")) -> OK | AK50: =IF(COUNTA(E50:M50)=0,"",IF(COUNTIF(E50:M50,"L")>=2,"CAP AT BUY","OK")) -> OK | AL50: Energy | AM50: Oil & Gas Equipment & Services | AP50: =IF(OR(AN50="",AO50=""),"",IF(AN50>AO50,"OK","LOW CONF")) | AS50: =IF(OR(AQ50="",AR50=""),"",IF(AQ50<AR50,"Decreased",IF(AQ50>AR50,"Increased","Flat")))
N51: =IF(COUNT(D51,F51,H51,J51,L51)=0,"",(D51*0.2+F51*0.15+H51*0.15+J51*0.1+L51*0.1)/(IF(D51<>"",0.2,0)+IF(F51<>"",0.15,0)+IF(H51<>"",0.15,0)+IF(J51<>"",0.1,0)+IF(L51<>"",0.1,0))) | O51: =IF(COUNT(D51,F51,H51,J51,L51)=0,"",D51*0.2+F51*0.15+H51*0.15+J51*0.1+L51*0.1) | X51: =IF(COUNT(P51,R51,T51,V51)=0,"",P51*0.08+R51*0.06+T51*0.03+V51*0.08) | AE51: =IF(COUNT(Y51,AA51,AC51)=0,"",Y51*0.02+AA51*0.02+AC51*0.01) | AF51: =IF(OR(COUNT(D51,F51,H51,J51,L51)<5,COUNT(P51,R51,T51,V51)<4,COUNT(Y51,AA51,AC51)<3),"",(O51+X51+AE51)*20) | AG51: =IF(AF51="","",IF(AF51>=80,"STRONG BUY",IF(AF51>=65,"BUY",IF(AF51>=50,"WATCH LIST",IF(AF51>=35,"AVOID","PASS"))))) | AH51: =IF(N51="","",IF(N51<3,"FAIL","OK")) | AI51: =IF(COUNT(D51:L51)=0,"",IF(COUNTIF(D51:L51,1)>0,"REVIEW","OK")) | AJ51: =IF(COUNT(D51:L51)=0,"",IF(COUNTIF(D51:L51,"<=2")>=2,"AVOID","OK")) | AK51: =IF(COUNTA(E51:M51)=0,"",IF(COUNTIF(E51:M51,"L")>=2,"CAP AT BUY","OK")) | AP51: =IF(OR(AN51="",AO51=""),"",IF(AN51>AO51,"OK","LOW CONF")) | AS51: =IF(OR(AQ51="",AR51=""),"",IF(AQ51<AR51,"Decreased",IF(AQ51>AR51,"Increased","Flat")))
N52: =IF(COUNT(D52,F52,H52,J52,L52)=0,"",(D52*0.2+F52*0.15+H52*0.15+J52*0.1+L52*0.1)/(IF(D52<>"",0.2,0)+IF(F52<>"",0.15,0)+IF(H52<>"",0.15,0)+IF(J52<>"",0.1,0)+IF(L52<>"",0.1,0))) | O52: =IF(COUNT(D52,F52,H52,J52,L52)=0,"",D52*0.2+F52*0.15+H52*0.15+J52*0.1+L52*0.1) | X52: =IF(COUNT(P52,R52,T52,V52)=0,"",P52*0.08+R52*0.06+T52*0.03+V52*0.08) | AE52: =IF(COUNT(Y52,AA52,AC52)=0,"",Y52*0.02+AA52*0.02+AC52*0.01) | AF52: =IF(OR(COUNT(D52,F52,H52,J52,L52)<5,COUNT(P52,R52,T52,V52)<4,COUNT(Y52,AA52,AC52)<3),"",(O52+X52+AE52)*20) | AG52: =IF(AF52="","",IF(AF52>=80,"STRONG BUY",IF(AF52>=65,"BUY",IF(AF52>=50,"WATCH LIST",IF(AF52>=35,"AVOID","PASS"))))) | AH52: =IF(N52="","",IF(N52<3,"FAIL","OK")) | AI52: =IF(COUNT(D52:L52)=0,"",IF(COUNTIF(D52:L52,1)>0,"REVIEW","OK")) | AJ52: =IF(COUNT(D52:L52)=0,"",IF(COUNTIF(D52:L52,"<=2")>=2,"AVOID","OK")) | AK52: =IF(COUNTA(E52:M52)=0,"",IF(COUNTIF(E52:M52,"L")>=2,"CAP AT BUY","OK")) | AP52: =IF(OR(AN52="",AO52=""),"",IF(AN52>AO52,"OK","LOW CONF")) | AS52: =IF(OR(AQ52="",AR52=""),"",IF(AQ52<AR52,"Decreased",IF(AQ52>AR52,"Increased","Flat")))
N53: =IF(COUNT(D53,F53,H53,J53,L53)=0,"",(D53*0.2+F53*0.15+H53*0.15+J53*0.1+L53*0.1)/(IF(D53<>"",0.2,0)+IF(F53<>"",0.15,0)+IF(H53<>"",0.15,0)+IF(J53<>"",0.1,0)+IF(L53<>"",0.1,0))) | O53: =IF(COUNT(D53,F53,H53,J53,L53)=0,"",D53*0.2+F53*0.15+H53*0.15+J53*0.1+L53*0.1) | X53: =IF(COUNT(P53,R53,T53,V53)=0,"",P53*0.08+R53*0.06+T53*0.03+V53*0.08) | AE53: =IF(COUNT(Y53,AA53,AC53)=0,"",Y53*0.02+AA53*0.02+AC53*0.01) | AF53: =IF(OR(COUNT(D53,F53,H53,J53,L53)<5,COUNT(P53,R53,T53,V53)<4,COUNT(Y53,AA53,AC53)<3),"",(O53+X53+AE53)*20) | AG53: =IF(AF53="","",IF(AF53>=80,"STRONG BUY",IF(AF53>=65,"BUY",IF(AF53>=50,"WATCH LIST",IF(AF53>=35,"AVOID","PASS"))))) | AH53: =IF(N53="","",IF(N53<3,"FAIL","OK")) | AI53: =IF(COUNT(D53:L53)=0,"",IF(COUNTIF(D53:L53,1)>0,"REVIEW","OK")) | AJ53: =IF(COUNT(D53:L53)=0,"",IF(COUNTIF(D53:L53,"<=2")>=2,"AVOID","OK")) | AK53: =IF(COUNTA(E53:M53)=0,"",IF(COUNTIF(E53:M53,"L")>=2,"CAP AT BUY","OK")) | AP53: =IF(OR(AN53="",AO53=""),"",IF(AN53>AO53,"OK","LOW CONF")) | AS53: =IF(OR(AQ53="",AR53=""),"",IF(AQ53<AR53,"Decreased",IF(AQ53>AR53,"Increased","Flat")))
N54: =IF(COUNT(D54,F54,H54,J54,L54)=0,"",(D54*0.2+F54*0.15+H54*0.15+J54*0.1+L54*0.1)/(IF(D54<>"",0.2,0)+IF(F54<>"",0.15,0)+IF(H54<>"",0.15,0)+IF(J54<>"",0.1,0)+IF(L54<>"",0.1,0))) | O54: =IF(COUNT(D54,F54,H54,J54,L54)=0,"",D54*0.2+F54*0.15+H54*0.15+J54*0.1+L54*0.1) | X54: =IF(COUNT(P54,R54,T54,V54)=0,"",P54*0.08+R54*0.06+T54*0.03+V54*0.08) | AE54: =IF(COUNT(Y54,AA54,AC54)=0,"",Y54*0.02+AA54*0.02+AC54*0.01) | AF54: =IF(OR(COUNT(D54,F54,H54,J54,L54)<5,COUNT(P54,R54,T54,V54)<4,COUNT(Y54,AA54,AC54)<3),"",(O54+X54+AE54)*20) | AG54: =IF(AF54="","",IF(AF54>=80,"STRONG BUY",IF(AF54>=65,"BUY",IF(AF54>=50,"WATCH LIST",IF(AF54>=35,"AVOID","PASS"))))) | AH54: =IF(N54="","",IF(N54<3,"FAIL","OK")) | AI54: =IF(COUNT(D54:L54)=0,"",IF(COUNTIF(D54:L54,1)>0,"REVIEW","OK")) | AJ54: =IF(COUNT(D54:L54)=0,"",IF(COUNTIF(D54:L54,"<=2")>=2,"AVOID","OK")) | AK54: =IF(COUNTA(E54:M54)=0,"",IF(COUNTIF(E54:M54,"L")>=2,"CAP AT BUY","OK")) | AP54: =IF(OR(AN54="",AO54=""),"",IF(AN54>AO54,"OK","LOW CONF")) | AS54: =IF(OR(AQ54="",AR54=""),"",IF(AQ54<AR54,"Decreased",IF(AQ54>AR54,"Increased","Flat")))
N55: =IF(COUNT(D55,F55,H55,J55,L55)=0,"",(D55*0.2+F55*0.15+H55*0.15+J55*0.1+L55*0.1)/(IF(D55<>"",0.2,0)+IF(F55<>"",0.15,0)+IF(H55<>"",0.15,0)+IF(J55<>"",0.1,0)+IF(L55<>"",0.1,0))) | O55: =IF(COUNT(D55,F55,H55,J55,L55)=0,"",D55*0.2+F55*0.15+H55*0.15+J55*0.1+L55*0.1) | X55: =IF(COUNT(P55,R55,T55,V55)=0,"",P55*0.08+R55*0.06+T55*0.03+V55*0.08) | AE55: =IF(COUNT(Y55,AA55,AC55)=0,"",Y55*0.02+AA55*0.02+AC55*0.01) | AF55: =IF(OR(COUNT(D55,F55,H55,J55,L55)<5,COUNT(P55,R55,T55,V55)<4,COUNT(Y55,AA55,AC55)<3),"",(O55+X55+AE55)*20) | AG55: =IF(AF55="","",IF(AF55>=80,"STRONG BUY",IF(AF55>=65,"BUY",IF(AF55>=50,"WATCH LIST",IF(AF55>=35,"AVOID","PASS"))))) | AH55: =IF(N55="","",IF(N55<3,"FAIL","OK")) | AI55: =IF(COUNT(D55:L55)=0,"",IF(COUNTIF(D55:L55,1)>0,"REVIEW","OK")) | AJ55: =IF(COUNT(D55:L55)=0,"",IF(COUNTIF(D55:L55,"<=2")>=2,"AVOID","OK")) | AK55: =IF(COUNTA(E55:M55)=0,"",IF(COUNTIF(E55:M55,"L")>=2,"CAP AT BUY","OK")) | AP55: =IF(OR(AN55="",AO55=""),"",IF(AN55>AO55,"OK","LOW CONF")) | AS55: =IF(OR(AQ55="",AR55=""),"",IF(AQ55<AR55,"Decreased",IF(AQ55>AR55,"Increased","Flat")))
N56: =IF(COUNT(D56,F56,H56,J56,L56)=0,"",(D56*0.2+F56*0.15+H56*0.15+J56*0.1+L56*0.1)/(IF(D56<>"",0.2,0)+IF(F56<>"",0.15,0)+IF(H56<>"",0.15,0)+IF(J56<>"",0.1,0)+IF(L56<>"",0.1,0))) | O56: =IF(COUNT(D56,F56,H56,J56,L56)=0,"",D56*0.2+F56*0.15+H56*0.15+J56*0.1+L56*0.1) | X56: =IF(COUNT(P56,R56,T56,V56)=0,"",P56*0.08+R56*0.06+T56*0.03+V56*0.08) | AE56: =IF(COUNT(Y56,AA56,AC56)=0,"",Y56*0.02+AA56*0.02+AC56*0.01) | AF56: =IF(OR(COUNT(D56,F56,H56,J56,L56)<5,COUNT(P56,R56,T56,V56)<4,COUNT(Y56,AA56,AC56)<3),"",(O56+X56+AE56)*20) | AG56: =IF(AF56="","",IF(AF56>=80,"STRONG BUY",IF(AF56>=65,"BUY",IF(AF56>=50,"WATCH LIST",IF(AF56>=35,"AVOID","PASS"))))) | AH56: =IF(N56="","",IF(N56<3,"FAIL","OK")) | AI56: =IF(COUNT(D56:L56)=0,"",IF(COUNTIF(D56:L56,1)>0,"REVIEW","OK")) | AJ56: =IF(COUNT(D56:L56)=0,"",IF(COUNTIF(D56:L56,"<=2")>=2,"AVOID","OK")) | AK56: =IF(COUNTA(E56:M56)=0,"",IF(COUNTIF(E56:M56,"L")>=2,"CAP AT BUY","OK")) | AP56: =IF(OR(AN56="",AO56=""),"",IF(AN56>AO56,"OK","LOW CONF")) | AS56: =IF(OR(AQ56="",AR56=""),"",IF(AQ56<AR56,"Decreased",IF(AQ56>AR56,"Increased","Flat")))
N57: =IF(COUNT(D57,F57,H57,J57,L57)=0,"",(D57*0.2+F57*0.15+H57*0.15+J57*0.1+L57*0.1)/(IF(D57<>"",0.2,0)+IF(F57<>"",0.15,0)+IF(H57<>"",0.15,0)+IF(J57<>"",0.1,0)+IF(L57<>"",0.1,0))) | O57: =IF(COUNT(D57,F57,H57,J57,L57)=0,"",D57*0.2+F57*0.15+H57*0.15+J57*0.1+L57*0.1) | X57: =IF(COUNT(P57,R57,T57,V57)=0,"",P57*0.08+R57*0.06+T57*0.03+V57*0.08) | AE57: =IF(COUNT(Y57,AA57,AC57)=0,"",Y57*0.02+AA57*0.02+AC57*0.01) | AF57: =IF(OR(COUNT(D57,F57,H57,J57,L57)<5,COUNT(P57,R57,T57,V57)<4,COUNT(Y57,AA57,AC57)<3),"",(O57+X57+AE57)*20) | AG57: =IF(AF57="","",IF(AF57>=80,"STRONG BUY",IF(AF57>=65,"BUY",IF(AF57>=50,"WATCH LIST",IF(AF57>=35,"AVOID","PASS"))))) | AH57: =IF(N57="","",IF(N57<3,"FAIL","OK")) | AI57: =IF(COUNT(D57:L57)=0,"",IF(COUNTIF(D57:L57,1)>0,"REVIEW","OK")) | AJ57: =IF(COUNT(D57:L57)=0,"",IF(COUNTIF(D57:L57,"<=2")>=2,"AVOID","OK")) | AK57: =IF(COUNTA(E57:M57)=0,"",IF(COUNTIF(E57:M57,"L")>=2,"CAP AT BUY","OK")) | AP57: =IF(OR(AN57="",AO57=""),"",IF(AN57>AO57,"OK","LOW CONF")) | AS57: =IF(OR(AQ57="",AR57=""),"",IF(AQ57<AR57,"Decreased",IF(AQ57>AR57,"Increased","Flat")))
N58: =IF(COUNT(D58,F58,H58,J58,L58)=0,"",(D58*0.2+F58*0.15+H58*0.15+J58*0.1+L58*0.1)/(IF(D58<>"",0.2,0)+IF(F58<>"",0.15,0)+IF(H58<>"",0.15,0)+IF(J58<>"",0.1,0)+IF(L58<>"",0.1,0))) | O58: =IF(COUNT(D58,F58,H58,J58,L58)=0,"",D58*0.2+F58*0.15+H58*0.15+J58*0.1+L58*0.1) | X58: =IF(COUNT(P58,R58,T58,V58)=0,"",P58*0.08+R58*0.06+T58*0.03+V58*0.08) | AE58: =IF(COUNT(Y58,AA58,AC58)=0,"",Y58*0.02+AA58*0.02+AC58*0.01) | AF58: =IF(OR(COUNT(D58,F58,H58,J58,L58)<5,COUNT(P58,R58,T58,V58)<4,COUNT(Y58,AA58,AC58)<3),"",(O58+X58+AE58)*20) | AG58: =IF(AF58="","",IF(AF58>=80,"STRONG BUY",IF(AF58>=65,"BUY",IF(AF58>=50,"WATCH LIST",IF(AF58>=35,"AVOID","PASS"))))) | AH58: =IF(N58="","",IF(N58<3,"FAIL","OK")) | AI58: =IF(COUNT(D58:L58)=0,"",IF(COUNTIF(D58:L58,1)>0,"REVIEW","OK")) | AJ58: =IF(COUNT(D58:L58)=0,"",IF(COUNTIF(D58:L58,"<=2")>=2,"AVOID","OK")) | AK58: =IF(COUNTA(E58:M58)=0,"",IF(COUNTIF(E58:M58,"L")>=2,"CAP AT BUY","OK")) | AP58: =IF(OR(AN58="",AO58=""),"",IF(AN58>AO58,"OK","LOW CONF")) | AS58: =IF(OR(AQ58="",AR58=""),"",IF(AQ58<AR58,"Decreased",IF(AQ58>AR58,"Increased","Flat")))
N59: =IF(COUNT(D59,F59,H59,J59,L59)=0,"",(D59*0.2+F59*0.15+H59*0.15+J59*0.1+L59*0.1)/(IF(D59<>"",0.2,0)+IF(F59<>"",0.15,0)+IF(H59<>"",0.15,0)+IF(J59<>"",0.1,0)+IF(L59<>"",0.1,0))) | O59: =IF(COUNT(D59,F59,H59,J59,L59)=0,"",D59*0.2+F59*0.15+H59*0.15+J59*0.1+L59*0.1) | X59: =IF(COUNT(P59,R59,T59,V59)=0,"",P59*0.08+R59*0.06+T59*0.03+V59*0.08) | AE59: =IF(COUNT(Y59,AA59,AC59)=0,"",Y59*0.02+AA59*0.02+AC59*0.01) | AF59: =IF(OR(COUNT(D59,F59,H59,J59,L59)<5,COUNT(P59,R59,T59,V59)<4,COUNT(Y59,AA59,AC59)<3),"",(O59+X59+AE59)*20) | AG59: =IF(AF59="","",IF(AF59>=80,"STRONG BUY",IF(AF59>=65,"BUY",IF(AF59>=50,"WATCH LIST",IF(AF59>=35,"AVOID","PASS"))))) | AH59: =IF(N59="","",IF(N59<3,"FAIL","OK")) | AI59: =IF(COUNT(D59:L59)=0,"",IF(COUNTIF(D59:L59,1)>0,"REVIEW","OK")) | AJ59: =IF(COUNT(D59:L59)=0,"",IF(COUNTIF(D59:L59,"<=2")>=2,"AVOID","OK")) | AK59: =IF(COUNTA(E59:M59)=0,"",IF(COUNTIF(E59:M59,"L")>=2,"CAP AT BUY","OK")) | AP59: =IF(OR(AN59="",AO59=""),"",IF(AN59>AO59,"OK","LOW CONF")) | AS59: =IF(OR(AQ59="",AR59=""),"",IF(AQ59<AR59,"Decreased",IF(AQ59>AR59,"Increased","Flat")))
N60: =IF(COUNT(D60,F60,H60,J60,L60)=0,"",(D60*0.2+F60*0.15+H60*0.15+J60*0.1+L60*0.1)/(IF(D60<>"",0.2,0)+IF(F60<>"",0.15,0)+IF(H60<>"",0.15,0)+IF(J60<>"",0.1,0)+IF(L60<>"",0.1,0))) | O60: =IF(COUNT(D60,F60,H60,J60,L60)=0,"",D60*0.2+F60*0.15+H60*0.15+J60*0.1+L60*0.1) | X60: =IF(COUNT(P60,R60,T60,V60)=0,"",P60*0.08+R60*0.06+T60*0.03+V60*0.08) | AE60: =IF(COUNT(Y60,AA60,AC60)=0,"",Y60*0.02+AA60*0.02+AC60*0.01) | AF60: =IF(OR(COUNT(D60,F60,H60,J60,L60)<5,COUNT(P60,R60,T60,V60)<4,COUNT(Y60,AA60,AC60)<3),"",(O60+X60+AE60)*20) | AG60: =IF(AF60="","",IF(AF60>=80,"STRONG BUY",IF(AF60>=65,"BUY",IF(AF60>=50,"WATCH LIST",IF(AF60>=35,"AVOID","PASS"))))) | AH60: =IF(N60="","",IF(N60<3,"FAIL","OK")) | AI60: =IF(COUNT(D60:L60)=0,"",IF(COUNTIF(D60:L60,1)>0,"REVIEW","OK")) | AJ60: =IF(COUNT(D60:L60)=0,"",IF(COUNTIF(D60:L60,"<=2")>=2,"AVOID","OK")) | AK60: =IF(COUNTA(E60:M60)=0,"",IF(COUNTIF(E60:M60,"L")>=2,"CAP AT BUY","OK")) | AP60: =IF(OR(AN60="",AO60=""),"",IF(AN60>AO60,"OK","LOW CONF")) | AS60: =IF(OR(AQ60="",AR60=""),"",IF(AQ60<AR60,"Decreased",IF(AQ60>AR60,"Increased","Flat")))
A62: =SUBTOTAL(103,A3:A60) -> 29 | B62: Tickers

Sheet Entry Checklist
A1: Part 4 Entry Rules (5-10, 13). Rules 5-7 pull from the Scoring tab; Rules 11-12 pull from the Implied-Return Calculator; Rules 8-9-10-13 are entered here. Keep this tab's row order matching Scoring/Dashboard/Implied-Return Calculator for the same stock (row 3 = same stock across all four).
A2: Ticker | B2: Company | C2: Rule 5 Composite ≥65? | D2: Rule 6 Tier1 ≥3.0? | E2: Rule 7 No Tier1 =1? | F2: Rule 8 Above / reclaimed 200-wk MA? (Y/N) | G2: Rule 9 Monthly MACD positive / turning? (Y/N) | H2: Staging Result (Rules 8-9) | I2: Rule 10 Binary event risk present? (Y/N) | J2: Risk included in thesis? (Y/N) | K2: Rule 10 Result | L2: Base Case >10%? | M2: Rule 11 Bear Case ≥0%? | N2: Rule 12 Scenario tags OK? | O2: P/FCF (current) | P2: Consensus FCF growth, 2-yr annualized | Q2: Rule 13 Valuation Ceiling | R2: ENTRY AUTHORIZED? | S2: Recommended Action
A3: =IF(Scoring!A3="","",Scoring!A3) -> MU | B3: =IF(Scoring!B3="","",Scoring!B3) -> Micron Technology | C3: =IF(Scoring!AG3="","",IF(OR(Scoring!AG3="STRONG BUY",Scoring!AG3="BUY"),"PASS","FAIL")) -> PASS | D3: =IF(Scoring!AH3="","",IF(Scoring!AH3="OK","PASS","FAIL")) -> PASS | E3: =IF(Scoring!AI3="","",IF(Scoring!AI3="OK","PASS","FAIL — mandatory review required")) -> PASS | H3: =IF(OR(F3="",G3=""),"",IF(AND(F3="Y",G3="Y"),"Standard initial size","50% of normal initial size + 90-day technical review")) | K3: =IF(I3="","",IF(I3="N","PASS",IF(J3="Y","PASS — risk documented in thesis","FAIL — undocumented binary risk"))) | L3: =IF('Implied-Return Calculator'!S4="","",'Implied-Return Calculator'!S4) | M3: =IF('Implied-Return Calculator'!T4="","",'Implied-Return Calculator'!T4) | N3: =IF('Implied-Return Calculator'!U4="","",'Implied-Return Calculator'!U4) | Q3: =IF(OR(N3="",O3=""),"",IF(N3<=50,"PASS — within ceiling",IF(AND(O3>0.3,L3="PASS"),"PASS — growth+bear case exception met","FAIL — exceeds 50x, exception not met"))) | R3: =IF(OR(C3="",D3="",E3="",K3="",L3="",M3="",N3="",Q3=""),"",IF(AND(C3="PASS",D3="PASS",LEFT(E3,4)="PASS",LEFT(K3,4)="PASS",L3="PASS",M3="PASS",N3="OK",LEFT(Q3,4)="PASS"),"YES","NO — see failing rule(s)")) | S3: =IF(R3="","",IF(R3="YES","Initiate: "&H3,"DO NOT ENTER — resolve failing Entry Rule(s) above first"))
A4: =IF(Scoring!A4="","",Scoring!A4) -> AVGO | B4: =IF(Scoring!B4="","",Scoring!B4) -> Broadcom Inc. | C4: =IF(Scoring!AG4="","",IF(OR(Scoring!AG4="STRONG BUY",Scoring!AG4="BUY"),"PASS","FAIL")) -> PASS | D4: =IF(Scoring!AH4="","",IF(Scoring!AH4="OK","PASS","FAIL")) -> PASS | E4: =IF(Scoring!AI4="","",IF(Scoring!AI4="OK","PASS","FAIL — mandatory review required")) -> PASS | H4: =IF(OR(F4="",G4=""),"",IF(AND(F4="Y",G4="Y"),"Standard initial size","50% of normal initial size + 90-day technical review")) | K4: =IF(I4="","",IF(I4="N","PASS",IF(J4="Y","PASS — risk documented in thesis","FAIL — undocumented binary risk"))) | L4: =IF('Implied-Return Calculator'!S5="","",'Implied-Return Calculator'!S5) | M4: =IF('Implied-Return Calculator'!T5="","",'Implied-Return Calculator'!T5) | N4: =IF('Implied-Return Calculator'!U5="","",'Implied-Return Calculator'!U5) | Q4: =IF(OR(N4="",O4=""),"",IF(N4<=50,"PASS — within ceiling",IF(AND(O4>0.3,L4="PASS"),"PASS — growth+bear case exception met","FAIL — exceeds 50x, exception not met"))) | R4: =IF(OR(C4="",D4="",E4="",K4="",L4="",M4="",N4="",Q4=""),"",IF(AND(C4="PASS",D4="PASS",LEFT(E4,4)="PASS",LEFT(K4,4)="PASS",L4="PASS",M4="PASS",N4="OK",LEFT(Q4,4)="PASS"),"YES","NO — see failing rule(s)")) | S4: =IF(R4="","",IF(R4="YES","Initiate: "&H4,"DO NOT ENTER — resolve failing Entry Rule(s) above first"))
